Workbook

Sheet IC Summary
A1: LEVIATHAN — 10-YR INFRASTRUCTURE & SMALL BUSINESS ROLL-UP VEHICLE
A2: Position: East Coast Marine Diesel Engine & Service Center Roll-Up | Leviathan equity cap $15M | Exit lens: Blackstone Infrastructure (Safe Harbor) / MarineMax
A4: Live scenario | B4: =Assumptions!C4 -> Base
A5: Selected exit route / year | B5: =Assumptions!$B$91 -> 1 | C5: =Assumptions!$B$90 -> 7
A7: HEADLINE (selected route & year)
A8: Leviathan equity drawn | B8: ='Exit & Returns'!C82 -> 15
A9: Gross value to Leviathan (exit + interim distributions) | B9: ='Exit & Returns'!C85 -> 203.58352
A10: Gross MOIC | B10: ='Exit & Returns'!C86 -> 13.572234
A11: Gross IRR | B11: ='Exit & Returns'!C87 -> 0.67672747
A12: Net MOIC to LPs (after 2% fee / 8% pref / 20% carry) | B12: ='Exit & Returns'!C93 -> 9.8671398
A13: Net IRR to LPs | B13: ='Exit & Returns'!C96 -> 0.60319562
A15: PLATFORM TRAJECTORY
A16: Metric | B16: Close | C16: Y3 (2029) | D16: Y5 (2031) | E16: Y7 (2033) | F16: Y10 (2036)
A17: Revenue | B17: ='Roll-Up Model'!C28 -> 10 | C17: ='Roll-Up Model'!F28 -> 38.12565 | D17: ='Roll-Up Model'!H28 -> 73.414379 | E17: ='Roll-Up Model'!J28 -> 106.96681 | F17: ='Roll-Up Model'!M28 -> 151.8704
A18: Adjusted EBITDA | B18: ='Roll-Up Model'!C40 -> 1.8 | C18: ='Roll-Up Model'!F40 -> 6.4385044 | D18: ='Roll-Up Model'!H40 -> 14.441766 | E18: ='Roll-Up Model'!J40 -> 21.52728 | F18: ='Roll-Up Model'!M40 -> 31.008694
A19: EBITDA margin | B19: ='Roll-Up Model'!C42 -> 0.18 | C19: ='Roll-Up Model'!F42 -> 0.16887593 | D19: ='Roll-Up Model'!H42 -> 0.19671577 | E19: ='Roll-Up Model'!J42 -> 0.20125196 | F19: ='Roll-Up Model'!M42 -> 0.20417865
A20: Locations | B20: ='Roll-Up Model'!C11 -> 2 | C20: ='Roll-Up Model'!F11 -> 10 | D20: ='Roll-Up Model'!H11 -> 16 | E20: ='Roll-Up Model'!J11 -> 20 | F20: ='Roll-Up Model'!M11 -> 23
A21: Contracted % of revenue | B21: ='Roll-Up Model'!C32 -> 0.15 | C21: ='Roll-Up Model'!F32 -> 0.26954275 | D21: ='Roll-Up Model'!H32 -> 0.37412893 | E21: ='Roll-Up Model'!J32 -> 0.44228914 | F21: ='Roll-Up Model'!M32 -> 0.45833662
A22: Safe Harbor embedded bays | B22: ='Roll-Up Model'!C26 -> 0 | C22: ='Roll-Up Model'!F26 -> 3.75 | D22: ='Roll-Up Model'!H26 -> 11.25 | E22: ='Roll-Up Model'!J26 -> 18.75 | F22: ='Roll-Up Model'!M26 -> 30
A23: Total leverage | B23: ='Roll-Up Model'!C86 -> 2.775 | C23: ='Roll-Up Model'!F86 -> 1.6004378 | D23: ='Roll-Up Model'!H86 -> 0.8367502 | E23: ='Roll-Up Model'!J86 -> 0.67171872 | F23: ='Roll-Up Model'!M86 -> 0.4676342
A24: Cumulative Leviathan equity | B24: ='Roll-Up Model'!C94 -> 2.9705 | C24: ='Roll-Up Model'!F94 -> 8.9657475 | D24: ='Roll-Up Model'!H94 -> 12.549817 | E24: ='Roll-Up Model'!J94 -> 15 | F24: ='Roll-Up Model'!M94 -> 15
A25: Leviathan ownership | B25: ='Roll-Up Model'!C101 -> 0.67695989 | C25: ='Roll-Up Model'!F101 -> 0.76775583 | D25: ='Roll-Up Model'!H101 -> 0.77300854 | E25: ='Roll-Up Model'!J101 -> 0.7744942 | F25: ='Roll-Up Model'!M101 -> 0.77232085
A27: RETURNS MATRIX (gross to Leviathan)
A28: Route | B28: MOIC Y5 | C28: MOIC Y7 | D28: MOIC Y10 | E28: IRR Y7 | F28: IRR Y10
A29: ='Exit & Returns'!A74 -> Route 1 — BX Infra sale | B29: ='Exit & Returns'!C74 -> 10.053404 | C29: ='Exit & Returns'!D74 -> 13.572234 | D29: ='Exit & Returns'!E74 -> 21.121384 | E29: ='Exit & Returns'!G74 -> 0.67672747 | F29: ='Exit & Returns'!H74 -> 0.50374645
A30: ='Exit & Returns'!A75 -> Route 2 — Spin/partial to BX | B30: ='Exit & Returns'!C75 -> 13.074358 | C30: ='Exit & Returns'!D75 -> 15.624069 | D30: ='Exit & Returns'!E75 -> 21.121384 | E30: ='Exit & Returns'!G75 -> 0.59966145 | F30: ='Exit & Returns'!H75 -> 0.50374645
A31: ='Exit & Returns'!A76 -> Route 3 — MarineMax | B31: ='Exit & Returns'!C76 -> 7.0394867 | C31: ='Exit & Returns'!D76 -> 9.6028716 | D31: ='Exit & Returns'!E76 -> 15.491814 | E31: ='Exit & Returns'!G76 -> 0.58226755 | F31: ='Exit & Returns'!H76 -> 0.4553353
A32: ='Exit & Returns'!A77 -> Route 4 — Sponsor | B32: ='Exit & Returns'!C77 -> 7.4061024 | C32: ='Exit & Returns'!D77 -> 10.135466 | D32: ='Exit & Returns'!E77 -> 16.424583 | E32: ='Exit & Returns'!G77 -> 0.5967823 | F32: ='Exit & Returns'!H77 -> 0.4643514
A34: INTEGRITY CHECKS (1 = OK)
A35: Sources = uses at close | B35: =IF(ABS('Sources & Uses'!C24)<0.001,1,0) -> 1
A36: Leviathan equity at close <= $15M | B36: =IF('Sources & Uses'!C22<=Assumptions!$B$23,1,0) -> 1
A37: Covenant, cap and min-cash checks (all years) | B37: ='Roll-Up Model'!C106 -> 1
A39: HOW TO USE
A40: • Edit blue cells only. Key levers are in yellow on Assumptions: scenario switch (B4), $15M cap, exit year, exit route.
A41: • Thesis Review: line-by-line critique of the CIM and the optimized assumptions used here. Synergies: platform operating synergies (feed EBITDA) and buyer synergies (feed exit premium).
A42: • Roll-Up Model: acquisitions -> revenue -> EBITDA -> FCF -> funding waterfall (cash, then Leviathan equity up to the cap, then revolver) -> debt -> units / ownership.
A43: • Exit & Returns: all four routes for every exit year, an IRR engine, and the net-to-LP waterfall for the selected case. Sensitivity: live grids. Scenario Summary: pasted snapshot of all four cases.
A44: • Sources: Safe Harbor / Blackstone Infrastructure ($5.65B, 138 marinas, closed Apr-2025); MarineMax FY26 filings (120+ locations, 65 marinas/storage, FY26 adj. EBITDA guide $110-125M). Marina-bay economics, MarineMax routable volume and infra multiples are estimates, flagged as such.

Sheet Thesis Review
A1: MARINE DIESEL ROLL-UP — THESIS REVIEW & OPTIMIZATION
A2: Source: 'Marine Diesel Engine & Service Center Roll-Up Platform' CIM, Aug-2026 (17 pp). Re-underwritten for Leviathan's 10-Year Infrastructure & Small Business Roll-Up vehicle.
A4: Area | B4: CIM position | C4: Issue / gap | D4: Optimized thesis (as modeled) | E4: Model lever
A5: Capital required | B5: ~$80M cumulative capital by Y5 (p.12); platform $7-22M EV. | C5: 5x+ the $15M mandate. CIM never shows a capital stack. | D5: Hard $15M Leviathan cap. Stack: 2.25x senior + DDTL (40% of add-on EV) + seller notes (10-15%) + rollover (5-15%) + earnouts (10%) + retained FCF. Revolver only after cap is exhausted. | E5: Assumptions B-col capital block; Sources & Uses
A6: Platform size | B6: $8-15M revenue, 18-25% margin, 5-6x. | C6: Top of range unaffordable under the cap. | D6: $10M revenue / 18% normalized margin (QoE haircut) / 5.25x. ~$2.4M Leviathan check at close leaves ~$12.6M for add-ons. | E6: plat_rev, plat_margin, plat_mult
A7: Margins | B7: Blended EBITDA 20% -> 25% by Y5; parts GM 40-60%. | C7: Owner-operated marine shops normalize to 12-18%. OEM parts GM is closer to 30-40%. | D7: Platform 18% / add-ons 14% standalone + bottom-up synergies (~5.5 pts) less a real HQ cost line ($1.0M growing 8%). | E7: Synergies tab part A; oh1
A8: Synergy math | B8: Overhead 25-30% -> 18-22%; utilization 65-75% -> 85-95%. | C8: Double-counts: overhead savings with no HQ cost; 85-95% utilization means technicians relocate seasonally. | D8: Back-office +3 pts net; utilization 70% -> 80% with 25% flow-through; procurement 10% on parts COGS. | E8: Synergies C5:D12
A9: Return math | B9: '$213M EV vs $80M capital = 2.7x' (p.12). | C9: Compares EV to capital and ignores debt, seller paper, earnouts, rollover dilution and MIP. | D9: Equity-level waterfall: EV - net debt - exit costs - MIP, times Leviathan's fully-diluted ownership (units priced at fair-value marks). | E9: Exit & Returns
A10: Exit multiple | B10: 9-12x generic 'platform exit'. | C10: No named buyer and no reason for a premium. | D10: Blended multiple: services (10x) on transactional cash flows, infra (15x) on contracted / marina-embedded cash flows. Contracted share goes from 15% to 35% by Y7 in Base. | E10: svc_mult, infra_mult, contract_tgt
A11: Exit path | B11: Not specified. | C11: Exit is the main value driver of a roll-up. | D11: Pre-wire Blackstone Infrastructure: a Safe Harbor preferred-provider agreement in Y2 and embedded service bays from Y3 (30 marinas by Y10). Four modeled routes: 100% BX sale; spin/partial with 40% retained inside Safe Harbor; MarineMax strategic; sponsor. | E11: sh_target, route, exit_yr
A12: Geography | B12: S. Florida -> Mid-Atlantic -> Northeast by phase. | C12: Sequenced by vessel counts, not by where the exit buyer operates. | D12: Same phases, with a new screening rule: favor targets within ~25 miles of a Safe Harbor or MarineMax location (FL, Chesapeake, LI Sound, New England). | E12: Time-series schedule
A13: Market sizing | B13: $5.1B global MRO; 12.7-yr merchant-fleet age. | C13: Global / merchant-fleet data says little about East Coast recreational and workboat diesel. | D13: Bottom-up East Coast TAM below: registered vessels x diesel share x annual spend, plus commercial and workboat. | E13: TAM block below
A14: Sponsor framing | B14: Branded Blackstone Tactical Opportunities as sponsor. | C14: Conflict: BX is the intended buyer. Sponsor-to-affiliate sales need an independent process and fairness opinion. | D14: Leviathan is the sponsor and BX Infra is the buyer. Run a real auction (BX vs MarineMax vs sponsors); that competition is where the seller's synergy share comes from. | E14: syn_share
A15: Key risks | B15: Technician retention rated Moderate-High. | C15: This is the binding constraint. OEM authorization transfer is a gating item. | D15: Rollover + MIP (10% of gains) for GMs and lead techs; OEM consent as a closing condition; earnouts tied to technician retention. | E15: mip, p_ro, eo_ach
A16: 10-yr vehicle fit | B16: 5-year hold. | C16: The vehicle has a 10-year life, so there is time for a two-step exit. | D16: Route 2: sell 60% to BX Infra at Y5-7 for DPI and keep 40% compounding inside Safe Harbor to Y10. | E16: ret_pct, post_g
A18: BOTTOM-UP EAST COAST TAM (replaces global MRO figure)
A19: Registered vessels — East Coast corridor (#) | B19: 1800000 | C19: CIM Appendix A: S.FL 300k + C/N FL 600k + Mid-Atl 500k + NE 400k.
A20: Diesel-powered share of recreational fleet | B20: 0.07 | C20: Estimate: inboard diesel skews to 30ft+ vessels. Verify against NMMA / USCG data.
A21: Annual diesel service + parts spend per vessel ($) | B21: 7000 | C21: Estimate: annual service, impellers, injectors, plus amortized overhaul.
A22: Recreational diesel TAM ($M) | B22: =B19*B20*B21/1000000 -> 882
A23: Commercial / workboat / fishing / government diesel TAM ($M) | B23: 600 | C23: Estimate: Hampton Roads, New Bedford, Gulf-of-Maine fleets, ferries, tugs.
A24: TOTAL East Coast addressable ($M) | B24: =B22+B23 -> 1482
A25: Platform Y10 revenue share of TAM | B25: ='Roll-Up Model'!M28/B24 -> 0.10247665

Sheet Assumptions
A1: ASSUMPTIONS & SCENARIO LEVERS
A2: Blue = hardcoded input. Black = formula. Yellow = key lever. $M unless noted. Column B is the LIVE value used by the model.
A4: Active scenario (1 = Base, 2 = Upside / Infra Re-Rate, 3 = Downside, 4 = Aggressive) | B4: 1 | C4: =INDEX(C7:F7,$B$4) -> Base | N4: Change this one cell to flip every scenario-driven input below.
A6: SCENARIO-DRIVEN INPUTS
A7: Lever | B7: LIVE | C7: Base | D7: Upside | E7: Downside | F7: Aggressive | N7: Rationale / source
A8: Organic revenue growth (same-store) | B8: =INDEX(C8:F8,$B$4) -> 0.05 | C8: 0.05 | D8: 0.07 | E8: 0.02 | F8: 0.08 | N8: CIM 5-8%. Base at low end; Downside = recession boating cycle.
A9: Platform entry multiple (x EBITDA) | B9: =INDEX(C9:F9,$B$4) -> 5.25 | C9: 5.25 | D9: 5 | E9: 6 | F9: 4.75 | N9: CIM 5-6x. $15M cap forces the smaller end of the platform range.
A10: Add-on entry multiple (x EBITDA) | B10: =INDEX(C10:F10,$B$4) -> 4.25 | C10: 4.25 | D10: 4 | E10: 5 | F10: 3.75 | N10: CIM 4-5x for $2-10M revenue shops.
A11: Add-on pace multiplier (x base schedule) | B11: =INDEX(C11:F11,$B$4) -> 1 | C11: 1 | D11: 1.25 | E11: 0.6 | F11: 1.5 | N11: Scales the year-by-year deal schedule at the bottom of this tab.
A12: Add-on standalone EBITDA margin | B12: =INDEX(C12:F12,$B$4) -> 0.14 | C12: 0.14 | D12: 0.15 | E12: 0.12 | F12: 0.15 | N12: CIM 12-22%. Small shops normalize to low-mid teens after owner add-backs.
A13: Operating-synergy realization (% of Synergies tab) | B13: =INDEX(C13:F13,$B$4) -> 1 | C13: 1 | D13: 1.2 | E13: 0.5 | F13: 1.4 | N13: Applied to bottom-up mature margin uplift on Synergies tab.
A14: Contracted / recurring share of core revenue by Y7 | B14: =INDEX(C14:F14,$B$4) -> 0.35 | C14: 0.35 | D14: 0.45 | E14: 0.2 | F14: 0.5 | N14: Fleet MSAs, extended service plans, IoT monitoring subs. Drives the infra-multiple blend.
A15: Safe Harbor marinas with embedded service bay by Y10 (#) | B15: =INDEX(C15:F15,$B$4) -> 30 | C15: 30 | D15: 45 | E15: 10 | F15: 60 | N15: Preferred-provider agreement with Safe Harbor (138 marinas). Pre-wires the BX Infra exit.
A16: Exit multiple — services cash flows (x EBITDA) | B16: =INDEX(C16:F16,$B$4) -> 10 | C16: 10 | D16: 11 | E16: 8 | F16: 12 | N16: CIM 9-12x. Scaled multi-site industrial services.
A17: Exit multiple — contracted / infra-like cash flows (x EBITDA) | B17: =INDEX(C17:F17,$B$4) -> 15 | C17: 15 | D17: 17 | E17: 12 | F17: 18 | N17: Infra buyers capitalize contracted, marina-embedded cash flows like Safe Harbor itself. Estimate.
A18: Share of buyer synergies paid to seller | B18: =INDEX(C18:F18,$B$4) -> 0.35 | C18: 0.35 | D18: 0.45 | E18: 0.2 | F18: 0.5 | N18: Competitive tension: BX Infra vs MarineMax vs sponsors.
A19: Base rate (SOFR) | B19: =INDEX(C19:F19,$B$4) -> 0.04 | C19: 0.04 | D19: 0.035 | E19: 0.05 | F19: 0.0325 | N19: Floating-rate reference for senior, DDTL and revolver.
A20: Earnout achievement (% of max paid) | B20: =INDEX(C20:F20,$B$4) -> 0.75 | C20: 0.75 | D20: 1 | E20: 0.4 | F20: 1 | N20: Higher achievement = more cash out, but only when EBITDA delivered.
A22: CAPITAL & DEAL STRUCTURE (all scenarios)
A23: Leviathan equity commitment — HARD CAP ($M) | B23: 15 | N23: User mandate: no more than $15M to start. Model never draws above this.
A24: Platform LTM revenue ($M) | B24: 10 | N24: CIM platform range $8-15M; sized to the $15M cap.
A25: Platform normalized EBITDA margin | B25: 0.18 | N25: CIM 18-25%. Haircut to low end after QoE normalization.
A26: Platform locations (#) | B26: 2 | N26: CIM Year 1: 1-2 locations.
A27: Platform transaction costs (% of EV) | B27: 0.04 | N27: Legal, QoE, OEM consent, financing fees.
A28: Add-on transaction costs (% of EV) | B28: 0.05 | N28: Smaller deals carry higher % costs.
A29: Minimum operating cash ($M) | B29: 0.5
A30: Senior term loan at close (x platform EBITDA) | B30: 2.25 | N30: Lower-middle-market unitranche / SBA-adjacent capacity.
A31: Platform seller note (% of EV) | B31: 0.1 | N31: CIM: earnout 15-25%, rollover 10-20%. Optimized toward seller paper.
A32: Platform seller rollover equity (% of EV) | B32: 0.15
A33: Platform earnout — max (% of EV) | B33: 0.1 | N33: Paid after lag x achievement.
A34: Add-on: delayed-draw term loan (% of EV) | B34: 0.35 | N34: Lender sizing ~3.5-4.0x pro forma EBITDA at platform level.
A35: Add-on: minimum sponsor equity (% of EV) while commitment remains | B35: 0.25 | N35: Lender equity-cushion requirement; this also forces the $15M to be put to work.
A36: Add-on: seller note (% of EV) | B36: 0.15
A37: Add-on: seller rollover (% of EV) | B37: 0.05 | N37: CIM 0-10%.
A38: Add-on: earnout — max (% of EV) | B38: 0.1 | N38: CIM 10-20%.
A39: Earnout payment lag (years) | B39: 2
A40: Avg add-on revenue in Y1 ($M) | B40: 3.5 | N40: CIM add-on range $2-10M.
A41: Avg add-on size growth / yr | B41: 0.04 | N41: Later Northeast targets larger / premium-priced.
A42: Mid-year convention (share of acquired revenue in deal year) | B42: 0.5
A44: OPERATIONS, CONTRACTED REVENUE & SAFE HARBOR PROGRAM
A45: Contracted share of core revenue at close | B45: 0.15 | N45: Today: ad-hoc repair; few written service contracts.
A46: Years to reach contracted-share target | B46: 7
A47: Platform corporate overhead Y1 ($M) | B47: 1 | N47: CEO/CFO, integration team, IT/CRM, training academy.
A48: Corporate overhead growth / yr | B48: 0.08
A49: Safe Harbor program start year | B49: 3 | N49: Preferred-provider agreement negotiated Y2, first bays Y3.
A50: Revenue per embedded marina service bay ($M / yr) | B50: 0.9 | N50: Estimate: 3-4 techs + parts at a 300-500 slip marina. Verify in diligence.
A51: EBITDA margin — marina service bay (after rev share) | B51: 0.28 | N51: No real estate cost; ~10% revenue share to Safe Harbor embedded.
A52: Capex per new marina bay ($M) | B52: 0.35 | N52: Tooling, service vehicle, parts cage.
A53: D&A (% of revenue) | B53: 0.025
A54: Maintenance capex (% of revenue) | B54: 0.02
A55: NWC (% of incremental organic revenue) | B55: 0.1 | N55: Parts inventory + receivables.
A56: Cash tax rate on EBT | B56: 0.25 | N56: Blended fed + state; partnership flow-through ignored.
A58: DEBT TERMS
A59: Senior term loan spread over SOFR | B59: 0.05
A60: Senior amortization (% of original / yr) | B60: 0.05
A61: Excess cash sweep to senior (%) | B61: 0.5
A62: First year excess cash is distributed to equity | B62: 5 | N62: 10-yr vehicle: DPI from Y5 instead of letting cash sit.
A63: Share of post-sweep excess cash distributed | B63: 1
A64: DDTL spread over SOFR | B64: 0.0525
A65: DDTL amortization (% of beginning balance / yr) | B65: 0.05
A66: Revolver spread over SOFR | B66: 0.045 | N66: Funds any acquisition shortfall once the $15M cap is fully drawn.
A67: Seller note coupon (fixed) | B67: 0.07
A68: Seller note term — straight-line (years) | B68: 4
A69: Max total leverage covenant (x EBITDA) | B69: 5 | N69: Flag only; check row on Roll-Up Model.
A71: EQUITY, EXIT & VEHICLE TERMS
A72: Interim mark multiple for unit pricing (x prior-yr PF EBITDA) | B72: 7 | N72: Prices rollover & later Leviathan draws at fair value, not cost.
A73: Management incentive pool (% of equity gain) | B73: 0.1 | N73: Profits interest for platform CEO + GMs.
A74: Exit transaction costs (% of EV) | B74: 0.02
A75: Buyer-synergy probability / timing haircut | B75: 0.6 | N75: Applied before the seller share.
A76: Safe Harbor marina count | B76: 138 | N76: Source: Blackstone Infrastructure / Sun Communities, Safe Harbor sale closed Apr-2025 ($5.65B; 138 marinas).
A77: Share of Safe Harbor network a buyer can equip with service bays | B77: 0.4 | N77: Buyer-side synergy; non-Atlantic / dry-stack sites excluded.
A78: BX scale cost synergies (% of revenue) — insurance, GPO, fleet | B78: 0.015 | N78: Blackstone portfolio procurement programs.
A79: MarineMax East Coast service / repower volume routable to platform ($M rev) | B79: 20 | N79: Estimate. MarineMax: 120+ locations, 70+ dealerships, 65 marinas/storage (FY26 filings).
A80: EBITDA margin on routed MarineMax volume | B80: 0.22
A81: Platform locations needed to absorb full MarineMax volume (#) | B81: 20 | N81: Volume scales linearly with footprint below this.
A82: Probability MarineMax channel deal exists under BX ownership | B82: 0.5 | N82: Commercial agreement (not ownership) when BX is the buyer.
A83: MarineMax strategic exit multiple (x EBITDA) | B83: 9 | N83: Dealer-group buyer pays services multiple; FY26 adj. EBITDA guide $110-125M.
A84: MarineMax cost synergies (% of revenue) | B84: 0.0075 | N84: Parts purchasing overlap.
A85: Partial-sale route: share retained by Leviathan | B85: 0.4 | N85: Route 2 'Spin / partial' — sell 60% to BX Infra, keep 40% inside Safe Harbor.
A86: Retained-stake equity value growth / yr post-sale | B86: 0.12 | N86: Rides Safe Harbor integration to Y10.
A87: Vehicle management fee (% of commitment / yr) | B87: 0.02 | N87: Mirrors Leviathan core holdco terms.
A88: Preferred return (compounded) | B88: 0.08
A89: Carried interest | B89: 0.2
A90: SELECTED exit year (5-10) | B90: 7 | N90: Drives headline + net-to-LP. All years shown on Exit & Returns.
A91: SELECTED exit route (1 BX Infra sale, 2 Spin/partial to BX, 3 MarineMax, 4 Sponsor) | B91: 1
A93: TIME-SERIES INPUTS (columns aligned to model years)
A94: Year | C94: Close | D94: 2027 | E94: 2028 | F94: 2029 | G94: 2030 | H94: 2031 | I94: 2032 | J94: 2033 | K94: 2034 | L94: 2035 | M94: 2036
A95: Base add-on schedule (# deals, before pace multiplier) | C95: 0 | D95: 2 | E95: 3 | F95: 3 | G95: 3 | H95: 3 | I95: 2 | J95: 2 | K95: 2 | L95: 1 | M95: 0 | N95: Phase I S. Florida (Y1-2) -> Phase II Mid-Atlantic (Y2-4) -> Phase III Northeast (Y3-6) -> fill-ins. Y10 = no deals (exit prep).
A96: Phase | C96: Platform | D96: I S.FL | E96: I/II | F96: II Mid-Atl | G96: II/III | H96: III NE | I96: III NE | J96: Fill-in | K96: Fill-in | L96: Fill-in | M96: Exit prep

Sheet Sources & Uses
A1: PLATFORM SOURCES & USES (Y0) + 10-YEAR CAPITAL STACK
A2: $M. Leviathan equity is the plug at close and must stay inside the $15M commitment.
A4: PLATFORM CLOSE — USES
A5: Platform LTM revenue | C5: =Assumptions!$B$24 -> 10
A6: Normalized EBITDA margin | C6: =Assumptions!$B$25 -> 0.18
A7: Platform EBITDA | C7: =C5*C6 -> 1.8
A8: Entry multiple | C8: =Assumptions!$B$9 -> 5.25
A9: Purchase enterprise value | C9: =C7*C8 -> 9.45
A10: Transaction costs | C10: =C9*Assumptions!$B$27 -> 0.378
A11: Cash to balance sheet | C11: =Assumptions!$B$29 -> 0.5
A12: TOTAL USES | C12: =C9+C10+C11 -> 10.328
A13: Less: earnout (contingent, paid later) | C13: =-C21 -> -0.945
A14: Cash uses at close | C14: =C12+C13 -> 9.383
A16: PLATFORM CLOSE — SOURCES
A17: Source | C17: $M | D17: % of EV | E17: Note
A18: Senior term loan | C18: =Assumptions!$B$30*C7 -> 4.05 | D18: =C18/$C$9 -> 0.42857143 | E18: x platform EBITDA
A19: Seller note | C19: =Assumptions!$B$31*C9 -> 0.945 | D19: =C19/$C$9 -> 0.1 | E19: Subordinated, 7% fixed, 4-yr straight-line
A20: Seller rollover equity | C20: =Assumptions!$B$32*C9 -> 1.4175 | D20: =C20/$C$9 -> 0.15 | E20: Same unit price as Leviathan at close
A21: Earnout (deferred, max) | C21: =Assumptions!$B$33*C9 -> 0.945 | D21: =C21/$C$9 -> 0.1 | E21: Paid Y2 x achievement
A22: LEVIATHAN EQUITY (plug) | C22: =C12-C18-C19-C20-C21 -> 2.9705 | D22: =C22/$C$9 -> 0.31433862 | E22: Must be <= $15M cap
A23: TOTAL SOURCES | C23: =SUM(C18:C22) -> 10.328
A24: Check: sources = uses (0 = OK) | C24: =ROUND(C23-C12,6) -> 0
A25: Total debt at close / EBITDA | C25: =(C18+C19)/C7 -> 2.775
A26: Leviathan equity at close vs $15M cap | C26: =C22/Assumptions!$B$23 -> 0.19803333
A27: Reserved for add-ons (remaining commitment) | C27: =Assumptions!$B$23-C22 -> 12.0295
A29: 10-YEAR PROGRAM CAPITAL STACK — how $15M controls the platform
A30: Funding source (Y0-Y10 cumulative) | C30: $M | D30: % total | E30: Note
A31: Leviathan equity (capped) | C31: =SUM('Roll-Up Model'!C63:M63) -> 15 | D31: =IF($C$40=0,0,C31/$C$40) -> 0.23706606
A32: Seller rollover equity | C32: =SUM('Roll-Up Model'!C96:M96) -> 3.9387145 | D32: =IF($C$40=0,0,C32/$C$40) -> 0.062249034
A33: Senior term loan (at close) | C33: =C18 -> 4.05 | D33: =IF($C$40=0,0,C33/$C$40) -> 0.064007835
A34: DDTL draws | C34: =SUM('Roll-Up Model'!D76:M76) -> 17.648501 | D34: =IF($C$40=0,0,C34/$C$40) -> 0.27892404
A35: Seller notes issued | C35: =SUM('Roll-Up Model'!C80:M80) -> 8.5086434 | D35: =IF($C$40=0,0,C35/$C$40) -> 0.13447404
A36: Earnouts (max, contingent) | C36: =SUM('Roll-Up Model'!C88:M88) -> 5.9874289 | D36: =IF($C$40=0,0,C36/$C$40) -> 0.094627744
A37: Revolver draws | C37: =SUM('Roll-Up Model'!D64:M64) -> 0 | D37: =IF($C$40=0,0,C37/$C$40) -> 0
A38: Internally generated cash (plug) | C38: =C40-SUM(C31:C37) -> 8.1402157 | D38: =IF($C$40=0,0,C38/$C$40) -> 0.12865126 | E38: FCF retained and reinvested into add-ons (and cash on hand).
A40: TOTAL ACQUISITION SPEND (EV + costs + platform cash) | C40: =C12+SUM('Roll-Up Model'!D15:M15)+SUM('Roll-Up Model'!D16:M16) -> 63.273504
A41: Acquisition spend per $1 of Leviathan equity | C41: =IF(C31=0,0,C40/C31) -> 4.2182336

Sheet Roll-Up Model
A1: ROLL-UP OPERATING, FUNDING & DEBT MODEL
A2: Annual. Y0 = close (LTM). $M. Green = link to Assumptions. Interest on beginning balances (no circularity).
A5: $M | C5: Close | D5: 2027 | E5: 2028 | F5: 2029 | G5: 2030 | H5: 2031 | I5: 2032 | J5: 2033 | K5: 2034 | L5: 2035 | M5: 2036
A6: Year index | C6: 0 | D6: 1 | E6: 2 | F6: 3 | G6: 4 | H6: 5 | I6: 6 | J6: 7 | K6: 8 | L6: 9 | M6: 10
A7: Phase | C7: =Assumptions!C$96 -> Platform | D7: =Assumptions!D$96 -> I S.FL | E7: =Assumptions!E$96 -> I/II | F7: =Assumptions!F$96 -> II Mid-Atl | G7: =Assumptions!G$96 -> II/III | H7: =Assumptions!H$96 -> III NE | I7: =Assumptions!I$96 -> III NE | J7: =Assumptions!J$96 -> Fill-in | ... M7: =Assumptions!M$96 -> Exit prep
A8: 1. ACQUISITION PROGRAM
A9: Add-ons closed (#) | C9: 0 | D9: =ROUND(Assumptions!D$95*Assumptions!$B$11,0) -> 2 | E9: =ROUND(Assumptions!E$95*Assumptions!$B$11,0) -> 3 | F9: =ROUND(Assumptions!F$95*Assumptions!$B$11,0) -> 3 | G9: =ROUND(Assumptions!G$95*Assumptions!$B$11,0) -> 3 | H9: =ROUND(Assumptions!H$95*Assumptions!$B$11,0) -> 3 | I9: =ROUND(Assumptions!I$95*Assumptions!$B$11,0) -> 2 | J9: =ROUND(Assumptions!J$95*Assumptions!$B$11,0) -> 2 | K9: =ROUND(Assumptions!K$95*Assumptions!$B$11,0) -> 2 | ... M9: =ROUND(Assumptions!M$95*Assumptions!$B$11,0) -> 0
A10: Cumulative add-ons (#) | C10: 0 | D10: =C10+D9 -> 2 | E10: =D10+E9 -> 5 | F10: =E10+F9 -> 8 | G10: =F10+G9 -> 11 | H10: =G10+H9 -> 14 | I10: =H10+I9 -> 16 | J10: =I10+J9 -> 18 | K10: =J10+K9 -> 20 | ... M10: =L10+M9 -> 21
A11: Locations (#) | C11: =Assumptions!$B$26 -> 2 | D11: =Assumptions!$B$26+D10 -> 4 | E11: =Assumptions!$B$26+E10 -> 7 | F11: =Assumptions!$B$26+F10 -> 10 | G11: =Assumptions!$B$26+G10 -> 13 | H11: =Assumptions!$B$26+H10 -> 16 | I11: =Assumptions!$B$26+I10 -> 18 | J11: =Assumptions!$B$26+J10 -> 20 | K11: =Assumptions!$B$26+K10 -> 22 | ... M11: =Assumptions!$B$26+M10 -> 23
A12: Avg add-on revenue ($M) | D12: =Assumptions!$B$40*(1+Assumptions!$B$41)^(D6-1) -> 3.5 | E12: =Assumptions!$B$40*(1+Assumptions!$B$41)^(E6-1) -> 3.64 | F12: =Assumptions!$B$40*(1+Assumptions!$B$41)^(F6-1) -> 3.7856 | G12: =Assumptions!$B$40*(1+Assumptions!$B$41)^(G6-1) -> 3.937024 | H12: =Assumptions!$B$40*(1+Assumptions!$B$41)^(H6-1) -> 4.094505 | I12: =Assumptions!$B$40*(1+Assumptions!$B$41)^(I6-1) -> 4.2582852 | J12: =Assumptions!$B$40*(1+Assumptions!$B$41)^(J6-1) -> 4.4286166 | K12: =Assumptions!$B$40*(1+Assumptions!$B$41)^(K6-1) -> 4.6057612 | ... M12: =Assumptions!$B$40*(1+Assumptions!$B$41)^(M6-1) -> 4.9815913
A13: New acquired revenue — run-rate | D13: =D9*D12 -> 7 | E13: =E9*E12 -> 10.92 | F13: =F9*F12 -> 11.3568 | G13: =G9*G12 -> 11.811072 | H13: =H9*H12 -> 12.283515 | I13: =I9*I12 -> 8.5165703 | J13: =J9*J12 -> 8.8572331 | K13: =K9*K12 -> 9.2115225 | ... M13: =M9*M12 -> 0
A14: New acquired EBITDA — run-rate | D14: =D13*Assumptions!$B$12 -> 0.98 | E14: =E13*Assumptions!$B$12 -> 1.5288 | F14: =F13*Assumptions!$B$12 -> 1.589952 | G14: =G13*Assumptions!$B$12 -> 1.6535501 | H14: =H13*Assumptions!$B$12 -> 1.7196921 | I14: =I13*Assumptions!$B$12 -> 1.1923198 | J14: =J13*Assumptions!$B$12 -> 1.2400126 | K14: =K13*Assumptions!$B$12 -> 1.2896131 | ... M14: =M13*Assumptions!$B$12 -> 0
A15: Add-on purchase EV | D15: =D14*Assumptions!$B$10 -> 4.165 | E15: =E14*Assumptions!$B$10 -> 6.4974 | F15: =F14*Assumptions!$B$10 -> 6.757296 | G15: =G14*Assumptions!$B$10 -> 7.0275878 | H15: =H14*Assumptions!$B$10 -> 7.3086914 | I15: =I14*Assumptions!$B$10 -> 5.0673593 | J15: =J14*Assumptions!$B$10 -> 5.2700537 | K15: =K14*Assumptions!$B$10 -> 5.4808559 | ... M15: =M14*Assumptions!$B$10 -> 0
A16: Add-on transaction costs | D16: =D15*Assumptions!$B$28 -> 0.20825 | E16: =E15*Assumptions!$B$28 -> 0.32487 | F16: =F15*Assumptions!$B$28 -> 0.3378648 | G16: =G15*Assumptions!$B$28 -> 0.35137939 | H16: =H15*Assumptions!$B$28 -> 0.36543457 | I16: =I15*Assumptions!$B$28 -> 0.25336797 | J16: =J15*Assumptions!$B$28 -> 0.26350269 | K16: =K15*Assumptions!$B$28 -> 0.27404279 | ... M16: =M15*Assumptions!$B$28 -> 0
A17: Funded by DDTL | D17: =D15*Assumptions!$B$34 -> 1.45775 | E17: =E15*Assumptions!$B$34 -> 2.27409 | F17: =F15*Assumptions!$B$34 -> 2.3650536 | G17: =G15*Assumptions!$B$34 -> 2.4596557 | H17: =H15*Assumptions!$B$34 -> 2.558042 | I17: =I15*Assumptions!$B$34 -> 1.7735758 | J17: =J15*Assumptions!$B$34 -> 1.8445188 | K17: =K15*Assumptions!$B$34 -> 1.9182996 | ... M17: =M15*Assumptions!$B$34 -> 0
A18: Funded by seller notes | D18: =D15*Assumptions!$B$36 -> 0.62475 | E18: =E15*Assumptions!$B$36 -> 0.97461 | F18: =F15*Assumptions!$B$36 -> 1.0135944 | G18: =G15*Assumptions!$B$36 -> 1.0541382 | H18: =H15*Assumptions!$B$36 -> 1.0963037 | I18: =I15*Assumptions!$B$36 -> 0.7601039 | J18: =J15*Assumptions!$B$36 -> 0.79050806 | K18: =K15*Assumptions!$B$36 -> 0.82212838 | ... M18: =M15*Assumptions!$B$36 -> 0
A19: Funded by seller rollover equity | D19: =D15*Assumptions!$B$37 -> 0.20825 | E19: =E15*Assumptions!$B$37 -> 0.32487 | F19: =F15*Assumptions!$B$37 -> 0.3378648 | G19: =G15*Assumptions!$B$37 -> 0.35137939 | H19: =H15*Assumptions!$B$37 -> 0.36543457 | I19: =I15*Assumptions!$B$37 -> 0.25336797 | J19: =J15*Assumptions!$B$37 -> 0.26350269 | K19: =K15*Assumptions!$B$37 -> 0.27404279 | ... M19: =M15*Assumptions!$B$37 -> 0
A20: Deferred via earnout (max) | D20: =D15*Assumptions!$B$38 -> 0.4165 | E20: =E15*Assumptions!$B$38 -> 0.64974 | F20: =F15*Assumptions!$B$38 -> 0.6757296 | G20: =G15*Assumptions!$B$38 -> 0.70275878 | H20: =H15*Assumptions!$B$38 -> 0.73086914 | I20: =I15*Assumptions!$B$38 -> 0.50673593 | J20: =J15*Assumptions!$B$38 -> 0.52700537 | K20: =K15*Assumptions!$B$38 -> 0.54808559 | ... M20: =M15*Assumptions!$B$38 -> 0
A21: Cash required at close (cash / equity / revolver) | D21: =D15+D16-D17-D18-D19-D20 -> 1.666 | E21: =E15+E16-E17-E18-E19-E20 -> 2.59896 | F21: =F15+F16-F17-F18-F19-F20 -> 2.7029184 | G21: =G15+G16-G17-G18-G19-G20 -> 2.8110351 | H21: =H15+H16-H17-H18-H19-H20 -> 2.9234765 | I21: =I15+I16-I17-I18-I19-I20 -> 2.0269437 | J21: =J15+J16-J17-J18-J19-J20 -> 2.1080215 | K21: =K15+K16-K17-K18-K19-K20 -> 2.1923423 | ... M21: =M15+M16-M17-M18-M19-M20 -> 0
A22: 2. REVENUE BUILD
A23: Platform run-rate revenue | C23: =Assumptions!$B$24 -> 10 | D23: =C23*(1+Assumptions!$B$8) -> 10.5 | E23: =D23*(1+Assumptions!$B$8) -> 11.025 | F23: =E23*(1+Assumptions!$B$8) -> 11.57625 | G23: =F23*(1+Assumptions!$B$8) -> 12.155062 | H23: =G23*(1+Assumptions!$B$8) -> 12.762816 | I23: =H23*(1+Assumptions!$B$8) -> 13.400956 | J23: =I23*(1+Assumptions!$B$8) -> 14.071004 | K23: =J23*(1+Assumptions!$B$8) -> 14.774554 | ... M23: =L23*(1+Assumptions!$B$8) -> 16.288946
A24: Acquired run-rate revenue (cumulative) | C24: 0 | D24: =C24*(1+Assumptions!$B$8)+D13 -> 7 | E24: =D24*(1+Assumptions!$B$8)+E13 -> 18.27 | F24: =E24*(1+Assumptions!$B$8)+F13 -> 30.5403 | G24: =F24*(1+Assumptions!$B$8)+G13 -> 43.878387 | H24: =G24*(1+Assumptions!$B$8)+H13 -> 58.355821 | I24: =H24*(1+Assumptions!$B$8)+I13 -> 69.790183 | J24: =I24*(1+Assumptions!$B$8)+J13 -> 82.136925 | K24: =J24*(1+Assumptions!$B$8)+K13 -> 95.455294 | ... M24: =L24*(1+Assumptions!$B$8)+M13 -> 110.26895
A25: Core revenue — reported (mid-year convention) | C25: =Assumptions!$B$24 -> 10 | D25: =D23+C24*(1+Assumptions!$B$8)+D13*Assumptions!$B$42 -> 14 | E25: =E23+D24*(1+Assumptions!$B$8)+E13*Assumptions!$B$42 -> 23.835 | F25: =F23+E24*(1+Assumptions!$B$8)+F13*Assumptions!$B$42 -> 36.43815 | G25: =G23+F24*(1+Assumptions!$B$8)+G13*Assumptions!$B$42 -> 50.127913 | H25: =H23+G24*(1+Assumptions!$B$8)+H13*Assumptions!$B$42 -> 64.976879 | I25: =I23+H24*(1+Assumptions!$B$8)+I13*Assumptions!$B$42 -> 78.932854 | J25: =J23+I24*(1+Assumptions!$B$8)+J13*Assumptions!$B$42 -> 91.779313 | K25: =K23+J24*(1+Assumptions!$B$8)+K13*Assumptions!$B$42 -> 105.62409 | ... M25: =M23+L24*(1+Assumptions!$B$8)+M13*Assumptions!$B$42 -> 126.5579
A26: Safe Harbor marinas with embedded bay (#, end of yr) | C26: 0 | D26: =IF(D6<Assumptions!$B$49,0,MIN(Assumptions!$B$15,Assumptions!$B$15*(D6-Assumptions!$B$49+1)/(10-Assumptions!$B$49+1))) -> 0 | E26: =IF(E6<Assumptions!$B$49,0,MIN(Assumptions!$B$15,Assumptions!$B$15*(E6-Assumptions!$B$49+1)/(10-Assumptions!$B$49+1))) -> 0 | F26: =IF(F6<Assumptions!$B$49,0,MIN(Assumptions!$B$15,Assumptions!$B$15*(F6-Assumptions!$B$49+1)/(10-Assumptions!$B$49+1))) -> 3.75 | G26: =IF(G6<Assumptions!$B$49,0,MIN(Assumptions!$B$15,Assumptions!$B$15*(G6-Assumptions!$B$49+1)/(10-Assumptions!$B$49+1))) -> 7.5 | H26: =IF(H6<Assumptions!$B$49,0,MIN(Assumptions!$B$15,Assumptions!$B$15*(H6-Assumptions!$B$49+1)/(10-Assumptions!$B$49+1))) -> 11.25 | I26: =IF(I6<Assumptions!$B$49,0,MIN(Assumptions!$B$15,Assumptions!$B$15*(I6-Assumptions!$B$49+1)/(10-Assumptions!$B$49+1))) -> 15 | J26: =IF(J6<Assumptions!$B$49,0,MIN(Assumptions!$B$15,Assumptions!$B$15*(J6-Assumptions!$B$49+1)/(10-Assumptions!$B$49+1))) -> 18.75 | K26: =IF(K6<Assumptions!$B$49,0,MIN(Assumptions!$B$15,Assumptions!$B$15*(K6-Assumptions!$B$49+1)/(10-Assumptions!$B$49+1))) -> 22.5 | ... M26: =IF(M6<Assumptions!$B$49,0,MIN(Assumptions!$B$15,Assumptions!$B$15*(M6-Assumptions!$B$49+1)/(10-Assumptions!$B$49+1))) -> 30
A27: Safe Harbor embedded-service revenue | C27: 0 | D27: =AVERAGE(C26,D26)*Assumptions!$B$50 -> 0 | E27: =AVERAGE(D26,E26)*Assumptions!$B$50 -> 0 | F27: =AVERAGE(E26,F26)*Assumptions!$B$50 -> 1.6875 | G27: =AVERAGE(F26,G26)*Assumptions!$B$50 -> 5.0625 | H27: =AVERAGE(G26,H26)*Assumptions!$B$50 -> 8.4375 | I27: =AVERAGE(H26,I26)*Assumptions!$B$50 -> 11.8125 | J27: =AVERAGE(I26,J26)*Assumptions!$B$50 -> 15.1875 | K27: =AVERAGE(J26,K26)*Assumptions!$B$50 -> 18.5625 | ... M27: =AVERAGE(L26,M26)*Assumptions!$B$50 -> 25.3125
A28: TOTAL REVENUE | C28: =C25+C27 -> 10 | D28: =D25+D27 -> 14 | E28: =E25+E27 -> 23.835 | F28: =F25+F27 -> 38.12565 | G28: =G25+G27 -> 55.190413 | H28: =H25+H27 -> 73.414379 | I28: =I25+I27 -> 90.745354 | J28: =J25+J27 -> 106.96681 | ... M28: =M25+M27 -> 151.8704
A29: Growth % | D29: =IF(C28=0,0,D28/C28-1) -> 0.4 | E29: =IF(D28=0,0,E28/D28-1) -> 0.7025 | F29: =IF(E28=0,0,F28/E28-1) -> 0.59956576 | G29: =IF(F28=0,0,G28/F28-1) -> 0.44759272 | H29: =IF(G28=0,0,H28/G28-1) -> 0.33020166 | I29: =IF(H28=0,0,I28/H28-1) -> 0.23607057 | J29: =IF(I28=0,0,J28/I28-1) -> 0.17875801 | K29: =IF(J28=0,0,K28/J28-1) -> 0.1609824 | ... M29: =IF(L28=0,0,M28/L28-1) -> 0.084216744
A30: Contracted share of core revenue | C30: =Assumptions!$B$45 -> 0.15 | D30: =Assumptions!$B$45+(Assumptions!$B$14-Assumptions!$B$45)*MIN(1,D6/Assumptions!$B$46) -> 0.17857143 | E30: =Assumptions!$B$45+(Assumptions!$B$14-Assumptions!$B$45)*MIN(1,E6/Assumptions!$B$46) -> 0.20714286 | F30: =Assumptions!$B$45+(Assumptions!$B$14-Assumptions!$B$45)*MIN(1,F6/Assumptions!$B$46) -> 0.23571429 | G30: =Assumptions!$B$45+(Assumptions!$B$14-Assumptions!$B$45)*MIN(1,G6/Assumptions!$B$46) -> 0.26428571 | H30: =Assumptions!$B$45+(Assumptions!$B$14-Assumptions!$B$45)*MIN(1,H6/Assumptions!$B$46) -> 0.29285714 | I30: =Assumptions!$B$45+(Assumptions!$B$14-Assumptions!$B$45)*MIN(1,I6/Assumptions!$B$46) -> 0.32142857 | J30: =Assumptions!$B$45+(Assumptions!$B$14-Assumptions!$B$45)*MIN(1,J6/Assumptions!$B$46) -> 0.35 | K30: =Assumptions!$B$45+(Assumptions!$B$14-Assumptions!$B$45)*MIN(1,K6/Assumptions!$B$46) -> 0.35 | ... M30: =Assumptions!$B$45+(Assumptions!$B$14-Assumptions!$B$45)*MIN(1,M6/Assumptions!$B$46) -> 0.35
A31: Contracted / infra-like revenue | C31: =C25*C30+C27 -> 1.5 | D31: =D25*D30+D27 -> 2.5 | E31: =E25*E30+E27 -> 4.93725 | F31: =F25*F30+F27 -> 10.276492 | G31: =G25*G30+G27 -> 18.310591 | H31: =H25*H30+H27 -> 27.466443 | I31: =I25*I30+I27 -> 37.183774 | J31: =J25*J30+J27 -> 47.310259 | ... M31: =M25*M30+M27 -> 69.607765
A32: Contracted % of total revenue (drives exit multiple) | C32: =IF(C28=0,0,C31/C28) -> 0.15 | D32: =IF(D28=0,0,D31/D28) -> 0.17857143 | E32: =IF(E28=0,0,E31/E28) -> 0.20714286 | F32: =IF(F28=0,0,F31/F28) -> 0.26954275 | G32: =IF(G28=0,0,G31/G28) -> 0.33177123 | H32: =IF(H28=0,0,H31/H28) -> 0.37412893 | I32: =IF(I28=0,0,I31/I28) -> 0.40975954 | J32: =IF(J28=0,0,J31/J28) -> 0.44228914 | ... M32: =IF(M28=0,0,M31/M28) -> 0.45833662
A33: 3. EBITDA BUILD
A34: Standalone margin (run-rate weighted platform / add-ons) | C34: =(C23*Assumptions!$B$25+C24*Assumptions!$B$12)/(C23+C24) -> 0.18 | D34: =(D23*Assumptions!$B$25+D24*Assumptions!$B$12)/(D23+D24) -> 0.164 | E34: =(E23*Assumptions!$B$25+E24*Assumptions!$B$12)/(E23+E24) -> 0.15505376 | F34: =(F23*Assumptions!$B$25+F24*Assumptions!$B$12)/(F23+F24) -> 0.15099449 | G34: =(G23*Assumptions!$B$25+G24*Assumptions!$B$12)/(G23+G24) -> 0.148677 | H34: =(H23*Assumptions!$B$25+H24*Assumptions!$B$12)/(H23+H24) -> 0.14717832 | I34: =(I23*Assumptions!$B$25+I24*Assumptions!$B$12)/(I23+I24) -> 0.14644345 | J34: =(J23*Assumptions!$B$25+J24*Assumptions!$B$12)/(J23+J24) -> 0.14585025 | ... M34: =(M23*Assumptions!$B$25+M24*Assumptions!$B$12)/(M23+M24) -> 0.1451483
A35: Core EBITDA — standalone | C35: =C25*C34 -> 1.8 | D35: =D25*D34 -> 2.296 | E35: =E25*E34 -> 3.6957065 | F35: =F25*F34 -> 5.5019599 | G35: =G25*G34 -> 7.452868 | H35: =H25*H34 -> 9.5631882 | I35: =I25*I34 -> 11.5592 | J35: =J25*J34 -> 13.386035 | ... M35: =M25*M34 -> 18.369664
A36: Operating-synergy margin uplift | C36: 0 | D36: =Synergies!$C$13*Assumptions!$B$13*MIN(1,D6/Synergies!$C$14) -> 0.014915179 | E36: =Synergies!$C$13*Assumptions!$B$13*MIN(1,E6/Synergies!$C$14) -> 0.029830357 | F36: =Synergies!$C$13*Assumptions!$B$13*MIN(1,F6/Synergies!$C$14) -> 0.044745536 | G36: =Synergies!$C$13*Assumptions!$B$13*MIN(1,G6/Synergies!$C$14) -> 0.059660714 | H36: =Synergies!$C$13*Assumptions!$B$13*MIN(1,H6/Synergies!$C$14) -> 0.059660714 | I36: =Synergies!$C$13*Assumptions!$B$13*MIN(1,I6/Synergies!$C$14) -> 0.059660714 | J36: =Synergies!$C$13*Assumptions!$B$13*MIN(1,J6/Synergies!$C$14) -> 0.059660714 | K36: =Synergies!$C$13*Assumptions!$B$13*MIN(1,K6/Synergies!$C$14) -> 0.059660714 | ... M36: =Synergies!$C$13*Assumptions!$B$13*MIN(1,M6/Synergies!$C$14) -> 0.059660714
A37: Operating-synergy EBITDA | C37: 0 | D37: =D25*D36 -> 0.2088125 | E37: =E25*E36 -> 0.71100656 | F37: =F25*F36 -> 1.6304445 | G37: =G25*G36 -> 2.9906671 | H37: =H25*H36 -> 3.876567 | I37: =I25*I36 -> 4.7091904 | J37: =J25*J36 -> 5.4756193 | K37: =K25*K36 -> 6.3016085 | ... M37: =M25*M36 -> 7.5505346
A38: Safe Harbor embedded-service EBITDA | C38: 0 | D38: =D27*Assumptions!$B$51 -> 0 | E38: =E27*Assumptions!$B$51 -> 0 | F38: =F27*Assumptions!$B$51 -> 0.4725 | G38: =G27*Assumptions!$B$51 -> 1.4175 | H38: =H27*Assumptions!$B$51 -> 2.3625 | I38: =I27*Assumptions!$B$51 -> 3.3075 | J38: =J27*Assumptions!$B$51 -> 4.2525 | K38: =K27*Assumptions!$B$51 -> 5.1975 | ... M38: =M27*Assumptions!$B$51 -> 7.0875
A39: Platform corporate overhead | C39: 0 | D39: =-Assumptions!$B$47*(1+Assumptions!$B$48)^(D6-1) -> -1 | E39: =-Assumptions!$B$47*(1+Assumptions!$B$48)^(E6-1) -> -1.08 | F39: =-Assumptions!$B$47*(1+Assumptions!$B$48)^(F6-1) -> -1.1664 | G39: =-Assumptions!$B$47*(1+Assumptions!$B$48)^(G6-1) -> -1.259712 | H39: =-Assumptions!$B$47*(1+Assumptions!$B$48)^(H6-1) -> -1.360489 | I39: =-Assumptions!$B$47*(1+Assumptions!$B$48)^(I6-1) -> -1.4693281 | J39: =-Assumptions!$B$47*(1+Assumptions!$B$48)^(J6-1) -> -1.5868743 | K39: =-Assumptions!$B$47*(1+Assumptions!$B$48)^(K6-1) -> -1.7138243 | ... M39: =-Assumptions!$B$47*(1+Assumptions!$B$48)^(M6-1) -> -1.9990046
A40: ADJUSTED EBITDA | C40: =C35+C37+C38+C39 -> 1.8 | D40: =D35+D37+D38+D39 -> 1.5048125 | E40: =E35+E37+E38+E39 -> 3.326713 | F40: =F35+F37+F38+F39 -> 6.4385044 | G40: =G35+G37+G38+G39 -> 10.601323 | H40: =H35+H37+H38+H39 -> 14.441766 | I40: =I35+I37+I38+I39 -> 18.106562 | J40: =J35+J37+J38+J39 -> 21.52728 | ... M40: =M35+M37+M38+M39 -> 31.008694
A41: Pro forma run-rate EBITDA (full-year add-ons) | C41: =C40 -> 1.8 | D41: =D40+D14*(1-Assumptions!$B$42) -> 1.9948125 | E41: =E40+E14*(1-Assumptions!$B$42) -> 4.091113 | F41: =F40+F14*(1-Assumptions!$B$42) -> 7.2334804 | G41: =G40+G14*(1-Assumptions!$B$42) -> 11.428098 | H41: =H40+H14*(1-Assumptions!$B$42) -> 15.301612 | I41: =I40+I14*(1-Assumptions!$B$42) -> 18.702722 | J41: =J40+J14*(1-Assumptions!$B$42) -> 22.147287 | K41: =K40+K14*(1-Assumptions!$B$42) -> 25.783752 | ... M41: =M40+M14*(1-Assumptions!$B$42) -> 31.008694
A42: EBITDA margin | C42: =IF(C28=0,0,C40/C28) -> 0.18 | D42: =IF(D28=0,0,D40/D28) -> 0.10748661 | E42: =IF(E28=0,0,E40/E28) -> 0.1395726 | F42: =IF(F28=0,0,F40/F28) -> 0.16887593 | G42: =IF(G28=0,0,G40/G28) -> 0.19208631 | H42: =IF(H28=0,0,H40/H28) -> 0.19671577 | I42: =IF(I28=0,0,I40/I28) -> 0.19953156 | J42: =IF(J28=0,0,J40/J28) -> 0.20125196 | ... M42: =IF(M28=0,0,M40/M28) -> 0.20417865
A43: 4. FREE CASH FLOW
A44: D&A | D44: =-D28*Assumptions!$B$53 -> -0.35 | E44: =-E28*Assumptions!$B$53 -> -0.595875 | F44: =-F28*Assumptions!$B$53 -> -0.95314125 | G44: =-G28*Assumptions!$B$53 -> -1.3797603 | H44: =-H28*Assumptions!$B$53 -> -1.8353595 | I44: =-I28*Assumptions!$B$53 -> -2.2686338 | J44: =-J28*Assumptions!$B$53 -> -2.6741703 | K44: =-K28*Assumptions!$B$53 -> -3.1046647 | ... M44: =-M28*Assumptions!$B$53 -> -3.79676
A45: EBIT | D45: =D40+D44 -> 1.1548125 | E45: =E40+E44 -> 2.730838 | F45: =F40+F44 -> 5.4853632 | G45: =G40+G44 -> 9.2215628 | H45: =H40+H44 -> 12.606407 | I45: =I40+I44 -> 15.837928 | J45: =J40+J44 -> 18.85311 | K45: =K40+K44 -> 22.034281 | ... M45: =M40+M44 -> 27.211934
A46: Interest expense (cash) | D46: =D89+D90+D91+D92 -> -0.49807094 | E46: =E89+E90+E91+E92 -> -0.67963854 | F46: =F89+F90+F91+F92 -> -0.90998391 | G46: =G89+G90+G91+G92 -> -1.1244044 | H46: =H89+H90+H91+H92 -> -1.2515366 | I46: =I89+I90+I91+I92 -> -1.2070229 | J46: =J89+J90+J91+J92 -> -1.3081217 | K46: =K89+K90+K91+K92 -> -1.4159443 | ... M46: =M89+M90+M91+M92 -> -1.435483
A47: EBT | D47: =D45+D46 -> 0.65674156 | E47: =E45+E46 -> 2.0511995 | F47: =F45+F46 -> 4.5753793 | G47: =G45+G46 -> 8.0971584 | H47: =H45+H46 -> 11.35487 | I47: =I45+I46 -> 14.630905 | J47: =J45+J46 -> 17.544988 | K47: =K45+K46 -> 20.618336 | ... M47: =M45+M46 -> 25.776451
A48: Cash taxes | D48: =-MAX(0,D47*Assumptions!$B$56) -> -0.16418539 | E48: =-MAX(0,E47*Assumptions!$B$56) -> -0.51279987 | F48: =-MAX(0,F47*Assumptions!$B$56) -> -1.1438448 | G48: =-MAX(0,G47*Assumptions!$B$56) -> -2.0242896 | H48: =-MAX(0,H47*Assumptions!$B$56) -> -2.8387176 | I48: =-MAX(0,I47*Assumptions!$B$56) -> -3.6577263 | J48: =-MAX(0,J47*Assumptions!$B$56) -> -4.3862471 | K48: =-MAX(0,K47*Assumptions!$B$56) -> -5.1545841 | ... M48: =-MAX(0,M47*Assumptions!$B$56) -> -6.4441127
A49: Maintenance capex | D49: =-D28*Assumptions!$B$54 -> -0.28 | E49: =-E28*Assumptions!$B$54 -> -0.4767 | F49: =-F28*Assumptions!$B$54 -> -0.762513 | G49: =-G28*Assumptions!$B$54 -> -1.1038083 | H49: =-H28*Assumptions!$B$54 -> -1.4682876 | I49: =-I28*Assumptions!$B$54 -> -1.8149071 | J49: =-J28*Assumptions!$B$54 -> -2.1393363 | K49: =-K28*Assumptions!$B$54 -> -2.4837317 | ... M49: =-M28*Assumptions!$B$54 -> -3.037408
A50: Growth capex — marina service bays | D50: =-(D26-C26)*Assumptions!$B$52 -> 0 | E50: =-(E26-D26)*Assumptions!$B$52 -> 0 | F50: =-(F26-E26)*Assumptions!$B$52 -> -1.3125 | G50: =-(G26-F26)*Assumptions!$B$52 -> -1.3125 | H50: =-(H26-G26)*Assumptions!$B$52 -> -1.3125 | I50: =-(I26-H26)*Assumptions!$B$52 -> -1.3125 | J50: =-(J26-I26)*Assumptions!$B$52 -> -1.3125 | K50: =-(K26-J26)*Assumptions!$B$52 -> -1.3125 | ... M50: =-(M26-L26)*Assumptions!$B$52 -> -1.3125
A51: Change in NWC (organic + marina growth) | D51: =-(C28*Assumptions!$B$8+D27-C27)*Assumptions!$B$55 -> -0.05 | E51: =-(D28*Assumptions!$B$8+E27-D27)*Assumptions!$B$55 -> -0.07 | F51: =-(E28*Assumptions!$B$8+F27-E27)*Assumptions!$B$55 -> -0.287925 | G51: =-(F28*Assumptions!$B$8+G27-F27)*Assumptions!$B$55 -> -0.52812825 | H51: =-(G28*Assumptions!$B$8+H27-G27)*Assumptions!$B$55 -> -0.61345207 | I51: =-(H28*Assumptions!$B$8+I27-H27)*Assumptions!$B$55 -> -0.7045719 | J51: =-(I28*Assumptions!$B$8+J27-I27)*Assumptions!$B$55 -> -0.79122677 | K51: =-(J28*Assumptions!$B$8+K27-J27)*Assumptions!$B$55 -> -0.87233406 | ... M51: =-(L28*Assumptions!$B$8+M27-L27)*Assumptions!$B$55 -> -1.0378692
A52: Unlevered FCF (EBITDA - tax - capex - NWC) | D52: =D40+D48+D49+D50+D51 -> 1.0106271 | E52: =E40+E48+E49+E50+E51 -> 2.2672131 | F52: =F40+F48+F49+F50+F51 -> 2.9317216 | G52: =G40+G48+G49+G50+G51 -> 5.632597 | H52: =H40+H48+H49+H50+H51 -> 8.2088091 | I52: =I40+I48+I49+I50+I51 -> 10.616857 | J52: =J40+J48+J49+J50+J51 -> 12.89797 | K52: =K40+K48+K49+K50+K51 -> 15.315795 | ... M52: =M40+M48+M49+M50+M51 -> 19.176804
A53: Senior mandatory amortization | D53: =D72 -> -0.2025 | E53: =E72 -> -0.2025 | F53: =F72 -> -0.2025 | G53: =G72 -> -0.2025 | H53: =H72 -> -0.2025 | I53: =I72 -> 0 | J53: =J72 -> 0 | K53: =K72 -> 0 | ... M53: =M72 -> 0
A54: DDTL amortization | D54: =D77 -> 0 | E54: =E77 -> -0.0728875 | F54: =F77 -> -0.18294763 | G54: =G77 -> -0.29205292 | H54: =H77 -> -0.40043306 | I54: =I77 -> -0.50831351 | J54: =J77 -> -0.57157662 | K54: =K77 -> -0.63522373 | ... M54: =M77 -> -0.71428444
A55: Seller note repayments | D55: =D81 -> -0.23625 | E55: =E81 -> -0.3924375 | F55: =F81 -> -0.63609 | G55: =G81 -> -0.8894886 | H55: =H81 -> -0.91677314 | I55: =I81 -> -1.0346616 | J55: =J81 -> -0.98103504 | K55: =K81 -> -0.92526346 | ... M55: =M81 -> -0.70006177
A56: Earnout payments | D56: =-SUMPRODUCT(($C$6:$M$6=D6-Assumptions!$B$39)*($C$88:$M$88))*Assumptions!$B$20 -> 0 | E56: =-SUMPRODUCT(($C$6:$M$6=E6-Assumptions!$B$39)*($C$88:$M$88))*Assumptions!$B$20 -> -0.70875 | F56: =-SUMPRODUCT(($C$6:$M$6=F6-Assumptions!$B$39)*($C$88:$M$88))*Assumptions!$B$20 -> -0.312375 | G56: =-SUMPRODUCT(($C$6:$M$6=G6-Assumptions!$B$39)*($C$88:$M$88))*Assumptions!$B$20 -> -0.487305 | H56: =-SUMPRODUCT(($C$6:$M$6=H6-Assumptions!$B$39)*($C$88:$M$88))*Assumptions!$B$20 -> -0.5067972 | I56: =-SUMPRODUCT(($C$6:$M$6=I6-Assumptions!$B$39)*($C$88:$M$88))*Assumptions!$B$20 -> -0.52706909 | J56: =-SUMPRODUCT(($C$6:$M$6=J6-Assumptions!$B$39)*($C$88:$M$88))*Assumptions!$B$20 -> -0.54815185 | K56: =-SUMPRODUCT(($C$6:$M$6=K6-Assumptions!$B$39)*($C$88:$M$88))*Assumptions!$B$20 -> -0.38005195 | ... M56: =-SUMPRODUCT(($C$6:$M$6=M6-Assumptions!$B$39)*($C$88:$M$88))*Assumptions!$B$20 -> -0.41106419
A57: FCF after debt service & earnouts | D57: =D52+D46+D53+D54+D55+D56 -> 0.073806172 | E57: =E52+E46+E53+E54+E55+E56 -> 0.21099961 | F57: =F52+F46+F53+F54+F55+F56 -> 0.68782508 | G57: =G52+G46+G53+G54+G55+G56 -> 2.6368461 | H57: =H52+H46+H53+H54+H55+H56 -> 4.9307691 | I57: =I52+I46+I53+I54+I55+I56 -> 7.3397897 | J57: =J52+J46+J53+J54+J55+J56 -> 9.4890851 | K57: =K52+K46+K53+K54+K55+K56 -> 11.959312 | ... M57: =M52+M46+M53+M54+M55+M56 -> 15.91591
A58: 5. ACQUISITION FUNDING WATERFALL (cash -> Leviathan equity up to $15M cap -> revolver)
A59: Beginning cash | D59: =C69 -> 0.5 | E59: =D69 -> 0.5 | F59: =E69 -> 0.5 | G59: =F69 -> 0.5 | H59: =G69 -> 1.291354 | I59: =H69 -> 0.5 | J59: =I69 -> 0.5 | K59: =J69 -> 0.5 | ... M59: =L69 -> 0.5
A60: Cash available above minimum | D60: =D59+D57-Assumptions!$B$29 -> 0.073806172 | E60: =E59+E57-Assumptions!$B$29 -> 0.21099961 | F60: =F59+F57-Assumptions!$B$29 -> 0.68782508 | G60: =G59+G57-Assumptions!$B$29 -> 2.6368461 | H60: =H59+H57-Assumptions!$B$29 -> 5.722123 | I60: =I59+I57-Assumptions!$B$29 -> 7.3397897 | J60: =J59+J57-Assumptions!$B$29 -> 9.4890851 | K60: =K59+K57-Assumptions!$B$29 -> 11.959312 | ... M60: =M59+M57-Assumptions!$B$29 -> 15.91591
A61: Add-on cash required | D61: =D21 -> 1.666 | E61: =E21 -> 2.59896 | F61: =F21 -> 2.7029184 | G61: =G21 -> 2.8110351 | H61: =H21 -> 2.9234765 | I61: =I21 -> 2.0269437 | J61: =J21 -> 2.1080215 | K61: =K21 -> 2.1923423 | ... M61: =M21 -> 0
A62: Remaining Leviathan commitment (beginning) | D62: =Assumptions!$B$23-SUM($C$63:C63) -> 12.0295 | E62: =Assumptions!$B$23-SUM($C$63:D63) -> 10.437306 | F62: =Assumptions!$B$23-SUM($C$63:E63) -> 8.0493458 | G62: =Assumptions!$B$23-SUM($C$63:F63) -> 6.0342525 | H62: =Assumptions!$B$23-SUM($C$63:G63) -> 4.2773555 | I62: =Assumptions!$B$23-SUM($C$63:H63) -> 2.4501827 | J62: =Assumptions!$B$23-SUM($C$63:I63) -> 1.1833428 | K62: =Assumptions!$B$23-SUM($C$63:J63) -> 0 | ... M62: =Assumptions!$B$23-SUM($C$63:L63) -> 0
A63: Leviathan equity draw (max of shortfall, min equity slice; capped) | C63: ='Sources & Uses'!$C$22 -> 2.9705 | D63: =MIN(D62,MAX(Assumptions!$B$35*D15,D61-D60)) -> 1.5921938 | E63: =MIN(E62,MAX(Assumptions!$B$35*E15,E61-E60)) -> 2.3879604 | F63: =MIN(F62,MAX(Assumptions!$B$35*F15,F61-F60)) -> 2.0150933 | G63: =MIN(G62,MAX(Assumptions!$B$35*G15,G61-G60)) -> 1.756897 | H63: =MIN(H62,MAX(Assumptions!$B$35*H15,H61-H60)) -> 1.8271728 | I63: =MIN(I62,MAX(Assumptions!$B$35*I15,I61-I60)) -> 1.2668398 | J63: =MIN(J62,MAX(Assumptions!$B$35*J15,J61-J60)) -> 1.1833428 | K63: =MIN(K62,MAX(Assumptions!$B$35*K15,K61-K60)) -> 0 | ... M63: =MIN(M62,MAX(Assumptions!$B$35*M15,M61-M60)) -> 0
A64: Revolver draw (shortfall after cap) | D64: =MAX(0,D61-D60-D63) -> 0 | E64: =MAX(0,E61-E60-E63) -> 0 | F64: =MAX(0,F61-F60-F63) -> 0 | G64: =MAX(0,G61-G60-G63) -> 0 | H64: =MAX(0,H61-H60-H63) -> 0 | I64: =MAX(0,I61-I60-I63) -> 0 | J64: =MAX(0,J61-J60-J63) -> 0 | K64: =MAX(0,K61-K60-K63) -> 0 | ... M64: =MAX(0,M61-M60-M63) -> 0
A65: Excess cash after acquisitions | D65: =MAX(0,D60+D63-D61) -> 0 | E65: =MAX(0,E60+E63-E61) -> 0 | F65: =MAX(0,F60+F63-F61) -> 0 | G65: =MAX(0,G60+G63-G61) -> 1.582708 | H65: =MAX(0,H60+H63-H61) -> 4.6258193 | I65: =MAX(0,I60+I63-I61) -> 6.5796858 | J65: =MAX(0,J60+J63-J61) -> 8.5644064 | K65: =MAX(0,K60+K63-K61) -> 9.7669697 | ... M65: =MAX(0,M60+M63-M61) -> 15.91591
A66: Revolver repayment | D66: =-MIN(C83,D65) -> 0 | E66: =-MIN(D83,E65) -> 0 | F66: =-MIN(E83,F65) -> 0 | G66: =-MIN(F83,G65) -> 0 | H66: =-MIN(G83,H65) -> 0 | I66: =-MIN(H83,I65) -> 0 | J66: =-MIN(I83,J65) -> 0 | K66: =-MIN(J83,K65) -> 0 | ... M66: =-MIN(L83,M65) -> 0
A67: Cash sweep to senior | D67: =-MIN(C74+D72,Assumptions!$B$61*(D65+D66)) -> 0 | E67: =-MIN(D74+E72,Assumptions!$B$61*(E65+E66)) -> 0 | F67: =-MIN(E74+F72,Assumptions!$B$61*(F65+F66)) -> 0 | G67: =-MIN(F74+G72,Assumptions!$B$61*(G65+G66)) -> -0.79135398 | H67: =-MIN(G74+H72,Assumptions!$B$61*(H65+H66)) -> -2.246146 | I67: =-MIN(H74+I72,Assumptions!$B$61*(I65+I66)) -> 0 | J67: =-MIN(I74+J72,Assumptions!$B$61*(J65+J66)) -> 0 | K67: =-MIN(J74+K72,Assumptions!$B$61*(K65+K66)) -> 0 | ... M67: =-MIN(L74+M72,Assumptions!$B$61*(M65+M66)) -> 0
A68: Distributions to equity (100%) | D68: =-IF(D6>=Assumptions!$B$62,Assumptions!$B$63*(D65+D66+D67),0) -> 0 | E68: =-IF(E6>=Assumptions!$B$62,Assumptions!$B$63*(E65+E66+E67),0) -> 0 | F68: =-IF(F6>=Assumptions!$B$62,Assumptions!$B$63*(F65+F66+F67),0) -> 0 | G68: =-IF(G6>=Assumptions!$B$62,Assumptions!$B$63*(G65+G66+G67),0) -> 0 | H68: =-IF(H6>=Assumptions!$B$62,Assumptions!$B$63*(H65+H66+H67),0) -> -2.3796733 | I68: =-IF(I6>=Assumptions!$B$62,Assumptions!$B$63*(I65+I66+I67),0) -> -6.5796858 | J68: =-IF(J6>=Assumptions!$B$62,Assumptions!$B$63*(J65+J66+J67),0) -> -8.5644064 | K68: =-IF(K6>=Assumptions!$B$62,Assumptions!$B$63*(K65+K66+K67),0) -> -9.7669697 | ... M68: =-IF(M6>=Assumptions!$B$62,Assumptions!$B$63*(M65+M66+M67),0) -> -15.91591
A69: Ending cash | C69: =Assumptions!$B$29 -> 0.5 | D69: =D59+D57-D61+D63+D64+D66+D67+D68 -> 0.5 | E69: =E59+E57-E61+E63+E64+E66+E67+E68 -> 0.5 | F69: =F59+F57-F61+F63+F64+F66+F67+F68 -> 0.5 | G69: =G59+G57-G61+G63+G64+G66+G67+G68 -> 1.291354 | H69: =H59+H57-H61+H63+H64+H66+H67+H68 -> 0.5 | I69: =I59+I57-I61+I63+I64+I66+I67+I68 -> 0.5 | J69: =J59+J57-J61+J63+J64+J66+J67+J68 -> 0.5 | K69: =K59+K57-K61+K63+K64+K66+K67+K68 -> 0.5 | ... M69: =M59+M57-M61+M63+M64+M66+M67+M68 -> 0.5
A70: 6. DEBT SCHEDULE
A71: Senior term loan — beginning | D71: =C74 -> 4.05 | E71: =D74 -> 3.8475 | F71: =E74 -> 3.645 | G71: =F74 -> 3.4425 | H71: =G74 -> 2.448646 | I71: =H74 -> 0 | J71: =I74 -> 0 | K71: =J74 -> 0 | ... M71: =L74 -> 0
A72: Mandatory amortization | D72: =-MIN(D71,$C$74*Assumptions!$B$60) -> -0.2025 | E72: =-MIN(E71,$C$74*Assumptions!$B$60) -> -0.2025 | F72: =-MIN(F71,$C$74*Assumptions!$B$60) -> -0.2025 | G72: =-MIN(G71,$C$74*Assumptions!$B$60) -> -0.2025 | H72: =-MIN(H71,$C$74*Assumptions!$B$60) -> -0.2025 | I72: =-MIN(I71,$C$74*Assumptions!$B$60) -> 0 | J72: =-MIN(J71,$C$74*Assumptions!$B$60) -> 0 | K72: =-MIN(K71,$C$74*Assumptions!$B$60) -> 0 | ... M72: =-MIN(M71,$C$74*Assumptions!$B$60) -> 0
A73: Cash sweep | D73: =D67 -> 0 | E73: =E67 -> 0 | F73: =F67 -> 0 | G73: =G67 -> -0.79135398 | H73: =H67 -> -2.246146 | I73: =I67 -> 0 | J73: =J67 -> 0 | K73: =K67 -> 0 | ... M73: =M67 -> 0
A74: Senior term loan — ending | C74: ='Sources & Uses'!$C$18 -> 4.05 | D74: =D71+D72+D73 -> 3.8475 | E74: =E71+E72+E73 -> 3.645 | F74: =F71+F72+F73 -> 3.4425 | G74: =G71+G72+G73 -> 2.448646 | H74: =H71+H72+H73 -> 0 | I74: =I71+I72+I73 -> 0 | J74: =J71+J72+J73 -> 0 | K74: =K71+K72+K73 -> 0 | ... M74: =M71+M72+M73 -> 0
A75: DDTL — beginning | D75: =C78 -> 0 | E75: =D78 -> 1.45775 | F75: =E78 -> 3.6589525 | G75: =F78 -> 5.8410585 | H75: =G78 -> 8.0086613 | I75: =H78 -> 10.16627 | J75: =I78 -> 11.431532 | K75: =J78 -> 12.704475 | ... M75: =L78 -> 14.285689
A76: Draws for add-ons | D76: =D17 -> 1.45775 | E76: =E17 -> 2.27409 | F76: =F17 -> 2.3650536 | G76: =G17 -> 2.4596557 | H76: =H17 -> 2.558042 | I76: =I17 -> 1.7735758 | J76: =J17 -> 1.8445188 | K76: =K17 -> 1.9182996 | ... M76: =M17 -> 0
A77: Amortization | D77: =-D75*Assumptions!$B$65 -> 0 | E77: =-E75*Assumptions!$B$65 -> -0.0728875 | F77: =-F75*Assumptions!$B$65 -> -0.18294763 | G77: =-G75*Assumptions!$B$65 -> -0.29205292 | H77: =-H75*Assumptions!$B$65 -> -0.40043306 | I77: =-I75*Assumptions!$B$65 -> -0.50831351 | J77: =-J75*Assumptions!$B$65 -> -0.57157662 | K77: =-K75*Assumptions!$B$65 -> -0.63522373 | ... M77: =-M75*Assumptions!$B$65 -> -0.71428444
A78: DDTL — ending | C78: 0 | D78: =D75+D76+D77 -> 1.45775 | E78: =E75+E76+E77 -> 3.6589525 | F78: =F75+F76+F77 -> 5.8410585 | G78: =G75+G76+G77 -> 8.0086613 | H78: =H75+H76+H77 -> 10.16627 | I78: =I75+I76+I77 -> 11.431532 | J78: =J75+J76+J77 -> 12.704475 | K78: =K75+K76+K77 -> 13.98755 | ... M78: =M75+M76+M77 -> 13.571404
A79: Seller notes — beginning | D79: =C82 -> 0.945 | E79: =D82 -> 1.3335 | F79: =E82 -> 1.9156725 | G79: =F82 -> 2.2931769 | H79: =G82 -> 2.4578265 | I79: =H82 -> 2.637357 | J79: =I82 -> 2.3627994 | K79: =J82 -> 2.1722724 | ... M79: =L82 -> 1.629383
A80: Issued | C80: ='Sources & Uses'!$C$19 -> 0.945 | D80: =D18 -> 0.62475 | E80: =E18 -> 0.97461 | F80: =F18 -> 1.0135944 | G80: =G18 -> 1.0541382 | H80: =H18 -> 1.0963037 | I80: =I18 -> 0.7601039 | J80: =J18 -> 0.79050806 | K80: =K18 -> 0.82212838 | ... M80: =M18 -> 0
A81: Straight-line repayment | D81: =-MIN(D79,SUMPRODUCT(($C$6:$M$6<D6)*($C$6:$M$6>=D6-Assumptions!$B$68)*($C$80:$M$80))/Assumptions!$B$68) -> -0.23625 | E81: =-MIN(E79,SUMPRODUCT(($C$6:$M$6<E6)*($C$6:$M$6>=E6-Assumptions!$B$68)*($C$80:$M$80))/Assumptions!$B$68) -> -0.3924375 | F81: =-MIN(F79,SUMPRODUCT(($C$6:$M$6<F6)*($C$6:$M$6>=F6-Assumptions!$B$68)*($C$80:$M$80))/Assumptions!$B$68) -> -0.63609 | G81: =-MIN(G79,SUMPRODUCT(($C$6:$M$6<G6)*($C$6:$M$6>=G6-Assumptions!$B$68)*($C$80:$M$80))/Assumptions!$B$68) -> -0.8894886 | H81: =-MIN(H79,SUMPRODUCT(($C$6:$M$6<H6)*($C$6:$M$6>=H6-Assumptions!$B$68)*($C$80:$M$80))/Assumptions!$B$68) -> -0.91677314 | I81: =-MIN(I79,SUMPRODUCT(($C$6:$M$6<I6)*($C$6:$M$6>=I6-Assumptions!$B$68)*($C$80:$M$80))/Assumptions!$B$68) -> -1.0346616 | J81: =-MIN(J79,SUMPRODUCT(($C$6:$M$6<J6)*($C$6:$M$6>=J6-Assumptions!$B$68)*($C$80:$M$80))/Assumptions!$B$68) -> -0.98103504 | K81: =-MIN(K79,SUMPRODUCT(($C$6:$M$6<K6)*($C$6:$M$6>=K6-Assumptions!$B$68)*($C$80:$M$80))/Assumptions!$B$68) -> -0.92526346 | ... M81: =-MIN(M79,SUMPRODUCT(($C$6:$M$6<M6)*($C$6:$M$6>=M6-Assumptions!$B$68)*($C$80:$M$80))/Assumptions!$B$68) -> -0.70006177
A82: Seller notes — ending | C82: =C80 -> 0.945 | D82: =D79+D81+D80 -> 1.3335 | E82: =E79+E81+E80 -> 1.9156725 | F82: =F79+F81+F80 -> 2.2931769 | G82: =G79+G81+G80 -> 2.4578265 | H82: =H79+H81+H80 -> 2.637357 | I82: =I79+I81+I80 -> 2.3627994 | J82: =J79+J81+J80 -> 2.1722724 | K82: =K79+K81+K80 -> 2.0691373 | ... M82: =M79+M81+M80 -> 0.92932127
A83: Revolver — ending | C83: 0 | D83: =C83+D64+D66 -> 0 | E83: =D83+E64+E66 -> 0 | F83: =E83+F64+F66 -> 0 | G83: =F83+G64+G66 -> 0 | H83: =G83+H64+H66 -> 0 | I83: =H83+I64+I66 -> 0 | J83: =I83+J64+J66 -> 0 | K83: =J83+K64+K66 -> 0 | ... M83: =L83+M64+M66 -> 0
A84: TOTAL DEBT | C84: =C74+C78+C82+C83 -> 4.995 | D84: =D74+D78+D82+D83 -> 6.63875 | E84: =E74+E78+E82+E83 -> 9.219625 | F84: =F74+F78+F82+F83 -> 11.576735 | G84: =G74+G78+G82+G83 -> 12.915134 | H84: =H74+H78+H82+H83 -> 12.803627 | I84: =I74+I78+I82+I83 -> 13.794332 | J84: =J74+J78+J82+J83 -> 14.876747 | ... M84: =M74+M78+M82+M83 -> 14.500726
A85: Net debt | C85: =C84-C69 -> 4.495 | D85: =D84-D69 -> 6.13875 | E85: =E84-E69 -> 8.719625 | F85: =F84-F69 -> 11.076735 | G85: =G84-G69 -> 11.62378 | H85: =H84-H69 -> 12.303627 | I85: =I84-I69 -> 13.294332 | J85: =J84-J69 -> 14.376747 | ... M85: =M84-M69 -> 14.000726
A86: Total leverage (Debt / PF EBITDA) | C86: =IF(C41<=0,0,C84/C41) -> 2.775 | D86: =IF(D41<=0,0,D84/D41) -> 3.328007 | E86: =IF(E41<=0,0,E84/E41) -> 2.2535738 | F86: =IF(F41<=0,0,F84/F41) -> 1.6004378 | G86: =IF(G41<=0,0,G84/G41) -> 1.130121 | H86: =IF(H41<=0,0,H84/H41) -> 0.8367502 | I86: =IF(I41<=0,0,I84/I41) -> 0.73755744 | J86: =IF(J41<=0,0,J84/J41) -> 0.67171872 | ... M86: =IF(M41<=0,0,M84/M41) -> 0.4676342
A87: Covenant check (1 = OK) | C87: =IF(C86<=Assumptions!$B$69,1,0) -> 1 | D87: =IF(D86<=Assumptions!$B$69,1,0) -> 1 | E87: =IF(E86<=Assumptions!$B$69,1,0) -> 1 | F87: =IF(F86<=Assumptions!$B$69,1,0) -> 1 | G87: =IF(G86<=Assumptions!$B$69,1,0) -> 1 | H87: =IF(H86<=Assumptions!$B$69,1,0) -> 1 | I87: =IF(I86<=Assumptions!$B$69,1,0) -> 1 | J87: =IF(J86<=Assumptions!$B$69,1,0) -> 1 | ... M87: =IF(M86<=Assumptions!$B$69,1,0) -> 1
A88: Earnout liability created (max) | C88: ='Sources & Uses'!$C$21 -> 0.945 | D88: =D20 -> 0.4165 | E88: =E20 -> 0.64974 | F88: =F20 -> 0.6757296 | G88: =G20 -> 0.70275878 | H88: =H20 -> 0.73086914 | I88: =I20 -> 0.50673593 | J88: =J20 -> 0.52700537 | K88: =K20 -> 0.54808559 | ... M88: =M20 -> 0
A89: Interest — senior | D89: =-D71*(Assumptions!$B$19+Assumptions!$B$59) -> -0.3645 | E89: =-E71*(Assumptions!$B$19+Assumptions!$B$59) -> -0.346275 | F89: =-F71*(Assumptions!$B$19+Assumptions!$B$59) -> -0.32805 | G89: =-G71*(Assumptions!$B$19+Assumptions!$B$59) -> -0.309825 | H89: =-H71*(Assumptions!$B$19+Assumptions!$B$59) -> -0.22037814 | I89: =-I71*(Assumptions!$B$19+Assumptions!$B$59) -> 0 | J89: =-J71*(Assumptions!$B$19+Assumptions!$B$59) -> 0 | K89: =-K71*(Assumptions!$B$19+Assumptions!$B$59) -> 0 | ... M89: =-M71*(Assumptions!$B$19+Assumptions!$B$59) -> 0
A90: Interest — DDTL (incl. half-year on new draws) | D90: =-(D75+D76*Assumptions!$B$42)*(Assumptions!$B$19+Assumptions!$B$64) -> -0.067420937 | E90: =-(E75+E76*Assumptions!$B$42)*(Assumptions!$B$19+Assumptions!$B$64) -> -0.24001854 | F90: =-(F75+F76*Assumptions!$B$42)*(Assumptions!$B$19+Assumptions!$B$64) -> -0.44783684 | G90: =-(G75+G76*Assumptions!$B$42)*(Assumptions!$B$19+Assumptions!$B$64) -> -0.65405699 | H90: =-(H75+H76*Assumptions!$B$42)*(Assumptions!$B$19+Assumptions!$B$64) -> -0.85911061 | I90: =-(I75+I76*Assumptions!$B$42)*(Assumptions!$B$19+Assumptions!$B$64) -> -1.0224079 | J90: =-(J75+J76*Assumptions!$B$42)*(Assumptions!$B$19+Assumptions!$B$64) -> -1.1427257 | K90: =-(K75+K76*Assumptions!$B$42)*(Assumptions!$B$19+Assumptions!$B$64) -> -1.2638853 | ... M90: =-(M75+M76*Assumptions!$B$42)*(Assumptions!$B$19+Assumptions!$B$64) -> -1.3214262
A91: Interest — seller notes | D91: =-D79*Assumptions!$B$67 -> -0.06615 | E91: =-E79*Assumptions!$B$67 -> -0.093345 | F91: =-F79*Assumptions!$B$67 -> -0.13409708 | G91: =-G79*Assumptions!$B$67 -> -0.16052238 | H91: =-H79*Assumptions!$B$67 -> -0.17204785 | I91: =-I79*Assumptions!$B$67 -> -0.18461499 | J91: =-J79*Assumptions!$B$67 -> -0.16539596 | K91: =-K79*Assumptions!$B$67 -> -0.15205907 | ... M91: =-M79*Assumptions!$B$67 -> -0.11405681
A92: Interest — revolver | D92: =-C83*(Assumptions!$B$19+Assumptions!$B$66) -> 0 | E92: =-D83*(Assumptions!$B$19+Assumptions!$B$66) -> 0 | F92: =-E83*(Assumptions!$B$19+Assumptions!$B$66) -> 0 | G92: =-F83*(Assumptions!$B$19+Assumptions!$B$66) -> 0 | H92: =-G83*(Assumptions!$B$19+Assumptions!$B$66) -> 0 | I92: =-H83*(Assumptions!$B$19+Assumptions!$B$66) -> 0 | J92: =-I83*(Assumptions!$B$19+Assumptions!$B$66) -> 0 | K92: =-J83*(Assumptions!$B$19+Assumptions!$B$66) -> 0 | ... M92: =-L83*(Assumptions!$B$19+Assumptions!$B$66) -> 0
A93: 7. EQUITY, UNITS & OWNERSHIP
A94: Cumulative Leviathan equity drawn | C94: =C63 -> 2.9705 | D94: =C94+D63 -> 4.5626938 | E94: =D94+E63 -> 6.9506542 | F94: =E94+F63 -> 8.9657475 | G94: =F94+G63 -> 10.722645 | H94: =G94+H63 -> 12.549817 | I94: =H94+I63 -> 13.816657 | J94: =I94+J63 -> 15 | K94: =J94+K63 -> 15 | ... M94: =L94+M63 -> 15
A95: Cap check: drawn <= $15M (1 = OK) | C95: =IF(C94<=Assumptions!$B$23+0.0001,1,0) -> 1 | D95: =IF(D94<=Assumptions!$B$23+0.0001,1,0) -> 1 | E95: =IF(E94<=Assumptions!$B$23+0.0001,1,0) -> 1 | F95: =IF(F94<=Assumptions!$B$23+0.0001,1,0) -> 1 | G95: =IF(G94<=Assumptions!$B$23+0.0001,1,0) -> 1 | H95: =IF(H94<=Assumptions!$B$23+0.0001,1,0) -> 1 | I95: =IF(I94<=Assumptions!$B$23+0.0001,1,0) -> 1 | J95: =IF(J94<=Assumptions!$B$23+0.0001,1,0) -> 1 | ... M95: =IF(M94<=Assumptions!$B$23+0.0001,1,0) -> 1
A96: Seller rollover equity contributed | C96: ='Sources & Uses'!$C$20 -> 1.4175 | D96: =D19 -> 0.20825 | E96: =E19 -> 0.32487 | F96: =F19 -> 0.3378648 | G96: =G19 -> 0.35137939 | H96: =H19 -> 0.36543457 | I96: =I19 -> 0.25336797 | J96: =J19 -> 0.26350269 | K96: =K19 -> 0.27404279 | ... M96: =M19 -> 0
A97: Cumulative contributed equity (Leviathan + rollover) | C97: =C63+C96 -> 4.388 | D97: =C97+D63+D96 -> 6.1884438 | E97: =D97+E63+E96 -> 8.9012742 | F97: =E97+F63+F96 -> 11.254232 | G97: =F97+G63+G96 -> 13.362509 | H97: =G97+H63+H96 -> 15.555116 | I97: =H97+I63+I96 -> 17.075324 | J97: =I97+J63+J96 -> 18.522169 | K97: =J97+K63+K96 -> 18.796212 | ... M97: =L97+M63+M96 -> 18.938714
A98: Unit price ($ per unit) | C98: 1 | D98: =MAX($C$98,(C41*Assumptions!$B$72-C85)/C100) -> 1.847083 | E98: =MAX($C$98,(D41*Assumptions!$B$72-D85)/D100) -> 1.4591278 | F98: =MAX($C$98,(E41*Assumptions!$B$72-E85)/E100) -> 2.7579987 | G98: =MAX($C$98,(F41*Assumptions!$B$72-F85)/F100) -> 4.8987148 | H98: =MAX($C$98,(G41*Assumptions!$B$72-G85)/G100) -> 8.0386921 | I98: =MAX($C$98,(H41*Assumptions!$B$72-H85)/H100) -> 10.800312 | J98: =MAX($C$98,(I41*Assumptions!$B$72-I85)/I100) -> 13.188123 | K98: =MAX($C$98,(J41*Assumptions!$B$72-J85)/J100) -> 15.578577 | ... M98: =MAX($C$98,(L41*Assumptions!$B$72-L85)/L100) -> 20.5808
A99: Leviathan units (cumulative, M) | C99: =C63/C98 -> 2.9705 | D99: =C99+D63/D98 -> 3.8325045 | E99: =D99+E63/E98 -> 5.4690715 | F99: =E99+F63/F98 -> 6.1997075 | G99: =F99+G63/G98 -> 6.558352 | H99: =G99+H63/H98 -> 6.7856493 | I99: =H99+I63/I98 -> 6.9029459 | J99: =I99+J63/J98 -> 6.9926738 | K99: =J99+K63/K98 -> 6.9926738 | ... M99: =L99+M63/M98 -> 6.9926738
A100: Total units (cumulative, M) | C100: =(C63+C96)/C98 -> 4.388 | D100: =C100+(D63+D96)/D98 -> 5.3627498 | E100: =D100+(E63+E96)/E98 -> 7.2219635 | F100: =E100+(F63+F96)/F98 -> 8.0751032 | G100: =F100+(G63+G96)/G98 -> 8.5054766 | H100: =G100+(H63+H96)/H98 -> 8.7782333 | I100: =H100+(I63+I96)/I98 -> 8.9189892 | J100: =I100+(J63+J96)/J98 -> 9.0286974 | K100: =J100+(K63+K96)/K98 -> 9.0462884 | ... M100: =L100+(M63+M96)/M98 -> 9.0541046
A101: Leviathan fully-diluted ownership (pre-MIP) | C101: =C99/C100 -> 0.67695989 | D101: =D99/D100 -> 0.71465286 | E101: =E99/E100 -> 0.75728318 | F101: =F99/F100 -> 0.76775583 | G101: =G99/G100 -> 0.77107402 | H101: =H99/H100 -> 0.77300854 | I101: =I99/I100 -> 0.77396056 | J101: =J99/J100 -> 0.7744942 | ... M101: =M99/M100 -> 0.77232085
A102: Distributions to Leviathan (x ownership) | D102: =-D68*D101 -> 0 | E102: =-E68*E101 -> 0 | F102: =-F68*F101 -> 0 | G102: =-G68*G101 -> 0 | H102: =-H68*H101 -> 1.8395078 | I102: =-I68*I101 -> 5.0924173 | J102: =-J68*J101 -> 6.6330831 | K102: =-K68*K101 -> 7.5497519 | ... M102: =-M68*M101 -> 12.29219
...

Sheet Synergies
A1: SYNERGIES — PLATFORM OPERATING + BUYER (BX INFRA / SAFE HARBOR, MARINEMAX)
A2: Part A feeds platform EBITDA. Part B is buyer-side value that a strategic shares with the seller at exit.
A4: A. PLATFORM OPERATING SYNERGIES — mature margin uplift (% of core revenue)
A5: OEM parts share of revenue | C5: 0.275 | N5: CIM: 25-30%.
A6: Parts COGS as % of parts revenue | C6: 0.65 | N6: Optimized: OEM parts gross margin ~35%, not CIM's 40-60%.
A7: Procurement savings on parts COGS | C7: 0.1 | N7: CIM 8-15%.
A8: Back-office consolidation (pts of revenue) | C8: 0.02 | N8: CIM implies 6-8 pts (25-30% -> 18-22%); haircut to 2 pts. HQ cost is modeled separately.
A9: Labor share of revenue | C9: 0.5 | N9: Maintenance/repair + repower + mobile.
A10: Technician utilization: standalone -> platform | C10: 0.7 | D10: 0.8 | N10: CIM 65-75% -> 85-95%. Optimized target 80% (cell D10).
A11: Flow-through of incremental billable hours | C11: 0.2 | N11: Techs are paid more under platform comp plans.
A12: Pricing / mix (ESPs, e-commerce parts, IoT subs) (pts) | C12: 0.0075
A13: TOTAL mature margin uplift (pre-scenario scaling) | C13: =C5*C6*C7+C8+C9*(D10/C10-1)*C11+C12 -> 0.059660714
A14: Years to full run-rate (integration ramp) | C14: 4
A15: Procurement component | C15: =C5*C6*C7 -> 0.017875
A16: Back-office component | C16: =C8 -> 0.02
A17: Utilization component | C17: =C9*(D10/C10-1)*C11 -> 0.014285714
A18: Pricing / mix component | C18: =C12 -> 0.0075
A20: B. BUYER SYNERGIES BY EXIT YEAR ($M EBITDA, run-rate at exit)
A21: Blackstone Infrastructure (Safe Harbor integration) | C21: Close | D21: 2027 | E21: 2028 | F21: 2029 | G21: 2030 | H21: 2031 | I21: 2032 | J21: 2033 | K21: 2034 | L21: 2035 | M21: 2036
A22: Safe Harbor marinas a buyer could equip (#) | D22: =Assumptions!$B$76*Assumptions!$B$77 -> 55.2 | E22: =Assumptions!$B$76*Assumptions!$B$77 -> 55.2 | F22: =Assumptions!$B$76*Assumptions!$B$77 -> 55.2 | G22: =Assumptions!$B$76*Assumptions!$B$77 -> 55.2 | H22: =Assumptions!$B$76*Assumptions!$B$77 -> 55.2 | I22: =Assumptions!$B$76*Assumptions!$B$77 -> 55.2 | J22: =Assumptions!$B$76*Assumptions!$B$77 -> 55.2 | K22: =Assumptions!$B$76*Assumptions!$B$77 -> 55.2 | ... M22: =Assumptions!$B$76*Assumptions!$B$77 -> 55.2
A23: Incremental marinas = MIN(open network, 1 per platform location) | D23: =MIN(MAX(0,D22-'Roll-Up Model'!D26),'Roll-Up Model'!D11) -> 4 | E23: =MIN(MAX(0,E22-'Roll-Up Model'!E26),'Roll-Up Model'!E11) -> 7 | F23: =MIN(MAX(0,F22-'Roll-Up Model'!F26),'Roll-Up Model'!F11) -> 10 | G23: =MIN(MAX(0,G22-'Roll-Up Model'!G26),'Roll-Up Model'!G11) -> 13 | H23: =MIN(MAX(0,H22-'Roll-Up Model'!H26),'Roll-Up Model'!H11) -> 16 | I23: =MIN(MAX(0,I22-'Roll-Up Model'!I26),'Roll-Up Model'!I11) -> 18 | J23: =MIN(MAX(0,J22-'Roll-Up Model'!J26),'Roll-Up Model'!J11) -> 20 | K23: =MIN(MAX(0,K22-'Roll-Up Model'!K26),'Roll-Up Model'!K11) -> 22 | ... M23: =MIN(MAX(0,M22-'Roll-Up Model'!M26),'Roll-Up Model'!M11) -> 23
A24: Marina-network revenue synergy EBITDA | D24: =D23*Assumptions!$B$50*Assumptions!$B$51 -> 1.008 | E24: =E23*Assumptions!$B$50*Assumptions!$B$51 -> 1.764 | F24: =F23*Assumptions!$B$50*Assumptions!$B$51 -> 2.52 | G24: =G23*Assumptions!$B$50*Assumptions!$B$51 -> 3.276 | H24: =H23*Assumptions!$B$50*Assumptions!$B$51 -> 4.032 | I24: =I23*Assumptions!$B$50*Assumptions!$B$51 -> 4.536 | J24: =J23*Assumptions!$B$50*Assumptions!$B$51 -> 5.04 | K24: =K23*Assumptions!$B$50*Assumptions!$B$51 -> 5.544 | ... M24: =M23*Assumptions!$B$50*Assumptions!$B$51 -> 5.796
A25: BX scale cost synergies (insurance, GPO, fleet) | D25: ='Roll-Up Model'!D28*Assumptions!$B$78 -> 0.21 | E25: ='Roll-Up Model'!E28*Assumptions!$B$78 -> 0.357525 | F25: ='Roll-Up Model'!F28*Assumptions!$B$78 -> 0.57188475 | G25: ='Roll-Up Model'!G28*Assumptions!$B$78 -> 0.8278562 | H25: ='Roll-Up Model'!H28*Assumptions!$B$78 -> 1.1012157 | I25: ='Roll-Up Model'!I28*Assumptions!$B$78 -> 1.3611803 | J25: ='Roll-Up Model'!J28*Assumptions!$B$78 -> 1.6045022 | K25: ='Roll-Up Model'!K28*Assumptions!$B$78 -> 1.8627988 | ... M25: ='Roll-Up Model'!M28*Assumptions!$B$78 -> 2.278056
A26: MarineMax channel agreement (prob-weighted, scaled to footprint) | D26: =Assumptions!$B$79*Assumptions!$B$80*Assumptions!$B$82*MIN(1,'Roll-Up Model'!D11/Assumptions!$B$81) -> 0.44 | E26: =Assumptions!$B$79*Assumptions!$B$80*Assumptions!$B$82*MIN(1,'Roll-Up Model'!E11/Assumptions!$B$81) -> 0.77 | F26: =Assumptions!$B$79*Assumptions!$B$80*Assumptions!$B$82*MIN(1,'Roll-Up Model'!F11/Assumptions!$B$81) -> 1.1 | G26: =Assumptions!$B$79*Assumptions!$B$80*Assumptions!$B$82*MIN(1,'Roll-Up Model'!G11/Assumptions!$B$81) -> 1.43 | H26: =Assumptions!$B$79*Assumptions!$B$80*Assumptions!$B$82*MIN(1,'Roll-Up Model'!H11/Assumptions!$B$81) -> 1.76 | I26: =Assumptions!$B$79*Assumptions!$B$80*Assumptions!$B$82*MIN(1,'Roll-Up Model'!I11/Assumptions!$B$81) -> 1.98 | J26: =Assumptions!$B$79*Assumptions!$B$80*Assumptions!$B$82*MIN(1,'Roll-Up Model'!J11/Assumptions!$B$81) -> 2.2 | K26: =Assumptions!$B$79*Assumptions!$B$80*Assumptions!$B$82*MIN(1,'Roll-Up Model'!K11/Assumptions!$B$81) -> 2.2 | ... M26: =Assumptions!$B$79*Assumptions!$B$80*Assumptions!$B$82*MIN(1,'Roll-Up Model'!M11/Assumptions!$B$81) -> 2.2
A27: TOTAL BX Infra buyer synergy EBITDA | D27: =SUM(D24:D26) -> 1.658 | E27: =SUM(E24:E26) -> 2.891525 | F27: =SUM(F24:F26) -> 4.1918847 | G27: =SUM(G24:G26) -> 5.5338562 | H27: =SUM(H24:H26) -> 6.8932157 | I27: =SUM(I24:I26) -> 7.8771803 | J27: =SUM(J24:J26) -> 8.8445022 | K27: =SUM(K24:K26) -> 9.6067988 | ... M27: =SUM(M24:M26) -> 10.274056
A28: Synergy value paid to seller (x infra mult x haircut x share) | D28: =D27*Assumptions!$B$17*Assumptions!$B$75*Assumptions!$B$18 -> 5.2227 | E28: =E27*Assumptions!$B$17*Assumptions!$B$75*Assumptions!$B$18 -> 9.1083037 | F28: =F27*Assumptions!$B$17*Assumptions!$B$75*Assumptions!$B$18 -> 13.204437 | G28: =G27*Assumptions!$B$17*Assumptions!$B$75*Assumptions!$B$18 -> 17.431647 | H28: =H27*Assumptions!$B$17*Assumptions!$B$75*Assumptions!$B$18 -> 21.713629 | I28: =I27*Assumptions!$B$17*Assumptions!$B$75*Assumptions!$B$18 -> 24.813118 | J28: =J27*Assumptions!$B$17*Assumptions!$B$75*Assumptions!$B$18 -> 27.860182 | K28: =K27*Assumptions!$B$17*Assumptions!$B$75*Assumptions!$B$18 -> 30.261416 | ... M28: =M27*Assumptions!$B$17*Assumptions!$B$75*Assumptions!$B$18 -> 32.363276
A30: MarineMax (strategic dealer-group buyer)
A31: Routed MarineMax service / repower EBITDA (scaled to footprint) | D31: =Assumptions!$B$79*Assumptions!$B$80*MIN(1,'Roll-Up Model'!D11/Assumptions!$B$81) -> 0.88 | E31: =Assumptions!$B$79*Assumptions!$B$80*MIN(1,'Roll-Up Model'!E11/Assumptions!$B$81) -> 1.54 | F31: =Assumptions!$B$79*Assumptions!$B$80*MIN(1,'Roll-Up Model'!F11/Assumptions!$B$81) -> 2.2 | G31: =Assumptions!$B$79*Assumptions!$B$80*MIN(1,'Roll-Up Model'!G11/Assumptions!$B$81) -> 2.86 | H31: =Assumptions!$B$79*Assumptions!$B$80*MIN(1,'Roll-Up Model'!H11/Assumptions!$B$81) -> 3.52 | I31: =Assumptions!$B$79*Assumptions!$B$80*MIN(1,'Roll-Up Model'!I11/Assumptions!$B$81) -> 3.96 | J31: =Assumptions!$B$79*Assumptions!$B$80*MIN(1,'Roll-Up Model'!J11/Assumptions!$B$81) -> 4.4 | K31: =Assumptions!$B$79*Assumptions!$B$80*MIN(1,'Roll-Up Model'!K11/Assumptions!$B$81) -> 4.4 | ... M31: =Assumptions!$B$79*Assumptions!$B$80*MIN(1,'Roll-Up Model'!M11/Assumptions!$B$81) -> 4.4
A32: Parts purchasing cost synergies | D32: ='Roll-Up Model'!D28*Assumptions!$B$84 -> 0.105 | E32: ='Roll-Up Model'!E28*Assumptions!$B$84 -> 0.1787625 | F32: ='Roll-Up Model'!F28*Assumptions!$B$84 -> 0.28594238 | G32: ='Roll-Up Model'!G28*Assumptions!$B$84 -> 0.4139281 | H32: ='Roll-Up Model'!H28*Assumptions!$B$84 -> 0.55060785 | I32: ='Roll-Up Model'!I28*Assumptions!$B$84 -> 0.68059015 | J32: ='Roll-Up Model'!J28*Assumptions!$B$84 -> 0.80225109 | K32: ='Roll-Up Model'!K28*Assumptions!$B$84 -> 0.9313994 | ... M32: ='Roll-Up Model'!M28*Assumptions!$B$84 -> 1.139028
A33: TOTAL MarineMax buyer synergy EBITDA | D33: =D31+D32 -> 0.985 | E33: =E31+E32 -> 1.7187625 | F33: =F31+F32 -> 2.4859424 | G33: =G31+G32 -> 3.2739281 | H33: =H31+H32 -> 4.0706078 | I33: =I31+I32 -> 4.6405902 | J33: =J31+J32 -> 5.2022511 | K33: =K31+K32 -> 5.3313994 | ... M33: =M31+M32 -> 5.539028
A34: Synergy value paid to seller (x HZO mult x haircut x share) | D34: =D33*Assumptions!$B$83*Assumptions!$B$75*Assumptions!$B$18 -> 1.86165 | E34: =E33*Assumptions!$B$83*Assumptions!$B$75*Assumptions!$B$18 -> 3.2484611 | F34: =F33*Assumptions!$B$83*Assumptions!$B$75*Assumptions!$B$18 -> 4.6984311 | G34: =G33*Assumptions!$B$83*Assumptions!$B$75*Assumptions!$B$18 -> 6.1877241 | H34: =H33*Assumptions!$B$83*Assumptions!$B$75*Assumptions!$B$18 -> 7.6934488 | I34: =I33*Assumptions!$B$83*Assumptions!$B$75*Assumptions!$B$18 -> 8.7707154 | J34: =J33*Assumptions!$B$83*Assumptions!$B$75*Assumptions!$B$18 -> 9.8322546 | K34: =K33*Assumptions!$B$83*Assumptions!$B$75*Assumptions!$B$18 -> 10.076345 | ... M34: =M33*Assumptions!$B$83*Assumptions!$B$75*Assumptions!$B$18 -> 10.468763
A36: C. WHY BX INFRA IS THE NATURAL OWNER
A37: 1. Safe Harbor (BX Infra, $5.65B, 138 marinas, closed Apr-2025) owns the slips; the platform owns the engine-room. Embedding service bays converts ad-hoc repair into marina-contracted, infra-like revenue.
A38: 2. Every Safe Harbor slip holder with a diesel is a captive service customer; the platform's own embedded-bay program (Roll-Up Model row 'Safe Harbor marinas') is the proof-of-concept a buyer underwrites.
A39: 3. MarineMax (120+ locations, 65 marinas/storage, IGY superyacht marinas) is both a channel (repower, warranty overflow, superyacht diesel work) and the competing strategic bidder that keeps BX honest on price.
A40: 4. Infra capital prices contracted cash flows at a premium to services multiples; the model blends exit multiple by contracted revenue share, so the thesis is to 'infrastructure-ize' revenue before exit.

Sheet Exit & Returns
A1: EXIT ROUTES & LEVIATHAN RETURNS
A2: Routes: (1) 100% sale to Blackstone Infrastructure / Safe Harbor (2) Spin / partial: 60% to BX Infra, 40% retained to Y10 (3) MarineMax strategic (4) Sponsor-to-sponsor. $M.
A3: Year index | C3: 0 | D3: 1 | E3: 2 | F3: 3 | G3: 4 | H3: 5 | I3: 6 | J3: 7 | K3: 8 | L3: 9 | M3: 10
A4: Exit valuation if sold at end of year | C4: Close | D4: 2027 | E4: 2028 | F4: 2029 | G4: 2030 | H4: 2031 | I4: 2032 | J4: 2033 | K4: 2034 | L4: 2035 | M4: 2036
A5: Adjusted EBITDA | D5: ='Roll-Up Model'!D40 -> 1.5048125 | E5: ='Roll-Up Model'!E40 -> 3.326713 | F5: ='Roll-Up Model'!F40 -> 6.4385044 | G5: ='Roll-Up Model'!G40 -> 10.601323 | H5: ='Roll-Up Model'!H40 -> 14.441766 | I5: ='Roll-Up Model'!I40 -> 18.106562 | J5: ='Roll-Up Model'!J40 -> 21.52728 | K5: ='Roll-Up Model'!K40 -> 25.138945 | ... M5: ='Roll-Up Model'!M40 -> 31.008694
A6: Contracted % of revenue | D6: ='Roll-Up Model'!D32 -> 0.17857143 | E6: ='Roll-Up Model'!E32 -> 0.20714286 | F6: ='Roll-Up Model'!F32 -> 0.26954275 | G6: ='Roll-Up Model'!G32 -> 0.33177123 | H6: ='Roll-Up Model'!H32 -> 0.37412893 | I6: ='Roll-Up Model'!I32 -> 0.40975954 | J6: ='Roll-Up Model'!J32 -> 0.44228914 | K6: ='Roll-Up Model'!K32 -> 0.44715723 | ... M6: ='Roll-Up Model'!M32 -> 0.45833662
A7: Blended standalone multiple (services x (1-c) + infra x c) | D7: =Assumptions!$B$16*(1-D6)+Assumptions!$B$17*D6 -> 10.892857 | E7: =Assumptions!$B$16*(1-E6)+Assumptions!$B$17*E6 -> 11.035714 | F7: =Assumptions!$B$16*(1-F6)+Assumptions!$B$17*F6 -> 11.347714 | G7: =Assumptions!$B$16*(1-G6)+Assumptions!$B$17*G6 -> 11.658856 | H7: =Assumptions!$B$16*(1-H6)+Assumptions!$B$17*H6 -> 11.870645 | I7: =Assumptions!$B$16*(1-I6)+Assumptions!$B$17*I6 -> 12.048798 | J7: =Assumptions!$B$16*(1-J6)+Assumptions!$B$17*J6 -> 12.211446 | K7: =Assumptions!$B$16*(1-K6)+Assumptions!$B$17*K6 -> 12.235786 | ... M7: =Assumptions!$B$16*(1-M6)+Assumptions!$B$17*M6 -> 12.291683
A8: Net debt | D8: ='Roll-Up Model'!D85 -> 6.13875 | E8: ='Roll-Up Model'!E85 -> 8.719625 | F8: ='Roll-Up Model'!F85 -> 11.076735 | G8: ='Roll-Up Model'!G85 -> 11.62378 | H8: ='Roll-Up Model'!H85 -> 12.303627 | I8: ='Roll-Up Model'!I85 -> 13.294332 | J8: ='Roll-Up Model'!J85 -> 14.376747 | K8: ='Roll-Up Model'!K85 -> 15.556688 | ... M8: ='Roll-Up Model'!M85 -> 14.000726
A9: Cumulative contributed equity (Leviathan + rollover) | D9: ='Roll-Up Model'!D97 -> 6.1884438 | E9: ='Roll-Up Model'!E97 -> 8.9012742 | F9: ='Roll-Up Model'!F97 -> 11.254232 | G9: ='Roll-Up Model'!G97 -> 13.362509 | H9: ='Roll-Up Model'!H97 -> 15.555116 | I9: ='Roll-Up Model'!I97 -> 17.075324 | J9: ='Roll-Up Model'!J97 -> 18.522169 | K9: ='Roll-Up Model'!K97 -> 18.796212 | ... M9: ='Roll-Up Model'!M97 -> 18.938714
A10: Leviathan ownership | D10: ='Roll-Up Model'!D101 -> 0.71465286 | E10: ='Roll-Up Model'!E101 -> 0.75728318 | F10: ='Roll-Up Model'!F101 -> 0.76775583 | G10: ='Roll-Up Model'!G101 -> 0.77107402 | H10: ='Roll-Up Model'!H101 -> 0.77300854 | I10: ='Roll-Up Model'!I101 -> 0.77396056 | J10: ='Roll-Up Model'!J101 -> 0.7744942 | K10: ='Roll-Up Model'!K101 -> 0.77298815 | ... M10: ='Roll-Up Model'!M101 -> 0.77232085
A11: Cumulative Leviathan equity drawn | D11: ='Roll-Up Model'!D94 -> 4.5626938 | E11: ='Roll-Up Model'!E94 -> 6.9506542 | F11: ='Roll-Up Model'!F94 -> 8.9657475 | G11: ='Roll-Up Model'!G94 -> 10.722645 | H11: ='Roll-Up Model'!H94 -> 12.549817 | I11: ='Roll-Up Model'!I94 -> 13.816657 | J11: ='Roll-Up Model'!J94 -> 15 | K11: ='Roll-Up Model'!K94 -> 15 | ... M11: ='Roll-Up Model'!M94 -> 15
A12: Cumulative interim distributions to Leviathan (Y5+) | D12: ='Roll-Up Model'!D103 -> 0 | E12: ='Roll-Up Model'!E103 -> 0 | F12: ='Roll-Up Model'!F103 -> 0 | G12: ='Roll-Up Model'!G103 -> 0 | H12: ='Roll-Up Model'!H103 -> 1.8395078 | I12: ='Roll-Up Model'!I103 -> 6.9319251 | J12: ='Roll-Up Model'!J103 -> 13.565008 | K12: ='Roll-Up Model'!K103 -> 21.11476 | ... M12: ='Roll-Up Model'!M103 -> 43.410622
A14: ROUTE 1 — 100% SALE TO BLACKSTONE INFRASTRUCTURE (Safe Harbor tuck-in)
A15: Enterprise value | D15: =D5*D7+Synergies!D28 -> 21.614408 | E15: =E5*E7+Synergies!E28 -> 45.820958 | F15: =F5*F7+Synergies!F28 -> 86.266742 | G15: =G5*G7+Synergies!G28 -> 141.03095 | H15: =H5*H7+Synergies!H28 -> 193.14671 | I15: =I5*I7+Synergies!I28 -> 242.97542 | J15: =J5*J7+Synergies!J28 -> 290.7394 | K15: =K5*K7+Synergies!K28 -> 337.85618 | ... M15: =M5*M7+Synergies!M28 -> 413.51231
A16: Implied EV / EBITDA | D16: =IF(D5=0,0,D15/D5) -> 14.363522 | E16: =IF(E5=0,0,E15/E5) -> 13.773643 | F16: =IF(F5=0,0,F15/F5) -> 13.398568 | G16: =IF(G5=0,0,G15/G5) -> 13.303146 | H16: =IF(H5=0,0,H15/H5) -> 13.374175 | I16: =IF(I5=0,0,I15/I5) -> 13.419191 | J16: =IF(J5=0,0,J15/J5) -> 13.505626 | K16: =IF(K5=0,0,K15/K5) -> 13.439552 | ... M16: =IF(M5=0,0,M15/M5) -> 13.335367
A17: Equity value (EV - net debt - exit costs) | D17: =D15*(1-Assumptions!$B$74)-D8 -> 15.043369 | E17: =E15*(1-Assumptions!$B$74)-E8 -> 36.184914 | F17: =F15*(1-Assumptions!$B$74)-F8 -> 73.464672 | G17: =G15*(1-Assumptions!$B$74)-G8 -> 126.58655 | H17: =H15*(1-Assumptions!$B$74)-H8 -> 176.98014 | I17: =I15*(1-Assumptions!$B$74)-I8 -> 224.82158 | J17: =J15*(1-Assumptions!$B$74)-J8 -> 270.54786 | K17: =K15*(1-Assumptions!$B$74)-K8 -> 315.54236 | ... M17: =M15*(1-Assumptions!$B$74)-M8 -> 391.24134
A18: Less: management incentive pool | D18: =-Assumptions!$B$73*MAX(0,D17-D9) -> -0.88549256 | E18: =-Assumptions!$B$73*MAX(0,E17-E9) -> -2.728364 | F18: =-Assumptions!$B$73*MAX(0,F17-F9) -> -6.221044 | G18: =-Assumptions!$B$73*MAX(0,G17-G9) -> -11.322404 | H18: =-Assumptions!$B$73*MAX(0,H17-H9) -> -16.142503 | I18: =-Assumptions!$B$73*MAX(0,I17-I9) -> -20.774626 | J18: =-Assumptions!$B$73*MAX(0,J17-J9) -> -25.202569 | K18: =-Assumptions!$B$73*MAX(0,K17-K9) -> -29.674615 | ... M18: =-Assumptions!$B$73*MAX(0,M17-M9) -> -37.230263
A19: LEVIATHAN GROSS PROCEEDS | D19: =MAX(0,(D17+D18)*D10) -> 10.117967 | E19: =MAX(0,(E17+E18)*E10) -> 25.336082 | F19: =MAX(0,(F17+F18)*F10) -> 51.626687 | G19: =MAX(0,(G17+G18)*G10) -> 88.877188 | H19: =MAX(0,(H17+H18)*H10) -> 124.32887 | I19: =MAX(0,(I17+I18)*I10) -> 157.9243 | J19: =MAX(0,(J17+J18)*J10) -> 190.01851 | K19: =MAX(0,(K17+K18)*K10) -> 220.97238 | ... M19: =MAX(0,(M17+M18)*M10) -> 273.41014
A20: Gross MOIC (incl. interim distributions) | D20: =IF(D11=0,0,(D19+D12)/D11) -> 2.2175424 | E20: =IF(E11=0,0,(E19+E12)/E11) -> 3.6451364 | F20: =IF(F11=0,0,(F19+F12)/F11) -> 5.7582134 | G20: =IF(G11=0,0,(G19+G12)/G11) -> 8.2887378 | H20: =IF(H11=0,0,(H19+H12)/H11) -> 10.053404 | I20: =IF(I11=0,0,(I19+I12)/I11) -> 11.931701 | J20: =IF(J11=0,0,(J19+J12)/J11) -> 13.572234 | K20: =IF(K11=0,0,(K19+K12)/K11) -> 16.139143 | ... M20: =IF(M11=0,0,(M19+M12)/M11) -> 21.121384
A22: ROUTE 2 — SPIN / PARTIAL: 60% SOLD TO BX INFRA, 40% RETAINED TO Y10
A23: Proceeds on 60% sold at exit year (Route 1 pricing) | D23: =D19*(1-Assumptions!$B$85) -> 6.0707803 | E23: =E19*(1-Assumptions!$B$85) -> 15.201649 | F23: =F19*(1-Assumptions!$B$85) -> 30.976012 | G23: =G19*(1-Assumptions!$B$85) -> 53.326313 | H23: =H19*(1-Assumptions!$B$85) -> 74.597322 | I23: =I19*(1-Assumptions!$B$85) -> 94.754578 | J23: =J19*(1-Assumptions!$B$85) -> 114.0111 | K23: =K19*(1-Assumptions!$B$85) -> 132.58343 | ... M23: =M19*(1-Assumptions!$B$85) -> 164.04608
A24: Retained 40% value carried to Y10 | D24: =D19*Assumptions!$B$85*(1+Assumptions!$B$86)^(10-D$3) -> 11.223168 | E24: =E19*Assumptions!$B$85*(1+Assumptions!$B$86)^(10-E$3) -> 25.092483 | F24: =F19*Assumptions!$B$85*(1+Assumptions!$B$86)^(10-F$3) -> 45.652063 | G24: =G19*Assumptions!$B$85*(1+Assumptions!$B$86)^(10-G$3) -> 70.171124 | H24: =H19*Assumptions!$B$85*(1+Assumptions!$B$86)^(10-H$3) -> 87.64398 | I24: =I19*Assumptions!$B$85*(1+Assumptions!$B$86)^(10-I$3) -> 99.398775 | J24: =J19*Assumptions!$B$85*(1+Assumptions!$B$86)^(10-J$3) -> 106.78493 | K24: =K19*Assumptions!$B$85*(1+Assumptions!$B$86)^(10-K$3) -> 110.8751 | ... M24: =M19*Assumptions!$B$85*(1+Assumptions!$B$86)^(10-M$3) -> 109.36406
A25: LEVIATHAN TOTAL VALUE (sold + retained @Y10) | D25: =D23+D24 -> 17.293948 | E25: =E23+E24 -> 40.294132 | F25: =F23+F24 -> 76.628075 | G25: =G23+G24 -> 123.49744 | H25: =H23+H24 -> 162.2413 | I25: =I23+I24 -> 194.15335 | J25: =J23+J24 -> 220.79603 | K25: =K23+K24 -> 243.45853 | ... M25: =M23+M24 -> 273.41014
A26: Gross MOIC (incl. interim distributions) | D26: =IF(D11=0,0,(D25+D12)/D11) -> 3.7902934 | E26: =IF(E11=0,0,(E25+E12)/E11) -> 5.7971712 | F26: =IF(F11=0,0,(F25+F12)/F11) -> 8.5467581 | G26: =IF(G11=0,0,(G25+G12)/G11) -> 11.517442 | H26: =IF(H11=0,0,(H25+H12)/H11) -> 13.074358 | I26: =IF(I11=0,0,(I25+I12)/I11) -> 14.55383 | J26: =IF(J11=0,0,(J25+J12)/J11) -> 15.624069 | K26: =IF(K11=0,0,(K25+K12)/K11) -> 17.63822 | ... M26: =IF(M11=0,0,(M25+M12)/M11) -> 21.121384
A28: ROUTE 3 — STRATEGIC SALE TO MARINEMAX
A29: Enterprise value | D29: =D5*Assumptions!$B$83+Synergies!D34 -> 15.404962 | E29: =E5*Assumptions!$B$83+Synergies!E34 -> 33.188878 | F29: =F5*Assumptions!$B$83+Synergies!F34 -> 62.644971 | G29: =G5*Assumptions!$B$83+Synergies!G34 -> 101.59963 | H29: =H5*Assumptions!$B$83+Synergies!H34 -> 137.66935 | I29: =I5*Assumptions!$B$83+Synergies!I34 -> 171.72977 | J29: =J5*Assumptions!$B$83+Synergies!J34 -> 203.57778 | K29: =K5*Assumptions!$B$83+Synergies!K34 -> 236.32685 | ... M29: =M5*Assumptions!$B$83+Synergies!M34 -> 289.54701
A30: Implied EV / EBITDA | D30: =IF(D5=0,0,D29/D5) -> 10.237131 | E30: =IF(E5=0,0,E29/E5) -> 9.9764777 | F30: =IF(F5=0,0,F29/F5) -> 9.7297395 | G30: =IF(G5=0,0,G29/G5) -> 9.5836747 | H30: =IF(H5=0,0,H29/H5) -> 9.5327222 | I30: =IF(I5=0,0,I29/I5) -> 9.4843943 | J30: =IF(J5=0,0,J29/J5) -> 9.4567346 | K30: =IF(K5=0,0,K29/K5) -> 9.4008261 | ... M30: =IF(M5=0,0,M29/M5) -> 9.3376074
A31: Equity value (EV - net debt - exit costs) | D31: =D29*(1-Assumptions!$B$74)-D8 -> 8.9581133 | E31: =E29*(1-Assumptions!$B$74)-E8 -> 23.805476 | F31: =F29*(1-Assumptions!$B$74)-F8 -> 50.315336 | G31: =G29*(1-Assumptions!$B$74)-G8 -> 87.94386 | H31: =H29*(1-Assumptions!$B$74)-H8 -> 122.61233 | I31: =I29*(1-Assumptions!$B$74)-I8 -> 155.00085 | J31: =J29*(1-Assumptions!$B$74)-J8 -> 185.12948 | K31: =K29*(1-Assumptions!$B$74)-K8 -> 216.04363 | ... M31: =M29*(1-Assumptions!$B$74)-M8 -> 269.75534
A32: Less: management incentive pool | D32: =-Assumptions!$B$73*MAX(0,D31-D9) -> -0.27696694 | E32: =-Assumptions!$B$73*MAX(0,E31-E9) -> -1.4904201 | F32: =-Assumptions!$B$73*MAX(0,F31-F9) -> -3.9061104 | G32: =-Assumptions!$B$73*MAX(0,G31-G9) -> -7.4581351 | H32: =-Assumptions!$B$73*MAX(0,H31-H9) -> -10.705722 | I32: =-Assumptions!$B$73*MAX(0,I31-I9) -> -13.792552 | J32: =-Assumptions!$B$73*MAX(0,J31-J9) -> -16.660731 | K32: =-Assumptions!$B$73*MAX(0,K31-K9) -> -19.724742 | ... M32: =-Assumptions!$B$73*MAX(0,M31-M9) -> -25.081663
A33: LEVIATHAN GROSS PROCEEDS | D33: =MAX(0,(D31+D32)*D10) -> 6.204006 | E33: =MAX(0,(E31+E32)*E10) -> 16.898816 | F33: =MAX(0,(F31+F32)*F10) -> 35.630954 | G33: =MAX(0,(G31+G32)*G10) -> 62.060451 | H33: =MAX(0,(H31+H32)*H10) -> 86.504765 | I33: =MAX(0,(I31+I32)*I10) -> 109.28965 | J33: =MAX(0,(J31+J32)*J10) -> 130.47807 | K33: =MAX(0,(K31+K32)*K10) -> 151.75217 | ... M33: =MAX(0,(M31+M32)*M10) -> 188.96658
A34: Gross MOIC (incl. interim distributions) | D34: =IF(D11=0,0,(D33+D12)/D11) -> 1.3597244 | E34: =IF(E11=0,0,(E33+E12)/E11) -> 2.4312555 | F34: =IF(F11=0,0,(F33+F12)/F11) -> 3.9741197 | G34: =IF(G11=0,0,(G33+G12)/G11) -> 5.7877934 | H34: =IF(H11=0,0,(H33+H12)/H11) -> 7.0394867 | I34: =IF(I11=0,0,(I33+I12)/I11) -> 8.4117001 | J34: =IF(J11=0,0,(J33+J12)/J11) -> 9.6028716 | K34: =IF(K11=0,0,(K33+K12)/K11) -> 11.524462 | ... M34: =IF(M11=0,0,(M33+M12)/M11) -> 15.491814
A36: ROUTE 4 — SPONSOR-TO-SPONSOR (services multiple, no synergies)
A37: Enterprise value | D37: =D5*Assumptions!$B$16 -> 15.048125 | E37: =E5*Assumptions!$B$16 -> 33.26713 | F37: =F5*Assumptions!$B$16 -> 64.385044 | G37: =G5*Assumptions!$B$16 -> 106.01323 | H37: =H5*Assumptions!$B$16 -> 144.41766 | I37: =I5*Assumptions!$B$16 -> 181.06562 | J37: =J5*Assumptions!$B$16 -> 215.2728 | K37: =K5*Assumptions!$B$16 -> 251.38945 | ... M37: =M5*Assumptions!$B$16 -> 310.08694
A38: Implied EV / EBITDA | D38: =IF(D5=0,0,D37/D5) -> 10 | E38: =IF(E5=0,0,E37/E5) -> 10 | F38: =IF(F5=0,0,F37/F5) -> 10 | G38: =IF(G5=0,0,G37/G5) -> 10 | H38: =IF(H5=0,0,H37/H5) -> 10 | I38: =IF(I5=0,0,I37/I5) -> 10 | J38: =IF(J5=0,0,J37/J5) -> 10 | K38: =IF(K5=0,0,K37/K5) -> 10 | ... M38: =IF(M5=0,0,M37/M5) -> 10
A39: Equity value (EV - net debt - exit costs) | D39: =D37*(1-Assumptions!$B$74)-D8 -> 8.6084125 | E39: =E37*(1-Assumptions!$B$74)-E8 -> 23.882163 | F39: =F37*(1-Assumptions!$B$74)-F8 -> 52.020608 | G39: =G37*(1-Assumptions!$B$74)-G8 -> 92.269187 | H39: =H37*(1-Assumptions!$B$74)-H8 -> 129.22568 | I39: =I37*(1-Assumptions!$B$74)-I8 -> 164.14998 | J39: =J37*(1-Assumptions!$B$74)-J8 -> 196.5906 | K39: =K37*(1-Assumptions!$B$74)-K8 -> 230.80498 | ... M39: =M37*(1-Assumptions!$B$74)-M8 -> 289.88447
A40: Less: management incentive pool | D40: =-Assumptions!$B$73*MAX(0,D39-D9) -> -0.24199687 | E40: =-Assumptions!$B$73*MAX(0,E39-E9) -> -1.4980888 | F40: =-Assumptions!$B$73*MAX(0,F39-F9) -> -4.0766376 | G40: =-Assumptions!$B$73*MAX(0,G39-G9) -> -7.8906678 | H40: =-Assumptions!$B$73*MAX(0,H39-H9) -> -11.367057 | I40: =-Assumptions!$B$73*MAX(0,I39-I9) -> -14.707465 | J40: =-Assumptions!$B$73*MAX(0,J39-J9) -> -17.806843 | K40: =-Assumptions!$B$73*MAX(0,K39-K9) -> -21.200876 | ... M40: =-Assumptions!$B$73*MAX(0,M39-M9) -> -27.094576
A41: LEVIATHAN GROSS PROCEEDS | D41: =MAX(0,(D39+D40)*D10) -> 5.9790828 | E41: =MAX(0,(E39+E40)*E10) -> 16.951082 | F41: =MAX(0,(F39+F40)*F10) -> 36.809263 | G41: =MAX(0,(G39+G40)*G10) -> 65.062084 | H41: =MAX(0,(H39+H40)*H10) -> 91.105724 | I41: =MAX(0,(I39+I40)*I10) -> 115.66261 | J41: =MAX(0,(J39+J40)*J10) -> 138.46698 | K41: =MAX(0,(K39+K40)*K10) -> 162.02149 | ... M41: =MAX(0,(M39+M40)*M10) -> 202.95812
A42: Gross MOIC (incl. interim distributions) | D42: =IF(D11=0,0,(D41+D12)/D11) -> 1.3104282 | E42: =IF(E11=0,0,(E41+E12)/E11) -> 2.4387751 | F42: =IF(F11=0,0,(F41+F12)/F11) -> 4.1055431 | G42: =IF(G11=0,0,(G41+G12)/G11) -> 6.0677274 | H42: =IF(H11=0,0,(H41+H12)/H11) -> 7.4061024 | I42: =IF(I11=0,0,(I41+I12)/I11) -> 8.8729519 | J42: =IF(J11=0,0,(J41+J12)/J11) -> 10.135466 | K42: =IF(K11=0,0,(K41+K12)/K11) -> 12.209083 | ... M42: =IF(M11=0,0,(M41+M12)/M11) -> 16.424583
A45: IRR ENGINE — Leviathan gross cash flows by route x exit year (draws negative, proceeds at exit)
A46: Route / exit year | B46: Exit | C46: Close | D46: 2027 | E46: 2028 | F46: 2029 | G46: 2030 | H46: 2031 | I46: 2032 | J46: 2033 | K46: 2034 | L46: 2035 | M46: 2036 | N46: Gross IRR
A47: Route 1 — BX Infra sale | B47: 5 | C47: =IF(0<=$B47,-'Roll-Up Model'!C63+0,0)+IF(0=$B47,INDEX($D$19:$M$19,$B47),0) -> -2.9705 | D47: =IF(1<=$B47,-'Roll-Up Model'!D63+'Roll-Up Model'!D102,0)+IF(1=$B47,INDEX($D$19:$M$19,$B47),0) -> -1.5921938 | E47: =IF(2<=$B47,-'Roll-Up Model'!E63+'Roll-Up Model'!E102,0)+IF(2=$B47,INDEX($D$19:$M$19,$B47),0) -> -2.3879604 | F47: =IF(3<=$B47,-'Roll-Up Model'!F63+'Roll-Up Model'!F102,0)+IF(3=$B47,INDEX($D$19:$M$19,$B47),0) -> -2.0150933 | G47: =IF(4<=$B47,-'Roll-Up Model'!G63+'Roll-Up Model'!G102,0)+IF(4=$B47,INDEX($D$19:$M$19,$B47),0) -> -1.756897 | H47: =IF(5<=$B47,-'Roll-Up Model'!H63+'Roll-Up Model'!H102,0)+IF(5=$B47,INDEX($D$19:$M$19,$B47),0) -> 124.3412 | I47: =IF(6<=$B47,-'Roll-Up Model'!I63+'Roll-Up Model'!I102,0)+IF(6=$B47,INDEX($D$19:$M$19,$B47),0) -> 0 | J47: =IF(7<=$B47,-'Roll-Up Model'!J63+'Roll-Up Model'!J102,0)+IF(7=$B47,INDEX($D$19:$M$19,$B47),0) -> 0 | K47: =IF(8<=$B47,-'Roll-Up Model'!K63+'Roll-Up Model'!K102,0)+IF(8=$B47,INDEX($D$19:$M$19,$B47),0) -> 0 | L47: =IF(9<=$B47,-'Roll-Up Model'!L63+'Roll-Up Model'!L102,0)+IF(9=$B47,INDEX($D$19:$M$19,$B47),0) -> 0 | M47: =IF(10<=$B47,-'Roll-Up Model'!M63+'Roll-Up Model'!M102,0)+IF(10=$B47,INDEX($D$19:$M$19,$B47),0) -> 0 | N47: =IRR(C47:M47,0.25) -> 0.9110678
A48: Route 1 — BX Infra sale | B48: 6 | C48: =IF(0<=$B48,-'Roll-Up Model'!C63+0,0)+IF(0=$B48,INDEX($D$19:$M$19,$B48),0) -> -2.9705 | D48: =IF(1<=$B48,-'Roll-Up Model'!D63+'Roll-Up Model'!D102,0)+IF(1=$B48,INDEX($D$19:$M$19,$B48),0) -> -1.5921938 | E48: =IF(2<=$B48,-'Roll-Up Model'!E63+'Roll-Up Model'!E102,0)+IF(2=$B48,INDEX($D$19:$M$19,$B48),0) -> -2.3879604 | F48: =IF(3<=$B48,-'Roll-Up Model'!F63+'Roll-Up Model'!F102,0)+IF(3=$B48,INDEX($D$19:$M$19,$B48),0) -> -2.0150933 | G48: =IF(4<=$B48,-'Roll-Up Model'!G63+'Roll-Up Model'!G102,0)+IF(4=$B48,INDEX($D$19:$M$19,$B48),0) -> -1.756897 | H48: =IF(5<=$B48,-'Roll-Up Model'!H63+'Roll-Up Model'!H102,0)+IF(5=$B48,INDEX($D$19:$M$19,$B48),0) -> 0.012334957 | I48: =IF(6<=$B48,-'Roll-Up Model'!I63+'Roll-Up Model'!I102,0)+IF(6=$B48,INDEX($D$19:$M$19,$B48),0) -> 161.74987 | J48: =IF(7<=$B48,-'Roll-Up Model'!J63+'Roll-Up Model'!J102,0)+IF(7=$B48,INDEX($D$19:$M$19,$B48),0) -> 0 | K48: =IF(8<=$B48,-'Roll-Up Model'!K63+'Roll-Up Model'!K102,0)+IF(8=$B48,INDEX($D$19:$M$19,$B48),0) -> 0 | L48: =IF(9<=$B48,-'Roll-Up Model'!L63+'Roll-Up Model'!L102,0)+IF(9=$B48,INDEX($D$19:$M$19,$B48),0) -> 0 | M48: =IF(10<=$B48,-'Roll-Up Model'!M63+'Roll-Up Model'!M102,0)+IF(10=$B48,INDEX($D$19:$M$19,$B48),0) -> 0 | N48: =IRR(C48:M48,0.25) -> 0.77565444
A49: Route 1 — BX Infra sale | B49: 7 | C49: =IF(0<=$B49,-'Roll-Up Model'!C63+0,0)+IF(0=$B49,INDEX($D$19:$M$19,$B49),0) -> -2.9705 | D49: =IF(1<=$B49,-'Roll-Up Model'!D63+'Roll-Up Model'!D102,0)+IF(1=$B49,INDEX($D$19:$M$19,$B49),0) -> -1.5921938 | E49: =IF(2<=$B49,-'Roll-Up Model'!E63+'Roll-Up Model'!E102,0)+IF(2=$B49,INDEX($D$19:$M$19,$B49),0) -> -2.3879604 | F49: =IF(3<=$B49,-'Roll-Up Model'!F63+'Roll-Up Model'!F102,0)+IF(3=$B49,INDEX($D$19:$M$19,$B49),0) -> -2.0150933 | G49: =IF(4<=$B49,-'Roll-Up Model'!G63+'Roll-Up Model'!G102,0)+IF(4=$B49,INDEX($D$19:$M$19,$B49),0) -> -1.756897 | H49: =IF(5<=$B49,-'Roll-Up Model'!H63+'Roll-Up Model'!H102,0)+IF(5=$B49,INDEX($D$19:$M$19,$B49),0) -> 0.012334957 | I49: =IF(6<=$B49,-'Roll-Up Model'!I63+'Roll-Up Model'!I102,0)+IF(6=$B49,INDEX($D$19:$M$19,$B49),0) -> 3.8255775 | J49: =IF(7<=$B49,-'Roll-Up Model'!J63+'Roll-Up Model'!J102,0)+IF(7=$B49,INDEX($D$19:$M$19,$B49),0) -> 195.46825 | K49: =IF(8<=$B49,-'Roll-Up Model'!K63+'Roll-Up Model'!K102,0)+IF(8=$B49,INDEX($D$19:$M$19,$B49),0) -> 0 | L49: =IF(9<=$B49,-'Roll-Up Model'!L63+'Roll-Up Model'!L102,0)+IF(9=$B49,INDEX($D$19:$M$19,$B49),0) -> 0 | M49: =IF(10<=$B49,-'Roll-Up Model'!M63+'Roll-Up Model'!M102,0)+IF(10=$B49,INDEX($D$19:$M$19,$B49),0) -> 0 | N49: =IRR(C49:M49,0.25) -> 0.67672747
A50: Route 1 — BX Infra sale | B50: 8 | C50: =IF(0<=$B50,-'Roll-Up Model'!C63+0,0)+IF(0=$B50,INDEX($D$19:$M$19,$B50),0) -> -2.9705 | D50: =IF(1<=$B50,-'Roll-Up Model'!D63+'Roll-Up Model'!D102,0)+IF(1=$B50,INDEX($D$19:$M$19,$B50),0) -> -1.5921938 | E50: =IF(2<=$B50,-'Roll-Up Model'!E63+'Roll-Up Model'!E102,0)+IF(2=$B50,INDEX($D$19:$M$19,$B50),0) -> -2.3879604 | F50: =IF(3<=$B50,-'Roll-Up Model'!F63+'Roll-Up Model'!F102,0)+IF(3=$B50,INDEX($D$19:$M$19,$B50),0) -> -2.0150933 | G50: =IF(4<=$B50,-'Roll-Up Model'!G63+'Roll-Up Model'!G102,0)+IF(4=$B50,INDEX($D$19:$M$19,$B50),0) -> -1.756897 | H50: =IF(5<=$B50,-'Roll-Up Model'!H63+'Roll-Up Model'!H102,0)+IF(5=$B50,INDEX($D$19:$M$19,$B50),0) -> 0.012334957 | I50: =IF(6<=$B50,-'Roll-Up Model'!I63+'Roll-Up Model'!I102,0)+IF(6=$B50,INDEX($D$19:$M$19,$B50),0) -> 3.8255775 | J50: =IF(7<=$B50,-'Roll-Up Model'!J63+'Roll-Up Model'!J102,0)+IF(7=$B50,INDEX($D$19:$M$19,$B50),0) -> 5.4497403 | K50: =IF(8<=$B50,-'Roll-Up Model'!K63+'Roll-Up Model'!K102,0)+IF(8=$B50,INDEX($D$19:$M$19,$B50),0) -> 228.52214 | L50: =IF(9<=$B50,-'Roll-Up Model'!L63+'Roll-Up Model'!L102,0)+IF(9=$B50,INDEX($D$19:$M$19,$B50),0) -> 0 | M50: =IF(10<=$B50,-'Roll-Up Model'!M63+'Roll-Up Model'!M102,0)+IF(10=$B50,INDEX($D$19:$M$19,$B50),0) -> 0 | N50: =IRR(C50:M50,0.25) -> 0.60382621
A51: Route 1 — BX Infra sale | B51: 9 | C51: =IF(0<=$B51,-'Roll-Up Model'!C63+0,0)+IF(0=$B51,INDEX($D$19:$M$19,$B51),0) -> -2.9705 | D51: =IF(1<=$B51,-'Roll-Up Model'!D63+'Roll-Up Model'!D102,0)+IF(1=$B51,INDEX($D$19:$M$19,$B51),0) -> -1.5921938 | E51: =IF(2<=$B51,-'Roll-Up Model'!E63+'Roll-Up Model'!E102,0)+IF(2=$B51,INDEX($D$19:$M$19,$B51),0) -> -2.3879604 | F51: =IF(3<=$B51,-'Roll-Up Model'!F63+'Roll-Up Model'!F102,0)+IF(3=$B51,INDEX($D$19:$M$19,$B51),0) -> -2.0150933 | G51: =IF(4<=$B51,-'Roll-Up Model'!G63+'Roll-Up Model'!G102,0)+IF(4=$B51,INDEX($D$19:$M$19,$B51),0) -> -1.756897 | H51: =IF(5<=$B51,-'Roll-Up Model'!H63+'Roll-Up Model'!H102,0)+IF(5=$B51,INDEX($D$19:$M$19,$B51),0) -> 0.012334957 | I51: =IF(6<=$B51,-'Roll-Up Model'!I63+'Roll-Up Model'!I102,0)+IF(6=$B51,INDEX($D$19:$M$19,$B51),0) -> 3.8255775 | J51: =IF(7<=$B51,-'Roll-Up Model'!J63+'Roll-Up Model'!J102,0)+IF(7=$B51,INDEX($D$19:$M$19,$B51),0) -> 5.4497403 | K51: =IF(8<=$B51,-'Roll-Up Model'!K63+'Roll-Up Model'!K102,0)+IF(8=$B51,INDEX($D$19:$M$19,$B51),0) -> 7.5497519 | L51: =IF(9<=$B51,-'Roll-Up Model'!L63+'Roll-Up Model'!L102,0)+IF(9=$B51,INDEX($D$19:$M$19,$B51),0) -> 260.30237 | M51: =IF(10<=$B51,-'Roll-Up Model'!M63+'Roll-Up Model'!M102,0)+IF(10=$B51,INDEX($D$19:$M$19,$B51),0) -> 0 | N51: =IRR(C51:M51,0.25) -> 0.54865387
A52: Route 1 — BX Infra sale | B52: 10 | C52: =IF(0<=$B52,-'Roll-Up Model'!C63+0,0)+IF(0=$B52,INDEX($D$19:$M$19,$B52),0) -> -2.9705 | D52: =IF(1<=$B52,-'Roll-Up Model'!D63+'Roll-Up Model'!D102,0)+IF(1=$B52,INDEX($D$19:$M$19,$B52),0) -> -1.5921938 | E52: =IF(2<=$B52,-'Roll-Up Model'!E63+'Roll-Up Model'!E102,0)+IF(2=$B52,INDEX($D$19:$M$19,$B52),0) -> -2.3879604 | F52: =IF(3<=$B52,-'Roll-Up Model'!F63+'Roll-Up Model'!F102,0)+IF(3=$B52,INDEX($D$19:$M$19,$B52),0) -> -2.0150933 | G52: =IF(4<=$B52,-'Roll-Up Model'!G63+'Roll-Up Model'!G102,0)+IF(4=$B52,INDEX($D$19:$M$19,$B52),0) -> -1.756897 | H52: =IF(5<=$B52,-'Roll-Up Model'!H63+'Roll-Up Model'!H102,0)+IF(5=$B52,INDEX($D$19:$M$19,$B52),0) -> 0.012334957 | I52: =IF(6<=$B52,-'Roll-Up Model'!I63+'Roll-Up Model'!I102,0)+IF(6=$B52,INDEX($D$19:$M$19,$B52),0) -> 3.8255775 | J52: =IF(7<=$B52,-'Roll-Up Model'!J63+'Roll-Up Model'!J102,0)+IF(7=$B52,INDEX($D$19:$M$19,$B52),0) -> 5.4497403 | K52: =IF(8<=$B52,-'Roll-Up Model'!K63+'Roll-Up Model'!K102,0)+IF(8=$B52,INDEX($D$19:$M$19,$B52),0) -> 7.5497519 | L52: =IF(9<=$B52,-'Roll-Up Model'!L63+'Roll-Up Model'!L102,0)+IF(9=$B52,INDEX($D$19:$M$19,$B52),0) -> 10.003672 | M52: =IF(10<=$B52,-'Roll-Up Model'!M63+'Roll-Up Model'!M102,0)+IF(10=$B52,INDEX($D$19:$M$19,$B52),0) -> 285.70233 | N52: =IRR(C52:M52,0.25) -> 0.50374645
A53: Route 2 — Spin/partial to BX | B53: 5 | C53: =IF(0<=$B53,-'Roll-Up Model'!C63+0,0)+IF(0=$B53,INDEX($D$23:$M$23,$B53),0)+IF(0=10,INDEX($D$24:$M$24,$B53),0) -> -2.9705 | D53: =IF(1<=$B53,-'Roll-Up Model'!D63+'Roll-Up Model'!D102,0)+IF(1=$B53,INDEX($D$23:$M$23,$B53),0)+IF(1=10,INDEX($D$24:$M$24,$B53),0) -> -1.5921938 | E53: =IF(2<=$B53,-'Roll-Up Model'!E63+'Roll-Up Model'!E102,0)+IF(2=$B53,INDEX($D$23:$M$23,$B53),0)+IF(2=10,INDEX($D$24:$M$24,$B53),0) -> -2.3879604 | F53: =IF(3<=$B53,-'Roll-Up Model'!F63+'Roll-Up Model'!F102,0)+IF(3=$B53,INDEX($D$23:$M$23,$B53),0)+IF(3=10,INDEX($D$24:$M$24,$B53),0) -> -2.0150933 | G53: =IF(4<=$B53,-'Roll-Up Model'!G63+'Roll-Up Model'!G102,0)+IF(4=$B53,INDEX($D$23:$M$23,$B53),0)+IF(4=10,INDEX($D$24:$M$24,$B53),0) -> -1.756897 | H53: =IF(5<=$B53,-'Roll-Up Model'!H63+'Roll-Up Model'!H102,0)+IF(5=$B53,INDEX($D$23:$M$23,$B53),0)+IF(5=10,INDEX($D$24:$M$24,$B53),0) -> 74.609657 | I53: =IF(6<=$B53,-'Roll-Up Model'!I63+'Roll-Up Model'!I102,0)+IF(6=$B53,INDEX($D$23:$M$23,$B53),0)+IF(6=10,INDEX($D$24:$M$24,$B53),0) -> 0 | J53: =IF(7<=$B53,-'Roll-Up Model'!J63+'Roll-Up Model'!J102,0)+IF(7=$B53,INDEX($D$23:$M$23,$B53),0)+IF(7=10,INDEX($D$24:$M$24,$B53),0) -> 0 | K53: =IF(8<=$B53,-'Roll-Up Model'!K63+'Roll-Up Model'!K102,0)+IF(8=$B53,INDEX($D$23:$M$23,$B53),0)+IF(8=10,INDEX($D$24:$M$24,$B53),0) -> 0 | L53: =IF(9<=$B53,-'Roll-Up Model'!L63+'Roll-Up Model'!L102,0)+IF(9=$B53,INDEX($D$23:$M$23,$B53),0)+IF(9=10,INDEX($D$24:$M$24,$B53),0) -> 0 | M53: =IF(10<=$B53,-'Roll-Up Model'!M63+'Roll-Up Model'!M102,0)+IF(10=$B53,INDEX($D$23:$M$23,$B53),0)+IF(10=10,INDEX($D$24:$M$24,$B53),0) -> 87.64398 | N53: =IRR(C53:M53,0.25) -> 0.72307771
A54: Route 2 — Spin/partial to BX | B54: 6 | C54: =IF(0<=$B54,-'Roll-Up Model'!C63+0,0)+IF(0=$B54,INDEX($D$23:$M$23,$B54),0)+IF(0=10,INDEX($D$24:$M$24,$B54),0) -> -2.9705 | D54: =IF(1<=$B54,-'Roll-Up Model'!D63+'Roll-Up Model'!D102,0)+IF(1=$B54,INDEX($D$23:$M$23,$B54),0)+IF(1=10,INDEX($D$24:$M$24,$B54),0) -> -1.5921938 | E54: =IF(2<=$B54,-'Roll-Up Model'!E63+'Roll-Up Model'!E102,0)+IF(2=$B54,INDEX($D$23:$M$23,$B54),0)+IF(2=10,INDEX($D$24:$M$24,$B54),0) -> -2.3879604 | F54: =IF(3<=$B54,-'Roll-Up Model'!F63+'Roll-Up Model'!F102,0)+IF(3=$B54,INDEX($D$23:$M$23,$B54),0)+IF(3=10,INDEX($D$24:$M$24,$B54),0) -> -2.0150933 | G54: =IF(4<=$B54,-'Roll-Up Model'!G63+'Roll-Up Model'!G102,0)+IF(4=$B54,INDEX($D$23:$M$23,$B54),0)+IF(4=10,INDEX($D$24:$M$24,$B54),0) -> -1.756897 | H54: =IF(5<=$B54,-'Roll-Up Model'!H63+'Roll-Up Model'!H102,0)+IF(5=$B54,INDEX($D$23:$M$23,$B54),0)+IF(5=10,INDEX($D$24:$M$24,$B54),0) -> 0.012334957 | I54: =IF(6<=$B54,-'Roll-Up Model'!I63+'Roll-Up Model'!I102,0)+IF(6=$B54,INDEX($D$23:$M$23,$B54),0)+IF(6=10,INDEX($D$24:$M$24,$B54),0) -> 98.580155 | J54: =IF(7<=$B54,-'Roll-Up Model'!J63+'Roll-Up Model'!J102,0)+IF(7=$B54,INDEX($D$23:$M$23,$B54),0)+IF(7=10,INDEX($D$24:$M$24,$B54),0) -> 0 | K54: =IF(8<=$B54,-'Roll-Up Model'!K63+'Roll-Up Model'!K102,0)+IF(8=$B54,INDEX($D$23:$M$23,$B54),0)+IF(8=10,INDEX($D$24:$M$24,$B54),0) -> 0 | L54: =IF(9<=$B54,-'Roll-Up Model'!L63+'Roll-Up Model'!L102,0)+IF(9=$B54,INDEX($D$23:$M$23,$B54),0)+IF(9=10,INDEX($D$24:$M$24,$B54),0) -> 0 | M54: =IF(10<=$B54,-'Roll-Up Model'!M63+'Roll-Up Model'!M102,0)+IF(10=$B54,INDEX($D$23:$M$23,$B54),0)+IF(10=10,INDEX($D$24:$M$24,$B54),0) -> 99.398775 | N54: =IRR(C54:M54,0.25) -> 0.65282539
A55: Route 2 — Spin/partial to BX | B55: 7 | C55: =IF(0<=$B55,-'Roll-Up Model'!C63+0,0)+IF(0=$B55,INDEX($D$23:$M$23,$B55),0)+IF(0=10,INDEX($D$24:$M$24,$B55),0) -> -2.9705 | D55: =IF(1<=$B55,-'Roll-Up Model'!D63+'Roll-Up Model'!D102,0)+IF(1=$B55,INDEX($D$23:$M$23,$B55),0)+IF(1=10,INDEX($D$24:$M$24,$B55),0) -> -1.5921938 | E55: =IF(2<=$B55,-'Roll-Up Model'!E63+'Roll-Up Model'!E102,0)+IF(2=$B55,INDEX($D$23:$M$23,$B55),0)+IF(2=10,INDEX($D$24:$M$24,$B55),0) -> -2.3879604 | F55: =IF(3<=$B55,-'Roll-Up Model'!F63+'Roll-Up Model'!F102,0)+IF(3=$B55,INDEX($D$23:$M$23,$B55),0)+IF(3=10,INDEX($D$24:$M$24,$B55),0) -> -2.0150933 | G55: =IF(4<=$B55,-'Roll-Up Model'!G63+'Roll-Up Model'!G102,0)+IF(4=$B55,INDEX($D$23:$M$23,$B55),0)+IF(4=10,INDEX($D$24:$M$24,$B55),0) -> -1.756897 | H55: =IF(5<=$B55,-'Roll-Up Model'!H63+'Roll-Up Model'!H102,0)+IF(5=$B55,INDEX($D$23:$M$23,$B55),0)+IF(5=10,INDEX($D$24:$M$24,$B55),0) -> 0.012334957 | I55: =IF(6<=$B55,-'Roll-Up Model'!I63+'Roll-Up Model'!I102,0)+IF(6=$B55,INDEX($D$23:$M$23,$B55),0)+IF(6=10,INDEX($D$24:$M$24,$B55),0) -> 3.8255775 | J55: =IF(7<=$B55,-'Roll-Up Model'!J63+'Roll-Up Model'!J102,0)+IF(7=$B55,INDEX($D$23:$M$23,$B55),0)+IF(7=10,INDEX($D$24:$M$24,$B55),0) -> 119.46084 | K55: =IF(8<=$B55,-'Roll-Up Model'!K63+'Roll-Up Model'!K102,0)+IF(8=$B55,INDEX($D$23:$M$23,$B55),0)+IF(8=10,INDEX($D$24:$M$24,$B55),0) -> 0 | L55: =IF(9<=$B55,-'Roll-Up Model'!L63+'Roll-Up Model'!L102,0)+IF(9=$B55,INDEX($D$23:$M$23,$B55),0)+IF(9=10,INDEX($D$24:$M$24,$B55),0) -> 0 | M55: =IF(10<=$B55,-'Roll-Up Model'!M63+'Roll-Up Model'!M102,0)+IF(10=$B55,INDEX($D$23:$M$23,$B55),0)+IF(10=10,INDEX($D$24:$M$24,$B55),0) -> 106.78493 | N55: =IRR(C55:M55,0.25) -> 0.59966145
A56: Route 2 — Spin/partial to BX | B56: 8 | C56: =IF(0<=$B56,-'Roll-Up Model'!C63+0,0)+IF(0=$B56,INDEX($D$23:$M$23,$B56),0)+IF(0=10,INDEX($D$24:$M$24,$B56),0) -> -2.9705 | D56: =IF(1<=$B56,-'Roll-Up Model'!D63+'Roll-Up Model'!D102,0)+IF(1=$B56,INDEX($D$23:$M$23,$B56),0)+IF(1=10,INDEX($D$24:$M$24,$B56),0) -> -1.5921938 | E56: =IF(2<=$B56,-'Roll-Up Model'!E63+'Roll-Up Model'!E102,0)+IF(2=$B56,INDEX($D$23:$M$23,$B56),0)+IF(2=10,INDEX($D$24:$M$24,$B56),0) -> -2.3879604 | F56: =IF(3<=$B56,-'Roll-Up Model'!F63+'Roll-Up Model'!F102,0)+IF(3=$B56,INDEX($D$23:$M$23,$B56),0)+IF(3=10,INDEX($D$24:$M$24,$B56),0) -> -2.0150933 | G56: =IF(4<=$B56,-'Roll-Up Model'!G63+'Roll-Up Model'!G102,0)+IF(4=$B56,INDEX($D$23:$M$23,$B56),0)+IF(4=10,INDEX($D$24:$M$24,$B56),0) -> -1.756897 | H56: =IF(5<=$B56,-'Roll-Up Model'!H63+'Roll-Up Model'!H102,0)+IF(5=$B56,INDEX($D$23:$M$23,$B56),0)+IF(5=10,INDEX($D$24:$M$24,$B56),0) -> 0.012334957 | I56: =IF(6<=$B56,-'Roll-Up Model'!I63+'Roll-Up Model'!I102,0)+IF(6=$B56,INDEX($D$23:$M$23,$B56),0)+IF(6=10,INDEX($D$24:$M$24,$B56),0) -> 3.8255775 | J56: =IF(7<=$B56,-'Roll-Up Model'!J63+'Roll-Up Model'!J102,0)+IF(7=$B56,INDEX($D$23:$M$23,$B56),0)+IF(7=10,INDEX($D$24:$M$24,$B56),0) -> 5.4497403 | K56: =IF(8<=$B56,-'Roll-Up Model'!K63+'Roll-Up Model'!K102,0)+IF(8=$B56,INDEX($D$23:$M$23,$B56),0)+IF(8=10,INDEX($D$24:$M$24,$B56),0) -> 140.13318 | L56: =IF(9<=$B56,-'Roll-Up Model'!L63+'Roll-Up Model'!L102,0)+IF(9=$B56,INDEX($D$23:$M$23,$B56),0)+IF(9=10,INDEX($D$24:$M$24,$B56),0) -> 0 | M56: =IF(10<=$B56,-'Roll-Up Model'!M63+'Roll-Up Model'!M102,0)+IF(10=$B56,INDEX($D$23:$M$23,$B56),0)+IF(10=10,INDEX($D$24:$M$24,$B56),0) -> 110.8751 | N56: =IRR(C56:M56,0.25) -> 0.56012908
A57: Route 2 — Spin/partial to BX | B57: 9 | C57: =IF(0<=$B57,-'Roll-Up Model'!C63+0,0)+IF(0=$B57,INDEX($D$23:$M$23,$B57),0)+IF(0=10,INDEX($D$24:$M$24,$B57),0) -> -2.9705 | D57: =IF(1<=$B57,-'Roll-Up Model'!D63+'Roll-Up Model'!D102,0)+IF(1=$B57,INDEX($D$23:$M$23,$B57),0)+IF(1=10,INDEX($D$24:$M$24,$B57),0) -> -1.5921938 | E57: =IF(2<=$B57,-'Roll-Up Model'!E63+'Roll-Up Model'!E102,0)+IF(2=$B57,INDEX($D$23:$M$23,$B57),0)+IF(2=10,INDEX($D$24:$M$24,$B57),0) -> -2.3879604 | F57: =IF(3<=$B57,-'Roll-Up Model'!F63+'Roll-Up Model'!F102,0)+IF(3=$B57,INDEX($D$23:$M$23,$B57),0)+IF(3=10,INDEX($D$24:$M$24,$B57),0) -> -2.0150933 | G57: =IF(4<=$B57,-'Roll-Up Model'!G63+'Roll-Up Model'!G102,0)+IF(4=$B57,INDEX($D$23:$M$23,$B57),0)+IF(4=10,INDEX($D$24:$M$24,$B57),0) -> -1.756897 | H57: =IF(5<=$B57,-'Roll-Up Model'!H63+'Roll-Up Model'!H102,0)+IF(5=$B57,INDEX($D$23:$M$23,$B57),0)+IF(5=10,INDEX($D$24:$M$24,$B57),0) -> 0.012334957 | I57: =IF(6<=$B57,-'Roll-Up Model'!I63+'Roll-Up Model'!I102,0)+IF(6=$B57,INDEX($D$23:$M$23,$B57),0)+IF(6=10,INDEX($D$24:$M$24,$B57),0) -> 3.8255775 | J57: =IF(7<=$B57,-'Roll-Up Model'!J63+'Roll-Up Model'!J102,0)+IF(7=$B57,INDEX($D$23:$M$23,$B57),0)+IF(7=10,INDEX($D$24:$M$24,$B57),0) -> 5.4497403 | K57: =IF(8<=$B57,-'Roll-Up Model'!K63+'Roll-Up Model'!K102,0)+IF(8=$B57,INDEX($D$23:$M$23,$B57),0)+IF(8=10,INDEX($D$24:$M$24,$B57),0) -> 7.5497519 | L57: =IF(9<=$B57,-'Roll-Up Model'!L63+'Roll-Up Model'!L102,0)+IF(9=$B57,INDEX($D$23:$M$23,$B57),0)+IF(9=10,INDEX($D$24:$M$24,$B57),0) -> 160.18289 | M57: =IF(10<=$B57,-'Roll-Up Model'!M63+'Roll-Up Model'!M102,0)+IF(10=$B57,INDEX($D$23:$M$23,$B57),0)+IF(10=10,INDEX($D$24:$M$24,$B57),0) -> 112.13382 | N57: =IRR(C57:M57,0.25) -> 0.52987177
A58: Route 2 — Spin/partial to BX | B58: 10 | C58: =IF(0<=$B58,-'Roll-Up Model'!C63+0,0)+IF(0=$B58,INDEX($D$23:$M$23,$B58),0)+IF(0=10,INDEX($D$24:$M$24,$B58),0) -> -2.9705 | D58: =IF(1<=$B58,-'Roll-Up Model'!D63+'Roll-Up Model'!D102,0)+IF(1=$B58,INDEX($D$23:$M$23,$B58),0)+IF(1=10,INDEX($D$24:$M$24,$B58),0) -> -1.5921938 | E58: =IF(2<=$B58,-'Roll-Up Model'!E63+'Roll-Up Model'!E102,0)+IF(2=$B58,INDEX($D$23:$M$23,$B58),0)+IF(2=10,INDEX($D$24:$M$24,$B58),0) -> -2.3879604 | F58: =IF(3<=$B58,-'Roll-Up Model'!F63+'Roll-Up Model'!F102,0)+IF(3=$B58,INDEX($D$23:$M$23,$B58),0)+IF(3=10,INDEX($D$24:$M$24,$B58),0) -> -2.0150933 | G58: =IF(4<=$B58,-'Roll-Up Model'!G63+'Roll-Up Model'!G102,0)+IF(4=$B58,INDEX($D$23:$M$23,$B58),0)+IF(4=10,INDEX($D$24:$M$24,$B58),0) -> -1.756897 | H58: =IF(5<=$B58,-'Roll-Up Model'!H63+'Roll-Up Model'!H102,0)+IF(5=$B58,INDEX($D$23:$M$23,$B58),0)+IF(5=10,INDEX($D$24:$M$24,$B58),0) -> 0.012334957 | I58: =IF(6<=$B58,-'Roll-Up Model'!I63+'Roll-Up Model'!I102,0)+IF(6=$B58,INDEX($D$23:$M$23,$B58),0)+IF(6=10,INDEX($D$24:$M$24,$B58),0) -> 3.8255775 | J58: =IF(7<=$B58,-'Roll-Up Model'!J63+'Roll-Up Model'!J102,0)+IF(7=$B58,INDEX($D$23:$M$23,$B58),0)+IF(7=10,INDEX($D$24:$M$24,$B58),0) -> 5.4497403 | K58: =IF(8<=$B58,-'Roll-Up Model'!K63+'Roll-Up Model'!K102,0)+IF(8=$B58,INDEX($D$23:$M$23,$B58),0)+IF(8=10,INDEX($D$24:$M$24,$B58),0) -> 7.5497519 | L58: =IF(9<=$B58,-'Roll-Up Model'!L63+'Roll-Up Model'!L102,0)+IF(9=$B58,INDEX($D$23:$M$23,$B58),0)+IF(9=10,INDEX($D$24:$M$24,$B58),0) -> 10.003672 | M58: =IF(10<=$B58,-'Roll-Up Model'!M63+'Roll-Up Model'!M102,0)+IF(10=$B58,INDEX($D$23:$M$23,$B58),0)+IF(10=10,INDEX($D$24:$M$24,$B58),0) -> 285.70233 | N58: =IRR(C58:M58,0.25) -> 0.50374645
A59: Route 3 — MarineMax | B59: 5 | C59: =IF(0<=$B59,-'Roll-Up Model'!C63+0,0)+IF(0=$B59,INDEX($D$33:$M$33,$B59),0) -> -2.9705 | D59: =IF(1<=$B59,-'Roll-Up Model'!D63+'Roll-Up Model'!D102,0)+IF(1=$B59,INDEX($D$33:$M$33,$B59),0) -> -1.5921938 | E59: =IF(2<=$B59,-'Roll-Up Model'!E63+'Roll-Up Model'!E102,0)+IF(2=$B59,INDEX($D$33:$M$33,$B59),0) -> -2.3879604 | F59: =IF(3<=$B59,-'Roll-Up Model'!F63+'Roll-Up Model'!F102,0)+IF(3=$B59,INDEX($D$33:$M$33,$B59),0) -> -2.0150933 | G59: =IF(4<=$B59,-'Roll-Up Model'!G63+'Roll-Up Model'!G102,0)+IF(4=$B59,INDEX($D$33:$M$33,$B59),0) -> -1.756897 | H59: =IF(5<=$B59,-'Roll-Up Model'!H63+'Roll-Up Model'!H102,0)+IF(5=$B59,INDEX($D$33:$M$33,$B59),0) -> 86.5171 | I59: =IF(6<=$B59,-'Roll-Up Model'!I63+'Roll-Up Model'!I102,0)+IF(6=$B59,INDEX($D$33:$M$33,$B59),0) -> 0 | J59: =IF(7<=$B59,-'Roll-Up Model'!J63+'Roll-Up Model'!J102,0)+IF(7=$B59,INDEX($D$33:$M$33,$B59),0) -> 0 | K59: =IF(8<=$B59,-'Roll-Up Model'!K63+'Roll-Up Model'!K102,0)+IF(8=$B59,INDEX($D$33:$M$33,$B59),0) -> 0 | L59: =IF(9<=$B59,-'Roll-Up Model'!L63+'Roll-Up Model'!L102,0)+IF(9=$B59,INDEX($D$33:$M$33,$B59),0) -> 0 | M59: =IF(10<=$B59,-'Roll-Up Model'!M63+'Roll-Up Model'!M102,0)+IF(10=$B59,INDEX($D$33:$M$33,$B59),0) -> 0 | N59: =IRR(C59:M59,0.25) -> 0.75383108
A60: Route 3 — MarineMax | B60: 6 | C60: =IF(0<=$B60,-'Roll-Up Model'!C63+0,0)+IF(0=$B60,INDEX($D$33:$M$33,$B60),0) -> -2.9705 | D60: =IF(1<=$B60,-'Roll-Up Model'!D63+'Roll-Up Model'!D102,0)+IF(1=$B60,INDEX($D$33:$M$33,$B60),0) -> -1.5921938 | E60: =IF(2<=$B60,-'Roll-Up Model'!E63+'Roll-Up Model'!E102,0)+IF(2=$B60,INDEX($D$33:$M$33,$B60),0) -> -2.3879604 | F60: =IF(3<=$B60,-'Roll-Up Model'!F63+'Roll-Up Model'!F102,0)+IF(3=$B60,INDEX($D$33:$M$33,$B60),0) -> -2.0150933 | G60: =IF(4<=$B60,-'Roll-Up Model'!G63+'Roll-Up Model'!G102,0)+IF(4=$B60,INDEX($D$33:$M$33,$B60),0) -> -1.756897 | H60: =IF(5<=$B60,-'Roll-Up Model'!H63+'Roll-Up Model'!H102,0)+IF(5=$B60,INDEX($D$33:$M$33,$B60),0) -> 0.012334957 | I60: =IF(6<=$B60,-'Roll-Up Model'!I63+'Roll-Up Model'!I102,0)+IF(6=$B60,INDEX($D$33:$M$33,$B60),0) -> 113.11523 | J60: =IF(7<=$B60,-'Roll-Up Model'!J63+'Roll-Up Model'!J102,0)+IF(7=$B60,INDEX($D$33:$M$33,$B60),0) -> 0 | K60: =IF(8<=$B60,-'Roll-Up Model'!K63+'Roll-Up Model'!K102,0)+IF(8=$B60,INDEX($D$33:$M$33,$B60),0) -> 0 | L60: =IF(9<=$B60,-'Roll-Up Model'!L63+'Roll-Up Model'!L102,0)+IF(9=$B60,INDEX($D$33:$M$33,$B60),0) -> 0 | M60: =IF(10<=$B60,-'Roll-Up Model'!M63+'Roll-Up Model'!M102,0)+IF(10=$B60,INDEX($D$33:$M$33,$B60),0) -> 0 | N60: =IRR(C60:M60,0.25) -> 0.65633689
A61: Route 3 — MarineMax | B61: 7 | C61: =IF(0<=$B61,-'Roll-Up Model'!C63+0,0)+IF(0=$B61,INDEX($D$33:$M$33,$B61),0) -> -2.9705 | D61: =IF(1<=$B61,-'Roll-Up Model'!D63+'Roll-Up Model'!D102,0)+IF(1=$B61,INDEX($D$33:$M$33,$B61),0) -> -1.5921938 | E61: =IF(2<=$B61,-'Roll-Up Model'!E63+'Roll-Up Model'!E102,0)+IF(2=$B61,INDEX($D$33:$M$33,$B61),0) -> -2.3879604 | F61: =IF(3<=$B61,-'Roll-Up Model'!F63+'Roll-Up Model'!F102,0)+IF(3=$B61,INDEX($D$33:$M$33,$B61),0) -> -2.0150933 | G61: =IF(4<=$B61,-'Roll-Up Model'!G63+'Roll-Up Model'!G102,0)+IF(4=$B61,INDEX($D$33:$M$33,$B61),0) -> -1.756897 | H61: =IF(5<=$B61,-'Roll-Up Model'!H63+'Roll-Up Model'!H102,0)+IF(5=$B61,INDEX($D$33:$M$33,$B61),0) -> 0.012334957 | I61: =IF(6<=$B61,-'Roll-Up Model'!I63+'Roll-Up Model'!I102,0)+IF(6=$B61,INDEX($D$33:$M$33,$B61),0) -> 3.8255775 | J61: =IF(7<=$B61,-'Roll-Up Model'!J63+'Roll-Up Model'!J102,0)+IF(7=$B61,INDEX($D$33:$M$33,$B61),0) -> 135.92781 | K61: =IF(8<=$B61,-'Roll-Up Model'!K63+'Roll-Up Model'!K102,0)+IF(8=$B61,INDEX($D$33:$M$33,$B61),0) -> 0 | L61: =IF(9<=$B61,-'Roll-Up Model'!L63+'Roll-Up Model'!L102,0)+IF(9=$B61,INDEX($D$33:$M$33,$B61),0) -> 0 | M61: =IF(10<=$B61,-'Roll-Up Model'!M63+'Roll-Up Model'!M102,0)+IF(10=$B61,INDEX($D$33:$M$33,$B61),0) -> 0 | N61: =IRR(C61:M61,0.25) -> 0.58226755
A62: Route 3 — MarineMax | B62: 8 | C62: =IF(0<=$B62,-'Roll-Up Model'!C63+0,0)+IF(0=$B62,INDEX($D$33:$M$33,$B62),0) -> -2.9705 | D62: =IF(1<=$B62,-'Roll-Up Model'!D63+'Roll-Up Model'!D102,0)+IF(1=$B62,INDEX($D$33:$M$33,$B62),0) -> -1.5921938 | E62: =IF(2<=$B62,-'Roll-Up Model'!E63+'Roll-Up Model'!E102,0)+IF(2=$B62,INDEX($D$33:$M$33,$B62),0) -> -2.3879604 | F62: =IF(3<=$B62,-'Roll-Up Model'!F63+'Roll-Up Model'!F102,0)+IF(3=$B62,INDEX($D$33:$M$33,$B62),0) -> -2.0150933 | G62: =IF(4<=$B62,-'Roll-Up Model'!G63+'Roll-Up Model'!G102,0)+IF(4=$B62,INDEX($D$33:$M$33,$B62),0) -> -1.756897 | H62: =IF(5<=$B62,-'Roll-Up Model'!H63+'Roll-Up Model'!H102,0)+IF(5=$B62,INDEX($D$33:$M$33,$B62),0) -> 0.012334957 | I62: =IF(6<=$B62,-'Roll-Up Model'!I63+'Roll-Up Model'!I102,0)+IF(6=$B62,INDEX($D$33:$M$33,$B62),0) -> 3.8255775 | J62: =IF(7<=$B62,-'Roll-Up Model'!J63+'Roll-Up Model'!J102,0)+IF(7=$B62,INDEX($D$33:$M$33,$B62),0) -> 5.4497403 | K62: =IF(8<=$B62,-'Roll-Up Model'!K63+'Roll-Up Model'!K102,0)+IF(8=$B62,INDEX($D$33:$M$33,$B62),0) -> 159.30193 | L62: =IF(9<=$B62,-'Roll-Up Model'!L63+'Roll-Up Model'!L102,0)+IF(9=$B62,INDEX($D$33:$M$33,$B62),0) -> 0 | M62: =IF(10<=$B62,-'Roll-Up Model'!M63+'Roll-Up Model'!M102,0)+IF(10=$B62,INDEX($D$33:$M$33,$B62),0) -> 0 | N62: =IRR(C62:M62,0.25) -> 0.52878206
A63: Route 3 — MarineMax | B63: 9 | C63: =IF(0<=$B63,-'Roll-Up Model'!C63+0,0)+IF(0=$B63,INDEX($D$33:$M$33,$B63),0) -> -2.9705 | D63: =IF(1<=$B63,-'Roll-Up Model'!D63+'Roll-Up Model'!D102,0)+IF(1=$B63,INDEX($D$33:$M$33,$B63),0) -> -1.5921938 | E63: =IF(2<=$B63,-'Roll-Up Model'!E63+'Roll-Up Model'!E102,0)+IF(2=$B63,INDEX($D$33:$M$33,$B63),0) -> -2.3879604 | F63: =IF(3<=$B63,-'Roll-Up Model'!F63+'Roll-Up Model'!F102,0)+IF(3=$B63,INDEX($D$33:$M$33,$B63),0) -> -2.0150933 | G63: =IF(4<=$B63,-'Roll-Up Model'!G63+'Roll-Up Model'!G102,0)+IF(4=$B63,INDEX($D$33:$M$33,$B63),0) -> -1.756897 | H63: =IF(5<=$B63,-'Roll-Up Model'!H63+'Roll-Up Model'!H102,0)+IF(5=$B63,INDEX($D$33:$M$33,$B63),0) -> 0.012334957 | I63: =IF(6<=$B63,-'Roll-Up Model'!I63+'Roll-Up Model'!I102,0)+IF(6=$B63,INDEX($D$33:$M$33,$B63),0) -> 3.8255775 | J63: =IF(7<=$B63,-'Roll-Up Model'!J63+'Roll-Up Model'!J102,0)+IF(7=$B63,INDEX($D$33:$M$33,$B63),0) -> 5.4497403 | K63: =IF(8<=$B63,-'Roll-Up Model'!K63+'Roll-Up Model'!K102,0)+IF(8=$B63,INDEX($D$33:$M$33,$B63),0) -> 7.5497519 | L63: =IF(9<=$B63,-'Roll-Up Model'!L63+'Roll-Up Model'!L102,0)+IF(9=$B63,INDEX($D$33:$M$33,$B63),0) -> 182.41328 | M63: =IF(10<=$B63,-'Roll-Up Model'!M63+'Roll-Up Model'!M102,0)+IF(10=$B63,INDEX($D$33:$M$33,$B63),0) -> 0 | N63: =IRR(C63:M63,0.25) -> 0.48855717
A64: Route 3 — MarineMax | B64: 10 | C64: =IF(0<=$B64,-'Roll-Up Model'!C63+0,0)+IF(0=$B64,INDEX($D$33:$M$33,$B64),0) -> -2.9705 | D64: =IF(1<=$B64,-'Roll-Up Model'!D63+'Roll-Up Model'!D102,0)+IF(1=$B64,INDEX($D$33:$M$33,$B64),0) -> -1.5921938 | E64: =IF(2<=$B64,-'Roll-Up Model'!E63+'Roll-Up Model'!E102,0)+IF(2=$B64,INDEX($D$33:$M$33,$B64),0) -> -2.3879604 | F64: =IF(3<=$B64,-'Roll-Up Model'!F63+'Roll-Up Model'!F102,0)+IF(3=$B64,INDEX($D$33:$M$33,$B64),0) -> -2.0150933 | G64: =IF(4<=$B64,-'Roll-Up Model'!G63+'Roll-Up Model'!G102,0)+IF(4=$B64,INDEX($D$33:$M$33,$B64),0) -> -1.756897 | H64: =IF(5<=$B64,-'Roll-Up Model'!H63+'Roll-Up Model'!H102,0)+IF(5=$B64,INDEX($D$33:$M$33,$B64),0) -> 0.012334957 | I64: =IF(6<=$B64,-'Roll-Up Model'!I63+'Roll-Up Model'!I102,0)+IF(6=$B64,INDEX($D$33:$M$33,$B64),0) -> 3.8255775 | J64: =IF(7<=$B64,-'Roll-Up Model'!J63+'Roll-Up Model'!J102,0)+IF(7=$B64,INDEX($D$33:$M$33,$B64),0) -> 5.4497403 | K64: =IF(8<=$B64,-'Roll-Up Model'!K63+'Roll-Up Model'!K102,0)+IF(8=$B64,INDEX($D$33:$M$33,$B64),0) -> 7.5497519 | L64: =IF(9<=$B64,-'Roll-Up Model'!L63+'Roll-Up Model'!L102,0)+IF(9=$B64,INDEX($D$33:$M$33,$B64),0) -> 10.003672 | M64: =IF(10<=$B64,-'Roll-Up Model'!M63+'Roll-Up Model'!M102,0)+IF(10=$B64,INDEX($D$33:$M$33,$B64),0) -> 201.25877 | N64: =IRR(C64:M64,0.25) -> 0.4553353
A65: Route 4 — Sponsor | B65: 5 | C65: =IF(0<=$B65,-'Roll-Up Model'!C63+0,0)+IF(0=$B65,INDEX($D$41:$M$41,$B65),0) -> -2.9705 | D65: =IF(1<=$B65,-'Roll-Up Model'!D63+'Roll-Up Model'!D102,0)+IF(1=$B65,INDEX($D$41:$M$41,$B65),0) -> -1.5921938 | E65: =IF(2<=$B65,-'Roll-Up Model'!E63+'Roll-Up Model'!E102,0)+IF(2=$B65,INDEX($D$41:$M$41,$B65),0) -> -2.3879604 | F65: =IF(3<=$B65,-'Roll-Up Model'!F63+'Roll-Up Model'!F102,0)+IF(3=$B65,INDEX($D$41:$M$41,$B65),0) -> -2.0150933 | G65: =IF(4<=$B65,-'Roll-Up Model'!G63+'Roll-Up Model'!G102,0)+IF(4=$B65,INDEX($D$41:$M$41,$B65),0) -> -1.756897 | H65: =IF(5<=$B65,-'Roll-Up Model'!H63+'Roll-Up Model'!H102,0)+IF(5=$B65,INDEX($D$41:$M$41,$B65),0) -> 91.118059 | I65: =IF(6<=$B65,-'Roll-Up Model'!I63+'Roll-Up Model'!I102,0)+IF(6=$B65,INDEX($D$41:$M$41,$B65),0) -> 0 | J65: =IF(7<=$B65,-'Roll-Up Model'!J63+'Roll-Up Model'!J102,0)+IF(7=$B65,INDEX($D$41:$M$41,$B65),0) -> 0 | K65: =IF(8<=$B65,-'Roll-Up Model'!K63+'Roll-Up Model'!K102,0)+IF(8=$B65,INDEX($D$41:$M$41,$B65),0) -> 0 | L65: =IF(9<=$B65,-'Roll-Up Model'!L63+'Roll-Up Model'!L102,0)+IF(9=$B65,INDEX($D$41:$M$41,$B65),0) -> 0 | M65: =IF(10<=$B65,-'Roll-Up Model'!M63+'Roll-Up Model'!M102,0)+IF(10=$B65,INDEX($D$41:$M$41,$B65),0) -> 0 | N65: =IRR(C65:M65,0.25) -> 0.77571319
A66: Route 4 — Sponsor | B66: 6 | C66: =IF(0<=$B66,-'Roll-Up Model'!C63+0,0)+IF(0=$B66,INDEX($D$41:$M$41,$B66),0) -> -2.9705 | D66: =IF(1<=$B66,-'Roll-Up Model'!D63+'Roll-Up Model'!D102,0)+IF(1=$B66,INDEX($D$41:$M$41,$B66),0) -> -1.5921938 | E66: =IF(2<=$B66,-'Roll-Up Model'!E63+'Roll-Up Model'!E102,0)+IF(2=$B66,INDEX($D$41:$M$41,$B66),0) -> -2.3879604 | F66: =IF(3<=$B66,-'Roll-Up Model'!F63+'Roll-Up Model'!F102,0)+IF(3=$B66,INDEX($D$41:$M$41,$B66),0) -> -2.0150933 | G66: =IF(4<=$B66,-'Roll-Up Model'!G63+'Roll-Up Model'!G102,0)+IF(4=$B66,INDEX($D$41:$M$41,$B66),0) -> -1.756897 | H66: =IF(5<=$B66,-'Roll-Up Model'!H63+'Roll-Up Model'!H102,0)+IF(5=$B66,INDEX($D$41:$M$41,$B66),0) -> 0.012334957 | I66: =IF(6<=$B66,-'Roll-Up Model'!I63+'Roll-Up Model'!I102,0)+IF(6=$B66,INDEX($D$41:$M$41,$B66),0) -> 119.48819 | J66: =IF(7<=$B66,-'Roll-Up Model'!J63+'Roll-Up Model'!J102,0)+IF(7=$B66,INDEX($D$41:$M$41,$B66),0) -> 0 | K66: =IF(8<=$B66,-'Roll-Up Model'!K63+'Roll-Up Model'!K102,0)+IF(8=$B66,INDEX($D$41:$M$41,$B66),0) -> 0 | L66: =IF(9<=$B66,-'Roll-Up Model'!L63+'Roll-Up Model'!L102,0)+IF(9=$B66,INDEX($D$41:$M$41,$B66),0) -> 0 | M66: =IF(10<=$B66,-'Roll-Up Model'!M63+'Roll-Up Model'!M102,0)+IF(10=$B66,INDEX($D$41:$M$41,$B66),0) -> 0 | N66: =IRR(C66:M66,0.25) -> 0.67422739
A67: Route 4 — Sponsor | B67: 7 | C67: =IF(0<=$B67,-'Roll-Up Model'!C63+0,0)+IF(0=$B67,INDEX($D$41:$M$41,$B67),0) -> -2.9705 | D67: =IF(1<=$B67,-'Roll-Up Model'!D63+'Roll-Up Model'!D102,0)+IF(1=$B67,INDEX($D$41:$M$41,$B67),0) -> -1.5921938 | E67: =IF(2<=$B67,-'Roll-Up Model'!E63+'Roll-Up Model'!E102,0)+IF(2=$B67,INDEX($D$41:$M$41,$B67),0) -> -2.3879604 | F67: =IF(3<=$B67,-'Roll-Up Model'!F63+'Roll-Up Model'!F102,0)+IF(3=$B67,INDEX($D$41:$M$41,$B67),0) -> -2.0150933 | G67: =IF(4<=$B67,-'Roll-Up Model'!G63+'Roll-Up Model'!G102,0)+IF(4=$B67,INDEX($D$41:$M$41,$B67),0) -> -1.756897 | H67: =IF(5<=$B67,-'Roll-Up Model'!H63+'Roll-Up Model'!H102,0)+IF(5=$B67,INDEX($D$41:$M$41,$B67),0) -> 0.012334957 | I67: =IF(6<=$B67,-'Roll-Up Model'!I63+'Roll-Up Model'!I102,0)+IF(6=$B67,INDEX($D$41:$M$41,$B67),0) -> 3.8255775 | J67: =IF(7<=$B67,-'Roll-Up Model'!J63+'Roll-Up Model'!J102,0)+IF(7=$B67,INDEX($D$41:$M$41,$B67),0) -> 143.91672 | K67: =IF(8<=$B67,-'Roll-Up Model'!K63+'Roll-Up Model'!K102,0)+IF(8=$B67,INDEX($D$41:$M$41,$B67),0) -> 0 | L67: =IF(9<=$B67,-'Roll-Up Model'!L63+'Roll-Up Model'!L102,0)+IF(9=$B67,INDEX($D$41:$M$41,$B67),0) -> 0 | M67: =IF(10<=$B67,-'Roll-Up Model'!M63+'Roll-Up Model'!M102,0)+IF(10=$B67,INDEX($D$41:$M$41,$B67),0) -> 0 | N67: =IRR(C67:M67,0.25) -> 0.5967823
A68: Route 4 — Sponsor | B68: 8 | C68: =IF(0<=$B68,-'Roll-Up Model'!C63+0,0)+IF(0=$B68,INDEX($D$41:$M$41,$B68),0) -> -2.9705 | D68: =IF(1<=$B68,-'Roll-Up Model'!D63+'Roll-Up Model'!D102,0)+IF(1=$B68,INDEX($D$41:$M$41,$B68),0) -> -1.5921938 | E68: =IF(2<=$B68,-'Roll-Up Model'!E63+'Roll-Up Model'!E102,0)+IF(2=$B68,INDEX($D$41:$M$41,$B68),0) -> -2.3879604 | F68: =IF(3<=$B68,-'Roll-Up Model'!F63+'Roll-Up Model'!F102,0)+IF(3=$B68,INDEX($D$41:$M$41,$B68),0) -> -2.0150933 | G68: =IF(4<=$B68,-'Roll-Up Model'!G63+'Roll-Up Model'!G102,0)+IF(4=$B68,INDEX($D$41:$M$41,$B68),0) -> -1.756897 | H68: =IF(5<=$B68,-'Roll-Up Model'!H63+'Roll-Up Model'!H102,0)+IF(5=$B68,INDEX($D$41:$M$41,$B68),0) -> 0.012334957 | I68: =IF(6<=$B68,-'Roll-Up Model'!I63+'Roll-Up Model'!I102,0)+IF(6=$B68,INDEX($D$41:$M$41,$B68),0) -> 3.8255775 | J68: =IF(7<=$B68,-'Roll-Up Model'!J63+'Roll-Up Model'!J102,0)+IF(7=$B68,INDEX($D$41:$M$41,$B68),0) -> 5.4497403 | K68: =IF(8<=$B68,-'Roll-Up Model'!K63+'Roll-Up Model'!K102,0)+IF(8=$B68,INDEX($D$41:$M$41,$B68),0) -> 169.57124 | L68: =IF(9<=$B68,-'Roll-Up Model'!L63+'Roll-Up Model'!L102,0)+IF(9=$B68,INDEX($D$41:$M$41,$B68),0) -> 0 | M68: =IF(10<=$B68,-'Roll-Up Model'!M63+'Roll-Up Model'!M102,0)+IF(10=$B68,INDEX($D$41:$M$41,$B68),0) -> 0 | N68: =IRR(C68:M68,0.25) -> 0.5414659
A69: Route 4 — Sponsor | B69: 9 | C69: =IF(0<=$B69,-'Roll-Up Model'!C63+0,0)+IF(0=$B69,INDEX($D$41:$M$41,$B69),0) -> -2.9705 | D69: =IF(1<=$B69,-'Roll-Up Model'!D63+'Roll-Up Model'!D102,0)+IF(1=$B69,INDEX($D$41:$M$41,$B69),0) -> -1.5921938 | E69: =IF(2<=$B69,-'Roll-Up Model'!E63+'Roll-Up Model'!E102,0)+IF(2=$B69,INDEX($D$41:$M$41,$B69),0) -> -2.3879604 | F69: =IF(3<=$B69,-'Roll-Up Model'!F63+'Roll-Up Model'!F102,0)+IF(3=$B69,INDEX($D$41:$M$41,$B69),0) -> -2.0150933 | G69: =IF(4<=$B69,-'Roll-Up Model'!G63+'Roll-Up Model'!G102,0)+IF(4=$B69,INDEX($D$41:$M$41,$B69),0) -> -1.756897 | H69: =IF(5<=$B69,-'Roll-Up Model'!H63+'Roll-Up Model'!H102,0)+IF(5=$B69,INDEX($D$41:$M$41,$B69),0) -> 0.012334957 | I69: =IF(6<=$B69,-'Roll-Up Model'!I63+'Roll-Up Model'!I102,0)+IF(6=$B69,INDEX($D$41:$M$41,$B69),0) -> 3.8255775 | J69: =IF(7<=$B69,-'Roll-Up Model'!J63+'Roll-Up Model'!J102,0)+IF(7=$B69,INDEX($D$41:$M$41,$B69),0) -> 5.4497403 | K69: =IF(8<=$B69,-'Roll-Up Model'!K63+'Roll-Up Model'!K102,0)+IF(8=$B69,INDEX($D$41:$M$41,$B69),0) -> 7.5497519 | L69: =IF(9<=$B69,-'Roll-Up Model'!L63+'Roll-Up Model'!L102,0)+IF(9=$B69,INDEX($D$41:$M$41,$B69),0) -> 194.80095 | M69: =IF(10<=$B69,-'Roll-Up Model'!M63+'Roll-Up Model'!M102,0)+IF(10=$B69,INDEX($D$41:$M$41,$B69),0) -> 0 | N69: =IRR(C69:M69,0.25) -> 0.49937504
A70: Route 4 — Sponsor | B70: 10 | C70: =IF(0<=$B70,-'Roll-Up Model'!C63+0,0)+IF(0=$B70,INDEX($D$41:$M$41,$B70),0) -> -2.9705 | D70: =IF(1<=$B70,-'Roll-Up Model'!D63+'Roll-Up Model'!D102,0)+IF(1=$B70,INDEX($D$41:$M$41,$B70),0) -> -1.5921938 | E70: =IF(2<=$B70,-'Roll-Up Model'!E63+'Roll-Up Model'!E102,0)+IF(2=$B70,INDEX($D$41:$M$41,$B70),0) -> -2.3879604 | F70: =IF(3<=$B70,-'Roll-Up Model'!F63+'Roll-Up Model'!F102,0)+IF(3=$B70,INDEX($D$41:$M$41,$B70),0) -> -2.0150933 | G70: =IF(4<=$B70,-'Roll-Up Model'!G63+'Roll-Up Model'!G102,0)+IF(4=$B70,INDEX($D$41:$M$41,$B70),0) -> -1.756897 | H70: =IF(5<=$B70,-'Roll-Up Model'!H63+'Roll-Up Model'!H102,0)+IF(5=$B70,INDEX($D$41:$M$41,$B70),0) -> 0.012334957 | I70: =IF(6<=$B70,-'Roll-Up Model'!I63+'Roll-Up Model'!I102,0)+IF(6=$B70,INDEX($D$41:$M$41,$B70),0) -> 3.8255775 | J70: =IF(7<=$B70,-'Roll-Up Model'!J63+'Roll-Up Model'!J102,0)+IF(7=$B70,INDEX($D$41:$M$41,$B70),0) -> 5.4497403 | K70: =IF(8<=$B70,-'Roll-Up Model'!K63+'Roll-Up Model'!K102,0)+IF(8=$B70,INDEX($D$41:$M$41,$B70),0) -> 7.5497519 | L70: =IF(9<=$B70,-'Roll-Up Model'!L63+'Roll-Up Model'!L102,0)+IF(9=$B70,INDEX($D$41:$M$41,$B70),0) -> 10.003672 | M70: =IF(10<=$B70,-'Roll-Up Model'!M63+'Roll-Up Model'!M102,0)+IF(10=$B70,INDEX($D$41:$M$41,$B70),0) -> 215.25031 | N70: =IRR(C70:M70,0.25) -> 0.4643514
A72: RETURNS MATRIX — Leviathan gross (before vehicle fees / carry)
A73: Route | C73: MOIC Y5 | D73: MOIC Y7 | E73: MOIC Y10 | F73: IRR Y5 | G73: IRR Y7 | H73: IRR Y10
A74: Route 1 — BX Infra sale | C74: =H20 -> 10.053404 | D74: =J20 -> 13.572234 | E74: =M20 -> 21.121384 | F74: =N47 -> 0.9110678 | G74: =N49 -> 0.67672747 | H74: =N52 -> 0.50374645
A75: Route 2 — Spin/partial to BX | C75: =H26 -> 13.074358 | D75: =J26 -> 15.624069 | E75: =M26 -> 21.121384 | F75: =N53 -> 0.72307771 | G75: =N55 -> 0.59966145 | H75: =N58 -> 0.50374645
A76: Route 3 — MarineMax | C76: =H34 -> 7.0394867 | D76: =J34 -> 9.6028716 | E76: =M34 -> 15.491814 | F76: =N59 -> 0.75383108 | G76: =N61 -> 0.58226755 | H76: =N64 -> 0.4553353
A77: Route 4 — Sponsor | C77: =H42 -> 7.4061024 | D77: =J42 -> 10.135466 | E77: =M42 -> 16.424583 | F77: =N65 -> 0.77571319 | G77: =N67 -> 0.5967823 | H77: =N70 -> 0.4643514
A79: SELECTED CASE — HEADLINE & NET TO LEVIATHAN LPs (route + exit year set on Assumptions)
A80: Exit year | C80: =Assumptions!$B$90 -> 7
A81: Exit route | C81: =Assumptions!$B$91 -> 1
A82: Leviathan equity drawn through exit | C82: =INDEX($C$11:$M$11,C80+1) -> 15
A83: Gross exit proceeds (incl. retained stake for Route 2) | C83: =CHOOSE(C81,INDEX($C$19:$M$19,C80+1),INDEX($C$25:$M$25,C80+1),INDEX($C$33:$M$33,C80+1),INDEX($C$41:$M$41,C80+1)) -> 190.01851
A84: Interim distributions to Leviathan through exit | C84: =INDEX($C$12:$M$12,C80+1) -> 13.565008
A85: TOTAL gross value to Leviathan | C85: =C83+C84 -> 203.58352
A86: Gross MOIC | C86: =IF(C82=0,0,C85/C82) -> 13.572234
A87: Gross IRR | C87: =INDEX($N$47:$N$70,(C81-1)*6+C80-4) -> 0.67672747
A88: Management fees (fee x $15M commitment x years) | C88: =Assumptions!$B$87*Assumptions!$B$23*C80 -> 2.1
A89: Total LP paid-in (drawn + fees) | C89: =C82+C88 -> 17.1
A90: Preferred return hurdle (8% compounded on paid-in) | C90: =C89*((1+Assumptions!$B$88)^C80-1) -> 12.206395
A91: GP carry (20% of profit above pref, no catch-up) | C91: =-Assumptions!$B$89*MAX(0,C85-C89-C90) -> -34.855424
A92: NET VALUE TO LPs (exit + distributions - carry) | C92: =C85+C91 -> 168.72809
A93: Net MOIC (on paid-in) | C93: =IF(C89=0,0,C92/C89) -> 9.8671398
A95: Net LP cash flows (draws + fees out; distributions in; exit net of carry) | C95: =IF(0<=$C$80,-'Roll-Up Model'!C63-IF(0>=1,Assumptions!$B$87*Assumptions!$B$23,0)+0,0)+IF(0=$C$80,$C$92-$C$84,0) -> -2.9705 | D95: =IF(1<=$C$80,-'Roll-Up Model'!D63-IF(1>=1,Assumptions!$B$87*Assumptions!$B$23,0)+'Roll-Up Model'!D102,0)+IF(1=$C$80,$C$92-$C$84,0) -> -1.8921938 | E95: =IF(2<=$C$80,-'Roll-Up Model'!E63-IF(2>=1,Assumptions!$B$87*Assumptions!$B$23,0)+'Roll-Up Model'!E102,0)+IF(2=$C$80,$C$92-$C$84,0) -> -2.6879604 | F95: =IF(3<=$C$80,-'Roll-Up Model'!F63-IF(3>=1,Assumptions!$B$87*Assumptions!$B$23,0)+'Roll-Up Model'!F102,0)+IF(3=$C$80,$C$92-$C$84,0) -> -2.3150933 | G95: =IF(4<=$C$80,-'Roll-Up Model'!G63-IF(4>=1,Assumptions!$B$87*Assumptions!$B$23,0)+'Roll-Up Model'!G102,0)+IF(4=$C$80,$C$92-$C$84,0) -> -2.056897 | H95: =IF(5<=$C$80,-'Roll-Up Model'!H63-IF(5>=1,Assumptions!$B$87*Assumptions!$B$23,0)+'Roll-Up Model'!H102,0)+IF(5=$C$80,$C$92-$C$84,0) -> -0.28766504 | I95: =IF(6<=$C$80,-'Roll-Up Model'!I63-IF(6>=1,Assumptions!$B$87*Assumptions!$B$23,0)+'Roll-Up Model'!I102,0)+IF(6=$C$80,$C$92-$C$84,0) -> 3.5255775 | J95: =IF(7<=$C$80,-'Roll-Up Model'!J63-IF(7>=1,Assumptions!$B$87*Assumptions!$B$23,0)+'Roll-Up Model'!J102,0)+IF(7=$C$80,$C$92-$C$84,0) -> 160.31282 | K95: =IF(8<=$C$80,-'Roll-Up Model'!K63-IF(8>=1,Assumptions!$B$87*Assumptions!$B$23,0)+'Roll-Up Model'!K102,0)+IF(8=$C$80,$C$92-$C$84,0) -> 0 | L95: =IF(9<=$C$80,-'Roll-Up Model'!L63-IF(9>=1,Assumptions!$B$87*Assumptions!$B$23,0)+'Roll-Up Model'!L102,0)+IF(9=$C$80,$C$92-$C$84,0) -> 0 | M95: =IF(10<=$C$80,-'Roll-Up Model'!M63-IF(10>=1,Assumptions!$B$87*Assumptions!$B$23,0)+'Roll-Up Model'!M102,0)+IF(10=$C$80,$C$92-$C$84,0) -> 0
A96: Net IRR to LPs | C96: =IRR(C95:M95,0.2) -> 0.60319562
A97: Route 2 note: the retained stake is valued at Y10 in the gross IRR engine. The net waterfall above books it at the selected exit year (simplification).

Sheet Sensitivity
A1: SENSITIVITIES — ROUTE 1 (BX INFRA SALE)
A2: Live formulas off the model rows; no data tables. Gross to Leviathan.
A4: Table 1 — Gross MOIC: exit year (rows) x infra multiple on contracted cash flows (cols)
A5: Exit year \ Infra multiple | B5: 12 | C5: 14 | D5: 15 | E5: 16 | F5: 18 | G5: 20
A6: 5 | B6: =(MAX(0,(((INDEX('Roll-Up Model'!$C$40:$M$40,$A6+1)*(Assumptions!$B$16*(1-INDEX('Roll-Up Model'!$C$32:$M$32,$A6+1))+B$5*INDEX('Roll-Up Model'!$C$32:$M$32,$A6+1))+INDEX(Synergies!$C$27:$M$27,$A6+1)*B$5*Assumptions!$B$75*Assumptions!$B$18)*(1-Assumptions!$B$74)-INDEX('Roll-Up Model'!$C$85:$M$85,$A6+1))-Assumptions!$B$73*MAX(0,((INDEX('Roll-Up Model'!$C$40:$M$40,$A6+1)*(Assumptions!$B$16*(1-INDEX('Roll-Up Model'!$C$32:$M$32,$A6+1))+B$5*INDEX('Roll-Up Model'!$C$32:$M$32,$A6+1))+INDEX(Synergies!$C$27:$M$27,$A6+1)*B$5*Assumptions!$B$75*Assumptions!$B$18)*(1-Assumptions!$B$74)-INDEX('Roll-Up Model'!$C$85:$M$85,$A6+1))-INDEX('Roll-Up Model'!$C$97:$M$97,$A6+1)))*INDEX('Roll-Up Model'!$C$101:$M$101,$A6+1))+INDEX('Roll-Up Model'!$C$103:$M$103,$A6+1))/INDEX('Roll-Up Model'!$C$94:$M$94,$A6+1) -> 8.9368771 | C6: =(MAX(0,(((INDEX('Roll-Up Model'!$C$40:$M$40,$A6+1)*(Assumptions!$B$16*(1-INDEX('Roll-Up Model'!$C$32:$M$32,$A6+1))+C$5*INDEX('Roll-Up Model'!$C$32:$M$32,$A6+1))+INDEX(Synergies!$C$27:$M$27,$A6+1)*C$5*Assumptions!$B$75*Assumptions!$B$18)*(1-Assumptions!$B$74)-INDEX('Roll-Up Model'!$C$85:$M$85,$A6+1))-Assumptions!$B$73*MAX(0,((INDEX('Roll-Up Model'!$C$40:$M$40,$A6+1)*(Assumptions!$B$16*(1-INDEX('Roll-Up Model'!$C$32:$M$32,$A6+1))+C$5*INDEX('Roll-Up Model'!$C$32:$M$32,$A6+1))+INDEX(Synergies!$C$27:$M$27,$A6+1)*C$5*Assumptions!$B$75*Assumptions!$B$18)*(1-Assumptions!$B$74)-INDEX('Roll-Up Model'!$C$85:$M$85,$A6+1))-INDEX('Roll-Up Model'!$C$97:$M$97,$A6+1)))*INDEX('Roll-Up Model'!$C$101:$M$101,$A6+1))+INDEX('Roll-Up Model'!$C$103:$M$103,$A6+1))/INDEX('Roll-Up Model'!$C$94:$M$94,$A6+1) -> 9.681228 | D6: =(MAX(0,(((INDEX('Roll-Up Model'!$C$40:$M$40,$A6+1)*(Assumptions!$B$16*(1-INDEX('Roll-Up Model'!$C$32:$M$32,$A6+1))+D$5*INDEX('Roll-Up Model'!$C$32:$M$32,$A6+1))+INDEX(Synergies!$C$27:$M$27,$A6+1)*D$5*Assumptions!$B$75*Assumptions!$B$18)*(1-Assumptions!$B$74)-INDEX('Roll-Up Model'!$C$85:$M$85,$A6+1))-Assumptions!$B$73*MAX(0,((INDEX('Roll-Up Model'!$C$40:$M$40,$A6+1)*(Assumptions!$B$16*(1-INDEX('Roll-Up Model'!$C$32:$M$32,$A6+1))+D$5*INDEX('Roll-Up Model'!$C$32:$M$32,$A6+1))+INDEX(Synergies!$C$27:$M$27,$A6+1)*D$5*Assumptions!$B$75*Assumptions!$B$18)*(1-Assumptions!$B$74)-INDEX('Roll-Up Model'!$C$85:$M$85,$A6+1))-INDEX('Roll-Up Model'!$C$97:$M$97,$A6+1)))*INDEX('Roll-Up Model'!$C$101:$M$101,$A6+1))+INDEX('Roll-Up Model'!$C$103:$M$103,$A6+1))/INDEX('Roll-Up Model'!$C$94:$M$94,$A6+1) -> 10.053404 | E6: =(MAX(0,(((INDEX('Roll-Up Model'!$C$40:$M$40,$A6+1)*(Assumptions!$B$16*(1-INDEX('Roll-Up Model'!$C$32:$M$32,$A6+1))+E$5*INDEX('Roll-Up Model'!$C$32:$M$32,$A6+1))+INDEX(Synergies!$C$27:$M$27,$A6+1)*E$5*Assumptions!$B$75*Assumptions!$B$18)*(1-Assumptions!$B$74)-INDEX('Roll-Up Model'!$C$85:$M$85,$A6+1))-Assumptions!$B$73*MAX(0,((INDEX('Roll-Up Model'!$C$40:$M$40,$A6+1)*(Assumptions!$B$16*(1-INDEX('Roll-Up Model'!$C$32:$M$32,$A6+1))+E$5*INDEX('Roll-Up Model'!$C$32:$M$32,$A6+1))+INDEX(Synergies!$C$27:$M$27,$A6+1)*E$5*Assumptions!$B$75*Assumptions!$B$18)*(1-Assumptions!$B$74)-INDEX('Roll-Up Model'!$C$85:$M$85,$A6+1))-INDEX('Roll-Up Model'!$C$97:$M$97,$A6+1)))*INDEX('Roll-Up Model'!$C$101:$M$101,$A6+1))+INDEX('Roll-Up Model'!$C$103:$M$103,$A6+1))/INDEX('Roll-Up Model'!$C$94:$M$94,$A6+1) -> 10.425579 | F6: =(MAX(0,(((INDEX('Roll-Up Model'!$C$40:$M$40,$A6+1)*(Assumptions!$B$16*(1-INDEX('Roll-Up Model'!$C$32:$M$32,$A6+1))+F$5*INDEX('Roll-Up Model'!$C$32:$M$32,$A6+1))+INDEX(Synergies!$C$27:$M$27,$A6+1)*F$5*Assumptions!$B$75*Assumptions!$B$18)*(1-Assumptions!$B$74)-INDEX('Roll-Up Model'!$C$85:$M$85,$A6+1))-Assumptions!$B$73*MAX(0,((INDEX('Roll-Up Model'!$C$40:$M$40,$A6+1)*(Assumptions!$B$16*(1-INDEX('Roll-Up Model'!$C$32:$M$32,$A6+1))+F$5*INDEX('Roll-Up Model'!$C$32:$M$32,$A6+1))+INDEX(Synergies!$C$27:$M$27,$A6+1)*F$5*Assumptions!$B$75*Assumptions!$B$18)*(1-Assumptions!$B$74)-INDEX('Roll-Up Model'!$C$85:$M$85,$A6+1))-INDEX('Roll-Up Model'!$C$97:$M$97,$A6+1)))*INDEX('Roll-Up Model'!$C$101:$M$101,$A6+1))+INDEX('Roll-Up Model'!$C$103:$M$103,$A6+1))/INDEX('Roll-Up Model'!$C$94:$M$94,$A6+1) -> 11.16993 | G6: =(MAX(0,(((INDEX('Roll-Up Model'!$C$40:$M$40,$A6+1)*(Assumptions!$B$16*(1-INDEX('Roll-Up Model'!$C$32:$M$32,$A6+1))+G$5*INDEX('Roll-Up Model'!$C$32:$M$32,$A6+1))+INDEX(Synergies!$C$27:$M$27,$A6+1)*G$5*Assumptions!$B$75*Assumptions!$B$18)*(1-Assumptions!$B$74)-INDEX('Roll-Up Model'!$C$85:$M$85,$A6+1))-Assumptions!$B$73*MAX(0,((INDEX('Roll-Up Model'!$C$40:$M$40,$A6+1)*(Assumptions!$B$16*(1-INDEX('Roll-Up Model'!$C$32:$M$32,$A6+1))+G$5*INDEX('Roll-Up Model'!$C$32:$M$32,$A6+1))+INDEX(Synergies!$C$27:$M$27,$A6+1)*G$5*Assumptions!$B$75*Assumptions!$B$18)*(1-Assumptions!$B$74)-INDEX('Roll-Up Model'!$C$85:$M$85,$A6+1))-INDEX('Roll-Up Model'!$C$97:$M$97,$A6+1)))*INDEX('Roll-Up Model'!$C$101:$M$101,$A6+1))+INDEX('Roll-Up Model'!$C$103:$M$103,$A6+1))/INDEX('Roll-Up Model'!$C$94:$M$94,$A6+1) -> 11.914281
A7: 6 | B7: =(MAX(0,(((INDEX('Roll-Up Model'!$C$40:$M$40,$A7+1)*(Assumptions!$B$16*(1-INDEX('Roll-Up Model'!$C$32:$M$32,$A7+1))+B$5*INDEX('Roll-Up Model'!$C$32:$M$32,$A7+1))+INDEX(Synergies!$C$27:$M$27,$A7+1)*B$5*Assumptions!$B$75*Assumptions!$B$18)*(1-Assumptions!$B$74)-INDEX('Roll-Up Model'!$C$85:$M$85,$A7+1))-Assumptions!$B$73*MAX(0,((INDEX('Roll-Up Model'!$C$40:$M$40,$A7+1)*(Assumptions!$B$16*(1-INDEX('Roll-Up Model'!$C$32:$M$32,$A7+1))+B$5*INDEX('Roll-Up Model'!$C$32:$M$32,$A7+1))+INDEX(Synergies!$C$27:$M$27,$A7+1)*B$5*Assumptions!$B$75*Assumptions!$B$18)*(1-Assumptions!$B$74)-INDEX('Roll-Up Model'!$C$85:$M$85,$A7+1))-INDEX('Roll-Up Model'!$C$97:$M$97,$A7+1)))*INDEX('Roll-Up Model'!$C$101:$M$101,$A7+1))+INDEX('Roll-Up Model'!$C$103:$M$103,$A7+1))/INDEX('Roll-Up Model'!$C$94:$M$94,$A7+1) -> 10.586824 | C7: =(MAX(0,(((INDEX('Roll-Up Model'!$C$40:$M$40,$A7+1)*(Assumptions!$B$16*(1-INDEX('Roll-Up Model'!$C$32:$M$32,$A7+1))+C$5*INDEX('Roll-Up Model'!$C$32:$M$32,$A7+1))+INDEX(Synergies!$C$27:$M$27,$A7+1)*C$5*Assumptions!$B$75*Assumptions!$B$18)*(1-Assumptions!$B$74)-INDEX('Roll-Up Model'!$C$85:$M$85,$A7+1))-Assumptions!$B$73*MAX(0,((INDEX('Roll-Up Model'!$C$40:$M$40,$A7+1)*(Assumptions!$B$16*(1-INDEX('Roll-Up Model'!$C$32:$M$32,$A7+1))+C$5*INDEX('Roll-Up Model'!$C$32:$M$32,$A7+1))+INDEX(Synergies!$C$27:$M$27,$A7+1)*C$5*Assumptions!$B$75*Assumptions!$B$18)*(1-Assumptions!$B$74)-INDEX('Roll-Up Model'!$C$85:$M$85,$A7+1))-INDEX('Roll-Up Model'!$C$97:$M$97,$A7+1)))*INDEX('Roll-Up Model'!$C$101:$M$101,$A7+1))+INDEX('Roll-Up Model'!$C$103:$M$103,$A7+1))/INDEX('Roll-Up Model'!$C$94:$M$94,$A7+1) -> 11.483408 | D7: =(MAX(0,(((INDEX('Roll-Up Model'!$C$40:$M$40,$A7+1)*(Assumptions!$B$16*(1-INDEX('Roll-Up Model'!$C$32:$M$32,$A7+1))+D$5*INDEX('Roll-Up Model'!$C$32:$M$32,$A7+1))+INDEX(Synergies!$C$27:$M$27,$A7+1)*D$5*Assumptions!$B$75*Assumptions!$B$18)*(1-Assumptions!$B$74)-INDEX('Roll-Up Model'!$C$85:$M$85,$A7+1))-Assumptions!$B$73*MAX(0,((INDEX('Roll-Up Model'!$C$40:$M$40,$A7+1)*(Assumptions!$B$16*(1-INDEX('Roll-Up Model'!$C$32:$M$32,$A7+1))+D$5*INDEX('Roll-Up Model'!$C$32:$M$32,$A7+1))+INDEX(Synergies!$C$27:$M$27,$A7+1)*D$5*Assumptions!$B$75*Assumptions!$B$18)*(1-Assumptions!$B$74)-INDEX('Roll-Up Model'!$C$85:$M$85,$A7+1))-INDEX('Roll-Up Model'!$C$97:$M$97,$A7+1)))*INDEX('Roll-Up Model'!$C$101:$M$101,$A7+1))+INDEX('Roll-Up Model'!$C$103:$M$103,$A7+1))/INDEX('Roll-Up Model'!$C$94:$M$94,$A7+1) -> 11.931701 | E7: =(MAX(0,(((INDEX('Roll-Up Model'!$C$40:$M$40,$A7+1)*(Assumptions!$B$16*(1-INDEX('Roll-Up Model'!$C$32:$M$32,$A7+1))+E$5*INDEX('Roll-Up Model'!$C$32:$M$32,$A7+1))+INDEX(Synergies!$C$27:$M$27,$A7+1)*E$5*Assumptions!$B$75*Assumptions!$B$18)*(1-Assumptions!$B$74)-INDEX('Roll-Up Model'!$C$85:$M$85,$A7+1))-Assumptions!$B$73*MAX(0,((INDEX('Roll-Up Model'!$C$40:$M$40,$A7+1)*(Assumptions!$B$16*(1-INDEX('Roll-Up Model'!$C$32:$M$32,$A7+1))+E$5*INDEX('Roll-Up Model'!$C$32:$M$32,$A7+1))+INDEX(Synergies!$C$27:$M$27,$A7+1)*E$5*Assumptions!$B$75*Assumptions!$B$18)*(1-Assumptions!$B$74)-INDEX('Roll-Up Model'!$C$85:$M$85,$A7+1))-INDEX('Roll-Up Model'!$C$97:$M$97,$A7+1)))*INDEX('Roll-Up Model'!$C$101:$M$101,$A7+1))+INDEX('Roll-Up Model'!$C$103:$M$103,$A7+1))/INDEX('Roll-Up Model'!$C$94:$M$94,$A7+1) -> 12.379993 | F7: =(MAX(0,(((INDEX('Roll-Up Model'!$C$40:$M$40,$A7+1)*(Assumptions!$B$16*(1-INDEX('Roll-Up Model'!$C$32:$M$32,$A7+1))+F$5*INDEX('Roll-Up Model'!$C$32:$M$32,$A7+1))+INDEX(Synergies!$C$27:$M$27,$A7+1)*F$5*Assumptions!$B$75*Assumptions!$B$18)*(1-Assumptions!$B$74)-INDEX('Roll-Up Model'!$C$85:$M$85,$A7+1))-Assumptions!$B$73*MAX(0,((INDEX('Roll-Up Model'!$C$40:$M$40,$A7+1)*(Assumptions!$B$16*(1-INDEX('Roll-Up Model'!$C$32:$M$32,$A7+1))+F$5*INDEX('Roll-Up Model'!$C$32:$M$32,$A7+1))+INDEX(Synergies!$C$27:$M$27,$A7+1)*F$5*Assumptions!$B$75*Assumptions!$B$18)*(1-Assumptions!$B$74)-INDEX('Roll-Up Model'!$C$85:$M$85,$A7+1))-INDEX('Roll-Up Model'!$C$97:$M$97,$A7+1)))*INDEX('Roll-Up Model'!$C$101:$M$101,$A7+1))+INDEX('Roll-Up Model'!$C$103:$M$103,$A7+1))/INDEX('Roll-Up Model'!$C$94:$M$94,$A7+1) -> 13.276578 | G7: =(MAX(0,(((INDEX('Roll-Up Model'!$C$40:$M$40,$A7+1)*(Assumptions!$B$16*(1-INDEX('Roll-Up Model'!$C$32:$M$32,$A7+1))+G$5*INDEX('Roll-Up Model'!$C$32:$M$32,$A7+1))+INDEX(Synergies!$C$27:$M$27,$A7+1)*G$5*Assumptions!$B$75*Assumptions!$B$18)*(1-Assumptions!$B$74)-INDEX('Roll-Up Model'!$C$85:$M$85,$A7+1))-Assumptions!$B$73*MAX(0,((INDEX('Roll-Up Model'!$C$40:$M$40,$A7+1)*(Assumptions!$B$16*(1-INDEX('Roll-Up Model'!$C$32:$M$32,$A7+1))+G$5*INDEX('Roll-Up Model'!$C$32:$M$32,$A7+1))+INDEX(Synergies!$C$27:$M$27,$A7+1)*G$5*Assumptions!$B$75*Assumptions!$B$18)*(1-Assumptions!$B$74)-INDEX('Roll-Up Model'!$C$85:$M$85,$A7+1))-INDEX('Roll-Up Model'!$C$97:$M$97,$A7+1)))*INDEX('Roll-Up Model'!$C$101:$M$101,$A7+1))+INDEX('Roll-Up Model'!$C$103:$M$103,$A7+1))/INDEX('Roll-Up Model'!$C$94:$M$94,$A7+1) -> 14.173163
A8: 7 | B8: =(MAX(0,(((INDEX('Roll-Up Model'!$C$40:$M$40,$A8+1)*(Assumptions!$B$16*(1-INDEX('Roll-Up Model'!$C$32:$M$32,$A8+1))+B$5*INDEX('Roll-Up Model'!$C$32:$M$32,$A8+1))+INDEX(Synergies!$C$27:$M$27,$A8+1)*B$5*Assumptions!$B$75*Assumptions!$B$18)*(1-Assumptions!$B$74)-INDEX('Roll-Up Model'!$C$85:$M$85,$A8+1))-Assumptions!$B$73*MAX(0,((INDEX('Roll-Up Model'!$C$40:$M$40,$A8+1)*(Assumptions!$B$16*(1-INDEX('Roll-Up Model'!$C$32:$M$32,$A8+1))+B$5*INDEX('Roll-Up Model'!$C$32:$M$32,$A8+1))+INDEX(Synergies!$C$27:$M$27,$A8+1)*B$5*Assumptions!$B$75*Assumptions!$B$18)*(1-Assumptions!$B$74)-INDEX('Roll-Up Model'!$C$85:$M$85,$A8+1))-INDEX('Roll-Up Model'!$C$97:$M$97,$A8+1)))*INDEX('Roll-Up Model'!$C$101:$M$101,$A8+1))+INDEX('Roll-Up Model'!$C$103:$M$103,$A8+1))/INDEX('Roll-Up Model'!$C$94:$M$94,$A8+1) -> 12.017677 | C8: =(MAX(0,(((INDEX('Roll-Up Model'!$C$40:$M$40,$A8+1)*(Assumptions!$B$16*(1-INDEX('Roll-Up Model'!$C$32:$M$32,$A8+1))+C$5*INDEX('Roll-Up Model'!$C$32:$M$32,$A8+1))+INDEX(Synergies!$C$27:$M$27,$A8+1)*C$5*Assumptions!$B$75*Assumptions!$B$18)*(1-Assumptions!$B$74)-INDEX('Roll-Up Model'!$C$85:$M$85,$A8+1))-Assumptions!$B$73*MAX(0,((INDEX('Roll-Up Model'!$C$40:$M$40,$A8+1)*(Assumptions!$B$16*(1-INDEX('Roll-Up Model'!$C$32:$M$32,$A8+1))+C$5*INDEX('Roll-Up Model'!$C$32:$M$32,$A8+1))+INDEX(Synergies!$C$27:$M$27,$A8+1)*C$5*Assumptions!$B$75*Assumptions!$B$18)*(1-Assumptions!$B$74)-INDEX('Roll-Up Model'!$C$85:$M$85,$A8+1))-INDEX('Roll-Up Model'!$C$97:$M$97,$A8+1)))*INDEX('Roll-Up Model'!$C$101:$M$101,$A8+1))+INDEX('Roll-Up Model'!$C$103:$M$103,$A8+1))/INDEX('Roll-Up Model'!$C$94:$M$94,$A8+1) -> 13.054049 | D8: =(MAX(0,(((INDEX('Roll-Up Model'!$C$40:$M$40,$A8+1)*(Assumptions!$B$16*(1-INDEX('Roll-Up Model'!$C$32:$M$32,$A8+1))+D$5*INDEX('Roll-Up Model'!$C$32:$M$32,$A8+1))+INDEX(Synergies!$C$27:$M$27,$A8+1)*D$5*Assumptions!$B$75*Assumptions!$B$18)*(1-Assumptions!$B$74)-INDEX('Roll-Up Model'!$C$85:$M$85,$A8+1))-Assumptions!$B$73*MAX(0,((INDEX('Roll-Up Model'!$C$40:$M$40,$A8+1)*(Assumptions!$B$16*(1-INDEX('Roll-Up Model'!$C$32:$M$32,$A8+1))+D$5*INDEX('Roll-Up Model'!$C$32:$M$32,$A8+1))+INDEX(Synergies!$C$27:$M$27,$A8+1)*D$5*Assumptions!$B$75*Assumptions!$B$18)*(1-Assumptions!$B$74)-INDEX('Roll-Up Model'!$C$85:$M$85,$A8+1))-INDEX('Roll-Up Model'!$C$97:$M$97,$A8+1)))*INDEX('Roll-Up Model'!$C$101:$M$101,$A8+1))+INDEX('Roll-Up Model'!$C$103:$M$103,$A8+1))/INDEX('Roll-Up Model'!$C$94:$M$94,$A8+1) -> 13.572234 | E8: =(MAX(0,(((INDEX('Roll-Up Model'!$C$40:$M$40,$A8+1)*(Assumptions!$B$16*(1-INDEX('Roll-Up Model'!$C$32:$M$32,$A8+1))+E$5*INDEX('Roll-Up Model'!$C$32:$M$32,$A8+1))+INDEX(Synergies!$C$27:$M$27,$A8+1)*E$5*Assumptions!$B$75*Assumptions!$B$18)*(1-Assumptions!$B$74)-INDEX('Roll-Up Model'!$C$85:$M$85,$A8+1))-Assumptions!$B$73*MAX(0,((INDEX('Roll-Up Model'!$C$40:$M$40,$A8+1)*(Assumptions!$B$16*(1-INDEX('Roll-Up Model'!$C$32:$M$32,$A8+1))+E$5*INDEX('Roll-Up Model'!$C$32:$M$32,$A8+1))+INDEX(Synergies!$C$27:$M$27,$A8+1)*E$5*Assumptions!$B$75*Assumptions!$B$18)*(1-Assumptions!$B$74)-INDEX('Roll-Up Model'!$C$85:$M$85,$A8+1))-INDEX('Roll-Up Model'!$C$97:$M$97,$A8+1)))*INDEX('Roll-Up Model'!$C$101:$M$101,$A8+1))+INDEX('Roll-Up Model'!$C$103:$M$103,$A8+1))/INDEX('Roll-Up Model'!$C$94:$M$94,$A8+1) -> 14.09042 | F8: =(MAX(0,(((INDEX('Roll-Up Model'!$C$40:$M$40,$A8+1)*(Assumptions!$B$16*(1-INDEX('Roll-Up Model'!$C$32:$M$32,$A8+1))+F$5*INDEX('Roll-Up Model'!$C$32:$M$32,$A8+1))+INDEX(Synergies!$C$27:$M$27,$A8+1)*F$5*Assumptions!$B$75*Assumptions!$B$18)*(1-Assumptions!$B$74)-INDEX('Roll-Up Model'!$C$85:$M$85,$A8+1))-Assumptions!$B$73*MAX(0,((INDEX('Roll-Up Model'!$C$40:$M$40,$A8+1)*(Assumptions!$B$16*(1-INDEX('Roll-Up Model'!$C$32:$M$32,$A8+1))+F$5*INDEX('Roll-Up Model'!$C$32:$M$32,$A8+1))+INDEX(Synergies!$C$27:$M$27,$A8+1)*F$5*Assumptions!$B$75*Assumptions!$B$18)*(1-Assumptions!$B$74)-INDEX('Roll-Up Model'!$C$85:$M$85,$A8+1))-INDEX('Roll-Up Model'!$C$97:$M$97,$A8+1)))*INDEX('Roll-Up Model'!$C$101:$M$101,$A8+1))+INDEX('Roll-Up Model'!$C$103:$M$103,$A8+1))/INDEX('Roll-Up Model'!$C$94:$M$94,$A8+1) -> 15.126791 | G8: =(MAX(0,(((INDEX('Roll-Up Model'!$C$40:$M$40,$A8+1)*(Assumptions!$B$16*(1-INDEX('Roll-Up Model'!$C$32:$M$32,$A8+1))+G$5*INDEX('Roll-Up Model'!$C$32:$M$32,$A8+1))+INDEX(Synergies!$C$27:$M$27,$A8+1)*G$5*Assumptions!$B$75*Assumptions!$B$18)*(1-Assumptions!$B$74)-INDEX('Roll-Up Model'!$C$85:$M$85,$A8+1))-Assumptions!$B$73*MAX(0,((INDEX('Roll-Up Model'!$C$40:$M$40,$A8+1)*(Assumptions!$B$16*(1-INDEX('Roll-Up Model'!$C$32:$M$32,$A8+1))+G$5*INDEX('Roll-Up Model'!$C$32:$M$32,$A8+1))+INDEX(Synergies!$C$27:$M$27,$A8+1)*G$5*Assumptions!$B$75*Assumptions!$B$18)*(1-Assumptions!$B$74)-INDEX('Roll-Up Model'!$C$85:$M$85,$A8+1))-INDEX('Roll-Up Model'!$C$97:$M$97,$A8+1)))*INDEX('Roll-Up Model'!$C$101:$M$101,$A8+1))+INDEX('Roll-Up Model'!$C$103:$M$103,$A8+1))/INDEX('Roll-Up Model'!$C$94:$M$94,$A8+1) -> 16.163163
A9: 8 | B9: =(MAX(0,(((INDEX('Roll-Up Model'!$C$40:$M$40,$A9+1)*(Assumptions!$B$16*(1-INDEX('Roll-Up Model'!$C$32:$M$32,$A9+1))+B$5*INDEX('Roll-Up Model'!$C$32:$M$32,$A9+1))+INDEX(Synergies!$C$27:$M$27,$A9+1)*B$5*Assumptions!$B$75*Assumptions!$B$18)*(1-Assumptions!$B$74)-INDEX('Roll-Up Model'!$C$85:$M$85,$A9+1))-Assumptions!$B$73*MAX(0,((INDEX('Roll-Up Model'!$C$40:$M$40,$A9+1)*(Assumptions!$B$16*(1-INDEX('Roll-Up Model'!$C$32:$M$32,$A9+1))+B$5*INDEX('Roll-Up Model'!$C$32:$M$32,$A9+1))+INDEX(Synergies!$C$27:$M$27,$A9+1)*B$5*Assumptions!$B$75*Assumptions!$B$18)*(1-Assumptions!$B$74)-INDEX('Roll-Up Model'!$C$85:$M$85,$A9+1))-INDEX('Roll-Up Model'!$C$97:$M$97,$A9+1)))*INDEX('Roll-Up Model'!$C$101:$M$101,$A9+1))+INDEX('Roll-Up Model'!$C$103:$M$103,$A9+1))/INDEX('Roll-Up Model'!$C$94:$M$94,$A9+1) -> 14.33128 | C9: =(MAX(0,(((INDEX('Roll-Up Model'!$C$40:$M$40,$A9+1)*(Assumptions!$B$16*(1-INDEX('Roll-Up Model'!$C$32:$M$32,$A9+1))+C$5*INDEX('Roll-Up Model'!$C$32:$M$32,$A9+1))+INDEX(Synergies!$C$27:$M$27,$A9+1)*C$5*Assumptions!$B$75*Assumptions!$B$18)*(1-Assumptions!$B$74)-INDEX('Roll-Up Model'!$C$85:$M$85,$A9+1))-Assumptions!$B$73*MAX(0,((INDEX('Roll-Up Model'!$C$40:$M$40,$A9+1)*(Assumptions!$B$16*(1-INDEX('Roll-Up Model'!$C$32:$M$32,$A9+1))+C$5*INDEX('Roll-Up Model'!$C$32:$M$32,$A9+1))+INDEX(Synergies!$C$27:$M$27,$A9+1)*C$5*Assumptions!$B$75*Assumptions!$B$18)*(1-Assumptions!$B$74)-INDEX('Roll-Up Model'!$C$85:$M$85,$A9+1))-INDEX('Roll-Up Model'!$C$97:$M$97,$A9+1)))*INDEX('Roll-Up Model'!$C$101:$M$101,$A9+1))+INDEX('Roll-Up Model'!$C$103:$M$103,$A9+1))/INDEX('Roll-Up Model'!$C$94:$M$94,$A9+1) -> 15.536522 | D9: =(MAX(0,(((INDEX('Roll-Up Model'!$C$40:$M$40,$A9+1)*(Assumptions!$B$16*(1-INDEX('Roll-Up Model'!$C$32:$M$32,$A9+1))+D$5*INDEX('Roll-Up Model'!$C$32:$M$32,$A9+1))+INDEX(Synergies!$C$27:$M$27,$A9+1)*D$5*Assumptions!$B$75*Assumptions!$B$18)*(1-Assumptions!$B$74)-INDEX('Roll-Up Model'!$C$85:$M$85,$A9+1))-Assumptions!$B$73*MAX(0,((INDEX('Roll-Up Model'!$C$40:$M$40,$A9+1)*(Assumptions!$B$16*(1-INDEX('Roll-Up Model'!$C$32:$M$32,$A9+1))+D$5*INDEX('Roll-Up Model'!$C$32:$M$32,$A9+1))+INDEX(Synergies!$C$27:$M$27,$A9+1)*D$5*Assumptions!$B$75*Assumptions!$B$18)*(1-Assumptions!$B$74)-INDEX('Roll-Up Model'!$C$85:$M$85,$A9+1))-INDEX('Roll-Up Model'!$C$97:$M$97,$A9+1)))*INDEX('Roll-Up Model'!$C$101:$M$101,$A9+1))+INDEX('Roll-Up Model'!$C$103:$M$103,$A9+1))/INDEX('Roll-Up Model'!$C$94:$M$94,$A9+1) -> 16.139143 | E9: =(MAX(0,(((INDEX('Roll-Up Model'!$C$40:$M$40,$A9+1)*(Assumptions!$B$16*(1-INDEX('Roll-Up Model'!$C$32:$M$32,$A9+1))+E$5*INDEX('Roll-Up Model'!$C$32:$M$32,$A9+1))+INDEX(Synergies!$C$27:$M$27,$A9+1)*E$5*Assumptions!$B$75*Assumptions!$B$18)*(1-Assumptions!$B$74)-INDEX('Roll-Up Model'!$C$85:$M$85,$A9+1))-Assumptions!$B$73*MAX(0,((INDEX('Roll-Up Model'!$C$40:$M$40,$A9+1)*(Assumptions!$B$16*(1-INDEX('Roll-Up Model'!$C$32:$M$32,$A9+1))+E$5*INDEX('Roll-Up Model'!$C$32:$M$32,$A9+1))+INDEX(Synergies!$C$27:$M$27,$A9+1)*E$5*Assumptions!$B$75*Assumptions!$B$18)*(1-Assumptions!$B$74)-INDEX('Roll-Up Model'!$C$85:$M$85,$A9+1))-INDEX('Roll-Up Model'!$C$97:$M$97,$A9+1)))*INDEX('Roll-Up Model'!$C$101:$M$101,$A9+1))+INDEX('Roll-Up Model'!$C$103:$M$103,$A9+1))/INDEX('Roll-Up Model'!$C$94:$M$94,$A9+1) -> 16.741764 | F9: =(MAX(0,(((INDEX('Roll-Up Model'!$C$40:$M$40,$A9+1)*(Assumptions!$B$16*(1-INDEX('Roll-Up Model'!$C$32:$M$32,$A9+1))+F$5*INDEX('Roll-Up Model'!$C$32:$M$32,$A9+1))+INDEX(Synergies!$C$27:$M$27,$A9+1)*F$5*Assumptions!$B$75*Assumptions!$B$18)*(1-Assumptions!$B$74)-INDEX('Roll-Up Model'!$C$85:$M$85,$A9+1))-Assumptions!$B$73*MAX(0,((INDEX('Roll-Up Model'!$C$40:$M$40,$A9+1)*(Assumptions!$B$16*(1-INDEX('Roll-Up Model'!$C$32:$M$32,$A9+1))+F$5*INDEX('Roll-Up Model'!$C$32:$M$32,$A9+1))+INDEX(Synergies!$C$27:$M$27,$A9+1)*F$5*Assumptions!$B$75*Assumptions!$B$18)*(1-Assumptions!$B$74)-INDEX('Roll-Up Model'!$C$85:$M$85,$A9+1))-INDEX('Roll-Up Model'!$C$97:$M$97,$A9+1)))*INDEX('Roll-Up Model'!$C$101:$M$101,$A9+1))+INDEX('Roll-Up Model'!$C$103:$M$103,$A9+1))/INDEX('Roll-Up Model'!$C$94:$M$94,$A9+1) -> 17.947006 | G9: =(MAX(0,(((INDEX('Roll-Up Model'!$C$40:$M$40,$A9+1)*(Assumptions!$B$16*(1-INDEX('Roll-Up Model'!$C$32:$M$32,$A9+1))+G$5*INDEX('Roll-Up Model'!$C$32:$M$32,$A9+1))+INDEX(Synergies!$C$27:$M$27,$A9+1)*G$5*Assumptions!$B$75*Assumptions!$B$18)*(1-Assumptions!$B$74)-INDEX('Roll-Up Model'!$C$85:$M$85,$A9+1))-Assumptions!$B$73*MAX(0,((INDEX('Roll-Up Model'!$C$40:$M$40,$A9+1)*(Assumptions!$B$16*(1-INDEX('Roll-Up Model'!$C$32:$M$32,$A9+1))+G$5*INDEX('Roll-Up Model'!$C$32:$M$32,$A9+1))+INDEX(Synergies!$C$27:$M$27,$A9+1)*G$5*Assumptions!$B$75*Assumptions!$B$18)*(1-Assumptions!$B$74)-INDEX('Roll-Up Model'!$C$85:$M$85,$A9+1))-INDEX('Roll-Up Model'!$C$97:$M$97,$A9+1)))*INDEX('Roll-Up Model'!$C$101:$M$101,$A9+1))+INDEX('Roll-Up Model'!$C$103:$M$103,$A9+1))/INDEX('Roll-Up Model'!$C$94:$M$94,$A9+1) -> 19.152247
A10: 9 | B10: =(MAX(0,(((INDEX('Roll-Up Model'!$C$40:$M$40,$A10+1)*(Assumptions!$B$16*(1-INDEX('Roll-Up Model'!$C$32:$M$32,$A10+1))+B$5*INDEX('Roll-Up Model'!$C$32:$M$32,$A10+1))+INDEX(Synergies!$C$27:$M$27,$A10+1)*B$5*Assumptions!$B$75*Assumptions!$B$18)*(1-Assumptions!$B$74)-INDEX('Roll-Up Model'!$C$85:$M$85,$A10+1))-Assumptions!$B$73*MAX(0,((INDEX('Roll-Up Model'!$C$40:$M$40,$A10+1)*(Assumptions!$B$16*(1-INDEX('Roll-Up Model'!$C$32:$M$32,$A10+1))+B$5*INDEX('Roll-Up Model'!$C$32:$M$32,$A10+1))+INDEX(Synergies!$C$27:$M$27,$A10+1)*B$5*Assumptions!$B$75*Assumptions!$B$18)*(1-Assumptions!$B$74)-INDEX('Roll-Up Model'!$C$85:$M$85,$A10+1))-INDEX('Roll-Up Model'!$C$97:$M$97,$A10+1)))*INDEX('Roll-Up Model'!$C$101:$M$101,$A10+1))+INDEX('Roll-Up Model'!$C$103:$M$103,$A10+1))/INDEX('Roll-Up Model'!$C$94:$M$94,$A10+1) -> 16.718839 | C10: =(MAX(0,(((INDEX('Roll-Up Model'!$C$40:$M$40,$A10+1)*(Assumptions!$B$16*(1-INDEX('Roll-Up Model'!$C$32:$M$32,$A10+1))+C$5*INDEX('Roll-Up Model'!$C$32:$M$32,$A10+1))+INDEX(Synergies!$C$27:$M$27,$A10+1)*C$5*Assumptions!$B$75*Assumptions!$B$18)*(1-Assumptions!$B$74)-INDEX('Roll-Up Model'!$C$85:$M$85,$A10+1))-Assumptions!$B$73*MAX(0,((INDEX('Roll-Up Model'!$C$40:$M$40,$A10+1)*(Assumptions!$B$16*(1-INDEX('Roll-Up Model'!$C$32:$M$32,$A10+1))+C$5*INDEX('Roll-Up Model'!$C$32:$M$32,$A10+1))+INDEX(Synergies!$C$27:$M$27,$A10+1)*C$5*Assumptions!$B$75*Assumptions!$B$18)*(1-Assumptions!$B$74)-INDEX('Roll-Up Model'!$C$85:$M$85,$A10+1))-INDEX('Roll-Up Model'!$C$97:$M$97,$A10+1)))*INDEX('Roll-Up Model'!$C$101:$M$101,$A10+1))+INDEX('Roll-Up Model'!$C$103:$M$103,$A10+1))/INDEX('Roll-Up Model'!$C$94:$M$94,$A10+1) -> 18.080374 | D10: =(MAX(0,(((INDEX('Roll-Up Model'!$C$40:$M$40,$A10+1)*(Assumptions!$B$16*(1-INDEX('Roll-Up Model'!$C$32:$M$32,$A10+1))+D$5*INDEX('Roll-Up Model'!$C$32:$M$32,$A10+1))+INDEX(Synergies!$C$27:$M$27,$A10+1)*D$5*Assumptions!$B$75*Assumptions!$B$18)*(1-Assumptions!$B$74)-INDEX('Roll-Up Model'!$C$85:$M$85,$A10+1))-Assumptions!$B$73*MAX(0,((INDEX('Roll-Up Model'!$C$40:$M$40,$A10+1)*(Assumptions!$B$16*(1-INDEX('Roll-Up Model'!$C$32:$M$32,$A10+1))+D$5*INDEX('Roll-Up Model'!$C$32:$M$32,$A10+1))+INDEX(Synergies!$C$27:$M$27,$A10+1)*D$5*Assumptions!$B$75*Assumptions!$B$18)*(1-Assumptions!$B$74)-INDEX('Roll-Up Model'!$C$85:$M$85,$A10+1))-INDEX('Roll-Up Model'!$C$97:$M$97,$A10+1)))*INDEX('Roll-Up Model'!$C$101:$M$101,$A10+1))+INDEX('Roll-Up Model'!$C$103:$M$103,$A10+1))/INDEX('Roll-Up Model'!$C$94:$M$94,$A10+1) -> 18.761142 | E10: =(MAX(0,(((INDEX('Roll-Up Model'!$C$40:$M$40,$A10+1)*(Assumptions!$B$16*(1-INDEX('Roll-Up Model'!$C$32:$M$32,$A10+1))+E$5*INDEX('Roll-Up Model'!$C$32:$M$32,$A10+1))+INDEX(Synergies!$C$27:$M$27,$A10+1)*E$5*Assumptions!$B$75*Assumptions!$B$18)*(1-Assumptions!$B$74)-INDEX('Roll-Up Model'!$C$85:$M$85,$A10+1))-Assumptions!$B$73*MAX(0,((INDEX('Roll-Up Model'!$C$40:$M$40,$A10+1)*(Assumptions!$B$16*(1-INDEX('Roll-Up Model'!$C$32:$M$32,$A10+1))+E$5*INDEX('Roll-Up Model'!$C$32:$M$32,$A10+1))+INDEX(Synergies!$C$27:$M$27,$A10+1)*E$5*Assumptions!$B$75*Assumptions!$B$18)*(1-Assumptions!$B$74)-INDEX('Roll-Up Model'!$C$85:$M$85,$A10+1))-INDEX('Roll-Up Model'!$C$97:$M$97,$A10+1)))*INDEX('Roll-Up Model'!$C$101:$M$101,$A10+1))+INDEX('Roll-Up Model'!$C$103:$M$103,$A10+1))/INDEX('Roll-Up Model'!$C$94:$M$94,$A10+1) -> 19.44191 | F10: =(MAX(0,(((INDEX('Roll-Up Model'!$C$40:$M$40,$A10+1)*(Assumptions!$B$16*(1-INDEX('Roll-Up Model'!$C$32:$M$32,$A10+1))+F$5*INDEX('Roll-Up Model'!$C$32:$M$32,$A10+1))+INDEX(Synergies!$C$27:$M$27,$A10+1)*F$5*Assumptions!$B$75*Assumptions!$B$18)*(1-Assumptions!$B$74)-INDEX('Roll-Up Model'!$C$85:$M$85,$A10+1))-Assumptions!$B$73*MAX(0,((INDEX('Roll-Up Model'!$C$40:$M$40,$A10+1)*(Assumptions!$B$16*(1-INDEX('Roll-Up Model'!$C$32:$M$32,$A10+1))+F$5*INDEX('Roll-Up Model'!$C$32:$M$32,$A10+1))+INDEX(Synergies!$C$27:$M$27,$A10+1)*F$5*Assumptions!$B$75*Assumptions!$B$18)*(1-Assumptions!$B$74)-INDEX('Roll-Up Model'!$C$85:$M$85,$A10+1))-INDEX('Roll-Up Model'!$C$97:$M$97,$A10+1)))*INDEX('Roll-Up Model'!$C$101:$M$101,$A10+1))+INDEX('Roll-Up Model'!$C$103:$M$103,$A10+1))/INDEX('Roll-Up Model'!$C$94:$M$94,$A10+1) -> 20.803446 | G10: =(MAX(0,(((INDEX('Roll-Up Model'!$C$40:$M$40,$A10+1)*(Assumptions!$B$16*(1-INDEX('Roll-Up Model'!$C$32:$M$32,$A10+1))+G$5*INDEX('Roll-Up Model'!$C$32:$M$32,$A10+1))+INDEX(Synergies!$C$27:$M$27,$A10+1)*G$5*Assumptions!$B$75*Assumptions!$B$18)*(1-Assumptions!$B$74)-INDEX('Roll-Up Model'!$C$85:$M$85,$A10+1))-Assumptions!$B$73*MAX(0,((INDEX('Roll-Up Model'!$C$40:$M$40,$A10+1)*(Assumptions!$B$16*(1-INDEX('Roll-Up Model'!$C$32:$M$32,$A10+1))+G$5*INDEX('Roll-Up Model'!$C$32:$M$32,$A10+1))+INDEX(Synergies!$C$27:$M$27,$A10+1)*G$5*Assumptions!$B$75*Assumptions!$B$18)*(1-Assumptions!$B$74)-INDEX('Roll-Up Model'!$C$85:$M$85,$A10+1))-INDEX('Roll-Up Model'!$C$97:$M$97,$A10+1)))*INDEX('Roll-Up Model'!$C$101:$M$101,$A10+1))+INDEX('Roll-Up Model'!$C$103:$M$103,$A10+1))/INDEX('Roll-Up Model'!$C$94:$M$94,$A10+1) -> 22.164982
A11: 10 | B11: =(MAX(0,(((INDEX('Roll-Up Model'!$C$40:$M$40,$A11+1)*(Assumptions!$B$16*(1-INDEX('Roll-Up Model'!$C$32:$M$32,$A11+1))+B$5*INDEX('Roll-Up Model'!$C$32:$M$32,$A11+1))+INDEX(Synergies!$C$27:$M$27,$A11+1)*B$5*Assumptions!$B$75*Assumptions!$B$18)*(1-Assumptions!$B$74)-INDEX('Roll-Up Model'!$C$85:$M$85,$A11+1))-Assumptions!$B$73*MAX(0,((INDEX('Roll-Up Model'!$C$40:$M$40,$A11+1)*(Assumptions!$B$16*(1-INDEX('Roll-Up Model'!$C$32:$M$32,$A11+1))+B$5*INDEX('Roll-Up Model'!$C$32:$M$32,$A11+1))+INDEX(Synergies!$C$27:$M$27,$A11+1)*B$5*Assumptions!$B$75*Assumptions!$B$18)*(1-Assumptions!$B$74)-INDEX('Roll-Up Model'!$C$85:$M$85,$A11+1))-INDEX('Roll-Up Model'!$C$97:$M$97,$A11+1)))*INDEX('Roll-Up Model'!$C$101:$M$101,$A11+1))+INDEX('Roll-Up Model'!$C$103:$M$103,$A11+1))/INDEX('Roll-Up Model'!$C$94:$M$94,$A11+1) -> 18.891182 | C11: =(MAX(0,(((INDEX('Roll-Up Model'!$C$40:$M$40,$A11+1)*(Assumptions!$B$16*(1-INDEX('Roll-Up Model'!$C$32:$M$32,$A11+1))+C$5*INDEX('Roll-Up Model'!$C$32:$M$32,$A11+1))+INDEX(Synergies!$C$27:$M$27,$A11+1)*C$5*Assumptions!$B$75*Assumptions!$B$18)*(1-Assumptions!$B$74)-INDEX('Roll-Up Model'!$C$85:$M$85,$A11+1))-Assumptions!$B$73*MAX(0,((INDEX('Roll-Up Model'!$C$40:$M$40,$A11+1)*(Assumptions!$B$16*(1-INDEX('Roll-Up Model'!$C$32:$M$32,$A11+1))+C$5*INDEX('Roll-Up Model'!$C$32:$M$32,$A11+1))+INDEX(Synergies!$C$27:$M$27,$A11+1)*C$5*Assumptions!$B$75*Assumptions!$B$18)*(1-Assumptions!$B$74)-INDEX('Roll-Up Model'!$C$85:$M$85,$A11+1))-INDEX('Roll-Up Model'!$C$97:$M$97,$A11+1)))*INDEX('Roll-Up Model'!$C$101:$M$101,$A11+1))+INDEX('Roll-Up Model'!$C$103:$M$103,$A11+1))/INDEX('Roll-Up Model'!$C$94:$M$94,$A11+1) -> 20.377983 | D11: =(MAX(0,(((INDEX('Roll-Up Model'!$C$40:$M$40,$A11+1)*(Assumptions!$B$16*(1-INDEX('Roll-Up Model'!$C$32:$M$32,$A11+1))+D$5*INDEX('Roll-Up Model'!$C$32:$M$32,$A11+1))+INDEX(Synergies!$C$27:$M$27,$A11+1)*D$5*Assumptions!$B$75*Assumptions!$B$18)*(1-Assumptions!$B$74)-INDEX('Roll-Up Model'!$C$85:$M$85,$A11+1))-Assumptions!$B$73*MAX(0,((INDEX('Roll-Up Model'!$C$40:$M$40,$A11+1)*(Assumptions!$B$16*(1-INDEX('Roll-Up Model'!$C$32:$M$32,$A11+1))+D$5*INDEX('Roll-Up Model'!$C$32:$M$32,$A11+1))+INDEX(Synergies!$C$27:$M$27,$A11+1)*D$5*Assumptions!$B$75*Assumptions!$B$18)*(1-Assumptions!$B$74)-INDEX('Roll-Up Model'!$C$85:$M$85,$A11+1))-INDEX('Roll-Up Model'!$C$97:$M$97,$A11+1)))*INDEX('Roll-Up Model'!$C$101:$M$101,$A11+1))+INDEX('Roll-Up Model'!$C$103:$M$103,$A11+1))/INDEX('Roll-Up Model'!$C$94:$M$94,$A11+1) -> 21.121384 | E11: =(MAX(0,(((INDEX('Roll-Up Model'!$C$40:$M$40,$A11+1)*(Assumptions!$B$16*(1-INDEX('Roll-Up Model'!$C$32:$M$32,$A11+1))+E$5*INDEX('Roll-Up Model'!$C$32:$M$32,$A11+1))+INDEX(Synergies!$C$27:$M$27,$A11+1)*E$5*Assumptions!$B$75*Assumptions!$B$18)*(1-Assumptions!$B$74)-INDEX('Roll-Up Model'!$C$85:$M$85,$A11+1))-Assumptions!$B$73*MAX(0,((INDEX('Roll-Up Model'!$C$40:$M$40,$A11+1)*(Assumptions!$B$16*(1-INDEX('Roll-Up Model'!$C$32:$M$32,$A11+1))+E$5*INDEX('Roll-Up Model'!$C$32:$M$32,$A11+1))+INDEX(Synergies!$C$27:$M$27,$A11+1)*E$5*Assumptions!$B$75*Assumptions!$B$18)*(1-Assumptions!$B$74)-INDEX('Roll-Up Model'!$C$85:$M$85,$A11+1))-INDEX('Roll-Up Model'!$C$97:$M$97,$A11+1)))*INDEX('Roll-Up Model'!$C$101:$M$101,$A11+1))+INDEX('Roll-Up Model'!$C$103:$M$103,$A11+1))/INDEX('Roll-Up Model'!$C$94:$M$94,$A11+1) -> 21.864785 | F11: =(MAX(0,(((INDEX('Roll-Up Model'!$C$40:$M$40,$A11+1)*(Assumptions!$B$16*(1-INDEX('Roll-Up Model'!$C$32:$M$32,$A11+1))+F$5*INDEX('Roll-Up Model'!$C$32:$M$32,$A11+1))+INDEX(Synergies!$C$27:$M$27,$A11+1)*F$5*Assumptions!$B$75*Assumptions!$B$18)*(1-Assumptions!$B$74)-INDEX('Roll-Up Model'!$C$85:$M$85,$A11+1))-Assumptions!$B$73*MAX(0,((INDEX('Roll-Up Model'!$C$40:$M$40,$A11+1)*(Assumptions!$B$16*(1-INDEX('Roll-Up Model'!$C$32:$M$32,$A11+1))+F$5*INDEX('Roll-Up Model'!$C$32:$M$32,$A11+1))+INDEX(Synergies!$C$27:$M$27,$A11+1)*F$5*Assumptions!$B$75*Assumptions!$B$18)*(1-Assumptions!$B$74)-INDEX('Roll-Up Model'!$C$85:$M$85,$A11+1))-INDEX('Roll-Up Model'!$C$97:$M$97,$A11+1)))*INDEX('Roll-Up Model'!$C$101:$M$101,$A11+1))+INDEX('Roll-Up Model'!$C$103:$M$103,$A11+1))/INDEX('Roll-Up Model'!$C$94:$M$94,$A11+1) -> 23.351586 | G11: =(MAX(0,(((INDEX('Roll-Up Model'!$C$40:$M$40,$A11+1)*(Assumptions!$B$16*(1-INDEX('Roll-Up Model'!$C$32:$M$32,$A11+1))+G$5*INDEX('Roll-Up Model'!$C$32:$M$32,$A11+1))+INDEX(Synergies!$C$27:$M$27,$A11+1)*G$5*Assumptions!$B$75*Assumptions!$B$18)*(1-Assumptions!$B$74)-INDEX('Roll-Up Model'!$C$85:$M$85,$A11+1))-Assumptions!$B$73*MAX(0,((INDEX('Roll-Up Model'!$C$40:$M$40,$A11+1)*(Assumptions!$B$16*(1-INDEX('Roll-Up Model'!$C$32:$M$32,$A11+1))+G$5*INDEX('Roll-Up Model'!$C$32:$M$32,$A11+1))+INDEX(Synergies!$C$27:$M$27,$A11+1)*G$5*Assumptions!$B$75*Assumptions!$B$18)*(1-Assumptions!$B$74)-INDEX('Roll-Up Model'!$C$85:$M$85,$A11+1))-INDEX('Roll-Up Model'!$C$97:$M$97,$A11+1)))*INDEX('Roll-Up Model'!$C$101:$M$101,$A11+1))+INDEX('Roll-Up Model'!$C$103:$M$103,$A11+1))/INDEX('Roll-Up Model'!$C$94:$M$94,$A11+1) -> 24.838388
A13: Table 2 — Gross IRR: same grid
A14: Exit year \ Infra multiple | B14: =B5 -> 12 | C14: =C5 -> 14 | D14: =D5 -> 15 | E14: =E5 -> 16 | F14: =F5 -> 18 | G14: =G5 -> 20
A15: =A6 -> 5 | B15: =IRR(I40:S40,0.25) -> 0.8581673 | C15: =IRR(I41:S41,0.25) -> 0.89401005 | D15: =IRR(I42:S42,0.25) -> 0.9110678 | E15: =IRR(I43:S43,0.25) -> 0.92760247 | F15: =IRR(I44:S44,0.25) -> 0.95923698 | G15: =IRR(I45:S45,0.25) -> 0.98915103
A16: =A7 -> 6 | B16: =IRR(I46:S46,0.25) -> 0.73424891 | C16: =IRR(I47:S47,0.25) -> 0.76232636 | D16: =IRR(I48:S48,0.25) -> 0.77565444 | E16: =IRR(I49:S49,0.25) -> 0.78855332 | F16: =IRR(I50:S50,0.25) -> 0.81317673 | G16: =IRR(I51:S51,0.25) -> 0.83639616
A17: =A8 -> 7 | B17: =IRR(I52:S52,0.25) -> 0.64311829 | C17: =IRR(I53:S53,0.25) -> 0.66592391 | D17: =IRR(I54:S54,0.25) -> 0.67672747 | E17: =IRR(I55:S55,0.25) -> 0.68717006 | F17: =IRR(I56:S56,0.25) -> 0.7070699 | G17: =IRR(I57:S57,0.25) -> 0.72579485
A18: =A9 -> 8 | B18: =IRR(I58:S58,0.25) -> 0.57706558 | C18: =IRR(I59:S59,0.25) -> 0.59521913 | D18: =IRR(I60:S60,0.25) -> 0.60382621 | E18: =IRR(I61:S61,0.25) -> 0.61214973 | F18: =IRR(I62:S62,0.25) -> 0.62802129 | G18: =IRR(I63:S63,0.25) -> 0.64296625
A19: =A10 -> 9 | B19: =IRR(I64:S64,0.25) -> 0.52705978 | C19: =IRR(I65:S65,0.25) -> 0.54170159 | D19: =IRR(I66:S66,0.25) -> 0.54865387 | E19: =IRR(I67:S67,0.25) -> 0.55538295 | F19: =IRR(I68:S68,0.25) -> 0.56822905 | G19: =IRR(I69:S69,0.25) -> 0.58034167
A20: =A11 -> 10 | B20: =IRR(I70:S70,0.25) -> 0.48614269 | C20: =IRR(I71:S71,0.25) -> 0.49807195 | D20: =IRR(I72:S72,0.25) -> 0.50374645 | E20: =IRR(I73:S73,0.25) -> 0.50924467 | F20: =IRR(I74:S74,0.25) -> 0.51975631 | G20: =IRR(I75:S75,0.25) -> 0.52968502
A22: Table 3 — Gross MOIC at selected exit year: contracted share at exit (rows) x services multiple (cols)
A23: Contracted % \ Services mult | B23: 8 | C23: 9 | D23: 10 | E23: 11 | F23: 12 | G23: 13
A24: 0.15 | B24: =(MAX(0,(((INDEX('Roll-Up Model'!$C$40:$M$40,Assumptions!$B$90+1)*(B$23*(1-$A24)+Assumptions!$B$17*$A24)+INDEX(Synergies!$C$28:$M$28,Assumptions!$B$90+1))*(1-Assumptions!$B$74)-INDEX('Roll-Up Model'!$C$85:$M$85,Assumptions!$B$90+1))-Assumptions!$B$73*MAX(0,((INDEX('Roll-Up Model'!$C$40:$M$40,Assumptions!$B$90+1)*(B$23*(1-$A24)+Assumptions!$B$17*$A24)+INDEX(Synergies!$C$28:$M$28,Assumptions!$B$90+1))*(1-Assumptions!$B$74)-INDEX('Roll-Up Model'!$C$85:$M$85,Assumptions!$B$90+1))-INDEX('Roll-Up Model'!$C$97:$M$97,Assumptions!$B$90+1)))*INDEX('Roll-Up Model'!$C$101:$M$101,Assumptions!$B$90+1))+INDEX('Roll-Up Model'!$C$103:$M$103,Assumptions!$B$90+1))/INDEX('Roll-Up Model'!$C$94:$M$94,Assumptions!$B$90+1) -> 10.472886 | C24: =(MAX(0,(((INDEX('Roll-Up Model'!$C$40:$M$40,Assumptions!$B$90+1)*(C$23*(1-$A24)+Assumptions!$B$17*$A24)+INDEX(Synergies!$C$28:$M$28,Assumptions!$B$90+1))*(1-Assumptions!$B$74)-INDEX('Roll-Up Model'!$C$85:$M$85,Assumptions!$B$90+1))-Assumptions!$B$73*MAX(0,((INDEX('Roll-Up Model'!$C$40:$M$40,Assumptions!$B$90+1)*(C$23*(1-$A24)+Assumptions!$B$17*$A24)+INDEX(Synergies!$C$28:$M$28,Assumptions!$B$90+1))*(1-Assumptions!$B$74)-INDEX('Roll-Up Model'!$C$85:$M$85,Assumptions!$B$90+1))-INDEX('Roll-Up Model'!$C$97:$M$97,Assumptions!$B$90+1)))*INDEX('Roll-Up Model'!$C$101:$M$101,Assumptions!$B$90+1))+INDEX('Roll-Up Model'!$C$103:$M$103,Assumptions!$B$90+1))/INDEX('Roll-Up Model'!$C$94:$M$94,Assumptions!$B$90+1) -> 11.30619 | D24: =(MAX(0,(((INDEX('Roll-Up Model'!$C$40:$M$40,Assumptions!$B$90+1)*(D$23*(1-$A24)+Assumptions!$B$17*$A24)+INDEX(Synergies!$C$28:$M$28,Assumptions!$B$90+1))*(1-Assumptions!$B$74)-INDEX('Roll-Up Model'!$C$85:$M$85,Assumptions!$B$90+1))-Assumptions!$B$73*MAX(0,((INDEX('Roll-Up Model'!$C$40:$M$40,Assumptions!$B$90+1)*(D$23*(1-$A24)+Assumptions!$B$17*$A24)+INDEX(Synergies!$C$28:$M$28,Assumptions!$B$90+1))*(1-Assumptions!$B$74)-INDEX('Roll-Up Model'!$C$85:$M$85,Assumptions!$B$90+1))-INDEX('Roll-Up Model'!$C$97:$M$97,Assumptions!$B$90+1)))*INDEX('Roll-Up Model'!$C$101:$M$101,Assumptions!$B$90+1))+INDEX('Roll-Up Model'!$C$103:$M$103,Assumptions!$B$90+1))/INDEX('Roll-Up Model'!$C$94:$M$94,Assumptions!$B$90+1) -> 12.139494 | E24: =(MAX(0,(((INDEX('Roll-Up Model'!$C$40:$M$40,Assumptions!$B$90+1)*(E$23*(1-$A24)+Assumptions!$B$17*$A24)+INDEX(Synergies!$C$28:$M$28,Assumptions!$B$90+1))*(1-Assumptions!$B$74)-INDEX('Roll-Up Model'!$C$85:$M$85,Assumptions!$B$90+1))-Assumptions!$B$73*MAX(0,((INDEX('Roll-Up Model'!$C$40:$M$40,Assumptions!$B$90+1)*(E$23*(1-$A24)+Assumptions!$B$17*$A24)+INDEX(Synergies!$C$28:$M$28,Assumptions!$B$90+1))*(1-Assumptions!$B$74)-INDEX('Roll-Up Model'!$C$85:$M$85,Assumptions!$B$90+1))-INDEX('Roll-Up Model'!$C$97:$M$97,Assumptions!$B$90+1)))*INDEX('Roll-Up Model'!$C$101:$M$101,Assumptions!$B$90+1))+INDEX('Roll-Up Model'!$C$103:$M$103,Assumptions!$B$90+1))/INDEX('Roll-Up Model'!$C$94:$M$94,Assumptions!$B$90+1) -> 12.972799 | F24: =(MAX(0,(((INDEX('Roll-Up Model'!$C$40:$M$40,Assumptions!$B$90+1)*(F$23*(1-$A24)+Assumptions!$B$17*$A24)+INDEX(Synergies!$C$28:$M$28,Assumptions!$B$90+1))*(1-Assumptions!$B$74)-INDEX('Roll-Up Model'!$C$85:$M$85,Assumptions!$B$90+1))-Assumptions!$B$73*MAX(0,((INDEX('Roll-Up Model'!$C$40:$M$40,Assumptions!$B$90+1)*(F$23*(1-$A24)+Assumptions!$B$17*$A24)+INDEX(Synergies!$C$28:$M$28,Assumptions!$B$90+1))*(1-Assumptions!$B$74)-INDEX('Roll-Up Model'!$C$85:$M$85,Assumptions!$B$90+1))-INDEX('Roll-Up Model'!$C$97:$M$97,Assumptions!$B$90+1)))*INDEX('Roll-Up Model'!$C$101:$M$101,Assumptions!$B$90+1))+INDEX('Roll-Up Model'!$C$103:$M$103,Assumptions!$B$90+1))/INDEX('Roll-Up Model'!$C$94:$M$94,Assumptions!$B$90+1) -> 13.806103 | G24: =(MAX(0,(((INDEX('Roll-Up Model'!$C$40:$M$40,Assumptions!$B$90+1)*(G$23*(1-$A24)+Assumptions!$B$17*$A24)+INDEX(Synergies!$C$28:$M$28,Assumptions!$B$90+1))*(1-Assumptions!$B$74)-INDEX('Roll-Up Model'!$C$85:$M$85,Assumptions!$B$90+1))-Assumptions!$B$73*MAX(0,((INDEX('Roll-Up Model'!$C$40:$M$40,Assumptions!$B$90+1)*(G$23*(1-$A24)+Assumptions!$B$17*$A24)+INDEX(Synergies!$C$28:$M$28,Assumptions!$B$90+1))*(1-Assumptions!$B$74)-INDEX('Roll-Up Model'!$C$85:$M$85,Assumptions!$B$90+1))-INDEX('Roll-Up Model'!$C$97:$M$97,Assumptions!$B$90+1)))*INDEX('Roll-Up Model'!$C$101:$M$101,Assumptions!$B$90+1))+INDEX('Roll-Up Model'!$C$103:$M$103,Assumptions!$B$90+1))/INDEX('Roll-Up Model'!$C$94:$M$94,Assumptions!$B$90+1) -> 14.639407
A25: 0.25 | B25: =(MAX(0,(((INDEX('Roll-Up Model'!$C$40:$M$40,Assumptions!$B$90+1)*(B$23*(1-$A25)+Assumptions!$B$17*$A25)+INDEX(Synergies!$C$28:$M$28,Assumptions!$B$90+1))*(1-Assumptions!$B$74)-INDEX('Roll-Up Model'!$C$85:$M$85,Assumptions!$B$90+1))-Assumptions!$B$73*MAX(0,((INDEX('Roll-Up Model'!$C$40:$M$40,Assumptions!$B$90+1)*(B$23*(1-$A25)+Assumptions!$B$17*$A25)+INDEX(Synergies!$C$28:$M$28,Assumptions!$B$90+1))*(1-Assumptions!$B$74)-INDEX('Roll-Up Model'!$C$85:$M$85,Assumptions!$B$90+1))-INDEX('Roll-Up Model'!$C$97:$M$97,Assumptions!$B$90+1)))*INDEX('Roll-Up Model'!$C$101:$M$101,Assumptions!$B$90+1))+INDEX('Roll-Up Model'!$C$103:$M$103,Assumptions!$B$90+1))/INDEX('Roll-Up Model'!$C$94:$M$94,Assumptions!$B$90+1) -> 11.159137 | C25: =(MAX(0,(((INDEX('Roll-Up Model'!$C$40:$M$40,Assumptions!$B$90+1)*(C$23*(1-$A25)+Assumptions!$B$17*$A25)+INDEX(Synergies!$C$28:$M$28,Assumptions!$B$90+1))*(1-Assumptions!$B$74)-INDEX('Roll-Up Model'!$C$85:$M$85,Assumptions!$B$90+1))-Assumptions!$B$73*MAX(0,((INDEX('Roll-Up Model'!$C$40:$M$40,Assumptions!$B$90+1)*(C$23*(1-$A25)+Assumptions!$B$17*$A25)+INDEX(Synergies!$C$28:$M$28,Assumptions!$B$90+1))*(1-Assumptions!$B$74)-INDEX('Roll-Up Model'!$C$85:$M$85,Assumptions!$B$90+1))-INDEX('Roll-Up Model'!$C$97:$M$97,Assumptions!$B$90+1)))*INDEX('Roll-Up Model'!$C$101:$M$101,Assumptions!$B$90+1))+INDEX('Roll-Up Model'!$C$103:$M$103,Assumptions!$B$90+1))/INDEX('Roll-Up Model'!$C$94:$M$94,Assumptions!$B$90+1) -> 11.894405 | D25: =(MAX(0,(((INDEX('Roll-Up Model'!$C$40:$M$40,Assumptions!$B$90+1)*(D$23*(1-$A25)+Assumptions!$B$17*$A25)+INDEX(Synergies!$C$28:$M$28,Assumptions!$B$90+1))*(1-Assumptions!$B$74)-INDEX('Roll-Up Model'!$C$85:$M$85,Assumptions!$B$90+1))-Assumptions!$B$73*MAX(0,((INDEX('Roll-Up Model'!$C$40:$M$40,Assumptions!$B$90+1)*(D$23*(1-$A25)+Assumptions!$B$17*$A25)+INDEX(Synergies!$C$28:$M$28,Assumptions!$B$90+1))*(1-Assumptions!$B$74)-INDEX('Roll-Up Model'!$C$85:$M$85,Assumptions!$B$90+1))-INDEX('Roll-Up Model'!$C$97:$M$97,Assumptions!$B$90+1)))*INDEX('Roll-Up Model'!$C$101:$M$101,Assumptions!$B$90+1))+INDEX('Roll-Up Model'!$C$103:$M$103,Assumptions!$B$90+1))/INDEX('Roll-Up Model'!$C$94:$M$94,Assumptions!$B$90+1) -> 12.629673 | E25: =(MAX(0,(((INDEX('Roll-Up Model'!$C$40:$M$40,Assumptions!$B$90+1)*(E$23*(1-$A25)+Assumptions!$B$17*$A25)+INDEX(Synergies!$C$28:$M$28,Assumptions!$B$90+1))*(1-Assumptions!$B$74)-INDEX('Roll-Up Model'!$C$85:$M$85,Assumptions!$B$90+1))-Assumptions!$B$73*MAX(0,((INDEX('Roll-Up Model'!$C$40:$M$40,Assumptions!$B$90+1)*(E$23*(1-$A25)+Assumptions!$B$17*$A25)+INDEX(Synergies!$C$28:$M$28,Assumptions!$B$90+1))*(1-Assumptions!$B$74)-INDEX('Roll-Up Model'!$C$85:$M$85,Assumptions!$B$90+1))-INDEX('Roll-Up Model'!$C$97:$M$97,Assumptions!$B$90+1)))*INDEX('Roll-Up Model'!$C$101:$M$101,Assumptions!$B$90+1))+INDEX('Roll-Up Model'!$C$103:$M$103,Assumptions!$B$90+1))/INDEX('Roll-Up Model'!$C$94:$M$94,Assumptions!$B$90+1) -> 13.364942 | F25: =(MAX(0,(((INDEX('Roll-Up Model'!$C$40:$M$40,Assumptions!$B$90+1)*(F$23*(1-$A25)+Assumptions!$B$17*$A25)+INDEX(Synergies!$C$28:$M$28,Assumptions!$B$90+1))*(1-Assumptions!$B$74)-INDEX('Roll-Up Model'!$C$85:$M$85,Assumptions!$B$90+1))-Assumptions!$B$73*MAX(0,((INDEX('Roll-Up Model'!$C$40:$M$40,Assumptions!$B$90+1)*(F$23*(1-$A25)+Assumptions!$B$17*$A25)+INDEX(Synergies!$C$28:$M$28,Assumptions!$B$90+1))*(1-Assumptions!$B$74)-INDEX('Roll-Up Model'!$C$85:$M$85,Assumptions!$B$90+1))-INDEX('Roll-Up Model'!$C$97:$M$97,Assumptions!$B$90+1)))*INDEX('Roll-Up Model'!$C$101:$M$101,Assumptions!$B$90+1))+INDEX('Roll-Up Model'!$C$103:$M$103,Assumptions!$B$90+1))/INDEX('Roll-Up Model'!$C$94:$M$94,Assumptions!$B$90+1) -> 14.10021 | G25: =(MAX(0,(((INDEX('Roll-Up Model'!$C$40:$M$40,Assumptions!$B$90+1)*(G$23*(1-$A25)+Assumptions!$B$17*$A25)+INDEX(Synergies!$C$28:$M$28,Assumptions!$B$90+1))*(1-Assumptions!$B$74)-INDEX('Roll-Up Model'!$C$85:$M$85,Assumptions!$B$90+1))-Assumptions!$B$73*MAX(0,((INDEX('Roll-Up Model'!$C$40:$M$40,Assumptions!$B$90+1)*(G$23*(1-$A25)+Assumptions!$B$17*$A25)+INDEX(Synergies!$C$28:$M$28,Assumptions!$B$90+1))*(1-Assumptions!$B$74)-INDEX('Roll-Up Model'!$C$85:$M$85,Assumptions!$B$90+1))-INDEX('Roll-Up Model'!$C$97:$M$97,Assumptions!$B$90+1)))*INDEX('Roll-Up Model'!$C$101:$M$101,Assumptions!$B$90+1))+INDEX('Roll-Up Model'!$C$103:$M$103,Assumptions!$B$90+1))/INDEX('Roll-Up Model'!$C$94:$M$94,Assumptions!$B$90+1) -> 14.835479
A26: 0.35 | B26: =(MAX(0,(((INDEX('Roll-Up Model'!$C$40:$M$40,Assumptions!$B$90+1)*(B$23*(1-$A26)+Assumptions!$B$17*$A26)+INDEX(Synergies!$C$28:$M$28,Assumptions!$B$90+1))*(1-Assumptions!$B$74)-INDEX('Roll-Up Model'!$C$85:$M$85,Assumptions!$B$90+1))-Assumptions!$B$73*MAX(0,((INDEX('Roll-Up Model'!$C$40:$M$40,Assumptions!$B$90+1)*(B$23*(1-$A26)+Assumptions!$B$17*$A26)+INDEX(Synergies!$C$28:$M$28,Assumptions!$B$90+1))*(1-Assumptions!$B$74)-INDEX('Roll-Up Model'!$C$85:$M$85,Assumptions!$B$90+1))-INDEX('Roll-Up Model'!$C$97:$M$97,Assumptions!$B$90+1)))*INDEX('Roll-Up Model'!$C$101:$M$101,Assumptions!$B$90+1))+INDEX('Roll-Up Model'!$C$103:$M$103,Assumptions!$B$90+1))/INDEX('Roll-Up Model'!$C$94:$M$94,Assumptions!$B$90+1) -> 11.845387 | C26: =(MAX(0,(((INDEX('Roll-Up Model'!$C$40:$M$40,Assumptions!$B$90+1)*(C$23*(1-$A26)+Assumptions!$B$17*$A26)+INDEX(Synergies!$C$28:$M$28,Assumptions!$B$90+1))*(1-Assumptions!$B$74)-INDEX('Roll-Up Model'!$C$85:$M$85,Assumptions!$B$90+1))-Assumptions!$B$73*MAX(0,((INDEX('Roll-Up Model'!$C$40:$M$40,Assumptions!$B$90+1)*(C$23*(1-$A26)+Assumptions!$B$17*$A26)+INDEX(Synergies!$C$28:$M$28,Assumptions!$B$90+1))*(1-Assumptions!$B$74)-INDEX('Roll-Up Model'!$C$85:$M$85,Assumptions!$B$90+1))-INDEX('Roll-Up Model'!$C$97:$M$97,Assumptions!$B$90+1)))*INDEX('Roll-Up Model'!$C$101:$M$101,Assumptions!$B$90+1))+INDEX('Roll-Up Model'!$C$103:$M$103,Assumptions!$B$90+1))/INDEX('Roll-Up Model'!$C$94:$M$94,Assumptions!$B$90+1) -> 12.48262 | D26: =(MAX(0,(((INDEX('Roll-Up Model'!$C$40:$M$40,Assumptions!$B$90+1)*(D$23*(1-$A26)+Assumptions!$B$17*$A26)+INDEX(Synergies!$C$28:$M$28,Assumptions!$B$90+1))*(1-Assumptions!$B$74)-INDEX('Roll-Up Model'!$C$85:$M$85,Assumptions!$B$90+1))-Assumptions!$B$73*MAX(0,((INDEX('Roll-Up Model'!$C$40:$M$40,Assumptions!$B$90+1)*(D$23*(1-$A26)+Assumptions!$B$17*$A26)+INDEX(Synergies!$C$28:$M$28,Assumptions!$B$90+1))*(1-Assumptions!$B$74)-INDEX('Roll-Up Model'!$C$85:$M$85,Assumptions!$B$90+1))-INDEX('Roll-Up Model'!$C$97:$M$97,Assumptions!$B$90+1)))*INDEX('Roll-Up Model'!$C$101:$M$101,Assumptions!$B$90+1))+INDEX('Roll-Up Model'!$C$103:$M$103,Assumptions!$B$90+1))/INDEX('Roll-Up Model'!$C$94:$M$94,Assumptions!$B$90+1) -> 13.119852 | E26: =(MAX(0,(((INDEX('Roll-Up Model'!$C$40:$M$40,Assumptions!$B$90+1)*(E$23*(1-$A26)+Assumptions!$B$17*$A26)+INDEX(Synergies!$C$28:$M$28,Assumptions!$B$90+1))*(1-Assumptions!$B$74)-INDEX('Roll-Up Model'!$C$85:$M$85,Assumptions!$B$90+1))-Assumptions!$B$73*MAX(0,((INDEX('Roll-Up Model'!$C$40:$M$40,Assumptions!$B$90+1)*(E$23*(1-$A26)+Assumptions!$B$17*$A26)+INDEX(Synergies!$C$28:$M$28,Assumptions!$B$90+1))*(1-Assumptions!$B$74)-INDEX('Roll-Up Model'!$C$85:$M$85,Assumptions!$B$90+1))-INDEX('Roll-Up Model'!$C$97:$M$97,Assumptions!$B$90+1)))*INDEX('Roll-Up Model'!$C$101:$M$101,Assumptions!$B$90+1))+INDEX('Roll-Up Model'!$C$103:$M$103,Assumptions!$B$90+1))/INDEX('Roll-Up Model'!$C$94:$M$94,Assumptions!$B$90+1) -> 13.757085 | F26: =(MAX(0,(((INDEX('Roll-Up Model'!$C$40:$M$40,Assumptions!$B$90+1)*(F$23*(1-$A26)+Assumptions!$B$17*$A26)+INDEX(Synergies!$C$28:$M$28,Assumptions!$B$90+1))*(1-Assumptions!$B$74)-INDEX('Roll-Up Model'!$C$85:$M$85,Assumptions!$B$90+1))-Assumptions!$B$73*MAX(0,((INDEX('Roll-Up Model'!$C$40:$M$40,Assumptions!$B$90+1)*(F$23*(1-$A26)+Assumptions!$B$17*$A26)+INDEX(Synergies!$C$28:$M$28,Assumptions!$B$90+1))*(1-Assumptions!$B$74)-INDEX('Roll-Up Model'!$C$85:$M$85,Assumptions!$B$90+1))-INDEX('Roll-Up Model'!$C$97:$M$97,Assumptions!$B$90+1)))*INDEX('Roll-Up Model'!$C$101:$M$101,Assumptions!$B$90+1))+INDEX('Roll-Up Model'!$C$103:$M$103,Assumptions!$B$90+1))/INDEX('Roll-Up Model'!$C$94:$M$94,Assumptions!$B$90+1) -> 14.394318 | G26: =(MAX(0,(((INDEX('Roll-Up Model'!$C$40:$M$40,Assumptions!$B$90+1)*(G$23*(1-$A26)+Assumptions!$B$17*$A26)+INDEX(Synergies!$C$28:$M$28,Assumptions!$B$90+1))*(1-Assumptions!$B$74)-INDEX('Roll-Up Model'!$C$85:$M$85,Assumptions!$B$90+1))-Assumptions!$B$73*MAX(0,((INDEX('Roll-Up Model'!$C$40:$M$40,Assumptions!$B$90+1)*(G$23*(1-$A26)+Assumptions!$B$17*$A26)+INDEX(Synergies!$C$28:$M$28,Assumptions!$B$90+1))*(1-Assumptions!$B$74)-INDEX('Roll-Up Model'!$C$85:$M$85,Assumptions!$B$90+1))-INDEX('Roll-Up Model'!$C$97:$M$97,Assumptions!$B$90+1)))*INDEX('Roll-Up Model'!$C$101:$M$101,Assumptions!$B$90+1))+INDEX('Roll-Up Model'!$C$103:$M$103,Assumptions!$B$90+1))/INDEX('Roll-Up Model'!$C$94:$M$94,Assumptions!$B$90+1) -> 15.03155
A27: 0.45 | B27: =(MAX(0,(((INDEX('Roll-Up Model'!$C$40:$M$40,Assumptions!$B$90+1)*(B$23*(1-$A27)+Assumptions!$B$17*$A27)+INDEX(Synergies!$C$28:$M$28,Assumptions!$B$90+1))*(1-Assumptions!$B$74)-INDEX('Roll-Up Model'!$C$85:$M$85,Assumptions!$B$90+1))-Assumptions!$B$73*MAX(0,((INDEX('Roll-Up Model'!$C$40:$M$40,Assumptions!$B$90+1)*(B$23*(1-$A27)+Assumptions!$B$17*$A27)+INDEX(Synergies!$C$28:$M$28,Assumptions!$B$90+1))*(1-Assumptions!$B$74)-INDEX('Roll-Up Model'!$C$85:$M$85,Assumptions!$B$90+1))-INDEX('Roll-Up Model'!$C$97:$M$97,Assumptions!$B$90+1)))*INDEX('Roll-Up Model'!$C$101:$M$101,Assumptions!$B$90+1))+INDEX('Roll-Up Model'!$C$103:$M$103,Assumptions!$B$90+1))/INDEX('Roll-Up Model'!$C$94:$M$94,Assumptions!$B$90+1) -> 12.531638 | C27: =(MAX(0,(((INDEX('Roll-Up Model'!$C$40:$M$40,Assumptions!$B$90+1)*(C$23*(1-$A27)+Assumptions!$B$17*$A27)+INDEX(Synergies!$C$28:$M$28,Assumptions!$B$90+1))*(1-Assumptions!$B$74)-INDEX('Roll-Up Model'!$C$85:$M$85,Assumptions!$B$90+1))-Assumptions!$B$73*MAX(0,((INDEX('Roll-Up Model'!$C$40:$M$40,Assumptions!$B$90+1)*(C$23*(1-$A27)+Assumptions!$B$17*$A27)+INDEX(Synergies!$C$28:$M$28,Assumptions!$B$90+1))*(1-Assumptions!$B$74)-INDEX('Roll-Up Model'!$C$85:$M$85,Assumptions!$B$90+1))-INDEX('Roll-Up Model'!$C$97:$M$97,Assumptions!$B$90+1)))*INDEX('Roll-Up Model'!$C$101:$M$101,Assumptions!$B$90+1))+INDEX('Roll-Up Model'!$C$103:$M$103,Assumptions!$B$90+1))/INDEX('Roll-Up Model'!$C$94:$M$94,Assumptions!$B$90+1) -> 13.070835 | D27: =(MAX(0,(((INDEX('Roll-Up Model'!$C$40:$M$40,Assumptions!$B$90+1)*(D$23*(1-$A27)+Assumptions!$B$17*$A27)+INDEX(Synergies!$C$28:$M$28,Assumptions!$B$90+1))*(1-Assumptions!$B$74)-INDEX('Roll-Up Model'!$C$85:$M$85,Assumptions!$B$90+1))-Assumptions!$B$73*MAX(0,((INDEX('Roll-Up Model'!$C$40:$M$40,Assumptions!$B$90+1)*(D$23*(1-$A27)+Assumptions!$B$17*$A27)+INDEX(Synergies!$C$28:$M$28,Assumptions!$B$90+1))*(1-Assumptions!$B$74)-INDEX('Roll-Up Model'!$C$85:$M$85,Assumptions!$B$90+1))-INDEX('Roll-Up Model'!$C$97:$M$97,Assumptions!$B$90+1)))*INDEX('Roll-Up Model'!$C$101:$M$101,Assumptions!$B$90+1))+INDEX('Roll-Up Model'!$C$103:$M$103,Assumptions!$B$90+1))/INDEX('Roll-Up Model'!$C$94:$M$94,Assumptions!$B$90+1) -> 13.610031 | E27: =(MAX(0,(((INDEX('Roll-Up Model'!$C$40:$M$40,Assumptions!$B$90+1)*(E$23*(1-$A27)+Assumptions!$B$17*$A27)+INDEX(Synergies!$C$28:$M$28,Assumptions!$B$90+1))*(1-Assumptions!$B$74)-INDEX('Roll-Up Model'!$C$85:$M$85,Assumptions!$B$90+1))-Assumptions!$B$73*MAX(0,((INDEX('Roll-Up Model'!$C$40:$M$40,Assumptions!$B$90+1)*(E$23*(1-$A27)+Assumptions!$B$17*$A27)+INDEX(Synergies!$C$28:$M$28,Assumptions!$B$90+1))*(1-Assumptions!$B$74)-INDEX('Roll-Up Model'!$C$85:$M$85,Assumptions!$B$90+1))-INDEX('Roll-Up Model'!$C$97:$M$97,Assumptions!$B$90+1)))*INDEX('Roll-Up Model'!$C$101:$M$101,Assumptions!$B$90+1))+INDEX('Roll-Up Model'!$C$103:$M$103,Assumptions!$B$90+1))/INDEX('Roll-Up Model'!$C$94:$M$94,Assumptions!$B$90+1) -> 14.149228 | F27: =(MAX(0,(((INDEX('Roll-Up Model'!$C$40:$M$40,Assumptions!$B$90+1)*(F$23*(1-$A27)+Assumptions!$B$17*$A27)+INDEX(Synergies!$C$28:$M$28,Assumptions!$B$90+1))*(1-Assumptions!$B$74)-INDEX('Roll-Up Model'!$C$85:$M$85,Assumptions!$B$90+1))-Assumptions!$B$73*MAX(0,((INDEX('Roll-Up Model'!$C$40:$M$40,Assumptions!$B$90+1)*(F$23*(1-$A27)+Assumptions!$B$17*$A27)+INDEX(Synergies!$C$28:$M$28,Assumptions!$B$90+1))*(1-Assumptions!$B$74)-INDEX('Roll-Up Model'!$C$85:$M$85,Assumptions!$B$90+1))-INDEX('Roll-Up Model'!$C$97:$M$97,Assumptions!$B$90+1)))*INDEX('Roll-Up Model'!$C$101:$M$101,Assumptions!$B$90+1))+INDEX('Roll-Up Model'!$C$103:$M$103,Assumptions!$B$90+1))/INDEX('Roll-Up Model'!$C$94:$M$94,Assumptions!$B$90+1) -> 14.688425 | G27: =(MAX(0,(((INDEX('Roll-Up Model'!$C$40:$M$40,Assumptions!$B$90+1)*(G$23*(1-$A27)+Assumptions!$B$17*$A27)+INDEX(Synergies!$C$28:$M$28,Assumptions!$B$90+1))*(1-Assumptions!$B$74)-INDEX('Roll-Up Model'!$C$85:$M$85,Assumptions!$B$90+1))-Assumptions!$B$73*MAX(0,((INDEX('Roll-Up Model'!$C$40:$M$40,Assumptions!$B$90+1)*(G$23*(1-$A27)+Assumptions!$B$17*$A27)+INDEX(Synergies!$C$28:$M$28,Assumptions!$B$90+1))*(1-Assumptions!$B$74)-INDEX('Roll-Up Model'!$C$85:$M$85,Assumptions!$B$90+1))-INDEX('Roll-Up Model'!$C$97:$M$97,Assumptions!$B$90+1)))*INDEX('Roll-Up Model'!$C$101:$M$101,Assumptions!$B$90+1))+INDEX('Roll-Up Model'!$C$103:$M$103,Assumptions!$B$90+1))/INDEX('Roll-Up Model'!$C$94:$M$94,Assumptions!$B$90+1) -> 15.227622
A28: 0.55 | B28: =(MAX(0,(((INDEX('Roll-Up Model'!$C$40:$M$40,Assumptions!$B$90+1)*(B$23*(1-$A28)+Assumptions!$B$17*$A28)+INDEX(Synergies!$C$28:$M$28,Assumptions!$B$90+1))*(1-Assumptions!$B$74)-INDEX('Roll-Up Model'!$C$85:$M$85,Assumptions!$B$90+1))-Assumptions!$B$73*MAX(0,((INDEX('Roll-Up Model'!$C$40:$M$40,Assumptions!$B$90+1)*(B$23*(1-$A28)+Assumptions!$B$17*$A28)+INDEX(Synergies!$C$28:$M$28,Assumptions!$B$90+1))*(1-Assumptions!$B$74)-INDEX('Roll-Up Model'!$C$85:$M$85,Assumptions!$B$90+1))-INDEX('Roll-Up Model'!$C$97:$M$97,Assumptions!$B$90+1)))*INDEX('Roll-Up Model'!$C$101:$M$101,Assumptions!$B$90+1))+INDEX('Roll-Up Model'!$C$103:$M$103,Assumptions!$B$90+1))/INDEX('Roll-Up Model'!$C$94:$M$94,Assumptions!$B$90+1) -> 13.217888 | C28: =(MAX(0,(((INDEX('Roll-Up Model'!$C$40:$M$40,Assumptions!$B$90+1)*(C$23*(1-$A28)+Assumptions!$B$17*$A28)+INDEX(Synergies!$C$28:$M$28,Assumptions!$B$90+1))*(1-Assumptions!$B$74)-INDEX('Roll-Up Model'!$C$85:$M$85,Assumptions!$B$90+1))-Assumptions!$B$73*MAX(0,((INDEX('Roll-Up Model'!$C$40:$M$40,Assumptions!$B$90+1)*(C$23*(1-$A28)+Assumptions!$B$17*$A28)+INDEX(Synergies!$C$28:$M$28,Assumptions!$B$90+1))*(1-Assumptions!$B$74)-INDEX('Roll-Up Model'!$C$85:$M$85,Assumptions!$B$90+1))-INDEX('Roll-Up Model'!$C$97:$M$97,Assumptions!$B$90+1)))*INDEX('Roll-Up Model'!$C$101:$M$101,Assumptions!$B$90+1))+INDEX('Roll-Up Model'!$C$103:$M$103,Assumptions!$B$90+1))/INDEX('Roll-Up Model'!$C$94:$M$94,Assumptions!$B$90+1) -> 13.659049 | D28: =(MAX(0,(((INDEX('Roll-Up Model'!$C$40:$M$40,Assumptions!$B$90+1)*(D$23*(1-$A28)+Assumptions!$B$17*$A28)+INDEX(Synergies!$C$28:$M$28,Assumptions!$B$90+1))*(1-Assumptions!$B$74)-INDEX('Roll-Up Model'!$C$85:$M$85,Assumptions!$B$90+1))-Assumptions!$B$73*MAX(0,((INDEX('Roll-Up Model'!$C$40:$M$40,Assumptions!$B$90+1)*(D$23*(1-$A28)+Assumptions!$B$17*$A28)+INDEX(Synergies!$C$28:$M$28,Assumptions!$B$90+1))*(1-Assumptions!$B$74)-INDEX('Roll-Up Model'!$C$85:$M$85,Assumptions!$B$90+1))-INDEX('Roll-Up Model'!$C$97:$M$97,Assumptions!$B$90+1)))*INDEX('Roll-Up Model'!$C$101:$M$101,Assumptions!$B$90+1))+INDEX('Roll-Up Model'!$C$103:$M$103,Assumptions!$B$90+1))/INDEX('Roll-Up Model'!$C$94:$M$94,Assumptions!$B$90+1) -> 14.10021 | E28: =(MAX(0,(((INDEX('Roll-Up Model'!$C$40:$M$40,Assumptions!$B$90+1)*(E$23*(1-$A28)+Assumptions!$B$17*$A28)+INDEX(Synergies!$C$28:$M$28,Assumptions!$B$90+1))*(1-Assumptions!$B$74)-INDEX('Roll-Up Model'!$C$85:$M$85,Assumptions!$B$90+1))-Assumptions!$B$73*MAX(0,((INDEX('Roll-Up Model'!$C$40:$M$40,Assumptions!$B$90+1)*(E$23*(1-$A28)+Assumptions!$B$17*$A28)+INDEX(Synergies!$C$28:$M$28,Assumptions!$B$90+1))*(1-Assumptions!$B$74)-INDEX('Roll-Up Model'!$C$85:$M$85,Assumptions!$B$90+1))-INDEX('Roll-Up Model'!$C$97:$M$97,Assumptions!$B$90+1)))*INDEX('Roll-Up Model'!$C$101:$M$101,Assumptions!$B$90+1))+INDEX('Roll-Up Model'!$C$103:$M$103,Assumptions!$B$90+1))/INDEX('Roll-Up Model'!$C$94:$M$94,Assumptions!$B$90+1) -> 14.541371 | F28: =(MAX(0,(((INDEX('Roll-Up Model'!$C$40:$M$40,Assumptions!$B$90+1)*(F$23*(1-$A28)+Assumptions!$B$17*$A28)+INDEX(Synergies!$C$28:$M$28,Assumptions!$B$90+1))*(1-Assumptions!$B$74)-INDEX('Roll-Up Model'!$C$85:$M$85,Assumptions!$B$90+1))-Assumptions!$B$73*MAX(0,((INDEX('Roll-Up Model'!$C$40:$M$40,Assumptions!$B$90+1)*(F$23*(1-$A28)+Assumptions!$B$17*$A28)+INDEX(Synergies!$C$28:$M$28,Assumptions!$B$90+1))*(1-Assumptions!$B$74)-INDEX('Roll-Up Model'!$C$85:$M$85,Assumptions!$B$90+1))-INDEX('Roll-Up Model'!$C$97:$M$97,Assumptions!$B$90+1)))*INDEX('Roll-Up Model'!$C$101:$M$101,Assumptions!$B$90+1))+INDEX('Roll-Up Model'!$C$103:$M$103,Assumptions!$B$90+1))/INDEX('Roll-Up Model'!$C$94:$M$94,Assumptions!$B$90+1) -> 14.982532 | G28: =(MAX(0,(((INDEX('Roll-Up Model'!$C$40:$M$40,Assumptions!$B$90+1)*(G$23*(1-$A28)+Assumptions!$B$17*$A28)+INDEX(Synergies!$C$28:$M$28,Assumptions!$B$90+1))*(1-Assumptions!$B$74)-INDEX('Roll-Up Model'!$C$85:$M$85,Assumptions!$B$90+1))-Assumptions!$B$73*MAX(0,((INDEX('Roll-Up Model'!$C$40:$M$40,Assumptions!$B$90+1)*(G$23*(1-$A28)+Assumptions!$B$17*$A28)+INDEX(Synergies!$C$28:$M$28,Assumptions!$B$90+1))*(1-Assumptions!$B$74)-INDEX('Roll-Up Model'!$C$85:$M$85,Assumptions!$B$90+1))-INDEX('Roll-Up Model'!$C$97:$M$97,Assumptions!$B$90+1)))*INDEX('Roll-Up Model'!$C$101:$M$101,Assumptions!$B$90+1))+INDEX('Roll-Up Model'!$C$103:$M$103,Assumptions!$B$90+1))/INDEX('Roll-Up Model'!$C$94:$M$94,Assumptions!$B$90+1) -> 15.423694
A29: 0.65 | B29: =(MAX(0,(((INDEX('Roll-Up Model'!$C$40:$M$40,Assumptions!$B$90+1)*(B$23*(1-$A29)+Assumptions!$B$17*$A29)+INDEX(Synergies!$C$28:$M$28,Assumptions!$B$90+1))*(1-Assumptions!$B$74)-INDEX('Roll-Up Model'!$C$85:$M$85,Assumptions!$B$90+1))-Assumptions!$B$73*MAX(0,((INDEX('Roll-Up Model'!$C$40:$M$40,Assumptions!$B$90+1)*(B$23*(1-$A29)+Assumptions!$B$17*$A29)+INDEX(Synergies!$C$28:$M$28,Assumptions!$B$90+1))*(1-Assumptions!$B$74)-INDEX('Roll-Up Model'!$C$85:$M$85,Assumptions!$B$90+1))-INDEX('Roll-Up Model'!$C$97:$M$97,Assumptions!$B$90+1)))*INDEX('Roll-Up Model'!$C$101:$M$101,Assumptions!$B$90+1))+INDEX('Roll-Up Model'!$C$103:$M$103,Assumptions!$B$90+1))/INDEX('Roll-Up Model'!$C$94:$M$94,Assumptions!$B$90+1) -> 13.904139 | C29: =(MAX(0,(((INDEX('Roll-Up Model'!$C$40:$M$40,Assumptions!$B$90+1)*(C$23*(1-$A29)+Assumptions!$B$17*$A29)+INDEX(Synergies!$C$28:$M$28,Assumptions!$B$90+1))*(1-Assumptions!$B$74)-INDEX('Roll-Up Model'!$C$85:$M$85,Assumptions!$B$90+1))-Assumptions!$B$73*MAX(0,((INDEX('Roll-Up Model'!$C$40:$M$40,Assumptions!$B$90+1)*(C$23*(1-$A29)+Assumptions!$B$17*$A29)+INDEX(Synergies!$C$28:$M$28,Assumptions!$B$90+1))*(1-Assumptions!$B$74)-INDEX('Roll-Up Model'!$C$85:$M$85,Assumptions!$B$90+1))-INDEX('Roll-Up Model'!$C$97:$M$97,Assumptions!$B$90+1)))*INDEX('Roll-Up Model'!$C$101:$M$101,Assumptions!$B$90+1))+INDEX('Roll-Up Model'!$C$103:$M$103,Assumptions!$B$90+1))/INDEX('Roll-Up Model'!$C$94:$M$94,Assumptions!$B$90+1) -> 14.247264 | D29: =(MAX(0,(((INDEX('Roll-Up Model'!$C$40:$M$40,Assumptions!$B$90+1)*(D$23*(1-$A29)+Assumptions!$B$17*$A29)+INDEX(Synergies!$C$28:$M$28,Assumptions!$B$90+1))*(1-Assumptions!$B$74)-INDEX('Roll-Up Model'!$C$85:$M$85,Assumptions!$B$90+1))-Assumptions!$B$73*MAX(0,((INDEX('Roll-Up Model'!$C$40:$M$40,Assumptions!$B$90+1)*(D$23*(1-$A29)+Assumptions!$B$17*$A29)+INDEX(Synergies!$C$28:$M$28,Assumptions!$B$90+1))*(1-Assumptions!$B$74)-INDEX('Roll-Up Model'!$C$85:$M$85,Assumptions!$B$90+1))-INDEX('Roll-Up Model'!$C$97:$M$97,Assumptions!$B$90+1)))*INDEX('Roll-Up Model'!$C$101:$M$101,Assumptions!$B$90+1))+INDEX('Roll-Up Model'!$C$103:$M$103,Assumptions!$B$90+1))/INDEX('Roll-Up Model'!$C$94:$M$94,Assumptions!$B$90+1) -> 14.590389 | E29: =(MAX(0,(((INDEX('Roll-Up Model'!$C$40:$M$40,Assumptions!$B$90+1)*(E$23*(1-$A29)+Assumptions!$B$17*$A29)+INDEX(Synergies!$C$28:$M$28,Assumptions!$B$90+1))*(1-Assumptions!$B$74)-INDEX('Roll-Up Model'!$C$85:$M$85,Assumptions!$B$90+1))-Assumptions!$B$73*MAX(0,((INDEX('Roll-Up Model'!$C$40:$M$40,Assumptions!$B$90+1)*(E$23*(1-$A29)+Assumptions!$B$17*$A29)+INDEX(Synergies!$C$28:$M$28,Assumptions!$B$90+1))*(1-Assumptions!$B$74)-INDEX('Roll-Up Model'!$C$85:$M$85,Assumptions!$B$90+1))-INDEX('Roll-Up Model'!$C$97:$M$97,Assumptions!$B$90+1)))*INDEX('Roll-Up Model'!$C$101:$M$101,Assumptions!$B$90+1))+INDEX('Roll-Up Model'!$C$103:$M$103,Assumptions!$B$90+1))/INDEX('Roll-Up Model'!$C$94:$M$94,Assumptions!$B$90+1) -> 14.933515 | F29: =(MAX(0,(((INDEX('Roll-Up Model'!$C$40:$M$40,Assumptions!$B$90+1)*(F$23*(1-$A29)+Assumptions!$B$17*$A29)+INDEX(Synergies!$C$28:$M$28,Assumptions!$B$90+1))*(1-Assumptions!$B$74)-INDEX('Roll-Up Model'!$C$85:$M$85,Assumptions!$B$90+1))-Assumptions!$B$73*MAX(0,((INDEX('Roll-Up Model'!$C$40:$M$40,Assumptions!$B$90+1)*(F$23*(1-$A29)+Assumptions!$B$17*$A29)+INDEX(Synergies!$C$28:$M$28,Assumptions!$B$90+1))*(1-Assumptions!$B$74)-INDEX('Roll-Up Model'!$C$85:$M$85,Assumptions!$B$90+1))-INDEX('Roll-Up Model'!$C$97:$M$97,Assumptions!$B$90+1)))*INDEX('Roll-Up Model'!$C$101:$M$101,Assumptions!$B$90+1))+INDEX('Roll-Up Model'!$C$103:$M$103,Assumptions!$B$90+1))/INDEX('Roll-Up Model'!$C$94:$M$94,Assumptions!$B$90+1) -> 15.27664 | G29: =(MAX(0,(((INDEX('Roll-Up Model'!$C$40:$M$40,Assumptions!$B$90+1)*(G$23*(1-$A29)+Assumptions!$B$17*$A29)+INDEX(Synergies!$C$28:$M$28,Assumptions!$B$90+1))*(1-Assumptions!$B$74)-INDEX('Roll-Up Model'!$C$85:$M$85,Assumptions!$B$90+1))-Assumptions!$B$73*MAX(0,((INDEX('Roll-Up Model'!$C$40:$M$40,Assumptions!$B$90+1)*(G$23*(1-$A29)+Assumptions!$B$17*$A29)+INDEX(Synergies!$C$28:$M$28,Assumptions!$B$90+1))*(1-Assumptions!$B$74)-INDEX('Roll-Up Model'!$C$85:$M$85,Assumptions!$B$90+1))-INDEX('Roll-Up Model'!$C$97:$M$97,Assumptions!$B$90+1)))*INDEX('Roll-Up Model'!$C$101:$M$101,Assumptions!$B$90+1))+INDEX('Roll-Up Model'!$C$103:$M$103,Assumptions!$B$90+1))/INDEX('Roll-Up Model'!$C$94:$M$94,Assumptions!$B$90+1) -> 15.619765
A31: Read: each row is the contracted-revenue share actually achieved by exit. Moving from 15% to 45% contracted is worth more than +2 turns of services multiple — the core optimization of the thesis.
A39: IRR helper — cash flows per grid cell (Y0..Y10 in cols I:S)
A40: =A6 -> 5 | B40: =B$5 -> 12 | I40: =IF(0<=$A40,-'Roll-Up Model'!C63+0,0)+IF(0=$A40,MAX(0,(((INDEX('Roll-Up Model'!$C$40:$M$40,$A40+1)*(Assumptions!$B$16*(1-INDEX('Roll-Up Model'!$C$32:$M$32,$A40+1))+$B40*INDEX('Roll-Up Model'!$C$32:$M$32,$A40+1))+INDEX(Synergies!$C$27:$M$27,$A40+1)*$B40*Assumptions!$B$75*Assumptions!$B$18)*(1-Assumptions!$B$74)-INDEX('Roll-Up Model'!$C$85:$M$85,$A40+1))-Assumptions!$B$73*MAX(0,((INDEX('Roll-Up Model'!$C$40:$M$40,$A40+1)*(Assumptions!$B$16*(1-INDEX('Roll-Up Model'!$C$32:$M$32,$A40+1))+$B40*INDEX('Roll-Up Model'!$C$32:$M$32,$A40+1))+INDEX(Synergies!$C$27:$M$27,$A40+1)*$B40*Assumptions!$B$75*Assumptions!$B$18)*(1-Assumptions!$B$74)-INDEX('Roll-Up Model'!$C$85:$M$85,$A40+1))-INDEX('Roll-Up Model'!$C$97:$M$97,$A40+1)))*INDEX('Roll-Up Model'!$C$101:$M$101,$A40+1)),0) -> -2.9705 | J40: =IF(1<=$A40,-'Roll-Up Model'!D63+'Roll-Up Model'!D102,0)+IF(1=$A40,MAX(0,(((INDEX('Roll-Up Model'!$C$40:$M$40,$A40+1)*(Assumptions!$B$16*(1-INDEX('Roll-Up Model'!$C$32:$M$32,$A40+1))+$B40*INDEX('Roll-Up Model'!$C$32:$M$32,$A40+1))+INDEX(Synergies!$C$27:$M$27,$A40+1)*$B40*Assumptions!$B$75*Assumptions!$B$18)*(1-Assumptions!$B$74)-INDEX('Roll-Up Model'!$C$85:$M$85,$A40+1))-Assumptions!$B$73*MAX(0,((INDEX('Roll-Up Model'!$C$40:$M$40,$A40+1)*(Assumptions!$B$16*(1-INDEX('Roll-Up Model'!$C$32:$M$32,$A40+1))+$B40*INDEX('Roll-Up Model'!$C$32:$M$32,$A40+1))+INDEX(Synergies!$C$27:$M$27,$A40+1)*$B40*Assumptions!$B$75*Assumptions!$B$18)*(1-Assumptions!$B$74)-INDEX('Roll-Up Model'!$C$85:$M$85,$A40+1))-INDEX('Roll-Up Model'!$C$97:$M$97,$A40+1)))*INDEX('Roll-Up Model'!$C$101:$M$101,$A40+1)),0) -> -1.5921938 | K40: =IF(2<=$A40,-'Roll-Up Model'!E63+'Roll-Up Model'!E102,0)+IF(2=$A40,MAX(0,(((INDEX('Roll-Up Model'!$C$40:$M$40,$A40+1)*(Assumptions!$B$16*(1-INDEX('Roll-Up Model'!$C$32:$M$32,$A40+1))+$B40*INDEX('Roll-Up Model'!$C$32:$M$32,$A40+1))+INDEX(Synergies!$C$27:$M$27,$A40+1)*$B40*Assumptions!$B$75*Assumptions!$B$18)*(1-Assumptions!$B$74)-INDEX('Roll-Up Model'!$C$85:$M$85,$A40+1))-Assumptions!$B$73*MAX(0,((INDEX('Roll-Up Model'!$C$40:$M$40,$A40+1)*(Assumptions!$B$16*(1-INDEX('Roll-Up Model'!$C$32:$M$32,$A40+1))+$B40*INDEX('Roll-Up Model'!$C$32:$M$32,$A40+1))+INDEX(Synergies!$C$27:$M$27,$A40+1)*$B40*Assumptions!$B$75*Assumptions!$B$18)*(1-Assumptions!$B$74)-INDEX('Roll-Up Model'!$C$85:$M$85,$A40+1))-INDEX('Roll-Up Model'!$C$97:$M$97,$A40+1)))*INDEX('Roll-Up Model'!$C$101:$M$101,$A40+1)),0) -> -2.3879604 | L40: =IF(3<=$A40,-'Roll-Up Model'!F63+'Roll-Up Model'!F102,0)+IF(3=$A40,MAX(0,(((INDEX('Roll-Up Model'!$C$40:$M$40,$A40+1)*(Assumptions!$B$16*(1-INDEX('Roll-Up Model'!$C$32:$M$32,$A40+1))+$B40*INDEX('Roll-Up Model'!$C$32:$M$32,$A40+1))+INDEX(Synergies!$C$27:$M$27,$A40+1)*$B40*Assumptions!$B$75*Assumptions!$B$18)*(1-Assumptions!$B$74)-INDEX('Roll-Up Model'!$C$85:$M$85,$A40+1))-Assumptions!$B$73*MAX(0,((INDEX('Roll-Up Model'!$C$40:$M$40,$A40+1)*(Assumptions!$B$16*(1-INDEX('Roll-Up Model'!$C$32:$M$32,$A40+1))+$B40*INDEX('Roll-Up Model'!$C$32:$M$32,$A40+1))+INDEX(Synergies!$C$27:$M$27,$A40+1)*$B40*Assumptions!$B$75*Assumptions!$B$18)*(1-Assumptions!$B$74)-INDEX('Roll-Up Model'!$C$85:$M$85,$A40+1))-INDEX('Roll-Up Model'!$C$97:$M$97,$A40+1)))*INDEX('Roll-Up Model'!$C$101:$M$101,$A40+1)),0) -> -2.0150933 | M40: =IF(4<=$A40,-'Roll-Up Model'!G63+'Roll-Up Model'!G102,0)+IF(4=$A40,MAX(0,(((INDEX('Roll-Up Model'!$C$40:$M$40,$A40+1)*(Assumptions!$B$16*(1-INDEX('Roll-Up Model'!$C$32:$M$32,$A40+1))+$B40*INDEX('Roll-Up Model'!$C$32:$M$32,$A40+1))+INDEX(Synergies!$C$27:$M$27,$A40+1)*$B40*Assumptions!$B$75*Assumptions!$B$18)*(1-Assumptions!$B$74)-INDEX('Roll-Up Model'!$C$85:$M$85,$A40+1))-Assumptions!$B$73*MAX(0,((INDEX('Roll-Up Model'!$C$40:$M$40,$A40+1)*(Assumptions!$B$16*(1-INDEX('Roll-Up Model'!$C$32:$M$32,$A40+1))+$B40*INDEX('Roll-Up Model'!$C$32:$M$32,$A40+1))+INDEX(Synergies!$C$27:$M$27,$A40+1)*$B40*Assumptions!$B$75*Assumptions!$B$18)*(1-Assumptions!$B$74)-INDEX('Roll-Up Model'!$C$85:$M$85,$A40+1))-INDEX('Roll-Up Model'!$C$97:$M$97,$A40+1)))*INDEX('Roll-Up Model'!$C$101:$M$101,$A40+1)),0) -> -1.756897 | N40: =IF(5<=$A40,-'Roll-Up Model'!H63+'Roll-Up Model'!H102,0)+IF(5=$A40,MAX(0,(((INDEX('Roll-Up Model'!$C$40:$M$40,$A40+1)*(Assumptions!$B$16*(1-INDEX('Roll-Up Model'!$C$32:$M$32,$A40+1))+$B40*INDEX('Roll-Up Model'!$C$32:$M$32,$A40+1))+INDEX(Synergies!$C$27:$M$27,$A40+1)*$B40*Assumptions!$B$75*Assumptions!$B$18)*(1-Assumptions!$B$74)-INDEX('Roll-Up Model'!$C$85:$M$85,$A40+1))-Assumptions!$B$73*MAX(0,((INDEX('Roll-Up Model'!$C$40:$M$40,$A40+1)*(Assumptions!$B$16*(1-INDEX('Roll-Up Model'!$C$32:$M$32,$A40+1))+$B40*INDEX('Roll-Up Model'!$C$32:$M$32,$A40+1))+INDEX(Synergies!$C$27:$M$27,$A40+1)*$B40*Assumptions!$B$75*Assumptions!$B$18)*(1-Assumptions!$B$74)-INDEX('Roll-Up Model'!$C$85:$M$85,$A40+1))-INDEX('Roll-Up Model'!$C$97:$M$97,$A40+1)))*INDEX('Roll-Up Model'!$C$101:$M$101,$A40+1)),0) -> 110.329 | O40: =IF(6<=$A40,-'Roll-Up Model'!I63+'Roll-Up Model'!I102,0)+IF(6=$A40,MAX(0,(((INDEX('Roll-Up Model'!$C$40:$M$40,$A40+1)*(Assumptions!$B$16*(1-INDEX('Roll-Up Model'!$C$32:$M$32,$A40+1))+$B40*INDEX('Roll-Up Model'!$C$32:$M$32,$A40+1))+INDEX(Synergies!$C$27:$M$27,$A40+1)*$B40*Assumptions!$B$75*Assumptions!$B$18)*(1-Assumptions!$B$74)-INDEX('Roll-Up Model'!$C$85:$M$85,$A40+1))-Assumptions!$B$73*MAX(0,((INDEX('Roll-Up Model'!$C$40:$M$40,$A40+1)*(Assumptions!$B$16*(1-INDEX('Roll-Up Model'!$C$32:$M$32,$A40+1))+$B40*INDEX('Roll-Up Model'!$C$32:$M$32,$A40+1))+INDEX(Synergies!$C$27:$M$27,$A40+1)*$B40*Assumptions!$B$75*Assumptions!$B$18)*(1-Assumptions!$B$74)-INDEX('Roll-Up Model'!$C$85:$M$85,$A40+1))-INDEX('Roll-Up Model'!$C$97:$M$97,$A40+1)))*INDEX('Roll-Up Model'!$C$101:$M$101,$A40+1)),0) -> 0 | P40: =IF(7<=$A40,-'Roll-Up Model'!J63+'Roll-Up Model'!J102,0)+IF(7=$A40,MAX(0,(((INDEX('Roll-Up Model'!$C$40:$M$40,$A40+1)*(Assumptions!$B$16*(1-INDEX('Roll-Up Model'!$C$32:$M$32,$A40+1))+$B40*INDEX('Roll-Up Model'!$C$32:$M$32,$A40+1))+INDEX(Synergies!$C$27:$M$27,$A40+1)*$B40*Assumptions!$B$75*Assumptions!$B$18)*(1-Assumptions!$B$74)-INDEX('Roll-Up Model'!$C$85:$M$85,$A40+1))-Assumptions!$B$73*MAX(0,((INDEX('Roll-Up Model'!$C$40:$M$40,$A40+1)*(Assumptions!$B$16*(1-INDEX('Roll-Up Model'!$C$32:$M$32,$A40+1))+$B40*INDEX('Roll-Up Model'!$C$32:$M$32,$A40+1))+INDEX(Synergies!$C$27:$M$27,$A40+1)*$B40*Assumptions!$B$75*Assumptions!$B$18)*(1-Assumptions!$B$74)-INDEX('Roll-Up Model'!$C$85:$M$85,$A40+1))-INDEX('Roll-Up Model'!$C$97:$M$97,$A40+1)))*INDEX('Roll-Up Model'!$C$101:$M$101,$A40+1)),0) -> 0 | Q40: =IF(8<=$A40,-'Roll-Up Model'!K63+'Roll-Up Model'!K102,0)+IF(8=$A40,MAX(0,(((INDEX('Roll-Up Model'!$C$40:$M$40,$A40+1)*(Assumptions!$B$16*(1-INDEX('Roll-Up Model'!$C$32:$M$32,$A40+1))+$B40*INDEX('Roll-Up Model'!$C$32:$M$32,$A40+1))+INDEX(Synergies!$C$27:$M$27,$A40+1)*$B40*Assumptions!$B$75*Assumptions!$B$18)*(1-Assumptions!$B$74)-INDEX('Roll-Up Model'!$C$85:$M$85,$A40+1))-Assumptions!$B$73*MAX(0,((INDEX('Roll-Up Model'!$C$40:$M$40,$A40+1)*(Assumptions!$B$16*(1-INDEX('Roll-Up Model'!$C$32:$M$32,$A40+1))+$B40*INDEX('Roll-Up Model'!$C$32:$M$32,$A40+1))+INDEX(Synergies!$C$27:$M$27,$A40+1)*$B40*Assumptions!$B$75*Assumptions!$B$18)*(1-Assumptions!$B$74)-INDEX('Roll-Up Model'!$C$85:$M$85,$A40+1))-INDEX('Roll-Up Model'!$C$97:$M$97,$A40+1)))*INDEX('Roll-Up Model'!$C$101:$M$101,$A40+1)),0) -> 0 | R40: =IF(9<=$A40,-'Roll-Up Model'!L63+'Roll-Up Model'!L102,0)+IF(9=$A40,MAX(0,(((INDEX('Roll-Up Model'!$C$40:$M$40,$A40+1)*(Assumptions!$B$16*(1-INDEX('Roll-Up Model'!$C$32:$M$32,$A40+1))+$B40*INDEX('Roll-Up Model'!$C$32:$M$32,$A40+1))+INDEX(Synergies!$C$27:$M$27,$A40+1)*$B40*Assumptions!$B$75*Assumptions!$B$18)*(1-Assumptions!$B$74)-INDEX('Roll-Up Model'!$C$85:$M$85,$A40+1))-Assumptions!$B$73*MAX(0,((INDEX('Roll-Up Model'!$C$40:$M$40,$A40+1)*(Assumptions!$B$16*(1-INDEX('Roll-Up Model'!$C$32:$M$32,$A40+1))+$B40*INDEX('Roll-Up Model'!$C$32:$M$32,$A40+1))+INDEX(Synergies!$C$27:$M$27,$A40+1)*$B40*Assumptions!$B$75*Assumptions!$B$18)*(1-Assumptions!$B$74)-INDEX('Roll-Up Model'!$C$85:$M$85,$A40+1))-INDEX('Roll-Up Model'!$C$97:$M$97,$A40+1)))*INDEX('Roll-Up Model'!$C$101:$M$101,$A40+1)),0) -> 0 | S40: =IF(10<=$A40,-'Roll-Up Model'!M63+'Roll-Up Model'!M102,0)+IF(10=$A40,MAX(0,(((INDEX('Roll-Up Model'!$C$40:$M$40,$A40+1)*(Assumptions!$B$16*(1-INDEX('Roll-Up Model'!$C$32:$M$32,$A40+1))+$B40*INDEX('Roll-Up Model'!$C$32:$M$32,$A40+1))+INDEX(Synergies!$C$27:$M$27,$A40+1)*$B40*Assumptions!$B$75*Assumptions!$B$18)*(1-Assumptions!$B$74)-INDEX('Roll-Up Model'!$C$85:$M$85,$A40+1))-Assumptions!$B$73*MAX(0,((INDEX('Roll-Up Model'!$C$40:$M$40,$A40+1)*(Assumptions!$B$16*(1-INDEX('Roll-Up Model'!$C$32:$M$32,$A40+1))+$B40*INDEX('Roll-Up Model'!$C$32:$M$32,$A40+1))+INDEX(Synergies!$C$27:$M$27,$A40+1)*$B40*Assumptions!$B$75*Assumptions!$B$18)*(1-Assumptions!$B$74)-INDEX('Roll-Up Model'!$C$85:$M$85,$A40+1))-INDEX('Roll-Up Model'!$C$97:$M$97,$A40+1)))*INDEX('Roll-Up Model'!$C$101:$M$101,$A40+1)),0) -> 0
