Workbook
Name Hold_Short: Assumptions!$F$5
Name Hold_Mid: Assumptions!$F$6
Name Hold_Long: Assumptions!$F$7
Name IQT_Committed: Assumptions!$B$5
Name Mgmt_Fee: Assumptions!$B$8
Name Carry: Assumptions!$B$9
Name Pref: Assumptions!$B$10
Name Ret_IQT_Short: Assumptions!$B$11
Name Ret_IQT_Mid: Assumptions!$B$12
Name Ret_IQT_Long: Assumptions!$B$13
Name Ret_Wpn_Short: 'Weapons Sleeve'!$B$6
Name Ret_Wpn_Mid: 'Weapons Sleeve'!$B$7
Name Ret_Wpn_Long: 'Weapons Sleeve'!$B$8
Name Ret_Con_Short: 'Consumer Sleeve'!$B$6
Name Ret_Con_Mid: 'Consumer Sleeve'!$B$7
Name Ret_Con_Long: 'Consumer Sleeve'!$B$8
Name P_Base: 'Defense Supercycle'!$B$17
Name P_Bull: 'Defense Supercycle'!$B$18
Name P_Bear: 'Defense Supercycle'!$B$19
Name P_Shock: 'Defense Supercycle'!$B$20
Name Holdco_Size: 'Holdco Summary'!$B$9
Name IQT_Size: 'Holdco Summary'!$B$6
Name Wpn_Size: 'Holdco Summary'!$B$7
Name Con_Size: 'Holdco Summary'!$B$8
Name SPX_CAGR: 'PME, DPI & Sensitivity'!$B$5
Name NDX_CAGR: 'PME, DPI & Sensitivity'!$B$6
Name Basket_CAGR: 'Holdco Summary'!$B$23

Sheet Cover
B25: LEVIATHAN CORE PRIVATE EQUITY HOLDCO (“LPEH”)
B26: ="Internal IC planning model · v3 optimised 02-Oct-2026 · "&TEXT(Holdco_Size,"$#,##0")&"M across three sub-vehicles · USD millions" -> Internal IC planning model · v3 optimised 02-Oct-2026 · $840M across three sub-vehicles · USD millions
B27: =Checks!$B$3 -> MODEL INTEGRITY: ALL 21 CHECKS PASS
B28: HIGHLY CONFIDENTIAL & TRADE SECRET · Miami · London · Zurich · Tokyo
B30: NAVIGATION
B31: Read Me | D31: How the model is wired, caveats, v3 change summary
B32: Change Log | D32: Cell-level record of the optimisation pass
B33: Checks | D33: Model integrity dashboard
B34: IC Summary | D34: One-page holdco dashboard
B35: Holdco Summary | D35: Tripartite roll-up and holdco waterfall
B36: Assumptions | D36: Fund terms, hold levers, IQT-mirror entry marks
B37: Defense Supercycle | D37: Strategic scoring and shock engine
B38: Weapons Sleeve | D38: Defense sub-vehicle with munitions / FMS overlay
B39: Consumer Sleeve | D39: Consumer sub-vehicle with cohort-exposure overlay
B40: Sleeve Economics | D40: Gross-to-net by sub-vehicle and netting reconciliation
B41: PME, DPI & Sensitivity | D41: Public-market equivalents and shock pressure tests
B42: Fact Sheet Data | D42: Every figure on the external fact sheet

Sheet Read Me
B1: LEVIATHAN FUND — CORE PE VEHICLE
B2: ="IQT-Backed Deep-Tech Acquisition-Stake Portfolio | "&Hold_Short&" / "&Hold_Mid&" / "&Hold_Long&"-Year Holds | Defense-Supercycle Overlay" -> IQT-Backed Deep-Tech Acquisition-Stake Portfolio | 5 / 7 / 10-Year Holds | Defense-Supercycle Overlay
B3: Anchored by Substrate, Inc. · Prepared 22-Sep-2026 · v3 optimization pass 02-Oct-2026 · All figures USD millions unless noted
B5: PURPOSE
B6: Leviathan's core PE holdco is an $840M vehicle across THREE sub-funds: IQT-mirror deep-tech ($250M), Weapons ($390M), and Consumer/Value ($200M). All three sleeves are modeled bottom-up from individual holdings — IQT-mirror (nine In-Q-Tel names), Weapons (nine physical-layer holdings, incl. The Ellwood Group and Superior & Grand Valley for missile-procurement metal forging), Consumer/Value (nine DTC/spending-cycle names) — each across four scenarios, 5/7/10-yr holds, gross-to-net waterfall, and PME, and roll up to a blended holdco return on the Holdco Summary tab. Start there for the top-down view; the sleeve tabs hold the detail.
B7: Scope: Leviathan runs four vehicles (~$1.5B AUM total); this workbook models only the core PE holdco vehicle ($840M) and its equity targets — not the other three vehicles.
B8: THE DEFENSE-SUPERCYCLE THESIS (now wired into returns)
B9: The book is built to be long the US side of the AI / semiconductor race with China and structurally hedged against a Taiwan contingency or loss of TSMC access. The Defense Supercycle tab scores every name on five strategic axes — China-race criticality, Taiwan/TSMC-insulation value, government/defense embeddedness, CFIUS-clean US-sovereignty, and supply-chain chokepoint leverage. Those scores drive a composite, which drives each name's re-rating in the TSMC-Shock scenario. Change a score and the shock returns move.
B11: HOW THE MODEL IS WIRED (edit blue cells only)
B12: • IC Summary — one-page holdco dashboard: net IRR / MOIC / proceeds / KS-PME by hold x scenario, sleeve gross MOIC, scenario weights and model integrity checks. Start here. • Assumptions — fund terms + per-name entry marks, checks, ownership, and Base/Bull/Bear CAGRs. TSMC-Shock CAGR is computed from the Supercycle tab.
B13: • Defense Supercycle — strategic scoring matrix, axis weights, shock calibration levers, and the four scenario probability weights. This is the thesis engine.
B14: • Allocation — nine positions, tranche, ownership, domicile, structuring/CFIUS flags.
B15: • Portfolio Returns — per-name proceeds, MOIC, gross IRR for each hold x four scenarios.
B16: • Fund Economics — gross->net waterfall (2% fee, 8% pref, 20% carry) per vehicle x scenario, plus prob-weighted Expected.
... B35: • All IRR / Direct-Alpha formulas are guarded: a wipe-out returns -100% rather than #NUM!. Stale sleeve CAGR memos replaced by live links. Redundant same-sheet references removed. See the Change Log tab for the cell-level list.

Sheet Change Log
A1: CHANGE LOG — v3 OPTIMIZATION PASS (02-Oct-2026)
A2: Cell-level record of every edit made by the optimization script. 'Value impact' flags the only places where numbers moved; everything else is structural and was verified cell-by-cell against the prior version after a full recalculation.
A4: # | B4: Tab | C4: Range | D4: Change | E4: Value impact
A5: 1 | B5: Assumptions | C5: A4 | D5: Relabelled fund-terms block: these terms drive the holdco AND every sleeve waterfall, not just IQT. | E5: None
A6: 2 | B6: Assumptions | C6: E4:G7 | D6: NEW hold-period levers (5/7/10 yrs) with named ranges Hold_Short / Hold_Mid / Hold_Long. Every block header, hold exponent, fee-year multiplier and IRR root in the model now references these cells. | E6: None
A7: 3 | B7: Assumptions | C7: A29 | D7: NEW check: initial deployment + follow-on reserve must equal committed capital. | E7: None
A8: 4 | B8: Workbook | C8: Defined names | D8: NEW named ranges for every lever: Hold_Short, Hold_Mid, Hold_Long, IQT_Committed, Mgmt_Fee, Carry, Pref, Ret_IQT_Short, Ret_IQT_Mid, Ret_IQT_Long, Ret_Wpn_Short, Ret_Wpn_Mid, Ret_Wpn_Long, Ret_Con_Short, Ret_Con_Mid, Ret_Con_Long, P_Base, P_Bull, P_Bear, P_Shock, Holdco_Size, IQT_Size, Wpn_Size, Con_Size, SPX_CAGR, NDX_CAGR, Basket_CAGR. | E8: None
A9: 5 | B9: All tabs | C9: formulas | D9: Replaced 1424 repeated lever references with named ranges and removed 63 redundant same-sheet references (e.g. 'Holdco Summary'!$B$9 inside Holdco Summary). Pure readability; values unchanged. | E9: None
A10: 6 | B10: PME, DPI & Sensitivity | C10: B73:D73, B81:D81, B87:D94, B99:D100 | D10: Holdco PME / sensitivity blocks and the Weapons PME hold-year inputs now read the Hold_* levers instead of hard-coded 5 / 7 / 10. | E10: None
A11: 7 | B11: All model tabs | C11: hold blocks | D11: Rewrote 1062 hard-coded hold-period literals (^5, *7, (1/10) ...) to the Hold_Short / Hold_Mid / Hold_Long levers. Change a hold period once on Assumptions and every proceeds, pref, fee, IRR, PME and sensitivity formula follows. | E11: None
A12: 8 | B12: All tabs | C12: section labels | D12: 66 block headers / row labels that embedded '5-YEAR', '7-Year', 'Retention @ 10yr' etc. are now formulas driven by the hold levers, so labels can never drift from the maths. | E12: None
A13: 9 | B13: All model tabs | C13: IRR / Direct Alpha cells | D13: Guarded 498 IRR and Direct-Alpha formulas: a wipe-out (net proceeds <= 0) now returns -100% instead of #NUM!, so Expected columns and checks never break in a severe Bear case. | E13: None
A14: 10 | B14: Holdco Summary | C14: A14:F19 | D14: Stale hard-coded sleeve CAGR memos (Weapons 22/34/5/32%, Consumer 14/25/-10/-4%) replaced by live links to the bottom-up sleeve IRRs for all three sleeves; note moved to A19. | E14: Memo rows only
A15: 11 | B15: Holdco Summary | C15: F32:F37, F53:F58, F74:F79 | D15: Expected column now probability-weights each NET waterfall line (same method as Fund Economics / Scenario Summary). Rows F32/F33/F36 are constant across scenarios, F34/F35 were already weighted; the whole block is now written one way. | E15: None in this version (F34/F35 were already weighted); block is now uniformly weighted
A16: 12 | B16: Holdco Summary | C16: A3 | D16: Live model-integrity status pulled from the new Checks tab. | E16: None
... A24: 19 | B24: Cover | C24: whole tab | D24: NEW cover sheet: Leviathan logo, vehicle title, live integrity status and hyperlinked tab navigation. | E24: None

Sheet Checks
A1: MODEL INTEGRITY CHECKS
A2: Every structural identity the model relies on. Status flows to Holdco Summary!A3. Blue = target input.
A3: OVERALL STATUS | B3: =IF(COUNTIF(C8:C28,"ERROR")=0,"MODEL INTEGRITY: ALL "&COUNTA(A8:A28)&" CHECKS PASS","MODEL INTEGRITY: "&COUNTIF(C8:C28,"ERROR")&" OF "&COUNTA(A8:A28)&" CHECKS FAILING") -> MODEL INTEGRITY: ALL 21 CHECKS PASS
A5: Holdco target size ($M) | B5: 840 | D5: Sleeve sizes on Holdco Summary must add to this.
A7: Check | B7: Value | C7: Status | D7: What it protects
A8: Holdco sleeve sizes sum to target | B8: =Holdco_Size-$B$5 -> 0 | C8: =IF(ABS(B8)<0.5,"OK","ERROR") -> OK | D8: Holdco Summary B6:B9 vs target
A9: IQT sleeve: checks sum to sleeve size | B9: =Assumptions!C27-IQT_Size -> 0 | C9: =IF(ABS(B9)<0.5,"OK","ERROR") -> OK | D9: Assumptions C18:C26
A10: Weapons sleeve: checks sum to sleeve size | B10: ='Weapons Sleeve'!C21-Wpn_Size -> 0 | C10: =IF(ABS(B10)<0.5,"OK","ERROR") -> OK | D10: Weapons Sleeve C12:C18
A11: Consumer sleeve: checks sum to sleeve size | B11: ='Consumer Sleeve'!C21-Con_Size -> 0 | C11: =IF(ABS(B11)<0.5,"OK","ERROR") -> OK | D11: Consumer Sleeve C12:C20
A12: IQT: initial deployment + reserve = committed | B12: =Assumptions!B6+Assumptions!B7-IQT_Committed -> 0 | C12: =IF(ABS(B12)<0.5,"OK","ERROR") -> OK | D12: Assumptions B5:B7
A13: Strategic axis weights sum to 100% | B13: ='Defense Supercycle'!B10 -> 1 | C13: =IF(ABS(B13-1)<0.0001,"OK","ERROR") -> OK | D13: Defense Supercycle B5:B9
A14: Scenario probabilities sum to 100% | B14: ='Defense Supercycle'!B21 -> 1 | C14: =IF(ABS(B14-1)<0.0001,"OK","ERROR") -> OK | D14: Defense Supercycle B17:B20
A15: Hold periods positive and strictly increasing | B15: =Hold_Short&" < "&Hold_Mid&" < "&Hold_Long -> 5 < 7 < 10 | C15: =IF(AND(Hold_Short>0,Hold_Mid>Hold_Short,Hold_Long>Hold_Mid),"OK","ERROR") -> OK | D15: Assumptions F5:F7
A16: IQT retention in (0,1] and non-increasing with hold | B16: =TEXT(Ret_IQT_Short,"0%")&" ≥ "&TEXT(Ret_IQT_Mid,"0%")&" ≥ "&TEXT(Ret_IQT_Long,"0%") -> 85% ≥ 78% ≥ 68% | C16: =IF(AND(Ret_IQT_Short<=1,Ret_IQT_Short>=Ret_IQT_Mid,Ret_IQT_Mid>=Ret_IQT_Long,Ret_IQT_Long>0),"OK","ERROR") -> OK | D16: Assumptions B11:B13
A17: Weapons retention in (0,1] and non-increasing with hold | B17: =TEXT(Ret_Wpn_Short,"0%")&" ≥ "&TEXT(Ret_Wpn_Mid,"0%")&" ≥ "&TEXT(Ret_Wpn_Long,"0%") -> 92% ≥ 88% ≥ 82% | C17: =IF(AND(Ret_Wpn_Short<=1,Ret_Wpn_Short>=Ret_Wpn_Mid,Ret_Wpn_Mid>=Ret_Wpn_Long,Ret_Wpn_Long>0),"OK","ERROR") -> OK | D17: Weapons Sleeve B6:B8
A18: Consumer retention in (0,1] and non-increasing with hold | B18: =TEXT(Ret_Con_Short,"0%")&" ≥ "&TEXT(Ret_Con_Mid,"0%")&" ≥ "&TEXT(Ret_Con_Long,"0%") -> 90% ≥ 84% ≥ 75% | C18: =IF(AND(Ret_Con_Short<=1,Ret_Con_Short>=Ret_Con_Mid,Ret_Con_Mid>=Ret_Con_Long,Ret_Con_Long>0),"OK","ERROR") -> OK | D18: Consumer Sleeve B6:B8
A19: Fee, carry and pref each within [0%, 100%) | B19: =TEXT(Mgmt_Fee,"0.0%")&" / "&TEXT(Carry,"0%")&" / "&TEXT(Pref,"0%") -> 2.0% / 20% / 8% | C19: =IF(AND(Mgmt_Fee>=0,Mgmt_Fee<1,Carry>=0,Carry<1,Pref>=0,Pref<1),"OK","ERROR") -> OK | D19: Assumptions B8:B10
A20: Allocation tab total = Assumptions deployed total | B20: =Allocation!B14-Assumptions!C27 -> 0 | C20: =IF(ABS(B20)<0.5,"OK","ERROR") -> OK | D20: Allocation B5:B14
A21: IQT Clusters total = Assumptions deployed total | B21: ='IQT Clusters'!C10-Assumptions!C27 -> 0 | C21: =IF(ABS(B21)<0.5,"OK","ERROR") -> OK | D21: IQT Clusters C6:C10
A22: Sleeve Economics IQT net = Fund Economics net (all holds, all cases) | B22: =SUMPRODUCT(ABS('Fund Economics'!B12:F12-'Sleeve Economics'!B12:F12))+SUMPRODUCT(ABS('Fund Economics'!B28:F28-'Sleeve Economics'!B29:F29))+SUMPRODUCT(ABS('Fund Economics'!B44:F44-'Sleeve Economics'!B46:F46)) -> 0 | C22: =IF(ABS(B22)<0.01,"OK","ERROR") -> OK | D22: Two independent waterfalls of the same sleeve must agree
A23: Holdco gross proceeds = sum of sleeve gross (all holds, all cases) | B23: =SUMPRODUCT(ABS('Holdco Summary'!B31:F31-('Sleeve Economics'!B6:F6+'Sleeve Economics'!H6:L6+'Sleeve Economics'!N6:R6)))+SUMPRODUCT(ABS('Holdco Summary'!B52:F52-('Sleeve Economics'!B23:F23+'Sleeve Economics'!H23:L23+'Sleeve Economics'!N23:R23)))+SUMPRODUCT(ABS('Holdco Summary'!B73:F73-('Sleeve Economics'!B40:F40+'Sleeve Economics'!H40:L40+'Sleeve Economics'!N40:R40))) -> 0 | C23: =IF(ABS(B23)<0.01,"OK","ERROR") -> OK | D23: Roll-up links point at the right sleeve rows
A24: Fact-sheet holdings register sums to holdco size | B24: ='Fact Sheet Data'!C85-Holdco_Size -> 0 | C24: =IF(ABS(B24)<0.5,"OK","ERROR") -> OK | D24: Every holding is tagged exactly once
A25: Fact-sheet breakdowns each sum to 100% | B25: =ABS('Fact Sheet Data'!C92-1)+ABS('Fact Sheet Data'!C106-1)+ABS('Fact Sheet Data'!C114-1)+ABS('Fact Sheet Data'!C123-1) -> 1.110223e-16 | C25: =IF(ABS(B25)<0.0001,"OK","ERROR") -> OK | D25: No untagged / mistyped sector, region or stage
A26: Consumer cohort weights sum to 100% | B26: ='Consumer Sleeve'!T8 -> 1 | C26: =IF(ABS(B26-1)<0.0001,"OK","ERROR") -> OK | D26: Consumer Sleeve T5:T7
A27: IC Summary integrity block reports ALL PASS | B27: ='IC Summary'!D80 -> ALL PASS | C27: =IF(B27="ALL PASS","OK","ERROR") -> OK | D27: The pre-existing 8-check block on IC Summary
A28: No formula errors on output tabs | B28: =SUMPRODUCT(ISERROR('Holdco Summary'!B28:F86)*1)+SUMPRODUCT(ISERROR('Fund Economics'!B6:F49)*1)+SUMPRODUCT(ISERROR('Sleeve Economics'!B6:R53)*1)+SUMPRODUCT(ISERROR('Scenario Summary'!B6:F22)*1)+SUMPRODUCT(ISERROR('PME, DPI & Sensitivity'!B13:F69)*1)+SUMPRODUCT(ISERROR('Fact Sheet Data'!B5:N143)*1)+SUMPRODUCT(ISERROR('IC Summary'!B6:F81)*1) -> 0 | C28: =IF(B28=0,"OK","ERROR") -> OK | D28: Count of #DIV/0!, #NUM!, #REF! etc. across all output ranges

Sheet IC Summary
A1: LEVIATHAN CORE PE HOLDCO — IC SUMMARY
A2: $840M tripartite holdco (IQT-mirror / Weapons / Consumer-Value). USD $M. Expected = probability-weighted across Base/Bull/Bear/TSMC-Shock (weights on Defense Supercycle tab). Every figure links live to the model — no inputs on this page.
A4: ="HEADLINE — RECOMMENDED "&Hold_Mid&"-YEAR VEHICLE (Expected case, net to LP)" -> HEADLINE — RECOMMENDED 7-YEAR VEHICLE (Expected case, net to LP)
A5: Metric | B5: Net IRR | C5: Net MOIC | D5: Net proceeds | E5: KS-PME basket | F5: KS-PME SPX
A6: Holdco — 7-yr, probability-weighted | B6: ='Holdco Summary'!F61 -> 0.19871158 | C6: ='Holdco Summary'!F59 -> 3.556337 | D6: ='Holdco Summary'!F58 -> 2987.3231 | E6: ='Holdco Summary'!F64 -> 1.3369588 | F6: ='Holdco Summary'!F62 -> 1.9454381
A8: HOLDCO NET IRR TO LP
A9: Vehicle | B9: Base | C9: Bull | D9: Bear | E9: TSMC-Shock | F9: Expected
A10: =Hold_Short&"-Year Hold" -> 5-Year Hold | B10: ='Holdco Summary'!B40 -> 0.16099973 | C10: ='Holdco Summary'!C40 -> 0.28032381 | D10: ='Holdco Summary'!D40 -> -0.047351614 | E10: ='Holdco Summary'!E40 -> 0.21405233 | F10: ='Holdco Summary'!F40 -> 0.18357543
A11: =Hold_Mid&"-Year Hold" -> 7-Year Hold | B11: ='Holdco Summary'!B61 -> 0.16509984 | C11: ='Holdco Summary'!C61 -> 0.28959836 | D11: ='Holdco Summary'!D61 -> -0.044375165 | E11: ='Holdco Summary'!E61 -> 0.23378367 | F11: ='Holdco Summary'!F61 -> 0.19871158
A12: =Hold_Long&"-Year Hold" -> 10-Year Hold | B12: ='Holdco Summary'!B82 -> 0.17091166 | C12: ='Holdco Summary'!C82 -> 0.30129185 | D12: ='Holdco Summary'!D82 -> -0.039722227 | E12: ='Holdco Summary'!E82 -> 0.25664155 | F12: ='Holdco Summary'!F82 -> 0.21881304
A14: HOLDCO NET MOIC TO LP
A15: Vehicle | B15: Base | C15: Bull | D15: Bear | E15: TSMC-Shock | F15: Expected
A16: =Hold_Short&"-Year Hold" -> 5-Year Hold | B16: ='Holdco Summary'!B38 -> 2.1094081 | C16: ='Holdco Summary'!C38 -> 3.4403221 | D16: ='Holdco Summary'!D38 -> 0.78462688 | E16: ='Holdco Summary'!E38 -> 2.637467 | F16: ='Holdco Summary'!F38 -> 2.3226282
A17: =Hold_Mid&"-Year Hold" -> 7-Year Hold | B17: ='Holdco Summary'!B59 -> 2.914352 | C17: ='Holdco Summary'!C59 -> 5.9317292 | D17: ='Holdco Summary'!D59 -> 0.7277999 | E17: ='Holdco Summary'!E59 -> 4.3518419 | F17: ='Holdco Summary'!F59 -> 3.556337
A18: =Hold_Long&"-Year Hold" -> 10-Year Hold | B18: ='Holdco Summary'!B80 -> 4.8444146 | C18: ='Holdco Summary'!C80 -> 13.923458 | D18: ='Holdco Summary'!D80 -> 0.66675881 | E18: ='Holdco Summary'!E80 -> 9.8200601 | F18: ='Holdco Summary'!F80 -> 7.2338739
A20: HOLDCO NET PROCEEDS TO LP ($M)
A21: Vehicle | B21: Base | C21: Bull | D21: Bear | E21: TSMC-Shock | F21: Expected
A22: =Hold_Short&"-Year Hold" -> 5-Year Hold | B22: ='Holdco Summary'!B37 -> 1771.9028 | C22: ='Holdco Summary'!C37 -> 2889.8706 | D22: ='Holdco Summary'!D37 -> 659.08658 | E22: ='Holdco Summary'!E37 -> 2215.4723 | F22: ='Holdco Summary'!F37 -> 1951.0077
A23: =Hold_Mid&"-Year Hold" -> 7-Year Hold | B23: ='Holdco Summary'!B58 -> 2448.0557 | C23: ='Holdco Summary'!C58 -> 4982.6525 | D23: ='Holdco Summary'!D58 -> 611.35192 | E23: ='Holdco Summary'!E58 -> 3655.5472 | F23: ='Holdco Summary'!F58 -> 2987.3231
A24: =Hold_Long&"-Year Hold" -> 10-Year Hold | B24: ='Holdco Summary'!B79 -> 4069.3083 | C24: ='Holdco Summary'!C79 -> 11695.705 | D24: ='Holdco Summary'!D79 -> 560.0774 | E24: ='Holdco Summary'!E79 -> 8248.8505 | F24: ='Holdco Summary'!F79 -> 6076.4541
A26: KS-PME vs DEFENSE+SEMIS BASKET (>1.00x = beat the thematic ETFs)
A27: Vehicle | B27: Base | C27: Bull | D27: Bear | E27: TSMC-Shock | F27: Expected
A28: =Hold_Short&"-Year Hold" -> 5-Year Hold | B28: ='Holdco Summary'!B43 -> 1.0487486 | C28: ='Holdco Summary'!C43 -> 1.7104481 | D28: ='Holdco Summary'!D43 -> 0.39009823 | E28: ='Holdco Summary'!E43 -> 1.3112872 | F28: ='Holdco Summary'!F43 -> 1.1547567
A29: =Hold_Mid&"-Year Hold" -> 7-Year Hold | B29: ='Holdco Summary'!B64 -> 1.0956129 | C29: ='Holdco Summary'!C64 -> 2.2299567 | D29: ='Holdco Summary'!D64 -> 0.27360694 | E29: ='Holdco Summary'!E64 -> 1.6360186 | F29: ='Holdco Summary'!F64 -> 1.3369588
A30: =Hold_Long&"-Year Hold" -> 10-Year Hold | B30: ='Holdco Summary'!B85 -> 1.1974652 | C30: ='Holdco Summary'!C85 -> 3.4416659 | D30: ='Holdco Summary'!D85 -> 0.16481258 | E30: ='Holdco Summary'!E85 -> 2.4273687 | F30: ='Holdco Summary'!F85 -> 1.788103
A32: KS-PME vs S&P 500 (>1.00x = beat)
A33: Vehicle | B33: Base | C33: Bull | D33: Bear | E33: TSMC-Shock | F33: Expected
A34: =Hold_Short&"-Year Hold" -> 5-Year Hold | B34: ='Holdco Summary'!B41 -> 1.3709705 | C34: ='Holdco Summary'!C41 -> 2.2359733 | D34: ='Holdco Summary'!D41 -> 0.50995363 | E34: ='Holdco Summary'!E41 -> 1.7141726 | F34: ='Holdco Summary'!F41 -> 1.509549
A35: =Hold_Mid&"-Year Hold" -> 7-Year Hold | B35: ='Holdco Summary'!B62 -> 1.5942504 | C35: ='Holdco Summary'!C62 -> 3.244859 | D35: ='Holdco Summary'!D62 -> 0.39813147 | E35: ='Holdco Summary'!E62 -> 2.3806066 | F35: ='Holdco Summary'!F62 -> 1.9454381
A36: =Hold_Long&"-Year Hold" -> 10-Year Hold | B36: ='Holdco Summary'!B83 -> 2.0463331 | C36: ='Holdco Summary'!C83 -> 5.8814191 | D36: ='Holdco Summary'!D83 -> 0.28164613 | E36: ='Holdco Summary'!E83 -> 4.1480995 | F36: ='Holdco Summary'!F83 -> 3.0556665
A38: SLEEVE SIZING
A39: Sleeve | B39: Size ($M) | C39: % Holdco | D39: # Positions
A40: ='Holdco Summary'!A6 -> IQT-mirror (deep-tech) | B40: ='Holdco Summary'!B6 -> 250 | C40: ='Holdco Summary'!C6 -> 0.29761905 | D40: =COUNT(Assumptions!C18:C26) -> 9
A41: ='Holdco Summary'!A7 -> Weapons (physical layer) | B41: ='Holdco Summary'!B7 -> 390 | C41: ='Holdco Summary'!C7 -> 0.46428571 | D41: =COUNT('Weapons Sleeve'!C12:C20) -> 9
A42: ='Holdco Summary'!A8 -> Consumer / Value | B42: ='Holdco Summary'!B8 -> 200 | C42: ='Holdco Summary'!C8 -> 0.23809524 | D42: =COUNT('Consumer Sleeve'!C12:C20) -> 9
A43: Total holdco | B43: =SUM(B40:B42) -> 840 | C43: =SUM(C40:C42) -> 1 | D43: =SUM(D40:D42) -> 27
A45: ="SLEEVE GROSS MOIC — "&Hold_Short&"-YEAR HOLD (gross proceeds / committed)" -> SLEEVE GROSS MOIC — 5-YEAR HOLD (gross proceeds / committed)
A46: Sleeve | B46: Base | C46: Bull | D46: Bear | E46: TSMC-Shock | F46: Expected
A47: IQT-mirror | B47: ='Holdco Summary'!B28/IQT_Size -> 2.2633231 | C47: ='Holdco Summary'!C28/IQT_Size -> 3.6174457 | D47: ='Holdco Summary'!D28/IQT_Size -> 0.5051741 | E47: ='Holdco Summary'!E28/IQT_Size -> 3.6616253 | F47: ='Holdco Summary'!F28/IQT_Size -> 2.5478767
A48: Weapons | B48: ='Holdco Summary'!B29/Wpn_Size -> 2.3992931 | C48: ='Holdco Summary'!C29/Wpn_Size -> 3.9652435 | D48: ='Holdco Summary'!D29/Wpn_Size -> 1.1367545 | E48: ='Holdco Summary'!E29/Wpn_Size -> 3.9733723 | F48: ='Holdco Summary'!F29/Wpn_Size -> 2.8375118
A49: Consumer / Value | B49: ='Holdco Summary'!B30/Con_Size -> 2.5488224 | C49: ='Holdco Summary'!C30/Con_Size -> 4.7898646 | D49: ='Holdco Summary'!D30/Con_Size -> 0.86729407 | E49: ='Holdco Summary'!E30/Con_Size -> 0.50379982 | F49: ='Holdco Summary'!F30/Con_Size -> 2.5501003
A50: Holdco gross | B50: ='Holdco Summary'!B31/Holdco_Size -> 2.3944281 | C50: ='Holdco Summary'!C31/Holdco_Size -> 4.0580706 | D50: ='Holdco Summary'!D31/Holdco_Size -> 0.88462688 | E50: ='Holdco Summary'!E31/Holdco_Size -> 3.0545017 | F50: ='Holdco Summary'!F31/Holdco_Size -> 2.6828796
A52: ="SLEEVE GROSS MOIC — "&Hold_Mid&"-YEAR HOLD (gross proceeds / committed)" -> SLEEVE GROSS MOIC — 7-YEAR HOLD (gross proceeds / committed)
A53: Sleeve | B53: Base | C53: Bull | D53: Bear | E53: TSMC-Shock | F53: Expected
A54: IQT-mirror | B54: ='Holdco Summary'!B49/IQT_Size -> 3.1125231 | C54: ='Holdco Summary'!C49/IQT_Size -> 5.9880212 | D54: ='Holdco Summary'!D49/IQT_Size -> 0.40013475 | E54: ='Holdco Summary'!E49/IQT_Size -> 6.1697901 | F54: ='Holdco Summary'!F49/IQT_Size -> 3.8831294
A55: Weapons | B55: ='Holdco Summary'!B50/Wpn_Size -> 3.424834 | C55: ='Holdco Summary'!C50/Wpn_Size -> 7.0110454 | D55: ='Holdco Summary'!D50/Wpn_Size -> 1.1890351 | E55: ='Holdco Summary'!E50/Wpn_Size -> 7.0198185 | F55: ='Holdco Summary'!F50/Wpn_Size -> 4.5252647
A56: Consumer / Value | B56: ='Holdco Summary'!B51/Con_Size -> 3.6667525 | C56: ='Holdco Summary'!C51/Con_Size -> 8.9204975 | D56: ='Holdco Summary'!D51/Con_Size -> 0.82597273 | E56: ='Holdco Summary'!E51/Con_Size -> 0.38177091 | F56: ='Holdco Summary'!F51/Con_Size -> 4.0613245
A57: Holdco gross | B57: ='Holdco Summary'!B52/Holdco_Size -> 3.389484 | C57: ='Holdco Summary'!C52/Holdco_Size -> 7.1612054 | D57: ='Holdco Summary'!D52/Holdco_Size -> 0.8677999 | E57: ='Holdco Summary'!E52/Holdco_Size -> 5.1863464 | F57: ='Holdco Summary'!F52/Holdco_Size -> 4.2236911
A59: ="SLEEVE GROSS MOIC — "&Hold_Long&"-YEAR HOLD (gross proceeds / committed)" -> SLEEVE GROSS MOIC — 10-YEAR HOLD (gross proceeds / committed)
A60: Sleeve | B60: Base | C60: Bull | D60: Bear | E60: TSMC-Shock | F60: Expected
A61: IQT-mirror | B61: ='Holdco Summary'!B70/IQT_Size -> 5.0458237 | C61: ='Holdco Summary'!C70/IQT_Size -> 12.790789 | D61: ='Holdco Summary'!D70/IQT_Size -> 0.29585342 | E61: ='Holdco Summary'!E70/IQT_Size -> 13.672406 | F61: ='Holdco Summary'!F70/IQT_Size -> 7.5635568
A62: Weapons | B62: ='Holdco Summary'!B71/Wpn_Size -> 5.9219052 | C62: ='Holdco Summary'!C71/Wpn_Size -> 16.921765 | D62: ='Holdco Summary'!D71/Wpn_Size -> 1.2731274 | E62: ='Holdco Summary'!E71/Wpn_Size -> 16.919488 | F62: ='Holdco Summary'!F71/Wpn_Size -> 9.624191
A63: Consumer / Value | B63: ='Holdco Summary'!B72/Con_Size -> 6.3613104 | C63: ='Holdco Summary'!C72/Con_Size -> 22.895354 | D63: ='Holdco Summary'!D72/Con_Size -> 0.78797181 | E63: ='Holdco Summary'!E72/Con_Size -> 0.25493539 | F63: ='Holdco Summary'!F72/Con_Size -> 8.7428644
A64: Holdco gross | B64: ='Holdco Summary'!B73/Holdco_Size -> 5.765787 | C64: ='Holdco Summary'!C73/Holdco_Size -> 17.114591 | D64: ='Holdco Summary'!D73/Holdco_Size -> 0.86675881 | E64: ='Holdco Summary'!E73/Holdco_Size -> 11.985344 | F64: ='Holdco Summary'!F73/Holdco_Size -> 8.8010673
A66: SCENARIO PROBABILITY WEIGHTS (edit on Defense Supercycle tab)
B67: Base | C67: Bull | D67: Bear | E67: TSMC-Shock | F67: Total
A68: Probability | B68: ='Defense Supercycle'!B17 -> 0.45 | C68: ='Defense Supercycle'!B18 -> 0.25 | D68: ='Defense Supercycle'!B19 -> 0.15 | E68: ='Defense Supercycle'!B20 -> 0.15 | F68: =SUM(B68:E68) -> 1
A70: MODEL INTEGRITY CHECKS
A71: Check | B71: Model | C71: Target | D71: Status
A72: ="Holdco size = "&TEXT(Checks!$B$5,"$#,##0")&"M" -> Holdco size = $840M | B72: ='Holdco Summary'!B9 -> 840 | C72: =Checks!$B$5 -> 840 | D72: =IF(ABS(B72-C72)<0.001,"OK","CHECK") -> OK
A73: IQT-mirror deployed = committed | B73: =Assumptions!C27 -> 250 | C73: =Assumptions!B5 -> 250 | D73: =IF(ABS(B73-C73)<0.001,"OK","CHECK") -> OK
A74: Weapons deployed = committed | B74: ='Weapons Sleeve'!C21 -> 390 | C74: ='Weapons Sleeve'!B5 -> 390 | D74: =IF(ABS(B74-C74)<0.001,"OK","CHECK") -> OK
A75: Consumer deployed = committed | B75: ='Consumer Sleeve'!C21 -> 200 | C75: ='Consumer Sleeve'!B5 -> 200 | D75: =IF(ABS(B75-C75)<0.001,"OK","CHECK") -> OK
A76: Scenario probabilities = 100% | B76: ='Defense Supercycle'!B21 -> 1 | C76: 1 | D76: =IF(ABS(B76-C76)<0.001,"OK","CHECK") -> OK
A77: Strategic axis weights = 100% | B77: ='Defense Supercycle'!B10 -> 1 | C77: 1 | D77: =IF(ABS(B77-C77)<0.001,"OK","CHECK") -> OK
A78: IQT allocation % fund = 100% | B78: =Allocation!D14 -> 1 | C78: 1 | D78: =IF(ABS(B78-C78)<0.001,"OK","CHECK") -> OK
A79: Holdco 7-yr gross ties to sleeves (Expected) | B79: ='Holdco Summary'!F52 -> 3547.9005 | C79: ='Fund Economics'!F22+'Holdco Summary'!F50+'Holdco Summary'!F51 -> 3547.9005 | D79: =IF(ABS(B79-C79)<0.001,"OK","CHECK") -> OK
A80: Overall | D80: =IF(COUNTIF(D72:D79,"OK")=8,"ALL PASS","REVIEW") -> ALL PASS
A82: READ-THROUGH
A83: ="• Underwrite to Expected: 7-yr holdco net IRR "&TEXT('Holdco Summary'!F61,"0.0%")&" / "&TEXT('Holdco Summary'!F59,"0.00")&"x net MOIC; Base "&TEXT('Holdco Summary'!B61,"0.0%")&", Bear "&TEXT('Holdco Summary'!D61,"0.0%")&"." -> • Underwrite to Expected: 7-yr holdco net IRR 19.9% / 3.56x net MOIC; Base 16.5%, Bear -4.4%.
A84: ="• Thematic scoreboard: 7-yr Expected KS-PME vs Defense+Semis basket "&TEXT('Holdco Summary'!F64,"0.00")&"x (Base "&TEXT('Holdco Summary'!B64,"0.00")&"x) — >1.00x means the holdco beats owning ITA/SOXX." -> • Thematic scoreboard: 7-yr Expected KS-PME vs Defense+Semis basket 1.34x (Base 1.10x) — >1.00x means the holdco beats owning ITA/SOXX.
A85: • Bear case is a capital-loss outcome at every hold (net MOIC < 1.0x) — the downside is carried by the IQT seed names and Consumer; sizing, not the thesis, is the protection.
A86: ="• TSMC-Shock is a low-probability tail ("&TEXT('Defense Supercycle'!B20,"0%")&") that lifts Expected because the book is overweight US sovereign-chokepoint names; Consumer is the one sleeve hurt in that case." -> • TSMC-Shock is a low-probability tail (15%) that lifts Expected because the book is overweight US sovereign-chokepoint names; Consumer is the one sleeve hurt in that case.
A87: • Six of nine IQT entry marks and most Weapons marks are estimates — see Assumptions col J / Weapons Sleeve col J. Confirm via primary diligence before IC vote.

Sheet Holdco Summary
A1: LEVIATHAN — CORE PE HOLDCO ($840M) — TRIPARTITE ROLL-UP
A2: Three sub-funds rolled up to a blended holdco return. Blue = lever. All three sleeves — IQT-mirror, Weapons, Consumer/Value — flow in bottom-up. Expected = probability-weighted net (consistent with Fund Economics).
A3: =Checks!$B$3 -> MODEL INTEGRITY: ALL 21 CHECKS PASS
A4: HOLDCO STRUCTURE & SIZING
A5: Sub-fund | B5: Size ($M) | C5: % Holdco | D5: Return driver | E5: Duration | F5: Role
A6: IQT-mirror (deep-tech) | B6: 250 | C6: =B6/$B$9 -> 0.29761905 | D6: Onshoring capex + Taiwan tail | E6: Longest | F6: Convex optionality / tail hedge
A7: Weapons (physical layer) | B7: 390 | C7: =B7/$B$9 -> 0.46428571 | D7: Defense opex — budgets, conflict | E7: Medium | F7: Cash-generative supercycle core
A8: Consumer / Value | B8: 200 | C8: =B8/$B$9 -> 0.23809524 | D8: Consumer cycle + DTC/wellness | E8: Shortest | F8: Ballast + near-term DPI engine
A9: TOTAL (must = $840M) | B9: =SUM(B6:B8) -> 840 | C9: =SUM(C6:C8) -> 1
A10: IQT-mirror: Substrate, EUV Tech, ThinTronics, EdgeCortix, Syntiant, Infleqtion, Diraq, Mueon, DefendEye
A11: Weapons: Epirus, Elta, Israel Aerospace Industries, Saronic, Helicon Chemical, Applied Research Associates, Heckler & Koch, The Ellwood Group, Superior & Grand Valley
A12: Consumer/Value: Quince, Thrive Market, The Farmer's Dog, Whoop, Plunge, Made In Cookware, Polymarket, Goat Group, Stripe
A14: ="SLEEVE RETURN SUMMARY — implied gross IRR on checks at the "&Hold_Short&"-yr hold, net of dilution (live links to the sleeve tabs)" -> SLEEVE RETURN SUMMARY — implied gross IRR on checks at the 5-yr hold, net of dilution (live links to the sleeve tabs)
A15: Sleeve | B15: Base | C15: Bull | D15: Bear | E15: TSMC-Shock
A16: IQT-mirror (bottom-up, live) | B16: ='Portfolio Returns'!E15 -> 0.17746854 | C16: ='Portfolio Returns'!H15 -> 0.29324379 | D16: ='Portfolio Returns'!K15 -> -0.12765512 | E16: ='Portfolio Returns'!N15 -> 0.29638733
A17: Weapons (bottom-up, live) | B17: ='Weapons Sleeve'!E34 -> 0.19128771 | C17: ='Weapons Sleeve'!H34 -> 0.31720683 | D17: ='Weapons Sleeve'!K34 -> 0.025966861 | E17: ='Weapons Sleeve'!N34 -> 0.31774644
A18: Consumer / Value (bottom-up, live) | B18: ='Consumer Sleeve'!E34 -> 0.20577955 | C18: ='Consumer Sleeve'!H34 -> 0.36793243 | D18: ='Consumer Sleeve'!K34 -> -0.028073832 | E18: ='Consumer Sleeve'!N34 -> -0.12813027
A19: Memo only — these rows are live reads of the sleeve tabs (gross IRR on checks at the short hold). The sleeve tabs are the source of truth; nothing downstream references this block.
A20: BENCHMARKS (KS-PME > 1.0x = beat)
A21: S&P 500 (SPX) total-return CAGR | B21: =SPX_CAGR -> 0.09
A22: Nasdaq-100 (NDX) total-return CAGR | B22: =NDX_CAGR -> 0.13
A23: Defense+Semis thematic basket CAGR (ITA/SOXX blend) | B23: 0.15
A24: Forward-tempered: 50/50 ITA/SOXX trailing 5yr is ~26% (ITA 18.2% / SOXX 34.5% to Jun-26), inflated by the AI+rearmament run; 15% forward. See Macro Overlay for comps & drivers.
A26: =Hold_Short&"-YEAR HOLDCO ROLL-UP" -> 5-YEAR HOLDCO ROLL-UP
A27: Line item ($M) | B27: Base | C27: Bull | D27: Bear | E27: TSMC-Shock | F27: Expected
A28: IQT-mirror gross | B28: ='Fund Economics'!B6 -> 565.83078 | C28: ='Fund Economics'!C6 -> 904.36142 | D28: ='Fund Economics'!D6 -> 126.29353 | E28: ='Fund Economics'!E6 -> 915.40631 | F28: ='Fund Economics'!F6 -> 636.96918
A29: Weapons gross | B29: ='Weapons Sleeve'!C34 -> 935.7243 | C29: ='Weapons Sleeve'!F34 -> 1546.445 | D29: ='Weapons Sleeve'!I34 -> 443.33424 | E29: ='Weapons Sleeve'!L34 -> 1549.6152 | F29: =B29*P_Base+C29*P_Bull+D29*P_Bear+E29*P_Shock -> 1106.6296
A30: Consumer/Value gross | B30: ='Consumer Sleeve'!C34 -> 509.76448 | C30: ='Consumer Sleeve'!F34 -> 957.97292 | D30: ='Consumer Sleeve'!I34 -> 173.45881 | E30: ='Consumer Sleeve'!L34 -> 100.75996 | F30: =B30*P_Base+C30*P_Bull+D30*P_Bear+E30*P_Shock -> 510.02006
A31: HOLDCO gross proceeds | B31: =B28+B29+B30 -> 2011.3196 | C31: =C28+C29+C30 -> 3408.7793 | D31: =D28+D29+D30 -> 743.08658 | E31: =E28+E29+E30 -> 2565.7815 | F31: =F28+F29+F30 -> 2253.6188
A32: (-) Return of capital | B32: =-Holdco_Size -> -840 | C32: =-Holdco_Size -> -840 | D32: =-Holdco_Size -> -840 | E32: =-Holdco_Size -> -840 | F32: =B32*P_Base+C32*P_Bull+D32*P_Bear+E32*P_Shock -> -840
A33: (-) Preferred (8% comp.) | B33: =-Holdco_Size*((1+Pref)^Hold_Short-1) -> -394.23558 | C33: =-Holdco_Size*((1+Pref)^Hold_Short-1) -> -394.23558 | D33: =-Holdco_Size*((1+Pref)^Hold_Short-1) -> -394.23558 | E33: =-Holdco_Size*((1+Pref)^Hold_Short-1) -> -394.23558 | F33: =B33*P_Base+C33*P_Bull+D33*P_Bear+E33*P_Shock -> -394.23558
A34: Profit above pref | B34: =MAX(0,B31+B32+B33) -> 777.08398 | C34: =MAX(0,C31+C32+C33) -> 2174.5437 | D34: =MAX(0,D31+D32+D33) -> 0 | E34: =MAX(0,E31+E32+E33) -> 1331.5459 | F34: =B34*P_Base+C34*P_Bull+D34*P_Bear+E34*P_Shock -> 1093.0556
A35: (-) Carry (20%) | B35: =-Carry*B34 -> -155.4168 | C35: =-Carry*C34 -> -434.90874 | D35: =-Carry*D34 -> 0 | E35: =-Carry*E34 -> -266.30917 | F35: =B35*P_Base+C35*P_Bull+D35*P_Bear+E35*P_Shock -> -218.61112
A36: (-) Mgmt fees (2%/yr) | B36: =-Holdco_Size*Mgmt_Fee*Hold_Short -> -84 | C36: =-Holdco_Size*Mgmt_Fee*Hold_Short -> -84 | D36: =-Holdco_Size*Mgmt_Fee*Hold_Short -> -84 | E36: =-Holdco_Size*Mgmt_Fee*Hold_Short -> -84 | F36: =B36*P_Base+C36*P_Bull+D36*P_Bear+E36*P_Shock -> -84
A37: NET proceeds to LP | B37: =B31+B35+B36 -> 1771.9028 | C37: =C31+C35+C36 -> 2889.8706 | D37: =D31+D35+D36 -> 659.08658 | E37: =E31+E35+E36 -> 2215.4723 | F37: =B37*P_Base+C37*P_Bull+D37*P_Bear+E37*P_Shock -> 1951.0077
A38: Net MOIC | B38: =B37/Holdco_Size -> 2.1094081 | C38: =C37/Holdco_Size -> 3.4403221 | D38: =D37/Holdco_Size -> 0.78462688 | E38: =E37/Holdco_Size -> 2.637467 | F38: =F37/Holdco_Size -> 2.3226282
A39: Net DPI (=TVPI at exit) | B39: =B37/Holdco_Size -> 2.1094081 | C39: =C37/Holdco_Size -> 3.4403221 | D39: =D37/Holdco_Size -> 0.78462688 | E39: =E37/Holdco_Size -> 2.637467 | F39: =F37/Holdco_Size -> 2.3226282
A40: Net IRR | B40: =IF((B37/Holdco_Size)<=0,-1,(B37/Holdco_Size)^(1/Hold_Short)-1) -> 0.16099973 | C40: =IF((C37/Holdco_Size)<=0,-1,(C37/Holdco_Size)^(1/Hold_Short)-1) -> 0.28032381 | D40: =IF((D37/Holdco_Size)<=0,-1,(D37/Holdco_Size)^(1/Hold_Short)-1) -> -0.047351614 | E40: =IF((E37/Holdco_Size)<=0,-1,(E37/Holdco_Size)^(1/Hold_Short)-1) -> 0.21405233 | F40: =IF((F37/Holdco_Size)<=0,-1,(F37/Holdco_Size)^(1/Hold_Short)-1) -> 0.18357543
A41: KS-PME vs SPX | B41: =B38/(1+SPX_CAGR)^Hold_Short -> 1.3709705 | C41: =C38/(1+SPX_CAGR)^Hold_Short -> 2.2359733 | D41: =D38/(1+SPX_CAGR)^Hold_Short -> 0.50995363 | E41: =E38/(1+SPX_CAGR)^Hold_Short -> 1.7141726 | F41: =F38/(1+SPX_CAGR)^Hold_Short -> 1.509549
A42: KS-PME vs NDX | B42: =B38/(1+NDX_CAGR)^Hold_Short -> 1.1449022 | C42: =C38/(1+NDX_CAGR)^Hold_Short -> 1.867269 | D42: =D38/(1+NDX_CAGR)^Hold_Short -> 0.42586403 | E42: =E38/(1+NDX_CAGR)^Hold_Short -> 1.4315114 | F42: =F38/(1+NDX_CAGR)^Hold_Short -> 1.2606296
A43: KS-PME vs Defense+Semis basket | B43: =B38/(1+Basket_CAGR)^Hold_Short -> 1.0487486 | C43: =C38/(1+Basket_CAGR)^Hold_Short -> 1.7104481 | D43: =D38/(1+Basket_CAGR)^Hold_Short -> 0.39009823 | E43: =E38/(1+Basket_CAGR)^Hold_Short -> 1.3112872 | F43: =F38/(1+Basket_CAGR)^Hold_Short -> 1.1547567
A44: Direct Alpha vs basket (ann.) | B44: =IF((B38/(1+Basket_CAGR)^Hold_Short)<=0,-1,(B38/(1+Basket_CAGR)^Hold_Short)^(1/Hold_Short)-1) -> 0.0095649859 | C44: =IF((C38/(1+Basket_CAGR)^Hold_Short)<=0,-1,(C38/(1+Basket_CAGR)^Hold_Short)^(1/Hold_Short)-1) -> 0.11332505 | D44: =IF((D38/(1+Basket_CAGR)^Hold_Short)<=0,-1,(D38/(1+Basket_CAGR)^Hold_Short)^(1/Hold_Short)-1) -> -0.1716101 | E44: =IF((E38/(1+Basket_CAGR)^Hold_Short)<=0,-1,(E38/(1+Basket_CAGR)^Hold_Short)^(1/Hold_Short)-1) -> 0.055697679 | F44: =IF((F38/(1+Basket_CAGR)^Hold_Short)<=0,-1,(F38/(1+Basket_CAGR)^Hold_Short)^(1/Hold_Short)-1) -> 0.029196024
A47: =Hold_Mid&"-YEAR HOLDCO ROLL-UP" -> 7-YEAR HOLDCO ROLL-UP
A48: Line item ($M) | B48: Base | C48: Bull | D48: Bear | E48: TSMC-Shock | F48: Expected
A49: IQT-mirror gross | B49: ='Fund Economics'!B22 -> 778.13077 | C49: ='Fund Economics'!C22 -> 1497.0053 | D49: ='Fund Economics'!D22 -> 100.03369 | E49: ='Fund Economics'!E22 -> 1542.4475 | F49: ='Fund Economics'!F22 -> 970.78235
A50: Weapons gross | B50: ='Weapons Sleeve'!C48 -> 1335.6853 | C50: ='Weapons Sleeve'!F48 -> 2734.3077 | D50: ='Weapons Sleeve'!I48 -> 463.72368 | E50: ='Weapons Sleeve'!L48 -> 2737.7292 | F50: =B50*P_Base+C50*P_Bull+D50*P_Bear+E50*P_Shock -> 1764.8532
A51: Consumer/Value gross | B51: ='Consumer Sleeve'!C48 -> 733.35049 | C51: ='Consumer Sleeve'!F48 -> 1784.0995 | D51: ='Consumer Sleeve'!I48 -> 165.19455 | E51: ='Consumer Sleeve'!L48 -> 76.354183 | F51: =B51*P_Base+C51*P_Bull+D51*P_Bear+E51*P_Shock -> 812.26491
A52: HOLDCO gross proceeds | B52: =B49+B50+B51 -> 2847.1665 | C52: =C49+C50+C51 -> 6015.4125 | D52: =D49+D50+D51 -> 728.95192 | E52: =E49+E50+E51 -> 4356.5309 | F52: =F49+F50+F51 -> 3547.9005
A53: (-) Return of capital | B53: =-Holdco_Size -> -840 | C53: =-Holdco_Size -> -840 | D53: =-Holdco_Size -> -840 | E53: =-Holdco_Size -> -840 | F53: =B53*P_Base+C53*P_Bull+D53*P_Bear+E53*P_Shock -> -840
A54: (-) Preferred (8% comp.) | B54: =-Holdco_Size*((1+Pref)^Hold_Mid-1) -> -599.61239 | C54: =-Holdco_Size*((1+Pref)^Hold_Mid-1) -> -599.61239 | D54: =-Holdco_Size*((1+Pref)^Hold_Mid-1) -> -599.61239 | E54: =-Holdco_Size*((1+Pref)^Hold_Mid-1) -> -599.61239 | F54: =B54*P_Base+C54*P_Bull+D54*P_Bear+E54*P_Shock -> -599.61239
A55: Profit above pref | B55: =MAX(0,B52+B53+B54) -> 1407.5541 | C55: =MAX(0,C52+C53+C54) -> 4575.8001 | D55: =MAX(0,D52+D53+D54) -> 0 | E55: =MAX(0,E52+E53+E54) -> 2916.9186 | F55: =B55*P_Base+C55*P_Bull+D55*P_Bear+E55*P_Shock -> 2214.8872
A56: (-) Carry (20%) | B56: =-Carry*B55 -> -281.51083 | C56: =-Carry*C55 -> -915.16003 | D56: =-Carry*D55 -> 0 | E56: =-Carry*E55 -> -583.38371 | F56: =B56*P_Base+C56*P_Bull+D56*P_Bear+E56*P_Shock -> -442.97744
A57: (-) Mgmt fees (2%/yr) | B57: =-Holdco_Size*Mgmt_Fee*Hold_Mid -> -117.6 | C57: =-Holdco_Size*Mgmt_Fee*Hold_Mid -> -117.6 | D57: =-Holdco_Size*Mgmt_Fee*Hold_Mid -> -117.6 | E57: =-Holdco_Size*Mgmt_Fee*Hold_Mid -> -117.6 | F57: =B57*P_Base+C57*P_Bull+D57*P_Bear+E57*P_Shock -> -117.6
A58: NET proceeds to LP | B58: =B52+B56+B57 -> 2448.0557 | C58: =C52+C56+C57 -> 4982.6525 | D58: =D52+D56+D57 -> 611.35192 | E58: =E52+E56+E57 -> 3655.5472 | F58: =B58*P_Base+C58*P_Bull+D58*P_Bear+E58*P_Shock -> 2987.3231
A59: Net MOIC | B59: =B58/Holdco_Size -> 2.914352 | C59: =C58/Holdco_Size -> 5.9317292 | D59: =D58/Holdco_Size -> 0.7277999 | E59: =E58/Holdco_Size -> 4.3518419 | F59: =F58/Holdco_Size -> 3.556337
A60: Net DPI (=TVPI at exit) | B60: =B58/Holdco_Size -> 2.914352 | C60: =C58/Holdco_Size -> 5.9317292 | D60: =D58/Holdco_Size -> 0.7277999 | E60: =E58/Holdco_Size -> 4.3518419 | F60: =F58/Holdco_Size -> 3.556337
A61: Net IRR | B61: =IF((B58/Holdco_Size)<=0,-1,(B58/Holdco_Size)^(1/Hold_Mid)-1) -> 0.16509984 | C61: =IF((C58/Holdco_Size)<=0,-1,(C58/Holdco_Size)^(1/Hold_Mid)-1) -> 0.28959836 | D61: =IF((D58/Holdco_Size)<=0,-1,(D58/Holdco_Size)^(1/Hold_Mid)-1) -> -0.044375165 | E61: =IF((E58/Holdco_Size)<=0,-1,(E58/Holdco_Size)^(1/Hold_Mid)-1) -> 0.23378367 | F61: =IF((F58/Holdco_Size)<=0,-1,(F58/Holdco_Size)^(1/Hold_Mid)-1) -> 0.19871158
A62: KS-PME vs SPX | B62: =B59/(1+SPX_CAGR)^Hold_Mid -> 1.5942504 | C62: =C59/(1+SPX_CAGR)^Hold_Mid -> 3.244859 | D62: =D59/(1+SPX_CAGR)^Hold_Mid -> 0.39813147 | E62: =E59/(1+SPX_CAGR)^Hold_Mid -> 2.3806066 | F62: =F59/(1+SPX_CAGR)^Hold_Mid -> 1.9454381
A63: KS-PME vs NDX | B63: =B59/(1+NDX_CAGR)^Hold_Mid -> 1.2387763 | C63: =C59/(1+NDX_CAGR)^Hold_Mid -> 2.5213446 | D63: =D59/(1+NDX_CAGR)^Hold_Mid -> 0.3093591 | E63: =E59/(1+NDX_CAGR)^Hold_Mid -> 1.8497967 | F63: =F59/(1+NDX_CAGR)^Hold_Mid -> 1.5116589
A64: KS-PME vs Defense+Semis basket | B64: =B59/(1+Basket_CAGR)^Hold_Mid -> 1.0956129 | C64: =C59/(1+Basket_CAGR)^Hold_Mid -> 2.2299567 | D64: =D59/(1+Basket_CAGR)^Hold_Mid -> 0.27360694 | E64: =E59/(1+Basket_CAGR)^Hold_Mid -> 1.6360186 | F64: =F59/(1+Basket_CAGR)^Hold_Mid -> 1.3369588
A65: Direct Alpha vs basket (ann.) | B65: =IF((B59/(1+Basket_CAGR)^Hold_Mid)<=0,-1,(B59/(1+Basket_CAGR)^Hold_Mid)^(1/Hold_Mid)-1) -> 0.013130299 | C65: =IF((C59/(1+Basket_CAGR)^Hold_Mid)<=0,-1,(C59/(1+Basket_CAGR)^Hold_Mid)^(1/Hold_Mid)-1) -> 0.12138988 | D65: =IF((D59/(1+Basket_CAGR)^Hold_Mid)<=0,-1,(D59/(1+Basket_CAGR)^Hold_Mid)^(1/Hold_Mid)-1) -> -0.16902188 | E65: =IF((E59/(1+Basket_CAGR)^Hold_Mid)<=0,-1,(E59/(1+Basket_CAGR)^Hold_Mid)^(1/Hold_Mid)-1) -> 0.072855361 | F65: =IF((F59/(1+Basket_CAGR)^Hold_Mid)<=0,-1,(F59/(1+Basket_CAGR)^Hold_Mid)^(1/Hold_Mid)-1) -> 0.042357895
A68: =Hold_Long&"-YEAR HOLDCO ROLL-UP" -> 10-YEAR HOLDCO ROLL-UP
A69: Line item ($M) | B69: Base | C69: Bull | D69: Bear | E69: TSMC-Shock | F69: Expected
A70: IQT-mirror gross | B70: ='Fund Economics'!B38 -> 1261.4559 | C70: ='Fund Economics'!C38 -> 3197.6972 | D70: ='Fund Economics'!D38 -> 73.963354 | E70: ='Fund Economics'!E38 -> 3418.1015 | F70: ='Fund Economics'!F38 -> 1890.8892
A71: Weapons gross | B71: ='Weapons Sleeve'!C62 -> 2309.543 | C71: ='Weapons Sleeve'!F62 -> 6599.4885 | D71: ='Weapons Sleeve'!I62 -> 496.51969 | E71: ='Weapons Sleeve'!L62 -> 6598.6003 | F71: =B71*P_Base+C71*P_Bull+D71*P_Bear+E71*P_Shock -> 3753.4345
A72: Consumer/Value gross | B72: ='Consumer Sleeve'!C62 -> 1272.2621 | C72: ='Consumer Sleeve'!F62 -> 4579.0709 | D72: ='Consumer Sleeve'!I62 -> 157.59436 | E72: ='Consumer Sleeve'!L62 -> 50.987077 | F72: =B72*P_Base+C72*P_Bull+D72*P_Bear+E72*P_Shock -> 1748.5729
A73: HOLDCO gross proceeds | B73: =B70+B71+B72 -> 4843.2611 | C73: =C70+C71+C72 -> 14376.257 | D73: =D70+D71+D72 -> 728.0774 | E73: =E70+E71+E72 -> 10067.689 | F73: =F70+F71+F72 -> 7392.8966
A74: (-) Return of capital | B74: =-Holdco_Size -> -840 | C74: =-Holdco_Size -> -840 | D74: =-Holdco_Size -> -840 | E74: =-Holdco_Size -> -840 | F74: =B74*P_Base+C74*P_Bull+D74*P_Bear+E74*P_Shock -> -840
A75: (-) Preferred (8% comp.) | B75: =-Holdco_Size*((1+Pref)^Hold_Long-1) -> -973.497 | C75: =-Holdco_Size*((1+Pref)^Hold_Long-1) -> -973.497 | D75: =-Holdco_Size*((1+Pref)^Hold_Long-1) -> -973.497 | E75: =-Holdco_Size*((1+Pref)^Hold_Long-1) -> -973.497 | F75: =B75*P_Base+C75*P_Bull+D75*P_Bear+E75*P_Shock -> -973.497
A76: Profit above pref | B76: =MAX(0,B73+B74+B75) -> 3029.7641 | C76: =MAX(0,C73+C74+C75) -> 12562.76 | D76: =MAX(0,D73+D74+D75) -> 0 | E76: =MAX(0,E73+E74+E75) -> 8254.1918 | F76: =B76*P_Base+C76*P_Bull+D76*P_Bear+E76*P_Shock -> 5742.2125
A77: (-) Carry (20%) | B77: =-Carry*B76 -> -605.95281 | C77: =-Carry*C76 -> -2512.5519 | D77: =-Carry*D76 -> 0 | E77: =-Carry*E76 -> -1650.8384 | F77: =B77*P_Base+C77*P_Bull+D77*P_Bear+E77*P_Shock -> -1148.4425
A78: (-) Mgmt fees (2%/yr) | B78: =-Holdco_Size*Mgmt_Fee*Hold_Long -> -168 | C78: =-Holdco_Size*Mgmt_Fee*Hold_Long -> -168 | D78: =-Holdco_Size*Mgmt_Fee*Hold_Long -> -168 | E78: =-Holdco_Size*Mgmt_Fee*Hold_Long -> -168 | F78: =B78*P_Base+C78*P_Bull+D78*P_Bear+E78*P_Shock -> -168
A79: NET proceeds to LP | B79: =B73+B77+B78 -> 4069.3083 | C79: =C73+C77+C78 -> 11695.705 | D79: =D73+D77+D78 -> 560.0774 | E79: =E73+E77+E78 -> 8248.8505 | F79: =B79*P_Base+C79*P_Bull+D79*P_Bear+E79*P_Shock -> 6076.4541
A80: Net MOIC | B80: =B79/Holdco_Size -> 4.8444146 | C80: =C79/Holdco_Size -> 13.923458 | D80: =D79/Holdco_Size -> 0.66675881 | E80: =E79/Holdco_Size -> 9.8200601 | F80: =F79/Holdco_Size -> 7.2338739
A81: Net DPI (=TVPI at exit) | B81: =B79/Holdco_Size -> 4.8444146 | C81: =C79/Holdco_Size -> 13.923458 | D81: =D79/Holdco_Size -> 0.66675881 | E81: =E79/Holdco_Size -> 9.8200601 | F81: =F79/Holdco_Size -> 7.2338739
A82: Net IRR | B82: =IF((B79/Holdco_Size)<=0,-1,(B79/Holdco_Size)^(1/Hold_Long)-1) -> 0.17091166 | C82: =IF((C79/Holdco_Size)<=0,-1,(C79/Holdco_Size)^(1/Hold_Long)-1) -> 0.30129185 | D82: =IF((D79/Holdco_Size)<=0,-1,(D79/Holdco_Size)^(1/Hold_Long)-1) -> -0.039722227 | E82: =IF((E79/Holdco_Size)<=0,-1,(E79/Holdco_Size)^(1/Hold_Long)-1) -> 0.25664155 | F82: =IF((F79/Holdco_Size)<=0,-1,(F79/Holdco_Size)^(1/Hold_Long)-1) -> 0.21881304
A83: KS-PME vs SPX | B83: =B80/(1+SPX_CAGR)^Hold_Long -> 2.0463331 | C83: =C80/(1+SPX_CAGR)^Hold_Long -> 5.8814191 | D83: =D80/(1+SPX_CAGR)^Hold_Long -> 0.28164613 | E83: =E80/(1+SPX_CAGR)^Hold_Long -> 4.1480995 | F83: =F80/(1+SPX_CAGR)^Hold_Long -> 3.0556665
A84: KS-PME vs NDX | B84: =B80/(1+NDX_CAGR)^Hold_Long -> 1.4271081 | C84: =C80/(1+NDX_CAGR)^Hold_Long -> 4.1016885 | D84: =D80/(1+NDX_CAGR)^Hold_Long -> 0.19641938 | E84: =E80/(1+NDX_CAGR)^Hold_Long -> 2.8928753 | F84: =F80/(1+NDX_CAGR)^Hold_Long -> 2.131015
A85: KS-PME vs Defense+Semis basket | B85: =B80/(1+Basket_CAGR)^Hold_Long -> 1.1974652 | C85: =C80/(1+Basket_CAGR)^Hold_Long -> 3.4416659 | D85: =D80/(1+Basket_CAGR)^Hold_Long -> 0.16481258 | E85: =E80/(1+Basket_CAGR)^Hold_Long -> 2.4273687 | F85: =F80/(1+Basket_CAGR)^Hold_Long -> 1.788103
A86: Direct Alpha vs basket (ann.) | B86: =IF((B80/(1+Basket_CAGR)^Hold_Long)<=0,-1,(B80/(1+Basket_CAGR)^Hold_Long)^(1/Hold_Long)-1) -> 0.018184051 | C86: =IF((C80/(1+Basket_CAGR)^Hold_Long)<=0,-1,(C80/(1+Basket_CAGR)^Hold_Long)^(1/Hold_Long)-1) -> 0.13155813 | D86: =IF((D80/(1+Basket_CAGR)^Hold_Long)<=0,-1,(D80/(1+Basket_CAGR)^Hold_Long)^(1/Hold_Long)-1) -> -0.16497585 | E86: =IF((E80/(1+Basket_CAGR)^Hold_Long)<=0,-1,(E80/(1+Basket_CAGR)^Hold_Long)^(1/Hold_Long)-1) -> 0.092731781 | F86: =IF((F80/(1+Basket_CAGR)^Hold_Long)<=0,-1,(F80/(1+Basket_CAGR)^Hold_Long)^(1/Hold_Long)-1) -> 0.059837429
A89: READ-THROUGH
A90: • The holdco is a tripartite barbell: two defense-supercycle sleeves (digital enablers + physical effectors) + a consumer/value ballast that is uncorrelated and carries the near-term DPI.
A91: • Judge the IQT sleeve on its marginal contribution here — convexity and a Taiwan/TSMC hedge — not on a standalone 'beat the Nasdaq' test. That test lives at the holdco level.
A92: • The KS-PME vs the Defense+Semis basket is the real scoreboard: it asks whether the holdco captures the sovereign-capital trend earlier and cheaper than the public thematic ETFs everyone else uses.
A93: • All three sleeves — IQT-mirror, Weapons, and Consumer/Value — are now modeled bottom-up from individual holdings; only the SPX/NDX/thematic-basket benchmarks remain top-down inputs.

Sheet Macro Overlay
A1: MACRO, GEOPOLITICAL & DEFENSE-SUPERCYCLE OVERLAY
A2: Grounds the sleeve return assumptions in current comps and the geopolitical/macro picture. Figures as of ~Jun-Sep 2026; sourced below.
A4: 1 | PUBLIC & PRIVATE COMPS GROUNDING THE SLEEVE ASSUMPTIONS
A5: Comparable | B5: Metric | C5: Value | D5: Note / relevance
A6: ITA (US Aero & Defense ETF) | B6: Total return 1/5/10-yr | C6: 29.3% / 18.2% / 15.7% | D6: Defense supercycle already priced into public primes (as of Jun-26)
A7: SOXX (Semiconductor ETF) | B7: Total return 1/5/10-yr | C7: 169.6% / 34.5% / 36.6% | D7: AI-driven surge; forward mean-reversion risk off a huge base
A8: 50/50 ITA/SOXX basket | B8: Trailing 5-yr blend | C8: ~26.3% | D8: Thematic hurdle; model uses 15% FORWARD (tempered)
A9: SPX / NDX | B9: Forward CAGR (model) | C9: 9.0% / 13.0% | D9: Broad-market floor benchmarks
A10: Rheinmetall (RHM) | B10: Rev growth / EV-Rev / EV-EBITDA | C10: 40% / 4.0x / 17.3x | D10: European rearmament bellwether; $54B cap
A11: AeroVironment (AVAV) | B11: TTM rev / YoY | C11: $1.61B / +117% | D11: Drones/loitering munitions (incl. M&A); supercycle demand
A12: L3Harris (LHX) | B12: EV-Rev / EV-EBITDA | C12: 2.6x / 15.1x | D12: Established prime multiple anchor
A13: Saronic (private) | B13: Valuation / 2025 rev | C13: $9.25B / $200M (+1,500%) | D13: Naval autonomy hypergrowth (Series D, Mar-26)
A14: Anduril (private) | B14: Valuation / 2025 rev | C14: $61B / $2.2B (+120%) | D14: Scale-up reference; $20B Army ceiling (Mar-26)
A15: Epirus (private) | B15: Directed energy / HPM | C15: Growth-stage | D15: Counter-drone; Weapons-sleeve holding
A16: Grounded sleeve assumptions (Base/Bull/Bear/Shock gross CAGR): Weapons 22/34/5/32% (original sleeve memo, reference only — model runs bottom-up per name with the munitions/FMS overlay); Consumer modeled bottom-up per-name, two now market-priced via Forge secondary (Quince 28/45/2/-18%, Whoop 27/42/-3/-16%, The Farmer's Dog 22/34/10/-5% @ $3.76B Forge-implied, Made In Cookware 14/26/-10/-14% est., Thrive Market 7/16/-5/-8% @ ~$945M Forge-implied (down from $1.29B Series C), Plunge 20/50/-22/-28% est.); thematic basket 15% fwd. IQT-mirror is bottom-up.
A18: 2 | DEFENSE SUPERCYCLE DRIVERS
A19: • NATO 5%-of-GDP pledge (Hague summit, Jun-2025): 3.5% core defense + 1.5% defense-related, on a path to 2035 — a structural, decade-long step-up, not a cyclical bump.
A20: • European allies + Canada raised defense spending ~20% in 2025 alone; all allies now above the old 2% floor. Rheinmetall growing 40%/yr is the bellwether.
A21: • Munitions/energetics replenishment (Ukraine drawdown) + naval autonomy (Replicator) + counter-drone are the fastest-growing demand pools — directly the Weapons sleeve (Helicon, Saronic, Epirus).
A23: 3 | CHINA & GEOPOLITICAL PICTURE
A24: • China official defense budget ~1.78T yuan (~$245B) for 2025, +7.2% YoY (widely cited; pre-cutoff — confirm 2026 figure) — sustained double-digit real modernization for a decade.
A25: • 'Davidson window' (PLA capability vs. Taiwan by 2027) frames the tail-risk timeline the TSMC-Shock scenario models — the single point of failure is TSMC leading-edge capacity.
A26: • US-China tech decoupling: export controls on advanced semis/tooling, entity-list expansion, and reshoring incentives are the policy tailwind behind the IQT-mirror sleeve's sovereign-chokepoint names.
A28: 4 | GLOBAL MACRO BACKDROP
A29: • Rates/exit markets: the Fed path drives PE exit windows and long-duration deep-tech valuations most — a higher-for-longer regime compresses the IQT sleeve's terminal multiples and delays exits (lengthens duration, lowers DPI timing).
A30: • USD & inflation: a decoupling/Taiwan shock is inflationary (supply shock) and USD-volatile — negative for the Consumer sleeve overall, though now modeled per-name on the Consumer Sleeve tab: import/hardware-exposed names (Quince, Whoop, Made In, Plunge) take the sharper Shock hit via COGS/chip-supply, while staple/subscription names (Farmer's Dog, Thrive Market) are more defensive; Goat Group (discretionary resale demand + cross-border logistics) also skews Shock-worse-than-Bear, while Stripe (fee-based payments infra, not import-exposed) skews milder, in line with its tighter Bear/Shock spread on the Consumer Sleeve tab.
... A39: 5 | DRIVER x SLEEVE MAPPING (direction of impact)
A40: Driver | B40: IQT-mirror | C40: Weapons | D40: Consumer / Value
A41: NATO / EU rearmament | B41: + | C41: + + | D41: 0
A42: US budget / Replicator / munitions | B42: + | C42: + + | D42: 0
A43: Classified / black-budget growth (+14% IC) | B43: + + (IQT = CIA arm) | C43: + + | D43: 0
A44: China modernization / decoupling | B44: + + | C44: + | D44: -
A45: Taiwan / TSMC shock | B45: + + (convex) | C45: + + (conflict demand) | D45: - (inflation/spend)
A46: CHIPS / reshoring capital | B46: + + | C46: + | D46: 0
A47: Higher-for-longer rates | B47: - (long-duration) | C47: - / 0 | D47: -
A48: USD strength / inflation | B48: 0 / - | C48: 0 | D48: - -
A49: Consumer spending cycle | B49: 0 | C49: 0 | D49: + + (primary driver)
A51: 6 | KEY TAKEAWAY
A52: • The supercycle is already loudly priced in PUBLIC comps (ITA +29% 1yr, SOXX +170% 1yr) — so the edge is NOT the theme being undiscovered; it is capturing it at PRIVATE / VC-stage entry before the public re-rate. That is why the scoreboard is KS-PME vs the ITA/SOXX basket, not vs SPX.
A53: • The barbell's logic: Weapons + IQT are both long the geopolitical supercycle (opex + capex legs) and both convex to a Taiwan/TSMC shock; Consumer is the uncorrelated ballast that carries near-term DPI and is the one sleeve hurt by the shock. Net holdco is long the supercycle with a spending-cycle diversifier.
A54: • Biggest swing factors: (1) Weapons CAGR (largest sleeve), (2) the thematic-basket hurdle, (3) the rate path via IQT exit timing. All are levers on the Holdco Summary / Assumptions / PME tabs.
A56: Sources: iShares ITA & SOXX fact sheets (Jun-30-2026); multiples.vc (Rheinmetall/L3Harris, Sep-2026); Macrotrends (AVAV); Sacra (Saronic $9.25B, Anduril $61B); NATO/Atlantic Council (Hague 5% pledge, +20% EU 2025); uploaded BX Tac Opps black-budget compilation (Sep-2026): classified spend ~$170-215B, IC +14.2%, contractor classified-revenue estimates. China budget & Davidson window are widely-cited pre-cutoff figures — confirm current.

Sheet Assumptions
A1: ASSUMPTIONS & INPUTS
A2: Blue = hardcoded input / lever. TSMC-Shock CAGR (col I) is computed on the Defense Supercycle tab. All $M.
A4: FUND TERMS (apply to the holdco and all three sleeves) | E4: VEHICLE HOLD PERIODS (yrs) — blue = lever
A5: Committed capital ($M) | B5: =IQT_Size -> 250 | C5: IQT sleeve = 1 of 3 holdco sub-funds (see Holdco Summary) | E5: Short hold (yrs) | F5: 5 | G5: Drives every 'short-hold' block model-wide
A6: Initial deployment ($M) | B6: 225 | C6: Memo — reserve embedded in retention | E6: Mid hold (yrs) | F6: 7 | G6: Drives every 'mid-hold' block; recommended vehicle
A7: Follow-on reserve ($M) | B7: 25 | C7: Pro-rata defense on winners | E7: Long hold (yrs) | F7: 10 | G7: Drives every 'long-hold' block model-wide
A8: Mgmt fee (% of committed / yr) | B8: 0.02 | C8: Charged over full vehicle life
A9: Carried interest (%) | B9: 0.2 | C9: Over pref, no catch-up modeled
A10: Preferred return (% comp.) | B10: 0.08 | C10: 8% compounded hurdle
A11: ="Retention @ "&Hold_Short&"yr" -> Retention @ 5yr | B11: 0.85 | C11: Ownership kept after dilution
A12: ="Retention @ "&Hold_Mid&"yr" -> Retention @ 7yr | B12: 0.78
A13: ="Retention @ "&Hold_Long&"yr" -> Retention @ 10yr | B13: 0.68
A16: PORTFOLIO — ENTRY MARKS, CHECKS & GROWTH ASSUMPTIONS
A17: Company | B17: Entry post-$M | C17: Check ($M) | D17: Own % | E17: Tranche | F17: Base CAGR | G17: Bull CAGR | H17: Bear CAGR | I17: TSMC-Shock | J17: Valuation basis
A18: Substrate (anchor) | B18: 1050 | C18: 80 | D18: =C18/B18 -> 0.076190476 | E18: Anchor / growth | F18: 0.22 | G18: 0.34 | H18: -0.18 | I18: ='Defense Supercycle'!I24 -> 0.408 | J18: Est. >$1.0B post (Oct-25 round)
A19: EUV Tech | B19: 180 | C19: 30 | D19: =C19/B19 -> 0.16666667 | E19: Growth core | F19: 0.14 | G19: 0.26 | H19: 0.03 | I19: ='Defense Supercycle'!I25 -> 0.304 | J19: Est. — undisclosed (rev-gen niche)
A20: ThinTronics | B20: 120 | C20: 22.5 | D20: =C20/B20 -> 0.1875 | E20: Growth core | F20: 0.26 | G20: 0.38 | H20: -0.1 | I20: ='Defense Supercycle'!I26 -> 0.416 | J20: Est. — undisclosed + $50M CHIPS LOI
A21: EdgeCortix | B21: 350 | C21: 30.5 | D21: =C21/B21 -> 0.087142857 | E21: Growth core | F21: 0.24 | G21: 0.36 | H21: -0.08 | I21: ='Defense Supercycle'!I27 -> 0.264 | J21: Est. — undisclosed (>$110M raised)
A22: Syntiant | B22: 700 | C22: 31.5 | D22: =C22/B22 -> 0.045 | E22: Pre-IPO / liquid | F22: 0.16 | G22: 0.28 | H22: -0.02 | I22: ='Defense Supercycle'!I28 -> 0.22 | J22: $646M Dec-24; S-1 filed (SYTN)
A23: Infleqtion | B23: 3000 | C23: 25 | D23: =C23/B23 -> 0.0083333333 | E23: Public / liquid | F23: 0.15 | G23: 0.27 | H23: -0.1 | I23: ='Defense Supercycle'!I29 -> 0.222 | J23: Public NYSE:INFQ (~$3.0B mkt cap)
A24: Diraq | B24: 150 | C24: 14 | D24: =C24/B24 -> 0.093333333 | E24: Quantum venture | F24: 0.3 | G24: 0.42 | H24: -0.22 | I24: ='Defense Supercycle'!I30 -> 0.384 | J24: Never disclosed (unverified ~$107M)
A25: Mueon | B25: 65 | C25: 10 | D25: =C25/B25 -> 0.15384615 | E25: Seed optionality | F25: 0.32 | G25: 0.44 | H25: -0.28 | I25: ='Defense Supercycle'!I31 -> 0.396 | J25: Est. — undisclosed ($15.5M seed)
A26: DefendEye | B26: 50 | C26: 6.5 | D26: =C26/B26 -> 0.13 | E26: Seed optionality | F26: 0.28 | G26: 0.4 | H26: -0.25 | I26: ='Defense Supercycle'!I32 -> 0.216 | J26: Est. — undisclosed seed
A27: TOTAL DEPLOYED | C27: =SUM(C18:C26) -> 250
A28: ="Check: deployed capital (C27) "&TEXT(C27,"$#,##0")&"M vs committed (B5) "&TEXT(B5,"$#,##0")&"M — "&IF(ABS(C27-B5)<0.5,"OK","MISMATCH") -> Check: deployed capital (C27) $250M vs committed (B5) $250M — OK
A29: ="Check: deployment (B6) + reserve (B7) = "&TEXT(B6+B7,"$#,##0")&"M vs committed (B5) "&TEXT(B5,"$#,##0")&"M — "&IF(ABS(B6+B7-B5)<0.5,"OK","MISMATCH") -> Check: deployment (B6) + reserve (B7) = $250M vs committed (B5) $250M — OK

Sheet Defense Supercycle
A1: DEFENSE SUPERCYCLE — STRATEGIC SCORING & SHOCK ENGINE
A2: Winning the US-China AI/semiconductor race + insulating against a Taiwan / loss-of-TSMC scenario. Blue = lever.
A4: STRATEGIC AXIS WEIGHTS (must sum to 100%)
A5: China AI/semi-race criticality | B5: 0.25 | C5: Advances US lead in AI compute / advanced nodes
A6: Taiwan / TSMC-insulation value | B6: 0.3 | C6: Reduces US dependence on Taiwan-based fabrication
A7: Government / defense embeddedness | B7: 0.15 | C7: IQT + DoD/DIU/DARPA/CHIPS pull
A8: CFIUS-clean / US-sovereign | B8: 0.15 | C8: US domicile & ownership; acquirable by US gov/primes
A9: Supply-chain chokepoint leverage | B9: 0.15 | C9: Sole/near-sole source at a critical node
A10: Sum (check = 100%) | B10: =SUM(B5:B9) -> 1
A12: TSMC-SHOCK CALIBRATION
A13: Pivot score (neutral) | B13: 2.5 | C13: Composite above pivot -> positive re-rating; below -> drag
A14: Premium per point (CAGR) | B14: 0.08 | C14: CAGR uplift per composite point above pivot, added to Base CAGR
A16: SCENARIO PROBABILITY WEIGHTS (must sum to 100%)
A17: Base | B17: 0.45
A18: Bull | B18: 0.25
A19: Bear | B19: 0.15
A20: TSMC-Shock | B20: 0.15
A21: Sum (check = 100%) | B21: =SUM(B17:B20) -> 1
A22: STRATEGIC SCORING MATRIX (1 = low, 5 = high; blue = lever)
A23: Company | B23: China Race | C23: TSMC Insul. | D23: Gov/Defense | E23: CFIUS-Clean | F23: Chokepoint | G23: Composite | H23: Shock prem. | I23: Shock CAGR
A24: Substrate (anchor) | B24: 5 | C24: 5 | D24: 4 | E24: 5 | F24: 5 | G24: =B24*$B$5+C24*$B$6+D24*$B$7+E24*$B$8+F24*$B$9 -> 4.85 | H24: =(G24-$B$13)*$B$14 -> 0.188 | I24: =Assumptions!F18+H24 -> 0.408
A25: EUV Tech | B25: 5 | C25: 4 | D25: 4 | E25: 5 | F25: 5 | G25: =B25*$B$5+C25*$B$6+D25*$B$7+E25*$B$8+F25*$B$9 -> 4.55 | H25: =(G25-$B$13)*$B$14 -> 0.164 | I25: =Assumptions!F19+H25 -> 0.304
A26: ThinTronics | B26: 4 | C26: 5 | D26: 4 | E26: 5 | F26: 4 | G26: =B26*$B$5+C26*$B$6+D26*$B$7+E26*$B$8+F26*$B$9 -> 4.45 | H26: =(G26-$B$13)*$B$14 -> 0.156 | I26: =Assumptions!F20+H26 -> 0.416
A27: EdgeCortix | B27: 4 | C27: 2 | D27: 4 | E27: 2 | F27: 2 | G27: =B27*$B$5+C27*$B$6+D27*$B$7+E27*$B$8+F27*$B$9 -> 2.8 | H27: =(G27-$B$13)*$B$14 -> 0.024 | I27: =Assumptions!F21+H27 -> 0.264
A28: Syntiant | B28: 4 | C28: 2 | D28: 4 | E28: 5 | F28: 2 | G28: =B28*$B$5+C28*$B$6+D28*$B$7+E28*$B$8+F28*$B$9 -> 3.25 | H28: =(G28-$B$13)*$B$14 -> 0.06 | I28: =Assumptions!F22+H28 -> 0.22
A29: Infleqtion | B29: 4 | C29: 2 | D29: 4 | E29: 5 | F29: 3 | G29: =B29*$B$5+C29*$B$6+D29*$B$7+E29*$B$8+F29*$B$9 -> 3.4 | H29: =(G29-$B$13)*$B$14 -> 0.072 | I29: =Assumptions!F23+H29 -> 0.222
A30: Diraq | B30: 4 | C30: 4 | D30: 4 | E30: 2 | F30: 3 | G30: =B30*$B$5+C30*$B$6+D30*$B$7+E30*$B$8+F30*$B$9 -> 3.55 | H30: =(G30-$B$13)*$B$14 -> 0.084 | I30: =Assumptions!F24+H30 -> 0.384
A31: Mueon | B31: 3 | C31: 3 | D31: 4 | E31: 5 | F31: 3 | G31: =B31*$B$5+C31*$B$6+D31*$B$7+E31*$B$8+F31*$B$9 -> 3.45 | H31: =(G31-$B$13)*$B$14 -> 0.076 | I31: =Assumptions!F25+H31 -> 0.396
A32: DefendEye | B32: 2 | C32: 1 | D32: 3 | E32: 2 | F32: 1 | G32: =B32*$B$5+C32*$B$6+D32*$B$7+E32*$B$8+F32*$B$9 -> 1.7 | H32: =(G32-$B$13)*$B$14 -> -0.064 | I32: =Assumptions!F26+H32 -> 0.216
A33: Avg / weighted | G33: =AVERAGE(G24:G32) -> 3.5555556
A35: SCENARIO NARRATIVE — TSMC SHOCK / TAIWAN CONTINGENCY
A36: • Trigger: a Taiwan blockade/quarantine, kinetic event, or hard US-China tech decoupling that removes or severely constrains access to TSMC's leading-edge capacity — the single point of failure in the AI-compute supply chain.
A37: • Winners (large re-rate): the US sovereign-chokepoint names. Substrate (domestic X-ray litho / fabs), EUV Tech (at-wavelength EUV metrology — no fab qualifies without it), ThinTronics (US ABF/substrate materials vs Japan's Ajinomoto monopoly). Onshoring becomes a national-security imperative; demand + pricing power inflect.
A38: • Partial winners: Mueon (US advanced packaging / rack density), Infleqtion & Diraq (quantum race convexity — the 'next' compute paradigm if classical leading-edge is contested), Syntiant (US-fab-flexible edge inference).
A39: • Laggards / drag: EdgeCortix (Japan HQ + TSMC-Kumamoto fab exposure, near-term supply hit and CFIUS ceiling) and DefendEye (foreign-nexus, low semiconductor-sovereignty relevance).
A40: • Portfolio design implication: the book is intentionally overweight the sovereign core, so a tail event that would hurt a generic tech portfolio is where this one is most convex. That asymmetry is the thesis.
A42: IQT WARTIME-FUNCTION MAP — SUBSTRATE-ANCHORED SLEEVE (from uploaded IQT strategic analysis)
A43: Strategic cluster | B43: Holdings | D43: Wartime function / why IQT funds it
A44: TSMC-alternative: packaging & substrates | B44: Substrate, ThinTronics, EUV Tech | D44: Build & package chips domestically if Taiwan is blockaded — X-ray litho (Substrate), CoWoS-alternative insulators for advanced packaging (ThinTronics, + $50M CHIPS LOI Jul-26), at-wavelength EUV metrology to keep domestic litho running (EUV Tech).
A45: Denied-environment edge AI | B45: Syntiant, EdgeCortix | D45: Onboard AI for autonomous weapons when GPS / cloud / comms are jammed by PLA electronic warfare — ultra-low-power SWaP-constrained inference on drones, missiles, naval sensors. Syntiant signed a Nov-2025 IQT strategic technology-development agreement; EdgeCortix's DNA accelerator targets defense/aerospace at the tactical edge.
A46: Post-Moore's next-gen compute | B46: Diraq, Mueon (+ Infleqtion) | D46: Bootstrap quantum on existing CMOS foundries (Diraq silicon spin qubits — no exotic materials) and ultra-dense secure domestic AI data-center compute (Mueon) — a hedge if China wins the legacy-silicon volume war.
A47: Strategic takeaway: IQT is using venture capital to construct a parallel, domestic 'fail-safe' tech stack so the US can build, package and deploy AI-driven weapons entirely from domestic supply chains through a 2026/27 Taiwan contingency. Mirroring the Substrate-anchored sleeve = owning that fail-safe at VC-stage entry. The scores above are lifted for the edge-AI and next-gen-compute names to reflect this direct, documented defense pull.

Sheet Allocation
A1: ALLOCATION & POSITION STRUCTURE
A2: Green = linked. Composite pulled from Defense Supercycle tab. Ownership >15% = significant minority (seek board seat / observer).
A4: Company | B4: Check ($M) | C4: Own % | D4: % Fund | E4: Supercycle | F4: Tranche | G4: Domicile | H4: Structuring / diligence flag
A5: =Assumptions!A18 -> Substrate (anchor) | B5: =Assumptions!C18 -> 80 | C5: =Assumptions!D18 -> 0.076190476 | D5: =Assumptions!C18/IQT_Committed -> 0.32 | E5: ='Defense Supercycle'!G24 -> 4.85 | F5: =Assumptions!E18 -> Anchor / growth | G5: USA (SF, CA) | H5: Anchor. Binary tech risk — capped ~32% of fund; the core sovereign-litho bet.
A6: =Assumptions!A19 -> EUV Tech | B6: =Assumptions!C19 -> 30 | C6: =Assumptions!D19 -> 0.16666667 | D6: =Assumptions!C19/IQT_Committed -> 0.12 | E6: ='Defense Supercycle'!G25 -> 4.55 | F6: =Assumptions!E19 -> Growth core | G6: USA (CA) | H6: Rev-generating niche leader — best risk-adjusted. ~17% stake = significant minority; seek a board seat.
A7: =Assumptions!A20 -> ThinTronics | B7: =Assumptions!C20 -> 22.5 | C7: =Assumptions!D20 -> 0.1875 | D7: =Assumptions!C20/IQT_Committed -> 0.09 | E7: ='Defense Supercycle'!G26 -> 4.45 | F7: =Assumptions!E20 -> Growth core | G7: USA (CA) | H7: CHIPS $50M LOI catalyst. ~19% stake = significant minority; likely primary + secondary blend.
A8: =Assumptions!A21 -> EdgeCortix | B8: =Assumptions!C21 -> 30.5 | C8: =Assumptions!D21 -> 0.087142857 | D8: =Assumptions!C21/IQT_Committed -> 0.122 | E8: ='Defense Supercycle'!G27 -> 2.8 | F8: =Assumptions!E21 -> Growth core | G8: JAPAN (Tokyo) | H8: CFIUS/allied flag — minority only. Renesas natural acquirer. TSMC-Kumamoto fab exposure.
A9: =Assumptions!A22 -> Syntiant | B9: =Assumptions!C22 -> 31.5 | C9: =Assumptions!D22 -> 0.045 | D9: =Assumptions!C22/IQT_Committed -> 0.126 | E9: ='Defense Supercycle'!G28 -> 3.25 | F9: =Assumptions!E22 -> Pre-IPO / liquid | G9: USA (CA) | H9: Pre-IPO secondary or SYTN cornerstone. Watch pricing vs $646M Dec-24 mark.
A10: =Assumptions!A23 -> Infleqtion | B10: =Assumptions!C23 -> 25 | C10: =Assumptions!D23 -> 0.0083333333 | D10: =Assumptions!C23/IQT_Committed -> 0.1 | E10: ='Defense Supercycle'!G29 -> 3.4 | F10: =Assumptions!E23 -> Public / liquid | G10: USA (CO) | H10: Public (INFQ). PIPE/secondary. Listed quantum benchmark for Diraq.
A11: =Assumptions!A24 -> Diraq | B11: =Assumptions!C24 -> 14 | C11: =Assumptions!D24 -> 0.093333333 | D11: =Assumptions!C24/IQT_Committed -> 0.056 | E11: ='Defense Supercycle'!G30 -> 3.55 | F11: =Assumptions!E24 -> Quantum venture | G11: AUSTRALIA (Sydney) | H11: Allied flag — minority. NRFC sovereignty covenants. AUKUS-aligned quantum optionality.
A12: =Assumptions!A25 -> Mueon | B12: =Assumptions!C25 -> 10 | C12: =Assumptions!D25 -> 0.15384615 | D12: =Assumptions!C25/IQT_Committed -> 0.04 | E12: ='Defense Supercycle'!G31 -> 3.45 | F12: =Assumptions!E25 -> Seed optionality | G12: USA (OR) | H12: Seed. Milestone-gated. Needs a shipping Cubelet design-win to scale exposure.
A13: =Assumptions!A26 -> DefendEye | B13: =Assumptions!C26 -> 6.5 | C13: =Assumptions!D26 -> 0.13 | D13: =Assumptions!C26/IQT_Committed -> 0.026 | E13: ='Defense Supercycle'!G32 -> 1.7 | F13: =Assumptions!E26 -> Seed optionality | G13: USA (FL)+POLAND | H13: EU cap table + Krakow mfg — Blue UAS/NDAA provenance diligence before US-defense thesis.
A14: TOTAL | B14: =SUM(B5:B13) -> 250 | D14: =SUM(D5:D13) -> 1

Sheet Portfolio Returns
A1: PORTFOLIO RETURNS BY HOLD & SCENARIO
A2: Proceeds = Check x (1+CAGR)^Hold x Retention. MOIC = Proceeds/Check. Gross IRR = MOIC^(1/Hold)-1.
A4: =Hold_Short&"-YEAR HOLD VEHICLE" -> 5-YEAR HOLD VEHICLE
A5: Company | B5: Check ($M) | C5: Base $ | D5: Base MOIC | E5: Base IRR | F5: Bull $ | G5: Bull MOIC | H5: Bull IRR | I5: Bear $ | J5: Bear MOIC | K5: Bear IRR | L5: Shock $ | M5: Shock MOIC | N5: Shock IRR
A6: =Assumptions!A18 -> Substrate (anchor) | B6: =Assumptions!C18 -> 80 | C6: =Assumptions!C18*(1+Assumptions!F18)^Hold_Short*Ret_IQT_Short -> 183.78416 | D6: =C6/B6 -> 2.2973019 | E6: =IF((C6/B6)<=0,-1,(C6/B6)^(1/Hold_Short)-1) -> 0.18098292 | F6: =Assumptions!C18*(1+Assumptions!G18)^Hold_Short*Ret_IQT_Short -> 293.78722 | G6: =F6/B6 -> 3.6723403 | H6: =IF((F6/B6)<=0,-1,(F6/B6)^(1/Hold_Short)-1) -> 0.29714517 | I6: =Assumptions!C18*(1+Assumptions!H18)^Hold_Short*Ret_IQT_Short -> 25.210309 | J6: =I6/B6 -> 0.31512887 | K6: =IF((I6/B6)<=0,-1,(I6/B6)^(1/Hold_Short)-1) -> -0.2062246 | L6: =Assumptions!C18*(1+Assumptions!I18)^Hold_Short*Ret_IQT_Short -> 376.28958 | M6: =L6/B6 -> 4.7036197 | N6: =IF((L6/B6)<=0,-1,(L6/B6)^(1/Hold_Short)-1) -> 0.36297045
A7: =Assumptions!A19 -> EUV Tech | B7: =Assumptions!C19 -> 30 | C7: =Assumptions!C19*(1+Assumptions!F19)^Hold_Short*Ret_IQT_Short -> 49.098072 | D7: =C7/B7 -> 1.6366024 | E7: =IF((C7/B7)<=0,-1,(C7/B7)^(1/Hold_Short)-1) -> 0.10354141 | F7: =Assumptions!C19*(1+Assumptions!G19)^Hold_Short*Ret_IQT_Short -> 80.982822 | G7: =F7/B7 -> 2.6994274 | H7: =IF((F7/B7)<=0,-1,(F7/B7)^(1/Hold_Short)-1) -> 0.21970367 | I7: =Assumptions!C19*(1+Assumptions!H19)^Hold_Short*Ret_IQT_Short -> 29.561489 | J7: =I7/B7 -> 0.98538296 | K7: =IF((I7/B7)<=0,-1,(I7/B7)^(1/Hold_Short)-1) -> -0.0029406514 | L7: =Assumptions!C19*(1+Assumptions!I19)^Hold_Short*Ret_IQT_Short -> 96.145317 | M7: =L7/B7 -> 3.2048439 | N7: =IF((L7/B7)<=0,-1,(L7/B7)^(1/Hold_Short)-1) -> 0.2622965
A8: =Assumptions!A20 -> ThinTronics | B8: =Assumptions!C20 -> 22.5 | C8: =Assumptions!C20*(1+Assumptions!F20)^Hold_Short*Ret_IQT_Short -> 60.737116 | D8: =C8/B8 -> 2.6994274 | E8: =IF((C8/B8)<=0,-1,(C8/B8)^(1/Hold_Short)-1) -> 0.21970367 | F8: =Assumptions!C20*(1+Assumptions!G20)^Hold_Short*Ret_IQT_Short -> 95.718719 | G8: =F8/B8 -> 4.2541653 | H8: =IF((F8/B8)<=0,-1,(F8/B8)^(1/Hold_Short)-1) -> 0.33586592 | I8: =Assumptions!C20*(1+Assumptions!H20)^Hold_Short*Ret_IQT_Short -> 11.293121 | J8: =I8/B8 -> 0.5019165 | K8: =IF((I8/B8)<=0,-1,(I8/B8)^(1/Hold_Short)-1) -> -0.12878309 | L8: =Assumptions!C20*(1+Assumptions!I20)^Hold_Short*Ret_IQT_Short -> 108.87238 | M8: =L8/B8 -> 4.8387724 | N8: =IF((L8/B8)<=0,-1,(L8/B8)^(1/Hold_Short)-1) -> 0.3707146
A9: =Assumptions!A21 -> EdgeCortix | B9: =Assumptions!C21 -> 30.5 | C9: =Assumptions!C21*(1+Assumptions!F21)^Hold_Short*Ret_IQT_Short -> 76.00238 | D9: =C9/B9 -> 2.4918813 | E9: =IF((C9/B9)<=0,-1,(C9/B9)^(1/Hold_Short)-1) -> 0.20034329 | F9: =Assumptions!C21*(1+Assumptions!G21)^Hold_Short*Ret_IQT_Short -> 120.61833 | G9: =F9/B9 -> 3.9546993 | H9: =IF((F9/B9)<=0,-1,(F9/B9)^(1/Hold_Short)-1) -> 0.31650555 | I9: =Assumptions!C21*(1+Assumptions!H21)^Hold_Short*Ret_IQT_Short -> 17.086688 | J9: =I9/B9 -> 0.56021929 | K9: =IF((I9/B9)<=0,-1,(I9/B9)^(1/Hold_Short)-1) -> -0.10942272 | L9: =Assumptions!C21*(1+Assumptions!I21)^Hold_Short*Ret_IQT_Short -> 83.647725 | M9: =L9/B9 -> 2.7425484 | N9: =IF((L9/B9)<=0,-1,(L9/B9)^(1/Hold_Short)-1) -> 0.22357574
A10: =Assumptions!A22 -> Syntiant | B10: =Assumptions!C22 -> 31.5 | C10: =Assumptions!C22*(1+Assumptions!F22)^Hold_Short*Ret_IQT_Short -> 56.236648 | D10: =C10/B10 -> 1.7852904 | E10: =IF((C10/B10)<=0,-1,(C10/B10)^(1/Hold_Short)-1) -> 0.12290179 | F10: =Assumptions!C22*(1+Assumptions!G22)^Hold_Short*Ret_IQT_Short -> 91.998199 | G10: =F10/B10 -> 2.9205778 | H10: =IF((F10/B10)<=0,-1,(F10/B10)^(1/Hold_Short)-1) -> 0.23906404 | I10: =Assumptions!C22*(1+Assumptions!H22)^Hold_Short*Ret_IQT_Short -> 24.202479 | J10: =I10/B10 -> 0.76833268 | K10: =IF((I10/B10)<=0,-1,(I10/B10)^(1/Hold_Short)-1) -> -0.051341591 | L10: =Assumptions!C22*(1+Assumptions!I22)^Hold_Short*Ret_IQT_Short -> 72.365011 | M10: =L10/B10 -> 2.2973019 | N10: =IF((L10/B10)<=0,-1,(L10/B10)^(1/Hold_Short)-1) -> 0.18098292
A11: =Assumptions!A23 -> Infleqtion | B11: =Assumptions!C23 -> 25 | C11: =Assumptions!C23*(1+Assumptions!F23)^Hold_Short*Ret_IQT_Short -> 42.74134 | D11: =C11/B11 -> 1.7096536 | E11: =IF((C11/B11)<=0,-1,(C11/B11)^(1/Hold_Short)-1) -> 0.1132216 | F11: =Assumptions!C23*(1+Assumptions!G23)^Hold_Short*Ret_IQT_Short -> 70.206535 | G11: =F11/B11 -> 2.8082614 | H11: =IF((F11/B11)<=0,-1,(F11/B11)^(1/Hold_Short)-1) -> 0.22938386 | I11: =Assumptions!C23*(1+Assumptions!H23)^Hold_Short*Ret_IQT_Short -> 12.547913 | J11: =I11/B11 -> 0.5019165 | K11: =IF((I11/B11)<=0,-1,(I11/B11)^(1/Hold_Short)-1) -> -0.12878309 | L11: =Assumptions!C23*(1+Assumptions!I23)^Hold_Short*Ret_IQT_Short -> 57.904853 | M11: =L11/B11 -> 2.3161941 | N11: =IF((L11/B11)<=0,-1,(L11/B11)^(1/Hold_Short)-1) -> 0.18291896
A12: =Assumptions!A24 -> Diraq | B12: =Assumptions!C24 -> 14 | C12: =Assumptions!C24*(1+Assumptions!F24)^Hold_Short*Ret_IQT_Short -> 44.183867 | D12: =C12/B12 -> 3.1559905 | E12: =IF((C12/B12)<=0,-1,(C12/B12)^(1/Hold_Short)-1) -> 0.25842442 | F12: =Assumptions!C24*(1+Assumptions!G24)^Hold_Short*Ret_IQT_Short -> 68.705054 | G12: =F12/B12 -> 4.9075038 | H12: =IF((F12/B12)<=0,-1,(F12/B12)^(1/Hold_Short)-1) -> 0.37458667 | I12: =Assumptions!C24*(1+Assumptions!H24)^Hold_Short*Ret_IQT_Short -> 3.4357375 | J12: =I12/B12 -> 0.24540982 | K12: =IF((I12/B12)<=0,-1,(I12/B12)^(1/Hold_Short)-1) -> -0.24494535 | L12: =Assumptions!C24*(1+Assumptions!I24)^Hold_Short*Ret_IQT_Short -> 60.426496 | M12: =L12/B12 -> 4.3161783 | N12: =IF((L12/B12)<=0,-1,(L12/B12)^(1/Hold_Short)-1) -> 0.339738
A13: =Assumptions!A25 -> Mueon | B13: =Assumptions!C25 -> 10 | C13: =Assumptions!C25*(1+Assumptions!F25)^Hold_Short*Ret_IQT_Short -> 34.063446 | D13: =C13/B13 -> 3.4063446 | E13: =IF((C13/B13)<=0,-1,(C13/B13)^(1/Hold_Short)-1) -> 0.2777848 | F13: =Assumptions!C25*(1+Assumptions!G25)^Hold_Short*Ret_IQT_Short -> 52.62976 | G13: =F13/B13 -> 5.262976 | H13: =IF((F13/B13)<=0,-1,(F13/B13)^(1/Hold_Short)-1) -> 0.39394705 | I13: =Assumptions!C25*(1+Assumptions!H25)^Hold_Short*Ret_IQT_Short -> 1.64468 | J13: =I13/B13 -> 0.164468 | K13: =IF((I13/B13)<=0,-1,(I13/B13)^(1/Hold_Short)-1) -> -0.30302647 | L13: =Assumptions!C25*(1+Assumptions!I25)^Hold_Short*Ret_IQT_Short -> 45.065689 | M13: =L13/B13 -> 4.5065689 | N13: =IF((L13/B13)<=0,-1,(L13/B13)^(1/Hold_Short)-1) -> 0.35135422
A14: =Assumptions!A26 -> DefendEye | B14: =Assumptions!C26 -> 6.5 | C14: =Assumptions!C26*(1+Assumptions!F26)^Hold_Short*Ret_IQT_Short -> 18.983755 | D14: =C14/B14 -> 2.9205778 | E14: =IF((C14/B14)<=0,-1,(C14/B14)^(1/Hold_Short)-1) -> 0.23906404 | F14: =Assumptions!C26*(1+Assumptions!G26)^Hold_Short*Ret_IQT_Short -> 29.714776 | G14: =F14/B14 -> 4.571504 | H14: =IF((F14/B14)<=0,-1,(F14/B14)^(1/Hold_Short)-1) -> 0.3552263 | I14: =Assumptions!C26*(1+Assumptions!H26)^Hold_Short*Ret_IQT_Short -> 1.3111084 | J14: =I14/B14 -> 0.20170898 | K14: =IF((I14/B14)<=0,-1,(I14/B14)^(1/Hold_Short)-1) -> -0.27398591 | L14: =Assumptions!C26*(1+Assumptions!I26)^Hold_Short*Ret_IQT_Short -> 14.689268 | M14: =L14/B14 -> 2.2598874 | N14: =IF((L14/B14)<=0,-1,(L14/B14)^(1/Hold_Short)-1) -> 0.17711084
A15: FUND TOTAL | B15: =SUM(B6:B14) -> 250 | C15: =SUM(C6:C14) -> 565.83078 | D15: =C15/B15 -> 2.2633231 | E15: =IF((C15/B15)<=0,-1,(C15/B15)^(1/Hold_Short)-1) -> 0.17746854 | F15: =SUM(F6:F14) -> 904.36142 | G15: =F15/B15 -> 3.6174457 | H15: =IF((F15/B15)<=0,-1,(F15/B15)^(1/Hold_Short)-1) -> 0.29324379 | I15: =SUM(I6:I14) -> 126.29353 | J15: =I15/B15 -> 0.5051741 | K15: =IF((I15/B15)<=0,-1,(I15/B15)^(1/Hold_Short)-1) -> -0.12765512 | L15: =SUM(L6:L14) -> 915.40631 | M15: =L15/B15 -> 3.6616253 | N15: =IF((L15/B15)<=0,-1,(L15/B15)^(1/Hold_Short)-1) -> 0.29638733
A18: =Hold_Mid&"-YEAR HOLD VEHICLE" -> 7-YEAR HOLD VEHICLE
A19: Company | B19: Check ($M) | C19: Base $ | D19: Base MOIC | E19: Base IRR | F19: Bull $ | G19: Bull MOIC | H19: Bull IRR | I19: Bear $ | J19: Bear MOIC | K19: Bear IRR | L19: Shock $ | M19: Shock MOIC | N19: Shock IRR
A20: =Assumptions!A18 -> Substrate (anchor) | B20: =Assumptions!C18 -> 80 | C20: =Assumptions!C18*(1+Assumptions!F18)^Hold_Mid*Ret_IQT_Mid -> 251.01716 | D20: =C20/B20 -> 3.1377144 | E20: =IF((C20/B20)<=0,-1,(C20/B20)^(1/Hold_Mid)-1) -> 0.17745624 | F20: =Assumptions!C18*(1+Assumptions!G18)^Hold_Mid*Ret_IQT_Mid -> 484.08116 | G20: =F20/B20 -> 6.0510145 | H20: =IF((F20/B20)<=0,-1,(F20/B20)^(1/Hold_Mid)-1) -> 0.2932716 | I20: =Assumptions!C18*(1+Assumptions!H18)^Hold_Mid*Ret_IQT_Mid -> 15.555413 | J20: =I20/B20 -> 0.19444267 | K20: =IF((I20/B20)<=0,-1,(I20/B20)^(1/Hold_Mid)-1) -> -0.20859499 | L20: =Assumptions!C18*(1+Assumptions!I18)^Hold_Mid*Ret_IQT_Mid -> 684.54685 | M20: =L20/B20 -> 8.5568356 | N20: =IF((L20/B20)<=0,-1,(L20/B20)^(1/Hold_Mid)-1) -> 0.35890031
A21: =Assumptions!A19 -> EUV Tech | B21: =Assumptions!C19 -> 30 | C21: =Assumptions!C19*(1+Assumptions!F19)^Hold_Mid*Ret_IQT_Mid -> 58.55309 | D21: =C21/B21 -> 1.9517697 | E21: =IF((C21/B21)<=0,-1,(C21/B21)^(1/Hold_Mid)-1) -> 0.10024599 | F21: =Assumptions!C19*(1+Assumptions!G19)^Hold_Mid*Ret_IQT_Mid -> 117.98035 | G21: =F21/B21 -> 3.9326783 | H21: =IF((F21/B21)<=0,-1,(F21/B21)^(1/Hold_Mid)-1) -> 0.21606136 | I21: =Assumptions!C19*(1+Assumptions!H19)^Hold_Mid*Ret_IQT_Mid -> 28.779048 | J21: =I21/B21 -> 0.95930162 | K21: =IF((I21/B21)<=0,-1,(I21/B21)^(1/Hold_Mid)-1) -> -0.0059180963 | L21: =Assumptions!C19*(1+Assumptions!I19)^Hold_Mid*Ret_IQT_Mid -> 150.0234 | M21: =L21/B21 -> 5.0007799 | N21: =IF((L21/B21)<=0,-1,(L21/B21)^(1/Hold_Mid)-1) -> 0.25852699
A22: =Assumptions!A20 -> ThinTronics | B22: =Assumptions!C20 -> 22.5 | C22: =Assumptions!C20*(1+Assumptions!F20)^Hold_Mid*Ret_IQT_Mid -> 88.485261 | D22: =C22/B22 -> 3.9326783 | E22: =IF((C22/B22)<=0,-1,(C22/B22)^(1/Hold_Mid)-1) -> 0.21606136 | F22: =Assumptions!C20*(1+Assumptions!G20)^Hold_Mid*Ret_IQT_Mid -> 167.27488 | G22: =F22/B22 -> 7.4344391 | H22: =IF((F22/B22)<=0,-1,(F22/B22)^(1/Hold_Mid)-1) -> 0.33187673 | I22: =Assumptions!C20*(1+Assumptions!H20)^Hold_Mid*Ret_IQT_Mid -> 8.3941106 | J22: =I22/B22 -> 0.37307158 | K22: =IF((I22/B22)<=0,-1,(I22/B22)^(1/Hold_Mid)-1) -> -0.13138474 | L22: =Assumptions!C20*(1+Assumptions!I20)^Hold_Mid*Ret_IQT_Mid -> 200.31796 | M22: =L22/B22 -> 8.9030206 | N22: =IF((L22/B22)<=0,-1,(L22/B22)^(1/Hold_Mid)-1) -> 0.36662134
A23: =Assumptions!A21 -> EdgeCortix | B23: =Assumptions!C21 -> 30.5 | C23: =Assumptions!C21*(1+Assumptions!F21)^Hold_Mid*Ret_IQT_Mid -> 107.23739 | D23: =C23/B23 -> 3.51598 | E23: =IF((C23/B23)<=0,-1,(C23/B23)^(1/Hold_Mid)-1) -> 0.1967588 | F23: =Assumptions!C21*(1+Assumptions!G21)^Hold_Mid*Ret_IQT_Mid -> 204.72308 | G23: =F23/B23 -> 6.712232 | H23: =IF((F23/B23)<=0,-1,(F23/B23)^(1/Hold_Mid)-1) -> 0.31257416 | I23: =Assumptions!C21*(1+Assumptions!H21)^Hold_Mid*Ret_IQT_Mid -> 13.271171 | J23: =I23/B23 -> 0.43512035 | K23: =IF((I23/B23)<=0,-1,(I23/B23)^(1/Hold_Mid)-1) -> -0.11208218 | L23: =Assumptions!C21*(1+Assumptions!I21)^Hold_Mid*Ret_IQT_Mid -> 122.63769 | M23: =L23/B23 -> 4.0209079 | N23: =IF((L23/B23)<=0,-1,(L23/B23)^(1/Hold_Mid)-1) -> 0.21992187
A24: =Assumptions!A22 -> Syntiant | B24: =Assumptions!C22 -> 31.5 | C24: =Assumptions!C22*(1+Assumptions!F22)^Hold_Mid*Ret_IQT_Mid -> 69.440219 | D24: =C24/B24 -> 2.2044514 | E24: =IF((C24/B24)<=0,-1,(C24/B24)^(1/Hold_Mid)-1) -> 0.11954855 | F24: =Assumptions!C22*(1+Assumptions!G22)^Hold_Mid*Ret_IQT_Mid -> 138.3168 | G24: =F24/B24 -> 4.3910096 | H24: =IF((F24/B24)<=0,-1,(F24/B24)^(1/Hold_Mid)-1) -> 0.23536392 | I24: =Assumptions!C22*(1+Assumptions!H22)^Hold_Mid*Ret_IQT_Mid -> 21.329844 | J24: =I24/B24 -> 0.67713792 | K24: =IF((I24/B24)<=0,-1,(I24/B24)^(1/Hold_Mid)-1) -> -0.054174499 | L24: =Assumptions!C22*(1+Assumptions!I22)^Hold_Mid*Ret_IQT_Mid -> 98.838005 | M24: =L24/B24 -> 3.1377144 | N24: =IF((L24/B24)<=0,-1,(L24/B24)^(1/Hold_Mid)-1) -> 0.17745624
A25: =Assumptions!A23 -> Infleqtion | B25: =Assumptions!C23 -> 25 | C25: =Assumptions!C23*(1+Assumptions!F23)^Hold_Mid*Ret_IQT_Mid -> 51.870388 | D25: =C25/B25 -> 2.0748155 | E25: =IF((C25/B25)<=0,-1,(C25/B25)^(1/Hold_Mid)-1) -> 0.10989727 | F25: =Assumptions!C23*(1+Assumptions!G23)^Hold_Mid*Ret_IQT_Mid -> 103.91079 | G25: =F25/B25 -> 4.1564317 | H25: =IF((F25/B25)<=0,-1,(F25/B25)^(1/Hold_Mid)-1) -> 0.22571264 | I25: =Assumptions!C23*(1+Assumptions!H23)^Hold_Mid*Ret_IQT_Mid -> 9.3267896 | J25: =I25/B25 -> 0.37307158 | K25: =IF((I25/B25)<=0,-1,(I25/B25)^(1/Hold_Mid)-1) -> -0.13138474 | L25: =Assumptions!C23*(1+Assumptions!I23)^Hold_Mid*Ret_IQT_Mid -> 79.347464 | M25: =L25/B25 -> 3.1738986 | N25: =IF((L25/B25)<=0,-1,(L25/B25)^(1/Hold_Mid)-1) -> 0.17938649
A26: =Assumptions!A24 -> Diraq | B26: =Assumptions!C24 -> 14 | C26: =Assumptions!C24*(1+Assumptions!F24)^Hold_Mid*Ret_IQT_Mid -> 68.521381 | D26: =C26/B26 -> 4.8943843 | E26: =IF((C26/B26)<=0,-1,(C26/B26)^(1/Hold_Mid)-1) -> 0.25466648 | F26: =Assumptions!C24*(1+Assumptions!G24)^Hold_Mid*Ret_IQT_Mid -> 127.12795 | G26: =F26/B26 -> 9.080568 | H26: =IF((F26/B26)<=0,-1,(F26/B26)^(1/Hold_Mid)-1) -> 0.37048185 | I26: =Assumptions!C24*(1+Assumptions!H24)^Hold_Mid*Ret_IQT_Mid -> 1.9181601 | J26: =I26/B26 -> 0.13701144 | K26: =IF((I26/B26)<=0,-1,(I26/B26)^(1/Hold_Mid)-1) -> -0.24720011 | L26: =Assumptions!C24*(1+Assumptions!I24)^Hold_Mid*Ret_IQT_Mid -> 106.21241 | M26: =L26/B26 -> 7.5866008 | N26: =IF((L26/B26)<=0,-1,(L26/B26)^(1/Hold_Mid)-1) -> 0.33573724
A27: =Assumptions!A25 -> Mueon | B27: =Assumptions!C25 -> 10 | C27: =Assumptions!C25*(1+Assumptions!F25)^Hold_Mid*Ret_IQT_Mid -> 54.464324 | D27: =C27/B27 -> 5.4464324 | E27: =IF((C27/B27)<=0,-1,(C27/B27)^(1/Hold_Mid)-1) -> 0.27396904 | F27: =Assumptions!C25*(1+Assumptions!G25)^Hold_Mid*Ret_IQT_Mid -> 100.14564 | G27: =F27/B27 -> 10.014564 | H27: =IF((F27/B27)<=0,-1,(F27/B27)^(1/Hold_Mid)-1) -> 0.38978441 | I27: =Assumptions!C25*(1+Assumptions!H25)^Hold_Mid*Ret_IQT_Mid -> 0.78238781 | J27: =I27/B27 -> 0.078238781 | K27: =IF((I27/B27)<=0,-1,(I27/B27)^(1/Hold_Mid)-1) -> -0.3051078 | L27: =Assumptions!C25*(1+Assumptions!I25)^Hold_Mid*Ret_IQT_Mid -> 80.592111 | M27: =L27/B27 -> 8.0592111 | N27: =IF((L27/B27)<=0,-1,(L27/B27)^(1/Hold_Mid)-1) -> 0.34731877
A28: =Assumptions!A26 -> DefendEye | B28: =Assumptions!C26 -> 6.5 | C28: =Assumptions!C26*(1+Assumptions!F26)^Hold_Mid*Ret_IQT_Mid -> 28.541563 | D28: =C28/B28 -> 4.3910096 | E28: =IF((C28/B28)<=0,-1,(C28/B28)^(1/Hold_Mid)-1) -> 0.23536392 | F28: =Assumptions!C26*(1+Assumptions!G26)^Hold_Mid*Ret_IQT_Mid -> 53.444647 | G28: =F28/B28 -> 8.2222533 | H28: =IF((F28/B28)<=0,-1,(F28/B28)^(1/Hold_Mid)-1) -> 0.35117929 | I28: =Assumptions!C26*(1+Assumptions!H26)^Hold_Mid*Ret_IQT_Mid -> 0.67676331 | J28: =I28/B28 -> 0.10411743 | K28: =IF((I28/B28)<=0,-1,(I28/B28)^(1/Hold_Mid)-1) -> -0.27615395 | L28: =Assumptions!C26*(1+Assumptions!I26)^Hold_Mid*Ret_IQT_Mid -> 19.931638 | M28: =L28/B28 -> 3.0664058 | N28: =IF((L28/B28)<=0,-1,(L28/B28)^(1/Hold_Mid)-1) -> 0.17359572
A29: FUND TOTAL | B29: =SUM(B20:B28) -> 250 | C29: =SUM(C20:C28) -> 778.13077 | D29: =C29/B29 -> 3.1125231 | E29: =IF((C29/B29)<=0,-1,(C29/B29)^(1/Hold_Mid)-1) -> 0.1761011 | F29: =SUM(F20:F28) -> 1497.0053 | G29: =F29/B29 -> 5.9880212 | H29: =IF((F29/B29)<=0,-1,(F29/B29)^(1/Hold_Mid)-1) -> 0.29133962 | I29: =SUM(I20:I28) -> 100.03369 | J29: =I29/B29 -> 0.40013475 | K29: =IF((I29/B29)<=0,-1,(I29/B29)^(1/Hold_Mid)-1) -> -0.12265112 | L29: =SUM(L20:L28) -> 1542.4475 | M29: =L29/B29 -> 6.1697901 | N29: =IF((L29/B29)<=0,-1,(L29/B29)^(1/Hold_Mid)-1) -> 0.29686799
A32: =Hold_Long&"-YEAR HOLD VEHICLE" -> 10-YEAR HOLD VEHICLE
A33: Company | B33: Check ($M) | C33: Base $ | D33: Base MOIC | E33: Base IRR | F33: Bull $ | G33: Bull MOIC | H33: Bull IRR | I33: Bear $ | J33: Bear MOIC | K33: Bear IRR | L33: Shock $ | M33: Shock MOIC | N33: Shock IRR
A34: =Assumptions!A18 -> Substrate (anchor) | B34: =Assumptions!C18 -> 80 | C34: =Assumptions!C18*(1+Assumptions!F18)^Hold_Long*Ret_IQT_Long -> 397.37195 | D34: =C34/B34 -> 4.9671494 | E34: =IF((C34/B34)<=0,-1,(C34/B34)^(1/Hold_Long)-1) -> 0.17384491 | F34: =Assumptions!C18*(1+Assumptions!G18)^Hold_Long*Ret_IQT_Long -> 1015.4227 | G34: =F34/B34 -> 12.692784 | H34: =IF((F34/B34)<=0,-1,(F34/B34)^(1/Hold_Long)-1) -> 0.28930507 | I34: =Assumptions!C18*(1+Assumptions!H18)^Hold_Long*Ret_IQT_Long -> 7.4771729 | J34: =I34/B34 -> 0.093464661 | K34: =IF((I34/B34)<=0,-1,(I34/B34)^(1/Hold_Long)-1) -> -0.21102227 | L34: =Assumptions!C18*(1+Assumptions!I18)^Hold_Long*Ret_IQT_Long -> 1665.8099 | M34: =L34/B34 -> 20.822624 | N34: =IF((L34/B34)<=0,-1,(L34/B34)^(1/Hold_Long)-1) -> 0.35473249
A35: =Assumptions!A19 -> EUV Tech | B35: =Assumptions!C19 -> 30 | C35: =Assumptions!C19*(1+Assumptions!F19)^Hold_Long*Ret_IQT_Long -> 75.627315 | D35: =C35/B35 -> 2.5209105 | E35: =IF((C35/B35)<=0,-1,(C35/B35)^(1/Hold_Long)-1) -> 0.096871475 | F35: =Assumptions!C19*(1+Assumptions!G19)^Hold_Long*Ret_IQT_Long -> 205.748 | G35: =F35/B35 -> 6.8582666 | H35: =IF((F35/B35)<=0,-1,(F35/B35)^(1/Hold_Long)-1) -> 0.21233163 | I35: =Assumptions!C19*(1+Assumptions!H19)^Hold_Long*Ret_IQT_Long -> 27.415894 | J35: =I35/B35 -> 0.91386314 | K35: =IF((I35/B35)<=0,-1,(I35/B35)^(1/Hold_Long)-1) -> -0.0089670003 | L35: =Assumptions!C19*(1+Assumptions!I19)^Hold_Long*Ret_IQT_Long -> 290.0054 | M35: =L35/B35 -> 9.6668466 | N35: =IF((L35/B35)<=0,-1,(L35/B35)^(1/Hold_Long)-1) -> 0.25466702
A36: =Assumptions!A20 -> ThinTronics | B36: =Assumptions!C20 -> 22.5 | C36: =Assumptions!C20*(1+Assumptions!F20)^Hold_Long*Ret_IQT_Long -> 154.311 | D36: =C36/B36 -> 6.8582666 | E36: =IF((C36/B36)<=0,-1,(C36/B36)^(1/Hold_Long)-1) -> 0.21233163 | F36: =Assumptions!C20*(1+Assumptions!G20)^Hold_Long*Ret_IQT_Long -> 383.25012 | G36: =F36/B36 -> 17.033338 | H36: =IF((F36/B36)<=0,-1,(F36/B36)^(1/Hold_Long)-1) -> 0.32779179 | I36: =Assumptions!C20*(1+Assumptions!H20)^Hold_Long*Ret_IQT_Long -> 5.3347801 | J36: =I36/B36 -> 0.23710134 | K36: =IF((I36/B36)<=0,-1,(I36/B36)^(1/Hold_Long)-1) -> -0.13404884 | L36: =Assumptions!C20*(1+Assumptions!I20)^Hold_Long*Ret_IQT_Long -> 495.81991 | M36: =L36/B36 -> 22.036441 | N36: =IF((L36/B36)<=0,-1,(L36/B36)^(1/Hold_Long)-1) -> 0.36242983
A37: =Assumptions!A21 -> EdgeCortix | B37: =Assumptions!C21 -> 30.5 | C37: =Assumptions!C21*(1+Assumptions!F21)^Hold_Long*Ret_IQT_Long -> 178.24839 | D37: =C37/B37 -> 5.8442093 | E37: =IF((C37/B37)<=0,-1,(C37/B37)^(1/Hold_Long)-1) -> 0.19308827 | F37: =Assumptions!C21*(1+Assumptions!G21)^Hold_Long*Ret_IQT_Long -> 448.94986 | G37: =F37/B37 -> 14.719667 | H37: =IF((F37/B37)<=0,-1,(F37/B37)^(1/Hold_Long)-1) -> 0.30854843 | I37: =Assumptions!C21*(1+Assumptions!H21)^Hold_Long*Ret_IQT_Long -> 9.0092165 | J37: =I37/B37 -> 0.29538415 | K37: =IF((I37/B37)<=0,-1,(I37/B37)^(1/Hold_Long)-1) -> -0.11480548 | L37: =Assumptions!C21*(1+Assumptions!I21)^Hold_Long*Ret_IQT_Long -> 215.91335 | M37: =L37/B37 -> 7.0791262 | N37: =IF((L37/B37)<=0,-1,(L37/B37)^(1/Hold_Long)-1) -> 0.2161803
A38: =Assumptions!A22 -> Syntiant | B38: =Assumptions!C22 -> 31.5 | C38: =Assumptions!C22*(1+Assumptions!F22)^Hold_Long*Ret_IQT_Long -> 94.492939 | D38: =C38/B38 -> 2.9997759 | E38: =IF((C38/B38)<=0,-1,(C38/B38)^(1/Hold_Long)-1) -> 0.11611483 | F38: =Assumptions!C22*(1+Assumptions!G22)^Hold_Long*Ret_IQT_Long -> 252.88273 | G38: =F38/B38 -> 8.028023 | H38: =IF((F38/B38)<=0,-1,(F38/B38)^(1/Hold_Long)-1) -> 0.23157499 | I38: =Assumptions!C22*(1+Assumptions!H22)^Hold_Long*Ret_IQT_Long -> 17.5017 | J38: =I38/B38 -> 0.55560951 | K38: =IF((I38/B38)<=0,-1,(I38/B38)^(1/Hold_Long)-1) -> -0.057075398 | L38: =Assumptions!C22*(1+Assumptions!I22)^Hold_Long*Ret_IQT_Long -> 156.4652 | M38: =L38/B38 -> 4.9671494 | N38: =IF((L38/B38)<=0,-1,(L38/B38)^(1/Hold_Long)-1) -> 0.17384491
A39: =Assumptions!A23 -> Infleqtion | B39: =Assumptions!C23 -> 25 | C39: =Assumptions!C23*(1+Assumptions!F23)^Hold_Long*Ret_IQT_Long -> 68.774482 | D39: =C39/B39 -> 2.7509793 | E39: =IF((C39/B39)<=0,-1,(C39/B39)^(1/Hold_Long)-1) -> 0.10649315 | F39: =Assumptions!C23*(1+Assumptions!G23)^Hold_Long*Ret_IQT_Long -> 185.56076 | G39: =F39/B39 -> 7.4224302 | H39: =IF((F39/B39)<=0,-1,(F39/B39)^(1/Hold_Long)-1) -> 0.22195331 | I39: =Assumptions!C23*(1+Assumptions!H23)^Hold_Long*Ret_IQT_Long -> 5.9275335 | J39: =I39/B39 -> 0.23710134 | K39: =IF((I39/B39)<=0,-1,(I39/B39)^(1/Hold_Long)-1) -> -0.13404884 | L39: =Assumptions!C23*(1+Assumptions!I23)^Hold_Long*Ret_IQT_Long -> 126.22953 | M39: =L39/B39 -> 5.0491814 | N39: =IF((L39/B39)<=0,-1,(L39/B39)^(1/Hold_Long)-1) -> 0.17576925
A40: =Assumptions!A24 -> Diraq | B40: =Assumptions!C24 -> 14 | C40: =Assumptions!C24*(1+Assumptions!F24)^Hold_Long*Ret_IQT_Long -> 131.24128 | D40: =C40/B40 -> 9.3743774 | E40: =IF((C40/B40)<=0,-1,(C40/B40)^(1/Hold_Long)-1) -> 0.25081835 | F40: =Assumptions!C24*(1+Assumptions!G24)^Hold_Long*Ret_IQT_Long -> 317.33677 | G40: =F40/B40 -> 22.666912 | H40: =IF((F40/B40)<=0,-1,(F40/B40)^(1/Hold_Long)-1) -> 0.3662785 | I40: =Assumptions!C24*(1+Assumptions!H24)^Hold_Long*Ret_IQT_Long -> 0.79356586 | J40: =I40/B40 -> 0.056683276 | K40: =IF((I40/B40)<=0,-1,(I40/B40)^(1/Hold_Long)-1) -> -0.24950899 | L40: =Assumptions!C24*(1+Assumptions!I24)^Hold_Long*Ret_IQT_Long -> 245.46968 | M40: =L40/B40 -> 17.533548 | N40: =IF((L40/B40)<=0,-1,(L40/B40)^(1/Hold_Long)-1) -> 0.33164046
A41: =Assumptions!A25 -> Mueon | B41: =Assumptions!C25 -> 10 | C41: =Assumptions!C25*(1+Assumptions!F25)^Hold_Long*Ret_IQT_Long -> 109.20643 | D41: =C41/B41 -> 10.920643 | E41: =IF((C41/B41)<=0,-1,(C41/B41)^(1/Hold_Long)-1) -> 0.27006171 | F41: =Assumptions!C25*(1+Assumptions!G25)^Hold_Long*Ret_IQT_Long -> 260.69568 | G41: =F41/B41 -> 26.069568 | H41: =IF((F41/B41)<=0,-1,(F41/B41)^(1/Hold_Long)-1) -> 0.38552186 | I41: =Assumptions!C25*(1+Assumptions!H25)^Hold_Long*Ret_IQT_Long -> 0.25458562 | J41: =I41/B41 -> 0.025458562 | K41: =IF((I41/B41)<=0,-1,(I41/B41)^(1/Hold_Long)-1) -> -0.30723907 | L41: =Assumptions!C25*(1+Assumptions!I25)^Hold_Long*Ret_IQT_Long -> 191.14507 | M41: =L41/B41 -> 19.114507 | N41: =IF((L41/B41)<=0,-1,(L41/B41)^(1/Hold_Long)-1) -> 0.34318647
A42: =Assumptions!A26 -> DefendEye | B42: =Assumptions!C26 -> 6.5 | C42: =Assumptions!C26*(1+Assumptions!F26)^Hold_Long*Ret_IQT_Long -> 52.18215 | D42: =C42/B42 -> 8.028023 | E42: =IF((C42/B42)<=0,-1,(C42/B42)^(1/Hold_Long)-1) -> 0.23157499 | F42: =Assumptions!C26*(1+Assumptions!G26)^Hold_Long*Ret_IQT_Long -> 127.85056 | G42: =F42/B42 -> 19.669317 | H42: =IF((F42/B42)<=0,-1,(F42/B42)^(1/Hold_Long)-1) -> 0.34703515 | I42: =Assumptions!C26*(1+Assumptions!H26)^Hold_Long*Ret_IQT_Long -> 0.24890574 | J42: =I42/B42 -> 0.03829319 | K42: =IF((I42/B42)<=0,-1,(I42/B42)^(1/Hold_Long)-1) -> -0.27837403 | L42: =Assumptions!C26*(1+Assumptions!I26)^Hold_Long*Ret_IQT_Long -> 31.243381 | M42: =L42/B42 -> 4.8066739 | N42: =IF((L42/B42)<=0,-1,(L42/B42)^(1/Hold_Long)-1) -> 0.16999624
A43: FUND TOTAL | B43: =SUM(B34:B42) -> 250 | C43: =SUM(C34:C42) -> 1261.4559 | D43: =C43/B43 -> 5.0458237 | E43: =IF((C43/B43)<=0,-1,(C43/B43)^(1/Hold_Long)-1) -> 0.17569104 | F43: =SUM(F34:F42) -> 3197.6972 | G43: =F43/B43 -> 12.790789 | H43: =IF((F43/B43)<=0,-1,(F43/B43)^(1/Hold_Long)-1) -> 0.29029713 | I43: =SUM(I34:I42) -> 73.963354 | J43: =I43/B43 -> 0.29585342 | K43: =IF((I43/B43)<=0,-1,(I43/B43)^(1/Hold_Long)-1) -> -0.11466495 | L43: =SUM(L34:L42) -> 3418.1015 | M43: =L43/B43 -> 13.672406 | N43: =IF((L43/B43)<=0,-1,(L43/B43)^(1/Hold_Long)-1) -> 0.29892625

Sheet Fund Economics
A1: FUND ECONOMICS — GROSS->NET WATERFALL
A2: Whole-fund European waterfall: return of capital -> 8% comp. pref -> 20% carry (no catch-up). Expected = prob-weighted. $M.
A4: =Hold_Short&"-YEAR VEHICLE" -> 5-YEAR VEHICLE
A5: Line item ($M) | B5: Base | C5: Bull | D5: Bear | E5: TSMC-Shock | F5: Expected
A6: Gross exit proceeds | B6: ='Portfolio Returns'!C15 -> 565.83078 | C6: ='Portfolio Returns'!F15 -> 904.36142 | D6: ='Portfolio Returns'!I15 -> 126.29353 | E6: ='Portfolio Returns'!L15 -> 915.40631 | F6: =B6*P_Base+C6*P_Bull+D6*P_Bear+E6*P_Shock -> 636.96918
A7: (-) Return of committed capital | B7: =-IQT_Committed -> -250 | C7: =-IQT_Committed -> -250 | D7: =-IQT_Committed -> -250 | E7: =-IQT_Committed -> -250 | F7: =B7*P_Base+C7*P_Bull+D7*P_Bear+E7*P_Shock -> -250
A8: (-) Preferred return (8% comp.) | B8: =-IQT_Committed*((1+Pref)^Hold_Short-1) -> -117.33202 | C8: =-IQT_Committed*((1+Pref)^Hold_Short-1) -> -117.33202 | D8: =-IQT_Committed*((1+Pref)^Hold_Short-1) -> -117.33202 | E8: =-IQT_Committed*((1+Pref)^Hold_Short-1) -> -117.33202 | F8: =B8*P_Base+C8*P_Bull+D8*P_Bear+E8*P_Shock -> -117.33202
A9: Profit above pref (carry base) | B9: =MAX(0,B6+B7+B8) -> 198.49876 | C9: =MAX(0,C6+C7+C8) -> 537.0294 | D9: =MAX(0,D6+D7+D8) -> 0 | E9: =MAX(0,E6+E7+E8) -> 548.07429 | F9: =B9*P_Base+C9*P_Bull+D9*P_Bear+E9*P_Shock -> 305.79294
A10: (-) GP carried interest (20%) | B10: =-Carry*B9 -> -39.699752 | C10: =-Carry*C9 -> -107.40588 | D10: =-Carry*D9 -> 0 | E10: =-Carry*E9 -> -109.61486 | F10: =B10*P_Base+C10*P_Bull+D10*P_Bear+E10*P_Shock -> -61.158587
A11: (-) Management fees | B11: =-IQT_Committed*Mgmt_Fee*Hold_Short -> -25 | C11: =-IQT_Committed*Mgmt_Fee*Hold_Short -> -25 | D11: =-IQT_Committed*Mgmt_Fee*Hold_Short -> -25 | E11: =-IQT_Committed*Mgmt_Fee*Hold_Short -> -25 | F11: =B11*P_Base+C11*P_Bull+D11*P_Bear+E11*P_Shock -> -25
A12: Net proceeds to LPs | B12: =B6+B10+B11 -> 501.13103 | C12: =C6+C10+C11 -> 771.95554 | D12: =D6+D10+D11 -> 101.29353 | E12: =E6+E10+E11 -> 780.79145 | F12: =B12*P_Base+C12*P_Bull+D12*P_Bear+E12*P_Shock -> 550.81059
A13: Gross MOIC | B13: =B6/IQT_Committed -> 2.2633231 | C13: =C6/IQT_Committed -> 3.6174457 | D13: =D6/IQT_Committed -> 0.5051741 | E13: =E6/IQT_Committed -> 3.6616253 | F13: =F6/IQT_Committed -> 2.5478767
A14: Net MOIC (to LP) | B14: =B12/IQT_Committed -> 2.0045241 | C14: =C12/IQT_Committed -> 3.0878221 | D14: =D12/IQT_Committed -> 0.4051741 | E14: =E12/IQT_Committed -> 3.1231658 | F14: =F12/IQT_Committed -> 2.2032424
A15: Gross IRR | B15: =IF((B6/IQT_Committed)<=0,-1,(B6/IQT_Committed)^(1/Hold_Short)-1) -> 0.17746854 | C15: =IF((C6/IQT_Committed)<=0,-1,(C6/IQT_Committed)^(1/Hold_Short)-1) -> 0.29324379 | D15: =IF((D6/IQT_Committed)<=0,-1,(D6/IQT_Committed)^(1/Hold_Short)-1) -> -0.12765512 | E15: =IF((E6/IQT_Committed)<=0,-1,(E6/IQT_Committed)^(1/Hold_Short)-1) -> 0.29638733 | F15: =IF((F6/IQT_Committed)<=0,-1,(F6/IQT_Committed)^(1/Hold_Short)-1) -> 0.20569006
A16: Net IRR (to LP) | B16: =IF((B12/IQT_Committed)<=0,-1,(B12/IQT_Committed)^(1/Hold_Short)-1) -> 0.14921757 | C16: =IF((C12/IQT_Committed)<=0,-1,(C12/IQT_Committed)^(1/Hold_Short)-1) -> 0.25294052 | D16: =IF((D12/IQT_Committed)<=0,-1,(D12/IQT_Committed)^(1/Hold_Short)-1) -> -0.16530399 | E16: =IF((E12/IQT_Committed)<=0,-1,(E12/IQT_Committed)^(1/Hold_Short)-1) -> 0.25579575 | F16: =IF((F12/IQT_Committed)<=0,-1,(F12/IQT_Committed)^(1/Hold_Short)-1) -> 0.17114982
A17: DPI = TVPI at exit | B17: =B12/IQT_Committed -> 2.0045241 | C17: =C12/IQT_Committed -> 3.0878221 | D17: =D12/IQT_Committed -> 0.4051741 | E17: =E12/IQT_Committed -> 3.1231658 | F17: =F12/IQT_Committed -> 2.2032424
A20: =Hold_Mid&"-YEAR VEHICLE" -> 7-YEAR VEHICLE
A21: Line item ($M) | B21: Base | C21: Bull | D21: Bear | E21: TSMC-Shock | F21: Expected
A22: Gross exit proceeds | B22: ='Portfolio Returns'!C29 -> 778.13077 | C22: ='Portfolio Returns'!F29 -> 1497.0053 | D22: ='Portfolio Returns'!I29 -> 100.03369 | E22: ='Portfolio Returns'!L29 -> 1542.4475 | F22: =B22*P_Base+C22*P_Bull+D22*P_Bear+E22*P_Shock -> 970.78235
A23: (-) Return of committed capital | B23: =-IQT_Committed -> -250 | C23: =-IQT_Committed -> -250 | D23: =-IQT_Committed -> -250 | E23: =-IQT_Committed -> -250 | F23: =B23*P_Base+C23*P_Bull+D23*P_Bear+E23*P_Shock -> -250
A24: (-) Preferred return (8% comp.) | B24: =-IQT_Committed*((1+Pref)^Hold_Mid-1) -> -178.45607 | C24: =-IQT_Committed*((1+Pref)^Hold_Mid-1) -> -178.45607 | D24: =-IQT_Committed*((1+Pref)^Hold_Mid-1) -> -178.45607 | E24: =-IQT_Committed*((1+Pref)^Hold_Mid-1) -> -178.45607 | F24: =B24*P_Base+C24*P_Bull+D24*P_Bear+E24*P_Shock -> -178.45607
A25: Profit above pref (carry base) | B25: =MAX(0,B22+B23+B24) -> 349.6747 | C25: =MAX(0,C22+C23+C24) -> 1068.5492 | D25: =MAX(0,D22+D23+D24) -> 0 | E25: =MAX(0,E22+E23+E24) -> 1113.9915 | F25: =B25*P_Base+C25*P_Bull+D25*P_Bear+E25*P_Shock -> 591.58964
A26: (-) GP carried interest (20%) | B26: =-Carry*B25 -> -69.934941 | C26: =-Carry*C25 -> -213.70985 | D26: =-Carry*D25 -> 0 | E26: =-Carry*E25 -> -222.79829 | F26: =B26*P_Base+C26*P_Bull+D26*P_Bear+E26*P_Shock -> -118.31793
A27: (-) Management fees | B27: =-IQT_Committed*Mgmt_Fee*Hold_Mid -> -35 | C27: =-IQT_Committed*Mgmt_Fee*Hold_Mid -> -35 | D27: =-IQT_Committed*Mgmt_Fee*Hold_Mid -> -35 | E27: =-IQT_Committed*Mgmt_Fee*Hold_Mid -> -35 | F27: =B27*P_Base+C27*P_Bull+D27*P_Bear+E27*P_Shock -> -35
A28: Net proceeds to LPs | B28: =B22+B26+B27 -> 673.19583 | C28: =C22+C26+C27 -> 1248.2955 | D28: =D22+D26+D27 -> 65.033688 | E28: =E22+E26+E27 -> 1284.6492 | F28: =B28*P_Base+C28*P_Bull+D28*P_Bear+E28*P_Shock -> 817.46442
A29: Gross MOIC | B29: =B22/IQT_Committed -> 3.1125231 | C29: =C22/IQT_Committed -> 5.9880212 | D29: =D22/IQT_Committed -> 0.40013475 | E29: =E22/IQT_Committed -> 6.1697901 | F29: =F22/IQT_Committed -> 3.8831294
A30: Net MOIC (to LP) | B30: =B28/IQT_Committed -> 2.6927833 | C30: =C28/IQT_Committed -> 4.9931818 | D30: =D28/IQT_Committed -> 0.26013475 | E30: =E28/IQT_Committed -> 5.1385969 | F30: =F28/IQT_Committed -> 3.2698577
A31: Gross IRR | B31: =IF((B22/IQT_Committed)<=0,-1,(B22/IQT_Committed)^(1/Hold_Mid)-1) -> 0.1761011 | C31: =IF((C22/IQT_Committed)<=0,-1,(C22/IQT_Committed)^(1/Hold_Mid)-1) -> 0.29133962 | D31: =IF((D22/IQT_Committed)<=0,-1,(D22/IQT_Committed)^(1/Hold_Mid)-1) -> -0.12265112 | E31: =IF((E22/IQT_Committed)<=0,-1,(E22/IQT_Committed)^(1/Hold_Mid)-1) -> 0.29686799 | F31: =IF((F22/IQT_Committed)<=0,-1,(F22/IQT_Committed)^(1/Hold_Mid)-1) -> 0.21386066
A32: Net IRR (to LP) | B32: =IF((B28/IQT_Committed)<=0,-1,(B28/IQT_Committed)^(1/Hold_Mid)-1) -> 0.1520129 | C32: =IF((C28/IQT_Committed)<=0,-1,(C28/IQT_Committed)^(1/Hold_Mid)-1) -> 0.25825364 | D32: =IF((D28/IQT_Committed)<=0,-1,(D28/IQT_Committed)^(1/Hold_Mid)-1) -> -0.17499437 | E32: =IF((E28/IQT_Committed)<=0,-1,(E28/IQT_Committed)^(1/Hold_Mid)-1) -> 0.26342429 | F32: =IF((F28/IQT_Committed)<=0,-1,(F28/IQT_Committed)^(1/Hold_Mid)-1) -> 0.18441561
A33: DPI = TVPI at exit | B33: =B28/IQT_Committed -> 2.6927833 | C33: =C28/IQT_Committed -> 4.9931818 | D33: =D28/IQT_Committed -> 0.26013475 | E33: =E28/IQT_Committed -> 5.1385969 | F33: =F28/IQT_Committed -> 3.2698577
A36: =Hold_Long&"-YEAR VEHICLE" -> 10-YEAR VEHICLE
A37: Line item ($M) | B37: Base | C37: Bull | D37: Bear | E37: TSMC-Shock | F37: Expected
A38: Gross exit proceeds | B38: ='Portfolio Returns'!C43 -> 1261.4559 | C38: ='Portfolio Returns'!F43 -> 3197.6972 | D38: ='Portfolio Returns'!I43 -> 73.963354 | E38: ='Portfolio Returns'!L43 -> 3418.1015 | F38: =B38*P_Base+C38*P_Bull+D38*P_Bear+E38*P_Shock -> 1890.8892
A39: (-) Return of committed capital | B39: =-IQT_Committed -> -250 | C39: =-IQT_Committed -> -250 | D39: =-IQT_Committed -> -250 | E39: =-IQT_Committed -> -250 | F39: =B39*P_Base+C39*P_Bull+D39*P_Bear+E39*P_Shock -> -250
A40: (-) Preferred return (8% comp.) | B40: =-IQT_Committed*((1+Pref)^Hold_Long-1) -> -289.73125 | C40: =-IQT_Committed*((1+Pref)^Hold_Long-1) -> -289.73125 | D40: =-IQT_Committed*((1+Pref)^Hold_Long-1) -> -289.73125 | E40: =-IQT_Committed*((1+Pref)^Hold_Long-1) -> -289.73125 | F40: =B40*P_Base+C40*P_Bull+D40*P_Bear+E40*P_Shock -> -289.73125
A41: Profit above pref (carry base) | B41: =MAX(0,B38+B39+B40) -> 721.72469 | C41: =MAX(0,C38+C39+C40) -> 2657.9659 | D41: =MAX(0,D38+D39+D40) -> 0 | E41: =MAX(0,E38+E39+E40) -> 2878.3702 | F41: =B41*P_Base+C41*P_Bull+D41*P_Bear+E41*P_Shock -> 1421.0231
A42: (-) GP carried interest (20%) | B42: =-Carry*B41 -> -144.34494 | C42: =-Carry*C41 -> -531.59319 | D42: =-Carry*D41 -> 0 | E42: =-Carry*E41 -> -575.67404 | F42: =B42*P_Base+C42*P_Bull+D42*P_Bear+E42*P_Shock -> -284.20462
A43: (-) Management fees | B43: =-IQT_Committed*Mgmt_Fee*Hold_Long -> -50 | C43: =-IQT_Committed*Mgmt_Fee*Hold_Long -> -50 | D43: =-IQT_Committed*Mgmt_Fee*Hold_Long -> -50 | E43: =-IQT_Committed*Mgmt_Fee*Hold_Long -> -50 | F43: =B43*P_Base+C43*P_Bull+D43*P_Bear+E43*P_Shock -> -50
A44: Net proceeds to LPs | B44: =B38+B42+B43 -> 1067.111 | C44: =C38+C42+C43 -> 2616.104 | D44: =D38+D42+D43 -> 23.963354 | E44: =E38+E42+E43 -> 2792.4274 | F44: =B44*P_Base+C44*P_Bull+D44*P_Bear+E44*P_Shock -> 1556.6846
A45: Gross MOIC | B45: =B38/IQT_Committed -> 5.0458237 | C45: =C38/IQT_Committed -> 12.790789 | D45: =D38/IQT_Committed -> 0.29585342 | E45: =E38/IQT_Committed -> 13.672406 | F45: =F38/IQT_Committed -> 7.5635568
A46: Net MOIC (to LP) | B46: =B44/IQT_Committed -> 4.268444 | C46: =C44/IQT_Committed -> 10.464416 | D46: =D44/IQT_Committed -> 0.095853416 | E46: =E44/IQT_Committed -> 11.16971 | F46: =F44/IQT_Committed -> 6.2267383
A47: Gross IRR | B47: =IF((B38/IQT_Committed)<=0,-1,(B38/IQT_Committed)^(1/Hold_Long)-1) -> 0.17569104 | C47: =IF((C38/IQT_Committed)<=0,-1,(C38/IQT_Committed)^(1/Hold_Long)-1) -> 0.29029713 | D47: =IF((D38/IQT_Committed)<=0,-1,(D38/IQT_Committed)^(1/Hold_Long)-1) -> -0.11466495 | E47: =IF((E38/IQT_Committed)<=0,-1,(E38/IQT_Committed)^(1/Hold_Long)-1) -> 0.29892625 | F47: =IF((F38/IQT_Committed)<=0,-1,(F38/IQT_Committed)^(1/Hold_Long)-1) -> 0.22425703
A48: Net IRR (to LP) | B48: =IF((B44/IQT_Committed)<=0,-1,(B44/IQT_Committed)^(1/Hold_Long)-1) -> 0.15618401 | C48: =IF((C44/IQT_Committed)<=0,-1,(C44/IQT_Committed)^(1/Hold_Long)-1) -> 0.26465335 | D48: =IF((D44/IQT_Committed)<=0,-1,(D44/IQT_Committed)^(1/Hold_Long)-1) -> -0.20902864 | E48: =IF((E44/IQT_Committed)<=0,-1,(E44/IQT_Committed)^(1/Hold_Long)-1) -> 0.27292902 | F48: =IF((F44/IQT_Committed)<=0,-1,(F44/IQT_Committed)^(1/Hold_Long)-1) -> 0.20067664
A49: DPI = TVPI at exit | B49: =B44/IQT_Committed -> 4.268444 | C49: =C44/IQT_Committed -> 10.464416 | D49: =D44/IQT_Committed -> 0.095853416 | E49: =E44/IQT_Committed -> 11.16971 | F49: =F44/IQT_Committed -> 6.2267383

Sheet IQT Clusters
A1: IQT SLEEVE — STRATEGIC-FUNCTION CLUSTER ROLL-UP
A2: The nine Substrate-anchored names grouped by wartime function (per the IQT strategic analysis). Green links to live per-name figures.
A4: SIZING & STRATEGIC SCORE BY CLUSTER
A5: Strategic cluster | B5: Holdings | C5: Check ($M) | D5: % Sleeve | E5: % Holdco | F5: Avg composite | G5: Avg shock CAGR
A6: TSMC-alternative: packaging & substrates | B6: Substrate, ThinTronics, EUV Tech | C6: =Assumptions!C18+Assumptions!C19+Assumptions!C20 -> 132.5 | D6: =C6/IQT_Committed -> 0.53 | E6: =C6/Holdco_Size -> 0.1577381 | F6: =AVERAGE('Defense Supercycle'!G24,'Defense Supercycle'!G25,'Defense Supercycle'!G26) -> 4.6166667 | G6: =AVERAGE('Defense Supercycle'!I24,'Defense Supercycle'!I25,'Defense Supercycle'!I26) -> 0.376
A7: Denied-environment edge AI | B7: Syntiant, EdgeCortix | C7: =Assumptions!C21+Assumptions!C22 -> 62 | D7: =C7/IQT_Committed -> 0.248 | E7: =C7/Holdco_Size -> 0.073809524 | F7: =AVERAGE('Defense Supercycle'!G27,'Defense Supercycle'!G28) -> 3.025 | G7: =AVERAGE('Defense Supercycle'!I27,'Defense Supercycle'!I28) -> 0.242
A8: Post-Moore's next-gen compute | B8: Infleqtion, Diraq, Mueon | C8: =Assumptions!C23+Assumptions!C24+Assumptions!C25 -> 49 | D8: =C8/IQT_Committed -> 0.196 | E8: =C8/Holdco_Size -> 0.058333333 | F8: =AVERAGE('Defense Supercycle'!G29,'Defense Supercycle'!G30,'Defense Supercycle'!G31) -> 3.4666667 | G8: =AVERAGE('Defense Supercycle'!I29,'Defense Supercycle'!I30,'Defense Supercycle'!I31) -> 0.334
A9: Autonomous sensing (adjacent) | B9: DefendEye | C9: =Assumptions!C26 -> 6.5 | D9: =C9/IQT_Committed -> 0.026 | E9: =C9/Holdco_Size -> 0.0077380952 | F9: =AVERAGE('Defense Supercycle'!G32) -> 1.7 | G9: =AVERAGE('Defense Supercycle'!I32) -> 0.216
A10: IQT SLEEVE TOTAL | C10: =SUM(C6:C9) -> 250 | D10: =SUM(D6:D9) -> 1 | F10: =AVERAGE('Defense Supercycle'!G24,'Defense Supercycle'!G25,'Defense Supercycle'!G26,'Defense Supercycle'!G27,'Defense Supercycle'!G28,'Defense Supercycle'!G29,'Defense Supercycle'!G30,'Defense Supercycle'!G31,'Defense Supercycle'!G32) -> 3.5555556
A12: =Hold_Short&"-YEAR HOLD — CLUSTER GROSS PROCEEDS & MOIC" -> 5-YEAR HOLD — CLUSTER GROSS PROCEEDS & MOIC
A13: Cluster | B13: Check ($M) | C13: Base $ | D13: Base MOIC | E13: Bull $ | F13: Bull MOIC | G13: Bear $ | H13: Bear MOIC | I13: Shock $ | J13: Shock MOIC
A14: TSMC-alternative: packaging & substrates | B14: =Assumptions!C18+Assumptions!C19+Assumptions!C20 -> 132.5 | C14: ='Portfolio Returns'!C6+'Portfolio Returns'!C7+'Portfolio Returns'!C8 -> 293.61934 | D14: =C14/B14 -> 2.215995 | E14: ='Portfolio Returns'!F6+'Portfolio Returns'!F7+'Portfolio Returns'!F8 -> 470.48876 | F14: =E14/B14 -> 3.5508586 | G14: ='Portfolio Returns'!I6+'Portfolio Returns'!I7+'Portfolio Returns'!I8 -> 66.064919 | H14: =G14/B14 -> 0.49860317 | I14: ='Portfolio Returns'!L6+'Portfolio Returns'!L7+'Portfolio Returns'!L8 -> 581.30727 | J14: =I14/B14 -> 4.3872247
A15: Denied-environment edge AI | B15: =Assumptions!C21+Assumptions!C22 -> 62 | C15: ='Portfolio Returns'!C9+'Portfolio Returns'!C10 -> 132.23903 | D15: =C15/B15 -> 2.1328875 | E15: ='Portfolio Returns'!F9+'Portfolio Returns'!F10 -> 212.61653 | F15: =E15/B15 -> 3.4292988 | G15: ='Portfolio Returns'!I9+'Portfolio Returns'!I10 -> 41.289168 | H15: =G15/B15 -> 0.66595432 | I15: ='Portfolio Returns'!L9+'Portfolio Returns'!L10 -> 156.01274 | J15: =I15/B15 -> 2.5163345
A16: Post-Moore's next-gen compute | B16: =Assumptions!C23+Assumptions!C24+Assumptions!C25 -> 49 | C16: ='Portfolio Returns'!C11+'Portfolio Returns'!C12+'Portfolio Returns'!C13 -> 120.98865 | D16: =C16/B16 -> 2.4691562 | E16: ='Portfolio Returns'!F11+'Portfolio Returns'!F12+'Portfolio Returns'!F13 -> 191.54135 | F16: =E16/B16 -> 3.9090071 | G16: ='Portfolio Returns'!I11+'Portfolio Returns'!I12+'Portfolio Returns'!I13 -> 17.62833 | H16: =G16/B16 -> 0.35976184 | I16: ='Portfolio Returns'!L11+'Portfolio Returns'!L12+'Portfolio Returns'!L13 -> 163.39704 | J16: =I16/B16 -> 3.3346334
A17: Autonomous sensing (adjacent) | B17: =Assumptions!C26 -> 6.5 | C17: ='Portfolio Returns'!C14 -> 18.983755 | D17: =C17/B17 -> 2.9205778 | E17: ='Portfolio Returns'!F14 -> 29.714776 | F17: =E17/B17 -> 4.571504 | G17: ='Portfolio Returns'!I14 -> 1.3111084 | H17: =G17/B17 -> 0.20170898 | I17: ='Portfolio Returns'!L14 -> 14.689268 | J17: =I17/B17 -> 2.2598874
A18: SLEEVE TOTAL | B18: =SUM(B14:B17) -> 250 | C18: =SUM(C14:C17) -> 565.83078 | D18: =C18/B18 -> 2.2633231 | E18: =SUM(E14:E17) -> 904.36142 | F18: =E18/B18 -> 3.6174457 | G18: =SUM(G14:G17) -> 126.29353 | H18: =G18/B18 -> 0.5051741 | I18: =SUM(I14:I17) -> 915.40631 | J18: =I18/B18 -> 3.6616253
A20: =Hold_Mid&"-YEAR HOLD — CLUSTER GROSS PROCEEDS & MOIC" -> 7-YEAR HOLD — CLUSTER GROSS PROCEEDS & MOIC
A21: Cluster | B21: Check ($M) | C21: Base $ | D21: Base MOIC | E21: Bull $ | F21: Bull MOIC | G21: Bear $ | H21: Bear MOIC | I21: Shock $ | J21: Shock MOIC
A22: TSMC-alternative: packaging & substrates | B22: =Assumptions!C18+Assumptions!C19+Assumptions!C20 -> 132.5 | C22: ='Portfolio Returns'!C20+'Portfolio Returns'!C21+'Portfolio Returns'!C22 -> 398.05551 | D22: =C22/B22 -> 3.0041925 | E22: ='Portfolio Returns'!F20+'Portfolio Returns'!F21+'Portfolio Returns'!F22 -> 769.33638 | F22: =E22/B22 -> 5.8063123 | G22: ='Portfolio Returns'!I20+'Portfolio Returns'!I21+'Portfolio Returns'!I22 -> 52.728572 | H22: =G22/B22 -> 0.39795149 | I22: ='Portfolio Returns'!L20+'Portfolio Returns'!L21+'Portfolio Returns'!L22 -> 1034.8882 | J22: =I22/B22 -> 7.810477
A23: Denied-environment edge AI | B23: =Assumptions!C21+Assumptions!C22 -> 62 | C23: ='Portfolio Returns'!C23+'Portfolio Returns'!C24 -> 176.67761 | D23: =C23/B23 -> 2.8496389 | E23: ='Portfolio Returns'!F23+'Portfolio Returns'!F24 -> 343.03988 | F23: =E23/B23 -> 5.5329013 | G23: ='Portfolio Returns'!I23+'Portfolio Returns'!I24 -> 34.601015 | H23: =G23/B23 -> 0.55808089 | I23: ='Portfolio Returns'!L23+'Portfolio Returns'!L24 -> 221.47569 | J23: =I23/B23 -> 3.5721886
A24: Post-Moore's next-gen compute | B24: =Assumptions!C23+Assumptions!C24+Assumptions!C25 -> 49 | C24: ='Portfolio Returns'!C25+'Portfolio Returns'!C26+'Portfolio Returns'!C27 -> 174.85609 | D24: =C24/B24 -> 3.5684917 | E24: ='Portfolio Returns'!F25+'Portfolio Returns'!F26+'Portfolio Returns'!F27 -> 331.18438 | F24: =E24/B24 -> 6.758865 | G24: ='Portfolio Returns'!I25+'Portfolio Returns'!I26+'Portfolio Returns'!I27 -> 12.027337 | H24: =G24/B24 -> 0.24545587 | I24: ='Portfolio Returns'!L25+'Portfolio Returns'!L26+'Portfolio Returns'!L27 -> 266.15199 | J24: =I24/B24 -> 5.4316732
A25: Autonomous sensing (adjacent) | B25: =Assumptions!C26 -> 6.5 | C25: ='Portfolio Returns'!C28 -> 28.541563 | D25: =C25/B25 -> 4.3910096 | E25: ='Portfolio Returns'!F28 -> 53.444647 | F25: =E25/B25 -> 8.2222533 | G25: ='Portfolio Returns'!I28 -> 0.67676331 | H25: =G25/B25 -> 0.10411743 | I25: ='Portfolio Returns'!L28 -> 19.931638 | J25: =I25/B25 -> 3.0664058
A26: SLEEVE TOTAL | B26: =SUM(B22:B25) -> 250 | C26: =SUM(C22:C25) -> 778.13077 | D26: =C26/B26 -> 3.1125231 | E26: =SUM(E22:E25) -> 1497.0053 | F26: =E26/B26 -> 5.9880212 | G26: =SUM(G22:G25) -> 100.03369 | H26: =G26/B26 -> 0.40013475 | I26: =SUM(I22:I25) -> 1542.4475 | J26: =I26/B26 -> 6.1697901
A28: =Hold_Long&"-YEAR HOLD — CLUSTER GROSS PROCEEDS & MOIC" -> 10-YEAR HOLD — CLUSTER GROSS PROCEEDS & MOIC
A29: Cluster | B29: Check ($M) | C29: Base $ | D29: Base MOIC | E29: Bull $ | F29: Bull MOIC | G29: Bear $ | H29: Bear MOIC | I29: Shock $ | J29: Shock MOIC
A30: TSMC-alternative: packaging & substrates | B30: =Assumptions!C18+Assumptions!C19+Assumptions!C20 -> 132.5 | C30: ='Portfolio Returns'!C34+'Portfolio Returns'!C35+'Portfolio Returns'!C36 -> 627.31026 | D30: =C30/B30 -> 4.7344171 | E30: ='Portfolio Returns'!F34+'Portfolio Returns'!F35+'Portfolio Returns'!F36 -> 1604.4209 | F30: =E30/B30 -> 12.108837 | G30: ='Portfolio Returns'!I34+'Portfolio Returns'!I35+'Portfolio Returns'!I36 -> 40.227847 | H30: =G30/B30 -> 0.30360639 | I30: ='Portfolio Returns'!L34+'Portfolio Returns'!L35+'Portfolio Returns'!L36 -> 2451.6352 | J30: =I30/B30 -> 18.502908
A31: Denied-environment edge AI | B31: =Assumptions!C21+Assumptions!C22 -> 62 | C31: ='Portfolio Returns'!C37+'Portfolio Returns'!C38 -> 272.74132 | D31: =C31/B31 -> 4.3990536 | E31: ='Portfolio Returns'!F37+'Portfolio Returns'!F38 -> 701.83258 | F31: =E31/B31 -> 11.31988 | G31: ='Portfolio Returns'!I37+'Portfolio Returns'!I38 -> 26.510916 | H31: =G31/B31 -> 0.42759542 | I31: ='Portfolio Returns'!L37+'Portfolio Returns'!L38 -> 372.37855 | J31: =I31/B31 -> 6.0061057
A32: Post-Moore's next-gen compute | B32: =Assumptions!C23+Assumptions!C24+Assumptions!C25 -> 49 | C32: ='Portfolio Returns'!C39+'Portfolio Returns'!C40+'Portfolio Returns'!C41 -> 309.2222 | D32: =C32/B32 -> 6.3106571 | E32: ='Portfolio Returns'!F39+'Portfolio Returns'!F40+'Portfolio Returns'!F41 -> 763.5932 | F32: =E32/B32 -> 15.583535 | G32: ='Portfolio Returns'!I39+'Portfolio Returns'!I40+'Portfolio Returns'!I41 -> 6.975685 | H32: =G32/B32 -> 0.14236092 | I32: ='Portfolio Returns'!L39+'Portfolio Returns'!L40+'Portfolio Returns'!L41 -> 562.84428 | J32: =I32/B32 -> 11.486618
A33: Autonomous sensing (adjacent) | B33: =Assumptions!C26 -> 6.5 | C33: ='Portfolio Returns'!C42 -> 52.18215 | D33: =C33/B33 -> 8.028023 | E33: ='Portfolio Returns'!F42 -> 127.85056 | F33: =E33/B33 -> 19.669317 | G33: ='Portfolio Returns'!I42 -> 0.24890574 | H33: =G33/B33 -> 0.03829319 | I33: ='Portfolio Returns'!L42 -> 31.243381 | J33: =I33/B33 -> 4.8066739
A34: SLEEVE TOTAL | B34: =SUM(B30:B33) -> 250 | C34: =SUM(C30:C33) -> 1261.4559 | D34: =C34/B34 -> 5.0458237 | E34: =SUM(E30:E33) -> 3197.6972 | F34: =E34/B34 -> 12.790789 | G34: =SUM(G30:G33) -> 73.963354 | H34: =G34/B34 -> 0.29585342 | I34: =SUM(I30:I33) -> 3418.1015 | J34: =I34/B34 -> 13.672406
A36: Read: sized by strategic function, the sleeve is ~53% TSMC-alternative packaging/substrates (the sovereign core), ~25% denied-environment edge AI, ~20% next-gen compute, ~3% adjacent autonomy — a deliberate overweight to the domestic fail-safe chokepoints that re-rate hardest in a Taiwan/TSMC shock.

Sheet Weapons Sleeve
A1: WEAPONS SLEEVE — BOTTOM-UP ($390M)
A2: Physical-layer defense holdings. Blue = input. Most entry marks are estimates; several names are access-constrained (see flags). Proceeds use munitions/FMS-adjusted CAGRs (cols S:V).
A4: SLEEVE TERMS | P4: MUNITIONS / FMS OVERLAY — CAGR UPLIFT PER EXPOSURE POINT
A5: Committed ($M) | B5: =Wpn_Size -> 390 | P5: Base uplift / pt | Q5: 0.005
A6: ="Retention @ "&Hold_Short&"yr" -> Retention @ 5yr | B6: 0.92 | P6: Bull uplift / pt | Q6: 0.008
A7: ="Retention @ "&Hold_Mid&"yr" -> Retention @ 7yr | B7: 0.88 | P7: Bear uplift / pt (backlog cushion) | Q7: 0.004
A8: ="Retention @ "&Hold_Long&"yr" -> Retention @ 10yr | B8: 0.82 | P8: Shock uplift / pt | Q8: 0.006
A10: HOLDINGS, ENTRY MARKS & GROWTH ASSUMPTIONS
A11: Company | B11: Entry post-$M | C11: Check ($M) | D11: Own % | E11: Access / structure flag | F11: Base | G11: Bull | H11: Bear | I11: Shock | J11: Valuation basis | P11: Munitions shortage (0-5) | Q11: FMS / export backlog (0-5) | R11: Exposure score | S11: Adj. Base | T11: Adj. Bull | U11: Adj. Bear | V11: Adj. Shock
A12: Saronic | B12: 9250 | C12: 70 | D12: =C12/B12 -> 0.0075675676 | E12: US clean; late/expensive — secondary or late primary | F12: 0.26 | G12: 0.4 | H12: 0 | I12: 0.38 | J12: Series D Mar-26 $9.25B post | P12: 2 | Q12: 3 | R12: =AVERAGE(P12:Q12) -> 2.5 | S12: =F12+$R12*$Q$5 -> 0.2725 | T12: =G12+$R12*$Q$6 -> 0.42 | U12: =H12+$R12*$Q$7 -> 0.01 | V12: =I12+$R12*$Q$8 -> 0.395
A13: Epirus | B13: 1350 | C13: 45 | D13: =C13/B13 -> 0.033333333 | E13: US clean; directed energy / HPM | F13: 0.24 | G13: 0.38 | H13: -0.02 | I13: 0.4 | J13: Est. — Series D 2025 (~$1.35B) | P13: 3 | Q13: 3 | R13: =AVERAGE(P13:Q13) -> 3 | S13: =F13+$R13*$Q$5 -> 0.255 | T13: =G13+$R13*$Q$6 -> 0.404 | U13: =H13+$R13*$Q$7 -> -0.008 | V13: =I13+$R13*$Q$8 -> 0.418
A14: Israel Aerospace Ind. | B14: 16000 | C14: 40 | D14: =C14/B14 -> 0.0025 | E14: IPO ATTEMPT (H2-26) — cornerstone/IPO allocation; ITAR/foreign-own. remains | F14: 0.17 | G14: 0.28 | H14: 0.06 | I14: 0.28 | J14: Est. — IPO-pending (Elbit-comp scale) | P14: 5 | Q14: 5 | R14: =AVERAGE(P14:Q14) -> 5 | S14: =F14+$R14*$Q$5 -> 0.195 | T14: =G14+$R14*$Q$6 -> 0.32 | U14: =H14+$R14*$Q$7 -> 0.08 | V14: =I14+$R14*$Q$8 -> 0.31
A15: Elta Systems | B15: 3000 | C15: 30 | D15: =C15/B15 -> 0.01 | E15: IAI subsidiary — consolidates into IAI IPO; EW/ISR | F15: 0.16 | G15: 0.26 | H15: 0.05 | I15: 0.28 | J15: Est. notional (within IAI) | P15: 2 | Q15: 4 | R15: =AVERAGE(P15:Q15) -> 3 | S15: =F15+$R15*$Q$5 -> 0.175 | T15: =G15+$R15*$Q$6 -> 0.284 | U15: =H15+$R15*$Q$7 -> 0.062 | V15: =I15+$R15*$Q$8 -> 0.298
A16: Heckler & Koch | B16: 1800 | C16: 35 | D16: =C16/B16 -> 0.019444444 | E16: Listed; closely held (CDR) — secondary/block | F16: 0.12 | G16: 0.2 | H16: 0.04 | I16: 0.22 | J16: Est. EV — listed small-arms | P16: 3 | Q16: 3 | R16: =AVERAGE(P16:Q16) -> 3 | S16: =F16+$R16*$Q$5 -> 0.135 | T16: =G16+$R16*$Q$6 -> 0.224 | U16: =H16+$R16*$Q$7 -> 0.052 | V16: =I16+$R16*$Q$8 -> 0.238
A17: Helicon Chemical | B17: 150 | C17: 40 | D17: =C17/B17 -> 0.26666667 | E17: US clean; investable small — real stake | F17: 0.28 | G17: 0.44 | H17: 0.02 | I17: 0.46 | J17: Est. — early-growth energetics | P17: 5 | Q17: 3 | R17: =AVERAGE(P17:Q17) -> 4 | S17: =F17+$R17*$Q$5 -> 0.3 | T17: =G17+$R17*$Q$6 -> 0.472 | U17: =H17+$R17*$Q$7 -> 0.036 | V17: =I17+$R17*$Q$8 -> 0.484
A18: The Ellwood Group | B18: 1200 | C18: 50 | D18: =C18/B18 -> 0.041666667 | E18: FAMILY-OWNED private (Ellwood City, PA) — minority/structured pref; missile-casing & naval open/closed-die forgings | F18: 0.13 | G18: 0.22 | H18: 0.04 | I18: 0.23 | J18: Post-money $1.2B (user input); ~0.9x sales on >$1.3B (AIST) | P18: 5 | Q18: 4 | R18: =AVERAGE(P18:Q18) -> 4.5 | S18: =F18+$R18*$Q$5 -> 0.1525 | T18: =G18+$R18*$Q$6 -> 0.256 | U18: =H18+$R18*$Q$7 -> 0.058 | V18: =I18+$R18*$Q$8 -> 0.257
A19: Superior & Grand Valley | B19: 400 | C19: 40 | D19: =C19/B19 -> 0.1 | E19: Private forger — missile procurement metal forging; entry mark unverified (placeholder) | F19: 0.13 | G19: 0.21 | H19: 0.03 | I19: 0.22 | J19: PLACEHOLDER — no disclosed mark | P19: 5 | Q19: 4 | R19: =AVERAGE(P19:Q19) -> 4.5 | S19: =F19+$R19*$Q$5 -> 0.1525 | T19: =G19+$R19*$Q$6 -> 0.246 | U19: =H19+$R19*$Q$7 -> 0.048 | V19: =I19+$R19*$Q$8 -> 0.247
A20: Applied Research Assoc. | B20: 1200 | C20: 40 | D20: =C20/B20 -> 0.033333333 | E20: EMPLOYEE-OWNED ESOP — structural, hard | F20: 0.14 | G20: 0.22 | H20: 0.06 | I20: 0.24 | J20: Est. EV (~$700M+ rev R&D) | P20: 3 | Q20: 2 | R20: =AVERAGE(P20:Q20) -> 2.5 | S20: =F20+$R20*$Q$5 -> 0.1525 | T20: =G20+$R20*$Q$6 -> 0.24 | U20: =H20+$R20*$Q$7 -> 0.07 | V20: =I20+$R20*$Q$8 -> 0.255
A21: TOTAL (=$390M) | C21: =SUM(C12:C20) -> 390
A23: =Hold_Short&"-YEAR HOLD — GROSS PROCEEDS" -> 5-YEAR HOLD — GROSS PROCEEDS
A24: Company | B24: Check ($M) | C24: Base $ | D24: Base MOIC | E24: Base IRR | F24: Bull $ | G24: Bull MOIC | H24: Bull IRR | I24: Bear $ | J24: Bear MOIC | K24: Bear IRR | L24: Shock $ | M24: Shock MOIC | N24: Shock IRR
A25: =A12 -> Saronic | B25: =C12 -> 70 | C25: =B25*(1+S12)^Hold_Short*Ret_Wpn_Short -> 214.86952 | D25: =C25/B25 -> 3.0695646 | E25: =IF((C25/B25)<=0,-1,(C25/B25)^(1/Hold_Short)-1) -> 0.25145534 | F25: =B25*(1+T12)^Hold_Short*Ret_Wpn_Short -> 371.81558 | G25: =F25/B25 -> 5.3116512 | H25: =IF((F25/B25)<=0,-1,(F25/B25)^(1/Hold_Short)-1) -> 0.39651598 | I25: =B25*(1+U12)^Hold_Short*Ret_Wpn_Short -> 67.685047 | J25: =I25/B25 -> 0.96692925 | K25: =IF((I25/B25)<=0,-1,(I25/B25)^(1/Hold_Short)-1) -> -0.0067034221 | L25: =B25*(1+V12)^Hold_Short*Ret_Wpn_Short -> 340.2177 | M25: =L25/B25 -> 4.8602529 | N25: =IF((L25/B25)<=0,-1,(L25/B25)^(1/Hold_Short)-1) -> 0.37192943
A26: =A13 -> Epirus | B26: =C13 -> 45 | C26: =B26*(1+S13)^Hold_Short*Ret_Wpn_Short -> 128.88992 | D26: =C26/B26 -> 2.8642206 | E26: =IF((C26/B26)<=0,-1,(C26/B26)^(1/Hold_Short)-1) -> 0.23424476 | F26: =B26*(1+T13)^Hold_Short*Ret_Wpn_Short -> 225.85821 | G26: =F26/B26 -> 5.0190713 | H26: =IF((F26/B26)<=0,-1,(F26/B26)^(1/Hold_Short)-1) -> 0.38078059 | I26: =B26*(1+U13)^Hold_Short*Ret_Wpn_Short -> 39.770285 | J26: =I26/B26 -> 0.88378411 | K26: =IF((I26/B26)<=0,-1,(I26/B26)^(1/Hold_Short)-1) -> -0.024405737 | L26: =B26*(1+V13)^Hold_Short*Ret_Wpn_Short -> 237.34577 | M26: =L26/B26 -> 5.2743504 | N26: =IF((L26/B26)<=0,-1,(L26/B26)^(1/Hold_Short)-1) -> 0.39454906
A27: =A14 -> Israel Aerospace Ind. | B27: =C14 -> 40 | C27: =B27*(1+S14)^Hold_Short*Ret_Wpn_Short -> 89.678295 | D27: =C27/B27 -> 2.2419574 | E27: =IF((C27/B27)<=0,-1,(C27/B27)^(1/Hold_Short)-1) -> 0.17523704 | F27: =B27*(1+T14)^Hold_Short*Ret_Wpn_Short -> 147.47468 | G27: =F27/B27 -> 3.6868671 | H27: =IF((F27/B27)<=0,-1,(F27/B27)^(1/Hold_Short)-1) -> 0.29816978 | I27: =B27*(1+U14)^Hold_Short*Ret_Wpn_Short -> 54.071273 | J27: =I27/B27 -> 1.3517818 | K27: =IF((I27/B27)<=0,-1,(I27/B27)^(1/Hold_Short)-1) -> 0.062138915 | L27: =B27*(1+V14)^Hold_Short*Ret_Wpn_Short -> 141.97252 | M27: =L27/B27 -> 3.549313 | N27: =IF((L27/B27)<=0,-1,(L27/B27)^(1/Hold_Short)-1) -> 0.28833517
A28: =A15 -> Elta Systems | B28: =C15 -> 30 | C28: =B28*(1+S15)^Hold_Short*Ret_Wpn_Short -> 61.815646 | D28: =C28/B28 -> 2.0605215 | E28: =IF((C28/B28)<=0,-1,(C28/B28)^(1/Hold_Short)-1) -> 0.1555678 | F28: =B28*(1+T15)^Hold_Short*Ret_Wpn_Short -> 96.323932 | G28: =F28/B28 -> 3.2107977 | H28: =IF((F28/B28)<=0,-1,(F28/B28)^(1/Hold_Short)-1) -> 0.26276515 | I28: =B28*(1+U15)^Hold_Short*Ret_Wpn_Short -> 37.284787 | J28: =I28/B28 -> 1.2428262 | K28: =IF((I28/B28)<=0,-1,(I28/B28)^(1/Hold_Short)-1) -> 0.0444366 | L28: =B28*(1+V15)^Hold_Short*Ret_Wpn_Short -> 101.69101 | M28: =L28/B28 -> 3.3897002 | N28: =IF((L28/B28)<=0,-1,(L28/B28)^(1/Hold_Short)-1) -> 0.27653362
A29: =A16 -> Heckler & Koch | B29: =C16 -> 35 | C29: =B29*(1+S16)^Hold_Short*Ret_Wpn_Short -> 60.650611 | D29: =C29/B29 -> 1.7328746 | E29: =IF((C29/B29)<=0,-1,(C29/B29)^(1/Hold_Short)-1) -> 0.11622932 | F29: =B29*(1+T16)^Hold_Short*Ret_Wpn_Short -> 88.463264 | G29: =F29/B29 -> 2.5275218 | H29: =IF((F29/B29)<=0,-1,(F29/B29)^(1/Hold_Short)-1) -> 0.20375744 | I29: =B29*(1+U16)^Hold_Short*Ret_Wpn_Short -> 41.489153 | J29: =I29/B29 -> 1.1854044 | K29: =IF((I29/B29)<=0,-1,(I29/B29)^(1/Hold_Short)-1) -> 0.03460198 | L29: =B29*(1+V16)^Hold_Short*Ret_Wpn_Short -> 93.639502 | M29: =L29/B29 -> 2.6754143 | N29: =IF((L29/B29)<=0,-1,(L29/B29)^(1/Hold_Short)-1) -> 0.2175259
A30: =A17 -> Helicon Chemical | B30: =C17 -> 40 | C30: =B30*(1+S17)^Hold_Short*Ret_Wpn_Short -> 136.63582 | D30: =C30/B30 -> 3.4158956 | E30: =IF((C30/B30)<=0,-1,(C30/B30)^(1/Hold_Short)-1) -> 0.27850055 | F30: =B30*(1+T17)^Hold_Short*Ret_Wpn_Short -> 254.32372 | G30: =F30/B30 -> 6.358093 | H30: =IF((F30/B30)<=0,-1,(F30/B30)^(1/Hold_Short)-1) -> 0.447656 | I30: =B30*(1+U17)^Hold_Short*Ret_Wpn_Short -> 43.918409 | J30: =I30/B30 -> 1.0979602 | K30: =IF((I30/B30)<=0,-1,(I30/B30)^(1/Hold_Short)-1) -> 0.018866589 | L30: =B30*(1+V17)^Hold_Short*Ret_Wpn_Short -> 264.86058 | M30: =L30/B30 -> 6.6215145 | N30: =IF((L30/B30)<=0,-1,(L30/B30)^(1/Hold_Short)-1) -> 0.45945755
A31: =A18 -> The Ellwood Group | B31: =C18 -> 50 | C31: =B31*(1+S18)^Hold_Short*Ret_Wpn_Short -> 93.532491 | D31: =C31/B31 -> 1.8706498 | E31: =IF((C31/B31)<=0,-1,(C31/B31)^(1/Hold_Short)-1) -> 0.13343991 | F31: =B31*(1+T18)^Hold_Short*Ret_Wpn_Short -> 143.7825 | G31: =F31/B31 -> 2.87565 | H31: =IF((F31/B31)<=0,-1,(F31/B31)^(1/Hold_Short)-1) -> 0.23522822 | I31: =B31*(1+U18)^Hold_Short*Ret_Wpn_Short -> 60.979825 | J31: =I31/B31 -> 1.2195965 | K31: =IF((I31/B31)<=0,-1,(I31/B31)^(1/Hold_Short)-1) -> 0.040502752 | L31: =B31*(1+V18)^Hold_Short*Ret_Wpn_Short -> 144.35579 | M31: =L31/B31 -> 2.8871159 | N31: =IF((L31/B31)<=0,-1,(L31/B31)^(1/Hold_Short)-1) -> 0.23621168
A32: =A19 -> Superior & Grand Valley | B32: =C19 -> 40 | C32: =B32*(1+S19)^Hold_Short*Ret_Wpn_Short -> 74.825993 | D32: =C32/B32 -> 1.8706498 | E32: =IF((C32/B32)<=0,-1,(C32/B32)^(1/Hold_Short)-1) -> 0.13343991 | F32: =B32*(1+T19)^Hold_Short*Ret_Wpn_Short -> 110.51928 | G32: =F32/B32 -> 2.7629819 | H32: =IF((F32/B32)<=0,-1,(F32/B32)^(1/Hold_Short)-1) -> 0.2253936 | I32: =B32*(1+U19)^Hold_Short*Ret_Wpn_Short -> 46.521556 | J32: =I32/B32 -> 1.1630389 | K32: =IF((I32/B32)<=0,-1,(I32/B32)^(1/Hold_Short)-1) -> 0.030668132 | L32: =B32*(1+V19)^Hold_Short*Ret_Wpn_Short -> 110.96348 | M32: =L32/B32 -> 2.7740871 | N32: =IF((L32/B32)<=0,-1,(L32/B32)^(1/Hold_Short)-1) -> 0.22637706
A33: =A20 -> Applied Research Assoc. | B33: =C20 -> 40 | C33: =B33*(1+S20)^Hold_Short*Ret_Wpn_Short -> 74.825993 | D33: =C33/B33 -> 1.8706498 | E33: =IF((C33/B33)<=0,-1,(C33/B33)^(1/Hold_Short)-1) -> 0.13343991 | F33: =B33*(1+T20)^Hold_Short*Ret_Wpn_Short -> 107.8838 | G33: =F33/B33 -> 2.6970951 | H33: =IF((F33/B33)<=0,-1,(F33/B33)^(1/Hold_Short)-1) -> 0.21949283 | I33: =B33*(1+U20)^Hold_Short*Ret_Wpn_Short -> 51.613904 | J33: =I33/B33 -> 1.2903476 | K33: =IF((I33/B33)<=0,-1,(I33/B33)^(1/Hold_Short)-1) -> 0.052304295 | L33: =B33*(1+V20)^Hold_Short*Ret_Wpn_Short -> 114.56882 | M33: =L33/B33 -> 2.8642206 | N33: =IF((L33/B33)<=0,-1,(L33/B33)^(1/Hold_Short)-1) -> 0.23424476
A34: SLEEVE TOTAL | B34: =SUM(B25:B33) -> 390 | C34: =SUM(C25:C33) -> 935.7243 | D34: =C34/B34 -> 2.3992931 | E34: =IF((C34/B34)<=0,-1,(C34/B34)^(1/Hold_Short)-1) -> 0.19128771 | F34: =SUM(F25:F33) -> 1546.445 | G34: =F34/B34 -> 3.9652435 | H34: =IF((F34/B34)<=0,-1,(F34/B34)^(1/Hold_Short)-1) -> 0.31720683 | I34: =SUM(I25:I33) -> 443.33424 | J34: =I34/B34 -> 1.1367545 | K34: =IF((I34/B34)<=0,-1,(I34/B34)^(1/Hold_Short)-1) -> 0.025966861 | L34: =SUM(L25:L33) -> 1549.6152 | M34: =L34/B34 -> 3.9733723 | N34: =IF((L34/B34)<=0,-1,(L34/B34)^(1/Hold_Short)-1) -> 0.31774644
A37: =Hold_Mid&"-YEAR HOLD — GROSS PROCEEDS" -> 7-YEAR HOLD — GROSS PROCEEDS
A38: Company | B38: Check ($M) | C38: Base $ | D38: Base MOIC | E38: Base IRR | F38: Bull $ | G38: Bull MOIC | H38: Bull IRR | I38: Bear $ | J38: Bear MOIC | K38: Bear IRR | L38: Shock $ | M38: Shock MOIC | N38: Shock IRR
A39: =A12 -> Saronic | B39: =C12 -> 70 | C39: =B39*(1+S12)^Hold_Mid*Ret_Wpn_Mid -> 332.80148 | D39: =C39/B39 -> 4.7543069 | E39: =IF((C39/B39)<=0,-1,(C39/B39)^(1/Hold_Mid)-1) -> 0.24947262 | F39: =B39*(1+T12)^Hold_Mid*Ret_Wpn_Mid -> 717.13203 | G39: =F39/B39 -> 10.244743 | H39: =IF((F39/B39)<=0,-1,(F39/B39)^(1/Hold_Mid)-1) -> 0.39430344 | I39: =B39*(1+U12)^Hold_Mid*Ret_Wpn_Mid -> 66.043538 | J39: =I39/B39 -> 0.94347911 | K39: =IF((I39/B39)<=0,-1,(I39/B39)^(1/Hold_Mid)-1) -> -0.0082771337 | L39: =B39*(1+V12)^Hold_Mid*Ret_Wpn_Mid -> 633.28641 | M39: =L39/B39 -> 9.0469487 | N39: =IF((L39/B39)<=0,-1,(L39/B39)^(1/Hold_Mid)-1) -> 0.36975584
A40: =A13 -> Epirus | B40: =C13 -> 45 | C40: =B40*(1+S13)^Hold_Mid*Ret_Wpn_Mid -> 194.17856 | D40: =C40/B40 -> 4.315079 | E40: =IF((C40/B40)<=0,-1,(C40/B40)^(1/Hold_Mid)-1) -> 0.2322893 | F40: =B40*(1+T13)^Hold_Mid*Ret_Wpn_Mid -> 425.85813 | G40: =F40/B40 -> 9.463514 | H40: =IF((F40/B40)<=0,-1,(F40/B40)^(1/Hold_Mid)-1) -> 0.37859297 | I40: =B40*(1+U13)^Hold_Mid*Ret_Wpn_Mid -> 37.434918 | J40: =I40/B40 -> 0.83188708 | K40: =IF((I40/B40)<=0,-1,(I40/B40)^(1/Hold_Mid)-1) -> -0.025951403 | L40: =B40*(1+V13)^Hold_Mid*Ret_Wpn_Mid -> 456.48741 | M40: =L40/B40 -> 10.144165 | N40: =IF((L40/B40)<=0,-1,(L40/B40)^(1/Hold_Mid)-1) -> 0.39233963
A41: =A14 -> Israel Aerospace Ind. | B41: =C14 -> 40 | C41: =B41*(1+S14)^Hold_Mid*Ret_Wpn_Mid -> 122.4949 | D41: =C41/B41 -> 3.0623725 | E41: =IF((C41/B41)<=0,-1,(C41/B41)^(1/Hold_Mid)-1) -> 0.17337507 | F41: =B41*(1+T14)^Hold_Mid*Ret_Wpn_Mid -> 245.78772 | G41: =F41/B41 -> 6.144693 | H41: =IF((F41/B41)<=0,-1,(F41/B41)^(1/Hold_Mid)-1) -> 0.29611305 | I41: =B41*(1+U14)^Hold_Mid*Ret_Wpn_Mid -> 60.326614 | J41: =I41/B41 -> 1.5081654 | K41: =IF((I41/B41)<=0,-1,(I41/B41)^(1/Hold_Mid)-1) -> 0.060456134 | L41: =B41*(1+V14)^Hold_Mid*Ret_Wpn_Mid -> 233.04604 | M41: =L41/B41 -> 5.8261511 | N41: =IF((L41/B41)<=0,-1,(L41/B41)^(1/Hold_Mid)-1) -> 0.28629401
A42: =A15 -> Elta Systems | B42: =C15 -> 30 | C42: =B42*(1+S15)^Hold_Mid*Ret_Wpn_Mid -> 81.633608 | D42: =C42/B42 -> 2.7211203 | E42: =IF((C42/B42)<=0,-1,(C42/B42)^(1/Hold_Mid)-1) -> 0.153737 | F42: =B42*(1+T15)^Hold_Mid*Ret_Wpn_Mid -> 151.90046 | G42: =F42/B42 -> 5.0633487 | H42: =IF((F42/B42)<=0,-1,(F42/B42)^(1/Hold_Mid)-1) -> 0.26076452 | I42: =B42*(1+U15)^Hold_Mid*Ret_Wpn_Mid -> 40.223101 | J42: =I42/B42 -> 1.34077 | K42: =IF((I42/B42)<=0,-1,(I42/B42)^(1/Hold_Mid)-1) -> 0.042781865 | L42: =B42*(1+V15)^Hold_Mid*Ret_Wpn_Mid -> 163.88031 | M42: =L42/B42 -> 5.462677 | N42: =IF((L42/B42)<=0,-1,(L42/B42)^(1/Hold_Mid)-1) -> 0.27451117
A43: =A16 -> Heckler & Koch | B43: =C16 -> 35 | C43: =B43*(1+S16)^Hold_Mid*Ret_Wpn_Mid -> 74.734606 | D43: =C43/B43 -> 2.1352744 | E43: =IF((C43/B43)<=0,-1,(C43/B43)^(1/Hold_Mid)-1) -> 0.11446084 | F43: =B43*(1+T16)^Hold_Mid*Ret_Wpn_Mid -> 126.77121 | G43: =F43/B43 -> 3.6220346 | H43: =IF((F43/B43)<=0,-1,(F43/B43)^(1/Hold_Mid)-1) -> 0.20185029 | I43: =B43*(1+U16)^Hold_Mid*Ret_Wpn_Mid -> 43.919855 | J43: =I43/B43 -> 1.254853 | K43: =IF((I43/B43)<=0,-1,(I43/B43)^(1/Hold_Mid)-1) -> 0.032962827 | L43: =B43*(1+V16)^Hold_Mid*Ret_Wpn_Mid -> 137.27619 | M43: =L43/B43 -> 3.922177 | N43: =IF((L43/B43)<=0,-1,(L43/B43)^(1/Hold_Mid)-1) -> 0.21559694
A44: =A17 -> Helicon Chemical | B44: =C17 -> 40 | C44: =B44*(1+S17)^Hold_Mid*Ret_Wpn_Mid -> 220.87478 | D44: =C44/B44 -> 5.5218695 | E44: =IF((C44/B44)<=0,-1,(C44/B44)^(1/Hold_Mid)-1) -> 0.27647498 | F44: =B44*(1+T17)^Hold_Mid*Ret_Wpn_Mid -> 527.10524 | G44: =F44/B44 -> 13.177631 | H44: =IF((F44/B44)<=0,-1,(F44/B44)^(1/Hold_Mid)-1) -> 0.44536243 | I44: =B44*(1+U17)^Hold_Mid*Ret_Wpn_Mid -> 45.087998 | J44: =I44/B44 -> 1.1271999 | K44: =IF((I44/B44)<=0,-1,(I44/B44)^(1/Hold_Mid)-1) -> 0.017252366 | L44: =B44*(1+V17)^Hold_Mid*Ret_Wpn_Mid -> 557.93033 | M44: =L44/B44 -> 13.948258 | N44: =IF((L44/B44)<=0,-1,(L44/B44)^(1/Hold_Mid)-1) -> 0.45714528
A45: =A18 -> The Ellwood Group | B45: =C18 -> 50 | C45: =B45*(1+S18)^Hold_Mid*Ret_Wpn_Mid -> 118.83359 | D45: =C45/B45 -> 2.3766718 | E45: =IF((C45/B45)<=0,-1,(C45/B45)^(1/Hold_Mid)-1) -> 0.13164416 | F45: =B45*(1+T18)^Hold_Mid*Ret_Wpn_Mid -> 216.96024 | G45: =F45/B45 -> 4.3392048 | H45: =IF((F45/B45)<=0,-1,(F45/B45)^(1/Hold_Mid)-1) -> 0.23327121 | I45: =B45*(1+U18)^Hold_Mid*Ret_Wpn_Mid -> 65.290854 | J45: =I45/B45 -> 1.3058171 | K45: =IF((I45/B45)<=0,-1,(I45/B45)^(1/Hold_Mid)-1) -> 0.03885425 | L45: =B45*(1+V18)^Hold_Mid*Ret_Wpn_Mid -> 218.17231 | M45: =L45/B45 -> 4.3634461 | N45: =IF((L45/B45)<=0,-1,(L45/B45)^(1/Hold_Mid)-1) -> 0.23425311
A46: =A19 -> Superior & Grand Valley | B46: =C19 -> 40 | C46: =B46*(1+S19)^Hold_Mid*Ret_Wpn_Mid -> 95.066871 | D46: =C46/B46 -> 2.3766718 | E46: =IF((C46/B46)<=0,-1,(C46/B46)^(1/Hold_Mid)-1) -> 0.13164416 | F46: =B46*(1+T19)^Hold_Mid*Ret_Wpn_Mid -> 164.12282 | G46: =F46/B46 -> 4.1030704 | H46: =IF((F46/B46)<=0,-1,(F46/B46)^(1/Hold_Mid)-1) -> 0.22345217 | I46: =B46*(1+U19)^Hold_Mid*Ret_Wpn_Mid -> 48.873297 | J46: =I46/B46 -> 1.2218324 | K46: =IF((I46/B46)<=0,-1,(I46/B46)^(1/Hold_Mid)-1) -> 0.029035212 | L46: =B46*(1+V19)^Hold_Mid*Ret_Wpn_Mid -> 165.04708 | M46: =L46/B46 -> 4.1261769 | N46: =IF((L46/B46)<=0,-1,(L46/B46)^(1/Hold_Mid)-1) -> 0.22443407
A47: =A20 -> Applied Research Assoc. | B47: =C20 -> 40 | C47: =B47*(1+S20)^Hold_Mid*Ret_Wpn_Mid -> 95.066871 | D47: =C47/B47 -> 2.3766718 | E47: =IF((C47/B47)<=0,-1,(C47/B47)^(1/Hold_Mid)-1) -> 0.13164416 | F47: =B47*(1+T20)^Hold_Mid*Ret_Wpn_Mid -> 158.66987 | G47: =F47/B47 -> 3.9667467 | H47: =IF((F47/B47)<=0,-1,(F47/B47)^(1/Hold_Mid)-1) -> 0.21756075 | I47: =B47*(1+U20)^Hold_Mid*Ret_Wpn_Mid -> 56.523508 | J47: =I47/B47 -> 1.4130877 | K47: =IF((I47/B47)<=0,-1,(I47/B47)^(1/Hold_Mid)-1) -> 0.050637096 | L47: =B47*(1+V20)^Hold_Mid*Ret_Wpn_Mid -> 172.60316 | M47: =L47/B47 -> 4.315079 | N47: =IF((L47/B47)<=0,-1,(L47/B47)^(1/Hold_Mid)-1) -> 0.2322893
A48: SLEEVE TOTAL | B48: =SUM(B39:B47) -> 390 | C48: =SUM(C39:C47) -> 1335.6853 | D48: =C48/B48 -> 3.424834 | E48: =IF((C48/B48)<=0,-1,(C48/B48)^(1/Hold_Mid)-1) -> 0.19227675 | F48: =SUM(F39:F47) -> 2734.3077 | G48: =F48/B48 -> 7.0110454 | H48: =IF((F48/B48)<=0,-1,(F48/B48)^(1/Hold_Mid)-1) -> 0.3207667 | I48: =SUM(I39:I47) -> 463.72368 | J48: =I48/B48 -> 1.1890351 | K48: =IF((I48/B48)<=0,-1,(I48/B48)^(1/Hold_Mid)-1) -> 0.025043027 | L48: =SUM(L39:L47) -> 2737.7292 | M48: =L48/B48 -> 7.0198185 | N48: =IF((L48/B48)<=0,-1,(L48/B48)^(1/Hold_Mid)-1) -> 0.32100268
A51: =Hold_Long&"-YEAR HOLD — GROSS PROCEEDS" -> 10-YEAR HOLD — GROSS PROCEEDS
A52: Company | B52: Check ($M) | C52: Base $ | D52: Base MOIC | E52: Base IRR | F52: Bull $ | G52: Bull MOIC | H52: Bull IRR | I52: Bear $ | J52: Bear MOIC | K52: Bear IRR | L52: Shock $ | M52: Shock MOIC | N52: Shock IRR
A53: =A12 -> Saronic | B53: =C12 -> 70 | C53: =B53*(1+S12)^Hold_Long*Ret_Wpn_Long -> 638.98373 | D53: =C53/B53 -> 9.128339 | E53: =IF((C53/B53)<=0,-1,(C53/B53)^(1/Hold_Long)-1) -> 0.24749604 | F53: =B53*(1+T12)^Hold_Long*Ret_Wpn_Long -> 1913.354 | G53: =F53/B53 -> 27.333629 | H53: =IF((F53/B53)<=0,-1,(F53/B53)^(1/Hold_Long)-1) -> 0.39209774 | I53: =B53*(1+U12)^Hold_Long*Ret_Wpn_Long -> 63.40531 | J53: =I53/B53 -> 0.90579014 | K53: =IF((I53/B53)<=0,-1,(I53/B53)^(1/Hold_Long)-1) -> -0.0098459709 | L53: =B53*(1+V12)^Hold_Long*Ret_Wpn_Long -> 1601.9685 | M53: =L53/B53 -> 22.885264 | N53: =IF((L53/B53)<=0,-1,(L53/B53)^(1/Hold_Long)-1) -> 0.36758898
A54: =A13 -> Epirus | B54: =C13 -> 45 | C54: =B54*(1+S13)^Hold_Long*Ret_Wpn_Long -> 357.65444 | D54: =C54/B54 -> 7.9478765 | E54: =IF((C54/B54)<=0,-1,(C54/B54)^(1/Hold_Long)-1) -> 0.23033991 | F54: =B54*(1+T13)^Hold_Long*Ret_Wpn_Long -> 1098.2405 | G54: =F54/B54 -> 24.405344 | H54: =IF((F54/B54)<=0,-1,(F54/B54)^(1/Hold_Long)-1) -> 0.37641214 | I54: =B54*(1+U13)^Hold_Long*Ret_Wpn_Long -> 34.052036 | J54: =I54/B54 -> 0.75671192 | K54: =IF((I54/B54)<=0,-1,(I54/B54)^(1/Hold_Long)-1) -> -0.02749228 | L54: =B54*(1+V13)^Hold_Long*Ret_Wpn_Long -> 1212.7986 | M54: =L54/B54 -> 26.951079 | N54: =IF((L54/B54)<=0,-1,(L54/B54)^(1/Hold_Long)-1) -> 0.39013704
A55: =A14 -> Israel Aerospace Ind. | B55: =C14 -> 40 | C55: =B55*(1+S14)^Hold_Long*Ret_Wpn_Long -> 194.78383 | D55: =C55/B55 -> 4.8695957 | E55: =IF((C55/B55)<=0,-1,(C55/B55)^(1/Hold_Long)-1) -> 0.17151888 | F55: =B55*(1+T14)^Hold_Long*Ret_Wpn_Long -> 526.76044 | G55: =F55/B55 -> 13.169011 | H55: =IF((F55/B55)<=0,-1,(F55/B55)^(1/Hold_Long)-1) -> 0.29406269 | I55: =B55*(1+U14)^Hold_Long*Ret_Wpn_Long -> 70.81274 | J55: =I55/B55 -> 1.7703185 | K55: =IF((I55/B55)<=0,-1,(I55/B55)^(1/Hold_Long)-1) -> 0.058778566 | L55: =B55*(1+V14)^Hold_Long*Ret_Wpn_Long -> 488.18766 | M55: =L55/B55 -> 12.204692 | N55: =IF((L55/B55)<=0,-1,(L55/B55)^(1/Hold_Long)-1) -> 0.28425919
A56: =A15 -> Elta Systems | B56: =C15 -> 30 | C56: =B56*(1+S15)^Hold_Long*Ret_Wpn_Long -> 123.39961 | D56: =C56/B56 -> 4.1133202 | E56: =IF((C56/B56)<=0,-1,(C56/B56)^(1/Hold_Long)-1) -> 0.15191187 | F56: =B56*(1+T15)^Hold_Long*Ret_Wpn_Long -> 299.63003 | G56: =F56/B56 -> 9.9876678 | H56: =IF((F56/B56)<=0,-1,(F56/B56)^(1/Hold_Long)-1) -> 0.25877007 | I56: =B56*(1+U15)^Hold_Long*Ret_Wpn_Long -> 44.89317 | J56: =I56/B56 -> 1.496439 | K56: =IF((I56/B56)<=0,-1,(I56/B56)^(1/Hold_Long)-1) -> 0.041132256 | L56: =B56*(1+V15)^Hold_Long*Ret_Wpn_Long -> 333.95045 | M56: =L56/B56 -> 11.131682 | N56: =IF((L56/B56)<=0,-1,(L56/B56)^(1/Hold_Long)-1) -> 0.27249498
A57: =A16 -> Heckler & Koch | B57: =C16 -> 35 | C57: =B57*(1+S16)^Hold_Long*Ret_Wpn_Long -> 101.82174 | D57: =C57/B57 -> 2.9091926 | E57: =IF((C57/B57)<=0,-1,(C57/B57)^(1/Hold_Long)-1) -> 0.11269784 | F57: =B57*(1+T16)^Hold_Long*Ret_Wpn_Long -> 216.61876 | G57: =F57/B57 -> 6.1891076 | H57: =IF((F57/B57)<=0,-1,(F57/B57)^(1/Hold_Long)-1) -> 0.19994904 | I57: =B57*(1+U16)^Hold_Long*Ret_Wpn_Long -> 47.64741 | J57: =I57/B57 -> 1.3613546 | K57: =IF((I57/B57)<=0,-1,(I57/B57)^(1/Hold_Long)-1) -> 0.031328751 | L57: =B57*(1+V16)^Hold_Long*Ret_Wpn_Long -> 242.71038 | M57: =L57/B57 -> 6.9345822 | N57: =IF((L57/B57)<=0,-1,(L57/B57)^(1/Hold_Long)-1) -> 0.21367395
A58: =A17 -> Helicon Chemical | B58: =C17 -> 40 | C58: =B58*(1+S17)^Hold_Long*Ret_Wpn_Long -> 452.17585 | D58: =C58/B58 -> 11.304396 | E58: =IF((C58/B58)<=0,-1,(C58/B58)^(1/Hold_Long)-1) -> 0.27445568 | F58: =B58*(1+T17)^Hold_Long*Ret_Wpn_Long -> 1566.5777 | G58: =F58/B58 -> 39.164443 | H58: =IF((F58/B58)<=0,-1,(F58/B58)^(1/Hold_Long)-1) -> 0.44307597 | I58: =B58*(1+U17)^Hold_Long*Ret_Wpn_Long -> 46.716618 | J58: =I58/B58 -> 1.1679155 | K58: =IF((I58/B58)<=0,-1,(I58/B58)^(1/Hold_Long)-1) -> 0.015643143 | L58: =B58*(1+V17)^Hold_Long*Ret_Wpn_Long -> 1699.0762 | M58: =L58/B58 -> 42.476905 | N58: =IF((L58/B58)<=0,-1,(L58/B58)^(1/Hold_Long)-1) -> 0.45484018
A59: =A18 -> The Ellwood Group | B59: =C18 -> 50 | C59: =B59*(1+S18)^Hold_Long*Ret_Wpn_Long -> 169.50917 | D59: =C59/B59 -> 3.3901834 | E59: =IF((C59/B59)<=0,-1,(C59/B59)^(1/Hold_Long)-1) -> 0.12985398 | F59: =B59*(1+T18)^Hold_Long*Ret_Wpn_Long -> 400.57169 | G59: =F59/B59 -> 8.0114338 | H59: =IF((F59/B59)<=0,-1,(F59/B59)^(1/Hold_Long)-1) -> 0.23132026 | I59: =B59*(1+U18)^Hold_Long*Ret_Wpn_Long -> 72.051086 | J59: =I59/B59 -> 1.4410217 | K59: =IF((I59/B59)<=0,-1,(I59/B59)^(1/Hold_Long)-1) -> 0.037210854 | L59: =B59*(1+V18)^Hold_Long*Ret_Wpn_Long -> 403.7724 | M59: =L59/B59 -> 8.0754481 | N59: =IF((L59/B59)<=0,-1,(L59/B59)^(1/Hold_Long)-1) -> 0.23230061
A60: =A19 -> Superior & Grand Valley | B60: =C19 -> 40 | C60: =B60*(1+S19)^Hold_Long*Ret_Wpn_Long -> 135.60734 | D60: =C60/B60 -> 3.3901834 | E60: =IF((C60/B60)<=0,-1,(C60/B60)^(1/Hold_Long)-1) -> 0.12985398 | F60: =B60*(1+T19)^Hold_Long*Ret_Wpn_Long -> 295.83821 | G60: =F60/B60 -> 7.3959553 | H60: =IF((F60/B60)<=0,-1,(F60/B60)^(1/Hold_Long)-1) -> 0.22151675 | I60: =B60*(1+U19)^Hold_Long*Ret_Wpn_Long -> 52.418751 | J60: =I60/B60 -> 1.3104688 | K60: =IF((I60/B60)<=0,-1,(I60/B60)^(1/Hold_Long)-1) -> 0.027407349 | L60: =B60*(1+V19)^Hold_Long*Ret_Wpn_Long -> 298.22111 | M60: =L60/B60 -> 7.4555277 | N60: =IF((L60/B60)<=0,-1,(L60/B60)^(1/Hold_Long)-1) -> 0.2224971
A61: =A20 -> Applied Research Assoc. | B61: =C20 -> 40 | C61: =B61*(1+S20)^Hold_Long*Ret_Wpn_Long -> 135.60734 | D61: =C61/B61 -> 3.3901834 | E61: =IF((C61/B61)<=0,-1,(C61/B61)^(1/Hold_Long)-1) -> 0.12985398 | F61: =B61*(1+T20)^Hold_Long*Ret_Wpn_Long -> 281.89716 | G61: =F61/B61 -> 7.0474289 | H61: =IF((F61/B61)<=0,-1,(F61/B61)^(1/Hold_Long)-1) -> 0.21563465 | I61: =B61*(1+U20)^Hold_Long*Ret_Wpn_Long -> 64.522565 | J61: =I61/B61 -> 1.6130641 | K61: =IF((I61/B61)<=0,-1,(I61/B61)^(1/Hold_Long)-1) -> 0.048975061 | L61: =B61*(1+V20)^Hold_Long*Ret_Wpn_Long -> 317.91506 | M61: =L61/B61 -> 7.9478765 | N61: =IF((L61/B61)<=0,-1,(L61/B61)^(1/Hold_Long)-1) -> 0.23033991
A62: SLEEVE TOTAL | B62: =SUM(B53:B61) -> 390 | C62: =SUM(C53:C61) -> 2309.543 | D62: =C62/B62 -> 5.9219052 | E62: =IF((C62/B62)<=0,-1,(C62/B62)^(1/Hold_Long)-1) -> 0.19466501 | F62: =SUM(F53:F61) -> 6599.4885 | G62: =F62/B62 -> 16.921765 | H62: =IF((F62/B62)<=0,-1,(F62/B62)^(1/Hold_Long)-1) -> 0.32691947 | I62: =SUM(I53:I61) -> 496.51969 | J62: =I62/B62 -> 1.2731274 | K62: =IF((I62/B62)<=0,-1,(I62/B62)^(1/Hold_Long)-1) -> 0.024441555 | L62: =SUM(L53:L61) -> 6598.6003 | M62: =L62/B62 -> 16.919488 | N62: =IF((L62/B62)<=0,-1,(L62/B62)^(1/Hold_Long)-1) -> 0.32690161

Sheet Consumer Sleeve
A1: CONSUMER / VALUE SLEEVE — BOTTOM-UP ($200M)
A2: Spending-cycle / DTC-value holdings. Blue = input. Proceeds use cohort-adjusted CAGRs (cols T:W): base CAGR + exposure score x uplift per point, where the exposure score weights each name's TAM across prime-earning, entering-prime and retiring-boomer cohorts. Quince & Whoop = confirmed 2026 primary rounds; Farmer's Dog, Thrive, Polymarket & Stripe = market-priced; Made In, Plunge & Goat remain estimates.
A4: SLEEVE TERMS | P4: COHORT-EXPOSURE OVERLAY — CAGR UPLIFT PER EXPOSURE POINT (blue = lever) | S4: COHORT WEIGHTS (must sum to 100%)
A5: Committed ($M) | B5: =Con_Size -> 200 | P5: Base uplift / pt | Q5: 0.005 | S5: Prime earning years (35-54) | T5: 0.5
A6: ="Retention @ "&Hold_Short&"yr" -> Retention @ 5yr | B6: 0.9 | P6: Bull uplift / pt | Q6: 0.008 | S6: Entering prime (22-34) | T6: 0.3
A7: ="Retention @ "&Hold_Mid&"yr" -> Retention @ 7yr | B7: 0.84 | P7: Bear uplift / pt (spend resilience) | Q7: 0.004 | S7: Boomers entering retirement (60+) | T7: 0.2
A8: ="Retention @ "&Hold_Long&"yr" -> Retention @ 10yr | B8: 0.75 | P8: Shock uplift / pt | Q8: 0.003 | S8: Sum (check = 100%) | T8: =SUM(T5:T7) -> 1
A10: HOLDINGS, ENTRY MARKS & GROWTH ASSUMPTIONS
A11: Company | B11: Entry post-$M | C11: Check ($M) | D11: Own % | E11: Channel / access note | F11: Base | G11: Bull | H11: Bear | I11: Shock | J11: Valuation basis | P11: Prime-earning TAM (0-5) | Q11: Entering-prime TAM (0-5) | R11: Boomer / retiree TAM (0-5) | S11: Exposure score | T11: Adj. Base | U11: Adj. Bull | V11: Adj. Bear | W11: Adj. Shock
A12: Quince | B12: 10100 | C12: 35 | D12: =C12/B12 -> 0.0034653465 | E12: Direct secondary/late-primary; watch ICONIQ round terms | F12: 0.28 | G12: 0.45 | H12: 0.02 | I12: -0.18 | J12: Series E Mar-26 $10.1B post (ICONIQ-led $500M; >$1B ARR, M2C manufacturer-to-consumer model) | P12: 4 | Q12: 5 | R12: 2 | S12: =P12*$T$5+Q12*$T$6+R12*$T$7 -> 3.9 | T12: =F12+$S12*$Q$5 -> 0.2995 | U12: =G12+$S12*$Q$6 -> 0.4812 | V12: =H12+$S12*$Q$7 -> 0.0356 | W12: =I12+$S12*$Q$8 -> -0.1683
A13: Whoop | B13: 10100 | C13: 31.5 | D13: =C13/B13 -> 0.0031188119 | E13: Direct secondary/late-primary; IPO window = public-exit optionality | F13: 0.27 | G13: 0.42 | H13: -0.03 | I13: -0.16 | J13: Series G Mar-26 $10.1B post ($575M raise; IPO-track, medical-grade/glucose-monitoring expansion) | P13: 4 | Q13: 4 | R13: 2 | S13: =P13*$T$5+Q13*$T$6+R13*$T$7 -> 3.6 | T13: =F13+$S13*$Q$5 -> 0.288 | U13: =G13+$S13*$Q$6 -> 0.4488 | V13: =H13+$S13*$Q$7 -> -0.0156 | W13: =I13+$S13*$Q$8 -> -0.1492
A14: The Farmer's Dog | B14: 3760 | C14: 24.5 | D14: =C14/B14 -> 0.0065159574 | E14: WALMART.COM LAUNCH (2025) — DTC-only to omni-channel; secondary access | F14: 0.22 | G14: 0.34 | H14: 0.1 | I14: -0.05 | J14: MARKET-PRICED — Forge secondary $23.64/sh (22-Sep-26) = $3.76B implied, up from $2.5B Series E ($15.72/sh, Jun-22); profitable, >$1B ann. revenue | P14: 4 | Q14: 3 | R14: 4 | S14: =P14*$T$5+Q14*$T$6+R14*$T$7 -> 3.7 | T14: =F14+$S14*$Q$5 -> 0.2385 | U14: =G14+$S14*$Q$6 -> 0.3696 | V14: =H14+$S14*$Q$7 -> 0.1148 | W14: =I14+$S14*$Q$8 -> -0.0389
A15: Made In Cookware | B15: 280 | C15: 17.5 | D15: =C15/B15 -> 0.0625 | E15: DTC + wholesale/restaurant placements; secondary access, thin float | F15: 0.14 | G15: 0.26 | H15: -0.1 | I15: -0.14 | J15: Est. EV — only ~$8.3M ever raised ($5M 2019 seed, KarpReilly-backed 2017); NO secondary market exists — least-grounded mark in the sleeve | P15: 4 | Q15: 2 | R15: 4 | S15: =P15*$T$5+Q15*$T$6+R15*$T$7 -> 3.4 | T15: =F15+$S15*$Q$5 -> 0.157 | U15: =G15+$S15*$Q$6 -> 0.2872 | V15: =H15+$S15*$Q$7 -> -0.0864 | W15: =I15+$S15*$Q$8 -> -0.1298
A16: Thrive Market | B16: 945 | C16: 14 | D16: =C16/B16 -> 0.014814815 | E16: Membership DTC; IPO-candidate, pre-IPO secondary | F16: 0.07 | G16: 0.16 | H16: -0.05 | I16: -0.08 | J16: MARKET-PRICED — Forge secondary $17.98/sh (21-Sep-26) implies ~$945M, DOWN ~27% from Series C $1.29B post ($24.60/sh, Jul-21) despite revenue growth $400M→$700M+ — real multiple compression | P16: 4 | Q16: 3 | R16: 3 | S16: =P16*$T$5+Q16*$T$6+R16*$T$7 -> 3.5 | T16: =F16+$S16*$Q$5 -> 0.0875 | U16: =G16+$S16*$Q$6 -> 0.188 | V16: =H16+$S16*$Q$7 -> -0.036 | W16: =I16+$S16*$Q$8 -> -0.0695
A17: Plunge | B17: 110 | C17: 7 | D17: =C17/B17 -> 0.063636364 | E17: Wefunder community round (2025) — direct primary access, small check | F17: 0.2 | G17: 0.5 | H17: -0.22 | I17: -0.28 | J17: Est. — NO priced VC round exists (only $4.75M raised incl. crowdfunding); 2021 Shark Tank ask was $10M (declined) vs. ~$200M lifetime sales by 2025 — mostly self-funded growth, entry mark is a rough estimate | P17: 3 | Q17: 4 | R17: 2 | S17: =P17*$T$5+Q17*$T$6+R17*$T$7 -> 3.1 | T17: =F17+$S17*$Q$5 -> 0.2155 | U17: =G17+$S17*$Q$6 -> 0.5248 | V17: =H17+$S17*$Q$7 -> -0.2076 | W17: =I17+$S17*$Q$8 -> -0.2707
A18: Polymarket | B18: 18000 | C18: 10.5 | D18: =C18/B18 -> 0.00058333333 | E18: Secondary / late-primary; prediction-market expansion (US regulated + ICE distribution) | F18: 0.25 | G18: 0.4 | H18: -0.05 | I18: -0.12 | J18: MARKET-PRICED — secondary ~$14-21B range (Sep-26); ICE-backed; US regulated expansion & sports/politics volume convexity | P18: 3 | Q18: 5 | R18: 1 | S18: =P18*$T$5+Q18*$T$6+R18*$T$7 -> 3.2 | T18: =F18+$S18*$Q$5 -> 0.266 | U18: =G18+$S18*$Q$6 -> 0.4256 | V18: =H18+$S18*$Q$7 -> -0.0372 | W18: =I18+$S18*$Q$8 -> -0.1104
A19: Goat Group | B19: 3730 | C19: 15 | D19: =C19/B19 -> 0.0040214477 | E19: Secondary access, thin float; last priced Series F (Jun-21); no active secondary quote — re-underwrite before check | F19: 0.15 | G19: 0.28 | H19: -0.12 | I19: -0.16 | J19: Est. — last priced Series F 24-Jun-21 $3.73B post ($5.82/sh; $195M raise, Dragoneer/Franklin Templeton); Forge Global lists GOAT with no live secondary match ("price not yet available") — 5-yr-stale mark, least-grounded alongside Made In/Plunge; no IPO filed | P19: 2 | Q19: 5 | R19: 0 | S19: =P19*$T$5+Q19*$T$6+R19*$T$7 -> 2.5 | T19: =F19+$S19*$Q$5 -> 0.1625 | U19: =G19+$S19*$Q$6 -> 0.3 | V19: =H19+$S19*$Q$7 -> -0.11 | W19: =I19+$S19*$Q$8 -> -0.1525
A20: Stripe | B20: 159000 | C20: 45 | D20: =C20/B20 -> 0.00028301887 | E20: Employee/investor tender access; most liquid, most de-risked name in the sleeve — recurring annual tender cadence gives a real-time mark | F20: 0.18 | G20: 0.35 | H20: -0.05 | I20: -0.08 | J20: MARKET-PRICED — Feb-26 employee tender $159B post (Bloomberg/CNBC, 24-Feb-26), up from ~$140B guided 9-Feb-26 and ~$91.5B Feb-25 tender; total payment volume +34% YoY (~$1.9-2T annualized); IPO-track, profitable at scale | P20: 4 | Q20: 4 | R20: 3 | S20: =P20*$T$5+Q20*$T$6+R20*$T$7 -> 3.8 | T20: =F20+$S20*$Q$5 -> 0.199 | U20: =G20+$S20*$Q$6 -> 0.3804 | V20: =H20+$S20*$Q$7 -> -0.0348 | W20: =I20+$S20*$Q$8 -> -0.0686
A21: TOTAL (=$200M) | C21: =SUM(C12:C20) -> 200
A23: =Hold_Short&"-YEAR HOLD — GROSS PROCEEDS" -> 5-YEAR HOLD — GROSS PROCEEDS
A24: Company | B24: Check ($M) | C24: Base $ | D24: Base MOIC | E24: Base IRR | F24: Bull $ | G24: Bull MOIC | H24: Bull IRR | I24: Bear $ | J24: Bear MOIC | K24: Bear IRR | L24: Shock $ | M24: Shock MOIC | N24: Shock IRR
A25: =A12 -> Quince | B25: =C12 -> 35 | C25: =B25*(1+T12)^Hold_Short*Ret_Con_Short -> 116.73255 | D25: =C25/B25 -> 3.3352157 | E25: =IF((C25/B25)<=0,-1,(C25/B25)^(1/Hold_Short)-1) -> 0.2724033 | F25: =B25*(1+U12)^Hold_Short*Ret_Con_Short -> 224.58413 | G25: =F25/B25 -> 6.4166895 | H25: =IF((F25/B25)<=0,-1,(F25/B25)^(1/Hold_Short)-1) -> 0.45031455 | I25: =B25*(1+V12)^Hold_Short*Ret_Con_Short -> 37.520685 | J25: =I25/B25 -> 1.0720196 | K25: =IF((I25/B25)<=0,-1,(I25/B25)^(1/Hold_Short)-1) -> 0.014006044 | L25: =B25*(1+W12)^Hold_Short*Ret_Con_Short -> 12.535569 | M25: =L25/B25 -> 0.35815912 | N25: =IF((L25/B25)<=0,-1,(L25/B25)^(1/Hold_Short)-1) -> -0.18564231
A26: =A13 -> Whoop | B26: =C13 -> 31.5 | C26: =B26*(1+T13)^Hold_Short*Ret_Con_Short -> 100.49221 | D26: =C26/B26 -> 3.1902288 | E26: =IF((C26/B26)<=0,-1,(C26/B26)^(1/Hold_Short)-1) -> 0.26114309 | F26: =B26*(1+U13)^Hold_Short*Ret_Con_Short -> 180.96528 | G26: =F26/B26 -> 5.7449294 | H26: =IF((F26/B26)<=0,-1,(F26/B26)^(1/Hold_Short)-1) -> 0.41859015 | I26: =B26*(1+V13)^Hold_Short*Ret_Con_Short -> 26.206625 | J26: =I26/B26 -> 0.83195634 | K26: =IF((I26/B26)<=0,-1,(I26/B26)^(1/Hold_Short)-1) -> -0.036126352 | L26: =B26*(1+W13)^Hold_Short*Ret_Con_Short -> 12.638353 | M26: =L26/B26 -> 0.40121754 | N26: =IF((L26/B26)<=0,-1,(L26/B26)^(1/Hold_Short)-1) -> -0.16694057
A27: =A14 -> The Farmer's Dog | B27: =C14 -> 24.5 | C27: =B27*(1+T14)^Hold_Short*Ret_Con_Short -> 64.252296 | D27: =C27/B27 -> 2.6225427 | E27: =IF((C27/B27)<=0,-1,(C27/B27)^(1/Hold_Short)-1) -> 0.21267525 | F27: =B27*(1+U14)^Hold_Short*Ret_Con_Short -> 106.26184 | G27: =F27/B27 -> 4.3372179 | H27: =IF((F27/B27)<=0,-1,(F27/B27)^(1/Hold_Short)-1) -> 0.3410416 | I27: =B27*(1+V14)^Hold_Short*Ret_Con_Short -> 37.965873 | J27: =I27/B27 -> 1.5496275 | K27: =IF((I27/B27)<=0,-1,(I27/B27)^(1/Hold_Short)-1) -> 0.091554594 | L27: =B27*(1+W14)^Hold_Short*Ret_Con_Short -> 18.082209 | M27: =L27/B27 -> 0.73804934 | N27: =IF((L27/B27)<=0,-1,(L27/B27)^(1/Hold_Short)-1) -> -0.058940509
A28: =A15 -> Made In Cookware | B28: =C15 -> 17.5 | C28: =B28*(1+T15)^Hold_Short*Ret_Con_Short -> 32.654824 | D28: =C28/B28 -> 1.86599 | E28: =IF((C28/B28)<=0,-1,(C28/B28)^(1/Hold_Short)-1) -> 0.13287466 | F28: =B28*(1+U15)^Hold_Short*Ret_Con_Short -> 55.655836 | G28: =F28/B28 -> 3.1803335 | H28: =IF((F28/B28)<=0,-1,(F28/B28)^(1/Hold_Short)-1) -> 0.26035977 | I28: =B28*(1+V15)^Hold_Short*Ret_Con_Short -> 10.024461 | J28: =I28/B28 -> 0.57282632 | K28: =IF((I28/B28)<=0,-1,(I28/B28)^(1/Hold_Short)-1) -> -0.10545006 | L28: =B28*(1+W15)^Hold_Short*Ret_Con_Short -> 7.8591568 | M28: =L28/B28 -> 0.44909467 | N28: =IF((L28/B28)<=0,-1,(L28/B28)^(1/Hold_Short)-1) -> -0.1479451
A29: =A16 -> Thrive Market | B29: =C16 -> 14 | C29: =B29*(1+T16)^Hold_Short*Ret_Con_Short -> 19.165355 | D29: =C29/B29 -> 1.3689539 | E29: =IF((C29/B29)<=0,-1,(C29/B29)^(1/Hold_Short)-1) -> 0.064823844 | F29: =B29*(1+U16)^Hold_Short*Ret_Con_Short -> 29.816231 | G29: =F29/B29 -> 2.1297308 | H29: =IF((F29/B29)<=0,-1,(F29/B29)^(1/Hold_Short)-1) -> 0.16322825 | I29: =B29*(1+V16)^Hold_Short*Ret_Con_Short -> 10.489522 | J29: =I29/B29 -> 0.7492516 | K29: =IF((I29/B29)<=0,-1,(I29/B29)^(1/Hold_Short)-1) -> -0.056100979 | L29: =B29*(1+W16)^Hold_Short*Ret_Con_Short -> 8.7892624 | M29: =L29/B29 -> 0.62780446 | N29: =IF((L29/B29)<=0,-1,(L29/B29)^(1/Hold_Short)-1) -> -0.088902449
A30: =A17 -> Plunge | B30: =C17 -> 7 | C30: =B30*(1+T17)^Hold_Short*Ret_Con_Short -> 16.715346 | D30: =C30/B30 -> 2.3879065 | E30: =IF((C30/B30)<=0,-1,(C30/B30)^(1/Hold_Short)-1) -> 0.19015483 | F30: =B30*(1+U17)^Hold_Short*Ret_Con_Short -> 51.928403 | G30: =F30/B30 -> 7.4183433 | H30: =IF((F30/B30)<=0,-1,(F30/B30)^(1/Hold_Short)-1) -> 0.49300542 | I30: =B30*(1+V17)^Hold_Short*Ret_Con_Short -> 1.9681713 | J30: =I30/B30 -> 0.28116732 | K30: =IF((I30/B30)<=0,-1,(I30/B30)^(1/Hold_Short)-1) -> -0.22412284 | L30: =B30*(1+W17)^Hold_Short*Ret_Con_Short -> 1.2997853 | M30: =L30/B30 -> 0.18568361 | N30: =IF((L30/B30)<=0,-1,(L30/B30)^(1/Hold_Short)-1) -> -0.2859071
A31: =A18 -> Polymarket | B31: =C18 -> 10.5 | C31: =B31*(1+T18)^Hold_Short*Ret_Con_Short -> 30.732673 | D31: =C31/B31 -> 2.9269213 | E31: =IF((C31/B31)<=0,-1,(C31/B31)^(1/Hold_Short)-1) -> 0.23960183 | F31: =B31*(1+U18)^Hold_Short*Ret_Con_Short -> 55.644243 | G31: =F31/B31 -> 5.2994518 | H31: =IF((F31/B31)<=0,-1,(F31/B31)^(1/Hold_Short)-1) -> 0.39587391 | I31: =B31*(1+V18)^Hold_Short*Ret_Con_Short -> 7.8182979 | J31: =I31/B31 -> 0.7445998 | K31: =IF((I31/B31)<=0,-1,(I31/B31)^(1/Hold_Short)-1) -> -0.057275957 | L31: =B31*(1+W18)^Hold_Short*Ret_Con_Short -> 5.2650886 | M31: =L31/B31 -> 0.501437 | N31: =IF((L31/B31)<=0,-1,(L31/B31)^(1/Hold_Short)-1) -> -0.12894962
A32: =A19 -> Goat Group | B32: =C19 -> 15 | C32: =B32*(1+T19)^Hold_Short*Ret_Con_Short -> 28.661478 | D32: =C32/B32 -> 1.9107652 | E32: =IF((C32/B32)<=0,-1,(C32/B32)^(1/Hold_Short)-1) -> 0.13825997 | F32: =B32*(1+U19)^Hold_Short*Ret_Con_Short -> 50.124555 | G32: =F32/B32 -> 3.341637 | H32: =IF((F32/B32)<=0,-1,(F32/B32)^(1/Hold_Short)-1) -> 0.27289287 | I32: =B32*(1+V19)^Hold_Short*Ret_Con_Short -> 7.5384803 | J32: =I32/B32 -> 0.50256535 | K32: =IF((I32/B32)<=0,-1,(I32/B32)^(1/Hold_Short)-1) -> -0.12855796 | L32: =B32*(1+W19)^Hold_Short*Ret_Con_Short -> 5.9024498 | M32: =L32/B32 -> 0.39349665 | N32: =IF((L32/B32)<=0,-1,(L32/B32)^(1/Hold_Short)-1) -> -0.17017176
A33: =A20 -> Stripe | B33: =C20 -> 45 | C33: =B33*(1+T20)^Hold_Short*Ret_Con_Short -> 100.35776 | D33: =C33/B33 -> 2.2301723 | E33: =IF((C33/B33)<=0,-1,(C33/B33)^(1/Hold_Short)-1) -> 0.17399889 | F33: =B33*(1+U20)^Hold_Short*Ret_Con_Short -> 202.9924 | G33: =F33/B33 -> 4.5109422 | H33: =IF((F33/B33)<=0,-1,(F33/B33)^(1/Hold_Short)-1) -> 0.3516164 | I33: =B33*(1+V20)^Hold_Short*Ret_Con_Short -> 33.926698 | J33: =I33/B33 -> 0.75392662 | K33: =IF((I33/B33)<=0,-1,(I33/B33)^(1/Hold_Short)-1) -> -0.054926001 | L33: =B33*(1+W20)^Hold_Short*Ret_Con_Short -> 28.388091 | M33: =L33/B33 -> 0.63084647 | N33: =IF((L33/B33)<=0,-1,(L33/B33)^(1/Hold_Short)-1) -> -0.088021215
A34: SLEEVE TOTAL | B34: =SUM(B25:B33) -> 200 | C34: =SUM(C25:C33) -> 509.76448 | D34: =C34/B34 -> 2.5488224 | E34: =IF((C34/B34)<=0,-1,(C34/B34)^(1/Hold_Short)-1) -> 0.20577955 | F34: =SUM(F25:F33) -> 957.97292 | G34: =F34/B34 -> 4.7898646 | H34: =IF((F34/B34)<=0,-1,(F34/B34)^(1/Hold_Short)-1) -> 0.36793243 | I34: =SUM(I25:I33) -> 173.45881 | J34: =I34/B34 -> 0.86729407 | K34: =IF((I34/B34)<=0,-1,(I34/B34)^(1/Hold_Short)-1) -> -0.028073832 | L34: =SUM(L25:L33) -> 100.75996 | M34: =L34/B34 -> 0.50379982 | N34: =IF((L34/B34)<=0,-1,(L34/B34)^(1/Hold_Short)-1) -> -0.12813027
A37: =Hold_Mid&"-YEAR HOLD — GROSS PROCEEDS" -> 7-YEAR HOLD — GROSS PROCEEDS
A38: Company | B38: Check ($M) | C38: Base $ | D38: Base MOIC | E38: Base IRR | F38: Bull $ | G38: Bull MOIC | H38: Bull IRR | I38: Bear $ | J38: Bear MOIC | K38: Bear IRR | L38: Shock $ | M38: Shock MOIC | N38: Shock IRR
A39: =A12 -> Quince | B39: =C12 -> 35 | C39: =B39*(1+T12)^Hold_Mid*Ret_Con_Mid -> 183.98453 | D39: =C39/B39 -> 5.256701 | E39: =IF((C39/B39)<=0,-1,(C39/B39)^(1/Hold_Mid)-1) -> 0.26753231 | F39: =B39*(1+U12)^Hold_Mid*Ret_Con_Mid -> 459.87866 | G39: =F39/B39 -> 13.13939 | H39: =IF((F39/B39)<=0,-1,(F39/B39)^(1/Hold_Mid)-1) -> 0.44476249 | I39: =B39*(1+V12)^Hold_Mid*Ret_Con_Mid -> 37.557063 | J39: =I39/B39 -> 1.0730589 | K39: =IF((I39/B39)<=0,-1,(I39/B39)^(1/Hold_Mid)-1) -> 0.010124249 | L39: =B39*(1+W12)^Hold_Mid*Ret_Con_Mid -> 8.0930876 | M39: =L39/B39 -> 0.23123107 | N39: =IF((L39/B39)<=0,-1,(L39/B39)^(1/Hold_Mid)-1) -> -0.18875981
A40: =A13 -> Whoop | B40: =C13 -> 31.5 | C40: =B40*(1+T13)^Hold_Mid*Ret_Con_Mid -> 155.59688 | D40: =C40/B40 -> 4.9395835 | E40: =IF((C40/B40)<=0,-1,(C40/B40)^(1/Hold_Mid)-1) -> 0.25631521 | F40: =B40*(1+U13)^Hold_Mid*Ret_Con_Mid -> 354.52666 | G40: =F40/B40 -> 11.254815 | H40: =IF((F40/B40)<=0,-1,(F40/B40)^(1/Hold_Mid)-1) -> 0.41315953 | I40: =B40*(1+V13)^Hold_Mid*Ret_Con_Mid -> 23.702332 | J40: =I40/B40 -> 0.75245498 | K40: =IF((I40/B40)<=0,-1,(I40/B40)^(1/Hold_Mid)-1) -> -0.039816231 | L40: =B40*(1+W13)^Hold_Mid*Ret_Con_Mid -> 8.5385123 | M40: =L40/B40 -> 0.27106388 | N40: =IF((L40/B40)<=0,-1,(L40/B40)^(1/Hold_Mid)-1) -> -0.17012967
A41: =A14 -> The Farmer's Dog | B41: =C14 -> 24.5 | C41: =B41*(1+T14)^Hold_Mid*Ret_Con_Mid -> 91.985092 | D41: =C41/B41 -> 3.7544935 | E41: =IF((C41/B41)<=0,-1,(C41/B41)^(1/Hold_Mid)-1) -> 0.20803291 | F41: =B41*(1+U14)^Hold_Mid*Ret_Con_Mid -> 186.03797 | G41: =F41/B41 -> 7.5933867 | H41: =IF((F41/B41)<=0,-1,(F41/B41)^(1/Hold_Mid)-1) -> 0.33590785 | I41: =B41*(1+V14)^Hold_Mid*Ret_Con_Mid -> 44.037645 | J41: =I41/B41 -> 1.7974549 | K41: =IF((I41/B41)<=0,-1,(I41/B41)^(1/Hold_Mid)-1) -> 0.08737593 | L41: =B41*(1+W14)^Hold_Mid*Ret_Con_Mid -> 15.589257 | M41: =L41/B41 -> 0.6362962 | N41: =IF((L41/B41)<=0,-1,(L41/B41)^(1/Hold_Mid)-1) -> -0.062543052
A42: =A15 -> Made In Cookware | B42: =C15 -> 17.5 | C42: =B42*(1+T15)^Hold_Mid*Ret_Con_Mid -> 40.799125 | D42: =C42/B42 -> 2.3313786 | E42: =IF((C42/B42)<=0,-1,(C42/B42)^(1/Hold_Mid)-1) -> 0.12853781 | F42: =B42*(1+U15)^Hold_Mid*Ret_Con_Mid -> 86.067572 | G42: =F42/B42 -> 4.918147 | H42: =IF((F42/B42)<=0,-1,(F42/B42)^(1/Hold_Mid)-1) -> 0.25553489 | I42: =B42*(1+V15)^Hold_Mid*Ret_Con_Mid -> 7.8092616 | J42: =I42/B42 -> 0.44624352 | K42: =IF((I42/B42)<=0,-1,(I42/B42)^(1/Hold_Mid)-1) -> -0.10887455 | L42: =B42*(1+W15)^Hold_Mid*Ret_Con_Mid -> 5.5545757 | M42: =L42/B42 -> 0.31740432 | N42: =IF((L42/B42)<=0,-1,(L42/B42)^(1/Hold_Mid)-1) -> -0.15120691
A43: =A16 -> Thrive Market | B43: =C16 -> 14 | C43: =B43*(1+T16)^Hold_Mid*Ret_Con_Mid -> 21.154959 | D43: =C43/B43 -> 1.5110685 | E43: =IF((C43/B43)<=0,-1,(C43/B43)^(1/Hold_Mid)-1) -> 0.06074751 | F43: =B43*(1+U16)^Hold_Mid*Ret_Con_Mid -> 39.275562 | G43: =F43/B43 -> 2.8053973 | H43: =IF((F43/B43)<=0,-1,(F43/B43)^(1/Hold_Mid)-1) -> 0.15877521 | I43: =B43*(1+V16)^Hold_Mid*Ret_Con_Mid -> 9.0980131 | J43: =I43/B43 -> 0.64985808 | K43: =IF((I43/B43)<=0,-1,(I43/B43)^(1/Hold_Mid)-1) -> -0.059714392 | L43: =B43*(1+W16)^Hold_Mid*Ret_Con_Mid -> 7.1026753 | M43: =L43/B43 -> 0.50733395 | N43: =IF((L43/B43)<=0,-1,(L43/B43)^(1/Hold_Mid)-1) -> -0.092390292
A44: =A17 -> Plunge | B44: =C17 -> 7 | C44: =B44*(1+T17)^Hold_Mid*Ret_Con_Mid -> 23.04953 | D44: =C44/B44 -> 3.29279 | E44: =IF((C44/B44)<=0,-1,(C44/B44)^(1/Hold_Mid)-1) -> 0.18559871 | F44: =B44*(1+U17)^Hold_Mid*Ret_Con_Mid -> 112.68536 | G44: =F44/B44 -> 16.097909 | H44: =IF((F44/B44)<=0,-1,(F44/B44)^(1/Hold_Mid)-1) -> 0.48728993 | I44: =B44*(1+V17)^Hold_Mid*Ret_Con_Mid -> 1.153423 | J44: =I44/B44 -> 0.16477471 | K44: =IF((I44/B44)<=0,-1,(I44/B44)^(1/Hold_Mid)-1) -> -0.22709303 | L44: =B44*(1+W17)^Hold_Mid*Ret_Con_Mid -> 0.64523931 | M44: =L44/B44 -> 0.092177045 | N44: =IF((L44/B44)<=0,-1,(L44/B44)^(1/Hold_Mid)-1) -> -0.28864077
A45: =A18 -> Polymarket | B45: =C18 -> 10.5 | C45: =B45*(1+T18)^Hold_Mid*Ret_Con_Mid -> 45.973178 | D45: =C45/B45 -> 4.3783979 | E45: =IF((C45/B45)<=0,-1,(C45/B45)^(1/Hold_Mid)-1) -> 0.23485641 | F45: =B45*(1+U18)^Hold_Mid*Ret_Con_Mid -> 105.54858 | G45: =F45/B45 -> 10.052246 | H45: =IF((F45/B45)<=0,-1,(F45/B45)^(1/Hold_Mid)-1) -> 0.39053025 | I45: =B45*(1+V18)^Hold_Mid*Ret_Con_Mid -> 6.7642735 | J45: =I45/B45 -> 0.64421652 | K45: =IF((I45/B45)<=0,-1,(I45/B45)^(1/Hold_Mid)-1) -> -0.060884872 | L45: =B45*(1+W18)^Hold_Mid*Ret_Con_Mid -> 3.8889468 | M45: =L45/B45 -> 0.37037589 | N45: =IF((L45/B45)<=0,-1,(L45/B45)^(1/Hold_Mid)-1) -> -0.13228415
A46: =A19 -> Goat Group | B46: =C19 -> 15 | C46: =B46*(1+T19)^Hold_Mid*Ret_Con_Mid -> 36.15108 | D46: =C46/B46 -> 2.410072 | E46: =IF((C46/B46)<=0,-1,(C46/B46)^(1/Hold_Mid)-1) -> 0.13390251 | F46: =B46*(1+U19)^Hold_Mid*Ret_Con_Mid -> 79.063131 | G46: =F46/B46 -> 5.2708754 | H46: =IF((F46/B46)<=0,-1,(F46/B46)^(1/Hold_Mid)-1) -> 0.26802001 | I46: =B46*(1+V19)^Hold_Mid*Ret_Con_Mid -> 5.5731482 | J46: =I46/B46 -> 0.37154321 | K46: =IF((I46/B46)<=0,-1,(I46/B46)^(1/Hold_Mid)-1) -> -0.13189399 | L46: =B46*(1+W19)^Hold_Mid*Ret_Con_Mid -> 3.95684 | M46: =L46/B46 -> 0.26378934 | N46: =IF((L46/B46)<=0,-1,(L46/B46)^(1/Hold_Mid)-1) -> -0.17334849
A47: =A20 -> Stripe | B47: =C20 -> 45 | C47: =B47*(1+T20)^Hold_Mid*Ret_Con_Mid -> 134.65612 | D47: =C47/B47 -> 2.9923581 | E47: =IF((C47/B47)<=0,-1,(C47/B47)^(1/Hold_Mid)-1) -> 0.16950461 | F47: =B47*(1+U20)^Hold_Mid*Ret_Con_Mid -> 361.016 | G47: =F47/B47 -> 8.0225779 | H47: =IF((F47/B47)<=0,-1,(F47/B47)^(1/Hold_Mid)-1) -> 0.34644217 | I47: =B47*(1+V20)^Hold_Mid*Ret_Con_Mid -> 29.499387 | J47: =I47/B47 -> 0.65554193 | K47: =IF((I47/B47)<=0,-1,(I47/B47)^(1/Hold_Mid)-1) -> -0.058543912 | L47: =B47*(1+W20)^Hold_Mid*Ret_Con_Mid -> 22.985049 | M47: =L47/B47 -> 0.51077887 | N47: =IF((L47/B47)<=0,-1,(L47/B47)^(1/Hold_Mid)-1) -> -0.091512432
A48: SLEEVE TOTAL | B48: =SUM(B39:B47) -> 200 | C48: =SUM(C39:C47) -> 733.35049 | D48: =C48/B48 -> 3.6667525 | E48: =IF((C48/B48)<=0,-1,(C48/B48)^(1/Hold_Mid)-1) -> 0.20395888 | F48: =SUM(F39:F47) -> 1784.0995 | G48: =F48/B48 -> 8.9204975 | H48: =IF((F48/B48)<=0,-1,(F48/B48)^(1/Hold_Mid)-1) -> 0.36700426 | I48: =SUM(I39:I47) -> 165.19455 | J48: =I48/B48 -> 0.82597273 | K48: =IF((I48/B48)<=0,-1,(I48/B48)^(1/Hold_Mid)-1) -> -0.026943723 | L48: =SUM(L39:L47) -> 76.354183 | M48: =L48/B48 -> 0.38177091 | N48: =IF((L48/B48)<=0,-1,(L48/B48)^(1/Hold_Mid)-1) -> -0.12851975
A51: =Hold_Long&"-YEAR HOLD — GROSS PROCEEDS" -> 10-YEAR HOLD — GROSS PROCEEDS
A52: Company | B52: Check ($M) | C52: Base $ | D52: Base MOIC | E52: Base IRR | F52: Bull $ | G52: Bull MOIC | H52: Bull IRR | I52: Bear $ | J52: Bear MOIC | K52: Bear IRR | L52: Shock $ | M52: Shock MOIC | N52: Shock IRR
A53: =A12 -> Quince | B53: =C12 -> 35 | C53: =B53*(1+T12)^Hold_Long*Ret_Con_Long -> 360.48911 | D53: =C53/B53 -> 10.299689 | E53: =IF((C53/B53)<=0,-1,(C53/B53)^(1/Hold_Long)-1) -> 0.26264833 | F53: =B53*(1+U12)^Hold_Long*Ret_Con_Long -> 1334.3395 | G53: =F53/B53 -> 38.123986 | H53: =IF((F53/B53)<=0,-1,(F53/B53)^(1/Hold_Long)-1) -> 0.43919562 | I53: =B53*(1+V12)^Hold_Long*Ret_Con_Long -> 37.243435 | J53: =I53/B53 -> 1.0640981 | K53: =IF((I53/B53)<=0,-1,(I53/B53)^(1/Hold_Long)-1) -> 0.0062321009 | L53: =B53*(1+W12)^Hold_Long*Ret_Con_Long -> 4.157156 | M53: =L53/B53 -> 0.11877589 | N53: =IF((L53/B53)<=0,-1,(L53/B53)^(1/Hold_Long)-1) -> -0.19188563
A54: =A13 -> Whoop | B54: =C13 -> 31.5 | C54: =B54*(1+T13)^Hold_Long*Ret_Con_Long -> 296.84548 | D54: =C54/B54 -> 9.4236662 | E54: =IF((C54/B54)<=0,-1,(C54/B54)^(1/Hold_Long)-1) -> 0.25147446 | F54: =B54*(1+U13)^Hold_Long*Ret_Con_Long -> 962.6229 | G54: =F54/B54 -> 30.559457 | H54: =IF((F54/B54)<=0,-1,(F54/B54)^(1/Hold_Long)-1) -> 0.40771443 | I54: =B54*(1+V13)^Hold_Long*Ret_Con_Long -> 20.187748 | J54: =I54/B54 -> 0.64088088 | K54: =IF((I54/B54)<=0,-1,(I54/B54)^(1/Hold_Long)-1) -> -0.043515952 | L54: =B54*(1+W13)^Hold_Long*Ret_Con_Long -> 4.6951193 | M54: =L54/B54 -> 0.14905141 | N54: =IF((L54/B54)<=0,-1,(L54/B54)^(1/Hold_Long)-1) -> -0.17332728
A55: =A14 -> The Farmer's Dog | B55: =C14 -> 24.5 | C55: =B55*(1+T14)^Hold_Long*Ret_Con_Long -> 156.02258 | D55: =C55/B55 -> 6.3682686 | E55: =IF((C55/B55)<=0,-1,(C55/B55)^(1/Hold_Long)-1) -> 0.20337819 | F55: =B55*(1+U14)^Hold_Long*Ret_Con_Long -> 426.74144 | G55: =F55/B55 -> 17.418018 | H55: =IF((F55/B55)<=0,-1,(F55/B55)^(1/Hold_Long)-1) -> 0.33076041 | I55: =B55*(1+V14)^Hold_Long*Ret_Con_Long -> 54.474964 | J55: =I55/B55 -> 2.2234679 | K55: =IF((I55/B55)<=0,-1,(I55/B55)^(1/Hold_Long)-1) -> 0.08318612 | L55: =B55*(1+W14)^Hold_Long*Ret_Con_Long -> 12.357002 | M55: =L55/B55 -> 0.50436743 | N55: =IF((L55/B55)<=0,-1,(L55/B55)^(1/Hold_Long)-1) -> -0.066155203
A56: =A15 -> Made In Cookware | B56: =C15 -> 17.5 | C56: =B56*(1+T15)^Hold_Long*Ret_Con_Long -> 56.419977 | D56: =C56/B56 -> 3.2239987 | E56: =IF((C56/B56)<=0,-1,(C56/B56)^(1/Hold_Long)-1) -> 0.1241894 | F56: =B56*(1+U15)^Hold_Long*Ret_Con_Long -> 163.8927 | G56: =F56/B56 -> 9.3652974 | H56: =IF((F56/B56)<=0,-1,(F56/B56)^(1/Hold_Long)-1) -> 0.25069714 | I56: =B56*(1+V15)^Hold_Long*Ret_Con_Long -> 5.3169212 | J56: =I56/B56 -> 0.30382407 | K56: =IF((I56/B56)<=0,-1,(I56/B56)^(1/Hold_Long)-1) -> -0.11230818 | L56: =B56*(1+W15)^Hold_Long*Ret_Con_Long -> 3.2680606 | M56: =L56/B56 -> 0.18674632 | N56: =IF((L56/B56)<=0,-1,(L56/B56)^(1/Hold_Long)-1) -> -0.15447743
A57: =A16 -> Thrive Market | B57: =C16 -> 14 | C57: =B57*(1+T16)^Hold_Long*Ret_Con_Long -> 24.293045 | D57: =C57/B57 -> 1.7352175 | E57: =IF((C57/B57)<=0,-1,(C57/B57)^(1/Hold_Long)-1) -> 0.056660303 | F57: =B57*(1+U16)^Hold_Long*Ret_Con_Long -> 58.796802 | G57: =F57/B57 -> 4.1997716 | H57: =IF((F57/B57)<=0,-1,(F57/B57)^(1/Hold_Long)-1) -> 0.15431029 | I57: =B57*(1+V16)^Hold_Long*Ret_Con_Long -> 7.2771217 | J57: =I57/B57 -> 0.51979441 | K57: =IF((I57/B57)<=0,-1,(I57/B57)^(1/Hold_Long)-1) -> -0.063337442 | L57: =B57*(1+W16)^Hold_Long*Ret_Con_Long -> 5.109202 | M57: =L57/B57 -> 0.364943 | N57: =IF((L57/B57)<=0,-1,(L57/B57)^(1/Hold_Long)-1) -> -0.095887437
A58: =A17 -> Plunge | B58: =C17 -> 7 | C58: =B58*(1+T17)^Hold_Long*Ret_Con_Long -> 36.95804 | D58: =C58/B58 -> 5.27972 | E58: =IF((C58/B58)<=0,-1,(C58/B58)^(1/Hold_Long)-1) -> 0.18103044 | F58: =B58*(1+U17)^Hold_Long*Ret_Con_Long -> 356.6877 | G58: =F58/B58 -> 50.955386 | H58: =IF((F58/B58)<=0,-1,(F58/B58)^(1/Hold_Long)-1) -> 0.4815592 | I58: =B58*(1+V17)^Hold_Long*Ret_Con_Long -> 0.51239393 | J58: =I58/B58 -> 0.073199132 | K58: =IF((I58/B58)<=0,-1,(I58/B58)^(1/Hold_Long)-1) -> -0.23007115 | L58: =B58*(1+W17)^Hold_Long*Ret_Con_Long -> 0.22347114 | M58: =L58/B58 -> 0.031924448 | N58: =IF((L58/B58)<=0,-1,(L58/B58)^(1/Hold_Long)-1) -> -0.29138174
A59: =A18 -> Polymarket | B59: =C18 -> 10.5 | C59: =B59*(1+T18)^Hold_Long*Ret_Con_Long -> 83.288995 | D59: =C59/B59 -> 7.9322852 | E59: =IF((C59/B59)<=0,-1,(C59/B59)^(1/Hold_Long)-1) -> 0.23009834 | F59: =B59*(1+U18)^Hold_Long*Ret_Con_Long -> 273.04073 | G59: =F59/B59 -> 26.003879 | H59: =IF((F59/B59)<=0,-1,(F59/B59)^(1/Hold_Long)-1) -> 0.38517235 | I59: =B59*(1+V18)^Hold_Long*Ret_Con_Long -> 5.3902807 | J59: =I59/B59 -> 0.51336006 | K59: =IF((I59/B59)<=0,-1,(I59/B59)^(1/Hold_Long)-1) -> -0.064503412 | L59: =B59*(1+W18)^Hold_Long*Ret_Con_Long -> 2.4445465 | M59: =L59/B59 -> 0.23281395 | N59: =IF((L59/B59)<=0,-1,(L59/B59)^(1/Hold_Long)-1) -> -0.13562758
A60: =A19 -> Goat Group | B60: =C19 -> 15 | C60: =B60*(1+T19)^Hold_Long*Ret_Con_Long -> 50.70866 | D60: =C60/B60 -> 3.3805774 | E60: =IF((C60/B60)<=0,-1,(C60/B60)^(1/Hold_Long)-1) -> 0.12953343 | F60: =B60*(1+U19)^Hold_Long*Ret_Con_Long -> 155.0908 | G60: =F60/B60 -> 10.339387 | H60: =IF((F60/B60)<=0,-1,(F60/B60)^(1/Hold_Long)-1) -> 0.26313416 | I60: =B60*(1+V19)^Hold_Long*Ret_Con_Long -> 3.5079435 | J60: =I60/B60 -> 0.2338629 | K60: =IF((I60/B60)<=0,-1,(I60/B60)^(1/Hold_Long)-1) -> -0.13523892 | L60: =B60*(1+W19)^Hold_Long*Ret_Con_Long -> 2.1505502 | M60: =L60/B60 -> 0.14337002 | N60: =IF((L60/B60)<=0,-1,(L60/B60)^(1/Hold_Long)-1) -> -0.17653369
A61: =A20 -> Stripe | B61: =C20 -> 45 | C61: =B61*(1+T20)^Hold_Long*Ret_Con_Long -> 207.23619 | D61: =C61/B61 -> 4.6052488 | E61: =IF((C61/B61)<=0,-1,(C61/B61)^(1/Hold_Long)-1) -> 0.16499835 | F61: =B61*(1+U20)^Hold_Long*Ret_Con_Long -> 847.85831 | G61: =F61/B61 -> 18.841296 | H61: =IF((F61/B61)<=0,-1,(F61/B61)^(1/Hold_Long)-1) -> 0.34125414 | I61: =B61*(1+V20)^Hold_Long*Ret_Con_Long -> 23.683556 | J61: =I61/B61 -> 0.52630124 | K61: =IF((I61/B61)<=0,-1,(I61/B61)^(1/Hold_Long)-1) -> -0.062171472 | L61: =B61*(1+W20)^Hold_Long*Ret_Con_Long -> 16.58197 | M61: =L61/B61 -> 0.36848821 | N61: =IF((L61/B61)<=0,-1,(L61/B61)^(1/Hold_Long)-1) -> -0.09501296
A62: SLEEVE TOTAL | B62: =SUM(B53:B61) -> 200 | C62: =SUM(C53:C61) -> 1272.2621 | D62: =C62/B62 -> 6.3613104 | E62: =IF((C62/B62)<=0,-1,(C62/B62)^(1/Hold_Long)-1) -> 0.20324664 | F62: =SUM(F53:F61) -> 4579.0709 | G62: =F62/B62 -> 22.895354 | H62: =IF((F62/B62)<=0,-1,(F62/B62)^(1/Hold_Long)-1) -> 0.36764927 | I62: =SUM(I53:I61) -> 157.59436 | J62: =I62/B62 -> 0.78797181 | K62: =IF((I62/B62)<=0,-1,(I62/B62)^(1/Hold_Long)-1) -> -0.02354762 | L62: =SUM(L53:L61) -> 50.987077 | M62: =L62/B62 -> 0.25493539 | N62: =IF((L62/B62)<=0,-1,(L62/B62)^(1/Hold_Long)-1) -> -0.12774591
A65: METHODOLOGY / DATA-CONFIDENCE NOTE
A66: Marks are now tiered by evidence quality. Quince and Whoop are confirmed 2026 primary rounds (both $10.1B post-money, Mar-26). The Farmer's Dog and Thrive Market are MARKET-PRICED off live Forge Global secondary quotes (22-Sep-26): Farmer's Dog implies $3.76B (up from its $2.5B Series E in Jun-22 — real appreciation, and its Walmart.com launch in 2025 is the modeled upside catalyst); Thrive Market implies ~$945M (DOWN ~27% from its $1.29B Series C post-money in Jul-21, despite revenue growing from $400M to $700M+ over the same period — genuine multiple compression, not a data gap, which is why its Base/Bull CAGRs were cut and its Bear turned negative). Made In Cookware and Plunge remain unpriced: Made In has raised only ~$8.3M total (no institutional round large enough to anchor an EV) and Plunge has raised just $4.75M against an estimated ~$200M in lifetime sales by 2025 (mostly self-funded) — both entry marks are directional estimates with no market to check them against, and are the first things to re-underwrite before a check is cut. Bear vs. Shock differ by name rather than using one sleeve-wide spread: staple/subscription names (Farmer's Dog, Thrive Market) see Shock milder than Bear — food/grocery spend is defensive and some trade-down benefit offsets inflation; import- or hardware-exposed names (Quince's direct-factory M2C sourcing, Whoop's own chip-dependent hardware, Made In's imported cookware inputs, Plunge's hardware BOM) see Shock worse than Bear — a Taiwan/decoupling scenario hits their COGS and supply chain directly, on top of softer discretionary demand. Polymarket added at $15M check (~$18B entry mark, mid of $14-21B secondary range Sep-26); Base 25%/Bull 40%/Bear -5%/Shock -12% — volume/fee leverage + US expansion convexity, with regulatory/competitive risk in Bear/Shock. Goat Group and Stripe were added Sep-26: Goat Group's last priced round is its Series F (24-Jun-21, $3.73B post, $195M raise); Forge Global shows no active secondary match for it, so — like Made In and Plunge — it is an unpriced, stale mark and among the first names to re-underwrite. Stripe is the opposite end of the confidence spectrum: MARKET-PRICED off a live, recurring employee tender ($159B post, 24-Feb-26, up from ~$140B guided 9-Feb-26 and ~$91.5B in the Feb-25 tender), with payment volume +34% YoY — the most liquid, best-evidenced mark in the sleeve. Both checks were funded by trimming the other seven positions pro-rata (×0.7× of prior check size) so total sleeve checks stay at exactly $200M, matching the Holdco Summary sleeve cap.

Sheet Sleeve Economics
A1: SLEEVE ECONOMICS — GROSS->NET WATERFALL BY SUB-VEHICLE
A2: Same European waterfall (return of capital -> pref -> carry, fees on committed) applied to each sleeve on a stand-alone basis. Expected = probability-weighted net. IQT block reconciles to Fund Economics (see Checks).
A4: =Hold_Short&"-YEAR HOLD — SLEEVE WATERFALLS" -> 5-YEAR HOLD — SLEEVE WATERFALLS | B4: IQT-MIRROR SLEEVE | H4: WEAPONS SLEEVE | N4: CONSUMER / VALUE SLEEVE
A5: Line item ($M) | B5: Base | C5: Bull | D5: Bear | E5: TSMC-Shock | F5: Expected | H5: Base | I5: Bull | J5: Bear | K5: TSMC-Shock | L5: Expected | N5: Base | O5: Bull | P5: Bear | Q5: TSMC-Shock | R5: Expected
A6: Gross exit proceeds | B6: ='Portfolio Returns'!C15 -> 565.83078 | C6: ='Portfolio Returns'!F15 -> 904.36142 | D6: ='Portfolio Returns'!I15 -> 126.29353 | E6: ='Portfolio Returns'!L15 -> 915.40631 | F6: =B6*P_Base+C6*P_Bull+D6*P_Bear+E6*P_Shock -> 636.96918 | H6: ='Weapons Sleeve'!C34 -> 935.7243 | I6: ='Weapons Sleeve'!F34 -> 1546.445 | J6: ='Weapons Sleeve'!I34 -> 443.33424 | K6: ='Weapons Sleeve'!L34 -> 1549.6152 | L6: =H6*P_Base+I6*P_Bull+J6*P_Bear+K6*P_Shock -> 1106.6296 | N6: ='Consumer Sleeve'!C34 -> 509.76448 | O6: ='Consumer Sleeve'!F34 -> 957.97292 | P6: ='Consumer Sleeve'!I34 -> 173.45881 | Q6: ='Consumer Sleeve'!L34 -> 100.75996 | R6: =N6*P_Base+O6*P_Bull+P6*P_Bear+Q6*P_Shock -> 510.02006
A7: (-) Return of committed capital | B7: =-IQT_Size -> -250 | C7: =-IQT_Size -> -250 | D7: =-IQT_Size -> -250 | E7: =-IQT_Size -> -250 | F7: =B7*P_Base+C7*P_Bull+D7*P_Bear+E7*P_Shock -> -250 | H7: =-Wpn_Size -> -390 | I7: =-Wpn_Size -> -390 | J7: =-Wpn_Size -> -390 | K7: =-Wpn_Size -> -390 | L7: =H7*P_Base+I7*P_Bull+J7*P_Bear+K7*P_Shock -> -390 | N7: =-Con_Size -> -200 | O7: =-Con_Size -> -200 | P7: =-Con_Size -> -200 | Q7: =-Con_Size -> -200 | R7: =N7*P_Base+O7*P_Bull+P7*P_Bear+Q7*P_Shock -> -200
A8: (-) Preferred return (comp.) | B8: =-IQT_Size*((1+Pref)^Hold_Short-1) -> -117.33202 | C8: =-IQT_Size*((1+Pref)^Hold_Short-1) -> -117.33202 | D8: =-IQT_Size*((1+Pref)^Hold_Short-1) -> -117.33202 | E8: =-IQT_Size*((1+Pref)^Hold_Short-1) -> -117.33202 | F8: =B8*P_Base+C8*P_Bull+D8*P_Bear+E8*P_Shock -> -117.33202 | H8: =-Wpn_Size*((1+Pref)^Hold_Short-1) -> -183.03795 | I8: =-Wpn_Size*((1+Pref)^Hold_Short-1) -> -183.03795 | J8: =-Wpn_Size*((1+Pref)^Hold_Short-1) -> -183.03795 | K8: =-Wpn_Size*((1+Pref)^Hold_Short-1) -> -183.03795 | L8: =H8*P_Base+I8*P_Bull+J8*P_Bear+K8*P_Shock -> -183.03795 | N8: =-Con_Size*((1+Pref)^Hold_Short-1) -> -93.865615 | O8: =-Con_Size*((1+Pref)^Hold_Short-1) -> -93.865615 | P8: =-Con_Size*((1+Pref)^Hold_Short-1) -> -93.865615 | Q8: =-Con_Size*((1+Pref)^Hold_Short-1) -> -93.865615 | R8: =N8*P_Base+O8*P_Bull+P8*P_Bear+Q8*P_Shock -> -93.865615
A9: Profit above pref (carry base) | B9: =MAX(0,B6+B7+B8) -> 198.49876 | C9: =MAX(0,C6+C7+C8) -> 537.0294 | D9: =MAX(0,D6+D7+D8) -> 0 | E9: =MAX(0,E6+E7+E8) -> 548.07429 | F9: =B9*P_Base+C9*P_Bull+D9*P_Bear+E9*P_Shock -> 305.79294 | H9: =MAX(0,H6+H7+H8) -> 362.68635 | I9: =MAX(0,I6+I7+I8) -> 973.40702 | J9: =MAX(0,J6+J7+J8) -> 0 | K9: =MAX(0,K6+K7+K8) -> 976.57723 | L9: =H9*P_Base+I9*P_Bull+J9*P_Bear+K9*P_Shock -> 553.0472 | N9: =MAX(0,N6+N7+N8) -> 215.89887 | O9: =MAX(0,O6+O7+O8) -> 664.1073 | P9: =MAX(0,P6+P7+P8) -> 0 | Q9: =MAX(0,Q6+Q7+Q8) -> 0 | R9: =N9*P_Base+O9*P_Bull+P9*P_Bear+Q9*P_Shock -> 263.18132
A10: (-) GP carried interest | B10: =-Carry*B9 -> -39.699752 | C10: =-Carry*C9 -> -107.40588 | D10: =-Carry*D9 -> 0 | E10: =-Carry*E9 -> -109.61486 | F10: =B10*P_Base+C10*P_Bull+D10*P_Bear+E10*P_Shock -> -61.158587 | H10: =-Carry*H9 -> -72.537271 | I10: =-Carry*I9 -> -194.6814 | J10: =-Carry*J9 -> 0 | K10: =-Carry*K9 -> -195.31545 | L10: =H10*P_Base+I10*P_Bull+J10*P_Bear+K10*P_Shock -> -110.60944 | N10: =-Carry*N9 -> -43.179773 | O10: =-Carry*O9 -> -132.82146 | P10: =-Carry*P9 -> 0 | Q10: =-Carry*Q9 -> 0 | R10: =N10*P_Base+O10*P_Bull+P10*P_Bear+Q10*P_Shock -> -52.636263
A11: (-) Management fees | B11: =-IQT_Size*Mgmt_Fee*Hold_Short -> -25 | C11: =-IQT_Size*Mgmt_Fee*Hold_Short -> -25 | D11: =-IQT_Size*Mgmt_Fee*Hold_Short -> -25 | E11: =-IQT_Size*Mgmt_Fee*Hold_Short -> -25 | F11: =B11*P_Base+C11*P_Bull+D11*P_Bear+E11*P_Shock -> -25 | H11: =-Wpn_Size*Mgmt_Fee*Hold_Short -> -39 | I11: =-Wpn_Size*Mgmt_Fee*Hold_Short -> -39 | J11: =-Wpn_Size*Mgmt_Fee*Hold_Short -> -39 | K11: =-Wpn_Size*Mgmt_Fee*Hold_Short -> -39 | L11: =H11*P_Base+I11*P_Bull+J11*P_Bear+K11*P_Shock -> -39 | N11: =-Con_Size*Mgmt_Fee*Hold_Short -> -20 | O11: =-Con_Size*Mgmt_Fee*Hold_Short -> -20 | P11: =-Con_Size*Mgmt_Fee*Hold_Short -> -20 | Q11: =-Con_Size*Mgmt_Fee*Hold_Short -> -20 | R11: =N11*P_Base+O11*P_Bull+P11*P_Bear+Q11*P_Shock -> -20
A12: Net proceeds to LPs | B12: =B6+B10+B11 -> 501.13103 | C12: =C6+C10+C11 -> 771.95554 | D12: =D6+D10+D11 -> 101.29353 | E12: =E6+E10+E11 -> 780.79145 | F12: =B12*P_Base+C12*P_Bull+D12*P_Bear+E12*P_Shock -> 550.81059 | H12: =H6+H10+H11 -> 824.18703 | I12: =I6+I10+I11 -> 1312.7636 | J12: =J6+J10+J11 -> 404.33424 | K12: =K6+K10+K11 -> 1315.2997 | L12: =H12*P_Base+I12*P_Bull+J12*P_Bear+K12*P_Shock -> 957.02015 | N12: =N6+N10+N11 -> 446.58471 | O12: =O6+O10+O11 -> 805.15146 | P12: =P6+P10+P11 -> 153.45881 | Q12: =Q6+Q10+Q11 -> 80.759965 | R12: =N12*P_Base+O12*P_Bull+P12*P_Bear+Q12*P_Shock -> 437.3838
A13: Gross MOIC | B13: =B6/IQT_Size -> 2.2633231 | C13: =C6/IQT_Size -> 3.6174457 | D13: =D6/IQT_Size -> 0.5051741 | E13: =E6/IQT_Size -> 3.6616253 | F13: =F6/IQT_Size -> 2.5478767 | H13: =H6/Wpn_Size -> 2.3992931 | I13: =I6/Wpn_Size -> 3.9652435 | J13: =J6/Wpn_Size -> 1.1367545 | K13: =K6/Wpn_Size -> 3.9733723 | L13: =L6/Wpn_Size -> 2.8375118 | N13: =N6/Con_Size -> 2.5488224 | O13: =O6/Con_Size -> 4.7898646 | P13: =P6/Con_Size -> 0.86729407 | Q13: =Q6/Con_Size -> 0.50379982 | R13: =R6/Con_Size -> 2.5501003
A14: Net MOIC (to LP) | B14: =B12/IQT_Size -> 2.0045241 | C14: =C12/IQT_Size -> 3.0878221 | D14: =D12/IQT_Size -> 0.4051741 | E14: =E12/IQT_Size -> 3.1231658 | F14: =F12/IQT_Size -> 2.2032424 | H14: =H12/Wpn_Size -> 2.1133001 | I14: =I12/Wpn_Size -> 3.3660604 | J14: =J12/Wpn_Size -> 1.0367545 | K14: =K12/Wpn_Size -> 3.3725634 | L14: =L12/Wpn_Size -> 2.4538978 | N14: =N12/Con_Size -> 2.2329235 | O14: =O12/Con_Size -> 4.0257573 | P14: =P12/Con_Size -> 0.76729407 | Q14: =Q12/Con_Size -> 0.40379982 | R14: =R12/Con_Size -> 2.186919
A15: Gross IRR | B15: =IF((B6/IQT_Size)<=0,-1,(B6/IQT_Size)^(1/Hold_Short)-1) -> 0.17746854 | C15: =IF((C6/IQT_Size)<=0,-1,(C6/IQT_Size)^(1/Hold_Short)-1) -> 0.29324379 | D15: =IF((D6/IQT_Size)<=0,-1,(D6/IQT_Size)^(1/Hold_Short)-1) -> -0.12765512 | E15: =IF((E6/IQT_Size)<=0,-1,(E6/IQT_Size)^(1/Hold_Short)-1) -> 0.29638733 | F15: =IF((F6/IQT_Size)<=0,-1,(F6/IQT_Size)^(1/Hold_Short)-1) -> 0.20569006 | H15: =IF((H6/Wpn_Size)<=0,-1,(H6/Wpn_Size)^(1/Hold_Short)-1) -> 0.19128771 | I15: =IF((I6/Wpn_Size)<=0,-1,(I6/Wpn_Size)^(1/Hold_Short)-1) -> 0.31720683 | J15: =IF((J6/Wpn_Size)<=0,-1,(J6/Wpn_Size)^(1/Hold_Short)-1) -> 0.025966861 | K15: =IF((K6/Wpn_Size)<=0,-1,(K6/Wpn_Size)^(1/Hold_Short)-1) -> 0.31774644 | L15: =IF((L6/Wpn_Size)<=0,-1,(L6/Wpn_Size)^(1/Hold_Short)-1) -> 0.23193426 | N15: =IF((N6/Con_Size)<=0,-1,(N6/Con_Size)^(1/Hold_Short)-1) -> 0.20577955 | O15: =IF((O6/Con_Size)<=0,-1,(O6/Con_Size)^(1/Hold_Short)-1) -> 0.36793243 | P15: =IF((P6/Con_Size)<=0,-1,(P6/Con_Size)^(1/Hold_Short)-1) -> -0.028073832 | Q15: =IF((Q6/Con_Size)<=0,-1,(Q6/Con_Size)^(1/Hold_Short)-1) -> -0.12813027 | R15: =IF((R6/Con_Size)<=0,-1,(R6/Con_Size)^(1/Hold_Short)-1) -> 0.20590044
A16: Net IRR (to LP) | B16: =IF((B12/IQT_Size)<=0,-1,(B12/IQT_Size)^(1/Hold_Short)-1) -> 0.14921757 | C16: =IF((C12/IQT_Size)<=0,-1,(C12/IQT_Size)^(1/Hold_Short)-1) -> 0.25294052 | D16: =IF((D12/IQT_Size)<=0,-1,(D12/IQT_Size)^(1/Hold_Short)-1) -> -0.16530399 | E16: =IF((E12/IQT_Size)<=0,-1,(E12/IQT_Size)^(1/Hold_Short)-1) -> 0.25579575 | F16: =IF((F12/IQT_Size)<=0,-1,(F12/IQT_Size)^(1/Hold_Short)-1) -> 0.17114982 | H16: =IF((H12/Wpn_Size)<=0,-1,(H12/Wpn_Size)^(1/Hold_Short)-1) -> 0.16142785 | I16: =IF((I12/Wpn_Size)<=0,-1,(I12/Wpn_Size)^(1/Hold_Short)-1) -> 0.27474812 | J16: =IF((J12/Wpn_Size)<=0,-1,(J12/Wpn_Size)^(1/Hold_Short)-1) -> 0.0072451438 | K16: =IF((K12/Wpn_Size)<=0,-1,(K12/Wpn_Size)^(1/Hold_Short)-1) -> 0.27524029 | L16: =IF((L12/Wpn_Size)<=0,-1,(L12/Wpn_Size)^(1/Hold_Short)-1) -> 0.19666144 | N16: =IF((N12/Con_Size)<=0,-1,(N12/Con_Size)^(1/Hold_Short)-1) -> 0.1742884 | O16: =IF((O12/Con_Size)<=0,-1,(O12/Con_Size)^(1/Hold_Short)-1) -> 0.3212029 | P16: =IF((P12/Con_Size)<=0,-1,(P12/Con_Size)^(1/Hold_Short)-1) -> -0.051598203 | Q16: =IF((Q12/Con_Size)<=0,-1,(Q12/Con_Size)^(1/Hold_Short)-1) -> -0.16587099 | R16: =IF((R12/Con_Size)<=0,-1,(R12/Con_Size)^(1/Hold_Short)-1) -> 0.16940929
A17: Net KS-PME vs SPX | B17: =B14/(1+SPX_CAGR)^Hold_Short -> 1.3028031 | C17: =C14/(1+SPX_CAGR)^Hold_Short -> 2.0068725 | D17: =D14/(1+SPX_CAGR)^Hold_Short -> 0.26333537 | E17: =E14/(1+SPX_CAGR)^Hold_Short -> 2.0298435 | F17: =F14/(1+SPX_CAGR)^Hold_Short -> 1.4319564 | H17: =H14/(1+SPX_CAGR)^Hold_Short -> 1.3735001 | I17: =I14/(1+SPX_CAGR)^Hold_Short -> 2.1877083 | J17: =J14/(1+SPX_CAGR)^Hold_Short -> 0.67381926 | K17: =K14/(1+SPX_CAGR)^Hold_Short -> 2.1919348 | L17: =L14/(1+SPX_CAGR)^Hold_Short -> 1.5948652 | N17: =N14/(1+SPX_CAGR)^Hold_Short -> 1.4512471 | O17: =O14/(1+SPX_CAGR)^Hold_Short -> 2.616466 | P17: =P14/(1+SPX_CAGR)^Hold_Short -> 0.4986885 | Q17: =Q14/(1+SPX_CAGR)^Hold_Short -> 0.26244218 | R17: =R14/(1+SPX_CAGR)^Hold_Short -> 1.4213473
A18: Net KS-PME vs NDX | B18: =B14/(1+NDX_CAGR)^Hold_Short -> 1.0879754 | C18: =C14/(1+NDX_CAGR)^Hold_Short -> 1.6759462 | D18: =D14/(1+NDX_CAGR)^Hold_Short -> 0.21991227 | E18: =E14/(1+NDX_CAGR)^Hold_Short -> 1.6951293 | F18: =F14/(1+NDX_CAGR)^Hold_Short -> 1.1958317 | H18: =H14/(1+NDX_CAGR)^Hold_Short -> 1.1470146 | I18: =I14/(1+NDX_CAGR)^Hold_Short -> 1.8269627 | J18: =J14/(1+NDX_CAGR)^Hold_Short -> 0.56270878 | K18: =K14/(1+NDX_CAGR)^Hold_Short -> 1.8304923 | L18: =L14/(1+NDX_CAGR)^Hold_Short -> 1.3318774 | N18: =N14/(1+NDX_CAGR)^Hold_Short -> 1.2119414 | O18: =O14/(1+NDX_CAGR)^Hold_Short -> 2.1850198 | P18: =P14/(1+NDX_CAGR)^Hold_Short -> 0.41645648 | Q18: =Q14/(1+NDX_CAGR)^Hold_Short -> 0.21916637 | R18: =R14/(1+NDX_CAGR)^Hold_Short -> 1.186972
A21: =Hold_Mid&"-YEAR HOLD — SLEEVE WATERFALLS" -> 7-YEAR HOLD — SLEEVE WATERFALLS | B21: IQT-MIRROR SLEEVE | H21: WEAPONS SLEEVE | N21: CONSUMER / VALUE SLEEVE
A22: Line item ($M) | B22: Base | C22: Bull | D22: Bear | E22: TSMC-Shock | F22: Expected | H22: Base | I22: Bull | J22: Bear | K22: TSMC-Shock | L22: Expected | N22: Base | O22: Bull | P22: Bear | Q22: TSMC-Shock | R22: Expected
A23: Gross exit proceeds | B23: ='Portfolio Returns'!C29 -> 778.13077 | C23: ='Portfolio Returns'!F29 -> 1497.0053 | D23: ='Portfolio Returns'!I29 -> 100.03369 | E23: ='Portfolio Returns'!L29 -> 1542.4475 | F23: =B23*P_Base+C23*P_Bull+D23*P_Bear+E23*P_Shock -> 970.78235 | H23: ='Weapons Sleeve'!C48 -> 1335.6853 | I23: ='Weapons Sleeve'!F48 -> 2734.3077 | J23: ='Weapons Sleeve'!I48 -> 463.72368 | K23: ='Weapons Sleeve'!L48 -> 2737.7292 | L23: =H23*P_Base+I23*P_Bull+J23*P_Bear+K23*P_Shock -> 1764.8532 | N23: ='Consumer Sleeve'!C48 -> 733.35049 | O23: ='Consumer Sleeve'!F48 -> 1784.0995 | P23: ='Consumer Sleeve'!I48 -> 165.19455 | Q23: ='Consumer Sleeve'!L48 -> 76.354183 | R23: =N23*P_Base+O23*P_Bull+P23*P_Bear+Q23*P_Shock -> 812.26491
A24: (-) Return of committed capital | B24: =-IQT_Size -> -250 | C24: =-IQT_Size -> -250 | D24: =-IQT_Size -> -250 | E24: =-IQT_Size -> -250 | F24: =B24*P_Base+C24*P_Bull+D24*P_Bear+E24*P_Shock -> -250 | H24: =-Wpn_Size -> -390 | I24: =-Wpn_Size -> -390 | J24: =-Wpn_Size -> -390 | K24: =-Wpn_Size -> -390 | L24: =H24*P_Base+I24*P_Bull+J24*P_Bear+K24*P_Shock -> -390 | N24: =-Con_Size -> -200 | O24: =-Con_Size -> -200 | P24: =-Con_Size -> -200 | Q24: =-Con_Size -> -200 | R24: =N24*P_Base+O24*P_Bull+P24*P_Bear+Q24*P_Shock -> -200
A25: (-) Preferred return (comp.) | B25: =-IQT_Size*((1+Pref)^Hold_Mid-1) -> -178.45607 | C25: =-IQT_Size*((1+Pref)^Hold_Mid-1) -> -178.45607 | D25: =-IQT_Size*((1+Pref)^Hold_Mid-1) -> -178.45607 | E25: =-IQT_Size*((1+Pref)^Hold_Mid-1) -> -178.45607 | F25: =B25*P_Base+C25*P_Bull+D25*P_Bear+E25*P_Shock -> -178.45607 | H25: =-Wpn_Size*((1+Pref)^Hold_Mid-1) -> -278.39146 | I25: =-Wpn_Size*((1+Pref)^Hold_Mid-1) -> -278.39146 | J25: =-Wpn_Size*((1+Pref)^Hold_Mid-1) -> -278.39146 | K25: =-Wpn_Size*((1+Pref)^Hold_Mid-1) -> -278.39146 | L25: =H25*P_Base+I25*P_Bull+J25*P_Bear+K25*P_Shock -> -278.39146 | N25: =-Con_Size*((1+Pref)^Hold_Mid-1) -> -142.76485 | O25: =-Con_Size*((1+Pref)^Hold_Mid-1) -> -142.76485 | P25: =-Con_Size*((1+Pref)^Hold_Mid-1) -> -142.76485 | Q25: =-Con_Size*((1+Pref)^Hold_Mid-1) -> -142.76485 | R25: =N25*P_Base+O25*P_Bull+P25*P_Bear+Q25*P_Shock -> -142.76485
A26: Profit above pref (carry base) | B26: =MAX(0,B23+B24+B25) -> 349.6747 | C26: =MAX(0,C23+C24+C25) -> 1068.5492 | D26: =MAX(0,D23+D24+D25) -> 0 | E26: =MAX(0,E23+E24+E25) -> 1113.9915 | F26: =B26*P_Base+C26*P_Bull+D26*P_Bear+E26*P_Shock -> 591.58964 | H26: =MAX(0,H23+H24+H25) -> 667.2938 | I26: =MAX(0,I23+I24+I25) -> 2065.9163 | J26: =MAX(0,J23+J24+J25) -> 0 | K26: =MAX(0,K23+K24+K25) -> 2069.3378 | L26: =H26*P_Base+I26*P_Bull+J26*P_Bear+K26*P_Shock -> 1127.1619 | N26: =MAX(0,N23+N24+N25) -> 390.58564 | O26: =MAX(0,O23+O24+O25) -> 1441.3347 | P26: =MAX(0,P23+P24+P25) -> 0 | Q26: =MAX(0,Q23+Q24+Q25) -> 0 | R26: =N26*P_Base+O26*P_Bull+P26*P_Bear+Q26*P_Shock -> 536.0972
A27: (-) GP carried interest | B27: =-Carry*B26 -> -69.934941 | C27: =-Carry*C26 -> -213.70985 | D27: =-Carry*D26 -> 0 | E27: =-Carry*E26 -> -222.79829 | F27: =B27*P_Base+C27*P_Bull+D27*P_Bear+E27*P_Shock -> -118.31793 | H27: =-Carry*H26 -> -133.45876 | I27: =-Carry*I26 -> -413.18325 | J27: =-Carry*J26 -> 0 | K27: =-Carry*K26 -> -413.86755 | L27: =H27*P_Base+I27*P_Bull+J27*P_Bear+K27*P_Shock -> -225.43239 | N27: =-Carry*N26 -> -78.117127 | O27: =-Carry*O26 -> -288.26693 | P27: =-Carry*P26 -> 0 | Q27: =-Carry*Q26 -> 0 | R27: =N27*P_Base+O27*P_Bull+P27*P_Bear+Q27*P_Shock -> -107.21944
A28: (-) Management fees | B28: =-IQT_Size*Mgmt_Fee*Hold_Mid -> -35 | C28: =-IQT_Size*Mgmt_Fee*Hold_Mid -> -35 | D28: =-IQT_Size*Mgmt_Fee*Hold_Mid -> -35 | E28: =-IQT_Size*Mgmt_Fee*Hold_Mid -> -35 | F28: =B28*P_Base+C28*P_Bull+D28*P_Bear+E28*P_Shock -> -35 | H28: =-Wpn_Size*Mgmt_Fee*Hold_Mid -> -54.6 | I28: =-Wpn_Size*Mgmt_Fee*Hold_Mid -> -54.6 | J28: =-Wpn_Size*Mgmt_Fee*Hold_Mid -> -54.6 | K28: =-Wpn_Size*Mgmt_Fee*Hold_Mid -> -54.6 | L28: =H28*P_Base+I28*P_Bull+J28*P_Bear+K28*P_Shock -> -54.6 | N28: =-Con_Size*Mgmt_Fee*Hold_Mid -> -28 | O28: =-Con_Size*Mgmt_Fee*Hold_Mid -> -28 | P28: =-Con_Size*Mgmt_Fee*Hold_Mid -> -28 | Q28: =-Con_Size*Mgmt_Fee*Hold_Mid -> -28 | R28: =N28*P_Base+O28*P_Bull+P28*P_Bear+Q28*P_Shock -> -28
A29: Net proceeds to LPs | B29: =B23+B27+B28 -> 673.19583 | C29: =C23+C27+C28 -> 1248.2955 | D29: =D23+D27+D28 -> 65.033688 | E29: =E23+E27+E28 -> 1284.6492 | F29: =B29*P_Base+C29*P_Bull+D29*P_Bear+E29*P_Shock -> 817.46442 | H29: =H23+H27+H28 -> 1147.6265 | I29: =I23+I27+I28 -> 2266.5245 | J29: =J23+J27+J28 -> 409.12368 | K29: =K23+K27+K28 -> 2269.2617 | L29: =H29*P_Base+I29*P_Bull+J29*P_Bear+K29*P_Shock -> 1484.8208 | N29: =N23+N27+N28 -> 627.23336 | O29: =O23+O27+O28 -> 1467.8326 | P29: =P23+P27+P28 -> 137.19455 | Q29: =Q23+Q27+Q28 -> 48.354183 | R29: =N29*P_Base+O29*P_Bull+P29*P_Bear+Q29*P_Shock -> 677.04547
A30: Gross MOIC | B30: =B23/IQT_Size -> 3.1125231 | C30: =C23/IQT_Size -> 5.9880212 | D30: =D23/IQT_Size -> 0.40013475 | E30: =E23/IQT_Size -> 6.1697901 | F30: =F23/IQT_Size -> 3.8831294 | H30: =H23/Wpn_Size -> 3.424834 | I30: =I23/Wpn_Size -> 7.0110454 | J30: =J23/Wpn_Size -> 1.1890351 | K30: =K23/Wpn_Size -> 7.0198185 | L30: =L23/Wpn_Size -> 4.5252647 | N30: =N23/Con_Size -> 3.6667525 | O30: =O23/Con_Size -> 8.9204975 | P30: =P23/Con_Size -> 0.82597273 | Q30: =Q23/Con_Size -> 0.38177091 | R30: =R23/Con_Size -> 4.0613245
A31: Net MOIC (to LP) | B31: =B29/IQT_Size -> 2.6927833 | C31: =C29/IQT_Size -> 4.9931818 | D31: =D29/IQT_Size -> 0.26013475 | E31: =E29/IQT_Size -> 5.1385969 | F31: =F29/IQT_Size -> 3.2698577 | H31: =H29/Wpn_Size -> 2.9426321 | I31: =I29/Wpn_Size -> 5.8116012 | J31: =J29/Wpn_Size -> 1.0490351 | K31: =K29/Wpn_Size -> 5.8186197 | L31: =L29/Wpn_Size -> 3.8072329 | N31: =N29/Con_Size -> 3.1361668 | O31: =O29/Con_Size -> 7.3391629 | P31: =P29/Con_Size -> 0.68597273 | Q31: =Q29/Con_Size -> 0.24177091 | R31: =R29/Con_Size -> 3.3852273
A32: Gross IRR | B32: =IF((B23/IQT_Size)<=0,-1,(B23/IQT_Size)^(1/Hold_Mid)-1) -> 0.1761011 | C32: =IF((C23/IQT_Size)<=0,-1,(C23/IQT_Size)^(1/Hold_Mid)-1) -> 0.29133962 | D32: =IF((D23/IQT_Size)<=0,-1,(D23/IQT_Size)^(1/Hold_Mid)-1) -> -0.12265112 | E32: =IF((E23/IQT_Size)<=0,-1,(E23/IQT_Size)^(1/Hold_Mid)-1) -> 0.29686799 | F32: =IF((F23/IQT_Size)<=0,-1,(F23/IQT_Size)^(1/Hold_Mid)-1) -> 0.21386066 | H32: =IF((H23/Wpn_Size)<=0,-1,(H23/Wpn_Size)^(1/Hold_Mid)-1) -> 0.19227675 | I32: =IF((I23/Wpn_Size)<=0,-1,(I23/Wpn_Size)^(1/Hold_Mid)-1) -> 0.3207667 | J32: =IF((J23/Wpn_Size)<=0,-1,(J23/Wpn_Size)^(1/Hold_Mid)-1) -> 0.025043027 | K32: =IF((K23/Wpn_Size)<=0,-1,(K23/Wpn_Size)^(1/Hold_Mid)-1) -> 0.32100268 | L32: =IF((L23/Wpn_Size)<=0,-1,(L23/Wpn_Size)^(1/Hold_Mid)-1) -> 0.24069041 | N32: =IF((N23/Con_Size)<=0,-1,(N23/Con_Size)^(1/Hold_Mid)-1) -> 0.20395888 | O32: =IF((O23/Con_Size)<=0,-1,(O23/Con_Size)^(1/Hold_Mid)-1) -> 0.36700426 | P32: =IF((P23/Con_Size)<=0,-1,(P23/Con_Size)^(1/Hold_Mid)-1) -> -0.026943723 | Q32: =IF((Q23/Con_Size)<=0,-1,(Q23/Con_Size)^(1/Hold_Mid)-1) -> -0.12851975 | R32: =IF((R23/Con_Size)<=0,-1,(R23/Con_Size)^(1/Hold_Mid)-1) -> 0.22166611
A33: Net IRR (to LP) | B33: =IF((B29/IQT_Size)<=0,-1,(B29/IQT_Size)^(1/Hold_Mid)-1) -> 0.1520129 | C33: =IF((C29/IQT_Size)<=0,-1,(C29/IQT_Size)^(1/Hold_Mid)-1) -> 0.25825364 | D33: =IF((D29/IQT_Size)<=0,-1,(D29/IQT_Size)^(1/Hold_Mid)-1) -> -0.17499437 | E33: =IF((E29/IQT_Size)<=0,-1,(E29/IQT_Size)^(1/Hold_Mid)-1) -> 0.26342429 | F33: =IF((F29/IQT_Size)<=0,-1,(F29/IQT_Size)^(1/Hold_Mid)-1) -> 0.18441561 | H33: =IF((H29/Wpn_Size)<=0,-1,(H29/Wpn_Size)^(1/Hold_Mid)-1) -> 0.16670828 | I33: =IF((I29/Wpn_Size)<=0,-1,(I29/Wpn_Size)^(1/Hold_Mid)-1) -> 0.28583462 | J33: =IF((J29/Wpn_Size)<=0,-1,(J29/Wpn_Size)^(1/Hold_Mid)-1) -> 0.0068621193 | K33: =IF((K29/Wpn_Size)<=0,-1,(K29/Wpn_Size)^(1/Hold_Mid)-1) -> 0.28605634 | L33: =IF((L29/Wpn_Size)<=0,-1,(L29/Wpn_Size)^(1/Hold_Mid)-1) -> 0.21044262 | N33: =IF((N29/Con_Size)<=0,-1,(N29/Con_Size)^(1/Hold_Mid)-1) -> 0.17737325 | O33: =IF((O29/Con_Size)<=0,-1,(O29/Con_Size)^(1/Hold_Mid)-1) -> 0.32942484 | P33: =IF((P29/Con_Size)<=0,-1,(P29/Con_Size)^(1/Hold_Mid)-1) -> -0.052421355 | Q33: =IF((Q29/Con_Size)<=0,-1,(Q29/Con_Size)^(1/Hold_Mid)-1) -> -0.18357769 | R33: =IF((R29/Con_Size)<=0,-1,(R29/Con_Size)^(1/Hold_Mid)-1) -> 0.19029718
A34: Net KS-PME vs SPX | B34: =B31/(1+SPX_CAGR)^Hold_Mid -> 1.4730447 | C34: =C31/(1+SPX_CAGR)^Hold_Mid -> 2.7314414 | D34: =D31/(1+SPX_CAGR)^Hold_Mid -> 0.14230262 | E34: =E31/(1+SPX_CAGR)^Hold_Mid -> 2.8109885 | F34: =F31/(1+SPX_CAGR)^Hold_Mid -> 1.7887241 | H34: =H31/(1+SPX_CAGR)^Hold_Mid -> 1.6097205 | I34: =I31/(1+SPX_CAGR)^Hold_Mid -> 3.1791449 | J34: =J31/(1+SPX_CAGR)^Hold_Mid -> 0.57385812 | K34: =K31/(1+SPX_CAGR)^Hold_Mid -> 3.1829842 | L34: =L31/(1+SPX_CAGR)^Hold_Mid -> 2.0826868 | N34: =N31/(1+SPX_CAGR)^Hold_Mid -> 1.7155906 | O34: =O31/(1+SPX_CAGR)^Hold_Mid -> 4.0147734 | P34: =P31/(1+SPX_CAGR)^Hold_Mid -> 0.37525058 | Q34: =Q31/(1+SPX_CAGR)^Hold_Mid -> 0.13225697 | R34: =R31/(1+SPX_CAGR)^Hold_Mid -> 1.8518353
A35: Net KS-PME vs NDX | B35: =B31/(1+NDX_CAGR)^Hold_Mid -> 1.1445962 | C35: =C31/(1+NDX_CAGR)^Hold_Mid -> 2.1224051 | D35: =D31/(1+NDX_CAGR)^Hold_Mid -> 0.11057305 | E35: =E31/(1+NDX_CAGR)^Hold_Mid -> 2.1842153 | F35: =F31/(1+NDX_CAGR)^Hold_Mid -> 1.3898878 | H35: =H31/(1+NDX_CAGR)^Hold_Mid -> 1.2507971 | I35: =I31/(1+NDX_CAGR)^Hold_Mid -> 2.4702829 | J35: =J31/(1+NDX_CAGR)^Hold_Mid -> 0.44590353 | K35: =K31/(1+NDX_CAGR)^Hold_Mid -> 2.4732662 | L35: =L31/(1+NDX_CAGR)^Hold_Mid -> 1.6183049 | N35: =N31/(1+NDX_CAGR)^Hold_Mid -> 1.3330611 | O35: =O31/(1+NDX_CAGR)^Hold_Mid -> 3.1195893 | P35: =P31/(1+NDX_CAGR)^Hold_Mid -> 0.29158001 | Q35: =Q31/(1+NDX_CAGR)^Hold_Mid -> 0.1027673 | R35: =R31/(1+NDX_CAGR)^Hold_Mid -> 1.4389269
A38: =Hold_Long&"-YEAR HOLD — SLEEVE WATERFALLS" -> 10-YEAR HOLD — SLEEVE WATERFALLS | B38: IQT-MIRROR SLEEVE | H38: WEAPONS SLEEVE | N38: CONSUMER / VALUE SLEEVE
A39: Line item ($M) | B39: Base | C39: Bull | D39: Bear | E39: TSMC-Shock | F39: Expected | H39: Base | I39: Bull | J39: Bear | K39: TSMC-Shock | L39: Expected | N39: Base | O39: Bull | P39: Bear | Q39: TSMC-Shock | R39: Expected
A40: Gross exit proceeds | B40: ='Portfolio Returns'!C43 -> 1261.4559 | C40: ='Portfolio Returns'!F43 -> 3197.6972 | D40: ='Portfolio Returns'!I43 -> 73.963354 | E40: ='Portfolio Returns'!L43 -> 3418.1015 | F40: =B40*P_Base+C40*P_Bull+D40*P_Bear+E40*P_Shock -> 1890.8892 | H40: ='Weapons Sleeve'!C62 -> 2309.543 | I40: ='Weapons Sleeve'!F62 -> 6599.4885 | J40: ='Weapons Sleeve'!I62 -> 496.51969 | K40: ='Weapons Sleeve'!L62 -> 6598.6003 | L40: =H40*P_Base+I40*P_Bull+J40*P_Bear+K40*P_Shock -> 3753.4345 | N40: ='Consumer Sleeve'!C62 -> 1272.2621 | O40: ='Consumer Sleeve'!F62 -> 4579.0709 | P40: ='Consumer Sleeve'!I62 -> 157.59436 | Q40: ='Consumer Sleeve'!L62 -> 50.987077 | R40: =N40*P_Base+O40*P_Bull+P40*P_Bear+Q40*P_Shock -> 1748.5729
A41: (-) Return of committed capital | B41: =-IQT_Size -> -250 | C41: =-IQT_Size -> -250 | D41: =-IQT_Size -> -250 | E41: =-IQT_Size -> -250 | F41: =B41*P_Base+C41*P_Bull+D41*P_Bear+E41*P_Shock -> -250 | H41: =-Wpn_Size -> -390 | I41: =-Wpn_Size -> -390 | J41: =-Wpn_Size -> -390 | K41: =-Wpn_Size -> -390 | L41: =H41*P_Base+I41*P_Bull+J41*P_Bear+K41*P_Shock -> -390 | N41: =-Con_Size -> -200 | O41: =-Con_Size -> -200 | P41: =-Con_Size -> -200 | Q41: =-Con_Size -> -200 | R41: =N41*P_Base+O41*P_Bull+P41*P_Bear+Q41*P_Shock -> -200
A42: (-) Preferred return (comp.) | B42: =-IQT_Size*((1+Pref)^Hold_Long-1) -> -289.73125 | C42: =-IQT_Size*((1+Pref)^Hold_Long-1) -> -289.73125 | D42: =-IQT_Size*((1+Pref)^Hold_Long-1) -> -289.73125 | E42: =-IQT_Size*((1+Pref)^Hold_Long-1) -> -289.73125 | F42: =B42*P_Base+C42*P_Bull+D42*P_Bear+E42*P_Shock -> -289.73125 | H42: =-Wpn_Size*((1+Pref)^Hold_Long-1) -> -451.98075 | I42: =-Wpn_Size*((1+Pref)^Hold_Long-1) -> -451.98075 | J42: =-Wpn_Size*((1+Pref)^Hold_Long-1) -> -451.98075 | K42: =-Wpn_Size*((1+Pref)^Hold_Long-1) -> -451.98075 | L42: =H42*P_Base+I42*P_Bull+J42*P_Bear+K42*P_Shock -> -451.98075 | N42: =-Con_Size*((1+Pref)^Hold_Long-1) -> -231.785 | O42: =-Con_Size*((1+Pref)^Hold_Long-1) -> -231.785 | P42: =-Con_Size*((1+Pref)^Hold_Long-1) -> -231.785 | Q42: =-Con_Size*((1+Pref)^Hold_Long-1) -> -231.785 | R42: =N42*P_Base+O42*P_Bull+P42*P_Bear+Q42*P_Shock -> -231.785
A43: Profit above pref (carry base) | B43: =MAX(0,B40+B41+B42) -> 721.72469 | C43: =MAX(0,C40+C41+C42) -> 2657.9659 | D43: =MAX(0,D40+D41+D42) -> 0 | E43: =MAX(0,E40+E41+E42) -> 2878.3702 | F43: =B43*P_Base+C43*P_Bull+D43*P_Bear+E43*P_Shock -> 1421.0231 | H43: =MAX(0,H40+H41+H42) -> 1467.5623 | I43: =MAX(0,I40+I41+I42) -> 5757.5078 | J43: =MAX(0,J40+J41+J42) -> 0 | K43: =MAX(0,K40+K41+K42) -> 5756.6196 | L43: =H43*P_Base+I43*P_Bull+J43*P_Bear+K43*P_Shock -> 2963.2729 | N43: =MAX(0,N40+N41+N42) -> 840.47708 | O43: =MAX(0,O40+O41+O42) -> 4147.2859 | P43: =MAX(0,P40+P41+P42) -> 0 | Q43: =MAX(0,Q40+Q41+Q42) -> 0 | R43: =N43*P_Base+O43*P_Bull+P43*P_Bear+Q43*P_Shock -> 1415.0362
A44: (-) GP carried interest | B44: =-Carry*B43 -> -144.34494 | C44: =-Carry*C43 -> -531.59319 | D44: =-Carry*D43 -> 0 | E44: =-Carry*E43 -> -575.67404 | F44: =B44*P_Base+C44*P_Bull+D44*P_Bear+E44*P_Shock -> -284.20462 | H44: =-Carry*H43 -> -293.51246 | I44: =-Carry*I43 -> -1151.5016 | J44: =-Carry*J43 -> 0 | K44: =-Carry*K43 -> -1151.3239 | L44: =H44*P_Base+I44*P_Bull+J44*P_Bear+K44*P_Shock -> -592.65458 | N44: =-Carry*N43 -> -168.09542 | O44: =-Carry*O43 -> -829.45718 | P44: =-Carry*P43 -> 0 | Q44: =-Carry*Q43 -> 0 | R44: =N44*P_Base+O44*P_Bull+P44*P_Bear+Q44*P_Shock -> -283.00723
A45: (-) Management fees | B45: =-IQT_Size*Mgmt_Fee*Hold_Long -> -50 | C45: =-IQT_Size*Mgmt_Fee*Hold_Long -> -50 | D45: =-IQT_Size*Mgmt_Fee*Hold_Long -> -50 | E45: =-IQT_Size*Mgmt_Fee*Hold_Long -> -50 | F45: =B45*P_Base+C45*P_Bull+D45*P_Bear+E45*P_Shock -> -50 | H45: =-Wpn_Size*Mgmt_Fee*Hold_Long -> -78 | I45: =-Wpn_Size*Mgmt_Fee*Hold_Long -> -78 | J45: =-Wpn_Size*Mgmt_Fee*Hold_Long -> -78 | K45: =-Wpn_Size*Mgmt_Fee*Hold_Long -> -78 | L45: =H45*P_Base+I45*P_Bull+J45*P_Bear+K45*P_Shock -> -78 | N45: =-Con_Size*Mgmt_Fee*Hold_Long -> -40 | O45: =-Con_Size*Mgmt_Fee*Hold_Long -> -40 | P45: =-Con_Size*Mgmt_Fee*Hold_Long -> -40 | Q45: =-Con_Size*Mgmt_Fee*Hold_Long -> -40 | R45: =N45*P_Base+O45*P_Bull+P45*P_Bear+Q45*P_Shock -> -40
A46: Net proceeds to LPs | B46: =B40+B44+B45 -> 1067.111 | C46: =C40+C44+C45 -> 2616.104 | D46: =D40+D44+D45 -> 23.963354 | E46: =E40+E44+E45 -> 2792.4274 | F46: =B46*P_Base+C46*P_Bull+D46*P_Bear+E46*P_Shock -> 1556.6846 | H46: =H40+H44+H45 -> 1938.0306 | I46: =I40+I44+I45 -> 5369.987 | J46: =J40+J44+J45 -> 418.51969 | K46: =K40+K44+K45 -> 5369.2764 | L46: =H46*P_Base+I46*P_Bull+J46*P_Bear+K46*P_Shock -> 3082.7799 | N46: =N40+N44+N45 -> 1064.1667 | O46: =O40+O44+O45 -> 3709.6137 | P46: =P40+P44+P45 -> 117.59436 | Q46: =Q40+Q44+Q45 -> 10.987077 | R46: =N46*P_Base+O46*P_Bull+P46*P_Bear+Q46*P_Shock -> 1425.5656
A47: Gross MOIC | B47: =B40/IQT_Size -> 5.0458237 | C47: =C40/IQT_Size -> 12.790789 | D47: =D40/IQT_Size -> 0.29585342 | E47: =E40/IQT_Size -> 13.672406 | F47: =F40/IQT_Size -> 7.5635568 | H47: =H40/Wpn_Size -> 5.9219052 | I47: =I40/Wpn_Size -> 16.921765 | J47: =J40/Wpn_Size -> 1.2731274 | K47: =K40/Wpn_Size -> 16.919488 | L47: =L40/Wpn_Size -> 9.624191 | N47: =N40/Con_Size -> 6.3613104 | O47: =O40/Con_Size -> 22.895354 | P47: =P40/Con_Size -> 0.78797181 | Q47: =Q40/Con_Size -> 0.25493539 | R47: =R40/Con_Size -> 8.7428644
A48: Net MOIC (to LP) | B48: =B46/IQT_Size -> 4.268444 | C48: =C46/IQT_Size -> 10.464416 | D48: =D46/IQT_Size -> 0.095853416 | E48: =E46/IQT_Size -> 11.16971 | F48: =F46/IQT_Size -> 6.2267383 | H48: =H46/Wpn_Size -> 4.9693092 | I48: =I46/Wpn_Size -> 13.769197 | J48: =J46/Wpn_Size -> 1.0731274 | K48: =K46/Wpn_Size -> 13.767375 | L48: =L46/Wpn_Size -> 7.9045639 | N48: =N46/Con_Size -> 5.3208333 | O48: =O46/Con_Size -> 18.548069 | P48: =P46/Con_Size -> 0.58797181 | Q48: =Q46/Con_Size -> 0.054935387 | R48: =R46/Con_Size -> 7.1278282
A49: Gross IRR | B49: =IF((B40/IQT_Size)<=0,-1,(B40/IQT_Size)^(1/Hold_Long)-1) -> 0.17569104 | C49: =IF((C40/IQT_Size)<=0,-1,(C40/IQT_Size)^(1/Hold_Long)-1) -> 0.29029713 | D49: =IF((D40/IQT_Size)<=0,-1,(D40/IQT_Size)^(1/Hold_Long)-1) -> -0.11466495 | E49: =IF((E40/IQT_Size)<=0,-1,(E40/IQT_Size)^(1/Hold_Long)-1) -> 0.29892625 | F49: =IF((F40/IQT_Size)<=0,-1,(F40/IQT_Size)^(1/Hold_Long)-1) -> 0.22425703 | H49: =IF((H40/Wpn_Size)<=0,-1,(H40/Wpn_Size)^(1/Hold_Long)-1) -> 0.19466501 | I49: =IF((I40/Wpn_Size)<=0,-1,(I40/Wpn_Size)^(1/Hold_Long)-1) -> 0.32691947 | J49: =IF((J40/Wpn_Size)<=0,-1,(J40/Wpn_Size)^(1/Hold_Long)-1) -> 0.024441555 | K49: =IF((K40/Wpn_Size)<=0,-1,(K40/Wpn_Size)^(1/Hold_Long)-1) -> 0.32690161 | L49: =IF((L40/Wpn_Size)<=0,-1,(L40/Wpn_Size)^(1/Hold_Long)-1) -> 0.25411229 | N49: =IF((N40/Con_Size)<=0,-1,(N40/Con_Size)^(1/Hold_Long)-1) -> 0.20324664 | O49: =IF((O40/Con_Size)<=0,-1,(O40/Con_Size)^(1/Hold_Long)-1) -> 0.36764927 | P49: =IF((P40/Con_Size)<=0,-1,(P40/Con_Size)^(1/Hold_Long)-1) -> -0.02354762 | Q49: =IF((Q40/Con_Size)<=0,-1,(Q40/Con_Size)^(1/Hold_Long)-1) -> -0.12774591 | R49: =IF((R40/Con_Size)<=0,-1,(R40/Con_Size)^(1/Hold_Long)-1) -> 0.2421252
A50: Net IRR (to LP) | B50: =IF((B46/IQT_Size)<=0,-1,(B46/IQT_Size)^(1/Hold_Long)-1) -> 0.15618401 | C50: =IF((C46/IQT_Size)<=0,-1,(C46/IQT_Size)^(1/Hold_Long)-1) -> 0.26465335 | D50: =IF((D46/IQT_Size)<=0,-1,(D46/IQT_Size)^(1/Hold_Long)-1) -> -0.20902864 | E50: =IF((E46/IQT_Size)<=0,-1,(E46/IQT_Size)^(1/Hold_Long)-1) -> 0.27292902 | F50: =IF((F46/IQT_Size)<=0,-1,(F46/IQT_Size)^(1/Hold_Long)-1) -> 0.20067664 | H50: =IF((H46/Wpn_Size)<=0,-1,(H46/Wpn_Size)^(1/Hold_Long)-1) -> 0.17389594 | I50: =IF((I46/Wpn_Size)<=0,-1,(I46/Wpn_Size)^(1/Hold_Long)-1) -> 0.29984289 | J50: =IF((J46/Wpn_Size)<=0,-1,(J46/Wpn_Size)^(1/Hold_Long)-1) -> 0.0070826834 | K50: =IF((K46/Wpn_Size)<=0,-1,(K46/Wpn_Size)^(1/Hold_Long)-1) -> 0.29982569 | L50: =IF((L46/Wpn_Size)<=0,-1,(L46/Wpn_Size)^(1/Hold_Long)-1) -> 0.22966777 | N50: =IF((N46/Con_Size)<=0,-1,(N46/Con_Size)^(1/Hold_Long)-1) -> 0.1819469 | O50: =IF((O46/Con_Size)<=0,-1,(O46/Con_Size)^(1/Hold_Long)-1) -> 0.33915198 | P50: =IF((P46/Con_Size)<=0,-1,(P46/Con_Size)^(1/Hold_Long)-1) -> -0.051722053 | Q50: =IF((Q46/Con_Size)<=0,-1,(Q46/Con_Size)^(1/Hold_Long)-1) -> -0.25185596 | R50: =IF((R46/Con_Size)<=0,-1,(R46/Con_Size)^(1/Hold_Long)-1) -> 0.21701442
A51: Net KS-PME vs SPX | B51: =B48/(1+SPX_CAGR)^Hold_Long -> 1.8030369 | C51: =C48/(1+SPX_CAGR)^Hold_Long -> 4.4202824 | D51: =D48/(1+SPX_CAGR)^Hold_Long -> 0.040489519 | E51: =E48/(1+SPX_CAGR)^Hold_Long -> 4.7182061 | F51: =F48/(1+SPX_CAGR)^Hold_Long -> 2.6302415 | H51: =H48/(1+SPX_CAGR)^Hold_Long -> 2.0990899 | I51: =I48/(1+SPX_CAGR)^Hold_Long -> 5.8162578 | J51: =J48/(1+SPX_CAGR)^Hold_Long -> 0.45330061 | K51: =K48/(1+SPX_CAGR)^Hold_Long -> 5.8154881 | L51: =L48/(1+SPX_CAGR)^Hold_Long -> 3.3389732 | N51: =N48/(1+SPX_CAGR)^Hold_Long -> 2.2475775 | O51: =O48/(1+SPX_CAGR)^Hold_Long -> 7.8349046 | P51: =P48/(1+SPX_CAGR)^Hold_Long -> 0.24836565 | Q51: =Q48/(1+SPX_CAGR)^Hold_Long -> 0.023205301 | R51: =R48/(1+SPX_CAGR)^Hold_Long -> 3.0108717
A52: Net KS-PME vs NDX | B52: =B48/(1+NDX_CAGR)^Hold_Long -> 1.2574339 | C52: =C48/(1+NDX_CAGR)^Hold_Long -> 3.082695 | D52: =D48/(1+NDX_CAGR)^Hold_Long -> 0.028237299 | E52: =E48/(1+NDX_CAGR)^Hold_Long -> 3.2904663 | F52: =F48/(1+NDX_CAGR)^Hold_Long -> 1.8343245 | H52: =H48/(1+NDX_CAGR)^Hold_Long -> 1.4639006 | I52: =I48/(1+NDX_CAGR)^Hold_Long -> 4.0562451 | J52: =J48/(1+NDX_CAGR)^Hold_Long -> 0.31613083 | K52: =K48/(1+NDX_CAGR)^Hold_Long -> 4.0557084 | L52: =L48/(1+NDX_CAGR)^Hold_Long -> 2.3285924 | N52: =N48/(1+NDX_CAGR)^Hold_Long -> 1.5674555 | O52: =O48/(1+NDX_CAGR)^Hold_Long -> 5.4640449 | P52: =P48/(1+NDX_CAGR)^Hold_Long -> 0.17320965 | Q52: =Q48/(1+NDX_CAGR)^Hold_Long -> 0.016183325 | R52: =R48/(1+NDX_CAGR)^Hold_Long -> 2.0997751
A55: RECONCILIATION — SUM OF STAND-ALONE SLEEVES vs HOLDCO (CROSS-COLLATERALISED) NET PROCEEDS ($M)
A56: Hold / line item | B56: Base | C56: Bull | D56: Bear | E56: TSMC-Shock | F56: Expected
A57: =Hold_Short&"-yr: sum of sleeve net proceeds" -> 5-yr: sum of sleeve net proceeds | B57: =B12+H12+N12 -> 1771.9028 | C57: =C12+I12+O12 -> 2889.8706 | D57: =D12+J12+P12 -> 659.08658 | E57: =E12+K12+Q12 -> 2176.8512 | F57: =F12+L12+R12 -> 1945.2145
A58: =Hold_Short&"-yr: holdco net proceeds (Holdco Summary)" -> 5-yr: holdco net proceeds (Holdco Summary) | B58: ='Holdco Summary'!B37 -> 1771.9028 | C58: ='Holdco Summary'!C37 -> 2889.8706 | D58: ='Holdco Summary'!D37 -> 659.08658 | E58: ='Holdco Summary'!E37 -> 2215.4723 | F58: ='Holdco Summary'!F37 -> 1951.0077
A59: =Hold_Short&"-yr: cross-sleeve netting effect" -> 5-yr: cross-sleeve netting effect | B59: =B58-B57 -> 0 | C59: =C58-C57 -> 0 | D59: =D58-D57 -> -1.1368684e-13 | E59: =E58-E57 -> 38.62113 | F59: =F58-F57 -> 5.7931695
A60: =Hold_Mid&"-yr: sum of sleeve net proceeds" -> 7-yr: sum of sleeve net proceeds | B60: =B29+H29+N29 -> 2448.0557 | C60: =C29+I29+O29 -> 4982.6525 | D60: =D29+J29+P29 -> 611.35192 | E60: =E29+K29+Q29 -> 3602.2651 | F60: =F29+L29+R29 -> 2979.3307
A61: =Hold_Mid&"-yr: holdco net proceeds (Holdco Summary)" -> 7-yr: holdco net proceeds (Holdco Summary) | B61: ='Holdco Summary'!B58 -> 2448.0557 | C61: ='Holdco Summary'!C58 -> 4982.6525 | D61: ='Holdco Summary'!D58 -> 611.35192 | E61: ='Holdco Summary'!E58 -> 3655.5472 | F61: ='Holdco Summary'!F58 -> 2987.3231
A62: =Hold_Mid&"-yr: cross-sleeve netting effect" -> 7-yr: cross-sleeve netting effect | B62: =B61-B60 -> 0 | C62: =C61-C60 -> -9.094947e-13 | D62: =D61-D60 -> 0 | E62: =E61-E60 -> 53.282134 | F62: =F61-F60 -> 7.9923201
A63: =Hold_Long&"-yr: sum of sleeve net proceeds" -> 10-yr: sum of sleeve net proceeds | B63: =B46+H46+N46 -> 4069.3083 | C63: =C46+I46+O46 -> 11695.705 | D63: =D46+J46+P46 -> 560.0774 | E63: =E46+K46+Q46 -> 8172.6909 | F63: =F46+L46+R46 -> 6065.0301
A64: =Hold_Long&"-yr: holdco net proceeds (Holdco Summary)" -> 10-yr: holdco net proceeds (Holdco Summary) | B64: ='Holdco Summary'!B79 -> 4069.3083 | C64: ='Holdco Summary'!C79 -> 11695.705 | D64: ='Holdco Summary'!D79 -> 560.0774 | E64: ='Holdco Summary'!E79 -> 8248.8505 | F64: ='Holdco Summary'!F79 -> 6076.4541
A65: =Hold_Long&"-yr: cross-sleeve netting effect" -> 10-yr: cross-sleeve netting effect | B65: =B64-B63 -> 0 | C65: =C64-C63 -> 1.8189894e-12 | D65: =D64-D63 -> 0 | E65: =E64-E63 -> 76.159584 | F65: =F64-F63 -> 11.423938
A66: Positive netting effect = the holdco waterfall (one pref / one carry across $750M) returns more to LPs than three stand-alone sleeve waterfalls, because strong sleeves offset weak ones before carry is charged. Negative = the reverse.

Sheet PME, DPI & Sensitivity
A1: PME, DPI & PROBABILITY PRESSURE TEST
A2: DPI/TVPI, KS-PME & Direct Alpha vs SPX/NDX, and Expected Net IRR sensitivity to the TSMC-Shock probability. Rows 11-69 = IQT-mirror sleeve ($250M) only; rows 72+ = total $840M holdco (all three sleeves) — ties to IC Summary headline.
A4: PUBLIC-MARKET BENCHMARK ASSUMPTIONS (blue = lever)
A5: S&P 500 (SPX) total-return CAGR | B5: 0.09
A6: Nasdaq-100 (NDX) total-return CAGR | B6: 0.13
A7: Long-run total-return assumptions; edit to your house view. KS-PME>1.0x = beat the index.
A9: Method: single terminal exit -> KS-PME = Net MOIC / index total-return multiple over the hold; Direct Alpha = KS-PME^(1/Hold)-1 (annualized outperformance). Paid-in assumed fully drawn = committed, so Net DPI = Net MOIC and RVPI=0 at exit (TVPI=DPI).
A11: ="IQT-MIRROR SLEEVE ($250M) — "&Hold_Short&"-YEAR DPI & PME" -> IQT-MIRROR SLEEVE ($250M) — 5-YEAR DPI & PME
A12: Metric | B12: Base | C12: Bull | D12: Bear | E12: TSMC-Shock | F12: Expected
A13: Net MOIC | B13: ='Fund Economics'!B14 -> 2.0045241 | C13: ='Fund Economics'!C14 -> 3.0878221 | D13: ='Fund Economics'!D14 -> 0.4051741 | E13: ='Fund Economics'!E14 -> 3.1231658 | F13: ='Fund Economics'!F14 -> 2.2032424
A14: Net DPI (to LP; =TVPI at exit) | B14: ='Fund Economics'!B12/IQT_Committed -> 2.0045241 | C14: ='Fund Economics'!C12/IQT_Committed -> 3.0878221 | D14: ='Fund Economics'!D12/IQT_Committed -> 0.4051741 | E14: ='Fund Economics'!E12/IQT_Committed -> 3.1231658 | F14: ='Fund Economics'!F12/IQT_Committed -> 2.2032424
A15: Gross DPI (deal-level) | B15: ='Fund Economics'!B6/IQT_Committed -> 2.2633231 | C15: ='Fund Economics'!C6/IQT_Committed -> 3.6174457 | D15: ='Fund Economics'!D6/IQT_Committed -> 0.5051741 | E15: ='Fund Economics'!E6/IQT_Committed -> 3.6616253 | F15: ='Fund Economics'!F6/IQT_Committed -> 2.5478767
