Workbook

Sheet Read Me
B1: LEVIATHAN FUND — CORE PE VEHICLE
B2: IQT-Backed Deep-Tech Acquisition-Stake Portfolio | 5 / 7 / 10-Year Holds | Defense-Supercycle Overlay
B3: Anchored by Substrate, Inc. · Prepared 22-Sep-2026 · All figures USD millions unless noted
B5: PURPOSE
B6: Leviathan's core PE holdco is an $840M vehicle across THREE sub-funds: IQT-mirror deep-tech ($250M), Weapons ($390M), and Consumer/Value ($200M). All three sleeves are modeled bottom-up from individual holdings — IQT-mirror (nine In-Q-Tel names), Weapons (ten physical-layer holdings, incl. The Ellwood Group and Superior & Grand Valley for missile-procurement metal forging, and Faxon Machining for NGP / MOP / TLAM / BLU-136 warhead-case and missile machining), Consumer/Value (nine DTC/spending-cycle names) — each across four scenarios, 5/7/10-yr holds, gross-to-net waterfall, and PME, and roll up to a blended holdco return on the Holdco Summary tab. Start there for the top-down view; the sleeve tabs hold the detail.
B7: Scope: Leviathan runs four vehicles (~$1.5B AUM total); this workbook models only the core PE holdco vehicle ($840M) and its equity targets — not the other three vehicles.
B8: THE DEFENSE-SUPERCYCLE THESIS (now wired into returns)
B9: The book is built to be long the US side of the AI / semiconductor race with China and structurally hedged against a Taiwan contingency or loss of TSMC access. The Defense Supercycle tab scores every name on five strategic axes — China-race criticality, Taiwan/TSMC-insulation value, government/defense embeddedness, CFIUS-clean US-sovereignty, and supply-chain chokepoint leverage. Those scores drive a composite, which drives each name's re-rating in the TSMC-Shock scenario. Change a score and the shock returns move.
B11: HOW THE MODEL IS WIRED (edit blue cells only)
B12: • IC Summary — one-page holdco dashboard: net IRR / MOIC / proceeds / KS-PME by hold x scenario, sleeve gross MOIC, scenario weights and model integrity checks. Start here. • Assumptions — fund terms + per-name entry marks, checks, ownership, and Base/Bull/Bear CAGRs. TSMC-Shock CAGR is computed from the Supercycle tab.
B13: • Defense Supercycle — strategic scoring matrix, axis weights, shock calibration levers, and the four scenario probability weights. This is the thesis engine.
B14: • Allocation — nine positions, tranche, ownership, domicile, structuring/CFIUS flags.
... B27: 5. Simplified whole-fund European waterfall (no GP catch-up). Not investment advice — an internal IC planning model.

Sheet IC Summary
A1: LEVIATHAN CORE PE HOLDCO — IC SUMMARY
A2: $840M tripartite holdco (IQT-mirror / Weapons / Consumer-Value). USD $M. Expected = probability-weighted across Base/Bull/Bear/TSMC-Shock (weights on Defense Supercycle tab). Every figure links live to the model — no inputs on this page.
A4: HEADLINE — RECOMMENDED 7-YEAR VEHICLE (Expected case, net to LP)
A5: Metric | B5: Net IRR | C5: Net MOIC | D5: Net proceeds | E5: KS-PME basket | F5: KS-PME SPX
A6: Holdco — 7-yr, probability-weighted | B6: ='Holdco Summary'!F61 -> 0.19465272 | C6: ='Holdco Summary'!F59 -> 3.4728957 | D6: ='Holdco Summary'!F58 -> 2917.2323 | E6: ='Holdco Summary'!F64 -> 1.3055901 | F6: ='Holdco Summary'!F62 -> 1.8997929
A8: HOLDCO NET IRR TO LP
A9: Vehicle | B9: Base | C9: Bull | D9: Bear | E9: TSMC-Shock | F9: Expected
A10: 5-Year Hold | B10: ='Holdco Summary'!B40 -> 0.15733927 | C10: ='Holdco Summary'!C40 -> 0.27428659 | D10: ='Holdco Summary'!D40 -> -0.052345391 | E10: ='Holdco Summary'!E40 -> 0.21435583 | F10: ='Holdco Summary'!F40 -> 0.17972702
A11: 7-Year Hold | B11: ='Holdco Summary'!B61 -> 0.16130617 | C11: ='Holdco Summary'!C61 -> 0.28304723 | D11: ='Holdco Summary'!D61 -> -0.049463782 | E11: ='Holdco Summary'!E61 -> 0.23435009 | F11: ='Holdco Summary'!F61 -> 0.19465272
A12: 10-Year Hold | B12: ='Holdco Summary'!B82 -> 0.16698042 | C12: ='Holdco Summary'!C82 -> 0.29410141 | D12: ='Holdco Summary'!D82 -> -0.044928106 | E12: ='Holdco Summary'!E82 -> 0.25729863 | F12: ='Holdco Summary'!F82 -> 0.214407
A14: HOLDCO NET MOIC TO LP
A15: Vehicle | B15: Base | C15: Bull | D15: Bear | E15: TSMC-Shock | F15: Expected
A16: 5-Year Hold | B16: ='Holdco Summary'!B38 -> 2.0763638 | C16: ='Holdco Summary'!C38 -> 3.3599712 | D16: ='Holdco Summary'!D38 -> 0.76427631 | E16: ='Holdco Summary'!E38 -> 2.6407654 | F16: ='Holdco Summary'!F38 -> 2.2851128
A17: 7-Year Hold | B17: ='Holdco Summary'!B59 -> 2.8485715 | C17: ='Holdco Summary'!C59 -> 5.7239853 | D17: ='Holdco Summary'!D59 -> 0.70110116 | E17: ='Holdco Summary'!E59 -> 4.3658466 | F17: ='Holdco Summary'!F59 -> 3.4728957
A18: 10-Year Hold | B18: ='Holdco Summary'!B80 -> 4.6842028 | C18: ='Holdco Summary'!C80 -> 13.172952 | D18: ='Holdco Summary'!D80 -> 0.63148152 | E18: ='Holdco Summary'!E80 -> 9.8715289 | F18: ='Holdco Summary'!F80 -> 6.9765809
A20: HOLDCO NET PROCEEDS TO LP ($M)
A21: Vehicle | B21: Base | C21: Bull | D21: Bear | E21: TSMC-Shock | F21: Expected
A22: 5-Year Hold | B22: ='Holdco Summary'!B37 -> 1744.1456 | C22: ='Holdco Summary'!C37 -> 2822.3758 | D22: ='Holdco Summary'!D37 -> 641.9921 | E22: ='Holdco Summary'!E37 -> 2218.2429 | F22: ='Holdco Summary'!F37 -> 1919.4947
A23: 7-Year Hold | B23: ='Holdco Summary'!B58 -> 2392.8 | C23: ='Holdco Summary'!C58 -> 4808.1476 | D23: ='Holdco Summary'!D58 -> 588.92498 | E23: ='Holdco Summary'!E58 -> 3667.3112 | F23: ='Holdco Summary'!F58 -> 2917.2323
A24: 10-Year Hold | B24: ='Holdco Summary'!B79 -> 3934.7303 | C24: ='Holdco Summary'!C79 -> 11065.28 | D24: ='Holdco Summary'!D79 -> 530.44448 | E24: ='Holdco Summary'!E79 -> 8292.0843 | F24: ='Holdco Summary'!F79 -> 5860.3279
A26: KS-PME vs DEFENSE+SEMIS BASKET (>1.00x = beat the thematic ETFs)
A27: Vehicle | B27: Base | C27: Bull | D27: Bear | E27: TSMC-Shock | F27: Expected
A28: 5-Year Hold | B28: ='Holdco Summary'!B43 -> 1.0323198 | C28: ='Holdco Summary'!C43 -> 1.6704995 | D28: ='Holdco Summary'!D43 -> 0.3799804 | E28: ='Holdco Summary'!E43 -> 1.3129271 | F28: ='Holdco Summary'!F43 -> 1.1361049
A29: 7-Year Hold | B29: ='Holdco Summary'!B64 -> 1.0708835 | C29: ='Holdco Summary'!C64 -> 2.1518581 | D29: ='Holdco Summary'!D64 -> 0.2635699 | E29: ='Holdco Summary'!E64 -> 1.6412835 | F29: ='Holdco Summary'!F64 -> 1.3055901
A30: 10-Year Hold | B30: ='Holdco Summary'!B85 -> 1.1578633 | C30: ='Holdco Summary'!C85 -> 3.2561523 | D30: ='Holdco Summary'!D85 -> 0.15609257 | E30: ='Holdco Summary'!E85 -> 2.440091 | F30: ='Holdco Summary'!F85 -> 1.7245041
A32: KS-PME vs S&P 500 (>1.00x = beat)
A33: Vehicle | B33: Base | C33: Bull | D33: Bear | E33: TSMC-Shock | F33: Expected
A34: 5-Year Hold | B34: ='Holdco Summary'!B41 -> 1.349494 | C34: ='Holdco Summary'!C41 -> 2.1837508 | D34: ='Holdco Summary'!D41 -> 0.49672716 | E34: ='Holdco Summary'!E41 -> 1.7163163 | F34: ='Holdco Summary'!F41 -> 1.4851665
A35: 7-Year Hold | B35: ='Holdco Summary'!B62 -> 1.5582661 | C35: ='Holdco Summary'!C62 -> 3.131216 | D35: ='Holdco Summary'!D62 -> 0.38352634 | E35: ='Holdco Summary'!E62 -> 2.3882676 | F35: ='Holdco Summary'!F62 -> 1.8997929
A36: 10-Year Hold | B36: ='Holdco Summary'!B83 -> 1.9786579 | C36: ='Holdco Summary'!C83 -> 5.5643974 | D36: ='Holdco Summary'!D83 -> 0.26674462 | E36: ='Holdco Summary'!E83 -> 4.1698405 | F36: ='Holdco Summary'!F83 -> 2.9469832
A38: SLEEVE SIZING
A39: Sleeve | B39: Size ($M) | C39: % Holdco | D39: # Positions
A40: ='Holdco Summary'!A6 -> IQT-mirror (deep-tech) | B40: ='Holdco Summary'!B6 -> 250 | C40: ='Holdco Summary'!C6 -> 0.29761905 | D40: =COUNT(Assumptions!C18:C26) -> 9
A41: ='Holdco Summary'!A7 -> Weapons (physical layer) | B41: ='Holdco Summary'!B7 -> 390 | C41: ='Holdco Summary'!C7 -> 0.46428571 | D41: =COUNT('Weapons Sleeve'!C12:C21) -> 10
A42: ='Holdco Summary'!A8 -> Consumer / Value | B42: ='Holdco Summary'!B8 -> 200 | C42: ='Holdco Summary'!C8 -> 0.23809524 | D42: =COUNT('Consumer Sleeve'!C12:C20) -> 9
A43: Total holdco | B43: =SUM(B40:B42) -> 840 | C43: =SUM(C40:C42) -> 1 | D43: =SUM(D40:D42) -> 28
A45: SLEEVE GROSS MOIC — 5-YEAR HOLD (gross proceeds / committed)
A46: Sleeve | B46: Base | C46: Bull | D46: Bear | E46: TSMC-Shock | F46: Expected
A47: IQT-mirror | B47: ='Holdco Summary'!B28/'Holdco Summary'!$B$6 -> 2.2633231 | C47: ='Holdco Summary'!C28/'Holdco Summary'!$B$6 -> 3.6174457 | D47: ='Holdco Summary'!D28/'Holdco Summary'!$B$6 -> 0.5051741 | E47: ='Holdco Summary'!E28/'Holdco Summary'!$B$6 -> 3.6616253 | F47: ='Holdco Summary'!F28/'Holdco Summary'!$B$6 -> 2.5478767
A48: Weapons | B48: ='Holdco Summary'!B29/'Holdco Summary'!$B$7 -> 2.4025132 | C48: ='Holdco Summary'!C29/'Holdco Summary'!$B$7 -> 3.9899007 | D48: ='Holdco Summary'!D29/'Holdco Summary'!$B$7 -> 1.124153 | E48: ='Holdco Summary'!E29/'Holdco Summary'!$B$7 -> 3.9973937 | F48: ='Holdco Summary'!F29/'Holdco Summary'!$B$7 -> 2.8468381
A49: Consumer / Value | B49: ='Holdco Summary'!B30/'Holdco Summary'!$B$8 -> 2.3690607 | C49: ='Holdco Summary'!C30/'Holdco Summary'!$B$8 -> 4.3199412 | D49: ='Holdco Summary'!D30/'Holdco Summary'!$B$8 -> 0.80639458 | E49: ='Holdco Summary'!E30/'Holdco Summary'!$B$8 -> 0.47427432 | F49: ='Holdco Summary'!F30/'Holdco Summary'!$B$8 -> 2.3381629
A50: Holdco gross | B50: ='Holdco Summary'!B31/'Holdco Summary'!$B$9 -> 2.3531227 | C50: ='Holdco Summary'!C31/'Holdco Summary'!$B$9 -> 3.957632 | D50: ='Holdco Summary'!D31/'Holdco Summary'!$B$9 -> 0.86427631 | E50: ='Holdco Summary'!E31/'Holdco Summary'!$B$9 -> 3.0586247 | F50: ='Holdco Summary'!F31/'Holdco Summary'!$B$9 -> 2.6367484
A52: SLEEVE GROSS MOIC — 7-YEAR HOLD (gross proceeds / committed)
A53: Sleeve | B53: Base | C53: Bull | D53: Bear | E53: TSMC-Shock | F53: Expected
A54: IQT-mirror | B54: ='Holdco Summary'!B49/'Holdco Summary'!$B$6 -> 3.1125231 | C54: ='Holdco Summary'!C49/'Holdco Summary'!$B$6 -> 5.9880212 | D54: ='Holdco Summary'!D49/'Holdco Summary'!$B$6 -> 0.40013475 | E54: ='Holdco Summary'!E49/'Holdco Summary'!$B$6 -> 6.1697901 | F54: ='Holdco Summary'!F49/'Holdco Summary'!$B$6 -> 3.8831294
A55: Weapons | B55: ='Holdco Summary'!B50/'Holdco Summary'!$B$7 -> 3.4306459 | C55: ='Holdco Summary'!C50/'Holdco Summary'!$B$7 -> 7.066006 | D55: ='Holdco Summary'!D50/'Holdco Summary'!$B$7 -> 1.1724463 | E55: ='Holdco Summary'!E50/'Holdco Summary'!$B$7 -> 7.0733477 | F55: ='Holdco Summary'!F50/'Holdco Summary'!$B$7 -> 4.5471613
A56: Consumer / Value | B56: ='Holdco Summary'!B51/'Holdco Summary'!$B$8 -> 3.3100714 | C56: ='Holdco Summary'!C51/'Holdco Summary'!$B$8 -> 7.7226691 | D56: ='Holdco Summary'!D51/'Holdco Summary'!$B$8 -> 0.74618623 | E56: ='Holdco Summary'!E51/'Holdco Summary'!$B$8 -> 0.35091369 | F56: ='Holdco Summary'!F51/'Holdco Summary'!$B$8 -> 3.5847644
A57: Holdco gross | B57: ='Holdco Summary'!B52/'Holdco Summary'!$B$9 -> 3.3072583 | C57: ='Holdco Summary'!C52/'Holdco Summary'!$B$9 -> 6.9015255 | D57: ='Holdco Summary'!D52/'Holdco Summary'!$B$9 -> 0.84110116 | E57: ='Holdco Summary'!E52/'Holdco Summary'!$B$9 -> 5.2038522 | F57: ='Holdco Summary'!F52/'Holdco Summary'!$B$9 -> 4.1203906
A59: SLEEVE GROSS MOIC — 10-YEAR HOLD (gross proceeds / committed)
A60: Sleeve | B60: Base | C60: Bull | D60: Bear | E60: TSMC-Shock | F60: Expected
A61: IQT-mirror | B61: ='Holdco Summary'!B70/'Holdco Summary'!$B$6 -> 5.0458237 | C61: ='Holdco Summary'!C70/'Holdco Summary'!$B$6 -> 12.790789 | D61: ='Holdco Summary'!D70/'Holdco Summary'!$B$6 -> 0.29585342 | E61: ='Holdco Summary'!E70/'Holdco Summary'!$B$6 -> 13.672406 | F61: ='Holdco Summary'!F70/'Holdco Summary'!$B$6 -> 7.5635568
A62: Weapons | B62: ='Holdco Summary'!B71/'Holdco Summary'!$B$7 -> 5.9340124 | C62: ='Holdco Summary'!C71/'Holdco Summary'!$B$7 -> 17.079294 | D62: ='Holdco Summary'!D71/'Holdco Summary'!$B$7 -> 1.2513962 | E62: ='Holdco Summary'!E71/'Holdco Summary'!$B$7 -> 17.072831 | F62: ='Holdco Summary'!F71/'Holdco Summary'!$B$7 -> 9.6887631
A63: Consumer / Value | B63: ='Holdco Summary'!B72/'Holdco Summary'!$B$8 -> 5.4965894 | C63: ='Holdco Summary'!C72/'Holdco Summary'!$B$8 -> 18.648019 | D63: ='Holdco Summary'!D72/'Holdco Summary'!$B$8 -> 0.68218299 | E63: ='Holdco Summary'!E72/'Holdco Summary'!$B$8 -> 0.22612753 | F63: ='Holdco Summary'!F72/'Holdco Summary'!$B$8 -> 7.2717166
A64: Holdco gross | B64: ='Holdco Summary'!B73/'Holdco Summary'!$B$9 -> 5.5655222 | C64: ='Holdco Summary'!C73/'Holdco Summary'!$B$9 -> 16.176459 | D64: ='Holdco Summary'!D73/'Holdco Summary'!$B$9 -> 0.83148152 | E64: ='Holdco Summary'!E73/'Holdco Summary'!$B$9 -> 12.04968 | F64: ='Holdco Summary'!F73/'Holdco Summary'!$B$9 -> 8.480774
A66: SCENARIO PROBABILITY WEIGHTS (edit on Defense Supercycle tab)
B67: Base | C67: Bull | D67: Bear | E67: TSMC-Shock | F67: Total
A68: Probability | B68: ='Defense Supercycle'!B17 -> 0.45 | C68: ='Defense Supercycle'!B18 -> 0.25 | D68: ='Defense Supercycle'!B19 -> 0.15 | E68: ='Defense Supercycle'!B20 -> 0.15 | F68: =SUM(B68:E68) -> 1
A70: MODEL INTEGRITY CHECKS
A71: Check | B71: Model | C71: Target | D71: Status
A72: Holdco size = $840M | B72: ='Holdco Summary'!B9 -> 840 | C72: 840 | D72: =IF(ABS(B72-C72)<0.001,"OK","CHECK") -> OK
A73: IQT-mirror deployed = committed | B73: =Assumptions!C27 -> 250 | C73: =Assumptions!B5 -> 250 | D73: =IF(ABS(B73-C73)<0.001,"OK","CHECK") -> OK
A74: Weapons deployed = committed | B74: ='Weapons Sleeve'!C22 -> 390 | C74: ='Weapons Sleeve'!B5 -> 390 | D74: =IF(ABS(B74-C74)<0.001,"OK","CHECK") -> OK
A75: Consumer deployed = committed | B75: ='Consumer Sleeve'!C21 -> 200 | C75: ='Consumer Sleeve'!B5 -> 200 | D75: =IF(ABS(B75-C75)<0.001,"OK","CHECK") -> OK
A76: Scenario probabilities = 100% | B76: ='Defense Supercycle'!B21 -> 1 | C76: 1 | D76: =IF(ABS(B76-C76)<0.001,"OK","CHECK") -> OK
A77: Strategic axis weights = 100% | B77: ='Defense Supercycle'!B10 -> 1 | C77: 1 | D77: =IF(ABS(B77-C77)<0.001,"OK","CHECK") -> OK
A78: IQT allocation % fund = 100% | B78: =Allocation!D14 -> 1 | C78: 1 | D78: =IF(ABS(B78-C78)<0.001,"OK","CHECK") -> OK
A79: Holdco 7-yr gross ties to sleeves (Expected) | B79: ='Holdco Summary'!F52 -> 3461.1281 | C79: ='Fund Economics'!F22+'Holdco Summary'!F50+'Holdco Summary'!F51 -> 3461.1281 | D79: =IF(ABS(B79-C79)<0.001,"OK","CHECK") -> OK
A80: Overall | D80: =IF(COUNTIF(D72:D79,"OK")=8,"ALL PASS","REVIEW") -> ALL PASS
A82: READ-THROUGH
A83: ="• Underwrite to Expected: 7-yr holdco net IRR "&TEXT('Holdco Summary'!F61,"0.0%")&" / "&TEXT('Holdco Summary'!F59,"0.00")&"x net MOIC; Base "&TEXT('Holdco Summary'!B61,"0.0%")&", Bear "&TEXT('Holdco Summary'!D61,"0.0%")&"." -> • Underwrite to Expected: 7-yr holdco net IRR 19.5% / 3.47x net MOIC; Base 16.1%, Bear -4.9%.
A84: ="• Thematic scoreboard: 7-yr Expected KS-PME vs Defense+Semis basket "&TEXT('Holdco Summary'!F64,"0.00")&"x (Base "&TEXT('Holdco Summary'!B64,"0.00")&"x) — >1.00x means the holdco beats owning ITA/SOXX." -> • Thematic scoreboard: 7-yr Expected KS-PME vs Defense+Semis basket 1.31x (Base 1.07x) — >1.00x means the holdco beats owning ITA/SOXX.
A85: • Bear case is a capital-loss outcome at every hold (net MOIC < 1.0x) — the downside is carried by the IQT seed names and Consumer; sizing, not the thesis, is the protection.
A86: ="• TSMC-Shock is a low-probability tail ("&TEXT('Defense Supercycle'!B20,"0%")&") that lifts Expected because the book is overweight US sovereign-chokepoint names; Consumer is the one sleeve hurt in that case." -> • TSMC-Shock is a low-probability tail (15%) that lifts Expected because the book is overweight US sovereign-chokepoint names; Consumer is the one sleeve hurt in that case.
A87: • Six of nine IQT entry marks and most Weapons marks are estimates — see Assumptions col J / Weapons Sleeve col J. Confirm via primary diligence before IC vote.

Sheet Holdco Summary
A1: LEVIATHAN — CORE PE HOLDCO ($840M) — TRIPARTITE ROLL-UP
A2: Three sub-funds rolled up to a blended holdco return. Blue = lever. All three sleeves — IQT-mirror, Weapons, Consumer/Value — flow in bottom-up.
A4: HOLDCO STRUCTURE & SIZING
A5: Sub-fund | B5: Size ($M) | C5: % Holdco | D5: Return driver | E5: Duration | F5: Role
A6: IQT-mirror (deep-tech) | B6: 250 | C6: =B6/$B$9 -> 0.29761905 | D6: Onshoring capex + Taiwan tail | E6: Longest | F6: Convex optionality / tail hedge
A7: Weapons (physical layer) | B7: 390 | C7: =B7/$B$9 -> 0.46428571 | D7: Defense opex — budgets, conflict | E7: Medium | F7: Cash-generative supercycle core
A8: Consumer / Value | B8: 200 | C8: =B8/$B$9 -> 0.23809524 | D8: Consumer cycle + DTC/wellness | E8: Shortest | F8: Ballast + near-term DPI engine
A9: TOTAL (must = $840M) | B9: =SUM(B6:B8) -> 840 | C9: =SUM(C6:C8) -> 1
A10: IQT-mirror: Substrate, EUV Tech, ThinTronics, EdgeCortix, Syntiant, Infleqtion, Diraq, Mueon, DefendEye
A11: Weapons: Epirus, Elta, Israel Aerospace Industries, Saronic, Helicon Chemical, Applied Research Associates, Heckler & Koch, The Ellwood Group, Superior & Grand Valley, Faxon Machining
A12: Consumer/Value: Quince, Thrive Market, The Farmer's Dog, Whoop, Plunge, Made In Cookware, Polymarket, Goat Group, Stripe
A14: SLEEVE RETURN ASSUMPTIONS — gross equity CAGR, net of dilution (blue)
A15: Sleeve | B15: Base | C15: Bull | D15: Bear | E15: TSMC-Shock
A16: Weapons (memo — now bottom-up) | B16: 0.22 | C16: 0.34 | D16: 0.05 | E16: 0.32
A17: Consumer / Value (memo — now bottom-up) | B17: 0.14 | C17: 0.25 | D17: -0.1 | E17: -0.04
A18: IQT-mirror, Weapons, AND Consumer/Value are all modeled bottom-up (Portfolio Returns / Weapons Sleeve / Consumer Sleeve tabs) and flow in directly. Both rows above are memos only, kept for reference to the original sleeve-level placeholder assumptions they replaced.
A20: BENCHMARKS (KS-PME > 1.0x = beat)
A21: S&P 500 (SPX) total-return CAGR | B21: ='PME, DPI & Sensitivity'!$B$5 -> 0.09
A22: Nasdaq-100 (NDX) total-return CAGR | B22: ='PME, DPI & Sensitivity'!$B$6 -> 0.13
A23: Defense+Semis thematic basket CAGR (ITA/SOXX blend) | B23: 0.15
A24: Forward-tempered: 50/50 ITA/SOXX trailing 5yr is ~26% (ITA 18.2% / SOXX 34.5% to Jun-26), inflated by the AI+rearmament run; 15% forward. See Macro Overlay for comps & drivers.
A26: 5-YEAR HOLDCO ROLL-UP
A27: Line item ($M) | B27: Base | C27: Bull | D27: Bear | E27: TSMC-Shock | F27: Expected
A28: IQT-mirror gross | B28: ='Fund Economics'!B6 -> 565.83078 | C28: ='Fund Economics'!C6 -> 904.36142 | D28: ='Fund Economics'!D6 -> 126.29353 | E28: ='Fund Economics'!E6 -> 915.40631 | F28: ='Fund Economics'!F6 -> 636.96918
A29: Weapons gross | B29: ='Weapons Sleeve'!C36 -> 936.98016 | C29: ='Weapons Sleeve'!F36 -> 1556.0613 | D29: ='Weapons Sleeve'!I36 -> 438.41966 | E29: ='Weapons Sleeve'!L36 -> 1558.9836 | F29: =B29*'Defense Supercycle'!$B$17+C29*'Defense Supercycle'!$B$18+D29*'Defense Supercycle'!$B$19+E29*'Defense Supercycle'!$B$20 -> 1110.2669
A30: Consumer/Value gross | B30: ='Consumer Sleeve'!C34 -> 473.81214 | C30: ='Consumer Sleeve'!F34 -> 863.98824 | D30: ='Consumer Sleeve'!I34 -> 161.27892 | E30: ='Consumer Sleeve'!L34 -> 94.854864 | F30: =B30*'Defense Supercycle'!$B$17+C30*'Defense Supercycle'!$B$18+D30*'Defense Supercycle'!$B$19+E30*'Defense Supercycle'!$B$20 -> 467.63259
A31: HOLDCO gross proceeds | B31: =B28+B29+B30 -> 1976.6231 | C31: =C28+C29+C30 -> 3324.4109 | D31: =D28+D29+D30 -> 725.9921 | E31: =E28+E29+E30 -> 2569.2447 | F31: =F28+F29+F30 -> 2214.8686
A32: (-) Return of capital | B32: =-'Holdco Summary'!$B$9 -> -840 | C32: =-'Holdco Summary'!$B$9 -> -840 | D32: =-'Holdco Summary'!$B$9 -> -840 | E32: =-'Holdco Summary'!$B$9 -> -840 | F32: =-'Holdco Summary'!$B$9 -> -840
A33: (-) Preferred (8% comp.) | B33: =-'Holdco Summary'!$B$9*((1+Assumptions!$B$10)^5-1) -> -394.23558 | C33: =-'Holdco Summary'!$B$9*((1+Assumptions!$B$10)^5-1) -> -394.23558 | D33: =-'Holdco Summary'!$B$9*((1+Assumptions!$B$10)^5-1) -> -394.23558 | E33: =-'Holdco Summary'!$B$9*((1+Assumptions!$B$10)^5-1) -> -394.23558 | F33: =-'Holdco Summary'!$B$9*((1+Assumptions!$B$10)^5-1) -> -394.23558
A34: Profit above pref | B34: =MAX(0,B31+B32+B33) -> 742.3875 | C34: =MAX(0,C31+C32+C33) -> 2090.1753 | D34: =MAX(0,D31+D32+D33) -> 0 | E34: =MAX(0,E31+E32+E33) -> 1335.0092 | F34: =B34*'Defense Supercycle'!$B$17+C34*'Defense Supercycle'!$B$18+D34*'Defense Supercycle'!$B$19+E34*'Defense Supercycle'!$B$20 -> 1056.8696
A35: (-) Carry (20%) | B35: =-Assumptions!$B$9*B34 -> -148.4775 | C35: =-Assumptions!$B$9*C34 -> -418.03507 | D35: =-Assumptions!$B$9*D34 -> 0 | E35: =-Assumptions!$B$9*E34 -> -267.00183 | F35: =B35*'Defense Supercycle'!$B$17+C35*'Defense Supercycle'!$B$18+D35*'Defense Supercycle'!$B$19+E35*'Defense Supercycle'!$B$20 -> -211.37392
A36: (-) Mgmt fees (2%/yr) | B36: =-'Holdco Summary'!$B$9*Assumptions!$B$8*5 -> -84 | C36: =-'Holdco Summary'!$B$9*Assumptions!$B$8*5 -> -84 | D36: =-'Holdco Summary'!$B$9*Assumptions!$B$8*5 -> -84 | E36: =-'Holdco Summary'!$B$9*Assumptions!$B$8*5 -> -84 | F36: =-'Holdco Summary'!$B$9*Assumptions!$B$8*5 -> -84
A37: NET proceeds to LP | B37: =B31+B35+B36 -> 1744.1456 | C37: =C31+C35+C36 -> 2822.3758 | D37: =D31+D35+D36 -> 641.9921 | E37: =E31+E35+E36 -> 2218.2429 | F37: =F31+F35+F36 -> 1919.4947
A38: Net MOIC | B38: =B37/'Holdco Summary'!$B$9 -> 2.0763638 | C38: =C37/'Holdco Summary'!$B$9 -> 3.3599712 | D38: =D37/'Holdco Summary'!$B$9 -> 0.76427631 | E38: =E37/'Holdco Summary'!$B$9 -> 2.6407654 | F38: =F37/'Holdco Summary'!$B$9 -> 2.2851128
A39: Net DPI (=TVPI at exit) | B39: =B37/'Holdco Summary'!$B$9 -> 2.0763638 | C39: =C37/'Holdco Summary'!$B$9 -> 3.3599712 | D39: =D37/'Holdco Summary'!$B$9 -> 0.76427631 | E39: =E37/'Holdco Summary'!$B$9 -> 2.6407654 | F39: =F37/'Holdco Summary'!$B$9 -> 2.2851128
A40: Net IRR | B40: =(B37/'Holdco Summary'!$B$9)^(1/5)-1 -> 0.15733927 | C40: =(C37/'Holdco Summary'!$B$9)^(1/5)-1 -> 0.27428659 | D40: =(D37/'Holdco Summary'!$B$9)^(1/5)-1 -> -0.052345391 | E40: =(E37/'Holdco Summary'!$B$9)^(1/5)-1 -> 0.21435583 | F40: =(F37/'Holdco Summary'!$B$9)^(1/5)-1 -> 0.17972702
A41: KS-PME vs SPX | B41: =B38/(1+'Holdco Summary'!$B$21)^5 -> 1.349494 | C41: =C38/(1+'Holdco Summary'!$B$21)^5 -> 2.1837508 | D41: =D38/(1+'Holdco Summary'!$B$21)^5 -> 0.49672716 | E41: =E38/(1+'Holdco Summary'!$B$21)^5 -> 1.7163163 | F41: =F38/(1+'Holdco Summary'!$B$21)^5 -> 1.4851665
A42: KS-PME vs NDX | B42: =B38/(1+'Holdco Summary'!$B$22)^5 -> 1.1269671 | C42: =C38/(1+'Holdco Summary'!$B$22)^5 -> 1.8236578 | D42: =D38/(1+'Holdco Summary'!$B$22)^5 -> 0.41481856 | E42: =E38/(1+'Holdco Summary'!$B$22)^5 -> 1.4333016 | F42: =F38/(1+'Holdco Summary'!$B$22)^5 -> 1.2402677
A43: KS-PME vs Defense+Semis basket | B43: =B38/(1+'Holdco Summary'!$B$23)^5 -> 1.0323198 | C43: =C38/(1+'Holdco Summary'!$B$23)^5 -> 1.6704995 | D43: =D38/(1+'Holdco Summary'!$B$23)^5 -> 0.3799804 | E43: =E38/(1+'Holdco Summary'!$B$23)^5 -> 1.3129271 | F43: =F38/(1+'Holdco Summary'!$B$23)^5 -> 1.1361049
A44: Direct Alpha vs basket (ann.) | B44: =(B38/(1+'Holdco Summary'!$B$23)^5)^(1/5)-1 -> 0.0063819732 | C44: =(C38/(1+'Holdco Summary'!$B$23)^5)^(1/5)-1 -> 0.10807529 | D44: =(D38/(1+'Holdco Summary'!$B$23)^5)^(1/5)-1 -> -0.17595251 | E44: =(E38/(1+'Holdco Summary'!$B$23)^5)^(1/5)-1 -> 0.055961593 | F44: =(F38/(1+'Holdco Summary'!$B$23)^5)^(1/5)-1 -> 0.025849585
A47: 7-YEAR HOLDCO ROLL-UP
A48: Line item ($M) | B48: Base | C48: Bull | D48: Bear | E48: TSMC-Shock | F48: Expected
A49: IQT-mirror gross | B49: ='Fund Economics'!B22 -> 778.13077 | C49: ='Fund Economics'!C22 -> 1497.0053 | D49: ='Fund Economics'!D22 -> 100.03369 | E49: ='Fund Economics'!E22 -> 1542.4475 | F49: ='Fund Economics'!F22 -> 970.78235
A50: Weapons gross | B50: ='Weapons Sleeve'!C51 -> 1337.9519 | C50: ='Weapons Sleeve'!F51 -> 2755.7423 | D50: ='Weapons Sleeve'!I51 -> 457.25404 | E50: ='Weapons Sleeve'!L51 -> 2758.6056 | F50: =B50*'Defense Supercycle'!$B$17+C50*'Defense Supercycle'!$B$18+D50*'Defense Supercycle'!$B$19+E50*'Defense Supercycle'!$B$20 -> 1773.3929
A51: Consumer/Value gross | B51: ='Consumer Sleeve'!C48 -> 662.01427 | C51: ='Consumer Sleeve'!F48 -> 1544.5338 | D51: ='Consumer Sleeve'!I48 -> 149.23725 | E51: ='Consumer Sleeve'!L48 -> 70.182739 | F51: =B51*'Defense Supercycle'!$B$17+C51*'Defense Supercycle'!$B$18+D51*'Defense Supercycle'!$B$19+E51*'Defense Supercycle'!$B$20 -> 716.95288
A52: HOLDCO gross proceeds | B52: =B49+B50+B51 -> 2778.097 | C52: =C49+C50+C51 -> 5797.2814 | D52: =D49+D50+D51 -> 706.52498 | E52: =E49+E50+E51 -> 4371.2359 | F52: =F49+F50+F51 -> 3461.1281
A53: (-) Return of capital | B53: =-'Holdco Summary'!$B$9 -> -840 | C53: =-'Holdco Summary'!$B$9 -> -840 | D53: =-'Holdco Summary'!$B$9 -> -840 | E53: =-'Holdco Summary'!$B$9 -> -840 | F53: =-'Holdco Summary'!$B$9 -> -840
A54: (-) Preferred (8% comp.) | B54: =-'Holdco Summary'!$B$9*((1+Assumptions!$B$10)^7-1) -> -599.61239 | C54: =-'Holdco Summary'!$B$9*((1+Assumptions!$B$10)^7-1) -> -599.61239 | D54: =-'Holdco Summary'!$B$9*((1+Assumptions!$B$10)^7-1) -> -599.61239 | E54: =-'Holdco Summary'!$B$9*((1+Assumptions!$B$10)^7-1) -> -599.61239 | F54: =-'Holdco Summary'!$B$9*((1+Assumptions!$B$10)^7-1) -> -599.61239
A55: Profit above pref | B55: =MAX(0,B52+B53+B54) -> 1338.4846 | C55: =MAX(0,C52+C53+C54) -> 4357.6691 | D55: =MAX(0,D52+D53+D54) -> 0 | E55: =MAX(0,E52+E53+E54) -> 2931.6235 | F55: =B55*'Defense Supercycle'!$B$17+C55*'Defense Supercycle'!$B$18+D55*'Defense Supercycle'!$B$19+E55*'Defense Supercycle'!$B$20 -> 2131.4788
A56: (-) Carry (20%) | B56: =-Assumptions!$B$9*B55 -> -267.69691 | C56: =-Assumptions!$B$9*C55 -> -871.53381 | D56: =-Assumptions!$B$9*D55 -> 0 | E56: =-Assumptions!$B$9*E55 -> -586.32469 | F56: =B56*'Defense Supercycle'!$B$17+C56*'Defense Supercycle'!$B$18+D56*'Defense Supercycle'!$B$19+E56*'Defense Supercycle'!$B$20 -> -426.29577
A57: (-) Mgmt fees (2%/yr) | B57: =-'Holdco Summary'!$B$9*Assumptions!$B$8*7 -> -117.6 | C57: =-'Holdco Summary'!$B$9*Assumptions!$B$8*7 -> -117.6 | D57: =-'Holdco Summary'!$B$9*Assumptions!$B$8*7 -> -117.6 | E57: =-'Holdco Summary'!$B$9*Assumptions!$B$8*7 -> -117.6 | F57: =-'Holdco Summary'!$B$9*Assumptions!$B$8*7 -> -117.6
A58: NET proceeds to LP | B58: =B52+B56+B57 -> 2392.8 | C58: =C52+C56+C57 -> 4808.1476 | D58: =D52+D56+D57 -> 588.92498 | E58: =E52+E56+E57 -> 3667.3112 | F58: =F52+F56+F57 -> 2917.2323
A59: Net MOIC | B59: =B58/'Holdco Summary'!$B$9 -> 2.8485715 | C59: =C58/'Holdco Summary'!$B$9 -> 5.7239853 | D59: =D58/'Holdco Summary'!$B$9 -> 0.70110116 | E59: =E58/'Holdco Summary'!$B$9 -> 4.3658466 | F59: =F58/'Holdco Summary'!$B$9 -> 3.4728957
A60: Net DPI (=TVPI at exit) | B60: =B58/'Holdco Summary'!$B$9 -> 2.8485715 | C60: =C58/'Holdco Summary'!$B$9 -> 5.7239853 | D60: =D58/'Holdco Summary'!$B$9 -> 0.70110116 | E60: =E58/'Holdco Summary'!$B$9 -> 4.3658466 | F60: =F58/'Holdco Summary'!$B$9 -> 3.4728957
A61: Net IRR | B61: =(B58/'Holdco Summary'!$B$9)^(1/7)-1 -> 0.16130617 | C61: =(C58/'Holdco Summary'!$B$9)^(1/7)-1 -> 0.28304723 | D61: =(D58/'Holdco Summary'!$B$9)^(1/7)-1 -> -0.049463782 | E61: =(E58/'Holdco Summary'!$B$9)^(1/7)-1 -> 0.23435009 | F61: =(F58/'Holdco Summary'!$B$9)^(1/7)-1 -> 0.19465272
A62: KS-PME vs SPX | B62: =B59/(1+'Holdco Summary'!$B$21)^7 -> 1.5582661 | C62: =C59/(1+'Holdco Summary'!$B$21)^7 -> 3.131216 | D62: =D59/(1+'Holdco Summary'!$B$21)^7 -> 0.38352634 | E62: =E59/(1+'Holdco Summary'!$B$21)^7 -> 2.3882676 | F62: =F59/(1+'Holdco Summary'!$B$21)^7 -> 1.8997929
A63: KS-PME vs NDX | B63: =B59/(1+'Holdco Summary'!$B$22)^7 -> 1.2108156 | C63: =C59/(1+'Holdco Summary'!$B$22)^7 -> 2.4330409 | D63: =D59/(1+'Holdco Summary'!$B$22)^7 -> 0.29801051 | E63: =E59/(1+'Holdco Summary'!$B$22)^7 -> 1.8557496 | F63: =F59/(1+'Holdco Summary'!$B$22)^7 -> 1.4761913
A64: KS-PME vs Defense+Semis basket | B64: =B59/(1+'Holdco Summary'!$B$23)^7 -> 1.0708835 | C64: =C59/(1+'Holdco Summary'!$B$23)^7 -> 2.1518581 | D64: =D59/(1+'Holdco Summary'!$B$23)^7 -> 0.2635699 | E64: =E59/(1+'Holdco Summary'!$B$23)^7 -> 1.6412835 | F64: =F59/(1+'Holdco Summary'!$B$23)^7 -> 1.3055901
A65: Direct Alpha vs basket (ann.) | B65: =(B59/(1+'Holdco Summary'!$B$23)^7)^(1/7)-1 -> 0.0098314481 | C65: =(C59/(1+'Holdco Summary'!$B$23)^7)^(1/7)-1 -> 0.11569325 | D65: =(D59/(1+'Holdco Summary'!$B$23)^7)^(1/7)-1 -> -0.17344677 | E65: =(E59/(1+'Holdco Summary'!$B$23)^7)^(1/7)-1 -> 0.073347905 | F65: =(F59/(1+'Holdco Summary'!$B$23)^7)^(1/7)-1 -> 0.038828452
A68: 10-YEAR HOLDCO ROLL-UP
A69: Line item ($M) | B69: Base | C69: Bull | D69: Bear | E69: TSMC-Shock | F69: Expected
A70: IQT-mirror gross | B70: ='Fund Economics'!B38 -> 1261.4559 | C70: ='Fund Economics'!C38 -> 3197.6972 | D70: ='Fund Economics'!D38 -> 73.963354 | E70: ='Fund Economics'!E38 -> 3418.1015 | F70: ='Fund Economics'!F38 -> 1890.8892
A71: Weapons gross | B71: ='Weapons Sleeve'!C66 -> 2314.2648 | C71: ='Weapons Sleeve'!F66 -> 6660.9246 | D71: ='Weapons Sleeve'!I66 -> 488.04453 | E71: ='Weapons Sleeve'!L66 -> 6658.4041 | F71: =B71*'Defense Supercycle'!$B$17+C71*'Defense Supercycle'!$B$18+D71*'Defense Supercycle'!$B$19+E71*'Defense Supercycle'!$B$20 -> 3778.6176
A72: Consumer/Value gross | B72: ='Consumer Sleeve'!C62 -> 1099.3179 | C72: ='Consumer Sleeve'!F62 -> 3729.6038 | D72: ='Consumer Sleeve'!I62 -> 136.4366 | E72: ='Consumer Sleeve'!L62 -> 45.225505 | F72: =B72*'Defense Supercycle'!$B$17+C72*'Defense Supercycle'!$B$18+D72*'Defense Supercycle'!$B$19+E72*'Defense Supercycle'!$B$20 -> 1454.3433
A73: HOLDCO gross proceeds | B73: =B70+B71+B72 -> 4675.0386 | C73: =C70+C71+C72 -> 13588.226 | D73: =D70+D71+D72 -> 698.44448 | E73: =E70+E71+E72 -> 10121.731 | F73: =F70+F71+F72 -> 7123.8501
A74: (-) Return of capital | B74: =-'Holdco Summary'!$B$9 -> -840 | C74: =-'Holdco Summary'!$B$9 -> -840 | D74: =-'Holdco Summary'!$B$9 -> -840 | E74: =-'Holdco Summary'!$B$9 -> -840 | F74: =-'Holdco Summary'!$B$9 -> -840
A75: (-) Preferred (8% comp.) | B75: =-'Holdco Summary'!$B$9*((1+Assumptions!$B$10)^10-1) -> -973.497 | C75: =-'Holdco Summary'!$B$9*((1+Assumptions!$B$10)^10-1) -> -973.497 | D75: =-'Holdco Summary'!$B$9*((1+Assumptions!$B$10)^10-1) -> -973.497 | E75: =-'Holdco Summary'!$B$9*((1+Assumptions!$B$10)^10-1) -> -973.497 | F75: =-'Holdco Summary'!$B$9*((1+Assumptions!$B$10)^10-1) -> -973.497
A76: Profit above pref | B76: =MAX(0,B73+B74+B75) -> 2861.5416 | C76: =MAX(0,C73+C74+C75) -> 11774.729 | D76: =MAX(0,D73+D74+D75) -> 0 | E76: =MAX(0,E73+E74+E75) -> 8308.2341 | F76: =B76*'Defense Supercycle'!$B$17+C76*'Defense Supercycle'!$B$18+D76*'Defense Supercycle'!$B$19+E76*'Defense Supercycle'!$B$20 -> 5477.611
A77: (-) Carry (20%) | B77: =-Assumptions!$B$9*B76 -> -572.30833 | C77: =-Assumptions!$B$9*C76 -> -2354.9457 | D77: =-Assumptions!$B$9*D76 -> 0 | E77: =-Assumptions!$B$9*E76 -> -1661.6468 | F77: =B77*'Defense Supercycle'!$B$17+C77*'Defense Supercycle'!$B$18+D77*'Defense Supercycle'!$B$19+E77*'Defense Supercycle'!$B$20 -> -1095.5222
A78: (-) Mgmt fees (2%/yr) | B78: =-'Holdco Summary'!$B$9*Assumptions!$B$8*10 -> -168 | C78: =-'Holdco Summary'!$B$9*Assumptions!$B$8*10 -> -168 | D78: =-'Holdco Summary'!$B$9*Assumptions!$B$8*10 -> -168 | E78: =-'Holdco Summary'!$B$9*Assumptions!$B$8*10 -> -168 | F78: =-'Holdco Summary'!$B$9*Assumptions!$B$8*10 -> -168
A79: NET proceeds to LP | B79: =B73+B77+B78 -> 3934.7303 | C79: =C73+C77+C78 -> 11065.28 | D79: =D73+D77+D78 -> 530.44448 | E79: =E73+E77+E78 -> 8292.0843 | F79: =F73+F77+F78 -> 5860.3279
A80: Net MOIC | B80: =B79/'Holdco Summary'!$B$9 -> 4.6842028 | C80: =C79/'Holdco Summary'!$B$9 -> 13.172952 | D80: =D79/'Holdco Summary'!$B$9 -> 0.63148152 | E80: =E79/'Holdco Summary'!$B$9 -> 9.8715289 | F80: =F79/'Holdco Summary'!$B$9 -> 6.9765809
A81: Net DPI (=TVPI at exit) | B81: =B79/'Holdco Summary'!$B$9 -> 4.6842028 | C81: =C79/'Holdco Summary'!$B$9 -> 13.172952 | D81: =D79/'Holdco Summary'!$B$9 -> 0.63148152 | E81: =E79/'Holdco Summary'!$B$9 -> 9.8715289 | F81: =F79/'Holdco Summary'!$B$9 -> 6.9765809
A82: Net IRR | B82: =(B79/'Holdco Summary'!$B$9)^(1/10)-1 -> 0.16698042 | C82: =(C79/'Holdco Summary'!$B$9)^(1/10)-1 -> 0.29410141 | D82: =(D79/'Holdco Summary'!$B$9)^(1/10)-1 -> -0.044928106 | E82: =(E79/'Holdco Summary'!$B$9)^(1/10)-1 -> 0.25729863 | F82: =(F79/'Holdco Summary'!$B$9)^(1/10)-1 -> 0.214407
A83: KS-PME vs SPX | B83: =B80/(1+'Holdco Summary'!$B$21)^10 -> 1.9786579 | C83: =C80/(1+'Holdco Summary'!$B$21)^10 -> 5.5643974 | D83: =D80/(1+'Holdco Summary'!$B$21)^10 -> 0.26674462 | E83: =E80/(1+'Holdco Summary'!$B$21)^10 -> 4.1698405 | F83: =F80/(1+'Holdco Summary'!$B$21)^10 -> 2.9469832
A84: KS-PME vs NDX | B84: =B80/(1+'Holdco Summary'!$B$22)^10 -> 1.3799116 | C84: =C80/(1+'Holdco Summary'!$B$22)^10 -> 3.8805983 | D84: =D80/(1+'Holdco Summary'!$B$22)^10 -> 0.1860271 | E84: =E80/(1+'Holdco Summary'!$B$22)^10 -> 2.9080374 | F84: =F80/(1+'Holdco Summary'!$B$22)^10 -> 2.0552194
A85: KS-PME vs Defense+Semis basket | B85: =B80/(1+'Holdco Summary'!$B$23)^10 -> 1.1578633 | C85: =C80/(1+'Holdco Summary'!$B$23)^10 -> 3.2561523 | D85: =D80/(1+'Holdco Summary'!$B$23)^10 -> 0.15609257 | E85: =E80/(1+'Holdco Summary'!$B$23)^10 -> 2.440091 | F85: =F80/(1+'Holdco Summary'!$B$23)^10 -> 1.7245041
A86: Direct Alpha vs basket (ann.) | B86: =(B80/(1+'Holdco Summary'!$B$23)^10)^(1/10)-1 -> 0.014765581 | C86: =(C80/(1+'Holdco Summary'!$B$23)^10)^(1/10)-1 -> 0.12530558 | D86: =(D80/(1+'Holdco Summary'!$B$23)^10)^(1/10)-1 -> -0.1695027 | E86: =(E80/(1+'Holdco Summary'!$B$23)^10)^(1/10)-1 -> 0.093303156 | F86: =(F80/(1+'Holdco Summary'!$B$23)^10)^(1/10)-1 -> 0.05600609
A89: READ-THROUGH
A90: • The holdco is a tripartite barbell: two defense-supercycle sleeves (digital enablers + physical effectors) + a consumer/value ballast that is uncorrelated and carries the near-term DPI.
A91: • Judge the IQT sleeve on its marginal contribution here — convexity and a Taiwan/TSMC hedge — not on a standalone 'beat the Nasdaq' test. That test lives at the holdco level.
A92: • The KS-PME vs the Defense+Semis basket is the real scoreboard: it asks whether the holdco captures the sovereign-capital trend earlier and cheaper than the public thematic ETFs everyone else uses.
A93: • All three sleeves — IQT-mirror, Weapons, and Consumer/Value — are now modeled bottom-up from individual holdings; only the SPX/NDX/thematic-basket benchmarks remain top-down inputs.

Sheet Macro Overlay
A1: MACRO, GEOPOLITICAL & DEFENSE-SUPERCYCLE OVERLAY
A2: Grounds the sleeve return assumptions in current comps and the geopolitical/macro picture. Figures as of ~Jun-Sep 2026; sourced below.
A4: 1 | PUBLIC & PRIVATE COMPS GROUNDING THE SLEEVE ASSUMPTIONS
A5: Comparable | B5: Metric | C5: Value | D5: Note / relevance
A6: ITA (US Aero & Defense ETF) | B6: Total return 1/5/10-yr | C6: 29.3% / 18.2% / 15.7% | D6: Defense supercycle already priced into public primes (as of Jun-26)
A7: SOXX (Semiconductor ETF) | B7: Total return 1/5/10-yr | C7: 169.6% / 34.5% / 36.6% | D7: AI-driven surge; forward mean-reversion risk off a huge base
A8: 50/50 ITA/SOXX basket | B8: Trailing 5-yr blend | C8: ~26.3% | D8: Thematic hurdle; model uses 15% FORWARD (tempered)
A9: SPX / NDX | B9: Forward CAGR (model) | C9: 9.0% / 13.0% | D9: Broad-market floor benchmarks
A10: Rheinmetall (RHM) | B10: Rev growth / EV-Rev / EV-EBITDA | C10: 40% / 4.0x / 17.3x | D10: European rearmament bellwether; $54B cap
A11: AeroVironment (AVAV) | B11: TTM rev / YoY | C11: $1.61B / +117% | D11: Drones/loitering munitions (incl. M&A); supercycle demand
A12: L3Harris (LHX) | B12: EV-Rev / EV-EBITDA | C12: 2.6x / 15.1x | D12: Established prime multiple anchor
A13: Saronic (private) | B13: Valuation / 2025 rev | C13: $9.25B / $200M (+1,500%) | D13: Naval autonomy hypergrowth (Series D, Mar-26)
A14: Anduril (private) | B14: Valuation / 2025 rev | C14: $61B / $2.2B (+120%) | D14: Scale-up reference; $20B Army ceiling (Mar-26)
A15: Epirus (private) | B15: Directed energy / HPM | C15: Growth-stage | D15: Counter-drone; Weapons-sleeve holding
A16: Grounded sleeve assumptions (Base/Bull/Bear/Shock gross CAGR): Weapons 22/34/5/32% (original sleeve memo, reference only — model runs bottom-up per name with the munitions/FMS overlay); Consumer modeled bottom-up per-name, two now market-priced via Forge secondary (Quince 28/45/2/-18%, Whoop 27/42/-3/-16%, The Farmer's Dog 22/34/10/-5% @ $3.76B Forge-implied, Made In Cookware 14/26/-10/-14% est., Thrive Market 7/16/-5/-8% @ ~$945M Forge-implied (down from $1.29B Series C), Plunge 20/50/-22/-28% est.); thematic basket 15% fwd. IQT-mirror is bottom-up.
A18: 2 | DEFENSE SUPERCYCLE DRIVERS
A19: • NATO 5%-of-GDP pledge (Hague summit, Jun-2025): 3.5% core defense + 1.5% defense-related, on a path to 2035 — a structural, decade-long step-up, not a cyclical bump.
A20: • European allies + Canada raised defense spending ~20% in 2025 alone; all allies now above the old 2% floor. Rheinmetall growing 40%/yr is the bellwether.
A21: • Munitions/energetics replenishment (Ukraine drawdown) + naval autonomy (Replicator) + counter-drone are the fastest-growing demand pools — directly the Weapons sleeve (Helicon, Saronic, Epirus).
A23: 3 | CHINA & GEOPOLITICAL PICTURE
A24: • China official defense budget ~1.78T yuan (~$245B) for 2025, +7.2% YoY (widely cited; pre-cutoff — confirm 2026 figure) — sustained double-digit real modernization for a decade.
A25: • 'Davidson window' (PLA capability vs. Taiwan by 2027) frames the tail-risk timeline the TSMC-Shock scenario models — the single point of failure is TSMC leading-edge capacity.
A26: • US-China tech decoupling: export controls on advanced semis/tooling, entity-list expansion, and reshoring incentives are the policy tailwind behind the IQT-mirror sleeve's sovereign-chokepoint names.
A28: 4 | GLOBAL MACRO BACKDROP
A29: • Rates/exit markets: the Fed path drives PE exit windows and long-duration deep-tech valuations most — a higher-for-longer regime compresses the IQT sleeve's terminal multiples and delays exits (lengthens duration, lowers DPI timing).
A30: • USD & inflation: a decoupling/Taiwan shock is inflationary (supply shock) and USD-volatile — negative for the Consumer sleeve overall, though now modeled per-name on the Consumer Sleeve tab: import/hardware-exposed names (Quince, Whoop, Made In, Plunge) take the sharper Shock hit via COGS/chip-supply, while staple/subscription names (Farmer's Dog, Thrive Market) are more defensive; Goat Group (discretionary resale demand + cross-border logistics) also skews Shock-worse-than-Bear, while Stripe (fee-based payments infra, not import-exposed) skews milder, in line with its tighter Bear/Shock spread on the Consumer Sleeve tab.
... A39: 5 | DRIVER x SLEEVE MAPPING (direction of impact)
A40: Driver | B40: IQT-mirror | C40: Weapons | D40: Consumer / Value
A41: NATO / EU rearmament | B41: + | C41: + + | D41: 0
A42: US budget / Replicator / munitions | B42: + | C42: + + | D42: 0
A43: Classified / black-budget growth (+14% IC) | B43: + + (IQT = CIA arm) | C43: + + | D43: 0
A44: China modernization / decoupling | B44: + + | C44: + | D44: -
A45: Taiwan / TSMC shock | B45: + + (convex) | C45: + + (conflict demand) | D45: - (inflation/spend)
A46: CHIPS / reshoring capital | B46: + + | C46: + | D46: 0
A47: Higher-for-longer rates | B47: - (long-duration) | C47: - / 0 | D47: -
A48: USD strength / inflation | B48: 0 / - | C48: 0 | D48: - -
A49: Consumer spending cycle | B49: 0 | C49: 0 | D49: + + (primary driver)
A51: 6 | KEY TAKEAWAY
A52: • The supercycle is already loudly priced in PUBLIC comps (ITA +29% 1yr, SOXX +170% 1yr) — so the edge is NOT the theme being undiscovered; it is capturing it at PRIVATE / VC-stage entry before the public re-rate. That is why the scoreboard is KS-PME vs the ITA/SOXX basket, not vs SPX.
A53: • The barbell's logic: Weapons + IQT are both long the geopolitical supercycle (opex + capex legs) and both convex to a Taiwan/TSMC shock; Consumer is the uncorrelated ballast that carries near-term DPI and is the one sleeve hurt by the shock. Net holdco is long the supercycle with a spending-cycle diversifier.
A54: • Biggest swing factors: (1) Weapons CAGR (largest sleeve), (2) the thematic-basket hurdle, (3) the rate path via IQT exit timing. All are levers on the Holdco Summary / Assumptions / PME tabs.
A56: Sources: iShares ITA & SOXX fact sheets (Jun-30-2026); multiples.vc (Rheinmetall/L3Harris, Sep-2026); Macrotrends (AVAV); Sacra (Saronic $9.25B, Anduril $61B); NATO/Atlantic Council (Hague 5% pledge, +20% EU 2025); uploaded BX Tac Opps black-budget compilation (Sep-2026): classified spend ~$170-215B, IC +14.2%, contractor classified-revenue estimates. China budget & Davidson window are widely-cited pre-cutoff figures — confirm current.

Sheet Assumptions
A1: ASSUMPTIONS & INPUTS
A2: Blue = hardcoded input / lever. TSMC-Shock CAGR (col I) is computed on the Defense Supercycle tab. All $M.
A4: FUND TERMS (IQT-mirror sleeve)
A5: Committed capital ($M) | B5: ='Holdco Summary'!$B$6 -> 250 | C5: IQT sleeve = 1 of 3 holdco sub-funds (see Holdco Summary)
A6: Initial deployment ($M) | B6: 225 | C6: Memo — reserve embedded in retention
A7: Follow-on reserve ($M) | B7: 25 | C7: Pro-rata defense on winners
A8: Mgmt fee (% of committed / yr) | B8: 0.02 | C8: Charged over full vehicle life
A9: Carried interest (%) | B9: 0.2 | C9: Over pref, no catch-up modeled
A10: Preferred return (% comp.) | B10: 0.08 | C10: 8% compounded hurdle
A11: Retention @ 5yr | B11: 0.85 | C11: Ownership kept after dilution
A12: Retention @ 7yr | B12: 0.78
A13: Retention @ 10yr | B13: 0.68
A16: PORTFOLIO — ENTRY MARKS, CHECKS & GROWTH ASSUMPTIONS
A17: Company | B17: Entry post-$M | C17: Check ($M) | D17: Own % | E17: Tranche | F17: Base CAGR | G17: Bull CAGR | H17: Bear CAGR | I17: TSMC-Shock | J17: Valuation basis
A18: Substrate (anchor) | B18: 1050 | C18: 80 | D18: =C18/B18 -> 0.076190476 | E18: Anchor / growth | F18: 0.22 | G18: 0.34 | H18: -0.18 | I18: ='Defense Supercycle'!I24 -> 0.408 | J18: Est. >$1.0B post (Oct-25 round)
A19: EUV Tech | B19: 180 | C19: 30 | D19: =C19/B19 -> 0.16666667 | E19: Growth core | F19: 0.14 | G19: 0.26 | H19: 0.03 | I19: ='Defense Supercycle'!I25 -> 0.304 | J19: Est. — undisclosed (rev-gen niche)
A20: ThinTronics | B20: 120 | C20: 22.5 | D20: =C20/B20 -> 0.1875 | E20: Growth core | F20: 0.26 | G20: 0.38 | H20: -0.1 | I20: ='Defense Supercycle'!I26 -> 0.416 | J20: Est. — undisclosed + $50M CHIPS LOI
A21: EdgeCortix | B21: 350 | C21: 30.5 | D21: =C21/B21 -> 0.087142857 | E21: Growth core | F21: 0.24 | G21: 0.36 | H21: -0.08 | I21: ='Defense Supercycle'!I27 -> 0.264 | J21: Est. — undisclosed (>$110M raised)
A22: Syntiant | B22: 700 | C22: 31.5 | D22: =C22/B22 -> 0.045 | E22: Pre-IPO / liquid | F22: 0.16 | G22: 0.28 | H22: -0.02 | I22: ='Defense Supercycle'!I28 -> 0.22 | J22: $646M Dec-24; S-1 filed (SYTN)
A23: Infleqtion | B23: 3000 | C23: 25 | D23: =C23/B23 -> 0.0083333333 | E23: Public / liquid | F23: 0.15 | G23: 0.27 | H23: -0.1 | I23: ='Defense Supercycle'!I29 -> 0.222 | J23: Public NYSE:INFQ (~$3.0B mkt cap)
A24: Diraq | B24: 150 | C24: 14 | D24: =C24/B24 -> 0.093333333 | E24: Quantum venture | F24: 0.3 | G24: 0.42 | H24: -0.22 | I24: ='Defense Supercycle'!I30 -> 0.384 | J24: Never disclosed (unverified ~$107M)
A25: Mueon | B25: 65 | C25: 10 | D25: =C25/B25 -> 0.15384615 | E25: Seed optionality | F25: 0.32 | G25: 0.44 | H25: -0.28 | I25: ='Defense Supercycle'!I31 -> 0.396 | J25: Est. — undisclosed ($15.5M seed)
A26: DefendEye | B26: 50 | C26: 6.5 | D26: =C26/B26 -> 0.13 | E26: Seed optionality | F26: 0.28 | G26: 0.4 | H26: -0.25 | I26: ='Defense Supercycle'!I32 -> 0.216 | J26: Est. — undisclosed seed
A27: TOTAL DEPLOYED | C27: =SUM(C18:C26) -> 250
A28: ="Check: deployed capital (C27) "&TEXT(C27,"$#,##0")&"M vs committed (B5) "&TEXT(B5,"$#,##0")&"M — "&IF(ABS(C27-B5)<0.5,"OK","MISMATCH") -> Check: deployed capital (C27) $250M vs committed (B5) $250M — OK

Sheet Defense Supercycle
A1: DEFENSE SUPERCYCLE — STRATEGIC SCORING & SHOCK ENGINE
A2: Winning the US-China AI/semiconductor race + insulating against a Taiwan / loss-of-TSMC scenario. Blue = lever.
A4: STRATEGIC AXIS WEIGHTS (must sum to 100%)
A5: China AI/semi-race criticality | B5: 0.25 | C5: Advances US lead in AI compute / advanced nodes
A6: Taiwan / TSMC-insulation value | B6: 0.3 | C6: Reduces US dependence on Taiwan-based fabrication
A7: Government / defense embeddedness | B7: 0.15 | C7: IQT + DoD/DIU/DARPA/CHIPS pull
A8: CFIUS-clean / US-sovereign | B8: 0.15 | C8: US domicile & ownership; acquirable by US gov/primes
A9: Supply-chain chokepoint leverage | B9: 0.15 | C9: Sole/near-sole source at a critical node
A10: Sum (check = 100%) | B10: =SUM(B5:B9) -> 1
A12: TSMC-SHOCK CALIBRATION
A13: Pivot score (neutral) | B13: 2.5 | C13: Composite above pivot -> positive re-rating; below -> drag
A14: Premium per point (CAGR) | B14: 0.08 | C14: CAGR uplift per composite point above pivot, added to Base CAGR
A16: SCENARIO PROBABILITY WEIGHTS (must sum to 100%)
A17: Base | B17: 0.45
A18: Bull | B18: 0.25
A19: Bear | B19: 0.15
A20: TSMC-Shock | B20: 0.15
A21: Sum (check = 100%) | B21: =SUM(B17:B20) -> 1
A22: STRATEGIC SCORING MATRIX (1 = low, 5 = high; blue = lever)
A23: Company | B23: China Race | C23: TSMC Insul. | D23: Gov/Defense | E23: CFIUS-Clean | F23: Chokepoint | G23: Composite | H23: Shock prem. | I23: Shock CAGR
A24: Substrate (anchor) | B24: 5 | C24: 5 | D24: 4 | E24: 5 | F24: 5 | G24: =B24*'Defense Supercycle'!$B$5+C24*'Defense Supercycle'!$B$6+D24*'Defense Supercycle'!$B$7+E24*'Defense Supercycle'!$B$8+F24*'Defense Supercycle'!$B$9 -> 4.85 | H24: =(G24-'Defense Supercycle'!$B$13)*'Defense Supercycle'!$B$14 -> 0.188 | I24: =Assumptions!F18+H24 -> 0.408
A25: EUV Tech | B25: 5 | C25: 4 | D25: 4 | E25: 5 | F25: 5 | G25: =B25*'Defense Supercycle'!$B$5+C25*'Defense Supercycle'!$B$6+D25*'Defense Supercycle'!$B$7+E25*'Defense Supercycle'!$B$8+F25*'Defense Supercycle'!$B$9 -> 4.55 | H25: =(G25-'Defense Supercycle'!$B$13)*'Defense Supercycle'!$B$14 -> 0.164 | I25: =Assumptions!F19+H25 -> 0.304
A26: ThinTronics | B26: 4 | C26: 5 | D26: 4 | E26: 5 | F26: 4 | G26: =B26*'Defense Supercycle'!$B$5+C26*'Defense Supercycle'!$B$6+D26*'Defense Supercycle'!$B$7+E26*'Defense Supercycle'!$B$8+F26*'Defense Supercycle'!$B$9 -> 4.45 | H26: =(G26-'Defense Supercycle'!$B$13)*'Defense Supercycle'!$B$14 -> 0.156 | I26: =Assumptions!F20+H26 -> 0.416
A27: EdgeCortix | B27: 4 | C27: 2 | D27: 4 | E27: 2 | F27: 2 | G27: =B27*'Defense Supercycle'!$B$5+C27*'Defense Supercycle'!$B$6+D27*'Defense Supercycle'!$B$7+E27*'Defense Supercycle'!$B$8+F27*'Defense Supercycle'!$B$9 -> 2.8 | H27: =(G27-'Defense Supercycle'!$B$13)*'Defense Supercycle'!$B$14 -> 0.024 | I27: =Assumptions!F21+H27 -> 0.264
A28: Syntiant | B28: 4 | C28: 2 | D28: 4 | E28: 5 | F28: 2 | G28: =B28*'Defense Supercycle'!$B$5+C28*'Defense Supercycle'!$B$6+D28*'Defense Supercycle'!$B$7+E28*'Defense Supercycle'!$B$8+F28*'Defense Supercycle'!$B$9 -> 3.25 | H28: =(G28-'Defense Supercycle'!$B$13)*'Defense Supercycle'!$B$14 -> 0.06 | I28: =Assumptions!F22+H28 -> 0.22
A29: Infleqtion | B29: 4 | C29: 2 | D29: 4 | E29: 5 | F29: 3 | G29: =B29*'Defense Supercycle'!$B$5+C29*'Defense Supercycle'!$B$6+D29*'Defense Supercycle'!$B$7+E29*'Defense Supercycle'!$B$8+F29*'Defense Supercycle'!$B$9 -> 3.4 | H29: =(G29-'Defense Supercycle'!$B$13)*'Defense Supercycle'!$B$14 -> 0.072 | I29: =Assumptions!F23+H29 -> 0.222
A30: Diraq | B30: 4 | C30: 4 | D30: 4 | E30: 2 | F30: 3 | G30: =B30*'Defense Supercycle'!$B$5+C30*'Defense Supercycle'!$B$6+D30*'Defense Supercycle'!$B$7+E30*'Defense Supercycle'!$B$8+F30*'Defense Supercycle'!$B$9 -> 3.55 | H30: =(G30-'Defense Supercycle'!$B$13)*'Defense Supercycle'!$B$14 -> 0.084 | I30: =Assumptions!F24+H30 -> 0.384
A31: Mueon | B31: 3 | C31: 3 | D31: 4 | E31: 5 | F31: 3 | G31: =B31*'Defense Supercycle'!$B$5+C31*'Defense Supercycle'!$B$6+D31*'Defense Supercycle'!$B$7+E31*'Defense Supercycle'!$B$8+F31*'Defense Supercycle'!$B$9 -> 3.45 | H31: =(G31-'Defense Supercycle'!$B$13)*'Defense Supercycle'!$B$14 -> 0.076 | I31: =Assumptions!F25+H31 -> 0.396
A32: DefendEye | B32: 2 | C32: 1 | D32: 3 | E32: 2 | F32: 1 | G32: =B32*'Defense Supercycle'!$B$5+C32*'Defense Supercycle'!$B$6+D32*'Defense Supercycle'!$B$7+E32*'Defense Supercycle'!$B$8+F32*'Defense Supercycle'!$B$9 -> 1.7 | H32: =(G32-'Defense Supercycle'!$B$13)*'Defense Supercycle'!$B$14 -> -0.064 | I32: =Assumptions!F26+H32 -> 0.216
A33: Avg / weighted | G33: =AVERAGE(G24:G32) -> 3.5555556
A35: SCENARIO NARRATIVE — TSMC SHOCK / TAIWAN CONTINGENCY
A36: • Trigger: a Taiwan blockade/quarantine, kinetic event, or hard US-China tech decoupling that removes or severely constrains access to TSMC's leading-edge capacity — the single point of failure in the AI-compute supply chain.
A37: • Winners (large re-rate): the US sovereign-chokepoint names. Substrate (domestic X-ray litho / fabs), EUV Tech (at-wavelength EUV metrology — no fab qualifies without it), ThinTronics (US ABF/substrate materials vs Japan's Ajinomoto monopoly). Onshoring becomes a national-security imperative; demand + pricing power inflect.
A38: • Partial winners: Mueon (US advanced packaging / rack density), Infleqtion & Diraq (quantum race convexity — the 'next' compute paradigm if classical leading-edge is contested), Syntiant (US-fab-flexible edge inference).
A39: • Laggards / drag: EdgeCortix (Japan HQ + TSMC-Kumamoto fab exposure, near-term supply hit and CFIUS ceiling) and DefendEye (foreign-nexus, low semiconductor-sovereignty relevance).
A40: • Portfolio design implication: the book is intentionally overweight the sovereign core, so a tail event that would hurt a generic tech portfolio is where this one is most convex. That asymmetry is the thesis.
A42: IQT WARTIME-FUNCTION MAP — SUBSTRATE-ANCHORED SLEEVE (from uploaded IQT strategic analysis)
A43: Strategic cluster | B43: Holdings | D43: Wartime function / why IQT funds it
A44: TSMC-alternative: packaging & substrates | B44: Substrate, ThinTronics, EUV Tech | D44: Build & package chips domestically if Taiwan is blockaded — X-ray litho (Substrate), CoWoS-alternative insulators for advanced packaging (ThinTronics, + $50M CHIPS LOI Jul-26), at-wavelength EUV metrology to keep domestic litho running (EUV Tech).
A45: Denied-environment edge AI | B45: Syntiant, EdgeCortix | D45: Onboard AI for autonomous weapons when GPS / cloud / comms are jammed by PLA electronic warfare — ultra-low-power SWaP-constrained inference on drones, missiles, naval sensors. Syntiant signed a Nov-2025 IQT strategic technology-development agreement; EdgeCortix's DNA accelerator targets defense/aerospace at the tactical edge.
A46: Post-Moore's next-gen compute | B46: Diraq, Mueon (+ Infleqtion) | D46: Bootstrap quantum on existing CMOS foundries (Diraq silicon spin qubits — no exotic materials) and ultra-dense secure domestic AI data-center compute (Mueon) — a hedge if China wins the legacy-silicon volume war.
A47: Strategic takeaway: IQT is using venture capital to construct a parallel, domestic 'fail-safe' tech stack so the US can build, package and deploy AI-driven weapons entirely from domestic supply chains through a 2026/27 Taiwan contingency. Mirroring the Substrate-anchored sleeve = owning that fail-safe at VC-stage entry. The scores above are lifted for the edge-AI and next-gen-compute names to reflect this direct, documented defense pull.

Sheet Allocation
A1: ALLOCATION & POSITION STRUCTURE
A2: Green = linked. Composite pulled from Defense Supercycle tab. Ownership >15% = significant minority (seek board seat / observer).
A4: Company | B4: Check ($M) | C4: Own % | D4: % Fund | E4: Supercycle | F4: Tranche | G4: Domicile | H4: Structuring / diligence flag
A5: =Assumptions!A18 -> Substrate (anchor) | B5: =Assumptions!C18 -> 80 | C5: =Assumptions!D18 -> 0.076190476 | D5: =Assumptions!C18/Assumptions!$B$5 -> 0.32 | E5: ='Defense Supercycle'!G24 -> 4.85 | F5: =Assumptions!E18 -> Anchor / growth | G5: USA (SF, CA) | H5: Anchor. Binary tech risk — capped ~32% of fund; the core sovereign-litho bet.
A6: =Assumptions!A19 -> EUV Tech | B6: =Assumptions!C19 -> 30 | C6: =Assumptions!D19 -> 0.16666667 | D6: =Assumptions!C19/Assumptions!$B$5 -> 0.12 | E6: ='Defense Supercycle'!G25 -> 4.55 | F6: =Assumptions!E19 -> Growth core | G6: USA (CA) | H6: Rev-generating niche leader — best risk-adjusted. ~17% stake = significant minority; seek a board seat.
A7: =Assumptions!A20 -> ThinTronics | B7: =Assumptions!C20 -> 22.5 | C7: =Assumptions!D20 -> 0.1875 | D7: =Assumptions!C20/Assumptions!$B$5 -> 0.09 | E7: ='Defense Supercycle'!G26 -> 4.45 | F7: =Assumptions!E20 -> Growth core | G7: USA (CA) | H7: CHIPS $50M LOI catalyst. ~19% stake = significant minority; likely primary + secondary blend.
A8: =Assumptions!A21 -> EdgeCortix | B8: =Assumptions!C21 -> 30.5 | C8: =Assumptions!D21 -> 0.087142857 | D8: =Assumptions!C21/Assumptions!$B$5 -> 0.122 | E8: ='Defense Supercycle'!G27 -> 2.8 | F8: =Assumptions!E21 -> Growth core | G8: JAPAN (Tokyo) | H8: CFIUS/allied flag — minority only. Renesas natural acquirer. TSMC-Kumamoto fab exposure.
A9: =Assumptions!A22 -> Syntiant | B9: =Assumptions!C22 -> 31.5 | C9: =Assumptions!D22 -> 0.045 | D9: =Assumptions!C22/Assumptions!$B$5 -> 0.126 | E9: ='Defense Supercycle'!G28 -> 3.25 | F9: =Assumptions!E22 -> Pre-IPO / liquid | G9: USA (CA) | H9: Pre-IPO secondary or SYTN cornerstone. Watch pricing vs $646M Dec-24 mark.
A10: =Assumptions!A23 -> Infleqtion | B10: =Assumptions!C23 -> 25 | C10: =Assumptions!D23 -> 0.0083333333 | D10: =Assumptions!C23/Assumptions!$B$5 -> 0.1 | E10: ='Defense Supercycle'!G29 -> 3.4 | F10: =Assumptions!E23 -> Public / liquid | G10: USA (CO) | H10: Public (INFQ). PIPE/secondary. Listed quantum benchmark for Diraq.
A11: =Assumptions!A24 -> Diraq | B11: =Assumptions!C24 -> 14 | C11: =Assumptions!D24 -> 0.093333333 | D11: =Assumptions!C24/Assumptions!$B$5 -> 0.056 | E11: ='Defense Supercycle'!G30 -> 3.55 | F11: =Assumptions!E24 -> Quantum venture | G11: AUSTRALIA (Sydney) | H11: Allied flag — minority. NRFC sovereignty covenants. AUKUS-aligned quantum optionality.
A12: =Assumptions!A25 -> Mueon | B12: =Assumptions!C25 -> 10 | C12: =Assumptions!D25 -> 0.15384615 | D12: =Assumptions!C25/Assumptions!$B$5 -> 0.04 | E12: ='Defense Supercycle'!G31 -> 3.45 | F12: =Assumptions!E25 -> Seed optionality | G12: USA (OR) | H12: Seed. Milestone-gated. Needs a shipping Cubelet design-win to scale exposure.
A13: =Assumptions!A26 -> DefendEye | B13: =Assumptions!C26 -> 6.5 | C13: =Assumptions!D26 -> 0.13 | D13: =Assumptions!C26/Assumptions!$B$5 -> 0.026 | E13: ='Defense Supercycle'!G32 -> 1.7 | F13: =Assumptions!E26 -> Seed optionality | G13: USA (FL)+POLAND | H13: EU cap table + Krakow mfg — Blue UAS/NDAA provenance diligence before US-defense thesis.
A14: TOTAL | B14: =SUM(B5:B13) -> 250 | D14: =SUM(D5:D13) -> 1

Sheet Portfolio Returns
A1: PORTFOLIO RETURNS BY HOLD & SCENARIO
A2: Proceeds = Check x (1+CAGR)^Hold x Retention. MOIC = Proceeds/Check. Gross IRR = MOIC^(1/Hold)-1.
A4: 5-YEAR HOLD VEHICLE
A5: Company | B5: Check ($M) | C5: Base $ | D5: Base MOIC | E5: Base IRR | F5: Bull $ | G5: Bull MOIC | H5: Bull IRR | I5: Bear $ | J5: Bear MOIC | K5: Bear IRR | L5: Shock $ | M5: Shock MOIC | N5: Shock IRR
A6: =Assumptions!A18 -> Substrate (anchor) | B6: =Assumptions!C18 -> 80 | C6: =Assumptions!C18*(1+Assumptions!F18)^5*Assumptions!$B$11 -> 183.78416 | D6: =C6/B6 -> 2.2973019 | E6: =(C6/B6)^(1/5)-1 -> 0.18098292 | F6: =Assumptions!C18*(1+Assumptions!G18)^5*Assumptions!$B$11 -> 293.78722 | G6: =F6/B6 -> 3.6723403 | H6: =(F6/B6)^(1/5)-1 -> 0.29714517 | I6: =Assumptions!C18*(1+Assumptions!H18)^5*Assumptions!$B$11 -> 25.210309 | J6: =I6/B6 -> 0.31512887 | K6: =(I6/B6)^(1/5)-1 -> -0.2062246 | L6: =Assumptions!C18*(1+Assumptions!I18)^5*Assumptions!$B$11 -> 376.28958 | M6: =L6/B6 -> 4.7036197 | N6: =(L6/B6)^(1/5)-1 -> 0.36297045
A7: =Assumptions!A19 -> EUV Tech | B7: =Assumptions!C19 -> 30 | C7: =Assumptions!C19*(1+Assumptions!F19)^5*Assumptions!$B$11 -> 49.098072 | D7: =C7/B7 -> 1.6366024 | E7: =(C7/B7)^(1/5)-1 -> 0.10354141 | F7: =Assumptions!C19*(1+Assumptions!G19)^5*Assumptions!$B$11 -> 80.982822 | G7: =F7/B7 -> 2.6994274 | H7: =(F7/B7)^(1/5)-1 -> 0.21970367 | I7: =Assumptions!C19*(1+Assumptions!H19)^5*Assumptions!$B$11 -> 29.561489 | J7: =I7/B7 -> 0.98538296 | K7: =(I7/B7)^(1/5)-1 -> -0.0029406514 | L7: =Assumptions!C19*(1+Assumptions!I19)^5*Assumptions!$B$11 -> 96.145317 | M7: =L7/B7 -> 3.2048439 | N7: =(L7/B7)^(1/5)-1 -> 0.2622965
A8: =Assumptions!A20 -> ThinTronics | B8: =Assumptions!C20 -> 22.5 | C8: =Assumptions!C20*(1+Assumptions!F20)^5*Assumptions!$B$11 -> 60.737116 | D8: =C8/B8 -> 2.6994274 | E8: =(C8/B8)^(1/5)-1 -> 0.21970367 | F8: =Assumptions!C20*(1+Assumptions!G20)^5*Assumptions!$B$11 -> 95.718719 | G8: =F8/B8 -> 4.2541653 | H8: =(F8/B8)^(1/5)-1 -> 0.33586592 | I8: =Assumptions!C20*(1+Assumptions!H20)^5*Assumptions!$B$11 -> 11.293121 | J8: =I8/B8 -> 0.5019165 | K8: =(I8/B8)^(1/5)-1 -> -0.12878309 | L8: =Assumptions!C20*(1+Assumptions!I20)^5*Assumptions!$B$11 -> 108.87238 | M8: =L8/B8 -> 4.8387724 | N8: =(L8/B8)^(1/5)-1 -> 0.3707146
A9: =Assumptions!A21 -> EdgeCortix | B9: =Assumptions!C21 -> 30.5 | C9: =Assumptions!C21*(1+Assumptions!F21)^5*Assumptions!$B$11 -> 76.00238 | D9: =C9/B9 -> 2.4918813 | E9: =(C9/B9)^(1/5)-1 -> 0.20034329 | F9: =Assumptions!C21*(1+Assumptions!G21)^5*Assumptions!$B$11 -> 120.61833 | G9: =F9/B9 -> 3.9546993 | H9: =(F9/B9)^(1/5)-1 -> 0.31650555 | I9: =Assumptions!C21*(1+Assumptions!H21)^5*Assumptions!$B$11 -> 17.086688 | J9: =I9/B9 -> 0.56021929 | K9: =(I9/B9)^(1/5)-1 -> -0.10942272 | L9: =Assumptions!C21*(1+Assumptions!I21)^5*Assumptions!$B$11 -> 83.647725 | M9: =L9/B9 -> 2.7425484 | N9: =(L9/B9)^(1/5)-1 -> 0.22357574
A10: =Assumptions!A22 -> Syntiant | B10: =Assumptions!C22 -> 31.5 | C10: =Assumptions!C22*(1+Assumptions!F22)^5*Assumptions!$B$11 -> 56.236648 | D10: =C10/B10 -> 1.7852904 | E10: =(C10/B10)^(1/5)-1 -> 0.12290179 | F10: =Assumptions!C22*(1+Assumptions!G22)^5*Assumptions!$B$11 -> 91.998199 | G10: =F10/B10 -> 2.9205778 | H10: =(F10/B10)^(1/5)-1 -> 0.23906404 | I10: =Assumptions!C22*(1+Assumptions!H22)^5*Assumptions!$B$11 -> 24.202479 | J10: =I10/B10 -> 0.76833268 | K10: =(I10/B10)^(1/5)-1 -> -0.051341591 | L10: =Assumptions!C22*(1+Assumptions!I22)^5*Assumptions!$B$11 -> 72.365011 | M10: =L10/B10 -> 2.2973019 | N10: =(L10/B10)^(1/5)-1 -> 0.18098292
A11: =Assumptions!A23 -> Infleqtion | B11: =Assumptions!C23 -> 25 | C11: =Assumptions!C23*(1+Assumptions!F23)^5*Assumptions!$B$11 -> 42.74134 | D11: =C11/B11 -> 1.7096536 | E11: =(C11/B11)^(1/5)-1 -> 0.1132216 | F11: =Assumptions!C23*(1+Assumptions!G23)^5*Assumptions!$B$11 -> 70.206535 | G11: =F11/B11 -> 2.8082614 | H11: =(F11/B11)^(1/5)-1 -> 0.22938386 | I11: =Assumptions!C23*(1+Assumptions!H23)^5*Assumptions!$B$11 -> 12.547913 | J11: =I11/B11 -> 0.5019165 | K11: =(I11/B11)^(1/5)-1 -> -0.12878309 | L11: =Assumptions!C23*(1+Assumptions!I23)^5*Assumptions!$B$11 -> 57.904853 | M11: =L11/B11 -> 2.3161941 | N11: =(L11/B11)^(1/5)-1 -> 0.18291896
A12: =Assumptions!A24 -> Diraq | B12: =Assumptions!C24 -> 14 | C12: =Assumptions!C24*(1+Assumptions!F24)^5*Assumptions!$B$11 -> 44.183867 | D12: =C12/B12 -> 3.1559905 | E12: =(C12/B12)^(1/5)-1 -> 0.25842442 | F12: =Assumptions!C24*(1+Assumptions!G24)^5*Assumptions!$B$11 -> 68.705054 | G12: =F12/B12 -> 4.9075038 | H12: =(F12/B12)^(1/5)-1 -> 0.37458667 | I12: =Assumptions!C24*(1+Assumptions!H24)^5*Assumptions!$B$11 -> 3.4357375 | J12: =I12/B12 -> 0.24540982 | K12: =(I12/B12)^(1/5)-1 -> -0.24494535 | L12: =Assumptions!C24*(1+Assumptions!I24)^5*Assumptions!$B$11 -> 60.426496 | M12: =L12/B12 -> 4.3161783 | N12: =(L12/B12)^(1/5)-1 -> 0.339738
A13: =Assumptions!A25 -> Mueon | B13: =Assumptions!C25 -> 10 | C13: =Assumptions!C25*(1+Assumptions!F25)^5*Assumptions!$B$11 -> 34.063446 | D13: =C13/B13 -> 3.4063446 | E13: =(C13/B13)^(1/5)-1 -> 0.2777848 | F13: =Assumptions!C25*(1+Assumptions!G25)^5*Assumptions!$B$11 -> 52.62976 | G13: =F13/B13 -> 5.262976 | H13: =(F13/B13)^(1/5)-1 -> 0.39394705 | I13: =Assumptions!C25*(1+Assumptions!H25)^5*Assumptions!$B$11 -> 1.64468 | J13: =I13/B13 -> 0.164468 | K13: =(I13/B13)^(1/5)-1 -> -0.30302647 | L13: =Assumptions!C25*(1+Assumptions!I25)^5*Assumptions!$B$11 -> 45.065689 | M13: =L13/B13 -> 4.5065689 | N13: =(L13/B13)^(1/5)-1 -> 0.35135422
A14: =Assumptions!A26 -> DefendEye | B14: =Assumptions!C26 -> 6.5 | C14: =Assumptions!C26*(1+Assumptions!F26)^5*Assumptions!$B$11 -> 18.983755 | D14: =C14/B14 -> 2.9205778 | E14: =(C14/B14)^(1/5)-1 -> 0.23906404 | F14: =Assumptions!C26*(1+Assumptions!G26)^5*Assumptions!$B$11 -> 29.714776 | G14: =F14/B14 -> 4.571504 | H14: =(F14/B14)^(1/5)-1 -> 0.3552263 | I14: =Assumptions!C26*(1+Assumptions!H26)^5*Assumptions!$B$11 -> 1.3111084 | J14: =I14/B14 -> 0.20170898 | K14: =(I14/B14)^(1/5)-1 -> -0.27398591 | L14: =Assumptions!C26*(1+Assumptions!I26)^5*Assumptions!$B$11 -> 14.689268 | M14: =L14/B14 -> 2.2598874 | N14: =(L14/B14)^(1/5)-1 -> 0.17711084
A15: FUND TOTAL | B15: =SUM(B6:B14) -> 250 | C15: =SUM(C6:C14) -> 565.83078 | D15: =C15/B15 -> 2.2633231 | E15: =(C15/B15)^(1/5)-1 -> 0.17746854 | F15: =SUM(F6:F14) -> 904.36142 | G15: =F15/B15 -> 3.6174457 | H15: =(F15/B15)^(1/5)-1 -> 0.29324379 | I15: =SUM(I6:I14) -> 126.29353 | J15: =I15/B15 -> 0.5051741 | K15: =(I15/B15)^(1/5)-1 -> -0.12765512 | L15: =SUM(L6:L14) -> 915.40631 | M15: =L15/B15 -> 3.6616253 | N15: =(L15/B15)^(1/5)-1 -> 0.29638733
A18: 7-YEAR HOLD VEHICLE
A19: Company | B19: Check ($M) | C19: Base $ | D19: Base MOIC | E19: Base IRR | F19: Bull $ | G19: Bull MOIC | H19: Bull IRR | I19: Bear $ | J19: Bear MOIC | K19: Bear IRR | L19: Shock $ | M19: Shock MOIC | N19: Shock IRR
A20: =Assumptions!A18 -> Substrate (anchor) | B20: =Assumptions!C18 -> 80 | C20: =Assumptions!C18*(1+Assumptions!F18)^7*Assumptions!$B$12 -> 251.01716 | D20: =C20/B20 -> 3.1377144 | E20: =(C20/B20)^(1/7)-1 -> 0.17745624 | F20: =Assumptions!C18*(1+Assumptions!G18)^7*Assumptions!$B$12 -> 484.08116 | G20: =F20/B20 -> 6.0510145 | H20: =(F20/B20)^(1/7)-1 -> 0.2932716 | I20: =Assumptions!C18*(1+Assumptions!H18)^7*Assumptions!$B$12 -> 15.555413 | J20: =I20/B20 -> 0.19444267 | K20: =(I20/B20)^(1/7)-1 -> -0.20859499 | L20: =Assumptions!C18*(1+Assumptions!I18)^7*Assumptions!$B$12 -> 684.54685 | M20: =L20/B20 -> 8.5568356 | N20: =(L20/B20)^(1/7)-1 -> 0.35890031
A21: =Assumptions!A19 -> EUV Tech | B21: =Assumptions!C19 -> 30 | C21: =Assumptions!C19*(1+Assumptions!F19)^7*Assumptions!$B$12 -> 58.55309 | D21: =C21/B21 -> 1.9517697 | E21: =(C21/B21)^(1/7)-1 -> 0.10024599 | F21: =Assumptions!C19*(1+Assumptions!G19)^7*Assumptions!$B$12 -> 117.98035 | G21: =F21/B21 -> 3.9326783 | H21: =(F21/B21)^(1/7)-1 -> 0.21606136 | I21: =Assumptions!C19*(1+Assumptions!H19)^7*Assumptions!$B$12 -> 28.779048 | J21: =I21/B21 -> 0.95930162 | K21: =(I21/B21)^(1/7)-1 -> -0.0059180963 | L21: =Assumptions!C19*(1+Assumptions!I19)^7*Assumptions!$B$12 -> 150.0234 | M21: =L21/B21 -> 5.0007799 | N21: =(L21/B21)^(1/7)-1 -> 0.25852699
A22: =Assumptions!A20 -> ThinTronics | B22: =Assumptions!C20 -> 22.5 | C22: =Assumptions!C20*(1+Assumptions!F20)^7*Assumptions!$B$12 -> 88.485261 | D22: =C22/B22 -> 3.9326783 | E22: =(C22/B22)^(1/7)-1 -> 0.21606136 | F22: =Assumptions!C20*(1+Assumptions!G20)^7*Assumptions!$B$12 -> 167.27488 | G22: =F22/B22 -> 7.4344391 | H22: =(F22/B22)^(1/7)-1 -> 0.33187673 | I22: =Assumptions!C20*(1+Assumptions!H20)^7*Assumptions!$B$12 -> 8.3941106 | J22: =I22/B22 -> 0.37307158 | K22: =(I22/B22)^(1/7)-1 -> -0.13138474 | L22: =Assumptions!C20*(1+Assumptions!I20)^7*Assumptions!$B$12 -> 200.31796 | M22: =L22/B22 -> 8.9030206 | N22: =(L22/B22)^(1/7)-1 -> 0.36662134
A23: =Assumptions!A21 -> EdgeCortix | B23: =Assumptions!C21 -> 30.5 | C23: =Assumptions!C21*(1+Assumptions!F21)^7*Assumptions!$B$12 -> 107.23739 | D23: =C23/B23 -> 3.51598 | E23: =(C23/B23)^(1/7)-1 -> 0.1967588 | F23: =Assumptions!C21*(1+Assumptions!G21)^7*Assumptions!$B$12 -> 204.72308 | G23: =F23/B23 -> 6.712232 | H23: =(F23/B23)^(1/7)-1 -> 0.31257416 | I23: =Assumptions!C21*(1+Assumptions!H21)^7*Assumptions!$B$12 -> 13.271171 | J23: =I23/B23 -> 0.43512035 | K23: =(I23/B23)^(1/7)-1 -> -0.11208218 | L23: =Assumptions!C21*(1+Assumptions!I21)^7*Assumptions!$B$12 -> 122.63769 | M23: =L23/B23 -> 4.0209079 | N23: =(L23/B23)^(1/7)-1 -> 0.21992187
A24: =Assumptions!A22 -> Syntiant | B24: =Assumptions!C22 -> 31.5 | C24: =Assumptions!C22*(1+Assumptions!F22)^7*Assumptions!$B$12 -> 69.440219 | D24: =C24/B24 -> 2.2044514 | E24: =(C24/B24)^(1/7)-1 -> 0.11954855 | F24: =Assumptions!C22*(1+Assumptions!G22)^7*Assumptions!$B$12 -> 138.3168 | G24: =F24/B24 -> 4.3910096 | H24: =(F24/B24)^(1/7)-1 -> 0.23536392 | I24: =Assumptions!C22*(1+Assumptions!H22)^7*Assumptions!$B$12 -> 21.329844 | J24: =I24/B24 -> 0.67713792 | K24: =(I24/B24)^(1/7)-1 -> -0.054174499 | L24: =Assumptions!C22*(1+Assumptions!I22)^7*Assumptions!$B$12 -> 98.838005 | M24: =L24/B24 -> 3.1377144 | N24: =(L24/B24)^(1/7)-1 -> 0.17745624
A25: =Assumptions!A23 -> Infleqtion | B25: =Assumptions!C23 -> 25 | C25: =Assumptions!C23*(1+Assumptions!F23)^7*Assumptions!$B$12 -> 51.870388 | D25: =C25/B25 -> 2.0748155 | E25: =(C25/B25)^(1/7)-1 -> 0.10989727 | F25: =Assumptions!C23*(1+Assumptions!G23)^7*Assumptions!$B$12 -> 103.91079 | G25: =F25/B25 -> 4.1564317 | H25: =(F25/B25)^(1/7)-1 -> 0.22571264 | I25: =Assumptions!C23*(1+Assumptions!H23)^7*Assumptions!$B$12 -> 9.3267896 | J25: =I25/B25 -> 0.37307158 | K25: =(I25/B25)^(1/7)-1 -> -0.13138474 | L25: =Assumptions!C23*(1+Assumptions!I23)^7*Assumptions!$B$12 -> 79.347464 | M25: =L25/B25 -> 3.1738986 | N25: =(L25/B25)^(1/7)-1 -> 0.17938649
A26: =Assumptions!A24 -> Diraq | B26: =Assumptions!C24 -> 14 | C26: =Assumptions!C24*(1+Assumptions!F24)^7*Assumptions!$B$12 -> 68.521381 | D26: =C26/B26 -> 4.8943843 | E26: =(C26/B26)^(1/7)-1 -> 0.25466648 | F26: =Assumptions!C24*(1+Assumptions!G24)^7*Assumptions!$B$12 -> 127.12795 | G26: =F26/B26 -> 9.080568 | H26: =(F26/B26)^(1/7)-1 -> 0.37048185 | I26: =Assumptions!C24*(1+Assumptions!H24)^7*Assumptions!$B$12 -> 1.9181601 | J26: =I26/B26 -> 0.13701144 | K26: =(I26/B26)^(1/7)-1 -> -0.24720011 | L26: =Assumptions!C24*(1+Assumptions!I24)^7*Assumptions!$B$12 -> 106.21241 | M26: =L26/B26 -> 7.5866008 | N26: =(L26/B26)^(1/7)-1 -> 0.33573724
A27: =Assumptions!A25 -> Mueon | B27: =Assumptions!C25 -> 10 | C27: =Assumptions!C25*(1+Assumptions!F25)^7*Assumptions!$B$12 -> 54.464324 | D27: =C27/B27 -> 5.4464324 | E27: =(C27/B27)^(1/7)-1 -> 0.27396904 | F27: =Assumptions!C25*(1+Assumptions!G25)^7*Assumptions!$B$12 -> 100.14564 | G27: =F27/B27 -> 10.014564 | H27: =(F27/B27)^(1/7)-1 -> 0.38978441 | I27: =Assumptions!C25*(1+Assumptions!H25)^7*Assumptions!$B$12 -> 0.78238781 | J27: =I27/B27 -> 0.078238781 | K27: =(I27/B27)^(1/7)-1 -> -0.3051078 | L27: =Assumptions!C25*(1+Assumptions!I25)^7*Assumptions!$B$12 -> 80.592111 | M27: =L27/B27 -> 8.0592111 | N27: =(L27/B27)^(1/7)-1 -> 0.34731877
A28: =Assumptions!A26 -> DefendEye | B28: =Assumptions!C26 -> 6.5 | C28: =Assumptions!C26*(1+Assumptions!F26)^7*Assumptions!$B$12 -> 28.541563 | D28: =C28/B28 -> 4.3910096 | E28: =(C28/B28)^(1/7)-1 -> 0.23536392 | F28: =Assumptions!C26*(1+Assumptions!G26)^7*Assumptions!$B$12 -> 53.444647 | G28: =F28/B28 -> 8.2222533 | H28: =(F28/B28)^(1/7)-1 -> 0.35117929 | I28: =Assumptions!C26*(1+Assumptions!H26)^7*Assumptions!$B$12 -> 0.67676331 | J28: =I28/B28 -> 0.10411743 | K28: =(I28/B28)^(1/7)-1 -> -0.27615395 | L28: =Assumptions!C26*(1+Assumptions!I26)^7*Assumptions!$B$12 -> 19.931638 | M28: =L28/B28 -> 3.0664058 | N28: =(L28/B28)^(1/7)-1 -> 0.17359572
A29: FUND TOTAL | B29: =SUM(B20:B28) -> 250 | C29: =SUM(C20:C28) -> 778.13077 | D29: =C29/B29 -> 3.1125231 | E29: =(C29/B29)^(1/7)-1 -> 0.1761011 | F29: =SUM(F20:F28) -> 1497.0053 | G29: =F29/B29 -> 5.9880212 | H29: =(F29/B29)^(1/7)-1 -> 0.29133962 | I29: =SUM(I20:I28) -> 100.03369 | J29: =I29/B29 -> 0.40013475 | K29: =(I29/B29)^(1/7)-1 -> -0.12265112 | L29: =SUM(L20:L28) -> 1542.4475 | M29: =L29/B29 -> 6.1697901 | N29: =(L29/B29)^(1/7)-1 -> 0.29686799
A32: 10-YEAR HOLD VEHICLE
A33: Company | B33: Check ($M) | C33: Base $ | D33: Base MOIC | E33: Base IRR | F33: Bull $ | G33: Bull MOIC | H33: Bull IRR | I33: Bear $ | J33: Bear MOIC | K33: Bear IRR | L33: Shock $ | M33: Shock MOIC | N33: Shock IRR
A34: =Assumptions!A18 -> Substrate (anchor) | B34: =Assumptions!C18 -> 80 | C34: =Assumptions!C18*(1+Assumptions!F18)^10*Assumptions!$B$13 -> 397.37195 | D34: =C34/B34 -> 4.9671494 | E34: =(C34/B34)^(1/10)-1 -> 0.17384491 | F34: =Assumptions!C18*(1+Assumptions!G18)^10*Assumptions!$B$13 -> 1015.4227 | G34: =F34/B34 -> 12.692784 | H34: =(F34/B34)^(1/10)-1 -> 0.28930507 | I34: =Assumptions!C18*(1+Assumptions!H18)^10*Assumptions!$B$13 -> 7.4771729 | J34: =I34/B34 -> 0.093464661 | K34: =(I34/B34)^(1/10)-1 -> -0.21102227 | L34: =Assumptions!C18*(1+Assumptions!I18)^10*Assumptions!$B$13 -> 1665.8099 | M34: =L34/B34 -> 20.822624 | N34: =(L34/B34)^(1/10)-1 -> 0.35473249
A35: =Assumptions!A19 -> EUV Tech | B35: =Assumptions!C19 -> 30 | C35: =Assumptions!C19*(1+Assumptions!F19)^10*Assumptions!$B$13 -> 75.627315 | D35: =C35/B35 -> 2.5209105 | E35: =(C35/B35)^(1/10)-1 -> 0.096871475 | F35: =Assumptions!C19*(1+Assumptions!G19)^10*Assumptions!$B$13 -> 205.748 | G35: =F35/B35 -> 6.8582666 | H35: =(F35/B35)^(1/10)-1 -> 0.21233163 | I35: =Assumptions!C19*(1+Assumptions!H19)^10*Assumptions!$B$13 -> 27.415894 | J35: =I35/B35 -> 0.91386314 | K35: =(I35/B35)^(1/10)-1 -> -0.0089670003 | L35: =Assumptions!C19*(1+Assumptions!I19)^10*Assumptions!$B$13 -> 290.0054 | M35: =L35/B35 -> 9.6668466 | N35: =(L35/B35)^(1/10)-1 -> 0.25466702
A36: =Assumptions!A20 -> ThinTronics | B36: =Assumptions!C20 -> 22.5 | C36: =Assumptions!C20*(1+Assumptions!F20)^10*Assumptions!$B$13 -> 154.311 | D36: =C36/B36 -> 6.8582666 | E36: =(C36/B36)^(1/10)-1 -> 0.21233163 | F36: =Assumptions!C20*(1+Assumptions!G20)^10*Assumptions!$B$13 -> 383.25012 | G36: =F36/B36 -> 17.033338 | H36: =(F36/B36)^(1/10)-1 -> 0.32779179 | I36: =Assumptions!C20*(1+Assumptions!H20)^10*Assumptions!$B$13 -> 5.3347801 | J36: =I36/B36 -> 0.23710134 | K36: =(I36/B36)^(1/10)-1 -> -0.13404884 | L36: =Assumptions!C20*(1+Assumptions!I20)^10*Assumptions!$B$13 -> 495.81991 | M36: =L36/B36 -> 22.036441 | N36: =(L36/B36)^(1/10)-1 -> 0.36242983
A37: =Assumptions!A21 -> EdgeCortix | B37: =Assumptions!C21 -> 30.5 | C37: =Assumptions!C21*(1+Assumptions!F21)^10*Assumptions!$B$13 -> 178.24839 | D37: =C37/B37 -> 5.8442093 | E37: =(C37/B37)^(1/10)-1 -> 0.19308827 | F37: =Assumptions!C21*(1+Assumptions!G21)^10*Assumptions!$B$13 -> 448.94986 | G37: =F37/B37 -> 14.719667 | H37: =(F37/B37)^(1/10)-1 -> 0.30854843 | I37: =Assumptions!C21*(1+Assumptions!H21)^10*Assumptions!$B$13 -> 9.0092165 | J37: =I37/B37 -> 0.29538415 | K37: =(I37/B37)^(1/10)-1 -> -0.11480548 | L37: =Assumptions!C21*(1+Assumptions!I21)^10*Assumptions!$B$13 -> 215.91335 | M37: =L37/B37 -> 7.0791262 | N37: =(L37/B37)^(1/10)-1 -> 0.2161803
A38: =Assumptions!A22 -> Syntiant | B38: =Assumptions!C22 -> 31.5 | C38: =Assumptions!C22*(1+Assumptions!F22)^10*Assumptions!$B$13 -> 94.492939 | D38: =C38/B38 -> 2.9997759 | E38: =(C38/B38)^(1/10)-1 -> 0.11611483 | F38: =Assumptions!C22*(1+Assumptions!G22)^10*Assumptions!$B$13 -> 252.88273 | G38: =F38/B38 -> 8.028023 | H38: =(F38/B38)^(1/10)-1 -> 0.23157499 | I38: =Assumptions!C22*(1+Assumptions!H22)^10*Assumptions!$B$13 -> 17.5017 | J38: =I38/B38 -> 0.55560951 | K38: =(I38/B38)^(1/10)-1 -> -0.057075398 | L38: =Assumptions!C22*(1+Assumptions!I22)^10*Assumptions!$B$13 -> 156.4652 | M38: =L38/B38 -> 4.9671494 | N38: =(L38/B38)^(1/10)-1 -> 0.17384491
A39: =Assumptions!A23 -> Infleqtion | B39: =Assumptions!C23 -> 25 | C39: =Assumptions!C23*(1+Assumptions!F23)^10*Assumptions!$B$13 -> 68.774482 | D39: =C39/B39 -> 2.7509793 | E39: =(C39/B39)^(1/10)-1 -> 0.10649315 | F39: =Assumptions!C23*(1+Assumptions!G23)^10*Assumptions!$B$13 -> 185.56076 | G39: =F39/B39 -> 7.4224302 | H39: =(F39/B39)^(1/10)-1 -> 0.22195331 | I39: =Assumptions!C23*(1+Assumptions!H23)^10*Assumptions!$B$13 -> 5.9275335 | J39: =I39/B39 -> 0.23710134 | K39: =(I39/B39)^(1/10)-1 -> -0.13404884 | L39: =Assumptions!C23*(1+Assumptions!I23)^10*Assumptions!$B$13 -> 126.22953 | M39: =L39/B39 -> 5.0491814 | N39: =(L39/B39)^(1/10)-1 -> 0.17576925
A40: =Assumptions!A24 -> Diraq | B40: =Assumptions!C24 -> 14 | C40: =Assumptions!C24*(1+Assumptions!F24)^10*Assumptions!$B$13 -> 131.24128 | D40: =C40/B40 -> 9.3743774 | E40: =(C40/B40)^(1/10)-1 -> 0.25081835 | F40: =Assumptions!C24*(1+Assumptions!G24)^10*Assumptions!$B$13 -> 317.33677 | G40: =F40/B40 -> 22.666912 | H40: =(F40/B40)^(1/10)-1 -> 0.3662785 | I40: =Assumptions!C24*(1+Assumptions!H24)^10*Assumptions!$B$13 -> 0.79356586 | J40: =I40/B40 -> 0.056683276 | K40: =(I40/B40)^(1/10)-1 -> -0.24950899 | L40: =Assumptions!C24*(1+Assumptions!I24)^10*Assumptions!$B$13 -> 245.46968 | M40: =L40/B40 -> 17.533548 | N40: =(L40/B40)^(1/10)-1 -> 0.33164046
A41: =Assumptions!A25 -> Mueon | B41: =Assumptions!C25 -> 10 | C41: =Assumptions!C25*(1+Assumptions!F25)^10*Assumptions!$B$13 -> 109.20643 | D41: =C41/B41 -> 10.920643 | E41: =(C41/B41)^(1/10)-1 -> 0.27006171 | F41: =Assumptions!C25*(1+Assumptions!G25)^10*Assumptions!$B$13 -> 260.69568 | G41: =F41/B41 -> 26.069568 | H41: =(F41/B41)^(1/10)-1 -> 0.38552186 | I41: =Assumptions!C25*(1+Assumptions!H25)^10*Assumptions!$B$13 -> 0.25458562 | J41: =I41/B41 -> 0.025458562 | K41: =(I41/B41)^(1/10)-1 -> -0.30723907 | L41: =Assumptions!C25*(1+Assumptions!I25)^10*Assumptions!$B$13 -> 191.14507 | M41: =L41/B41 -> 19.114507 | N41: =(L41/B41)^(1/10)-1 -> 0.34318647
A42: =Assumptions!A26 -> DefendEye | B42: =Assumptions!C26 -> 6.5 | C42: =Assumptions!C26*(1+Assumptions!F26)^10*Assumptions!$B$13 -> 52.18215 | D42: =C42/B42 -> 8.028023 | E42: =(C42/B42)^(1/10)-1 -> 0.23157499 | F42: =Assumptions!C26*(1+Assumptions!G26)^10*Assumptions!$B$13 -> 127.85056 | G42: =F42/B42 -> 19.669317 | H42: =(F42/B42)^(1/10)-1 -> 0.34703515 | I42: =Assumptions!C26*(1+Assumptions!H26)^10*Assumptions!$B$13 -> 0.24890574 | J42: =I42/B42 -> 0.03829319 | K42: =(I42/B42)^(1/10)-1 -> -0.27837403 | L42: =Assumptions!C26*(1+Assumptions!I26)^10*Assumptions!$B$13 -> 31.243381 | M42: =L42/B42 -> 4.8066739 | N42: =(L42/B42)^(1/10)-1 -> 0.16999624
A43: FUND TOTAL | B43: =SUM(B34:B42) -> 250 | C43: =SUM(C34:C42) -> 1261.4559 | D43: =C43/B43 -> 5.0458237 | E43: =(C43/B43)^(1/10)-1 -> 0.17569104 | F43: =SUM(F34:F42) -> 3197.6972 | G43: =F43/B43 -> 12.790789 | H43: =(F43/B43)^(1/10)-1 -> 0.29029713 | I43: =SUM(I34:I42) -> 73.963354 | J43: =I43/B43 -> 0.29585342 | K43: =(I43/B43)^(1/10)-1 -> -0.11466495 | L43: =SUM(L34:L42) -> 3418.1015 | M43: =L43/B43 -> 13.672406 | N43: =(L43/B43)^(1/10)-1 -> 0.29892625

Sheet Fund Economics
A1: FUND ECONOMICS — GROSS->NET WATERFALL
A2: Whole-fund European waterfall: return of capital -> 8% comp. pref -> 20% carry (no catch-up). Expected = prob-weighted. $M.
A4: 5-YEAR VEHICLE
A5: Line item ($M) | B5: Base | C5: Bull | D5: Bear | E5: TSMC-Shock | F5: Expected
A6: Gross exit proceeds | B6: ='Portfolio Returns'!C15 -> 565.83078 | C6: ='Portfolio Returns'!F15 -> 904.36142 | D6: ='Portfolio Returns'!I15 -> 126.29353 | E6: ='Portfolio Returns'!L15 -> 915.40631 | F6: =B6*'Defense Supercycle'!$B$17+C6*'Defense Supercycle'!$B$18+D6*'Defense Supercycle'!$B$19+E6*'Defense Supercycle'!$B$20 -> 636.96918
A7: (-) Return of committed capital | B7: =-Assumptions!$B$5 -> -250 | C7: =-Assumptions!$B$5 -> -250 | D7: =-Assumptions!$B$5 -> -250 | E7: =-Assumptions!$B$5 -> -250 | F7: =B7*'Defense Supercycle'!$B$17+C7*'Defense Supercycle'!$B$18+D7*'Defense Supercycle'!$B$19+E7*'Defense Supercycle'!$B$20 -> -250
A8: (-) Preferred return (8% comp.) | B8: =-Assumptions!$B$5*((1+Assumptions!$B$10)^5-1) -> -117.33202 | C8: =-Assumptions!$B$5*((1+Assumptions!$B$10)^5-1) -> -117.33202 | D8: =-Assumptions!$B$5*((1+Assumptions!$B$10)^5-1) -> -117.33202 | E8: =-Assumptions!$B$5*((1+Assumptions!$B$10)^5-1) -> -117.33202 | F8: =B8*'Defense Supercycle'!$B$17+C8*'Defense Supercycle'!$B$18+D8*'Defense Supercycle'!$B$19+E8*'Defense Supercycle'!$B$20 -> -117.33202
A9: Profit above pref (carry base) | B9: =MAX(0,B6+B7+B8) -> 198.49876 | C9: =MAX(0,C6+C7+C8) -> 537.0294 | D9: =MAX(0,D6+D7+D8) -> 0 | E9: =MAX(0,E6+E7+E8) -> 548.07429 | F9: =B9*'Defense Supercycle'!$B$17+C9*'Defense Supercycle'!$B$18+D9*'Defense Supercycle'!$B$19+E9*'Defense Supercycle'!$B$20 -> 305.79294
A10: (-) GP carried interest (20%) | B10: =-Assumptions!$B$9*B9 -> -39.699752 | C10: =-Assumptions!$B$9*C9 -> -107.40588 | D10: =-Assumptions!$B$9*D9 -> 0 | E10: =-Assumptions!$B$9*E9 -> -109.61486 | F10: =B10*'Defense Supercycle'!$B$17+C10*'Defense Supercycle'!$B$18+D10*'Defense Supercycle'!$B$19+E10*'Defense Supercycle'!$B$20 -> -61.158587
A11: (-) Management fees | B11: =-Assumptions!$B$5*Assumptions!$B$8*5 -> -25 | C11: =-Assumptions!$B$5*Assumptions!$B$8*5 -> -25 | D11: =-Assumptions!$B$5*Assumptions!$B$8*5 -> -25 | E11: =-Assumptions!$B$5*Assumptions!$B$8*5 -> -25 | F11: =B11*'Defense Supercycle'!$B$17+C11*'Defense Supercycle'!$B$18+D11*'Defense Supercycle'!$B$19+E11*'Defense Supercycle'!$B$20 -> -25
A12: Net proceeds to LPs | B12: =B6+B10+B11 -> 501.13103 | C12: =C6+C10+C11 -> 771.95554 | D12: =D6+D10+D11 -> 101.29353 | E12: =E6+E10+E11 -> 780.79145 | F12: =B12*'Defense Supercycle'!$B$17+C12*'Defense Supercycle'!$B$18+D12*'Defense Supercycle'!$B$19+E12*'Defense Supercycle'!$B$20 -> 550.81059
A13: Gross MOIC | B13: =B6/Assumptions!$B$5 -> 2.2633231 | C13: =C6/Assumptions!$B$5 -> 3.6174457 | D13: =D6/Assumptions!$B$5 -> 0.5051741 | E13: =E6/Assumptions!$B$5 -> 3.6616253 | F13: =F6/Assumptions!$B$5 -> 2.5478767
A14: Net MOIC (to LP) | B14: =B12/Assumptions!$B$5 -> 2.0045241 | C14: =C12/Assumptions!$B$5 -> 3.0878221 | D14: =D12/Assumptions!$B$5 -> 0.4051741 | E14: =E12/Assumptions!$B$5 -> 3.1231658 | F14: =F12/Assumptions!$B$5 -> 2.2032424
A15: Gross IRR | B15: =(B6/Assumptions!$B$5)^(1/5)-1 -> 0.17746854 | C15: =(C6/Assumptions!$B$5)^(1/5)-1 -> 0.29324379 | D15: =(D6/Assumptions!$B$5)^(1/5)-1 -> -0.12765512 | E15: =(E6/Assumptions!$B$5)^(1/5)-1 -> 0.29638733 | F15: =(F6/Assumptions!$B$5)^(1/5)-1 -> 0.20569006
A16: Net IRR (to LP) | B16: =(B12/Assumptions!$B$5)^(1/5)-1 -> 0.14921757 | C16: =(C12/Assumptions!$B$5)^(1/5)-1 -> 0.25294052 | D16: =(D12/Assumptions!$B$5)^(1/5)-1 -> -0.16530399 | E16: =(E12/Assumptions!$B$5)^(1/5)-1 -> 0.25579575 | F16: =(F12/Assumptions!$B$5)^(1/5)-1 -> 0.17114982
A17: DPI = TVPI at exit | B17: =B12/Assumptions!$B$5 -> 2.0045241 | C17: =C12/Assumptions!$B$5 -> 3.0878221 | D17: =D12/Assumptions!$B$5 -> 0.4051741 | E17: =E12/Assumptions!$B$5 -> 3.1231658 | F17: =F12/Assumptions!$B$5 -> 2.2032424
A20: 7-YEAR VEHICLE
A21: Line item ($M) | B21: Base | C21: Bull | D21: Bear | E21: TSMC-Shock | F21: Expected
A22: Gross exit proceeds | B22: ='Portfolio Returns'!C29 -> 778.13077 | C22: ='Portfolio Returns'!F29 -> 1497.0053 | D22: ='Portfolio Returns'!I29 -> 100.03369 | E22: ='Portfolio Returns'!L29 -> 1542.4475 | F22: =B22*'Defense Supercycle'!$B$17+C22*'Defense Supercycle'!$B$18+D22*'Defense Supercycle'!$B$19+E22*'Defense Supercycle'!$B$20 -> 970.78235
A23: (-) Return of committed capital | B23: =-Assumptions!$B$5 -> -250 | C23: =-Assumptions!$B$5 -> -250 | D23: =-Assumptions!$B$5 -> -250 | E23: =-Assumptions!$B$5 -> -250 | F23: =B23*'Defense Supercycle'!$B$17+C23*'Defense Supercycle'!$B$18+D23*'Defense Supercycle'!$B$19+E23*'Defense Supercycle'!$B$20 -> -250
A24: (-) Preferred return (8% comp.) | B24: =-Assumptions!$B$5*((1+Assumptions!$B$10)^7-1) -> -178.45607 | C24: =-Assumptions!$B$5*((1+Assumptions!$B$10)^7-1) -> -178.45607 | D24: =-Assumptions!$B$5*((1+Assumptions!$B$10)^7-1) -> -178.45607 | E24: =-Assumptions!$B$5*((1+Assumptions!$B$10)^7-1) -> -178.45607 | F24: =B24*'Defense Supercycle'!$B$17+C24*'Defense Supercycle'!$B$18+D24*'Defense Supercycle'!$B$19+E24*'Defense Supercycle'!$B$20 -> -178.45607
A25: Profit above pref (carry base) | B25: =MAX(0,B22+B23+B24) -> 349.6747 | C25: =MAX(0,C22+C23+C24) -> 1068.5492 | D25: =MAX(0,D22+D23+D24) -> 0 | E25: =MAX(0,E22+E23+E24) -> 1113.9915 | F25: =B25*'Defense Supercycle'!$B$17+C25*'Defense Supercycle'!$B$18+D25*'Defense Supercycle'!$B$19+E25*'Defense Supercycle'!$B$20 -> 591.58964
A26: (-) GP carried interest (20%) | B26: =-Assumptions!$B$9*B25 -> -69.934941 | C26: =-Assumptions!$B$9*C25 -> -213.70985 | D26: =-Assumptions!$B$9*D25 -> 0 | E26: =-Assumptions!$B$9*E25 -> -222.79829 | F26: =B26*'Defense Supercycle'!$B$17+C26*'Defense Supercycle'!$B$18+D26*'Defense Supercycle'!$B$19+E26*'Defense Supercycle'!$B$20 -> -118.31793
A27: (-) Management fees | B27: =-Assumptions!$B$5*Assumptions!$B$8*7 -> -35 | C27: =-Assumptions!$B$5*Assumptions!$B$8*7 -> -35 | D27: =-Assumptions!$B$5*Assumptions!$B$8*7 -> -35 | E27: =-Assumptions!$B$5*Assumptions!$B$8*7 -> -35 | F27: =B27*'Defense Supercycle'!$B$17+C27*'Defense Supercycle'!$B$18+D27*'Defense Supercycle'!$B$19+E27*'Defense Supercycle'!$B$20 -> -35
A28: Net proceeds to LPs | B28: =B22+B26+B27 -> 673.19583 | C28: =C22+C26+C27 -> 1248.2955 | D28: =D22+D26+D27 -> 65.033688 | E28: =E22+E26+E27 -> 1284.6492 | F28: =B28*'Defense Supercycle'!$B$17+C28*'Defense Supercycle'!$B$18+D28*'Defense Supercycle'!$B$19+E28*'Defense Supercycle'!$B$20 -> 817.46442
A29: Gross MOIC | B29: =B22/Assumptions!$B$5 -> 3.1125231 | C29: =C22/Assumptions!$B$5 -> 5.9880212 | D29: =D22/Assumptions!$B$5 -> 0.40013475 | E29: =E22/Assumptions!$B$5 -> 6.1697901 | F29: =F22/Assumptions!$B$5 -> 3.8831294
A30: Net MOIC (to LP) | B30: =B28/Assumptions!$B$5 -> 2.6927833 | C30: =C28/Assumptions!$B$5 -> 4.9931818 | D30: =D28/Assumptions!$B$5 -> 0.26013475 | E30: =E28/Assumptions!$B$5 -> 5.1385969 | F30: =F28/Assumptions!$B$5 -> 3.2698577
A31: Gross IRR | B31: =(B22/Assumptions!$B$5)^(1/7)-1 -> 0.1761011 | C31: =(C22/Assumptions!$B$5)^(1/7)-1 -> 0.29133962 | D31: =(D22/Assumptions!$B$5)^(1/7)-1 -> -0.12265112 | E31: =(E22/Assumptions!$B$5)^(1/7)-1 -> 0.29686799 | F31: =(F22/Assumptions!$B$5)^(1/7)-1 -> 0.21386066
A32: Net IRR (to LP) | B32: =(B28/Assumptions!$B$5)^(1/7)-1 -> 0.1520129 | C32: =(C28/Assumptions!$B$5)^(1/7)-1 -> 0.25825364 | D32: =(D28/Assumptions!$B$5)^(1/7)-1 -> -0.17499437 | E32: =(E28/Assumptions!$B$5)^(1/7)-1 -> 0.26342429 | F32: =(F28/Assumptions!$B$5)^(1/7)-1 -> 0.18441561
A33: DPI = TVPI at exit | B33: =B28/Assumptions!$B$5 -> 2.6927833 | C33: =C28/Assumptions!$B$5 -> 4.9931818 | D33: =D28/Assumptions!$B$5 -> 0.26013475 | E33: =E28/Assumptions!$B$5 -> 5.1385969 | F33: =F28/Assumptions!$B$5 -> 3.2698577
A36: 10-YEAR VEHICLE
A37: Line item ($M) | B37: Base | C37: Bull | D37: Bear | E37: TSMC-Shock | F37: Expected
A38: Gross exit proceeds | B38: ='Portfolio Returns'!C43 -> 1261.4559 | C38: ='Portfolio Returns'!F43 -> 3197.6972 | D38: ='Portfolio Returns'!I43 -> 73.963354 | E38: ='Portfolio Returns'!L43 -> 3418.1015 | F38: =B38*'Defense Supercycle'!$B$17+C38*'Defense Supercycle'!$B$18+D38*'Defense Supercycle'!$B$19+E38*'Defense Supercycle'!$B$20 -> 1890.8892
A39: (-) Return of committed capital | B39: =-Assumptions!$B$5 -> -250 | C39: =-Assumptions!$B$5 -> -250 | D39: =-Assumptions!$B$5 -> -250 | E39: =-Assumptions!$B$5 -> -250 | F39: =B39*'Defense Supercycle'!$B$17+C39*'Defense Supercycle'!$B$18+D39*'Defense Supercycle'!$B$19+E39*'Defense Supercycle'!$B$20 -> -250
A40: (-) Preferred return (8% comp.) | B40: =-Assumptions!$B$5*((1+Assumptions!$B$10)^10-1) -> -289.73125 | C40: =-Assumptions!$B$5*((1+Assumptions!$B$10)^10-1) -> -289.73125 | D40: =-Assumptions!$B$5*((1+Assumptions!$B$10)^10-1) -> -289.73125 | E40: =-Assumptions!$B$5*((1+Assumptions!$B$10)^10-1) -> -289.73125 | F40: =B40*'Defense Supercycle'!$B$17+C40*'Defense Supercycle'!$B$18+D40*'Defense Supercycle'!$B$19+E40*'Defense Supercycle'!$B$20 -> -289.73125
A41: Profit above pref (carry base) | B41: =MAX(0,B38+B39+B40) -> 721.72469 | C41: =MAX(0,C38+C39+C40) -> 2657.9659 | D41: =MAX(0,D38+D39+D40) -> 0 | E41: =MAX(0,E38+E39+E40) -> 2878.3702 | F41: =B41*'Defense Supercycle'!$B$17+C41*'Defense Supercycle'!$B$18+D41*'Defense Supercycle'!$B$19+E41*'Defense Supercycle'!$B$20 -> 1421.0231
A42: (-) GP carried interest (20%) | B42: =-Assumptions!$B$9*B41 -> -144.34494 | C42: =-Assumptions!$B$9*C41 -> -531.59319 | D42: =-Assumptions!$B$9*D41 -> 0 | E42: =-Assumptions!$B$9*E41 -> -575.67404 | F42: =B42*'Defense Supercycle'!$B$17+C42*'Defense Supercycle'!$B$18+D42*'Defense Supercycle'!$B$19+E42*'Defense Supercycle'!$B$20 -> -284.20462
A43: (-) Management fees | B43: =-Assumptions!$B$5*Assumptions!$B$8*10 -> -50 | C43: =-Assumptions!$B$5*Assumptions!$B$8*10 -> -50 | D43: =-Assumptions!$B$5*Assumptions!$B$8*10 -> -50 | E43: =-Assumptions!$B$5*Assumptions!$B$8*10 -> -50 | F43: =B43*'Defense Supercycle'!$B$17+C43*'Defense Supercycle'!$B$18+D43*'Defense Supercycle'!$B$19+E43*'Defense Supercycle'!$B$20 -> -50
A44: Net proceeds to LPs | B44: =B38+B42+B43 -> 1067.111 | C44: =C38+C42+C43 -> 2616.104 | D44: =D38+D42+D43 -> 23.963354 | E44: =E38+E42+E43 -> 2792.4274 | F44: =B44*'Defense Supercycle'!$B$17+C44*'Defense Supercycle'!$B$18+D44*'Defense Supercycle'!$B$19+E44*'Defense Supercycle'!$B$20 -> 1556.6846
A45: Gross MOIC | B45: =B38/Assumptions!$B$5 -> 5.0458237 | C45: =C38/Assumptions!$B$5 -> 12.790789 | D45: =D38/Assumptions!$B$5 -> 0.29585342 | E45: =E38/Assumptions!$B$5 -> 13.672406 | F45: =F38/Assumptions!$B$5 -> 7.5635568
A46: Net MOIC (to LP) | B46: =B44/Assumptions!$B$5 -> 4.268444 | C46: =C44/Assumptions!$B$5 -> 10.464416 | D46: =D44/Assumptions!$B$5 -> 0.095853416 | E46: =E44/Assumptions!$B$5 -> 11.16971 | F46: =F44/Assumptions!$B$5 -> 6.2267383
A47: Gross IRR | B47: =(B38/Assumptions!$B$5)^(1/10)-1 -> 0.17569104 | C47: =(C38/Assumptions!$B$5)^(1/10)-1 -> 0.29029713 | D47: =(D38/Assumptions!$B$5)^(1/10)-1 -> -0.11466495 | E47: =(E38/Assumptions!$B$5)^(1/10)-1 -> 0.29892625 | F47: =(F38/Assumptions!$B$5)^(1/10)-1 -> 0.22425703
A48: Net IRR (to LP) | B48: =(B44/Assumptions!$B$5)^(1/10)-1 -> 0.15618401 | C48: =(C44/Assumptions!$B$5)^(1/10)-1 -> 0.26465335 | D48: =(D44/Assumptions!$B$5)^(1/10)-1 -> -0.20902864 | E48: =(E44/Assumptions!$B$5)^(1/10)-1 -> 0.27292902 | F48: =(F44/Assumptions!$B$5)^(1/10)-1 -> 0.20067664
A49: DPI = TVPI at exit | B49: =B44/Assumptions!$B$5 -> 4.268444 | C49: =C44/Assumptions!$B$5 -> 10.464416 | D49: =D44/Assumptions!$B$5 -> 0.095853416 | E49: =E44/Assumptions!$B$5 -> 11.16971 | F49: =F44/Assumptions!$B$5 -> 6.2267383

Sheet IQT Clusters
A1: IQT SLEEVE — STRATEGIC-FUNCTION CLUSTER ROLL-UP
A2: The nine Substrate-anchored names grouped by wartime function (per the IQT strategic analysis). Green links to live per-name figures.
A4: SIZING & STRATEGIC SCORE BY CLUSTER
A5: Strategic cluster | B5: Holdings | C5: Check ($M) | D5: % Sleeve | E5: % Holdco | F5: Avg composite | G5: Avg shock CAGR
A6: TSMC-alternative: packaging & substrates | B6: Substrate, ThinTronics, EUV Tech | C6: =Assumptions!C18+Assumptions!C19+Assumptions!C20 -> 132.5 | D6: =C6/Assumptions!$B$5 -> 0.53 | E6: =C6/'Holdco Summary'!$B$9 -> 0.1577381 | F6: =AVERAGE('Defense Supercycle'!G24,'Defense Supercycle'!G25,'Defense Supercycle'!G26) -> 4.6166667 | G6: =AVERAGE('Defense Supercycle'!I24,'Defense Supercycle'!I25,'Defense Supercycle'!I26) -> 0.376
A7: Denied-environment edge AI | B7: Syntiant, EdgeCortix | C7: =Assumptions!C21+Assumptions!C22 -> 62 | D7: =C7/Assumptions!$B$5 -> 0.248 | E7: =C7/'Holdco Summary'!$B$9 -> 0.073809524 | F7: =AVERAGE('Defense Supercycle'!G27,'Defense Supercycle'!G28) -> 3.025 | G7: =AVERAGE('Defense Supercycle'!I27,'Defense Supercycle'!I28) -> 0.242
A8: Post-Moore's next-gen compute | B8: Infleqtion, Diraq, Mueon | C8: =Assumptions!C23+Assumptions!C24+Assumptions!C25 -> 49 | D8: =C8/Assumptions!$B$5 -> 0.196 | E8: =C8/'Holdco Summary'!$B$9 -> 0.058333333 | F8: =AVERAGE('Defense Supercycle'!G29,'Defense Supercycle'!G30,'Defense Supercycle'!G31) -> 3.4666667 | G8: =AVERAGE('Defense Supercycle'!I29,'Defense Supercycle'!I30,'Defense Supercycle'!I31) -> 0.334
A9: Autonomous sensing (adjacent) | B9: DefendEye | C9: =Assumptions!C26 -> 6.5 | D9: =C9/Assumptions!$B$5 -> 0.026 | E9: =C9/'Holdco Summary'!$B$9 -> 0.0077380952 | F9: =AVERAGE('Defense Supercycle'!G32) -> 1.7 | G9: =AVERAGE('Defense Supercycle'!I32) -> 0.216
A10: IQT SLEEVE TOTAL | C10: =SUM(C6:C9) -> 250 | D10: =SUM(D6:D9) -> 1 | F10: =AVERAGE('Defense Supercycle'!G24,'Defense Supercycle'!G25,'Defense Supercycle'!G26,'Defense Supercycle'!G27,'Defense Supercycle'!G28,'Defense Supercycle'!G29,'Defense Supercycle'!G30,'Defense Supercycle'!G31,'Defense Supercycle'!G32) -> 3.5555556
A12: 5-YEAR HOLD — CLUSTER GROSS PROCEEDS & MOIC
A13: Cluster | B13: Check ($M) | C13: Base $ | D13: Base MOIC | E13: Bull $ | F13: Bull MOIC | G13: Bear $ | H13: Bear MOIC | I13: Shock $ | J13: Shock MOIC
A14: TSMC-alternative: packaging & substrates | B14: =Assumptions!C18+Assumptions!C19+Assumptions!C20 -> 132.5 | C14: ='Portfolio Returns'!C6+'Portfolio Returns'!C7+'Portfolio Returns'!C8 -> 293.61934 | D14: =C14/B14 -> 2.215995 | E14: ='Portfolio Returns'!F6+'Portfolio Returns'!F7+'Portfolio Returns'!F8 -> 470.48876 | F14: =E14/B14 -> 3.5508586 | G14: ='Portfolio Returns'!I6+'Portfolio Returns'!I7+'Portfolio Returns'!I8 -> 66.064919 | H14: =G14/B14 -> 0.49860317 | I14: ='Portfolio Returns'!L6+'Portfolio Returns'!L7+'Portfolio Returns'!L8 -> 581.30727 | J14: =I14/B14 -> 4.3872247
A15: Denied-environment edge AI | B15: =Assumptions!C21+Assumptions!C22 -> 62 | C15: ='Portfolio Returns'!C9+'Portfolio Returns'!C10 -> 132.23903 | D15: =C15/B15 -> 2.1328875 | E15: ='Portfolio Returns'!F9+'Portfolio Returns'!F10 -> 212.61653 | F15: =E15/B15 -> 3.4292988 | G15: ='Portfolio Returns'!I9+'Portfolio Returns'!I10 -> 41.289168 | H15: =G15/B15 -> 0.66595432 | I15: ='Portfolio Returns'!L9+'Portfolio Returns'!L10 -> 156.01274 | J15: =I15/B15 -> 2.5163345
A16: Post-Moore's next-gen compute | B16: =Assumptions!C23+Assumptions!C24+Assumptions!C25 -> 49 | C16: ='Portfolio Returns'!C11+'Portfolio Returns'!C12+'Portfolio Returns'!C13 -> 120.98865 | D16: =C16/B16 -> 2.4691562 | E16: ='Portfolio Returns'!F11+'Portfolio Returns'!F12+'Portfolio Returns'!F13 -> 191.54135 | F16: =E16/B16 -> 3.9090071 | G16: ='Portfolio Returns'!I11+'Portfolio Returns'!I12+'Portfolio Returns'!I13 -> 17.62833 | H16: =G16/B16 -> 0.35976184 | I16: ='Portfolio Returns'!L11+'Portfolio Returns'!L12+'Portfolio Returns'!L13 -> 163.39704 | J16: =I16/B16 -> 3.3346334
A17: Autonomous sensing (adjacent) | B17: =Assumptions!C26 -> 6.5 | C17: ='Portfolio Returns'!C14 -> 18.983755 | D17: =C17/B17 -> 2.9205778 | E17: ='Portfolio Returns'!F14 -> 29.714776 | F17: =E17/B17 -> 4.571504 | G17: ='Portfolio Returns'!I14 -> 1.3111084 | H17: =G17/B17 -> 0.20170898 | I17: ='Portfolio Returns'!L14 -> 14.689268 | J17: =I17/B17 -> 2.2598874
A18: SLEEVE TOTAL | B18: =SUM(B14:B17) -> 250 | C18: =SUM(C14:C17) -> 565.83078 | D18: =C18/B18 -> 2.2633231 | E18: =SUM(E14:E17) -> 904.36142 | F18: =E18/B18 -> 3.6174457 | G18: =SUM(G14:G17) -> 126.29353 | H18: =G18/B18 -> 0.5051741 | I18: =SUM(I14:I17) -> 915.40631 | J18: =I18/B18 -> 3.6616253
A20: 7-YEAR HOLD — CLUSTER GROSS PROCEEDS & MOIC
A21: Cluster | B21: Check ($M) | C21: Base $ | D21: Base MOIC | E21: Bull $ | F21: Bull MOIC | G21: Bear $ | H21: Bear MOIC | I21: Shock $ | J21: Shock MOIC
A22: TSMC-alternative: packaging & substrates | B22: =Assumptions!C18+Assumptions!C19+Assumptions!C20 -> 132.5 | C22: ='Portfolio Returns'!C20+'Portfolio Returns'!C21+'Portfolio Returns'!C22 -> 398.05551 | D22: =C22/B22 -> 3.0041925 | E22: ='Portfolio Returns'!F20+'Portfolio Returns'!F21+'Portfolio Returns'!F22 -> 769.33638 | F22: =E22/B22 -> 5.8063123 | G22: ='Portfolio Returns'!I20+'Portfolio Returns'!I21+'Portfolio Returns'!I22 -> 52.728572 | H22: =G22/B22 -> 0.39795149 | I22: ='Portfolio Returns'!L20+'Portfolio Returns'!L21+'Portfolio Returns'!L22 -> 1034.8882 | J22: =I22/B22 -> 7.810477
A23: Denied-environment edge AI | B23: =Assumptions!C21+Assumptions!C22 -> 62 | C23: ='Portfolio Returns'!C23+'Portfolio Returns'!C24 -> 176.67761 | D23: =C23/B23 -> 2.8496389 | E23: ='Portfolio Returns'!F23+'Portfolio Returns'!F24 -> 343.03988 | F23: =E23/B23 -> 5.5329013 | G23: ='Portfolio Returns'!I23+'Portfolio Returns'!I24 -> 34.601015 | H23: =G23/B23 -> 0.55808089 | I23: ='Portfolio Returns'!L23+'Portfolio Returns'!L24 -> 221.47569 | J23: =I23/B23 -> 3.5721886
A24: Post-Moore's next-gen compute | B24: =Assumptions!C23+Assumptions!C24+Assumptions!C25 -> 49 | C24: ='Portfolio Returns'!C25+'Portfolio Returns'!C26+'Portfolio Returns'!C27 -> 174.85609 | D24: =C24/B24 -> 3.5684917 | E24: ='Portfolio Returns'!F25+'Portfolio Returns'!F26+'Portfolio Returns'!F27 -> 331.18438 | F24: =E24/B24 -> 6.758865 | G24: ='Portfolio Returns'!I25+'Portfolio Returns'!I26+'Portfolio Returns'!I27 -> 12.027337 | H24: =G24/B24 -> 0.24545587 | I24: ='Portfolio Returns'!L25+'Portfolio Returns'!L26+'Portfolio Returns'!L27 -> 266.15199 | J24: =I24/B24 -> 5.4316732
A25: Autonomous sensing (adjacent) | B25: =Assumptions!C26 -> 6.5 | C25: ='Portfolio Returns'!C28 -> 28.541563 | D25: =C25/B25 -> 4.3910096 | E25: ='Portfolio Returns'!F28 -> 53.444647 | F25: =E25/B25 -> 8.2222533 | G25: ='Portfolio Returns'!I28 -> 0.67676331 | H25: =G25/B25 -> 0.10411743 | I25: ='Portfolio Returns'!L28 -> 19.931638 | J25: =I25/B25 -> 3.0664058
A26: SLEEVE TOTAL | B26: =SUM(B22:B25) -> 250 | C26: =SUM(C22:C25) -> 778.13077 | D26: =C26/B26 -> 3.1125231 | E26: =SUM(E22:E25) -> 1497.0053 | F26: =E26/B26 -> 5.9880212 | G26: =SUM(G22:G25) -> 100.03369 | H26: =G26/B26 -> 0.40013475 | I26: =SUM(I22:I25) -> 1542.4475 | J26: =I26/B26 -> 6.1697901
A28: 10-YEAR HOLD — CLUSTER GROSS PROCEEDS & MOIC
A29: Cluster | B29: Check ($M) | C29: Base $ | D29: Base MOIC | E29: Bull $ | F29: Bull MOIC | G29: Bear $ | H29: Bear MOIC | I29: Shock $ | J29: Shock MOIC
A30: TSMC-alternative: packaging & substrates | B30: =Assumptions!C18+Assumptions!C19+Assumptions!C20 -> 132.5 | C30: ='Portfolio Returns'!C34+'Portfolio Returns'!C35+'Portfolio Returns'!C36 -> 627.31026 | D30: =C30/B30 -> 4.7344171 | E30: ='Portfolio Returns'!F34+'Portfolio Returns'!F35+'Portfolio Returns'!F36 -> 1604.4209 | F30: =E30/B30 -> 12.108837 | G30: ='Portfolio Returns'!I34+'Portfolio Returns'!I35+'Portfolio Returns'!I36 -> 40.227847 | H30: =G30/B30 -> 0.30360639 | I30: ='Portfolio Returns'!L34+'Portfolio Returns'!L35+'Portfolio Returns'!L36 -> 2451.6352 | J30: =I30/B30 -> 18.502908
A31: Denied-environment edge AI | B31: =Assumptions!C21+Assumptions!C22 -> 62 | C31: ='Portfolio Returns'!C37+'Portfolio Returns'!C38 -> 272.74132 | D31: =C31/B31 -> 4.3990536 | E31: ='Portfolio Returns'!F37+'Portfolio Returns'!F38 -> 701.83258 | F31: =E31/B31 -> 11.31988 | G31: ='Portfolio Returns'!I37+'Portfolio Returns'!I38 -> 26.510916 | H31: =G31/B31 -> 0.42759542 | I31: ='Portfolio Returns'!L37+'Portfolio Returns'!L38 -> 372.37855 | J31: =I31/B31 -> 6.0061057
A32: Post-Moore's next-gen compute | B32: =Assumptions!C23+Assumptions!C24+Assumptions!C25 -> 49 | C32: ='Portfolio Returns'!C39+'Portfolio Returns'!C40+'Portfolio Returns'!C41 -> 309.2222 | D32: =C32/B32 -> 6.3106571 | E32: ='Portfolio Returns'!F39+'Portfolio Returns'!F40+'Portfolio Returns'!F41 -> 763.5932 | F32: =E32/B32 -> 15.583535 | G32: ='Portfolio Returns'!I39+'Portfolio Returns'!I40+'Portfolio Returns'!I41 -> 6.975685 | H32: =G32/B32 -> 0.14236092 | I32: ='Portfolio Returns'!L39+'Portfolio Returns'!L40+'Portfolio Returns'!L41 -> 562.84428 | J32: =I32/B32 -> 11.486618
A33: Autonomous sensing (adjacent) | B33: =Assumptions!C26 -> 6.5 | C33: ='Portfolio Returns'!C42 -> 52.18215 | D33: =C33/B33 -> 8.028023 | E33: ='Portfolio Returns'!F42 -> 127.85056 | F33: =E33/B33 -> 19.669317 | G33: ='Portfolio Returns'!I42 -> 0.24890574 | H33: =G33/B33 -> 0.03829319 | I33: ='Portfolio Returns'!L42 -> 31.243381 | J33: =I33/B33 -> 4.8066739
A34: SLEEVE TOTAL | B34: =SUM(B30:B33) -> 250 | C34: =SUM(C30:C33) -> 1261.4559 | D34: =C34/B34 -> 5.0458237 | E34: =SUM(E30:E33) -> 3197.6972 | F34: =E34/B34 -> 12.790789 | G34: =SUM(G30:G33) -> 73.963354 | H34: =G34/B34 -> 0.29585342 | I34: =SUM(I30:I33) -> 3418.1015 | J34: =I34/B34 -> 13.672406
A36: Read: sized by strategic function, the sleeve is ~53% TSMC-alternative packaging/substrates (the sovereign core), ~25% denied-environment edge AI, ~20% next-gen compute, ~3% adjacent autonomy — a deliberate overweight to the domestic fail-safe chokepoints that re-rate hardest in a Taiwan/TSMC shock.

Sheet Weapons Sleeve
A1: WEAPONS SLEEVE — BOTTOM-UP ($390M)
A2: Physical-layer defense holdings. Blue = input. Most entry marks are estimates; several names are access-constrained (see flags). Proceeds use munitions/FMS-adjusted CAGRs (cols S:V).
A4: SLEEVE TERMS | P4: MUNITIONS / FMS OVERLAY — CAGR UPLIFT PER EXPOSURE POINT
A5: Committed ($M) | B5: ='Holdco Summary'!$B$7 -> 390 | P5: Base uplift / pt | Q5: 0.005
A6: Retention @5yr | B6: 0.92 | P6: Bull uplift / pt | Q6: 0.008
A7: Retention @7yr | B7: 0.88 | P7: Bear uplift / pt (backlog cushion) | Q7: 0.004
A8: Retention @10yr | B8: 0.82 | P8: Shock uplift / pt | Q8: 0.006
A10: HOLDINGS, ENTRY MARKS & GROWTH ASSUMPTIONS
A11: Company | B11: Entry post-$M | C11: Check ($M) | D11: Own % | E11: Access / structure flag | F11: Base | G11: Bull | H11: Bear | I11: Shock | J11: Valuation basis | P11: Munitions shortage (0-5) | Q11: FMS / export backlog (0-5) | R11: Exposure score | S11: Adj. Base | T11: Adj. Bull | U11: Adj. Bear | V11: Adj. Shock
A12: Saronic | B12: 9250 | C12: 70 | D12: =C12/B12 -> 0.0075675676 | E12: US clean; late/expensive — secondary or late primary | F12: 0.26 | G12: 0.4 | H12: 0 | I12: 0.38 | J12: Series D Mar-26 $9.25B post | P12: 2 | Q12: 3 | R12: =AVERAGE(P12:Q12) -> 2.5 | S12: =F12+$R12*$Q$5 -> 0.2725 | T12: =G12+$R12*$Q$6 -> 0.42 | U12: =H12+$R12*$Q$7 -> 0.01 | V12: =I12+$R12*$Q$8 -> 0.395
A13: Epirus | B13: 1350 | C13: 45 | D13: =C13/B13 -> 0.033333333 | E13: US clean; directed energy / HPM | F13: 0.24 | G13: 0.38 | H13: -0.02 | I13: 0.4 | J13: Est. — Series D 2025 (~$1.35B) | P13: 3 | Q13: 3 | R13: =AVERAGE(P13:Q13) -> 3 | S13: =F13+$R13*$Q$5 -> 0.255 | T13: =G13+$R13*$Q$6 -> 0.404 | U13: =H13+$R13*$Q$7 -> -0.008 | V13: =I13+$R13*$Q$8 -> 0.418
A14: Israel Aerospace Ind. | B14: 16000 | C14: 40 | D14: =C14/B14 -> 0.0025 | E14: IPO ATTEMPT (H2-26) — cornerstone/IPO allocation; ITAR/foreign-own. remains | F14: 0.17 | G14: 0.28 | H14: 0.06 | I14: 0.28 | J14: Est. — IPO-pending (Elbit-comp scale) | P14: 5 | Q14: 5 | R14: =AVERAGE(P14:Q14) -> 5 | S14: =F14+$R14*$Q$5 -> 0.195 | T14: =G14+$R14*$Q$6 -> 0.32 | U14: =H14+$R14*$Q$7 -> 0.08 | V14: =I14+$R14*$Q$8 -> 0.31
A15: Elta Systems | B15: 3000 | C15: 30 | D15: =C15/B15 -> 0.01 | E15: IAI subsidiary — consolidates into IAI IPO; EW/ISR | F15: 0.16 | G15: 0.26 | H15: 0.05 | I15: 0.28 | J15: Est. notional (within IAI) | P15: 2 | Q15: 4 | R15: =AVERAGE(P15:Q15) -> 3 | S15: =F15+$R15*$Q$5 -> 0.175 | T15: =G15+$R15*$Q$6 -> 0.284 | U15: =H15+$R15*$Q$7 -> 0.062 | V15: =I15+$R15*$Q$8 -> 0.298
A16: Heckler & Koch | B16: 1800 | C16: 35 | D16: =C16/B16 -> 0.019444444 | E16: Listed; closely held (CDR) — secondary/block | F16: 0.12 | G16: 0.2 | H16: 0.04 | I16: 0.22 | J16: Est. EV — listed small-arms | P16: 3 | Q16: 3 | R16: =AVERAGE(P16:Q16) -> 3 | S16: =F16+$R16*$Q$5 -> 0.135 | T16: =G16+$R16*$Q$6 -> 0.224 | U16: =H16+$R16*$Q$7 -> 0.052 | V16: =I16+$R16*$Q$8 -> 0.238
A17: Helicon Chemical | B17: 150 | C17: 40 | D17: =C17/B17 -> 0.26666667 | E17: US clean; investable small — real stake | F17: 0.28 | G17: 0.44 | H17: 0.02 | I17: 0.46 | J17: Est. — early-growth energetics | P17: 5 | Q17: 3 | R17: =AVERAGE(P17:Q17) -> 4 | S17: =F17+$R17*$Q$5 -> 0.3 | T17: =G17+$R17*$Q$6 -> 0.472 | U17: =H17+$R17*$Q$7 -> 0.036 | V17: =I17+$R17*$Q$8 -> 0.484
A18: The Ellwood Group | B18: 1200 | C18: 50 | D18: =C18/B18 -> 0.041666667 | E18: FAMILY-OWNED private (Ellwood City, PA) — minority/structured pref; missile-casing & naval open/closed-die forgings | F18: 0.13 | G18: 0.22 | H18: 0.04 | I18: 0.23 | J18: Post-money $1.2B (user input); ~0.9x sales on >$1.3B (AIST) | P18: 5 | Q18: 4 | R18: =AVERAGE(P18:Q18) -> 4.5 | S18: =F18+$R18*$Q$5 -> 0.1525 | T18: =G18+$R18*$Q$6 -> 0.256 | U18: =H18+$R18*$Q$7 -> 0.058 | V18: =I18+$R18*$Q$8 -> 0.257
A19: Superior & Grand Valley | B19: 400 | C19: 31 | D19: =C19/B19 -> 0.0775 | E19: Private forger — missile procurement metal forging; entry mark unverified (placeholder) | F19: 0.13 | G19: 0.21 | H19: 0.03 | I19: 0.22 | J19: PLACEHOLDER — no disclosed mark | P19: 5 | Q19: 4 | R19: =AVERAGE(P19:Q19) -> 4.5 | S19: =F19+$R19*$Q$5 -> 0.1525 | T19: =G19+$R19*$Q$6 -> 0.246 | U19: =H19+$R19*$Q$7 -> 0.048 | V19: =I19+$R19*$Q$8 -> 0.247
A20: Applied Research Assoc. | B20: 1200 | C20: 40 | D20: =C20/B20 -> 0.033333333 | E20: EMPLOYEE-OWNED ESOP — structural, hard | F20: 0.14 | G20: 0.22 | H20: 0.06 | I20: 0.24 | J20: Est. EV (~$700M+ rev R&D) | P20: 3 | Q20: 2 | R20: =AVERAGE(P20:Q20) -> 2.5 | S20: =F20+$R20*$Q$5 -> 0.1525 | T20: =G20+$R20*$Q$6 -> 0.24 | U20: =H20+$R20*$Q$7 -> 0.07 | V20: =I20+$R20*$Q$8 -> 0.255
A21: Faxon Machining | B21: ='Faxon Build'!$B$6 -> 92 | C21: ='Faxon Build'!$B$7 -> 9 | D21: =C21/B21 -> 0.097826087 | E21: PRIVATE — CBI sub; ~9.8% minority; warhead-case & missile machining: BLU-136/B, GBU-57 MOP, NGP GBU-76/B, TLAM, LPWC IDIQ; BLU-136 order period ends 30-Sep-26 | F21: ='Faxon Build'!C$97-$R21*$Q$5 -> 0.14670281 | G21: ='Faxon Build'!D$97-$R21*$Q$6 -> 0.29419484 | H21: ='Faxon Build'!E$97-$R21*$Q$7 -> -0.094799895 | I21: ='Faxon Build'!F$97-$R21*$Q$8 -> 0.30205133 | J21: Post-money $92M (user input); contract-derived prob-wtd EV — see Faxon Build | P21: 5 | Q21: 4 | R21: =AVERAGE(P21:Q21) -> 4.5 | S21: =F21+$R21*$Q$5 -> 0.16920281 | T21: =G21+$R21*$Q$6 -> 0.33019484 | U21: =H21+$R21*$Q$7 -> -0.076799895 | V21: =I21+$R21*$Q$8 -> 0.32905133
A22: TOTAL (=$390M) | C22: =SUM(C12:C21) -> 390
A24: 5-YEAR HOLD — GROSS PROCEEDS
A25: Company | B25: Check ($M) | C25: Base $ | D25: Base MOIC | E25: Base IRR | F25: Bull $ | G25: Bull MOIC | H25: Bull IRR | I25: Bear $ | J25: Bear MOIC | K25: Bear IRR | L25: Shock $ | M25: Shock MOIC | N25: Shock IRR
A26: =A12 -> Saronic | B26: =C12 -> 70 | C26: =B26*(1+S12)^5*'Weapons Sleeve'!$B$6 -> 214.86952 | D26: =C26/B26 -> 3.0695646 | E26: =(C26/B26)^(1/5)-1 -> 0.25145534 | F26: =B26*(1+T12)^5*'Weapons Sleeve'!$B$6 -> 371.81558 | G26: =F26/B26 -> 5.3116512 | H26: =(F26/B26)^(1/5)-1 -> 0.39651598 | I26: =B26*(1+U12)^5*'Weapons Sleeve'!$B$6 -> 67.685047 | J26: =I26/B26 -> 0.96692925 | K26: =(I26/B26)^(1/5)-1 -> -0.0067034221 | L26: =B26*(1+V12)^5*'Weapons Sleeve'!$B$6 -> 340.2177 | M26: =L26/B26 -> 4.8602529 | N26: =(L26/B26)^(1/5)-1 -> 0.37192943
A27: =A13 -> Epirus | B27: =C13 -> 45 | C27: =B27*(1+S13)^5*'Weapons Sleeve'!$B$6 -> 128.88992 | D27: =C27/B27 -> 2.8642206 | E27: =(C27/B27)^(1/5)-1 -> 0.23424476 | F27: =B27*(1+T13)^5*'Weapons Sleeve'!$B$6 -> 225.85821 | G27: =F27/B27 -> 5.0190713 | H27: =(F27/B27)^(1/5)-1 -> 0.38078059 | I27: =B27*(1+U13)^5*'Weapons Sleeve'!$B$6 -> 39.770285 | J27: =I27/B27 -> 0.88378411 | K27: =(I27/B27)^(1/5)-1 -> -0.024405737 | L27: =B27*(1+V13)^5*'Weapons Sleeve'!$B$6 -> 237.34577 | M27: =L27/B27 -> 5.2743504 | N27: =(L27/B27)^(1/5)-1 -> 0.39454906
A28: =A14 -> Israel Aerospace Ind. | B28: =C14 -> 40 | C28: =B28*(1+S14)^5*'Weapons Sleeve'!$B$6 -> 89.678295 | D28: =C28/B28 -> 2.2419574 | E28: =(C28/B28)^(1/5)-1 -> 0.17523704 | F28: =B28*(1+T14)^5*'Weapons Sleeve'!$B$6 -> 147.47468 | G28: =F28/B28 -> 3.6868671 | H28: =(F28/B28)^(1/5)-1 -> 0.29816978 | I28: =B28*(1+U14)^5*'Weapons Sleeve'!$B$6 -> 54.071273 | J28: =I28/B28 -> 1.3517818 | K28: =(I28/B28)^(1/5)-1 -> 0.062138915 | L28: =B28*(1+V14)^5*'Weapons Sleeve'!$B$6 -> 141.97252 | M28: =L28/B28 -> 3.549313 | N28: =(L28/B28)^(1/5)-1 -> 0.28833517
A29: =A15 -> Elta Systems | B29: =C15 -> 30 | C29: =B29*(1+S15)^5*'Weapons Sleeve'!$B$6 -> 61.815646 | D29: =C29/B29 -> 2.0605215 | E29: =(C29/B29)^(1/5)-1 -> 0.1555678 | F29: =B29*(1+T15)^5*'Weapons Sleeve'!$B$6 -> 96.323932 | G29: =F29/B29 -> 3.2107977 | H29: =(F29/B29)^(1/5)-1 -> 0.26276515 | I29: =B29*(1+U15)^5*'Weapons Sleeve'!$B$6 -> 37.284787 | J29: =I29/B29 -> 1.2428262 | K29: =(I29/B29)^(1/5)-1 -> 0.0444366 | L29: =B29*(1+V15)^5*'Weapons Sleeve'!$B$6 -> 101.69101 | M29: =L29/B29 -> 3.3897002 | N29: =(L29/B29)^(1/5)-1 -> 0.27653362
A30: =A16 -> Heckler & Koch | B30: =C16 -> 35 | C30: =B30*(1+S16)^5*'Weapons Sleeve'!$B$6 -> 60.650611 | D30: =C30/B30 -> 1.7328746 | E30: =(C30/B30)^(1/5)-1 -> 0.11622932 | F30: =B30*(1+T16)^5*'Weapons Sleeve'!$B$6 -> 88.463264 | G30: =F30/B30 -> 2.5275218 | H30: =(F30/B30)^(1/5)-1 -> 0.20375744 | I30: =B30*(1+U16)^5*'Weapons Sleeve'!$B$6 -> 41.489153 | J30: =I30/B30 -> 1.1854044 | K30: =(I30/B30)^(1/5)-1 -> 0.03460198 | L30: =B30*(1+V16)^5*'Weapons Sleeve'!$B$6 -> 93.639502 | M30: =L30/B30 -> 2.6754143 | N30: =(L30/B30)^(1/5)-1 -> 0.2175259
A31: =A17 -> Helicon Chemical | B31: =C17 -> 40 | C31: =B31*(1+S17)^5*'Weapons Sleeve'!$B$6 -> 136.63582 | D31: =C31/B31 -> 3.4158956 | E31: =(C31/B31)^(1/5)-1 -> 0.27850055 | F31: =B31*(1+T17)^5*'Weapons Sleeve'!$B$6 -> 254.32372 | G31: =F31/B31 -> 6.358093 | H31: =(F31/B31)^(1/5)-1 -> 0.447656 | I31: =B31*(1+U17)^5*'Weapons Sleeve'!$B$6 -> 43.918409 | J31: =I31/B31 -> 1.0979602 | K31: =(I31/B31)^(1/5)-1 -> 0.018866589 | L31: =B31*(1+V17)^5*'Weapons Sleeve'!$B$6 -> 264.86058 | M31: =L31/B31 -> 6.6215145 | N31: =(L31/B31)^(1/5)-1 -> 0.45945755
A32: =A18 -> The Ellwood Group | B32: =C18 -> 50 | C32: =B32*(1+S18)^5*'Weapons Sleeve'!$B$6 -> 93.532491 | D32: =C32/B32 -> 1.8706498 | E32: =(C32/B32)^(1/5)-1 -> 0.13343991 | F32: =B32*(1+T18)^5*'Weapons Sleeve'!$B$6 -> 143.7825 | G32: =F32/B32 -> 2.87565 | H32: =(F32/B32)^(1/5)-1 -> 0.23522822 | I32: =B32*(1+U18)^5*'Weapons Sleeve'!$B$6 -> 60.979825 | J32: =I32/B32 -> 1.2195965 | K32: =(I32/B32)^(1/5)-1 -> 0.040502752 | L32: =B32*(1+V18)^5*'Weapons Sleeve'!$B$6 -> 144.35579 | M32: =L32/B32 -> 2.8871159 | N32: =(L32/B32)^(1/5)-1 -> 0.23621168
A33: =A19 -> Superior & Grand Valley | B33: =C19 -> 31 | C33: =B33*(1+S19)^5*'Weapons Sleeve'!$B$6 -> 57.990145 | D33: =C33/B33 -> 1.8706498 | E33: =(C33/B33)^(1/5)-1 -> 0.13343991 | F33: =B33*(1+T19)^5*'Weapons Sleeve'!$B$6 -> 85.652439 | G33: =F33/B33 -> 2.7629819 | H33: =(F33/B33)^(1/5)-1 -> 0.2253936 | I33: =B33*(1+U19)^5*'Weapons Sleeve'!$B$6 -> 36.054206 | J33: =I33/B33 -> 1.1630389 | K33: =(I33/B33)^(1/5)-1 -> 0.030668132 | L33: =B33*(1+V19)^5*'Weapons Sleeve'!$B$6 -> 85.9967 | M33: =L33/B33 -> 2.7740871 | N33: =(L33/B33)^(1/5)-1 -> 0.22637706
A34: =A20 -> Applied Research Assoc. | B34: =C20 -> 40 | C34: =B34*(1+S20)^5*'Weapons Sleeve'!$B$6 -> 74.825993 | D34: =C34/B34 -> 1.8706498 | E34: =(C34/B34)^(1/5)-1 -> 0.13343991 | F34: =B34*(1+T20)^5*'Weapons Sleeve'!$B$6 -> 107.8838 | G34: =F34/B34 -> 2.6970951 | H34: =(F34/B34)^(1/5)-1 -> 0.21949283 | I34: =B34*(1+U20)^5*'Weapons Sleeve'!$B$6 -> 51.613904 | J34: =I34/B34 -> 1.2903476 | K34: =(I34/B34)^(1/5)-1 -> 0.052304295 | L34: =B34*(1+V20)^5*'Weapons Sleeve'!$B$6 -> 114.56882 | M34: =L34/B34 -> 2.8642206 | N34: =(L34/B34)^(1/5)-1 -> 0.23424476
A35: =A21 -> Faxon Machining | B35: =C21 -> 9 | C35: =B35*(1+S21)^5*'Weapons Sleeve'!$B$6 -> 18.091709 | D35: =C35/B35 -> 2.0101899 | E35: =(C35/B35)^(1/5)-1 -> 0.14986649 | F35: =B35*(1+T21)^5*'Weapons Sleeve'!$B$6 -> 34.483126 | G35: =F35/B35 -> 3.8314585 | H35: =(F35/B35)^(1/5)-1 -> 0.30819603 | I35: =B35*(1+U21)^5*'Weapons Sleeve'!$B$6 -> 5.5527684 | J35: =I35/B35 -> 0.61697427 | K35: =(I35/B35)^(1/5)-1 -> -0.092067817 | L35: =B35*(1+V21)^5*'Weapons Sleeve'!$B$6 -> 34.335163 | M35: =L35/B35 -> 3.8150181 | N35: =(L35/B35)^(1/5)-1 -> 0.30707142
A36: SLEEVE TOTAL | B36: =SUM(B26:B35) -> 390 | C36: =SUM(C26:C35) -> 936.98016 | D36: =C36/B36 -> 2.4025132 | E36: =(C36/B36)^(1/5)-1 -> 0.19160731 | F36: =SUM(F26:F35) -> 1556.0613 | G36: =F36/B36 -> 3.9899007 | H36: =(F36/B36)^(1/5)-1 -> 0.31884093 | I36: =SUM(I26:I35) -> 438.41966 | J36: =I36/B36 -> 1.124153 | K36: =(I36/B36)^(1/5)-1 -> 0.023682036 | L36: =SUM(L26:L35) -> 1558.9836 | M36: =L36/B36 -> 3.9973937 | N36: =(L36/B36)^(1/5)-1 -> 0.31933592
A39: 7-YEAR HOLD — GROSS PROCEEDS
A40: Company | B40: Check ($M) | C40: Base $ | D40: Base MOIC | E40: Base IRR | F40: Bull $ | G40: Bull MOIC | H40: Bull IRR | I40: Bear $ | J40: Bear MOIC | K40: Bear IRR | L40: Shock $ | M40: Shock MOIC | N40: Shock IRR
A41: =A12 -> Saronic | B41: =C12 -> 70 | C41: =B41*(1+S12)^7*'Weapons Sleeve'!$B$7 -> 332.80148 | D41: =C41/B41 -> 4.7543069 | E41: =(C41/B41)^(1/7)-1 -> 0.24947262 | F41: =B41*(1+T12)^7*'Weapons Sleeve'!$B$7 -> 717.13203 | G41: =F41/B41 -> 10.244743 | H41: =(F41/B41)^(1/7)-1 -> 0.39430344 | I41: =B41*(1+U12)^7*'Weapons Sleeve'!$B$7 -> 66.043538 | J41: =I41/B41 -> 0.94347911 | K41: =(I41/B41)^(1/7)-1 -> -0.0082771337 | L41: =B41*(1+V12)^7*'Weapons Sleeve'!$B$7 -> 633.28641 | M41: =L41/B41 -> 9.0469487 | N41: =(L41/B41)^(1/7)-1 -> 0.36975584
A42: =A13 -> Epirus | B42: =C13 -> 45 | C42: =B42*(1+S13)^7*'Weapons Sleeve'!$B$7 -> 194.17856 | D42: =C42/B42 -> 4.315079 | E42: =(C42/B42)^(1/7)-1 -> 0.2322893 | F42: =B42*(1+T13)^7*'Weapons Sleeve'!$B$7 -> 425.85813 | G42: =F42/B42 -> 9.463514 | H42: =(F42/B42)^(1/7)-1 -> 0.37859297 | I42: =B42*(1+U13)^7*'Weapons Sleeve'!$B$7 -> 37.434918 | J42: =I42/B42 -> 0.83188708 | K42: =(I42/B42)^(1/7)-1 -> -0.025951403 | L42: =B42*(1+V13)^7*'Weapons Sleeve'!$B$7 -> 456.48741 | M42: =L42/B42 -> 10.144165 | N42: =(L42/B42)^(1/7)-1 -> 0.39233963
A43: =A14 -> Israel Aerospace Ind. | B43: =C14 -> 40 | C43: =B43*(1+S14)^7*'Weapons Sleeve'!$B$7 -> 122.4949 | D43: =C43/B43 -> 3.0623725 | E43: =(C43/B43)^(1/7)-1 -> 0.17337507 | F43: =B43*(1+T14)^7*'Weapons Sleeve'!$B$7 -> 245.78772 | G43: =F43/B43 -> 6.144693 | H43: =(F43/B43)^(1/7)-1 -> 0.29611305 | I43: =B43*(1+U14)^7*'Weapons Sleeve'!$B$7 -> 60.326614 | J43: =I43/B43 -> 1.5081654 | K43: =(I43/B43)^(1/7)-1 -> 0.060456134 | L43: =B43*(1+V14)^7*'Weapons Sleeve'!$B$7 -> 233.04604 | M43: =L43/B43 -> 5.8261511 | N43: =(L43/B43)^(1/7)-1 -> 0.28629401
A44: =A15 -> Elta Systems | B44: =C15 -> 30 | C44: =B44*(1+S15)^7*'Weapons Sleeve'!$B$7 -> 81.633608 | D44: =C44/B44 -> 2.7211203 | E44: =(C44/B44)^(1/7)-1 -> 0.153737 | F44: =B44*(1+T15)^7*'Weapons Sleeve'!$B$7 -> 151.90046 | G44: =F44/B44 -> 5.0633487 | H44: =(F44/B44)^(1/7)-1 -> 0.26076452 | I44: =B44*(1+U15)^7*'Weapons Sleeve'!$B$7 -> 40.223101 | J44: =I44/B44 -> 1.34077 | K44: =(I44/B44)^(1/7)-1 -> 0.042781865 | L44: =B44*(1+V15)^7*'Weapons Sleeve'!$B$7 -> 163.88031 | M44: =L44/B44 -> 5.462677 | N44: =(L44/B44)^(1/7)-1 -> 0.27451117
A45: =A16 -> Heckler & Koch | B45: =C16 -> 35 | C45: =B45*(1+S16)^7*'Weapons Sleeve'!$B$7 -> 74.734606 | D45: =C45/B45 -> 2.1352744 | E45: =(C45/B45)^(1/7)-1 -> 0.11446084 | F45: =B45*(1+T16)^7*'Weapons Sleeve'!$B$7 -> 126.77121 | G45: =F45/B45 -> 3.6220346 | H45: =(F45/B45)^(1/7)-1 -> 0.20185029 | I45: =B45*(1+U16)^7*'Weapons Sleeve'!$B$7 -> 43.919855 | J45: =I45/B45 -> 1.254853 | K45: =(I45/B45)^(1/7)-1 -> 0.032962827 | L45: =B45*(1+V16)^7*'Weapons Sleeve'!$B$7 -> 137.27619 | M45: =L45/B45 -> 3.922177 | N45: =(L45/B45)^(1/7)-1 -> 0.21559694
A46: =A17 -> Helicon Chemical | B46: =C17 -> 40 | C46: =B46*(1+S17)^7*'Weapons Sleeve'!$B$7 -> 220.87478 | D46: =C46/B46 -> 5.5218695 | E46: =(C46/B46)^(1/7)-1 -> 0.27647498 | F46: =B46*(1+T17)^7*'Weapons Sleeve'!$B$7 -> 527.10524 | G46: =F46/B46 -> 13.177631 | H46: =(F46/B46)^(1/7)-1 -> 0.44536243 | I46: =B46*(1+U17)^7*'Weapons Sleeve'!$B$7 -> 45.087998 | J46: =I46/B46 -> 1.1271999 | K46: =(I46/B46)^(1/7)-1 -> 0.017252366 | L46: =B46*(1+V17)^7*'Weapons Sleeve'!$B$7 -> 557.93033 | M46: =L46/B46 -> 13.948258 | N46: =(L46/B46)^(1/7)-1 -> 0.45714528
A47: =A18 -> The Ellwood Group | B47: =C18 -> 50 | C47: =B47*(1+S18)^7*'Weapons Sleeve'!$B$7 -> 118.83359 | D47: =C47/B47 -> 2.3766718 | E47: =(C47/B47)^(1/7)-1 -> 0.13164416 | F47: =B47*(1+T18)^7*'Weapons Sleeve'!$B$7 -> 216.96024 | G47: =F47/B47 -> 4.3392048 | H47: =(F47/B47)^(1/7)-1 -> 0.23327121 | I47: =B47*(1+U18)^7*'Weapons Sleeve'!$B$7 -> 65.290854 | J47: =I47/B47 -> 1.3058171 | K47: =(I47/B47)^(1/7)-1 -> 0.03885425 | L47: =B47*(1+V18)^7*'Weapons Sleeve'!$B$7 -> 218.17231 | M47: =L47/B47 -> 4.3634461 | N47: =(L47/B47)^(1/7)-1 -> 0.23425311
A48: =A19 -> Superior & Grand Valley | B48: =C19 -> 31 | C48: =B48*(1+S19)^7*'Weapons Sleeve'!$B$7 -> 73.676825 | D48: =C48/B48 -> 2.3766718 | E48: =(C48/B48)^(1/7)-1 -> 0.13164416 | F48: =B48*(1+T19)^7*'Weapons Sleeve'!$B$7 -> 127.19518 | G48: =F48/B48 -> 4.1030704 | H48: =(F48/B48)^(1/7)-1 -> 0.22345217 | I48: =B48*(1+U19)^7*'Weapons Sleeve'!$B$7 -> 37.876806 | J48: =I48/B48 -> 1.2218324 | K48: =(I48/B48)^(1/7)-1 -> 0.029035212 | L48: =B48*(1+V19)^7*'Weapons Sleeve'!$B$7 -> 127.91148 | M48: =L48/B48 -> 4.1261769 | N48: =(L48/B48)^(1/7)-1 -> 0.22443407
A49: =A20 -> Applied Research Assoc. | B49: =C20 -> 40 | C49: =B49*(1+S20)^7*'Weapons Sleeve'!$B$7 -> 95.066871 | D49: =C49/B49 -> 2.3766718 | E49: =(C49/B49)^(1/7)-1 -> 0.13164416 | F49: =B49*(1+T20)^7*'Weapons Sleeve'!$B$7 -> 158.66987 | G49: =F49/B49 -> 3.9667467 | H49: =(F49/B49)^(1/7)-1 -> 0.21756075 | I49: =B49*(1+U20)^7*'Weapons Sleeve'!$B$7 -> 56.523508 | J49: =I49/B49 -> 1.4130877 | K49: =(I49/B49)^(1/7)-1 -> 0.050637096 | L49: =B49*(1+V20)^7*'Weapons Sleeve'!$B$7 -> 172.60316 | M49: =L49/B49 -> 4.315079 | N49: =(L49/B49)^(1/7)-1 -> 0.2322893
A50: =A21 -> Faxon Machining | B50: =C21 -> 9 | C50: =B50*(1+S21)^7*'Weapons Sleeve'!$B$7 -> 23.656699 | D50: =C50/B50 -> 2.6285221 | E50: =(C50/B50)^(1/7)-1 -> 0.14804472 | F50: =B50*(1+T21)^7*'Weapons Sleeve'!$B$7 -> 58.362246 | G50: =F50/B50 -> 6.484694 | H50: =(F50/B50)^(1/7)-1 -> 0.30612341 | I50: =B50*(1+U21)^7*'Weapons Sleeve'!$B$7 -> 4.5268499 | J50: =I50/B50 -> 0.50298333 | K50: =(I50/B50)^(1/7)-1 -> -0.093506283 | L50: =B50*(1+V21)^7*'Weapons Sleeve'!$B$7 -> 58.01195 | M50: =L50/B50 -> 6.4457722 | N50: =(L50/B50)^(1/7)-1 -> 0.30500059
A51: SLEEVE TOTAL | B51: =SUM(B41:B50) -> 390 | C51: =SUM(C41:C50) -> 1337.9519 | D51: =C51/B51 -> 3.4306459 | E51: =(C51/B51)^(1/7)-1 -> 0.19256558 | F51: =SUM(F41:F50) -> 2755.7423 | G51: =F51/B51 -> 7.066006 | H51: =(F51/B51)^(1/7)-1 -> 0.32224085 | I51: =SUM(I41:I50) -> 457.25404 | J51: =I51/B51 -> 1.1724463 | K51: =(I51/B51)^(1/7)-1 -> 0.022987721 | L51: =SUM(L41:L50) -> 2758.6056 | M51: =L51/B51 -> 7.0733477 | N51: =(L51/B51)^(1/7)-1 -> 0.32243703
A54: 10-YEAR HOLD — GROSS PROCEEDS
A55: Company | B55: Check ($M) | C55: Base $ | D55: Base MOIC | E55: Base IRR | F55: Bull $ | G55: Bull MOIC | H55: Bull IRR | I55: Bear $ | J55: Bear MOIC | K55: Bear IRR | L55: Shock $ | M55: Shock MOIC | N55: Shock IRR
A56: =A12 -> Saronic | B56: =C12 -> 70 | C56: =B56*(1+S12)^10*'Weapons Sleeve'!$B$8 -> 638.98373 | D56: =C56/B56 -> 9.128339 | E56: =(C56/B56)^(1/10)-1 -> 0.24749604 | F56: =B56*(1+T12)^10*'Weapons Sleeve'!$B$8 -> 1913.354 | G56: =F56/B56 -> 27.333629 | H56: =(F56/B56)^(1/10)-1 -> 0.39209774 | I56: =B56*(1+U12)^10*'Weapons Sleeve'!$B$8 -> 63.40531 | J56: =I56/B56 -> 0.90579014 | K56: =(I56/B56)^(1/10)-1 -> -0.0098459709 | L56: =B56*(1+V12)^10*'Weapons Sleeve'!$B$8 -> 1601.9685 | M56: =L56/B56 -> 22.885264 | N56: =(L56/B56)^(1/10)-1 -> 0.36758898
A57: =A13 -> Epirus | B57: =C13 -> 45 | C57: =B57*(1+S13)^10*'Weapons Sleeve'!$B$8 -> 357.65444 | D57: =C57/B57 -> 7.9478765 | E57: =(C57/B57)^(1/10)-1 -> 0.23033991 | F57: =B57*(1+T13)^10*'Weapons Sleeve'!$B$8 -> 1098.2405 | G57: =F57/B57 -> 24.405344 | H57: =(F57/B57)^(1/10)-1 -> 0.37641214 | I57: =B57*(1+U13)^10*'Weapons Sleeve'!$B$8 -> 34.052036 | J57: =I57/B57 -> 0.75671192 | K57: =(I57/B57)^(1/10)-1 -> -0.02749228 | L57: =B57*(1+V13)^10*'Weapons Sleeve'!$B$8 -> 1212.7986 | M57: =L57/B57 -> 26.951079 | N57: =(L57/B57)^(1/10)-1 -> 0.39013704
A58: =A14 -> Israel Aerospace Ind. | B58: =C14 -> 40 | C58: =B58*(1+S14)^10*'Weapons Sleeve'!$B$8 -> 194.78383 | D58: =C58/B58 -> 4.8695957 | E58: =(C58/B58)^(1/10)-1 -> 0.17151888 | F58: =B58*(1+T14)^10*'Weapons Sleeve'!$B$8 -> 526.76044 | G58: =F58/B58 -> 13.169011 | H58: =(F58/B58)^(1/10)-1 -> 0.29406269 | I58: =B58*(1+U14)^10*'Weapons Sleeve'!$B$8 -> 70.81274 | J58: =I58/B58 -> 1.7703185 | K58: =(I58/B58)^(1/10)-1 -> 0.058778566 | L58: =B58*(1+V14)^10*'Weapons Sleeve'!$B$8 -> 488.18766 | M58: =L58/B58 -> 12.204692 | N58: =(L58/B58)^(1/10)-1 -> 0.28425919
A59: =A15 -> Elta Systems | B59: =C15 -> 30 | C59: =B59*(1+S15)^10*'Weapons Sleeve'!$B$8 -> 123.39961 | D59: =C59/B59 -> 4.1133202 | E59: =(C59/B59)^(1/10)-1 -> 0.15191187 | F59: =B59*(1+T15)^10*'Weapons Sleeve'!$B$8 -> 299.63003 | G59: =F59/B59 -> 9.9876678 | H59: =(F59/B59)^(1/10)-1 -> 0.25877007 | I59: =B59*(1+U15)^10*'Weapons Sleeve'!$B$8 -> 44.89317 | J59: =I59/B59 -> 1.496439 | K59: =(I59/B59)^(1/10)-1 -> 0.041132256 | L59: =B59*(1+V15)^10*'Weapons Sleeve'!$B$8 -> 333.95045 | M59: =L59/B59 -> 11.131682 | N59: =(L59/B59)^(1/10)-1 -> 0.27249498
A60: =A16 -> Heckler & Koch | B60: =C16 -> 35 | C60: =B60*(1+S16)^10*'Weapons Sleeve'!$B$8 -> 101.82174 | D60: =C60/B60 -> 2.9091926 | E60: =(C60/B60)^(1/10)-1 -> 0.11269784 | F60: =B60*(1+T16)^10*'Weapons Sleeve'!$B$8 -> 216.61876 | G60: =F60/B60 -> 6.1891076 | H60: =(F60/B60)^(1/10)-1 -> 0.19994904 | I60: =B60*(1+U16)^10*'Weapons Sleeve'!$B$8 -> 47.64741 | J60: =I60/B60 -> 1.3613546 | K60: =(I60/B60)^(1/10)-1 -> 0.031328751 | L60: =B60*(1+V16)^10*'Weapons Sleeve'!$B$8 -> 242.71038 | M60: =L60/B60 -> 6.9345822 | N60: =(L60/B60)^(1/10)-1 -> 0.21367395
A61: =A17 -> Helicon Chemical | B61: =C17 -> 40 | C61: =B61*(1+S17)^10*'Weapons Sleeve'!$B$8 -> 452.17585 | D61: =C61/B61 -> 11.304396 | E61: =(C61/B61)^(1/10)-1 -> 0.27445568 | F61: =B61*(1+T17)^10*'Weapons Sleeve'!$B$8 -> 1566.5777 | G61: =F61/B61 -> 39.164443 | H61: =(F61/B61)^(1/10)-1 -> 0.44307597 | I61: =B61*(1+U17)^10*'Weapons Sleeve'!$B$8 -> 46.716618 | J61: =I61/B61 -> 1.1679155 | K61: =(I61/B61)^(1/10)-1 -> 0.015643143 | L61: =B61*(1+V17)^10*'Weapons Sleeve'!$B$8 -> 1699.0762 | M61: =L61/B61 -> 42.476905 | N61: =(L61/B61)^(1/10)-1 -> 0.45484018
A62: =A18 -> The Ellwood Group | B62: =C18 -> 50 | C62: =B62*(1+S18)^10*'Weapons Sleeve'!$B$8 -> 169.50917 | D62: =C62/B62 -> 3.3901834 | E62: =(C62/B62)^(1/10)-1 -> 0.12985398 | F62: =B62*(1+T18)^10*'Weapons Sleeve'!$B$8 -> 400.57169 | G62: =F62/B62 -> 8.0114338 | H62: =(F62/B62)^(1/10)-1 -> 0.23132026 | I62: =B62*(1+U18)^10*'Weapons Sleeve'!$B$8 -> 72.051086 | J62: =I62/B62 -> 1.4410217 | K62: =(I62/B62)^(1/10)-1 -> 0.037210854 | L62: =B62*(1+V18)^10*'Weapons Sleeve'!$B$8 -> 403.7724 | M62: =L62/B62 -> 8.0754481 | N62: =(L62/B62)^(1/10)-1 -> 0.23230061
A63: =A19 -> Superior & Grand Valley | B63: =C19 -> 31 | C63: =B63*(1+S19)^10*'Weapons Sleeve'!$B$8 -> 105.09569 | D63: =C63/B63 -> 3.3901834 | E63: =(C63/B63)^(1/10)-1 -> 0.12985398 | F63: =B63*(1+T19)^10*'Weapons Sleeve'!$B$8 -> 229.27461 | G63: =F63/B63 -> 7.3959553 | H63: =(F63/B63)^(1/10)-1 -> 0.22151675 | I63: =B63*(1+U19)^10*'Weapons Sleeve'!$B$8 -> 40.624532 | J63: =I63/B63 -> 1.3104688 | K63: =(I63/B63)^(1/10)-1 -> 0.027407349 | L63: =B63*(1+V19)^10*'Weapons Sleeve'!$B$8 -> 231.12136 | M63: =L63/B63 -> 7.4555277 | N63: =(L63/B63)^(1/10)-1 -> 0.2224971
A64: =A20 -> Applied Research Assoc. | B64: =C20 -> 40 | C64: =B64*(1+S20)^10*'Weapons Sleeve'!$B$8 -> 135.60734 | D64: =C64/B64 -> 3.3901834 | E64: =(C64/B64)^(1/10)-1 -> 0.12985398 | F64: =B64*(1+T20)^10*'Weapons Sleeve'!$B$8 -> 281.89716 | G64: =F64/B64 -> 7.0474289 | H64: =(F64/B64)^(1/10)-1 -> 0.21563465 | I64: =B64*(1+U20)^10*'Weapons Sleeve'!$B$8 -> 64.522565 | J64: =I64/B64 -> 1.6130641 | K64: =(I64/B64)^(1/10)-1 -> 0.048975061 | L64: =B64*(1+V20)^10*'Weapons Sleeve'!$B$8 -> 317.91506 | M64: =L64/B64 -> 7.9478765 | N64: =(L64/B64)^(1/10)-1 -> 0.23033991
A65: =A21 -> Faxon Machining | B65: =C21 -> 9 | C65: =B65*(1+S21)^10*'Weapons Sleeve'!$B$8 -> 35.233427 | D65: =C65/B65 -> 3.9148252 | E65: =(C65/B65)^(1/10)-1 -> 0.14622859 | F65: =B65*(1+T21)^10*'Weapons Sleeve'!$B$8 -> 127.9997 | G65: =F65/B65 -> 14.222189 | H65: =(F65/B65)^(1/10)-1 -> 0.30405721 | I65: =B65*(1+U21)^10*'Weapons Sleeve'!$B$8 -> 3.3190578 | J65: =I65/B65 -> 0.3687842 | K65: =(I65/B65)^(1/10)-1 -> -0.094940294 | L65: =B65*(1+V21)^10*'Weapons Sleeve'!$B$8 -> 126.90359 | M65: =L65/B65 -> 14.100399 | N65: =(L65/B65)^(1/10)-1 -> 0.30293617
A66: SLEEVE TOTAL | B66: =SUM(B56:B65) -> 390 | C66: =SUM(C56:C65) -> 2314.2648 | D66: =C66/B66 -> 5.9340124 | E66: =(C66/B66)^(1/10)-1 -> 0.19490903 | F66: =SUM(F56:F65) -> 6660.9246 | G66: =F66/B66 -> 17.079294 | H66: =(F66/B66)^(1/10)-1 -> 0.32814959 | I66: =SUM(I56:I65) -> 488.04453 | J66: =I66/B66 -> 1.2513962 | K66: =(I66/B66)^(1/10)-1 -> 0.022679343 | L66: =SUM(L56:L65) -> 6658.4041 | M66: =L66/B66 -> 17.072831 | N66: =(L66/B66)^(1/10)-1 -> 0.32809932

Sheet Faxon Build
A1: FAXON MACHINING — PROGRAM-LEVEL STAKE BUILD ($9M @ $92M POST)
A2: Weapons-sleeve holding #10. Revenue is built by program — BLU-136/B, GBU-57 MOP, NGP GBU-76/B, Tomahawk (TLAM), penetrator IDIQ, FMS — each tied to a defense-supercycle driver. NGP carries an explicit production-award step. Blue = input; green = link; black = formula. USD $M. 7-yr implied equity CAGR feeds Weapons Sleeve row 21.
A4: DEAL TERMS & ENTRY
A5: Item | B5: Value | C5: Source / basis
A6: Entry post-money valuation ($M) | B6: 92 | C6: User input (IC, 9/2026). Probability-weighted EV from contract-derived valuation: Bear $21M / Base $76M / Bull $194M at 25/50/25.
A7: Check size ($M) | B7: 9 | C7: User input: sub-$10M minority stake. Funded inside the fixed $390M sleeve by trimming Superior & Grand Valley $40M -> $31M.
A8: Ownership % | B8: =B7/B6 -> 0.097826087 | C8: Check / post-money.
A9: Net debt at entry ($M) | B9: 0 | C9: Assumed debt-free (private, CBI-owned). Confirm in diligence.
A10: FY26E revenue ($M) | B10: =B37 -> 60 | C10: Sum of program build below (contract-derived; aggregator figure of ~$21M judged stale vs $473M BLU-136/B award).
A11: FY26E EBITDA margin | B11: 0.14 | C11: Estimate — FFP high-volume case machining; 10-18% range for defense precision machining.
A12: FY26E EBITDA ($M) | B12: =B10*B11 -> 8.4 | C12: Revenue x margin.
A13: Implied entry EV / EBITDA | B13: =(B6+B9)/B12 -> 10.952381 | C13: Entry multiple implied by the $92M mark.
A14: FCF conversion (% of EBITDA retained as cash) | B14: 0.45 | C14: After tax and growth capex (large-case machining / deep-hole capacity for MOP & NGP); retained on balance sheet, no dividends.
A15: Margin ramp period (yrs) | B15: 5 | C15: EBITDA margin moves linearly from FY26E to scenario exit margin over this many years.
A17: SUPERCYCLE DRIVERS — ANNUAL PROGRAM / END-MARKET GROWTH BY SCENARIO (blue = lever)
A18: Driver | B18: Base | C18: Bull | D18: Bear | E18: TSMC-Shock | F18: Basis / evidence
A19: 1 US munitions procurement (bomb bodies / area-attack) | B19: 0.06 | C19: 0.12 | D19: -0.02 | E19: 0.14 | F19: Stockpile replenishment after 2025-26 Iran strikes; multiyear munitions buys.
A20: 2 TLAM production ramp (Tomahawk MYP) | B20: 0.2 | C20: 0.28 | D20: 0.06 | E20: 0.3 | F20: RTX $22.9B 7-yr Tomahawk multiyear to 1,000+/yr (Manufacturing Dive / Armada, Aug-26): ~4x from low-hundreds/yr => ~20%+/yr over 7 yrs.
A21: 3 Other missile production (SM-6 / PAC-3 / PrSM) | B21: 0.12 | C21: 0.2 | D21: 0.03 | E21: 0.22 | F21: Multiyear missile procurement; tier-2 deep-hole & flowform content.
A22: 4 GBU-57 MOP replenishment | B22: 0.15 | C22: 0.25 | D22: 0 | E22: 0.3 | F22: USAF buying more bunker busters after Iran nuclear strikes (Defense News, 13-Feb-26); MOP bridges to NGP.
A23: 5 NGP GBU-76/B development / LRIP | B23: 0.1 | C23: 0.15 | D23: 0 | E23: 0.15 | F23: ARA system design agent (Sep-25, 24-mo); full-scale static tests FY26; GBU-76/B production sources-sought 1-Jun-26. Production step modeled separately below.
A24: 6 FMS / allied export demand | B24: 0.1 | C24: 0.18 | D24: 0 | E24: 0.2 | F24: Record FMS (FY24 $117.9B per CRS IF11437); TLAM export buyers (Japan, Australia, Netherlands, UK); Israel / NATO replenishment.
A25: 7 Commercial & other defense industrial | B25: 0.03 | C25: 0.05 | D25: -0.02 | E25: 0.01 | F25: GD / L3Harris / Northrop / Lockheed machining work, vehicle and firearm components.
A27: PROGRAM REVENUE — FY26E BASE & PROGRAM CAGR = DRIVER GROWTH + SHARE GAIN
A28: Program / segment | B28: FY26E rev ($M) | C28: Driver # | D28: Share gain Base | E28: Share gain Bull | F28: Share gain Bear | G28: Share gain Shock | H28: CAGR Base | I28: CAGR Bull | J28: CAGR Bear | K28: CAGR Shock | L28: % FY26E | M28: Basis
A29: BLU-136/B area-attack warhead cases (USAF) | B29: 30 | C29: 1 | D29: 0 | E29: 0.03 | F29: -0.08 | G29: 0.03 | H29: =INDEX(B$19:B$25,$C29)+D29 -> 0.06 | I29: =INDEX(C$19:C$25,$C29)+E29 -> 0.15 | J29: =INDEX(D$19:D$25,$C29)+F29 -> -0.1 | K29: =INDEX(E$19:E$25,$C29)+G29 -> 0.17 | L29: =B29/$B$37 -> 0.5 | M29: $473M BLU-136/B bomb bodies & containers (Local12); order period ends 30-Sep-26 -> Bear = partial loss on recompete.
A30: GBU-57 MOP penetrator case machining | B30: 4 | C30: 4 | D30: 0.02 | E30: 0.04 | F30: -0.02 | G30: 0.04 | H30: =INDEX(B$19:B$25,$C30)+D30 -> 0.17 | I30: =INDEX(C$19:C$25,$C30)+E30 -> 0.29 | J30: =INDEX(D$19:D$25,$C30)+F30 -> -0.02 | K30: =INDEX(E$19:E$25,$C30)+G30 -> 0.34 | L30: =B30/$B$37 -> 0.066666667 | M30: MOP exposure per user (IC, 9/2026). Low-volume / high-value Eglin-steel cases; replenishment buy.
A31: NGP GBU-76/B prototype & dev cases | B31: 2 | C31: 5 | D31: 0 | E31: 0.02 | F31: -0.05 | G31: 0.02 | H31: =INDEX(B$19:B$25,$C31)+D31 -> 0.1 | I31: =INDEX(C$19:C$25,$C31)+E31 -> 0.17 | J31: =INDEX(D$19:D$25,$C31)+F31 -> -0.05 | K31: =INDEX(E$19:E$25,$C31)+G31 -> 0.17 | L31: =B31/$B$37 -> 0.033333333 | M31: NGP exposure per user (IC, 9/2026). Sub-scale / full-scale prototype cases; production phase in NGP step below.
A32: Tomahawk (TLAM) components | B32: 7 | C32: 2 | D32: 0 | E32: 0.02 | F32: -0.02 | G32: 0.02 | H32: =INDEX(B$19:B$25,$C32)+D32 -> 0.2 | I32: =INDEX(C$19:C$25,$C32)+E32 -> 0.3 | J32: =INDEX(D$19:D$25,$C32)+F32 -> 0.04 | K32: =INDEX(E$19:E$25,$C32)+G32 -> 0.32 | L32: =B32/$B$37 -> 0.11666667 | M32: TLAM exposure per user (IC, 9/2026); part scope to confirm in diligence (not in public contract data). Tracks Tomahawk ramp.
A33: Other penetrators — LPWC IDIQ (BLU-137 / BLU-109) | B33: 3 | C33: 1 | D33: 0.05 | E33: 0.08 | F33: -0.02 | G33: 0.08 | H33: =INDEX(B$19:B$25,$C33)+D33 -> 0.11 | I33: =INDEX(C$19:C$25,$C33)+E33 -> 0.2 | J33: =INDEX(D$19:D$25,$C33)+F33 -> -0.04 | K33: =INDEX(E$19:E$25,$C33)+G33 -> 0.22 | L33: =B33/$B$37 -> 0.05 | M33: 1 of 4 awardees on $149M large penetrator warhead case IDIQ (Defence Blog, 2026).
A34: Other missile structures / flowform (tier-2) | B34: 3 | C34: 3 | D34: 0.02 | E34: 0.04 | F34: -0.02 | G34: 0.04 | H34: =INDEX(B$19:B$25,$C34)+D34 -> 0.14 | I34: =INDEX(C$19:C$25,$C34)+E34 -> 0.24 | J34: =INDEX(D$19:D$25,$C34)+F34 -> 0.01 | K34: =INDEX(E$19:E$25,$C34)+G34 -> 0.26 | L34: =B34/$B$37 -> 0.05 | M34: Precision machining for primes; sister co. American Flowform (ex-ATI).
A35: FMS / allied export pull-through | B35: 4 | C35: 6 | D35: 0.02 | E35: 0.04 | F35: 0 | G35: 0.03 | H35: =INDEX(B$19:B$25,$C35)+D35 -> 0.12 | I35: =INDEX(C$19:C$25,$C35)+E35 -> 0.22 | J35: =INDEX(D$19:D$25,$C35)+F35 -> 0 | K35: =INDEX(E$19:E$25,$C35)+G35 -> 0.23 | L35: =B35/$B$37 -> 0.066666667 | M35: Allied buys of US bomb bodies / warheads routed via FMS.
A36: Commercial & other defense | B36: 7 | C36: 7 | D36: 0 | E36: 0.01 | F36: 0 | G36: 0 | H36: =INDEX(B$19:B$25,$C36)+D36 -> 0.03 | I36: =INDEX(C$19:C$25,$C36)+E36 -> 0.06 | J36: =INDEX(D$19:D$25,$C36)+F36 -> -0.02 | K36: =INDEX(E$19:E$25,$C36)+G36 -> 0.01 | L36: =B36/$B$37 -> 0.11666667 | M36: Legacy contract machining (since 1978).
A37: TOTAL FY26E revenue / revenue-weighted program CAGR | B37: =SUM(B29:B36) -> 60 | H37: =SUMPRODUCT($B$29:$B$36,H29:H36)/$B$37 -> 0.092 | I37: =SUMPRODUCT($B$29:$B$36,I29:I36)/$B$37 -> 0.17866667 | J37: =SUMPRODUCT($B$29:$B$36,J29:J36)/$B$37 -> -0.052166667 | K37: =SUMPRODUCT($B$29:$B$36,K29:K36)/$B$37 -> 0.19116667 | L37: =SUM(L29:L36) -> 1
A38: Memo: NGP + MOP + TLAM share of FY26E revenue | L38: =SUM(L30:L32) -> 0.21666667
A40: NGP GBU-76/B PRODUCTION STEP — ADDED ON TOP OF PROGRAM CAGR
A41: Item | B41: Base | C41: Bull | D41: Bear | E41: TSMC-Shock | F41: Basis
A42: First production year for Faxon (t, years from FY26) | B42: 3 | C42: 2 | D42: 99 | E42: 2 | F42: Base: production award FY28, deliveries FY29 after FY26-27 test program. Bear 99 = no Faxon production share.
A43: Faxon full-rate NGP revenue ($M/yr) | B43: 12 | C43: 20 | D43: 0 | E43: 24 | F43: Case machining content at full rate; B-21 carriage implies larger quantities than MOP. Shock = wartime surge.
A44: Ramp to full rate (yrs) | B44: 2 | C44: 2 | D44: 2 | E44: 1 | F44: Linear ramp from first production year.
A46: EXIT ASSUMPTIONS BY SCENARIO
A47: Item | B47: Base | C47: Bull | D47: Bear | E47: TSMC-Shock | F47: Basis
A48: Exit EBITDA margin | B48: 0.16 | C48: 0.19 | D48: 0.11 | E48: 0.18 | F48: Operating leverage on volume; MOP/NGP large-case work carries premium pricing. Bear = under-absorbed capacity after BLU-136 step-down.
A49: Exit EV / EBITDA | B49: 11 | C49: 14 | D49: 7 | E49: 13 | F49: Base ~ entry multiple; Bull/Shock = scarcity premium (sole-/few-source MOP, NGP & TLAM content) to a prime / strategic; Bear = generic job-shop.
A51: PROJECTIONS — YEAR 0 (FY26E) TO YEAR 10, BY SCENARIO
A52: Year | B52: 0 | C52: 1 | D52: 2 | E52: 3 | F52: 4 | G52: 5 | H52: 6 | I52: 7 | J52: 8 | K52: 9 | L52: 10
A53: Year index (t) | B53: 0 | C53: 1 | D53: 2 | E53: 3 | F53: 4 | G53: 5 | H53: 6 | I53: 7 | J53: 8 | K53: 9 | L53: 10
A54: BASE
A55: Program revenue ex-NGP production ($M) | B55: =SUMPRODUCT($B$29:$B$36,(1+$H$29:$H$36)^B$53) -> 60 | C55: =SUMPRODUCT($B$29:$B$36,(1+$H$29:$H$36)^C$53) -> 65.52 | D55: =SUMPRODUCT($B$29:$B$36,(1+$H$29:$H$36)^D$53) -> 71.7226 | E55: =SUMPRODUCT($B$29:$B$36,(1+$H$29:$H$36)^E$53) -> 78.711258 | F55: =SUMPRODUCT($B$29:$B$36,(1+$H$29:$H$36)^F$53) -> 86.606988 | G55: =SUMPRODUCT($B$29:$B$36,(1+$H$29:$H$36)^G$53) -> 95.551523 | H55: =SUMPRODUCT($B$29:$B$36,(1+$H$29:$H$36)^H$53) -> 105.71106 | I55: =SUMPRODUCT($B$29:$B$36,(1+$H$29:$H$36)^I$53) -> 117.28071 | ... L55: =SUMPRODUCT($B$29:$B$36,(1+$H$29:$H$36)^L$53) -> 162.95312
A56: NGP production revenue ($M) | B56: =B$43*MIN(MAX(B$53-B$42+1,0)/B$44,1) -> 0 | C56: =B$43*MIN(MAX(C$53-B$42+1,0)/B$44,1) -> 0 | D56: =B$43*MIN(MAX(D$53-B$42+1,0)/B$44,1) -> 0 | E56: =B$43*MIN(MAX(E$53-B$42+1,0)/B$44,1) -> 6 | F56: =B$43*MIN(MAX(F$53-B$42+1,0)/B$44,1) -> 12 | G56: =B$43*MIN(MAX(G$53-B$42+1,0)/B$44,1) -> 12 | H56: =B$43*MIN(MAX(H$53-B$42+1,0)/B$44,1) -> 12 | I56: =B$43*MIN(MAX(I$53-B$42+1,0)/B$44,1) -> 12 | J56: =B$43*MIN(MAX(J$53-B$42+1,0)/B$44,1) -> 12 | K56: =B$43*MIN(MAX(K$53-B$42+1,0)/B$44,1) -> 12 | L56: =B$43*MIN(MAX(L$53-B$42+1,0)/B$44,1) -> 12
A57: Total revenue ($M) | B57: =B55+B56 -> 60 | C57: =C55+C56 -> 65.52 | D57: =D55+D56 -> 71.7226 | E57: =E55+E56 -> 84.711258 | F57: =F55+F56 -> 98.606988 | G57: =G55+G56 -> 107.55152 | H57: =H55+H56 -> 117.71106 | I57: =I55+I56 -> 129.28071 | ... L57: =L55+L56 -> 174.95312
A58: EBITDA margin | B58: =$B$11+(B$48-$B$11)*MIN(B$53/$B$15,1) -> 0.14 | C58: =$B$11+(B$48-$B$11)*MIN(C$53/$B$15,1) -> 0.144 | D58: =$B$11+(B$48-$B$11)*MIN(D$53/$B$15,1) -> 0.148 | E58: =$B$11+(B$48-$B$11)*MIN(E$53/$B$15,1) -> 0.152 | F58: =$B$11+(B$48-$B$11)*MIN(F$53/$B$15,1) -> 0.156 | G58: =$B$11+(B$48-$B$11)*MIN(G$53/$B$15,1) -> 0.16 | H58: =$B$11+(B$48-$B$11)*MIN(H$53/$B$15,1) -> 0.16 | I58: =$B$11+(B$48-$B$11)*MIN(I$53/$B$15,1) -> 0.16 | J58: =$B$11+(B$48-$B$11)*MIN(J$53/$B$15,1) -> 0.16 | K58: =$B$11+(B$48-$B$11)*MIN(K$53/$B$15,1) -> 0.16 | L58: =$B$11+(B$48-$B$11)*MIN(L$53/$B$15,1) -> 0.16
A59: EBITDA ($M) | B59: =B57*B58 -> 8.4 | C59: =C57*C58 -> 9.43488 | D59: =D57*D58 -> 10.614945 | E59: =E57*E58 -> 12.876111 | F59: =F57*F58 -> 15.38269 | G59: =G57*G58 -> 17.208244 | H59: =H57*H58 -> 18.833769 | I59: =I57*I58 -> 20.684913 | ... L59: =L57*L58 -> 27.992499
A60: Cumulative retained cash ($M) | B60: 0 | C60: =B60+C59*$B$14 -> 4.245696 | D60: =C60+D59*$B$14 -> 9.0224212 | E60: =D60+E59*$B$14 -> 14.816671 | F60: =E60+F59*$B$14 -> 21.738882 | G60: =F60+G59*$B$14 -> 29.482591 | H60: =G60+H59*$B$14 -> 37.957788 | I60: =H60+I59*$B$14 -> 47.265998 | J60: =I60+J59*$B$14 -> 57.525262 | ... L60: =K60+L59*$B$14 -> 81.469663
A61: Enterprise value @ exit multiple ($M) | B61: =$B$6+$B$9 -> 92 | C61: =C59*B$49 -> 103.78368 | D61: =D59*B$49 -> 116.76439 | E61: =E59*B$49 -> 141.63722 | F61: =F59*B$49 -> 169.20959 | G61: =G59*B$49 -> 189.29068 | H61: =H59*B$49 -> 207.17146 | I61: =I59*B$49 -> 227.53404 | J61: =J59*B$49 -> 250.78199 | K61: =K59*B$49 -> 277.3901 | L61: =L59*B$49 -> 307.91749
A62: Equity value ($M) | B62: =B61+B60-$B$9 -> 92 | C62: =C61+C60-$B$9 -> 108.02938 | D62: =D61+D60-$B$9 -> 125.78681 | E62: =E61+E60-$B$9 -> 156.45389 | F62: =F61+F60-$B$9 -> 190.94847 | G62: =G61+G60-$B$9 -> 218.77327 | H62: =H61+H60-$B$9 -> 245.12925 | I62: =I61+I60-$B$9 -> 274.80004 | ... L62: =L61+L60-$B$9 -> 389.38715
A64: BULL
A65: Program revenue ex-NGP production ($M) | B65: =SUMPRODUCT($B$29:$B$36,(1+$I$29:$I$36)^B$53) -> 60 | C65: =SUMPRODUCT($B$29:$B$36,(1+$I$29:$I$36)^C$53) -> 70.72 | D65: =SUMPRODUCT($B$29:$B$36,(1+$I$29:$I$36)^D$53) -> 83.6508 | E65: =SUMPRODUCT($B$29:$B$36,(1+$I$29:$I$36)^E$53) -> 99.299608 | F65: =SUMPRODUCT($B$29:$B$36,(1+$I$29:$I$36)^F$53) -> 118.2997 | G65: =SUMPRODUCT($B$29:$B$36,(1+$I$29:$I$36)^G$53) -> 141.44359 | H65: =SUMPRODUCT($B$29:$B$36,(1+$I$29:$I$36)^H$53) -> 169.72536 | I65: =SUMPRODUCT($B$29:$B$36,(1+$I$29:$I$36)^I$53) -> 204.39453 | ... L65: =SUMPRODUCT($B$29:$B$36,(1+$I$29:$I$36)^L$53) -> 364.63974
A66: NGP production revenue ($M) | B66: =C$43*MIN(MAX(B$53-C$42+1,0)/C$44,1) -> 0 | C66: =C$43*MIN(MAX(C$53-C$42+1,0)/C$44,1) -> 0 | D66: =C$43*MIN(MAX(D$53-C$42+1,0)/C$44,1) -> 10 | E66: =C$43*MIN(MAX(E$53-C$42+1,0)/C$44,1) -> 20 | F66: =C$43*MIN(MAX(F$53-C$42+1,0)/C$44,1) -> 20 | G66: =C$43*MIN(MAX(G$53-C$42+1,0)/C$44,1) -> 20 | H66: =C$43*MIN(MAX(H$53-C$42+1,0)/C$44,1) -> 20 | I66: =C$43*MIN(MAX(I$53-C$42+1,0)/C$44,1) -> 20 | J66: =C$43*MIN(MAX(J$53-C$42+1,0)/C$44,1) -> 20 | K66: =C$43*MIN(MAX(K$53-C$42+1,0)/C$44,1) -> 20 | L66: =C$43*MIN(MAX(L$53-C$42+1,0)/C$44,1) -> 20
A67: Total revenue ($M) | B67: =B65+B66 -> 60 | C67: =C65+C66 -> 70.72 | D67: =D65+D66 -> 93.6508 | E67: =E65+E66 -> 119.29961 | F67: =F65+F66 -> 138.2997 | G67: =G65+G66 -> 161.44359 | H67: =H65+H66 -> 189.72536 | I67: =I65+I66 -> 224.39453 | ... L67: =L65+L66 -> 384.63974
A68: EBITDA margin | B68: =$B$11+(C$48-$B$11)*MIN(B$53/$B$15,1) -> 0.14 | C68: =$B$11+(C$48-$B$11)*MIN(C$53/$B$15,1) -> 0.15 | D68: =$B$11+(C$48-$B$11)*MIN(D$53/$B$15,1) -> 0.16 | E68: =$B$11+(C$48-$B$11)*MIN(E$53/$B$15,1) -> 0.17 | F68: =$B$11+(C$48-$B$11)*MIN(F$53/$B$15,1) -> 0.18 | G68: =$B$11+(C$48-$B$11)*MIN(G$53/$B$15,1) -> 0.19 | H68: =$B$11+(C$48-$B$11)*MIN(H$53/$B$15,1) -> 0.19 | I68: =$B$11+(C$48-$B$11)*MIN(I$53/$B$15,1) -> 0.19 | J68: =$B$11+(C$48-$B$11)*MIN(J$53/$B$15,1) -> 0.19 | K68: =$B$11+(C$48-$B$11)*MIN(K$53/$B$15,1) -> 0.19 | L68: =$B$11+(C$48-$B$11)*MIN(L$53/$B$15,1) -> 0.19
A69: EBITDA ($M) | B69: =B67*B68 -> 8.4 | C69: =C67*C68 -> 10.608 | D69: =D67*D68 -> 14.984128 | E69: =E67*E68 -> 20.280933 | F69: =F67*F68 -> 24.893945 | G69: =G67*G68 -> 30.674282 | H69: =H67*H68 -> 36.047818 | I69: =I67*I68 -> 42.634961 | ... L69: =L67*L68 -> 73.08155
A70: Cumulative retained cash ($M) | B70: 0 | C70: =B70+C69*$B$14 -> 4.7736 | D70: =C70+D69*$B$14 -> 11.516458 | E70: =D70+E69*$B$14 -> 20.642878 | F70: =E70+F69*$B$14 -> 31.845153 | G70: =F70+G69*$B$14 -> 45.64858 | H70: =G70+H69*$B$14 -> 61.870098 | I70: =H70+I69*$B$14 -> 81.05583 | J70: =I70+J69*$B$14 -> 103.88647 | ... L70: =K70+L69*$B$14 -> 164.09922
A71: Enterprise value @ exit multiple ($M) | B71: =$B$6+$B$9 -> 92 | C71: =C69*C$49 -> 148.512 | D71: =D69*C$49 -> 209.77779 | E71: =E69*C$49 -> 283.93307 | F71: =F69*C$49 -> 348.51523 | G71: =G69*C$49 -> 429.43995 | H71: =H69*C$49 -> 504.66945 | I71: =I69*C$49 -> 596.88946 | J71: =J69*C$49 -> 710.28648 | K71: =K69*C$49 -> 850.14392 | L71: =L69*C$49 -> 1023.1417
A72: Equity value ($M) | B72: =B71+B70-$B$9 -> 92 | C72: =C71+C70-$B$9 -> 153.2856 | D72: =D71+D70-$B$9 -> 221.29425 | E72: =E71+E70-$B$9 -> 304.57594 | F72: =F71+F70-$B$9 -> 380.36039 | G72: =G71+G70-$B$9 -> 475.08853 | H72: =H71+H70-$B$9 -> 566.53954 | I72: =I71+I70-$B$9 -> 677.94529 | ... L72: =L71+L70-$B$9 -> 1187.2409
A74: BEAR
A75: Program revenue ex-NGP production ($M) | B75: =SUMPRODUCT($B$29:$B$36,(1+$J$29:$J$36)^B$53) -> 60 | C75: =SUMPRODUCT($B$29:$B$36,(1+$J$29:$J$36)^C$53) -> 56.87 | D75: =SUMPRODUCT($B$29:$B$36,(1+$J$29:$J$36)^D$53) -> 54.0657 | E75: =SUMPRODUCT($B$29:$B$36,(1+$J$29:$J$36)^E$53) -> 51.557021 | F75: =SUMPRODUCT($B$29:$B$36,(1+$J$29:$J$36)^F$53) -> 49.316924 | G75: =SUMPRODUCT($B$29:$B$36,(1+$J$29:$J$36)^G$53) -> 47.321109 | H75: =SUMPRODUCT($B$29:$B$36,(1+$J$29:$J$36)^H$53) -> 45.547747 | I75: =SUMPRODUCT($B$29:$B$36,(1+$J$29:$J$36)^I$53) -> 43.977233 | ... L75: =SUMPRODUCT($B$29:$B$36,(1+$J$29:$J$36)^L$53) -> 40.315702
A76: NGP production revenue ($M) | B76: =D$43*MIN(MAX(B$53-D$42+1,0)/D$44,1) -> 0 | C76: =D$43*MIN(MAX(C$53-D$42+1,0)/D$44,1) -> 0 | D76: =D$43*MIN(MAX(D$53-D$42+1,0)/D$44,1) -> 0 | E76: =D$43*MIN(MAX(E$53-D$42+1,0)/D$44,1) -> 0 | F76: =D$43*MIN(MAX(F$53-D$42+1,0)/D$44,1) -> 0 | G76: =D$43*MIN(MAX(G$53-D$42+1,0)/D$44,1) -> 0 | H76: =D$43*MIN(MAX(H$53-D$42+1,0)/D$44,1) -> 0 | I76: =D$43*MIN(MAX(I$53-D$42+1,0)/D$44,1) -> 0 | J76: =D$43*MIN(MAX(J$53-D$42+1,0)/D$44,1) -> 0 | K76: =D$43*MIN(MAX(K$53-D$42+1,0)/D$44,1) -> 0 | L76: =D$43*MIN(MAX(L$53-D$42+1,0)/D$44,1) -> 0
A77: Total revenue ($M) | B77: =B75+B76 -> 60 | C77: =C75+C76 -> 56.87 | D77: =D75+D76 -> 54.0657 | E77: =E75+E76 -> 51.557021 | F77: =F75+F76 -> 49.316924 | G77: =G75+G76 -> 47.321109 | H77: =H75+H76 -> 45.547747 | I77: =I75+I76 -> 43.977233 | ... L77: =L75+L76 -> 40.315702
A78: EBITDA margin | B78: =$B$11+(D$48-$B$11)*MIN(B$53/$B$15,1) -> 0.14 | C78: =$B$11+(D$48-$B$11)*MIN(C$53/$B$15,1) -> 0.134 | D78: =$B$11+(D$48-$B$11)*MIN(D$53/$B$15,1) -> 0.128 | E78: =$B$11+(D$48-$B$11)*MIN(E$53/$B$15,1) -> 0.122 | F78: =$B$11+(D$48-$B$11)*MIN(F$53/$B$15,1) -> 0.116 | G78: =$B$11+(D$48-$B$11)*MIN(G$53/$B$15,1) -> 0.11 | H78: =$B$11+(D$48-$B$11)*MIN(H$53/$B$15,1) -> 0.11 | I78: =$B$11+(D$48-$B$11)*MIN(I$53/$B$15,1) -> 0.11 | J78: =$B$11+(D$48-$B$11)*MIN(J$53/$B$15,1) -> 0.11 | K78: =$B$11+(D$48-$B$11)*MIN(K$53/$B$15,1) -> 0.11 | L78: =$B$11+(D$48-$B$11)*MIN(L$53/$B$15,1) -> 0.11
A79: EBITDA ($M) | B79: =B77*B78 -> 8.4 | C79: =C77*C78 -> 7.62058 | D79: =D77*D78 -> 6.9204096 | E79: =E77*E78 -> 6.2899566 | F79: =F77*F78 -> 5.7207632 | G79: =G77*G78 -> 5.205322 | H79: =H77*H78 -> 5.0102522 | I79: =I77*I78 -> 4.8374957 | ... L79: =L77*L78 -> 4.4347272
A80: Cumulative retained cash ($M) | B80: 0 | C80: =B80+C79*$B$14 -> 3.429261 | D80: =C80+D79*$B$14 -> 6.5434453 | E80: =D80+E79*$B$14 -> 9.3739258 | F80: =E80+F79*$B$14 -> 11.948269 | G80: =F80+G79*$B$14 -> 14.290664 | H80: =G80+H79*$B$14 -> 16.545278 | I80: =H80+I79*$B$14 -> 18.722151 | J80: =I80+J79*$B$14 -> 20.830453 | ... L80: =K80+L79*$B$14 -> 24.874201
A81: Enterprise value @ exit multiple ($M) | B81: =$B$6+$B$9 -> 92 | C81: =C79*D$49 -> 53.34406 | D81: =D79*D$49 -> 48.442867 | E81: =E79*D$49 -> 44.029696 | F81: =F79*D$49 -> 40.045342 | G81: =G79*D$49 -> 36.437254 | H81: =H79*D$49 -> 35.071765 | I81: =I79*D$49 -> 33.86247 | J81: =J79*D$49 -> 32.795819 | K81: =K79*D$49 -> 31.859658 | L81: =L79*D$49 -> 31.043091
A82: Equity value ($M) | B82: =B81+B80-$B$9 -> 92 | C82: =C81+C80-$B$9 -> 56.773321 | D82: =D81+D80-$B$9 -> 54.986313 | E82: =E81+E80-$B$9 -> 53.403622 | F82: =F81+F80-$B$9 -> 51.993611 | G82: =G81+G80-$B$9 -> 50.727918 | H82: =H81+H80-$B$9 -> 51.617043 | I82: =I81+I80-$B$9 -> 52.58462 | ... L82: =L81+L80-$B$9 -> 55.917292
A84: TSMC-SHOCK
A85: Program revenue ex-NGP production ($M) | B85: =SUMPRODUCT($B$29:$B$36,(1+$K$29:$K$36)^B$53) -> 60 | C85: =SUMPRODUCT($B$29:$B$36,(1+$K$29:$K$36)^C$53) -> 71.47 | D85: =SUMPRODUCT($B$29:$B$36,(1+$K$29:$K$36)^D$53) -> 85.6043 | E85: =SUMPRODUCT($B$29:$B$36,(1+$K$29:$K$36)^E$53) -> 103.08006 | F85: =SUMPRODUCT($B$29:$B$36,(1+$K$29:$K$36)^F$53) -> 124.75993 | G85: =SUMPRODUCT($B$29:$B$36,(1+$K$29:$K$36)^G$53) -> 151.746 | H85: =SUMPRODUCT($B$29:$B$36,(1+$K$29:$K$36)^H$53) -> 185.44994 | I85: =SUMPRODUCT($B$29:$B$36,(1+$K$29:$K$36)^I$53) -> 227.6847 | ... L85: =SUMPRODUCT($B$29:$B$36,(1+$K$29:$K$36)^L$53) -> 432.50742
A86: NGP production revenue ($M) | B86: =E$43*MIN(MAX(B$53-E$42+1,0)/E$44,1) -> 0 | C86: =E$43*MIN(MAX(C$53-E$42+1,0)/E$44,1) -> 0 | D86: =E$43*MIN(MAX(D$53-E$42+1,0)/E$44,1) -> 24 | E86: =E$43*MIN(MAX(E$53-E$42+1,0)/E$44,1) -> 24 | F86: =E$43*MIN(MAX(F$53-E$42+1,0)/E$44,1) -> 24 | G86: =E$43*MIN(MAX(G$53-E$42+1,0)/E$44,1) -> 24 | H86: =E$43*MIN(MAX(H$53-E$42+1,0)/E$44,1) -> 24 | I86: =E$43*MIN(MAX(I$53-E$42+1,0)/E$44,1) -> 24 | J86: =E$43*MIN(MAX(J$53-E$42+1,0)/E$44,1) -> 24 | K86: =E$43*MIN(MAX(K$53-E$42+1,0)/E$44,1) -> 24 | L86: =E$43*MIN(MAX(L$53-E$42+1,0)/E$44,1) -> 24
A87: Total revenue ($M) | B87: =B85+B86 -> 60 | C87: =C85+C86 -> 71.47 | D87: =D85+D86 -> 109.6043 | E87: =E85+E86 -> 127.08006 | F87: =F85+F86 -> 148.75993 | G87: =G85+G86 -> 175.746 | H87: =H85+H86 -> 209.44994 | I87: =I85+I86 -> 251.6847 | ... L87: =L85+L86 -> 456.50742
A88: EBITDA margin | B88: =$B$11+(E$48-$B$11)*MIN(B$53/$B$15,1) -> 0.14 | C88: =$B$11+(E$48-$B$11)*MIN(C$53/$B$15,1) -> 0.148 | D88: =$B$11+(E$48-$B$11)*MIN(D$53/$B$15,1) -> 0.156 | E88: =$B$11+(E$48-$B$11)*MIN(E$53/$B$15,1) -> 0.164 | F88: =$B$11+(E$48-$B$11)*MIN(F$53/$B$15,1) -> 0.172 | G88: =$B$11+(E$48-$B$11)*MIN(G$53/$B$15,1) -> 0.18 | H88: =$B$11+(E$48-$B$11)*MIN(H$53/$B$15,1) -> 0.18 | I88: =$B$11+(E$48-$B$11)*MIN(I$53/$B$15,1) -> 0.18 | J88: =$B$11+(E$48-$B$11)*MIN(J$53/$B$15,1) -> 0.18 | K88: =$B$11+(E$48-$B$11)*MIN(K$53/$B$15,1) -> 0.18 | L88: =$B$11+(E$48-$B$11)*MIN(L$53/$B$15,1) -> 0.18
A89: EBITDA ($M) | B89: =B87*B88 -> 8.4 | C89: =C87*C88 -> 10.57756 | D89: =D87*D88 -> 17.098271 | E89: =E87*E88 -> 20.841129 | F89: =F87*F88 -> 25.586708 | G89: =G87*G88 -> 31.634279 | H89: =H87*H88 -> 37.700989 | I89: =I87*I88 -> 45.303246 | ... L89: =L87*L88 -> 82.171336
A90: Cumulative retained cash ($M) | B90: 0 | C90: =B90+C89*$B$14 -> 4.759902 | D90: =C90+D89*$B$14 -> 12.454124 | E90: =D90+E89*$B$14 -> 21.832632 | F90: =E90+F89*$B$14 -> 33.346651 | G90: =F90+G89*$B$14 -> 47.582076 | H90: =G90+H89*$B$14 -> 64.547521 | I90: =H90+I89*$B$14 -> 84.933982 | J90: =I90+J89*$B$14 -> 109.6215 | ... L90: =K90+L89*$B$14 -> 176.71118
A91: Enterprise value @ exit multiple ($M) | B91: =$B$6+$B$9 -> 92 | C91: =C89*E$49 -> 137.50828 | D91: =D89*E$49 -> 222.27752 | E91: =E89*E$49 -> 270.93468 | F91: =F89*E$49 -> 332.62721 | G91: =G89*E$49 -> 411.24563 | H91: =H89*E$49 -> 490.11286 | I91: =I89*E$49 -> 588.9422 | J91: =J89*E$49 -> 713.1951 | K91: =K89*E$49 -> 869.91891 | L91: =L89*E$49 -> 1068.2274
A92: Equity value ($M) | B92: =B91+B90-$B$9 -> 92 | C92: =C91+C90-$B$9 -> 142.26818 | D92: =D91+D90-$B$9 -> 234.73164 | E92: =E91+E90-$B$9 -> 292.76731 | F92: =F91+F90-$B$9 -> 365.97386 | G92: =G91+G90-$B$9 -> 458.82771 | H92: =H91+H90-$B$9 -> 554.66038 | I92: =I91+I90-$B$9 -> 673.87618 | ... L92: =L91+L90-$B$9 -> 1244.9386
A94: OUTPUT — IMPLIED EQUITY CAGR (entry $92M -> equity value in year t), FEEDS WEAPONS SLEEVE
A95: Metric | B95: Hold (yrs) | C95: Base | D95: Bull | E95: Bear | F95: TSMC-Shock | G95: Expected
A96: Implied equity CAGR — 5-yr | B96: 5 | C96: =(G62/$B$6)^(1/$B96)-1 -> 0.18916272 | D96: =(G72/$B$6)^(1/$B96)-1 -> 0.38866453 | E96: =(G82/$B$6)^(1/$B96)-1 -> -0.11224763 | F96: =(G92/$B$6)^(1/$B96)-1 -> 0.37902571 | G96: =C96*'Defense Supercycle'!$B$17+D96*'Defense Supercycle'!$B$18+E96*'Defense Supercycle'!$B$19+F96*'Defense Supercycle'!$B$20 -> 0.22230607
A97: Implied equity CAGR — 7-yr (feeds sleeve) | B97: 7 | C97: =(I62/$B$6)^(1/$B97)-1 -> 0.16920281 | D97: =(I72/$B$6)^(1/$B97)-1 -> 0.33019484 | E97: =(I82/$B$6)^(1/$B97)-1 -> -0.076799895 | F97: =(I92/$B$6)^(1/$B97)-1 -> 0.32905133 | G97: =C97*'Defense Supercycle'!$B$17+D97*'Defense Supercycle'!$B$18+E97*'Defense Supercycle'!$B$19+F97*'Defense Supercycle'!$B$20 -> 0.19652769
A98: Implied equity CAGR — 10-yr | B98: 10 | C98: =(L62/$B$6)^(1/$B98)-1 -> 0.15520585 | D98: =(L72/$B$6)^(1/$B98)-1 -> 0.29144258 | E98: =(L82/$B$6)^(1/$B98)-1 -> -0.048572214 | F98: =(L92/$B$6)^(1/$B98)-1 -> 0.29758558 | G98: =C98*'Defense Supercycle'!$B$17+D98*'Defense Supercycle'!$B$18+E98*'Defense Supercycle'!$B$19+F98*'Defense Supercycle'!$B$20 -> 0.18005528
A99: Year-7 revenue ($M) | C99: =I57 -> 129.28071 | D99: =I67 -> 224.39453 | E99: =I77 -> 43.977233 | F99: =I87 -> 251.6847 | G99: =C99*'Defense Supercycle'!$B$17+D99*'Defense Supercycle'!$B$18+E99*'Defense Supercycle'!$B$19+F99*'Defense Supercycle'!$B$20 -> 158.62424
A100: Year-7 NGP production share of revenue | C100: =I56/I57 -> 0.092821276 | D100: =I66/I67 -> 0.089128731 | E100: =I76/I77 -> 0 | F100: =I86/I87 -> 0.095357405
A102: STAKE RETURNS — $9M CHECK (from Weapons Sleeve, incl. dilution retention 0.92 / 0.88 / 0.82)
A103: Hold | B103: Check ($M) | C103: Base $ | D103: Bull $ | E103: Bear $ | F103: TSMC-Shock $ | G103: Expected $ | H103: Exp. MOIC | I103: Exp. IRR
A104: 5-year hold | B104: ='Weapons Sleeve'!B35 -> 9 | C104: ='Weapons Sleeve'!C35 -> 18.091709 | D104: ='Weapons Sleeve'!F35 -> 34.483126 | E104: ='Weapons Sleeve'!I35 -> 5.5527684 | F104: ='Weapons Sleeve'!L35 -> 34.335163 | G104: =C104*'Defense Supercycle'!$B$17+D104*'Defense Supercycle'!$B$18+E104*'Defense Supercycle'!$B$19+F104*'Defense Supercycle'!$B$20 -> 22.74524 | H104: =G104/B104 -> 2.5272489 | I104: =H104^(1/5)-1 -> 0.20373144
A105: 7-year hold | B105: ='Weapons Sleeve'!B50 -> 9 | C105: ='Weapons Sleeve'!C50 -> 23.656699 | D105: ='Weapons Sleeve'!F50 -> 58.362246 | E105: ='Weapons Sleeve'!I50 -> 4.5268499 | F105: ='Weapons Sleeve'!L50 -> 58.01195 | G105: =C105*'Defense Supercycle'!$B$17+D105*'Defense Supercycle'!$B$18+E105*'Defense Supercycle'!$B$19+F105*'Defense Supercycle'!$B$20 -> 34.616896 | H105: =G105/B105 -> 3.8463218 | I105: =H105^(1/7)-1 -> 0.21221023
A106: 10-year hold | B106: ='Weapons Sleeve'!B65 -> 9 | C106: ='Weapons Sleeve'!C65 -> 35.233427 | D106: ='Weapons Sleeve'!F65 -> 127.9997 | E106: ='Weapons Sleeve'!I65 -> 3.3190578 | F106: ='Weapons Sleeve'!L65 -> 126.90359 | G106: =C106*'Defense Supercycle'!$B$17+D106*'Defense Supercycle'!$B$18+E106*'Defense Supercycle'!$B$19+F106*'Defense Supercycle'!$B$20 -> 67.388364 | H106: =G106/B106 -> 7.4875961 | I106: =H106^(1/10)-1 -> 0.22302192
A107: Stake MOIC by scenario — 7-yr | C107: ='Weapons Sleeve'!D50 -> 2.6285221 | D107: ='Weapons Sleeve'!G50 -> 6.484694 | E107: ='Weapons Sleeve'!J50 -> 0.50298333 | F107: ='Weapons Sleeve'!M50 -> 6.4457722
A109: CHECKS
A110: Sleeve Adj. Base CAGR = build 7-yr Base CAGR | B110: =IF(ABS('Weapons Sleeve'!S21-C97)<0.00001,"OK","CHECK") -> OK
A111: Weapons sleeve still fully deployed ($390M) | B111: =IF(ABS('Weapons Sleeve'!C22-'Weapons Sleeve'!B5)<0.001,"OK","CHECK") -> OK
A112: Stake < $10M (user constraint) | B112: =IF(B7<10,"OK","CHECK") -> OK
...

Sheet Consumer Sleeve
A1: CONSUMER / VALUE SLEEVE — BOTTOM-UP ($200M)
A2: Spending-cycle / DTC-value holdings. Blue = input. Quince & Whoop = confirmed 2026 primary rounds; Farmer's Dog & Thrive Market = Forge secondary-market pricing (22-Sep-26); Made In & Plunge remain estimates — no market exists. Polymarket added (Sep-26) — prediction-market secondary at ~$14-21B. Goat Group added (stale Series F Jun-21 mark, $3.73B post, no live secondary) and Stripe added (MARKET-PRICED, $159B Feb-26 employee tender) — both funded by trimming the other seven checks pro-rata (×0.7×) to hold the sleeve at its $200M cap.
A4: SLEEVE TERMS
A5: Committed ($M) | B5: ='Holdco Summary'!$B$8 -> 200
A6: Retention @5yr | B6: 0.9
A7: Retention @7yr | B7: 0.84
A8: Retention @10yr | B8: 0.75
A10: HOLDINGS, ENTRY MARKS & GROWTH ASSUMPTIONS
A11: Company | B11: Entry post-$M | C11: Check ($M) | D11: Own % | E11: Channel / access note | F11: Base | G11: Bull | H11: Bear | I11: Shock | J11: Valuation basis
A12: Quince | B12: 10100 | C12: 35 | D12: =C12/B12 -> 0.0034653465 | E12: Direct secondary/late-primary; watch ICONIQ round terms | F12: 0.28 | G12: 0.45 | H12: 0.02 | I12: -0.18 | J12: Series E Mar-26 $10.1B post (ICONIQ-led $500M; >$1B ARR, M2C manufacturer-to-consumer model)
A13: Whoop | B13: 10100 | C13: 31.5 | D13: =C13/B13 -> 0.0031188119 | E13: Direct secondary/late-primary; IPO window = public-exit optionality | F13: 0.27 | G13: 0.42 | H13: -0.03 | I13: -0.16 | J13: Series G Mar-26 $10.1B post ($575M raise; IPO-track, medical-grade/glucose-monitoring expansion)
A14: The Farmer's Dog | B14: 3760 | C14: 24.5 | D14: =C14/B14 -> 0.0065159574 | E14: WALMART.COM LAUNCH (2025) — DTC-only to omni-channel; secondary access | F14: 0.22 | G14: 0.34 | H14: 0.1 | I14: -0.05 | J14: MARKET-PRICED — Forge secondary $23.64/sh (22-Sep-26) = $3.76B implied, up from $2.5B Series E ($15.72/sh, Jun-22); profitable, >$1B ann. revenue
A15: Made In Cookware | B15: 280 | C15: 17.5 | D15: =C15/B15 -> 0.0625 | E15: DTC + wholesale/restaurant placements; secondary access, thin float | F15: 0.14 | G15: 0.26 | H15: -0.1 | I15: -0.14 | J15: Est. EV — only ~$8.3M ever raised ($5M 2019 seed, KarpReilly-backed 2017); NO secondary market exists — least-grounded mark in the sleeve
A16: Thrive Market | B16: 945 | C16: 14 | D16: =C16/B16 -> 0.014814815 | E16: Membership DTC; IPO-candidate, pre-IPO secondary | F16: 0.07 | G16: 0.16 | H16: -0.05 | I16: -0.08 | J16: MARKET-PRICED — Forge secondary $17.98/sh (21-Sep-26) implies ~$945M, DOWN ~27% from Series C $1.29B post ($24.60/sh, Jul-21) despite revenue growth $400M→$700M+ — real multiple compression
A17: Plunge | B17: 110 | C17: 7 | D17: =C17/B17 -> 0.063636364 | E17: Wefunder community round (2025) — direct primary access, small check | F17: 0.2 | G17: 0.5 | H17: -0.22 | I17: -0.28 | J17: Est. — NO priced VC round exists (only $4.75M raised incl. crowdfunding); 2021 Shark Tank ask was $10M (declined) vs. ~$200M lifetime sales by 2025 — mostly self-funded growth, entry mark is a rough estimate
A18: Polymarket | B18: 18000 | C18: 10.5 | D18: =C18/B18 -> 0.00058333333 | E18: Secondary / late-primary; prediction-market expansion (US regulated + ICE distribution) | F18: 0.25 | G18: 0.4 | H18: -0.05 | I18: -0.12 | J18: MARKET-PRICED — secondary ~$14-21B range (Sep-26); ICE-backed; US regulated expansion & sports/politics volume convexity
A19: Goat Group | B19: 3730 | C19: 15 | D19: =C19/B19 -> 0.0040214477 | E19: Secondary access, thin float; last priced Series F (Jun-21); no active secondary quote — re-underwrite before check | F19: 0.15 | G19: 0.28 | H19: -0.12 | I19: -0.16 | J19: Est. — last priced Series F 24-Jun-21 $3.73B post ($5.82/sh; $195M raise, Dragoneer/Franklin Templeton); Forge Global lists GOAT with no live secondary match ("price not yet available") — 5-yr-stale mark, least-grounded alongside Made In/Plunge; no IPO filed
A20: Stripe | B20: 159000 | C20: 45 | D20: =C20/B20 -> 0.00028301887 | E20: Employee/investor tender access; most liquid, most de-risked name in the sleeve — recurring annual tender cadence gives a real-time mark | F20: 0.18 | G20: 0.35 | H20: -0.05 | I20: -0.08 | J20: MARKET-PRICED — Feb-26 employee tender $159B post (Bloomberg/CNBC, 24-Feb-26), up from ~$140B guided 9-Feb-26 and ~$91.5B Feb-25 tender; total payment volume +34% YoY (~$1.9-2T annualized); IPO-track, profitable at scale
A21: TOTAL (=$200M) | C21: =SUM(C12:C20) -> 200
A23: 5-YEAR HOLD — GROSS PROCEEDS
A24: Company | B24: Check ($M) | C24: Base $ | D24: Base MOIC | E24: Base IRR | F24: Bull $ | G24: Bull MOIC | H24: Bull IRR | I24: Bear $ | J24: Bear MOIC | K24: Bear IRR | L24: Shock $ | M24: Shock MOIC | N24: Shock IRR
A25: =A12 -> Quince | B25: =C12 -> 35 | C25: =B25*(1+F12)^5*'Consumer Sleeve'!$B$6 -> 108.23318 | D25: =C25/B25 -> 3.0923765 | E25: =(C25/B25)^(1/5)-1 -> 0.2533099 | F25: =B25*(1+G12)^5*'Consumer Sleeve'!$B$6 -> 201.90662 | G25: =F25/B25 -> 5.7687607 | H25: =(F25/B25)^(1/5)-1 -> 0.41976513 | I25: =B25*(1+H12)^5*'Consumer Sleeve'!$B$6 -> 34.778545 | J25: =I25/B25 -> 0.99367272 | K25: =(I25/B25)^(1/5)-1 -> -0.0012686704 | L25: =B25*(1+I12)^5*'Consumer Sleeve'!$B$6 -> 11.678305 | M25: =L25/B25 -> 0.33366586 | N25: =(L25/B25)^(1/5)-1 -> -0.19709834
A26: =A13 -> Whoop | B26: =C13 -> 31.5 | C26: =B26*(1+F13)^5*'Consumer Sleeve'!$B$6 -> 93.663777 | D26: =C26/B26 -> 2.9734532 | E26: =(C26/B26)^(1/5)-1 -> 0.24351842 | F26: =B26*(1+G13)^5*'Consumer Sleeve'!$B$6 -> 163.67969 | G26: =F26/B26 -> 5.1961805 | H26: =(F26/B26)^(1/5)-1 -> 0.39039067 | I26: =B26*(1+H13)^5*'Consumer Sleeve'!$B$6 -> 24.34511 | J26: =I26/B26 -> 0.77286062 | K26: =(I26/B26)^(1/5)-1 -> -0.050226089 | L26: =B26*(1+I13)^5*'Consumer Sleeve'!$B$6 -> 11.856309 | M26: =L26/B26 -> 0.37639075 | N26: =(L26/B26)^(1/5)-1 -> -0.17751538
A27: =A14 -> The Farmer's Dog | B27: =C14 -> 24.5 | C27: =B27*(1+F14)^5*'Consumer Sleeve'!$B$6 -> 59.594715 | D27: =C27/B27 -> 2.4324373 | E27: =(C27/B27)^(1/5)-1 -> 0.194561 | F27: =B27*(1+G14)^5*'Consumer Sleeve'!$B$6 -> 95.264828 | G27: =F27/B27 -> 3.8883603 | H27: =(F27/B27)^(1/5)-1 -> 0.31205881 | I27: =B27*(1+H14)^5*'Consumer Sleeve'!$B$6 -> 35.511746 | J27: =I27/B27 -> 1.449459 | K27: =(I27/B27)^(1/5)-1 -> 0.077063199 | L27: =B27*(1+I14)^5*'Consumer Sleeve'!$B$6 -> 17.06187 | M27: =L27/B27 -> 0.69640284 | N27: =(L27/B27)^(1/5)-1 -> -0.069809056
A28: =A15 -> Made In Cookware | B28: =C15 -> 17.5 | C28: =B28*(1+F15)^5*'Consumer Sleeve'!$B$6 -> 30.32528 | D28: =C28/B28 -> 1.7328731 | E28: =(C28/B28)^(1/5)-1 -> 0.11622913 | F28: =B28*(1+G15)^5*'Consumer Sleeve'!$B$6 -> 50.018802 | G28: =F28/B28 -> 2.8582172 | H28: =(F28/B28)^(1/5)-1 -> 0.23372694 | I28: =B28*(1+H15)^5*'Consumer Sleeve'!$B$6 -> 9.3002175 | J28: =I28/B28 -> 0.531441 | K28: =(I28/B28)^(1/5)-1 -> -0.11876647 | L28: =B28*(1+I15)^5*'Consumer Sleeve'!$B$6 -> 7.4092255 | M28: =L28/B28 -> 0.42338432 | N28: =(L28/B28)^(1/5)-1 -> -0.15793241
A29: =A16 -> Thrive Market | B29: =C16 -> 14 | C29: =B29*(1+F16)^5*'Consumer Sleeve'!$B$6 -> 17.672152 | D29: =C29/B29 -> 1.2622966 | E29: =(C29/B29)^(1/5)-1 -> 0.047688748 | F29: =B29*(1+G16)^5*'Consumer Sleeve'!$B$6 -> 26.464305 | G29: =F29/B29 -> 1.8903075 | H29: =(F29/B29)^(1/5)-1 -> 0.1358121 | I29: =B29*(1+H16)^5*'Consumer Sleeve'!$B$6 -> 9.7496398 | J29: =I29/B29 -> 0.69640284 | K29: =(I29/B29)^(1/5)-1 -> -0.069809056 | L29: =B29*(1+I16)^5*'Consumer Sleeve'!$B$6 -> 8.3044272 | M29: =L29/B29 -> 0.59317337 | N29: =(L29/B29)^(1/5)-1 -> -0.099183507
A30: =A17 -> Plunge | B30: =C17 -> 7 | C30: =B30*(1+F17)^5*'Consumer Sleeve'!$B$6 -> 15.676416 | D30: =C30/B30 -> 2.239488 | E30: =(C30/B30)^(1/5)-1 -> 0.17497803 | F30: =B30*(1+G17)^5*'Consumer Sleeve'!$B$6 -> 47.840625 | G30: =F30/B30 -> 6.834375 | H30: =(F30/B30)^(1/5)-1 -> 0.46872254 | I30: =B30*(1+H17)^5*'Consumer Sleeve'!$B$6 -> 1.8189199 | J30: =I30/B30 -> 0.25984569 | K30: =(I30/B30)^(1/5)-1 -> -0.23626428 | L30: =B30*(1+I17)^5*'Consumer Sleeve'!$B$6 -> 1.2189981 | M30: =L30/B30 -> 0.17414259 | N30: =(L30/B30)^(1/5)-1 -> -0.29501318
A31: =A18 -> Polymarket | B31: =C18 -> 10.5 | C31: =B31*(1+F18)^5*'Consumer Sleeve'!$B$6 -> 28.839111 | D31: =C31/B31 -> 2.746582 | E31: =(C31/B31)^(1/5)-1 -> 0.22393545 | F31: =B31*(1+G18)^5*'Consumer Sleeve'!$B$6 -> 50.824368 | G31: =F31/B31 -> 4.840416 | H31: =(F31/B31)^(1/5)-1 -> 0.37080771 | I31: =B31*(1+H18)^5*'Consumer Sleeve'!$B$6 -> 7.3122299 | J31: =I31/B31 -> 0.69640284 | K31: =(I31/B31)^(1/5)-1 -> -0.069809056 | L31: =B31*(1+I18)^5*'Consumer Sleeve'!$B$6 -> 4.9870666 | M31: =L31/B31 -> 0.47495873 | N31: =(L31/B31)^(1/5)-1 -> -0.13834944
A32: =A19 -> Goat Group | B32: =C19 -> 15 | C32: =B32*(1+F19)^5*'Consumer Sleeve'!$B$6 -> 27.153322 | D32: =C32/B32 -> 1.8102215 | E32: =(C32/B32)^(1/5)-1 -> 0.12602062 | F32: =B32*(1+G19)^5*'Consumer Sleeve'!$B$6 -> 46.385647 | G32: =F32/B32 -> 3.0923765 | H32: =(F32/B32)^(1/5)-1 -> 0.2533099 | I32: =B32*(1+H19)^5*'Consumer Sleeve'!$B$6 -> 7.1243809 | J32: =I32/B32 -> 0.47495873 | K32: =(I32/B32)^(1/5)-1 -> -0.13834944 | L32: =B32*(1+I19)^5*'Consumer Sleeve'!$B$6 -> 5.6458612 | M32: =L32/B32 -> 0.37639075 | N32: =(L32/B32)^(1/5)-1 -> -0.17751538
A33: =A20 -> Stripe | B33: =C20 -> 45 | C33: =B33*(1+F20)^5*'Consumer Sleeve'!$B$6 -> 92.654189 | D33: =C33/B33 -> 2.058982 | E33: =(C33/B33)^(1/5)-1 -> 0.15539507 | F33: =B33*(1+G20)^5*'Consumer Sleeve'!$B$6 -> 181.60335 | G33: =F33/B33 -> 4.0356301 | H33: =(F33/B33)^(1/5)-1 -> 0.32185029 | I33: =B33*(1+H20)^5*'Consumer Sleeve'!$B$6 -> 31.338128 | J33: =I33/B33 -> 0.69640284 | K33: =(I33/B33)^(1/5)-1 -> -0.069809056 | L33: =B33*(1+I20)^5*'Consumer Sleeve'!$B$6 -> 26.692802 | M33: =L33/B33 -> 0.59317337 | N33: =(L33/B33)^(1/5)-1 -> -0.099183507
A34: SLEEVE TOTAL | B34: =SUM(B25:B33) -> 200 | C34: =SUM(C25:C33) -> 473.81214 | D34: =C34/B34 -> 2.3690607 | E34: =(C34/B34)^(1/5)-1 -> 0.18827029 | F34: =SUM(F25:F33) -> 863.98824 | G34: =F34/B34 -> 4.3199412 | H34: =(F34/B34)^(1/5)-1 -> 0.33997152 | I34: =SUM(I25:I33) -> 161.27892 | J34: =I34/B34 -> 0.80639458 | K34: =(I34/B34)^(1/5)-1 -> -0.042123497 | L34: =SUM(L25:L33) -> 94.854864 | M34: =L34/B34 -> 0.47427432 | N34: =(L34/B34)^(1/5)-1 -> -0.13859791
A37: 7-YEAR HOLD — GROSS PROCEEDS
A38: Company | B38: Check ($M) | C38: Base $ | D38: Base MOIC | E38: Base IRR | F38: Bull $ | G38: Bull MOIC | H38: Bull IRR | I38: Bear $ | J38: Bear MOIC | K38: Bear IRR | L38: Shock $ | M38: Shock MOIC | N38: Shock IRR
A39: =A12 -> Quince | B39: =C12 -> 35 | C39: =B39*(1+F12)^7*'Consumer Sleeve'!$B$7 -> 165.50729 | D39: =C39/B39 -> 4.7287796 | E39: =(C39/B39)^(1/7)-1 -> 0.24851201 | F39: =B39*(1+G12)^7*'Consumer Sleeve'!$B$7 -> 396.2081 | G39: =F39/B39 -> 11.320231 | H39: =(F39/B39)^(1/7)-1 -> 0.41433001 | I39: =B39*(1+H12)^7*'Consumer Sleeve'!$B$7 -> 33.771359 | J39: =I39/B39 -> 0.96489596 | K39: =(I39/B39)^(1/7)-1 -> -0.0050919911 | L39: =B39*(1+I12)^7*'Consumer Sleeve'!$B$7 -> 7.3289928 | M39: =L39/B39 -> 0.2093998 | N39: =(L39/B39)^(1/7)-1 -> -0.20017199
A40: =A13 -> Whoop | B40: =C13 -> 31.5 | C40: =B40*(1+F13)^7*'Consumer Sleeve'!$B$7 -> 140.99895 | D40: =C40/B40 -> 4.4761572 | E40: =(C40/B40)^(1/7)-1 -> 0.23875801 | F40: =B40*(1+G13)^7*'Consumer Sleeve'!$B$7 -> 308.04081 | G40: =F40/B40 -> 9.7790732 | H40: =(F40/B40)^(1/7)-1 -> 0.38506801 | I40: =B40*(1+H13)^7*'Consumer Sleeve'!$B$7 -> 21.379226 | J40: =I40/B40 -> 0.67870559 | K40: =(I40/B40)^(1/7)-1 -> -0.053861992 | L40: =B40*(1+I13)^7*'Consumer Sleeve'!$B$7 -> 7.8080906 | M40: =L40/B40 -> 0.24787589 | N40: =(L40/B40)^(1/7)-1 -> -0.18066399
A41: =A14 -> The Farmer's Dog | B41: =C14 -> 24.5 | C41: =B41*(1+F14)^7*'Consumer Sleeve'!$B$7 -> 82.787389 | D41: =C41/B41 -> 3.3790771 | E41: =(C41/B41)^(1/7)-1 -> 0.18998801 | F41: =B41*(1+G14)^7*'Consumer Sleeve'!$B$7 -> 159.65369 | G41: =F41/B41 -> 6.5164771 | H41: =(F41/B41)^(1/7)-1 -> 0.30703601 | I41: =B41*(1+H14)^7*'Consumer Sleeve'!$B$7 -> 40.104598 | J41: =I41/B41 -> 1.6369224 | K41: =(I41/B41)^(1/7)-1 -> 0.07294001 | L41: =B41*(1+I14)^7*'Consumer Sleeve'!$B$7 -> 14.371782 | M41: =L41/B41 -> 0.58660333 | N41: =(L41/B41)^(1/7)-1 -> -0.073369992
A42: =A15 -> Made In Cookware | B42: =C15 -> 17.5 | C42: =B42*(1+F15)^7*'Consumer Sleeve'!$B$7 -> 36.783351 | D42: =C42/B42 -> 2.1019058 | E42: =(C42/B42)^(1/7)-1 -> 0.11195601 | F42: =B42*(1+G15)^7*'Consumer Sleeve'!$B$7 -> 74.11586 | G42: =F42/B42 -> 4.235192 | H42: =(F42/B42)^(1/7)-1 -> 0.22900401 | I42: =B42*(1+H15)^7*'Consumer Sleeve'!$B$7 -> 7.0309644 | J42: =I42/B42 -> 0.4017694 | K42: =(I42/B42)^(1/7)-1 -> -0.12213999 | L42: =B42*(1+I15)^7*'Consumer Sleeve'!$B$7 -> 5.114539 | M42: =L42/B42 -> 0.29225937 | N42: =(L42/B42)^(1/7)-1 -> -0.16115599
A43: =A16 -> Thrive Market | B43: =C16 -> 14 | C43: =B43*(1+F16)^7*'Consumer Sleeve'!$B$7 -> 18.88399 | D43: =C43/B43 -> 1.3488564 | E43: =(C43/B43)^(1/7)-1 -> 0.043678009 | F43: =B43*(1+G16)^7*'Consumer Sleeve'!$B$7 -> 33.236344 | G43: =F43/B43 -> 2.3740246 | H43: =(F43/B43)^(1/7)-1 -> 0.13146401 | I43: =B43*(1+H16)^7*'Consumer Sleeve'!$B$7 -> 8.2124466 | J43: =I43/B43 -> 0.58660333 | K43: =(I43/B43)^(1/7)-1 -> -0.073369992 | L43: =B43*(1+I16)^7*'Consumer Sleeve'!$B$7 -> 6.560276 | M43: =L43/B43 -> 0.46859115 | N43: =(L43/B43)^(1/7)-1 -> -0.10263199
A44: =A17 -> Plunge | B44: =C17 -> 7 | C44: =B44*(1+F17)^7*'Consumer Sleeve'!$B$7 -> 21.069103 | D44: =C44/B44 -> 3.0098719 | E44: =(C44/B44)^(1/7)-1 -> 0.17048001 | F44: =B44*(1+G17)^7*'Consumer Sleeve'!$B$7 -> 100.46531 | G44: =F44/B44 -> 14.352187 | H44: =(F44/B44)^(1/7)-1 -> 0.46310001 | I44: =B44*(1+H17)^7*'Consumer Sleeve'!$B$7 -> 1.0328554 | J44: =I44/B44 -> 0.14755078 | K44: =(I44/B44)^(1/7)-1 -> -0.23918799 | L44: =B44*(1+I17)^7*'Consumer Sleeve'!$B$7 -> 0.58980004 | M44: =L44/B44 -> 0.084257149 | N44: =(L44/B44)^(1/7)-1 -> -0.29771199
A45: =A18 -> Polymarket | B45: =C18 -> 10.5 | C45: =B45*(1+F18)^7*'Consumer Sleeve'!$B$7 -> 42.057037 | D45: =C45/B45 -> 4.0054321 | E45: =(C45/B45)^(1/7)-1 -> 0.21925001 | F45: =B45*(1+G18)^7*'Consumer Sleeve'!$B$7 -> 92.974711 | G45: =F45/B45 -> 8.8547343 | H45: =(F45/B45)^(1/7)-1 -> 0.36556001 | I45: =B45*(1+H18)^7*'Consumer Sleeve'!$B$7 -> 6.159335 | J45: =I45/B45 -> 0.58660333 | K45: =(I45/B45)^(1/7)-1 -> -0.073369992 | L45: =B45*(1+I18)^7*'Consumer Sleeve'!$B$7 -> 3.6045188 | M45: =L45/B45 -> 0.3432875 | N45: =(L45/B45)^(1/7)-1 -> -0.14164799
A46: =A19 -> Goat Group | B46: =C19 -> 15 | C46: =B46*(1+F19)^7*'Consumer Sleeve'!$B$7 -> 33.51625 | D46: =C46/B46 -> 2.2344167 | E46: =(C46/B46)^(1/7)-1 -> 0.12171001 | F46: =B46*(1+G19)^7*'Consumer Sleeve'!$B$7 -> 70.931694 | G46: =F46/B46 -> 4.7287796 | H46: =(F46/B46)^(1/7)-1 -> 0.24851201 | I46: =B46*(1+H19)^7*'Consumer Sleeve'!$B$7 -> 5.1493125 | J46: =I46/B46 -> 0.3432875 | K46: =(I46/B46)^(1/7)-1 -> -0.14164799 | L46: =B46*(1+I19)^7*'Consumer Sleeve'!$B$7 -> 3.7181384 | M46: =L46/B46 -> 0.24787589 | N46: =(L46/B46)^(1/7)-1 -> -0.18066399
A47: =A20 -> Stripe | B47: =C20 -> 45 | C47: =B47*(1+F20)^7*'Consumer Sleeve'!$B$7 -> 120.41091 | D47: =C47/B47 -> 2.6757981 | E47: =(C47/B47)^(1/7)-1 -> 0.15097201 | F47: =B47*(1+G20)^7*'Consumer Sleeve'!$B$7 -> 308.90731 | G47: =F47/B47 -> 6.8646068 | H47: =(F47/B47)^(1/7)-1 -> 0.31679001 | I47: =B47*(1+H20)^7*'Consumer Sleeve'!$B$7 -> 26.39715 | J47: =I47/B47 -> 0.58660333 | K47: =(I47/B47)^(1/7)-1 -> -0.073369992 | L47: =B47*(1+I20)^7*'Consumer Sleeve'!$B$7 -> 21.086602 | M47: =L47/B47 -> 0.46859115 | N47: =(L47/B47)^(1/7)-1 -> -0.10263199
A48: SLEEVE TOTAL | B48: =SUM(B39:B47) -> 200 | C48: =SUM(C39:C47) -> 662.01427 | D48: =C48/B48 -> 3.3100714 | E48: =(C48/B48)^(1/7)-1 -> 0.18648562 | F48: =SUM(F39:F47) -> 1544.5338 | G48: =F48/B48 -> 7.7226691 | H48: =(F48/B48)^(1/7)-1 -> 0.33913363 | I48: =SUM(I39:I47) -> 149.23725 | J48: =I48/B48 -> 0.74618623 | K48: =(I48/B48)^(1/7)-1 -> -0.040963097 | L48: =SUM(L39:L47) -> 70.182739 | M48: =L48/B48 -> 0.35091369 | N48: =(L48/B48)^(1/7)-1 -> -0.13894951
A51: 10-YEAR HOLD — GROSS PROCEEDS
A52: Company | B52: Check ($M) | C52: Base $ | D52: Base MOIC | E52: Base IRR | F52: Bull $ | G52: Bull MOIC | H52: Bull IRR | I52: Bear $ | J52: Bear MOIC | K52: Bear IRR | L52: Shock $ | M52: Shock MOIC | N52: Shock IRR
A53: =A12 -> Quince | B53: =C12 -> 35 | C53: =B53*(1+F12)^10*'Consumer Sleeve'!$B$8 -> 309.9053 | D53: =C53/B53 -> 8.8544372 | E53: =(C53/B53)^(1/10)-1 -> 0.24370132 | F53: =B53*(1+G12)^10*'Consumer Sleeve'!$B$8 -> 1078.4731 | G53: =F53/B53 -> 30.813518 | H53: =(F53/B53)^(1/10)-1 -> 0.4088804 | I53: =B53*(1+H12)^10*'Consumer Sleeve'!$B$8 -> 31.998604 | J53: =I53/B53 -> 0.91424581 | K53: =(I53/B53)^(1/10)-1 -> -0.008925509 | L53: =B53*(1+I12)^10*'Consumer Sleeve'!$B$8 -> 3.6080108 | M53: =L53/B53 -> 0.10308602 | N53: =(L53/B53)^(1/10)-1 -> -0.20325384
A54: =A13 -> Whoop | B54: =C13 -> 31.5 | C54: =B54*(1+F13)^10*'Consumer Sleeve'!$B$8 -> 257.87487 | D54: =C54/B54 -> 8.1865039 | E54: =(C54/B54)^(1/10)-1 -> 0.23398491 | F54: =B54*(1+G13)^10*'Consumer Sleeve'!$B$8 -> 787.50852 | G54: =F54/B54 -> 25.00027 | H54: =(F54/B54)^(1/10)-1 -> 0.37973115 | I54: =B54*(1+H13)^10*'Consumer Sleeve'!$B$8 -> 17.421645 | J54: =I54/B54 -> 0.5530681 | K54: =(I54/B54)^(1/10)-1 -> -0.057507592 | L54: =B54*(1+I13)^10*'Consumer Sleeve'!$B$8 -> 4.1320415 | M54: =L54/B54 -> 0.13117592 | N54: =(L54/B54)^(1/10)-1 -> -0.18382101
A55: =A14 -> The Farmer's Dog | B55: =C14 -> 24.5 | C55: =B55*(1+F14)^10*'Consumer Sleeve'!$B$8 -> 134.2226 | D55: =C55/B55 -> 5.4784736 | E55: =(C55/B55)^(1/10)-1 -> 0.18540282 | F55: =B55*(1+G14)^10*'Consumer Sleeve'!$B$8 -> 342.98516 | G55: =F55/B55 -> 13.999394 | H55: =(F55/B55)^(1/10)-1 -> 0.30199982 | I55: =B55*(1+H14)^10*'Consumer Sleeve'!$B$8 -> 47.660018 | J55: =I55/B55 -> 1.9453068 | K55: =(I55/B55)^(1/10)-1 -> 0.068805824 | L55: =B55*(1+I14)^10*'Consumer Sleeve'!$B$8 -> 11.001791 | M55: =L55/B55 -> 0.4490527 | N55: =(L55/B55)^(1/10)-1 -> -0.076940425
A56: =A15 -> Made In Cookware | B56: =C15 -> 17.5 | C56: =B56*(1+F15)^10*'Consumer Sleeve'!$B$8 -> 48.65728 | D56: =C56/B56 -> 2.780416 | E56: =(C56/B56)^(1/10)-1 -> 0.10767149 | F56: =B56*(1+G15)^10*'Consumer Sleeve'!$B$8 -> 132.37463 | G56: =F56/B56 -> 7.5642646 | H56: =(F56/B56)^(1/10)-1 -> 0.22426849 | I56: =B56*(1+H15)^10*'Consumer Sleeve'!$B$8 -> 4.5764045 | J56: =I56/B56 -> 0.26150883 | K56: =(I56/B56)^(1/10)-1 -> -0.12552251 | L56: =B56*(1+I15)^10*'Consumer Sleeve'!$B$8 -> 2.9045832 | M56: =L56/B56 -> 0.16597618 | N56: =(L56/B56)^(1/10)-1 -> -0.16438817
A57: =A16 -> Thrive Market | B57: =C16 -> 14 | C57: =B57*(1+F16)^10*'Consumer Sleeve'!$B$8 -> 20.655089 | D57: =C57/B57 -> 1.4753635 | E57: =(C57/B57)^(1/10)-1 -> 0.039656574 | F57: =B57*(1+G16)^10*'Consumer Sleeve'!$B$8 -> 46.320068 | G57: =F57/B57 -> 3.3085763 | H57: =(F57/B57)^(1/10)-1 -> 0.12710432 | I57: =B57*(1+H16)^10*'Consumer Sleeve'!$B$8 -> 6.2867379 | J57: =I57/B57 -> 0.4490527 | K57: =(I57/B57)^(1/10)-1 -> -0.076940425 | L57: =B57*(1+I16)^10*'Consumer Sleeve'!$B$8 -> 4.5610788 | M57: =L57/B57 -> 0.32579134 | N57: =(L57/B57)^(1/10)-1 -> -0.10608967
A58: =A17 -> Plunge | B58: =C17 -> 7 | C58: =B58*(1+F17)^10*'Consumer Sleeve'!$B$8 -> 32.506616 | D58: =C58/B58 -> 4.6438023 | E58: =(C58/B58)^(1/10)-1 -> 0.16596999 | F58: =B58*(1+G17)^10*'Consumer Sleeve'!$B$8 -> 302.74146 | G58: =F58/B58 -> 43.248779 | H58: =(F58/B58)^(1/10)-1 -> 0.45746249 | I58: =B58*(1+H17)^10*'Consumer Sleeve'!$B$8 -> 0.43762823 | J58: =I58/B58 -> 0.062518319 | K58: =(I58/B58)^(1/10)-1 -> -0.24211951 | L58: =B58*(1+I17)^10*'Consumer Sleeve'!$B$8 -> 0.19655508 | M58: =L58/B58 -> 0.028079297 | N58: =(L58/B58)^(1/10)-1 -> -0.30041801
A59: =A18 -> Polymarket | B59: =C18 -> 10.5 | C59: =B59*(1+F18)^10*'Consumer Sleeve'!$B$8 -> 73.341653 | D59: =C59/B59 -> 6.9849193 | E59: =(C59/B59)^(1/10)-1 -> 0.21455207 | F59: =B59*(1+G18)^10*'Consumer Sleeve'!$B$8 -> 227.78804 | G59: =F59/B59 -> 21.694099 | H59: =(F59/B59)^(1/10)-1 -> 0.36029832 | I59: =B59*(1+H18)^10*'Consumer Sleeve'!$B$8 -> 4.7150534 | J59: =I59/B59 -> 0.4490527 | K59: =(I59/B59)^(1/10)-1 -> -0.076940425 | L59: =B59*(1+I18)^10*'Consumer Sleeve'!$B$8 -> 2.1931952 | M59: =L59/B59 -> 0.20887573 | N59: =(L59/B59)^(1/10)-1 -> -0.14495534
A60: =A19 -> Goat Group | B60: =C19 -> 15 | C60: =B60*(1+F19)^10*'Consumer Sleeve'!$B$8 -> 45.512525 | D60: =C60/B60 -> 3.0341683 | E60: =(C60/B60)^(1/10)-1 -> 0.11738791 | F60: =B60*(1+G19)^10*'Consumer Sleeve'!$B$8 -> 132.81656 | G60: =F60/B60 -> 8.8544372 | H60: =(F60/B60)^(1/10)-1 -> 0.24370132 | I60: =B60*(1+H19)^10*'Consumer Sleeve'!$B$8 -> 3.133136 | J60: =I60/B60 -> 0.20887573 | K60: =(I60/B60)^(1/10)-1 -> -0.14495534 | L60: =B60*(1+I19)^10*'Consumer Sleeve'!$B$8 -> 1.9676388 | M60: =L60/B60 -> 0.13117592 | N60: =(L60/B60)^(1/10)-1 -> -0.18382101
A61: =A20 -> Stripe | B61: =C20 -> 45 | C61: =B61*(1+F20)^10*'Consumer Sleeve'!$B$8 -> 176.64195 | D61: =C61/B61 -> 3.9253767 | E61: =(C61/B61)^(1/10)-1 -> 0.14653716 | F61: =B61*(1+G20)^10*'Consumer Sleeve'!$B$8 -> 678.59626 | G61: =F61/B61 -> 15.079917 | H61: =(F61/B61)^(1/10)-1 -> 0.31171624 | I61: =B61*(1+H20)^10*'Consumer Sleeve'!$B$8 -> 20.207372 | J61: =I61/B61 -> 0.4490527 | K61: =(I61/B61)^(1/10)-1 -> -0.076940425 | L61: =B61*(1+I20)^10*'Consumer Sleeve'!$B$8 -> 14.66061 | M61: =L61/B61 -> 0.32579134 | N61: =(L61/B61)^(1/10)-1 -> -0.10608967
A62: SLEEVE TOTAL | B62: =SUM(B53:B61) -> 200 | C62: =SUM(C53:C61) -> 1099.3179 | D62: =C62/B62 -> 5.4965894 | E62: =(C62/B62)^(1/10)-1 -> 0.18579422 | F62: =SUM(F53:F61) -> 3729.6038 | G62: =F62/B62 -> 18.648019 | H62: =(F62/B62)^(1/10)-1 -> 0.33987187 | I62: =SUM(I53:I61) -> 136.4366 | J62: =I62/B62 -> 0.68218299 | K62: =(I62/B62)^(1/10)-1 -> -0.037523602 | L62: =SUM(L53:L61) -> 45.225505 | M62: =L62/B62 -> 0.22612753 | N62: =(L62/B62)^(1/10)-1 -> -0.13814274
A65: METHODOLOGY / DATA-CONFIDENCE NOTE
A66: Marks are now tiered by evidence quality. Quince and Whoop are confirmed 2026 primary rounds (both $10.1B post-money, Mar-26). The Farmer's Dog and Thrive Market are MARKET-PRICED off live Forge Global secondary quotes (22-Sep-26): Farmer's Dog implies $3.76B (up from its $2.5B Series E in Jun-22 — real appreciation, and its Walmart.com launch in 2025 is the modeled upside catalyst); Thrive Market implies ~$945M (DOWN ~27% from its $1.29B Series C post-money in Jul-21, despite revenue growing from $400M to $700M+ over the same period — genuine multiple compression, not a data gap, which is why its Base/Bull CAGRs were cut and its Bear turned negative). Made In Cookware and Plunge remain unpriced: Made In has raised only ~$8.3M total (no institutional round large enough to anchor an EV) and Plunge has raised just $4.75M against an estimated ~$200M in lifetime sales by 2025 (mostly self-funded) — both entry marks are directional estimates with no market to check them against, and are the first things to re-underwrite before a check is cut. Bear vs. Shock differ by name rather than using one sleeve-wide spread: staple/subscription names (Farmer's Dog, Thrive Market) see Shock milder than Bear — food/grocery spend is defensive and some trade-down benefit offsets inflation; import- or hardware-exposed names (Quince's direct-factory M2C sourcing, Whoop's own chip-dependent hardware, Made In's imported cookware inputs, Plunge's hardware BOM) see Shock worse than Bear — a Taiwan/decoupling scenario hits their COGS and supply chain directly, on top of softer discretionary demand. Polymarket added at $15M check (~$18B entry mark, mid of $14-21B secondary range Sep-26); Base 25%/Bull 40%/Bear -5%/Shock -12% — volume/fee leverage + US expansion convexity, with regulatory/competitive risk in Bear/Shock. Goat Group and Stripe were added Sep-26: Goat Group's last priced round is its Series F (24-Jun-21, $3.73B post, $195M raise); Forge Global shows no active secondary match for it, so — like Made In and Plunge — it is an unpriced, stale mark and among the first names to re-underwrite. Stripe is the opposite end of the confidence spectrum: MARKET-PRICED off a live, recurring employee tender ($159B post, 24-Feb-26, up from ~$140B guided 9-Feb-26 and ~$91.5B in the Feb-25 tender), with payment volume +34% YoY — the most liquid, best-evidenced mark in the sleeve. Both checks were funded by trimming the other seven positions pro-rata (×0.7× of prior check size) so total sleeve checks stay at exactly $200M, matching the Holdco Summary sleeve cap.

Sheet PME, DPI & Sensitivity
A1: PME, DPI & PROBABILITY PRESSURE TEST
A2: DPI/TVPI, KS-PME & Direct Alpha vs SPX/NDX, and Expected Net IRR sensitivity to the TSMC-Shock probability. Rows 11-69 = IQT-mirror sleeve ($250M) only; rows 72+ = total $840M holdco (all three sleeves) — ties to IC Summary headline.
A4: PUBLIC-MARKET BENCHMARK ASSUMPTIONS (blue = lever)
A5: S&P 500 (SPX) total-return CAGR | B5: 0.09
A6: Nasdaq-100 (NDX) total-return CAGR | B6: 0.13
A7: Long-run total-return assumptions; edit to your house view. KS-PME>1.0x = beat the index.
A9: Method: single terminal exit -> KS-PME = Net MOIC / index total-return multiple over the hold; Direct Alpha = KS-PME^(1/Hold)-1 (annualized outperformance). Paid-in assumed fully drawn = committed, so Net DPI = Net MOIC and RVPI=0 at exit (TVPI=DPI).
A11: IQT-MIRROR SLEEVE ($250M) — 5-YEAR DPI & PME
A12: Metric | B12: Base | C12: Bull | D12: Bear | E12: TSMC-Shock | F12: Expected
A13: Net MOIC | B13: ='Fund Economics'!B14 -> 2.0045241 | C13: ='Fund Economics'!C14 -> 3.0878221 | D13: ='Fund Economics'!D14 -> 0.4051741 | E13: ='Fund Economics'!E14 -> 3.1231658 | F13: ='Fund Economics'!F14 -> 2.2032424
A14: Net DPI (to LP; =TVPI at exit) | B14: ='Fund Economics'!B12/Assumptions!$B$5 -> 2.0045241 | C14: ='Fund Economics'!C12/Assumptions!$B$5 -> 3.0878221 | D14: ='Fund Economics'!D12/Assumptions!$B$5 -> 0.4051741 | E14: ='Fund Economics'!E12/Assumptions!$B$5 -> 3.1231658 | F14: ='Fund Economics'!F12/Assumptions!$B$5 -> 2.2032424
A15: Gross DPI (deal-level) | B15: ='Fund Economics'!B6/Assumptions!$B$5 -> 2.2633231 | C15: ='Fund Economics'!C6/Assumptions!$B$5 -> 3.6174457 | D15: ='Fund Economics'!D6/Assumptions!$B$5 -> 0.5051741 | E15: ='Fund Economics'!E6/Assumptions!$B$5 -> 3.6616253 | F15: ='Fund Economics'!F6/Assumptions!$B$5 -> 2.5478767
A16: Net IRR | B16: ='Fund Economics'!B16 -> 0.14921757 | C16: ='Fund Economics'!C16 -> 0.25294052 | D16: ='Fund Economics'!D16 -> -0.16530399 | E16: ='Fund Economics'!E16 -> 0.25579575 | F16: ='Fund Economics'!F16 -> 0.17114982
A17: SPX total-return multiple | B17: =(1+'PME, DPI & Sensitivity'!$B$5)^5 -> 1.538624 | C17: =(1+'PME, DPI & Sensitivity'!$B$5)^5 -> 1.538624 | D17: =(1+'PME, DPI & Sensitivity'!$B$5)^5 -> 1.538624 | E17: =(1+'PME, DPI & Sensitivity'!$B$5)^5 -> 1.538624 | F17: =(1+'PME, DPI & Sensitivity'!$B$5)^5 -> 1.538624
A18: Net KS-PME vs SPX | B18: ='Fund Economics'!B14/(1+'PME, DPI & Sensitivity'!$B$5)^5 -> 1.3028031 | C18: ='Fund Economics'!C14/(1+'PME, DPI & Sensitivity'!$B$5)^5 -> 2.0068725 | D18: ='Fund Economics'!D14/(1+'PME, DPI & Sensitivity'!$B$5)^5 -> 0.26333537 | E18: ='Fund Economics'!E14/(1+'PME, DPI & Sensitivity'!$B$5)^5 -> 2.0298435 | F18: ='Fund Economics'!F14/(1+'PME, DPI & Sensitivity'!$B$5)^5 -> 1.4319564
A19: Direct Alpha vs SPX (ann.) | B19: =('Fund Economics'!B14/(1+'PME, DPI & Sensitivity'!$B$5)^5)^(1/5)-1 -> 0.054328045 | C19: =('Fund Economics'!C14/(1+'PME, DPI & Sensitivity'!$B$5)^5)^(1/5)-1 -> 0.14948672 | D19: =('Fund Economics'!D14/(1+'PME, DPI & Sensitivity'!$B$5)^5)^(1/5)-1 -> -0.23422385 | E19: =('Fund Economics'!E14/(1+'PME, DPI & Sensitivity'!$B$5)^5)^(1/5)-1 -> 0.15210619 | F19: =('Fund Economics'!F14/(1+'PME, DPI & Sensitivity'!$B$5)^5)^(1/5)-1 -> 0.074449374
A20: NDX total-return multiple | B20: =(1+'PME, DPI & Sensitivity'!$B$6)^5 -> 1.8424352 | C20: =(1+'PME, DPI & Sensitivity'!$B$6)^5 -> 1.8424352 | D20: =(1+'PME, DPI & Sensitivity'!$B$6)^5 -> 1.8424352 | E20: =(1+'PME, DPI & Sensitivity'!$B$6)^5 -> 1.8424352 | F20: =(1+'PME, DPI & Sensitivity'!$B$6)^5 -> 1.8424352
A21: Net KS-PME vs NDX | B21: ='Fund Economics'!B14/(1+'PME, DPI & Sensitivity'!$B$6)^5 -> 1.0879754 | C21: ='Fund Economics'!C14/(1+'PME, DPI & Sensitivity'!$B$6)^5 -> 1.6759462 | D21: ='Fund Economics'!D14/(1+'PME, DPI & Sensitivity'!$B$6)^5 -> 0.21991227 | E21: ='Fund Economics'!E14/(1+'PME, DPI & Sensitivity'!$B$6)^5 -> 1.6951293 | F21: ='Fund Economics'!F14/(1+'PME, DPI & Sensitivity'!$B$6)^5 -> 1.1958317
A22: Direct Alpha vs NDX (ann.) | B22: =('Fund Economics'!B14/(1+'PME, DPI & Sensitivity'!$B$6)^5)^(1/5)-1 -> 0.017006698 | C22: =('Fund Economics'!C14/(1+'PME, DPI & Sensitivity'!$B$6)^5)^(1/5)-1 -> 0.10879692 | D22: =('Fund Economics'!D14/(1+'PME, DPI & Sensitivity'!$B$6)^5)^(1/5)-1 -> -0.26133097 | E22: =('Fund Economics'!E14/(1+'PME, DPI & Sensitivity'!$B$6)^5)^(1/5)-1 -> 0.11132367 | F22: =('Fund Economics'!F14/(1+'PME, DPI & Sensitivity'!$B$6)^5)^(1/5)-1 -> 0.036415768
A23: memo: Gross KS-PME vs SPX | B23: =('Fund Economics'!B6/Assumptions!$B$5)/(1+'PME, DPI & Sensitivity'!$B$5)^5 -> 1.4710047 | C23: =('Fund Economics'!C6/Assumptions!$B$5)/(1+'PME, DPI & Sensitivity'!$B$5)^5 -> 2.3510915 | D23: =('Fund Economics'!D6/Assumptions!$B$5)/(1+'PME, DPI & Sensitivity'!$B$5)^5 -> 0.3283285 | E23: =('Fund Economics'!E6/Assumptions!$B$5)/(1+'PME, DPI & Sensitivity'!$B$5)^5 -> 2.3798052 | F23: =('Fund Economics'!F6/Assumptions!$B$5)/(1+'PME, DPI & Sensitivity'!$B$5)^5 -> 1.6559451
A24: memo: Gross KS-PME vs NDX | B24: =('Fund Economics'!B6/Assumptions!$B$5)/(1+'PME, DPI & Sensitivity'!$B$6)^5 -> 1.2284411 | C24: =('Fund Economics'!C6/Assumptions!$B$5)/(1+'PME, DPI & Sensitivity'!$B$6)^5 -> 1.9634046 | D24: =('Fund Economics'!D6/Assumptions!$B$5)/(1+'PME, DPI & Sensitivity'!$B$6)^5 -> 0.27418826 | E24: =('Fund Economics'!E6/Assumptions!$B$5)/(1+'PME, DPI & Sensitivity'!$B$6)^5 -> 1.9873835 | F24: =('Fund Economics'!F6/Assumptions!$B$5)/(1+'PME, DPI & Sensitivity'!$B$6)^5 -> 1.3828854
A27: IQT-MIRROR SLEEVE ($250M) — 7-YEAR DPI & PME
A28: Metric | B28: Base | C28: Bull | D28: Bear | E28: TSMC-Shock | F28: Expected
A29: Net MOIC | B29: ='Fund Economics'!B30 -> 2.6927833 | C29: ='Fund Economics'!C30 -> 4.9931818 | D29: ='Fund Economics'!D30 -> 0.26013475 | E29: ='Fund Economics'!E30 -> 5.1385969 | F29: ='Fund Economics'!F30 -> 3.2698577
A30: Net DPI (to LP; =TVPI at exit) | B30: ='Fund Economics'!B28/Assumptions!$B$5 -> 2.6927833 | C30: ='Fund Economics'!C28/Assumptions!$B$5 -> 4.9931818 | D30: ='Fund Economics'!D28/Assumptions!$B$5 -> 0.26013475 | E30: ='Fund Economics'!E28/Assumptions!$B$5 -> 5.1385969 | F30: ='Fund Economics'!F28/Assumptions!$B$5 -> 3.2698577
A31: Gross DPI (deal-level) | B31: ='Fund Economics'!B22/Assumptions!$B$5 -> 3.1125231 | C31: ='Fund Economics'!C22/Assumptions!$B$5 -> 5.9880212 | D31: ='Fund Economics'!D22/Assumptions!$B$5 -> 0.40013475 | E31: ='Fund Economics'!E22/Assumptions!$B$5 -> 6.1697901 | F31: ='Fund Economics'!F22/Assumptions!$B$5 -> 3.8831294
A32: Net IRR | B32: ='Fund Economics'!B32 -> 0.1520129 | C32: ='Fund Economics'!C32 -> 0.25825364 | D32: ='Fund Economics'!D32 -> -0.17499437 | E32: ='Fund Economics'!E32 -> 0.26342429 | F32: ='Fund Economics'!F32 -> 0.18441561
A33: SPX total-return multiple | B33: =(1+'PME, DPI & Sensitivity'!$B$5)^7 -> 1.8280391 | C33: =(1+'PME, DPI & Sensitivity'!$B$5)^7 -> 1.8280391 | D33: =(1+'PME, DPI & Sensitivity'!$B$5)^7 -> 1.8280391 | E33: =(1+'PME, DPI & Sensitivity'!$B$5)^7 -> 1.8280391 | F33: =(1+'PME, DPI & Sensitivity'!$B$5)^7 -> 1.8280391
A34: Net KS-PME vs SPX | B34: ='Fund Economics'!B30/(1+'PME, DPI & Sensitivity'!$B$5)^7 -> 1.4730447 | C34: ='Fund Economics'!C30/(1+'PME, DPI & Sensitivity'!$B$5)^7 -> 2.7314414 | D34: ='Fund Economics'!D30/(1+'PME, DPI & Sensitivity'!$B$5)^7 -> 0.14230262 | E34: ='Fund Economics'!E30/(1+'PME, DPI & Sensitivity'!$B$5)^7 -> 2.8109885 | F34: ='Fund Economics'!F30/(1+'PME, DPI & Sensitivity'!$B$5)^7 -> 1.7887241
A35: Direct Alpha vs SPX (ann.) | B35: =('Fund Economics'!B30/(1+'PME, DPI & Sensitivity'!$B$5)^7)^(1/7)-1 -> 0.056892573 | C35: =('Fund Economics'!C30/(1+'PME, DPI & Sensitivity'!$B$5)^7)^(1/7)-1 -> 0.15436114 | D35: =('Fund Economics'!D30/(1+'PME, DPI & Sensitivity'!$B$5)^7)^(1/7)-1 -> -0.2431141 | E35: =('Fund Economics'!E30/(1+'PME, DPI & Sensitivity'!$B$5)^7)^(1/7)-1 -> 0.15910485 | F35: =('Fund Economics'!F30/(1+'PME, DPI & Sensitivity'!$B$5)^7)^(1/7)-1 -> 0.086619824
A36: NDX total-return multiple | B36: =(1+'PME, DPI & Sensitivity'!$B$6)^7 -> 2.3526055 | C36: =(1+'PME, DPI & Sensitivity'!$B$6)^7 -> 2.3526055 | D36: =(1+'PME, DPI & Sensitivity'!$B$6)^7 -> 2.3526055 | E36: =(1+'PME, DPI & Sensitivity'!$B$6)^7 -> 2.3526055 | F36: =(1+'PME, DPI & Sensitivity'!$B$6)^7 -> 2.3526055
A37: Net KS-PME vs NDX | B37: ='Fund Economics'!B30/(1+'PME, DPI & Sensitivity'!$B$6)^7 -> 1.1445962 | C37: ='Fund Economics'!C30/(1+'PME, DPI & Sensitivity'!$B$6)^7 -> 2.1224051 | D37: ='Fund Economics'!D30/(1+'PME, DPI & Sensitivity'!$B$6)^7 -> 0.11057305 | E37: ='Fund Economics'!E30/(1+'PME, DPI & Sensitivity'!$B$6)^7 -> 2.1842153 | F37: ='Fund Economics'!F30/(1+'PME, DPI & Sensitivity'!$B$6)^7 -> 1.3898878
A38: Direct Alpha vs NDX (ann.) | B38: =('Fund Economics'!B30/(1+'PME, DPI & Sensitivity'!$B$6)^7)^(1/7)-1 -> 0.019480447 | C38: =('Fund Economics'!C30/(1+'PME, DPI & Sensitivity'!$B$6)^7)^(1/7)-1 -> 0.1134988 | D38: =('Fund Economics'!D30/(1+'PME, DPI & Sensitivity'!$B$6)^7)^(1/7)-1 -> -0.26990652 | E38: =('Fund Economics'!E30/(1+'PME, DPI & Sensitivity'!$B$6)^7)^(1/7)-1 -> 0.11807459 | F38: =('Fund Economics'!F30/(1+'PME, DPI & Sensitivity'!$B$6)^7)^(1/7)-1 -> 0.048155405
A39: memo: Gross KS-PME vs SPX | B39: =('Fund Economics'!B22/Assumptions!$B$5)/(1+'PME, DPI & Sensitivity'!$B$5)^7 -> 1.7026567 | C39: =('Fund Economics'!C22/Assumptions!$B$5)/(1+'PME, DPI & Sensitivity'!$B$5)^7 -> 3.2756526 | D39: =('Fund Economics'!D22/Assumptions!$B$5)/(1+'PME, DPI & Sensitivity'!$B$5)^7 -> 0.21888741 | E39: =('Fund Economics'!E22/Assumptions!$B$5)/(1+'PME, DPI & Sensitivity'!$B$5)^7 -> 3.3750865 | F39: =('Fund Economics'!F22/Assumptions!$B$5)/(1+'PME, DPI & Sensitivity'!$B$5)^7 -> 2.1242048
A40: memo: Gross KS-PME vs NDX | B40: =('Fund Economics'!B22/Assumptions!$B$5)/(1+'PME, DPI & Sensitivity'!$B$6)^7 -> 1.3230111 | C40: =('Fund Economics'!C22/Assumptions!$B$5)/(1+'PME, DPI & Sensitivity'!$B$6)^7 -> 2.5452721 | D40: =('Fund Economics'!D22/Assumptions!$B$5)/(1+'PME, DPI & Sensitivity'!$B$6)^7 -> 0.17008154 | E40: =('Fund Economics'!E22/Assumptions!$B$5)/(1+'PME, DPI & Sensitivity'!$B$6)^7 -> 2.622535 | F40: =('Fund Economics'!F22/Assumptions!$B$5)/(1+'PME, DPI & Sensitivity'!$B$6)^7 -> 1.6505655
A43: IQT-MIRROR SLEEVE ($250M) — 10-YEAR DPI & PME
A44: Metric | B44: Base | C44: Bull | D44: Bear | E44: TSMC-Shock | F44: Expected
A45: Net MOIC | B45: ='Fund Economics'!B46 -> 4.268444 | C45: ='Fund Economics'!C46 -> 10.464416 | D45: ='Fund Economics'!D46 -> 0.095853416 | E45: ='Fund Economics'!E46 -> 11.16971 | F45: ='Fund Economics'!F46 -> 6.2267383
A46: Net DPI (to LP; =TVPI at exit) | B46: ='Fund Economics'!B44/Assumptions!$B$5 -> 4.268444 | C46: ='Fund Economics'!C44/Assumptions!$B$5 -> 10.464416 | D46: ='Fund Economics'!D44/Assumptions!$B$5 -> 0.095853416 | E46: ='Fund Economics'!E44/Assumptions!$B$5 -> 11.16971 | F46: ='Fund Economics'!F44/Assumptions!$B$5 -> 6.2267383
A47: Gross DPI (deal-level) | B47: ='Fund Economics'!B38/Assumptions!$B$5 -> 5.0458237 | C47: ='Fund Economics'!C38/Assumptions!$B$5 -> 12.790789 | D47: ='Fund Economics'!D38/Assumptions!$B$5 -> 0.29585342 | E47: ='Fund Economics'!E38/Assumptions!$B$5 -> 13.672406 | F47: ='Fund Economics'!F38/Assumptions!$B$5 -> 7.5635568
A48: Net IRR | B48: ='Fund Economics'!B48 -> 0.15618401 | C48: ='Fund Economics'!C48 -> 0.26465335 | D48: ='Fund Economics'!D48 -> -0.20902864 | E48: ='Fund Economics'!E48 -> 0.27292902 | F48: ='Fund Economics'!F48 -> 0.20067664
A49: SPX total-return multiple | B49: =(1+'PME, DPI & Sensitivity'!$B$5)^10 -> 2.3673637 | C49: =(1+'PME, DPI & Sensitivity'!$B$5)^10 -> 2.3673637 | D49: =(1+'PME, DPI & Sensitivity'!$B$5)^10 -> 2.3673637 | E49: =(1+'PME, DPI & Sensitivity'!$B$5)^10 -> 2.3673637 | F49: =(1+'PME, DPI & Sensitivity'!$B$5)^10 -> 2.3673637
A50: Net KS-PME vs SPX | B50: ='Fund Economics'!B46/(1+'PME, DPI & Sensitivity'!$B$5)^10 -> 1.8030369 | C50: ='Fund Economics'!C46/(1+'PME, DPI & Sensitivity'!$B$5)^10 -> 4.4202824 | D50: ='Fund Economics'!D46/(1+'PME, DPI & Sensitivity'!$B$5)^10 -> 0.040489519 | E50: ='Fund Economics'!E46/(1+'PME, DPI & Sensitivity'!$B$5)^10 -> 4.7182061 | F50: ='Fund Economics'!F46/(1+'PME, DPI & Sensitivity'!$B$5)^10 -> 2.6302415
A51: Direct Alpha vs SPX (ann.) | B51: =('Fund Economics'!B46/(1+'PME, DPI & Sensitivity'!$B$5)^10)^(1/10)-1 -> 0.060719275 | C51: =('Fund Economics'!C46/(1+'PME, DPI & Sensitivity'!$B$5)^10)^(1/10)-1 -> 0.16023243 | D51: =('Fund Economics'!D46/(1+'PME, DPI & Sensitivity'!$B$5)^10)^(1/10)-1 -> -0.2743382 | E51: =('Fund Economics'!E46/(1+'PME, DPI & Sensitivity'!$B$5)^10)^(1/10)-1 -> 0.16782479 | F51: =('Fund Economics'!F46/(1+'PME, DPI & Sensitivity'!$B$5)^10)^(1/10)-1 -> 0.1015382
A52: NDX total-return multiple | B52: =(1+'PME, DPI & Sensitivity'!$B$6)^10 -> 3.3945674 | C52: =(1+'PME, DPI & Sensitivity'!$B$6)^10 -> 3.3945674 | D52: =(1+'PME, DPI & Sensitivity'!$B$6)^10 -> 3.3945674 | E52: =(1+'PME, DPI & Sensitivity'!$B$6)^10 -> 3.3945674 | F52: =(1+'PME, DPI & Sensitivity'!$B$6)^10 -> 3.3945674
A53: Net KS-PME vs NDX | B53: ='Fund Economics'!B46/(1+'PME, DPI & Sensitivity'!$B$6)^10 -> 1.2574339 | C53: ='Fund Economics'!C46/(1+'PME, DPI & Sensitivity'!$B$6)^10 -> 3.082695 | D53: ='Fund Economics'!D46/(1+'PME, DPI & Sensitivity'!$B$6)^10 -> 0.028237299 | E53: ='Fund Economics'!E46/(1+'PME, DPI & Sensitivity'!$B$6)^10 -> 3.2904663 | F53: ='Fund Economics'!F46/(1+'PME, DPI & Sensitivity'!$B$6)^10 -> 1.8343245
A54: Direct Alpha vs NDX (ann.) | B54: =('Fund Economics'!B46/(1+'PME, DPI & Sensitivity'!$B$6)^10)^(1/10)-1 -> 0.02317169 | C54: =('Fund Economics'!C46/(1+'PME, DPI & Sensitivity'!$B$6)^10)^(1/10)-1 -> 0.11916226 | D54: =('Fund Economics'!D46/(1+'PME, DPI & Sensitivity'!$B$6)^10)^(1/10)-1 -> -0.30002534 | E54: =('Fund Economics'!E46/(1+'PME, DPI & Sensitivity'!$B$6)^10)^(1/10)-1 -> 0.12648586 | F54: =('Fund Economics'!F46/(1+'PME, DPI & Sensitivity'!$B$6)^10)^(1/10)-1 -> 0.062545699
A55: memo: Gross KS-PME vs SPX | B55: =('Fund Economics'!B38/Assumptions!$B$5)/(1+'PME, DPI & Sensitivity'!$B$5)^10 -> 2.1314105 | C55: =('Fund Economics'!C38/Assumptions!$B$5)/(1+'PME, DPI & Sensitivity'!$B$5)^10 -> 5.4029674 | D55: =('Fund Economics'!D38/Assumptions!$B$5)/(1+'PME, DPI & Sensitivity'!$B$5)^10 -> 0.12497168 | E55: =('Fund Economics'!E38/Assumptions!$B$5)/(1+'PME, DPI & Sensitivity'!$B$5)^10 -> 5.775372 | F55: =('Fund Economics'!F38/Assumptions!$B$5)/(1+'PME, DPI & Sensitivity'!$B$5)^10 -> 3.1949281
A56: memo: Gross KS-PME vs NDX | B56: =('Fund Economics'!B38/Assumptions!$B$5)/(1+'PME, DPI & Sensitivity'!$B$6)^10 -> 1.4864409 | C56: =('Fund Economics'!C38/Assumptions!$B$5)/(1+'PME, DPI & Sensitivity'!$B$6)^10 -> 3.7680173 | D56: =('Fund Economics'!D38/Assumptions!$B$5)/(1+'PME, DPI & Sensitivity'!$B$6)^10 -> 0.087154969 | E56: =('Fund Economics'!E38/Assumptions!$B$5)/(1+'PME, DPI & Sensitivity'!$B$6)^10 -> 4.0277314 | F56: =('Fund Economics'!F38/Assumptions!$B$5)/(1+'PME, DPI & Sensitivity'!$B$6)^10 -> 2.2281357
A59: IQT-MIRROR SLEEVE ($250M) — TSMC-SHOCK PROBABILITY PRESSURE TEST
A60: Expected Net IRR to LP (IQT-mirror sleeve only) as the TSMC-Shock probability varies. Base/Bull/Bear keep their current relative weights; shock takes the remainder. The row flagged 'current base case' matches Defense Supercycle!B20.
A61: Shock probability | B61: 5-yr Net IRR | C61: 7-yr Net IRR | D61: 10-yr Net IRR | E61: Note
A62: 0 | B62: =(((1-$A62)*('Defense Supercycle'!$B$17*'Fund Economics'!B12+'Defense Supercycle'!$B$18*'Fund Economics'!C12+'Defense Supercycle'!$B$19*'Fund Economics'!D12)/('Defense Supercycle'!$B$17+'Defense Supercycle'!$B$18+'Defense Supercycle'!$B$19)+$A62*'Fund Economics'!E12)/Assumptions!$B$5)^(1/5)-1 -> 0.1533589 | C62: =(((1-$A62)*('Defense Supercycle'!$B$17*'Fund Economics'!B28+'Defense Supercycle'!$B$18*'Fund Economics'!C28+'Defense Supercycle'!$B$19*'Fund Economics'!D28)/('Defense Supercycle'!$B$17+'Defense Supercycle'!$B$18+'Defense Supercycle'!$B$19)+$A62*'Fund Economics'!E28)/Assumptions!$B$5)^(1/7)-1 -> 0.16656369 | D62: =(((1-$A62)*('Defense Supercycle'!$B$17*'Fund Economics'!B44+'Defense Supercycle'!$B$18*'Fund Economics'!C44+'Defense Supercycle'!$B$19*'Fund Economics'!D44)/('Defense Supercycle'!$B$17+'Defense Supercycle'!$B$18+'Defense Supercycle'!$B$19)+$A62*'Fund Economics'!E44)/Assumptions!$B$5)^(1/10)-1 -> 0.18269151 | E62: shock excluded
A63: 0.05 | B63: =(((1-$A63)*('Defense Supercycle'!$B$17*'Fund Economics'!B12+'Defense Supercycle'!$B$18*'Fund Economics'!C12+'Defense Supercycle'!$B$19*'Fund Economics'!D12)/('Defense Supercycle'!$B$17+'Defense Supercycle'!$B$18+'Defense Supercycle'!$B$19)+$A63*'Fund Economics'!E12)/Assumptions!$B$5)^(1/5)-1 -> 0.15941115 | C63: =(((1-$A63)*('Defense Supercycle'!$B$17*'Fund Economics'!B28+'Defense Supercycle'!$B$18*'Fund Economics'!C28+'Defense Supercycle'!$B$19*'Fund Economics'!D28)/('Defense Supercycle'!$B$17+'Defense Supercycle'!$B$18+'Defense Supercycle'!$B$19)+$A63*'Fund Economics'!E28)/Assumptions!$B$5)^(1/7)-1 -> 0.172697 | D63: =(((1-$A63)*('Defense Supercycle'!$B$17*'Fund Economics'!B44+'Defense Supercycle'!$B$18*'Fund Economics'!C44+'Defense Supercycle'!$B$19*'Fund Economics'!D44)/('Defense Supercycle'!$B$17+'Defense Supercycle'!$B$18+'Defense Supercycle'!$B$19)+$A63*'Fund Economics'!E44)/Assumptions!$B$5)^(1/10)-1 -> 0.18896214 | E63: =IF(ABS($A63-'Defense Supercycle'!$B$20)<0.0001,"current base case","")
A64: 0.1 | B64: =(((1-$A64)*('Defense Supercycle'!$B$17*'Fund Economics'!B12+'Defense Supercycle'!$B$18*'Fund Economics'!C12+'Defense Supercycle'!$B$19*'Fund Economics'!D12)/('Defense Supercycle'!$B$17+'Defense Supercycle'!$B$18+'Defense Supercycle'!$B$19)+$A64*'Fund Economics'!E12)/Assumptions!$B$5)^(1/5)-1 -> 0.1653396 | C64: =(((1-$A64)*('Defense Supercycle'!$B$17*'Fund Economics'!B28+'Defense Supercycle'!$B$18*'Fund Economics'!C28+'Defense Supercycle'!$B$19*'Fund Economics'!D28)/('Defense Supercycle'!$B$17+'Defense Supercycle'!$B$18+'Defense Supercycle'!$B$19)+$A64*'Fund Economics'!E28)/Assumptions!$B$5)^(1/7)-1 -> 0.17864368 | D64: =(((1-$A64)*('Defense Supercycle'!$B$17*'Fund Economics'!B44+'Defense Supercycle'!$B$18*'Fund Economics'!C44+'Defense Supercycle'!$B$19*'Fund Economics'!D44)/('Defense Supercycle'!$B$17+'Defense Supercycle'!$B$18+'Defense Supercycle'!$B$19)+$A64*'Fund Economics'!E44)/Assumptions!$B$5)^(1/10)-1 -> 0.19494855 | E64: =IF(ABS($A64-'Defense Supercycle'!$B$20)<0.0001,"current base case","")
A65: 0.15 | B65: =(((1-$A65)*('Defense Supercycle'!$B$17*'Fund Economics'!B12+'Defense Supercycle'!$B$18*'Fund Economics'!C12+'Defense Supercycle'!$B$19*'Fund Economics'!D12)/('Defense Supercycle'!$B$17+'Defense Supercycle'!$B$18+'Defense Supercycle'!$B$19)+$A65*'Fund Economics'!E12)/Assumptions!$B$5)^(1/5)-1 -> 0.17114982 | C65: =(((1-$A65)*('Defense Supercycle'!$B$17*'Fund Economics'!B28+'Defense Supercycle'!$B$18*'Fund Economics'!C28+'Defense Supercycle'!$B$19*'Fund Economics'!D28)/('Defense Supercycle'!$B$17+'Defense Supercycle'!$B$18+'Defense Supercycle'!$B$19)+$A65*'Fund Economics'!E28)/Assumptions!$B$5)^(1/7)-1 -> 0.18441561 | D65: =(((1-$A65)*('Defense Supercycle'!$B$17*'Fund Economics'!B44+'Defense Supercycle'!$B$18*'Fund Economics'!C44+'Defense Supercycle'!$B$19*'Fund Economics'!D44)/('Defense Supercycle'!$B$17+'Defense Supercycle'!$B$18+'Defense Supercycle'!$B$19)+$A65*'Fund Economics'!E44)/Assumptions!$B$5)^(1/10)-1 -> 0.20067664 | E65: =IF(ABS($A65-'Defense Supercycle'!$B$20)<0.0001,"current base case","") -> current base case
A66: 0.2 | B66: =(((1-$A66)*('Defense Supercycle'!$B$17*'Fund Economics'!B12+'Defense Supercycle'!$B$18*'Fund Economics'!C12+'Defense Supercycle'!$B$19*'Fund Economics'!D12)/('Defense Supercycle'!$B$17+'Defense Supercycle'!$B$18+'Defense Supercycle'!$B$19)+$A66*'Fund Economics'!E12)/Assumptions!$B$5)^(1/5)-1 -> 0.17684697 | C66: =(((1-$A66)*('Defense Supercycle'!$B$17*'Fund Economics'!B28+'Defense Supercycle'!$B$18*'Fund Economics'!C28+'Defense Supercycle'!$B$19*'Fund Economics'!D28)/('Defense Supercycle'!$B$17+'Defense Supercycle'!$B$18+'Defense Supercycle'!$B$19)+$A66*'Fund Economics'!E28)/Assumptions!$B$5)^(1/7)-1 -> 0.19002355 | D66: =(((1-$A66)*('Defense Supercycle'!$B$17*'Fund Economics'!B44+'Defense Supercycle'!$B$18*'Fund Economics'!C44+'Defense Supercycle'!$B$19*'Fund Economics'!D44)/('Defense Supercycle'!$B$17+'Defense Supercycle'!$B$18+'Defense Supercycle'!$B$19)+$A66*'Fund Economics'!E44)/Assumptions!$B$5)^(1/10)-1 -> 0.20616886 | E66: =IF(ABS($A66-'Defense Supercycle'!$B$20)<0.0001,"current base case","")
A67: 0.25 | B67: =(((1-$A67)*('Defense Supercycle'!$B$17*'Fund Economics'!B12+'Defense Supercycle'!$B$18*'Fund Economics'!C12+'Defense Supercycle'!$B$19*'Fund Economics'!D12)/('Defense Supercycle'!$B$17+'Defense Supercycle'!$B$18+'Defense Supercycle'!$B$19)+$A67*'Fund Economics'!E12)/Assumptions!$B$5)^(1/5)-1 -> 0.18243589 | C67: =(((1-$A67)*('Defense Supercycle'!$B$17*'Fund Economics'!B28+'Defense Supercycle'!$B$18*'Fund Economics'!C28+'Defense Supercycle'!$B$19*'Fund Economics'!D28)/('Defense Supercycle'!$B$17+'Defense Supercycle'!$B$18+'Defense Supercycle'!$B$19)+$A67*'Fund Economics'!E28)/Assumptions!$B$5)^(1/7)-1 -> 0.19547727 | D67: =(((1-$A67)*('Defense Supercycle'!$B$17*'Fund Economics'!B44+'Defense Supercycle'!$B$18*'Fund Economics'!C44+'Defense Supercycle'!$B$19*'Fund Economics'!D44)/('Defense Supercycle'!$B$17+'Defense Supercycle'!$B$18+'Defense Supercycle'!$B$19)+$A67*'Fund Economics'!E44)/Assumptions!$B$5)^(1/10)-1 -> 0.21144483 | E67: =IF(ABS($A67-'Defense Supercycle'!$B$20)<0.0001,"current base case","")
A68: 0.3 | B68: =(((1-$A68)*('Defense Supercycle'!$B$17*'Fund Economics'!B12+'Defense Supercycle'!$B$18*'Fund Economics'!C12+'Defense Supercycle'!$B$19*'Fund Economics'!D12)/('Defense Supercycle'!$B$17+'Defense Supercycle'!$B$18+'Defense Supercycle'!$B$19)+$A68*'Fund Economics'!E12)/Assumptions!$B$5)^(1/5)-1 -> 0.18792109 | C68: =(((1-$A68)*('Defense Supercycle'!$B$17*'Fund Economics'!B28+'Defense Supercycle'!$B$18*'Fund Economics'!C28+'Defense Supercycle'!$B$19*'Fund Economics'!D28)/('Defense Supercycle'!$B$17+'Defense Supercycle'!$B$18+'Defense Supercycle'!$B$19)+$A68*'Fund Economics'!E28)/Assumptions!$B$5)^(1/7)-1 -> 0.20078568 | D68: =(((1-$A68)*('Defense Supercycle'!$B$17*'Fund Economics'!B44+'Defense Supercycle'!$B$18*'Fund Economics'!C44+'Defense Supercycle'!$B$19*'Fund Economics'!D44)/('Defense Supercycle'!$B$17+'Defense Supercycle'!$B$18+'Defense Supercycle'!$B$19)+$A68*'Fund Economics'!E44)/Assumptions!$B$5)^(1/10)-1 -> 0.21652177 | E68: =IF(ABS($A68-'Defense Supercycle'!$B$20)<0.0001,"current base case","")
A69: 0.4 | B69: =(((1-$A69)*('Defense Supercycle'!$B$17*'Fund Economics'!B12+'Defense Supercycle'!$B$18*'Fund Economics'!C12+'Defense Supercycle'!$B$19*'Fund Economics'!D12)/('Defense Supercycle'!$B$17+'Defense Supercycle'!$B$18+'Defense Supercycle'!$B$19)+$A69*'Fund Economics'!E12)/Assumptions!$B$5)^(1/5)-1 -> 0.19859704 | C69: =(((1-$A69)*('Defense Supercycle'!$B$17*'Fund Economics'!B28+'Defense Supercycle'!$B$18*'Fund Economics'!C28+'Defense Supercycle'!$B$19*'Fund Economics'!D28)/('Defense Supercycle'!$B$17+'Defense Supercycle'!$B$18+'Defense Supercycle'!$B$19)+$A69*'Fund Economics'!E28)/Assumptions!$B$5)^(1/7)-1 -> 0.21099842 | D69: =(((1-$A69)*('Defense Supercycle'!$B$17*'Fund Economics'!B44+'Defense Supercycle'!$B$18*'Fund Economics'!C44+'Defense Supercycle'!$B$19*'Fund Economics'!D44)/('Defense Supercycle'!$B$17+'Defense Supercycle'!$B$18+'Defense Supercycle'!$B$19)+$A69*'Fund Economics'!E44)/Assumptions!$B$5)^(1/10)-1 -> 0.22613771 | E69: =IF(ABS($A69-'Defense Supercycle'!$B$20)<0.0001,"current base case","")
A72: TOTAL HOLDCO ($840M) — DPI & PME BY HOLD (Expected, probability-weighted)
A73: Metric | B73: 5-yr | C73: 7-yr | D73: 10-yr
A74: Net MOIC | B74: ='Holdco Summary'!F38 -> 2.2851128 | C74: ='Holdco Summary'!F59 -> 3.4728957 | D74: ='Holdco Summary'!F80 -> 6.9765809
A75: Net DPI (=TVPI at exit) | B75: ='Holdco Summary'!F39 -> 2.2851128 | C75: ='Holdco Summary'!F60 -> 3.4728957 | D75: ='Holdco Summary'!F81 -> 6.9765809
A76: Net IRR | B76: ='Holdco Summary'!F40 -> 0.17972702 | C76: ='Holdco Summary'!F61 -> 0.19465272 | D76: ='Holdco Summary'!F82 -> 0.214407
A77: Net KS-PME vs SPX | B77: ='Holdco Summary'!F41 -> 1.4851665 | C77: ='Holdco Summary'!F62 -> 1.8997929 | D77: ='Holdco Summary'!F83 -> 2.9469832
A78: Net KS-PME vs NDX | B78: ='Holdco Summary'!F42 -> 1.2402677 | C78: ='Holdco Summary'!F63 -> 1.4761913 | D78: ='Holdco Summary'!F84 -> 2.0552194
A79: Net KS-PME vs Defense+Semis basket | B79: ='Holdco Summary'!F43 -> 1.1361049 | C79: ='Holdco Summary'!F64 -> 1.3055901 | D79: ='Holdco Summary'!F85 -> 1.7245041
A80: Direct Alpha vs basket (ann.) | B80: ='Holdco Summary'!F44 -> 0.025849585 | C80: ='Holdco Summary'!F65 -> 0.038828452 | D80: ='Holdco Summary'!F86 -> 0.05600609
A81: Direct Alpha vs SPX (ann.) | B81: =B77^(1/5)-1 -> 0.082318369 | C81: =C77^(1/7)-1 -> 0.09601167 | D81: =D77^(1/10)-1 -> 0.11413487
A82: Links to Holdco Summary roll-ups (rows 38-44 / 59-65 / 80-86). Holdco = IQT-mirror + Weapons + Consumer/Value, 2%/8%/20% on $840M.
A84: TOTAL HOLDCO ($840M) — TSMC-SHOCK PROBABILITY PRESSURE TEST
A85: Expected holdco Net IRR to LP as the TSMC-Shock probability varies (all three sleeves). Base/Bull/Bear keep their current relative weights; shock takes the remainder.
A86: Shock probability | B86: 5-yr Net IRR | C86: 7-yr Net IRR | D86: 10-yr Net IRR | E86: Note
A87: 0 | B87: =(((1-$A87)*('Defense Supercycle'!$B$17*'Holdco Summary'!B37+'Defense Supercycle'!$B$18*'Holdco Summary'!C37+'Defense Supercycle'!$B$19*'Holdco Summary'!D37)/('Defense Supercycle'!$B$17+'Defense Supercycle'!$B$18+'Defense Supercycle'!$B$19)+$A87*'Holdco Summary'!E37)/'Holdco Summary'!$B$9)^(1/5)-1 -> 0.17317422 | C87: =(((1-$A87)*('Defense Supercycle'!$B$17*'Holdco Summary'!B58+'Defense Supercycle'!$B$18*'Holdco Summary'!C58+'Defense Supercycle'!$B$19*'Holdco Summary'!D58)/('Defense Supercycle'!$B$17+'Defense Supercycle'!$B$18+'Defense Supercycle'!$B$19)+$A87*'Holdco Summary'!E58)/'Holdco Summary'!$B$9)^(1/7)-1 -> 0.186754 | D87: =(((1-$A87)*('Defense Supercycle'!$B$17*'Holdco Summary'!B79+'Defense Supercycle'!$B$18*'Holdco Summary'!C79+'Defense Supercycle'!$B$19*'Holdco Summary'!D79)/('Defense Supercycle'!$B$17+'Defense Supercycle'!$B$18+'Defense Supercycle'!$B$19)+$A87*'Holdco Summary'!E79)/'Holdco Summary'!$B$9)^(1/10)-1 -> 0.20520689 | E87: shock excluded
A88: 0.05 | B88: =(((1-$A88)*('Defense Supercycle'!$B$17*'Holdco Summary'!B37+'Defense Supercycle'!$B$18*'Holdco Summary'!C37+'Defense Supercycle'!$B$19*'Holdco Summary'!D37)/('Defense Supercycle'!$B$17+'Defense Supercycle'!$B$18+'Defense Supercycle'!$B$19)+$A88*'Holdco Summary'!E37)/'Holdco Summary'!$B$9)^(1/5)-1 -> 0.17537476 | C88: =(((1-$A88)*('Defense Supercycle'!$B$17*'Holdco Summary'!B58+'Defense Supercycle'!$B$18*'Holdco Summary'!C58+'Defense Supercycle'!$B$19*'Holdco Summary'!D58)/('Defense Supercycle'!$B$17+'Defense Supercycle'!$B$18+'Defense Supercycle'!$B$19)+$A88*'Holdco Summary'!E58)/'Holdco Summary'!$B$9)^(1/7)-1 -> 0.18942201 | D88: =(((1-$A88)*('Defense Supercycle'!$B$17*'Holdco Summary'!B79+'Defense Supercycle'!$B$18*'Holdco Summary'!C79+'Defense Supercycle'!$B$19*'Holdco Summary'!D79)/('Defense Supercycle'!$B$17+'Defense Supercycle'!$B$18+'Defense Supercycle'!$B$19)+$A88*'Holdco Summary'!E79)/'Holdco Summary'!$B$9)^(1/10)-1 -> 0.20834411 | E88: =IF(ABS($A88-'Defense Supercycle'!$B$20)<0.0001,"current base case","")
A89: 0.1 | B89: =(((1-$A89)*('Defense Supercycle'!$B$17*'Holdco Summary'!B37+'Defense Supercycle'!$B$18*'Holdco Summary'!C37+'Defense Supercycle'!$B$19*'Holdco Summary'!D37)/('Defense Supercycle'!$B$17+'Defense Supercycle'!$B$18+'Defense Supercycle'!$B$19)+$A89*'Holdco Summary'!E37)/'Holdco Summary'!$B$9)^(1/5)-1 -> 0.17755893 | C89: =(((1-$A89)*('Defense Supercycle'!$B$17*'Holdco Summary'!B58+'Defense Supercycle'!$B$18*'Holdco Summary'!C58+'Defense Supercycle'!$B$19*'Holdco Summary'!D58)/('Defense Supercycle'!$B$17+'Defense Supercycle'!$B$18+'Defense Supercycle'!$B$19)+$A89*'Holdco Summary'!E58)/'Holdco Summary'!$B$9)^(1/7)-1 -> 0.19205458 | D89: =(((1-$A89)*('Defense Supercycle'!$B$17*'Holdco Summary'!B79+'Defense Supercycle'!$B$18*'Holdco Summary'!C79+'Defense Supercycle'!$B$19*'Holdco Summary'!D79)/('Defense Supercycle'!$B$17+'Defense Supercycle'!$B$18+'Defense Supercycle'!$B$19)+$A89*'Holdco Summary'!E79)/'Holdco Summary'!$B$9)^(1/10)-1 -> 0.21140969 | E89: =IF(ABS($A89-'Defense Supercycle'!$B$20)<0.0001,"current base case","")
